Workbook
Name _ccVersion: 1.41
Name _HJAppendixVersion: 2
Name _kd01: #REF!
Name _kd02: #REF!
Name _kd03: #REF!
Name _kd04: #REF!
Name _kd05: #REF!
Name _kd06: #REF!
Name _kd07: #REF!
Name _kd08: #REF!
Name _kd09: #REF!
Name _kd10: #REF!
Name _kd11: #REF!
Name _kd12: #REF!
Name _kd13: #REF!
Name _kd14: #REF!
Name _kd15: #REF!
Name _kd16: #REF!
Name _kd17: #REF!
Name _kd18: #REF!
Name _kd19: #REF!
Name _kd20: #REF!
Name _kd21: #REF!
Name _kd22: #REF!
Name _kd23: #REF!
Name _kd24: #REF!
Name _kd25: #REF!
Name _Model_Path: "\\Ubsprod.msad.ubs.net\groupshares\GLOBAL\IB_RESEARCH_HKG\POWER\Models\Archives\Dongfang Electric Model 9.xlsx"
Name _pc01: #REF!
Name _pc02: #REF!
Name _pc03: #REF!
Name _pc04: #REF!
Name _pr05: #REF!
Name A: #REF!
Name AA: #REF!
Name aca: #REF!
Name acl: #REF!
Name ad00_: #REF!
Name ad01_: #REF!
Name ad02_: #REF!
Name ad03_: #REF!
Name ad04_: #REF!
Name ad05_: #REF!
Name ad06_: #REF!
Name ad07_: #REF!
Name ad08_: #REF!
Name ad09_: #REF!
Name Add__Cash: #REF!
Name Add__Listed_Investments: #REF!
Name Add__Other_Investments: #REF!
Name afa: #REF!
Name afc: #REF!
Name agd: #REF!
Name aie: #REF!
Name AK_ASAT: "F"
Name AK_BRKR: "XXX"
Name AK_CCY: "Raw"
Name AK_CDAT: "T-1WD"
Name AK_FDAT: "T-0Y-FWD"
Name AK_FSRC: "FX"

Sheet VA-Disclaimer

Sheet Fair Value - H
A2: P/E multiple valuation | D2: Forecast returns and rating | L2: 2025E | M2: 2026E | N2: 2027E | O2: 2028E | P2: 2029E
A3: Valuation date | B3: =+TODAY()
A4: 2027 forward target PE multiple | B4: 28 | D4: Current share price (HKD) | G4: 44.5 | K4: EPS | L4: =Model!U35 | M4: =Model!V35 | N4: =Model!W35 | O4: =Model!X35 | P4: =Model!Y35
A5: 2027E EPS (Rmb) | B5: =+Model!W35 | D5: Price target (HKD) | G5: =B10 | K5: BPS | L5: =Model!U37 | M5: =Model!V37 | N5: =Model!W37 | O5: =Model!X37 | P5: =Model!Y37
A6: Implied value per share (Rmb) | B6: =B4*B5 | D6: Upside/(Downside) | G6: =G5/G4-1 | K6: DPS | L6: =Model!U39 | M6: =Model!V39 | N6: =Model!W39 | O6: =Model!X39 | P6: =Model!Y39
A7: Roll forward at cost of equity | B7: =B6*(1+B16)^(((B3+365)-DATE(2026,12,31))/365) | D7: Forecast dividend yield | G7: =+Model!U39/G4
A8: Less: Dividends per share (Rmb) | B8: =-Model!V39*(((B3+365)-DATE(2026,12,31))/365) | D8: Market return assumption | G8: =5%+$B$13 | K8: P/E (current) | L8: =+$G$4/L4*$B$11 | M8: =+$G$4/M4*$B$11 | N8: =+$G$4/N4*$B$11 | O8: =+$G$4/O4*$B$11 | P8: =+$G$4/P4*$B$11
A9: Price target (Rmb) | B9: =SUM(B7:B8) | D9: Forecast excess return | G9: =G6+G7-G8 | K9: P/B (current) | L9: =+$G$4/L5*$B$11 | M9: =+$G$4/M5*$B$11 | N9: =+$G$4/N5*$B$11 | O9: =+$G$4/O5*$B$11 | P9: =+$G$4/P5*$B$11
A10: Price target (HKD) | B10: =ROUND(B9/B11,0) | D10: 12-month rating (UBS) | G10: =IF(G9>=6%, "BUY", IF(G9>=-6%,"NEUTRAL","SELL")) | K10: Dividend yield (current) | L10: =+L6/$G$4 | M10: =+M6/$G$4 | N10: =+N6/$G$4 | O10: =+O6/$G$4 | P10: =+P6/$G$4
A11: HKD/Rmb | B11: 0.91
A12: Valuation inputs | K12: P/E (Implied) | L12: =+$G$5/L4*$B$11 | M12: =+$G$5/M4*$B$11 | N12: =+$G$5/N4*$B$11 | O12: =+$G$5/O4*$B$11 | P12: =+$G$5/P4*$B$11
A13: Risk-free rate | B13: 0.035 | K13: P/B (Implied) | L13: =+$G$5/L5*$B$11 | M13: =+$G$5/M5*$B$11 | N13: =+$G$5/N5*$B$11 | O13: =+$G$5/O5*$B$11 | P13: =+$G$5/P5*$B$11
A14: Equity market risk premium | B14: 0.05
A15: Beta | B15: 0.49
A16: Cost of equity | B16: =B13+B14*B15
A18: UBSe 2026-29 EPS CAGR | B18: =+(Model!Y28/Model!V28)^(1/3)-1
A19: A/H discount | B19: 0

Sheet Fair Value - A
A2: P/E multiple valuation | D2: Forecast returns and rating | L2: 2025E | M2: 2026E | N2: 2027E | O2: 2028E | P2: 2029E
A3: Valuation date | B3: =+TODAY()
A4: 2027 forward target PE multiple | B4: 28 | D4: Current share price | G4: 42.21 | K4: EPS | L4: =Model!U35 | M4: =Model!V35 | N4: =Model!W35 | O4: =Model!X35 | P4: =Model!Y35
A5: 2027E EPS (Rmb) | B5: =+Model!W35 | D5: Price target (Rmb) | G5: =+B9 | K5: BPS | L5: =Model!U37 | M5: =Model!V37 | N5: =Model!W37 | O5: =Model!X37 | P5: =Model!Y37
A6: Implied value per share (Rmb) | B6: =B4*B5 | D6: Upside/(Downside) | G6: =G5/G4-1 | K6: DPS | L6: =Model!U39 | M6: =Model!V39 | N6: =Model!W39 | O6: =Model!X39 | P6: =Model!Y39
A7: Roll forward at cost of equity | B7: =B6*(1+B15)^(((B3+365)-DATE(2026,12,31))/365) | D7: Forecast dividend yield | G7: =+Model!U39/G4
A8: Less: Dividends per share (Rmb) | B8: =-Model!V39*(((B3+365)-DATE(2026,12,31))/365) | D8: Market return assumption | G8: =5%+$B$12 | K8: P/E (current) | L8: =+$G$4/L4 | M8: =+$G$4/M4 | N8: =+$G$4/N4 | O8: =+$G$4/O4 | P8: =+$G$4/P4
A9: Price target (Rmb) | B9: =ROUND(SUM(B7:B8),0) | D9: Forecast excess return | G9: =G6+G7-G8 | K9: P/B (current) | L9: =+$G$4/L5 | M9: =+$G$4/M5 | N9: =+$G$4/N5 | O9: =+$G$4/O5 | P9: =+$G$4/P5
D10: 12-month rating (UBS) | G10: =IF(G9>=6%, "BUY", IF(G9>=-6%,"NEUTRAL","SELL")) | K10: Dividend yield (current) | L10: =+L6/$G$4 | M10: =+M6/$G$4 | N10: =+N6/$G$4 | O10: =+O6/$G$4 | P10: =+P6/$G$4
A11: Valuation inputs
A12: Risk-free rate | B12: 0.018 | K12: P/E (Implied) | L12: =+$G$5/L4 | M12: =+$G$5/M4 | N12: =+$G$5/N4 | O12: =+$G$5/O4 | P12: =+$G$5/P4
A13: Equity market risk premium | B13: 0.05 | K13: P/B (Implied) | L13: =+$G$5/L5 | M13: =+$G$5/M5 | N13: =+$G$5/N5 | O13: =+$G$5/O5 | P13: =+$G$5/P5
A14: Beta | B14: 1.02
A15: Cost of equity | B15: =B12+B13*B14
A17: UBSe 2020-24 EPS CAGR | B17: =+(Model!T28/Model!P28)^(1/4)-1
A18: UBSe 2024-29 EPS CAGR | B18: =+(Model!Y28/Model!T28)^(1/5)-1
A19: UBSe 2025-27 EPS CAGR | B19: =+(Model!W28/Model!U28)^(1/2)-1
A20: UBSe 2025-28 EPS CAGR | B20: =+(Model!X28/Model!U28)^(1/3)-1
A21: UBSe 2026-29 EPS CAGR | B21: =+(Model!Y28/Model!V28)^(1/3)-1

Sheet Model
A1: Rmb m | BU1: H225
B2: 2006 | C2: 2007 | D2: 2008 | E2: 2009 | F2: 2010 | G2: 2011 | H2: 2012 | I2: 2013 | J2: 2014 | K2: 2015 | L2: 2016 | M2: 2017 | N2: 2018 | O2: 2019 | P2: 2020 | Q2: =P2+1 | R2: =Q2+1 | S2: =R2+1 | T2: =S2+1 | U2: =T2+1 | V2: =U2+1 | W2: =V2+1 | X2: =W2+1 | ... Z2: =Y2+1 | AA2: Change | AB2: Change % | AC2: 2025E | AD2: Difference | AE2: Diff % | AG2: H106 | AH2: H206 | AI2: H107 | AJ2: H207 | AK2: H108 | AL2: H208 | AM2: H109 | AN2: H209 | AO2: H110 | AP2: H210 | AQ2: H111 | AR2: H211 | AS2: H112 | AT2: H212 | AU2: H113 | AV2: H213 | AW2: H114 | AX2: H214 | AY2: H115 | AZ2: H215 | BA2: H116 | BB2: H216 | BC2: H117 | BD2: H217 | BE2: H118 | BF2: H218 | BG2: H119 | BH2: H219 | BI2: H120 | BJ2: H220 | BK2: H121 | BL2: H221 | BM2: H122 | BN2: H222 | BO2: H123 | BP2: H223 | BQ2: H124 | BR2: H224 | BS2: H125 | BT2: H225E | BU2: Change | BV2: Change % | BW2: % of last year | BX2: % of FY | BZ2: Q106 | CA2: Q206 | CB2: Q306 | CC2: Q406 | CD2: Q107 | CE2: Q207 | CF2: Q307 | CG2: Q407 | CH2: Q108 | CI2: Q208 | CJ2: Q308 | CK2: Q408 | CL2: Q109 | CM2: Q209 | CN2: Q309 | CO2: Q409 | CP2: Q110 | CQ2: Q210 | CR2: Q310 | CS2: Q410 | CT2: Q111 | CU2: Q211 | CV2: Q311 | CW2: Q411 | CX2: Q112 | CY2: Q212 | CZ2: Q312 | DA2: Q412 | DB2: Q113 | DC2: Q213 | DD2: Q313 | DE2: Q413 | DF2: Q114 | DG2: Q214 | DH2: Q314 | DI2: Q414 | DJ2: Q115 | DK2: Q215 | DL2: Q315 | DM2: Q415 | DN2: Q116 | DO2: Q216 | DP2: Q316 | DQ2: Q416 | DR2: Q117 | DS2: Q217 | DT2: Q317 | DU2: Q417 | DV2: Q118 | DW2: Q218 | DX2: Q318 | DY2: Q418 | DZ2: Q119 | EA2: Q219 | EB2: Q319 | EC2: Q419 | ED2: Q120 | EE2: Q220 | EF2: Q320 | EG2: Q420 | EH2: Q121 | EI2: Q221 | EJ2: Q321 | EK2: Q421 | EL2: Q122 | EM2: Q222 | EN2: Q322 | EO2: Q422 | EP2: Q123 | EQ2: Q223 | ER2: Q323 | ES2: Q423 | ET2: Q124 | EU2: Q224 | EV2: Q324 | EW2: Q424 | EX2: Q125 | EY2: Q225 | EZ2: Q325 | FA2: Q425 | FB2: Change | FC2: Change % | FD2: % of FY24 | FE2: % of FY25
A3: P&L
A4: Revenue | B4: ='Raw financials'!B4 | C4: ='Raw financials'!C4 | D4: ='Raw financials'!D4 | E4: ='Raw financials'!E4 | F4: ='Raw financials'!F4 | G4: ='Raw financials'!G4 | H4: ='Raw financials'!H4 | I4: ='Raw financials'!I4 | ... T4: ='Raw financials'!T4 | U4: =Driver!J14 | V4: =Driver!K14 | W4: =Driver!L14 | X4: =Driver!M14 | Y4: =Driver!N14 | Z4: =Driver!O14 | AA4: =+U4-T4 | AB4: =+AA4/T4 | AC4: 81355.398 | AD4: =+U4-AC4 | AE4: =+AD4/AC4 | AG4: ='Raw financials'!AA4 | AH4: =B4-AG4 | AI4: ='Raw financials'!AB4 | AJ4: =C4-AI4 | AK4: ='Raw financials'!AC4 | AL4: =D4-AK4 | AM4: ='Raw financials'!AD4 | AN4: =E4-AM4 | AO4: ='Raw financials'!AE4 | AP4: =F4-AO4 | AQ4: ='Raw financials'!AF4 | AR4: =G4-AQ4 | AS4: ='Raw financials'!AG4 | AT4: =H4-AS4 | AU4: ='Raw financials'!AH4 | AV4: =I4-AU4 | AW4: ='Raw financials'!AI4 | AX4: =J4-AW4 | AY4: ='Raw financials'!AJ4 | AZ4: =K4-AY4 | BA4: ='Raw financials'!AK4 | BB4: =L4-BA4 | BC4: ='Raw financials'!AL4 | BD4: =M4-BC4 | BE4: ='Raw financials'!AM4 | BF4: =N4-BE4 | BG4: ='Raw financials'!AN4 | BH4: =O4-BG4 | BI4: ='Raw financials'!AO4 | BJ4: =P4-BI4 | BK4: ='Raw financials'!AP4 | BL4: =Q4-BK4 | BM4: ='Raw financials'!AQ4 | BN4: =R4-BM4 | BO4: ='Raw financials'!AR4 | BP4: =S4-BO4 | BQ4: ='Raw financials'!AS4 | BR4: =T4-BQ4 | BT4: =U4-BS4 | BU4: =BT4-BR4 | BV4: =BU4/BR4 | BW4: =BT4/T4 | BX4: =BT4/U4 | BZ4: ='Raw financials'!BN4 | CA4: ='Raw financials'!BO4 | CB4: ='Raw financials'!BP4 | CC4: ='Raw financials'!BQ4 | CD4: ='Raw financials'!BR4 | CE4: ='Raw financials'!BS4 | CF4: ='Raw financials'!BT4 | CG4: ='Raw financials'!BU4 | ... EY4: ='Raw financials'!EM4 | FB4: =+FA4-EW4 | FC4: =+FB4/EW4 | FD4: =+FA4/T4 | FE4: =+FA4/U4
A5: YoY | D5: =D4/C4-1 | E5: =E4/D4-1 | F5: =F4/E4-1 | G5: =G4/F4-1 | H5: =H4/G4-1 | I5: =I4/H4-1 | J5: =J4/I4-1 | K5: =K4/J4-1 | ... Z5: =Z4/Y4-1 | BM5: =BM4/BK4-1 | BN5: =BN4/BL4-1 | BO5: =BO4/BM4-1 | BP5: =BP4/BN4-1 | BQ5: =BQ4/BO4-1 | BR5: =BR4/BP4-1 | BT5: =BT4/BR4-1 | EX5: =EX4/ET4-1 | EY5: =EY4/EU4-1
A6: COGS | B6: =-'Raw financials'!B8 | C6: =-'Raw financials'!C8 | D6: =-'Raw financials'!D8 | E6: =-'Raw financials'!E8 | F6: =-'Raw financials'!F8 | G6: =-'Raw financials'!G8 | H6: =-'Raw financials'!H8 | I6: =-'Raw financials'!I8 | ... T6: =-'Raw financials'!T8 | U6: =Driver!J47 | V6: =Driver!K47 | W6: =Driver!L47 | X6: =Driver!M47 | Y6: =Driver!N47 | Z6: =Driver!O47 | AA6: =+U6-T6 | AB6: =+AA6/T6 | AC6: -68165.604 | AD6: =+U6-AC6 | AE6: =+AD6/AC6 | AG6: =-'Raw financials'!AA8 | AH6: =B6-AG6 | AI6: =-'Raw financials'!AB8 | AJ6: =C6-AI6 | AK6: =-'Raw financials'!AC8 | AL6: =D6-AK6 | AM6: =-'Raw financials'!AD8 | AN6: =E6-AM6 | AO6: =-'Raw financials'!AE8 | AP6: =F6-AO6 | AQ6: =-'Raw financials'!AF8 | AR6: =G6-AQ6 | AS6: =-'Raw financials'!AG8 | AT6: =H6-AS6 | AU6: =-'Raw financials'!AH8 | AV6: =I6-AU6 | AW6: =-'Raw financials'!AI8 | AX6: =J6-AW6 | AY6: =-'Raw financials'!AJ8 | AZ6: =K6-AY6 | BA6: =-'Raw financials'!AK8 | BB6: =L6-BA6 | BC6: =-'Raw financials'!AL8 | BD6: =M6-BC6 | BE6: =-'Raw financials'!AM8 | BF6: =N6-BE6 | BG6: =-'Raw financials'!AN8 | BH6: =O6-BG6 | BI6: =-'Raw financials'!AO8 | BJ6: =P6-BI6 | BK6: =-'Raw financials'!AP8 | BL6: =Q6-BK6 | BM6: =-'Raw financials'!AQ8 | BN6: =R6-BM6 | BO6: =-'Raw financials'!AR8 | BP6: =S6-BO6 | BQ6: =-'Raw financials'!AS8 | BR6: =T6-BQ6 | BT6: =U6-BS6 | BU6: =BT6-BR6 | BV6: =BU6/BR6 | BW6: =BT6/T6 | BX6: =BT6/U6 | BZ6: =-'Raw financials'!BN8 | CA6: =-'Raw financials'!BO8 | CB6: =-'Raw financials'!BP8 | CC6: =-'Raw financials'!BQ8 | CD6: =-'Raw financials'!BR8 | CE6: =-'Raw financials'!BS8 | CF6: =-'Raw financials'!BT8 | CG6: =-'Raw financials'!BU8 | ... EY6: =-'Raw financials'!EM8 | FB6: =+FA6-EW6 | FC6: =+FB6/EW6 | FD6: =+FA6/T6 | FE6: =+FA6/U6
A7: Gross Profit | B7: =B4+B6 | C7: =C4+C6 | D7: =D4+D6 | E7: =E4+E6 | F7: =F4+F6 | G7: =G4+G6 | H7: =H4+H6 | I7: =I4+I6 | ... Z7: =Z4+Z6 | AA7: =+U7-T7 | AB7: =+AA7/T7 | AC7: 13189.794 | AD7: =+U7-AC7 | AE7: =+AD7/AC7 | AG7: =AG4+AG6 | AH7: =AH4+AH6 | AI7: =AI4+AI6 | AJ7: =AJ4+AJ6 | AK7: =AK4+AK6 | AL7: =AL4+AL6 | AM7: =AM4+AM6 | AN7: =AN4+AN6 | ... BR7: =BR4+BR6 | BT7: =BT4+BT6 | BU7: =BT7-BR7 | BV7: =BU7/BR7 | BW7: =BT7/T7 | BX7: =BT7/U7 | BZ7: =BZ4+BZ6 | CA7: =CA4+CA6 | CB7: =CB4+CB6 | CC7: =CC4+CC6 | CD7: =CD4+CD6 | CE7: =CE4+CE6 | CF7: =CF4+CF6 | CG7: =CG4+CG6 | ... EY7: =EY4+EY6 | FB7: =+FA7-EW7 | FC7: =+FB7/EW7 | FD7: =+FA7/T7 | FE7: =+FA7/U7
A8: GPM | B8: =B7/B4 | C8: =C7/C4 | D8: =D7/D4 | E8: =E7/E4 | F8: =F7/F4 | G8: =G7/G4 | H8: =H7/H4 | I8: =I7/I4 | ... Z8: =Z7/Z4 | AG8: =AG7/AG4 | AH8: =AH7/AH4 | AI8: =AI7/AI4 | AJ8: =AJ7/AJ4 | AK8: =AK7/AK4 | AL8: =AL7/AL4 | AM8: =AM7/AM4 | AN8: =AN7/AN4 | ... BR8: =BR7/BR4 | BT8: =BT7/BT4 | BU8: =BT8-BR8 | BV8: =BU8/BR8 | BW8: =BT8/T8 | BX8: =BT8/U8 | BZ8: =BZ7/BZ4 | CA8: =CA7/CA4 | CB8: =CB7/CB4 | CC8: =CC7/CC4 | CD8: =CD7/CD4 | CE8: =CE7/CE4 | CF8: =CF7/CF4 | CG8: =CG7/CG4 | ... EY8: =EY7/EY4
A9: Business tax | B9: =-'Raw financials'!B9 | C9: =-'Raw financials'!C9 | D9: =-'Raw financials'!D9 | E9: =-'Raw financials'!E9 | F9: =-'Raw financials'!F9 | G9: =-'Raw financials'!G9 | H9: =-'Raw financials'!H9 | I9: =-'Raw financials'!I9 | ... T9: =-'Raw financials'!T9 | U9: =T9/T4*U4 | V9: =U9/U4*V4 | W9: =V9/V4*W4 | X9: =W9/W4*X4 | Y9: =X9/X4*Y4 | Z9: =Y9/Y4*Z4 | AA9: =+U9-T9 | AB9: =+AA9/T9 | AC9: -441.85949 | AD9: =+U9-AC9 | AE9: =+AD9/AC9 | AG9: =-'Raw financials'!AA9 | AH9: =B9-AG9 | AI9: =-'Raw financials'!AB9 | AJ9: =C9-AI9 | AK9: =-'Raw financials'!AC9 | AL9: =D9-AK9 | AM9: =-'Raw financials'!AD9 | AN9: =E9-AM9 | AO9: =-'Raw financials'!AE9 | AP9: =F9-AO9 | AQ9: =-'Raw financials'!AF9 | AR9: =G9-AQ9 | AS9: =-'Raw financials'!AG9 | AT9: =H9-AS9 | AU9: =-'Raw financials'!AH9 | AV9: =I9-AU9 | AW9: =-'Raw financials'!AI9 | AX9: =J9-AW9 | AY9: =-'Raw financials'!AJ9 | AZ9: =K9-AY9 | BA9: =-'Raw financials'!AK9 | BB9: =L9-BA9 | BC9: =-'Raw financials'!AL9 | BD9: =M9-BC9 | BE9: =-'Raw financials'!AM9 | BF9: =N9-BE9 | BG9: =-'Raw financials'!AN9 | BH9: =O9-BG9 | BI9: =-'Raw financials'!AO9 | BJ9: =P9-BI9 | BK9: =-'Raw financials'!AP9 | BL9: =Q9-BK9 | BM9: =-'Raw financials'!AQ9 | BN9: =R9-BM9 | BO9: =-'Raw financials'!AR9 | BP9: =S9-BO9 | BQ9: =-'Raw financials'!AS9 | BR9: =T9-BQ9 | BT9: =U9-BS9 | BU9: =BT9-BR9 | BV9: =BU9/BR9 | BW9: =BT9/T9 | BX9: =BT9/U9 | BZ9: =-'Raw financials'!BN9 | CA9: =-'Raw financials'!BO9 | CB9: =-'Raw financials'!BP9 | CC9: =-'Raw financials'!BQ9 | CD9: =-'Raw financials'!BR9 | CE9: =-'Raw financials'!BS9 | CF9: =-'Raw financials'!BT9 | CG9: =-'Raw financials'!BU9 | ... EY9: =-'Raw financials'!EM9 | FB9: =+FA9-EW9 | FC9: =+FB9/EW9 | FD9: =+FA9/T9 | FE9: =+FA9/U9
A10: Selling expense | B10: =-'Raw financials'!B10 | C10: =-'Raw financials'!C10 | D10: =-'Raw financials'!D10 | E10: =-'Raw financials'!E10 | F10: =-'Raw financials'!F10 | G10: =-'Raw financials'!G10 | H10: =-'Raw financials'!H10 | I10: =-'Raw financials'!I10 | ... T10: =-'Raw financials'!T10 | U10: =T10/T4*U4 | V10: =U10/U4*V4 | W10: =V10/V4*W4 | X10: =W10/W4*X4 | Y10: =X10/X4*Y4 | Z10: =Y10/Y4*Z4 | AA10: =+U10-T10 | AB10: =+AA10/T10 | AC10: -959.94391 | AD10: =+U10-AC10 | AE10: =+AD10/AC10 | AG10: =-'Raw financials'!AA10 | AH10: =B10-AG10 | AI10: =-'Raw financials'!AB10 | AJ10: =C10-AI10 | AK10: =-'Raw financials'!AC10 | AL10: =D10-AK10 | AM10: =-'Raw financials'!AD10 | AN10: =E10-AM10 | AO10: =-'Raw financials'!AE10 | AP10: =F10-AO10 | AQ10: =-'Raw financials'!AF10 | AR10: =G10-AQ10 | AS10: =-'Raw financials'!AG10 | AT10: =H10-AS10 | AU10: =-'Raw financials'!AH10 | AV10: =I10-AU10 | AW10: =-'Raw financials'!AI10 | AX10: =J10-AW10 | AY10: =-'Raw financials'!AJ10 | AZ10: =K10-AY10 | BA10: =-'Raw financials'!AK10 | BB10: =L10-BA10 | BC10: =-'Raw financials'!AL10 | BD10: =M10-BC10 | BE10: =-'Raw financials'!AM10 | BF10: =N10-BE10 | BG10: =-'Raw financials'!AN10 | BH10: =O10-BG10 | BI10: =-'Raw financials'!AO10 | BJ10: =P10-BI10 | BK10: =-'Raw financials'!AP10 | BL10: =Q10-BK10 | BM10: =-'Raw financials'!AQ10 | BN10: =R10-BM10 | BO10: =-'Raw financials'!AR10 | BP10: =S10-BO10 | BQ10: =-'Raw financials'!AS10 | BR10: =T10-BQ10 | BT10: =U10-BS10 | BU10: =BT10-BR10 | BV10: =BU10/BR10 | BW10: =BT10/T10 | BX10: =BT10/U10 | BZ10: =-'Raw financials'!BN10 | CA10: =-'Raw financials'!BO10 | CB10: =-'Raw financials'!BP10 | CC10: =-'Raw financials'!BQ10 | CD10: =-'Raw financials'!BR10 | CE10: =-'Raw financials'!BS10 | CF10: =-'Raw financials'!BT10 | CG10: =-'Raw financials'!BU10 | ... EY10: =-'Raw financials'!EM10 | FB10: =+FA10-EW10 | FC10: =+FB10/EW10 | FD10: =+FA10/T10 | FE10: =+FA10/U10
A11: Administrative & R&D expenses | B11: =B12+B13 | C11: =C12+C13 | D11: =D12+D13 | E11: =E12+E13 | F11: =F12+F13 | G11: =G12+G13 | H11: =H12+H13 | I11: =I12+I13 | ... T11: =T12+T13 | U11: =-U4*U14-U10 | V11: =-V4*V14-V10 | W11: =-W4*W14-W10 | X11: =-X4*X14-X10 | Y11: =-Y4*Y14-Y10 | Z11: =-Z4*Z14-Z10 | AA11: =+U11-T11 | AB11: =+AA11/T11 | AC11: -7624.8981 | AD11: =+U11-AC11 | AE11: =+AD11/AC11 | AG11: =AG12+AG13 | AH11: =B11-AG11 | AI11: =AI12+AI13 | AJ11: =C11-AI11 | AK11: =AK12+AK13 | AL11: =D11-AK11 | AM11: =AM12+AM13 | AN11: =E11-AM11 | AO11: =AO12+AO13 | AP11: =F11-AO11 | AQ11: =AQ12+AQ13 | AR11: =G11-AQ11 | AS11: =AS12+AS13 | AT11: =H11-AS11 | AU11: =AU12+AU13 | AV11: =I11-AU11 | AW11: =AW12+AW13 | AX11: =J11-AW11 | AY11: =AY12+AY13 | AZ11: =K11-AY11 | BA11: =BA12+BA13 | BB11: =L11-BA11 | BC11: =BC12+BC13 | BD11: =M11-BC11 | BE11: =BE12+BE13 | BF11: =N11-BE11 | BG11: =BG12+BG13 | BH11: =O11-BG11 | BI11: =BI12+BI13 | BJ11: =P11-BI11 | BK11: =BK12+BK13 | BL11: =Q11-BK11 | BM11: =BM12+BM13 | BN11: =R11-BM11 | BO11: =BO12+BO13 | BP11: =S11-BO11 | BQ11: =BQ12+BQ13 | BR11: =T11-BQ11 | BT11: =U11-BS11 | BU11: =BT11-BR11 | BV11: =BU11/BR11 | BW11: =BT11/T11 | BX11: =BT11/U11 | BZ11: =BZ12+BZ13 | CA11: =CA12+CA13 | CB11: =CB12+CB13 | CC11: =CC12+CC13 | CD11: =CD12+CD13 | CE11: =CE12+CE13 | CF11: =CF12+CF13 | CG11: =CG12+CG13 | ... EY11: =EY12+EY13 | FB11: =+FA11-EW11 | FC11: =+FB11/EW11 | FD11: =+FA11/T11 | FE11: =+FA11/U11
A12: Admin expense | B12: =-'Raw financials'!B11 | C12: =-'Raw financials'!C11 | D12: =-'Raw financials'!D11 | E12: =-'Raw financials'!E11 | F12: =-'Raw financials'!F11 | G12: =-'Raw financials'!G11 | H12: =-'Raw financials'!H11 | I12: =-'Raw financials'!I11 | ... T12: =-'Raw financials'!T11 | AA12: =+U12-T12 | AB12: =+AA12/T12 | AD12: =+U12-AC12 | AE12: =+AD12/AC12 | AG12: =-'Raw financials'!AA11 | AI12: =-'Raw financials'!AB11 | AK12: =-'Raw financials'!AC11 | AM12: =-'Raw financials'!AD11 | AO12: =-'Raw financials'!AE11 | AQ12: =-'Raw financials'!AF11 | AS12: =-'Raw financials'!AG11 | AU12: =-'Raw financials'!AH11 | AW12: =-'Raw financials'!AI11 | AY12: =-'Raw financials'!AJ11 | BA12: =-'Raw financials'!AK11 | BC12: =-'Raw financials'!AL11 | BE12: =-'Raw financials'!AM11 | BG12: =-'Raw financials'!AN11 | BI12: =-'Raw financials'!AO11 | BK12: =-'Raw financials'!AP11 | BM12: =-'Raw financials'!AQ11 | BO12: =-'Raw financials'!AR11 | BQ12: =-'Raw financials'!AS11 | BU12: =BT12-BR12 | BV12: =BU12/BR12 | BW12: =BT12/T12 | BX12: =BT12/U12 | BZ12: =-'Raw financials'!BN11 | CA12: =-'Raw financials'!BO11 | CB12: =-'Raw financials'!BP11 | CC12: =-'Raw financials'!BQ11 | CD12: =-'Raw financials'!BR11 | CE12: =-'Raw financials'!BS11 | CF12: =-'Raw financials'!BT11 | CG12: =-'Raw financials'!BU11 | ... EY12: =-'Raw financials'!EM11 | FB12: =+FA12-EW12 | FC12: =+FB12/EW12 | FD12: =+FA12/T12 | FE12: =+FA12/U12
A13: R&D expense | B13: =-'Raw financials'!B12 | C13: =-'Raw financials'!C12 | D13: =-'Raw financials'!D12 | E13: =-'Raw financials'!E12 | F13: =-'Raw financials'!F12 | G13: =-'Raw financials'!G12 | H13: =-'Raw financials'!H12 | I13: =-'Raw financials'!I12 | ... T13: =-'Raw financials'!T12 | AA13: =+U13-T13 | AB13: =+AA13/T13 | AD13: =+U13-AC13 | AE13: =+AD13/AC13 | AG13: =-'Raw financials'!AA12 | AI13: =-'Raw financials'!AB12 | AK13: =-'Raw financials'!AC12 | AM13: =-'Raw financials'!AD12 | AO13: =-'Raw financials'!AE12 | AQ13: =-'Raw financials'!AF12 | AS13: =-'Raw financials'!AG12 | AU13: =-'Raw financials'!AH12 | AW13: =-'Raw financials'!AI12 | AY13: =-'Raw financials'!AJ12 | BA13: =-'Raw financials'!AK12 | BC13: =-'Raw financials'!AL12 | BE13: =-'Raw financials'!AM12 | BG13: =-'Raw financials'!AN12 | BI13: =-'Raw financials'!AO12 | BK13: =-'Raw financials'!AP12 | BM13: =-'Raw financials'!AQ12 | BO13: =-'Raw financials'!AR12 | BQ13: =-'Raw financials'!AS12 | BU13: =BT13-BR13 | BV13: =BU13/BR13 | BW13: =BT13/T13 | BX13: =BT13/U13 | BZ13: =-'Raw financials'!BN12 | CA13: =-'Raw financials'!BO12 | CB13: =-'Raw financials'!BP12 | CC13: =-'Raw financials'!BQ12 | CD13: =-'Raw financials'!BR12 | CE13: =-'Raw financials'!BS12 | CF13: =-'Raw financials'!BT12 | CG13: =-'Raw financials'!BU12 | ... EY13: =-'Raw financials'!EM12 | FB13: =+FA13-EW13 | FC13: =+FB13/EW13 | FD13: =+FA13/T13 | FE13: =+FA13/U13
A14: SGA as % of revenue | B14: =-(B11+B10)/B4 | C14: =-(C11+C10)/C4 | D14: =-(D11+D10)/D4 | E14: =-(E11+E10)/E4 | F14: =-(F11+F10)/F4 | G14: =-(G11+G10)/G4 | H14: =-(H11+H10)/H4 | I14: =-(I11+I10)/I4 | ... T14: =-(T11+T10)/T4 | U14: =T14 | V14: =U14 | W14: =V14 | X14: =W14 | Y14: =X14 | Z14: =Y14 | AG14: =-(AG11+AG10)/AG4 | AH14: =-(AH11+AH10)/AH4 | AI14: =-(AI11+AI10)/AI4 | AJ14: =-(AJ11+AJ10)/AJ4 | AK14: =-(AK11+AK10)/AK4 | AL14: =-(AL11+AL10)/AL4 | AM14: =-(AM11+AM10)/AM4 | AN14: =-(AN11+AN10)/AN4 | ... BR14: =-(BR11+BR10)/BR4 | BT14: =-(BT11+BT10)/BT4 | BU14: =BT14-BR14 | BV14: =BU14/BR14 | BW14: =BT14/T14 | BX14: =BT14/U14 | BZ14: =-(BZ11+BZ10)/BZ4 | CA14: =-(CA11+CA10)/CA4 | CB14: =-(CB11+CB10)/CB4 | CC14: =-(CC11+CC10)/CC4 | CD14: =-(CD11+CD10)/CD4 | CE14: =-(CE11+CE10)/CE4 | CF14: =-(CF11+CF10)/CF4 | CG14: =-(CG11+CG10)/CG4 | ... EY14: =-(EY11+EY10)/EY4
A15: EBIT | B15: =B7+B10+B11+B9 | C15: =C7+C10+C11+C9 | D15: =D7+D10+D11+D9 | E15: =E7+E10+E11+E9 | F15: =F7+F10+F11+F9 | G15: =G7+G10+G11+G9 | H15: =H7+H10+H11+H9 | I15: =I7+I10+I11+I9 | ... Z15: =Z7+Z10+Z11+Z9 | AA15: =+U15-T15 | AB15: =+AA15/T15 | AC15: 4163.0923 | AD15: =+U15-AC15 | AE15: =+AD15/AC15 | AG15: =AG7+AG10+AG11+AG9 | AH15: =AH7+AH10+AH11+AH9 | AI15: =AI7+AI10+AI11+AI9 | AJ15: =AJ7+AJ10+AJ11+AJ9 | AK15: =AK7+AK10+AK11+AK9 | AL15: =AL7+AL10+AL11+AL9 | AM15: =AM7+AM10+AM11+AM9 | AN15: =AN7+AN10+AN11+AN9 | ... BR15: =BR7+BR10+BR11+BR9 | BT15: =BT7+BT10+BT11+BT9 | BU15: =BT15-BR15 | BV15: =BU15/BR15 | BW15: =BT15/T15 | BX15: =BT15/U15 | BZ15: =BZ7+BZ10+BZ11+BZ9 | CA15: =CA7+CA10+CA11+CA9 | CB15: =CB7+CB10+CB11+CB9 | CC15: =CC7+CC10+CC11+CC9 | CD15: =CD7+CD10+CD11+CD9 | CE15: =CE7+CE10+CE11+CE9 | CF15: =CF7+CF10+CF11+CF9 | CG15: =CG7+CG10+CG11+CG9 | ... EY15: =EY7+EY10+EY11+EY9 | FB15: =+FA15-EW15 | FC15: =+FB15/EW15 | FD15: =+FA15/T15 | FE15: =+FA15/U15
A16: EBIT margin | B16: =B15/B4 | C16: =C15/C4 | D16: =D15/D4 | E16: =E15/E4 | F16: =F15/F4 | G16: =G15/G4 | H16: =H15/H4 | I16: =I15/I4 | ... Z16: =Z15/Z4 | AG16: =AG15/AG4 | AH16: =AH15/AH4 | AI16: =AI15/AI4 | AJ16: =AJ15/AJ4 | AK16: =AK15/AK4 | AL16: =AL15/AL4 | AM16: =AM15/AM4 | AN16: =AN15/AN4 | ... BR16: =BR15/BR4 | BT16: =BT15/BT4 | BU16: =BT16-BR16 | BV16: =BU16/BR16 | BW16: =BT16/T16 | BX16: =BT16/U16 | BZ16: =BZ15/BZ4 | CA16: =CA15/CA4 | CB16: =CB15/CB4 | CC16: =CC15/CC4 | CD16: =CD15/CD4 | CE16: =CE15/CE4 | CF16: =CF15/CF4 | CG16: =CG15/CG4 | ... EY16: =EY15/EY4
A17: Finance gain (cost) | B17: =-'Raw financials'!B13 | C17: =-'Raw financials'!C13 | D17: =-'Raw financials'!D13 | E17: =-'Raw financials'!E13 | F17: =-'Raw financials'!F13 | G17: =-'Raw financials'!G13 | H17: =-'Raw financials'!H13 | I17: =-'Raw financials'!I13 | ... T17: =-'Raw financials'!T13 | U17: =Driver!J138 | V17: =Driver!K138 | W17: =Driver!L138 | X17: =Driver!M138 | Y17: =Driver!N138 | Z17: =Driver!O138 | AA17: =+U17-T17 | AB17: =+AA17/T17 | AC17: -28.840856 | AD17: =+U17-AC17 | AE17: =+AD17/AC17 | AG17: =-'Raw financials'!AA13 | AH17: =B17-AG17 | AI17: =-'Raw financials'!AB13 | AJ17: =C17-AI17 | AK17: =-'Raw financials'!AC13 | AL17: =D17-AK17 | AM17: =-'Raw financials'!AD13 | AN17: =E17-AM17 | AO17: =-'Raw financials'!AE13 | AP17: =F17-AO17 | AQ17: =-'Raw financials'!AF13 | AR17: =G17-AQ17 | AS17: =-'Raw financials'!AG13 | AT17: =H17-AS17 | AU17: =-'Raw financials'!AH13 | AV17: =I17-AU17 | AW17: =-'Raw financials'!AI13 | AX17: =J17-AW17 | AY17: =-'Raw financials'!AJ13 | AZ17: =K17-AY17 | BA17: =-'Raw financials'!AK13 | BB17: =L17-BA17 | BC17: =-'Raw financials'!AL13 | BD17: =M17-BC17 | BE17: =-'Raw financials'!AM13 | BF17: =N17-BE17 | BG17: =-'Raw financials'!AN13 | BH17: =O17-BG17 | BI17: =-'Raw financials'!AO13 | BJ17: =P17-BI17 | BK17: =-'Raw financials'!AP13 | BL17: =Q17-BK17 | BM17: =-'Raw financials'!AQ13 | BN17: =R17-BM17 | BO17: =-'Raw financials'!AR13 | BP17: =S17-BO17 | BQ17: =-'Raw financials'!AS13 | BR17: =T17-BQ17 | BT17: =U17-BS17 | BU17: =BT17-BR17 | BV17: =BU17/BR17 | BW17: =BT17/T17 | BX17: =BT17/U17 | BZ17: =-'Raw financials'!BN13 | CA17: =-'Raw financials'!BO13 | CB17: =-'Raw financials'!BP13 | CC17: =-'Raw financials'!BQ13 | CD17: =-'Raw financials'!BR13 | CE17: =-'Raw financials'!BS13 | CF17: =-'Raw financials'!BT13 | CG17: =-'Raw financials'!BU13 | ... EY17: =-'Raw financials'!EM13 | FB17: =+FA17-EW17 | FC17: =+FB17/EW17 | FD17: =+FA17/T17 | FE17: =+FA17/U17
A18: Investment income | B18: ='Raw financials'!B18 | C18: ='Raw financials'!C18 | D18: ='Raw financials'!D18 | E18: ='Raw financials'!E18 | F18: ='Raw financials'!F18 | G18: ='Raw financials'!G18 | H18: ='Raw financials'!H18 | I18: ='Raw financials'!I18 | ... T18: ='Raw financials'!T18 | U18: =+T18 | V18: =+U18 | W18: =+V18 | X18: =+W18 | Y18: =+X18 | Z18: =+Y18 | AA18: =+U18-T18 | AB18: =+AA18/T18 | AC18: 1577.06 | AD18: =+U18-AC18 | AE18: =+AD18/AC18 | AG18: ='Raw financials'!AA18 | AH18: =B18-AG18 | AI18: ='Raw financials'!AB18 | AJ18: =C18-AI18 | AK18: ='Raw financials'!AC18 | AL18: =D18-AK18 | AM18: ='Raw financials'!AD18 | AN18: =E18-AM18 | AO18: ='Raw financials'!AE18 | AP18: =F18-AO18 | AQ18: ='Raw financials'!AF18 | AR18: =G18-AQ18 | AS18: ='Raw financials'!AG18 | AT18: =H18-AS18 | AU18: ='Raw financials'!AH18 | AV18: =I18-AU18 | AW18: ='Raw financials'!AI18 | AX18: =J18-AW18 | AY18: ='Raw financials'!AJ18 | AZ18: =K18-AY18 | BA18: ='Raw financials'!AK18 | BB18: =L18-BA18 | BC18: ='Raw financials'!AL18 | BD18: =M18-BC18 | BE18: ='Raw financials'!AM18 | BF18: =N18-BE18 | BG18: ='Raw financials'!AN18 | BH18: =O18-BG18 | BI18: ='Raw financials'!AO18 | BJ18: =P18-BI18 | BK18: ='Raw financials'!AP18 | BL18: =Q18-BK18 | BM18: ='Raw financials'!AQ18 | BN18: =R18-BM18 | BO18: ='Raw financials'!AR18 | BP18: =S18-BO18 | BQ18: ='Raw financials'!AS18 | BR18: =T18-BQ18 | BT18: =U18-BS18 | BU18: =BT18-BR18 | BV18: =BU18/BR18 | BW18: =BT18/T18 | BX18: =BT18/U18 | BZ18: ='Raw financials'!BN18 | CA18: ='Raw financials'!BO18 | CB18: ='Raw financials'!BP18 | CC18: ='Raw financials'!BQ18 | CD18: ='Raw financials'!BR18 | CE18: ='Raw financials'!BS18 | CF18: ='Raw financials'!BT18 | CG18: ='Raw financials'!BU18 | ... EY18: ='Raw financials'!EM18 | FB18: =+FA18-EW18 | FC18: =+FB18/EW18 | FD18: =+FA18/T18 | FE18: =+FA18/U18
A19: Of which is JV and asso income | AA19: =+U19-T19 | AB19: =+AA19/T19 | AD19: =+U19-AC19 | AE19: =+AD19/AC19 | AH19: =B19-AG19 | AJ19: =C19-AI19 | AL19: =D19-AK19 | AN19: =E19-AM19 | AP19: =F19-AO19 | AR19: =G19-AQ19 | AT19: =H19-AS19 | AV19: =I19-AU19 | AX19: =J19-AW19 | AZ19: =K19-AY19 | BB19: =L19-BA19 | BD19: =M19-BC19 | BF19: =N19-BE19 | BH19: =O19-BG19 | BJ19: =P19-BI19 | BL19: =Q19-BK19 | BN19: =R19-BM19 | BP19: =S19-BO19 | BR19: =T19-BQ19 | BT19: =U19-BS19 | BU19: =BT19-BR19 | BV19: =BU19/BR19 | BW19: =BT19/T19 | BX19: =BT19/U19 | FB19: =+FA19-EW19 | FC19: =+FB19/EW19 | FD19: =+FA19/T19 | FE19: =+FA19/U19
A20: Impairment losses | B20: =SUM('Raw financials'!B23,'Raw financials'!B24) | C20: =SUM('Raw financials'!C23,'Raw financials'!C24) | D20: =SUM('Raw financials'!D23,'Raw financials'!D24) | E20: =SUM('Raw financials'!E23,'Raw financials'!E24) | F20: =SUM('Raw financials'!F23,'Raw financials'!F24) | G20: =SUM('Raw financials'!G23,'Raw financials'!G24) | H20: =SUM('Raw financials'!H23,'Raw financials'!H24) | I20: =SUM('Raw financials'!I23,'Raw financials'!I24) | ... T20: =SUM('Raw financials'!T23,'Raw financials'!T24) | U20: =4*EX20 | V20: =U20 | W20: =V20 | X20: =W20 | Y20: =X20 | Z20: =Y20 | AA20: =+U20-T20 | AB20: =+AA20/T20 | AC20: -574.3 | AD20: =+U20-AC20 | AE20: =+AD20/AC20 | AG20: =SUM('Raw financials'!AA23,'Raw financials'!AA24) | AH20: =B20-AG20 | AI20: =SUM('Raw financials'!AB23,'Raw financials'!AB24) | AJ20: =C20-AI20 | AK20: =SUM('Raw financials'!AC23,'Raw financials'!AC24) | AL20: =D20-AK20 | AM20: =SUM('Raw financials'!AD23,'Raw financials'!AD24) | AN20: =E20-AM20 | AO20: =SUM('Raw financials'!AE23,'Raw financials'!AE24) | AP20: =F20-AO20 | AQ20: =SUM('Raw financials'!AF23,'Raw financials'!AF24) | AR20: =G20-AQ20 | AS20: =SUM('Raw financials'!AG23,'Raw financials'!AG24) | AT20: =H20-AS20 | AU20: =SUM('Raw financials'!AH23,'Raw financials'!AH24) | AV20: =I20-AU20 | AW20: =SUM('Raw financials'!AI23,'Raw financials'!AI24) | AX20: =J20-AW20 | AY20: =SUM('Raw financials'!AJ23,'Raw financials'!AJ24) | AZ20: =K20-AY20 | BA20: =SUM('Raw financials'!AK23,'Raw financials'!AK24) | BB20: =L20-BA20 | BC20: =SUM('Raw financials'!AL23,'Raw financials'!AL24) | BD20: =M20-BC20 | BE20: =SUM('Raw financials'!AM23,'Raw financials'!AM24) | BF20: =N20-BE20 | BG20: =SUM('Raw financials'!AN23,'Raw financials'!AN24) | BH20: =O20-BG20 | BI20: =SUM('Raw financials'!AO23,'Raw financials'!AO24) | BJ20: =P20-BI20 | BK20: =SUM('Raw financials'!AP23,'Raw financials'!AP24) | BL20: =Q20-BK20 | BM20: =SUM('Raw financials'!AQ23,'Raw financials'!AQ24) | BN20: =R20-BM20 | BO20: =SUM('Raw financials'!AR23,'Raw financials'!AR24) | BP20: =S20-BO20 | BQ20: =SUM('Raw financials'!AS23,'Raw financials'!AS24) | BR20: =T20-BQ20 | BT20: =U20-BS20 | BU20: =BT20-BR20 | BV20: =BU20/BR20 | BW20: =BT20/T20 | BX20: =BT20/U20 | BZ20: =SUM('Raw financials'!BN23,'Raw financials'!BN24) | CA20: =SUM('Raw financials'!BO23,'Raw financials'!BO24) | CB20: =SUM('Raw financials'!BP23,'Raw financials'!BP24) | CC20: =SUM('Raw financials'!BQ23,'Raw financials'!BQ24) | CD20: =SUM('Raw financials'!BR23,'Raw financials'!BR24) | CE20: =SUM('Raw financials'!BS23,'Raw financials'!BS24) | CF20: =SUM('Raw financials'!BT23,'Raw financials'!BT24) | CG20: =SUM('Raw financials'!BU23,'Raw financials'!BU24) | ... EY20: =SUM('Raw financials'!EM23,'Raw financials'!EM24) | FB20: =+FA20-EW20 | FC20: =+FB20/EW20 | FD20: =+FA20/T20 | FE20: =+FA20/U20
A21: Other income and expenses | B21: =SUM('Raw financials'!B17,'Raw financials'!B22,'Raw financials'!B25,'Raw financials'!B30,-'Raw financials'!B31) | C21: =SUM('Raw financials'!C17,'Raw financials'!C22,'Raw financials'!C25,'Raw financials'!C30,-'Raw financials'!C31) | D21: =SUM('Raw financials'!D17,'Raw financials'!D22,'Raw financials'!D25,'Raw financials'!D30,-'Raw financials'!D31) | E21: =SUM('Raw financials'!E17,'Raw financials'!E22,'Raw financials'!E25,'Raw financials'!E30,-'Raw financials'!E31) | F21: =SUM('Raw financials'!F17,'Raw financials'!F22,'Raw financials'!F25,'Raw financials'!F30,-'Raw financials'!F31) | G21: =SUM('Raw financials'!G17,'Raw financials'!G22,'Raw financials'!G25,'Raw financials'!G30,-'Raw financials'!G31) | H21: =SUM('Raw financials'!H17,'Raw financials'!H22,'Raw financials'!H25,'Raw financials'!H30,-'Raw financials'!H31) | I21: =SUM('Raw financials'!I17,'Raw financials'!I22,'Raw financials'!I25,'Raw financials'!I30,-'Raw financials'!I31) | ... S21: =SUM('Raw financials'!S17,'Raw financials'!S22,'Raw financials'!S25,'Raw financials'!S30,-'Raw financials'!S31) | T21: =SUM(-'Raw financials'!T16,'Raw financials'!T17,'Raw financials'!T22,'Raw financials'!T25,'Raw financials'!T26,'Raw financials'!T30,-'Raw financials'!T31) | U21: =T21/T4*U4 | V21: =+V4/U4*U21 | W21: =+W4/V4*V21 | X21: =+X4/W4*W21 | Y21: =+Y4/X4*X21 | Z21: =+Z4/Y4*Y21 | AA21: =+U21-T21 | AB21: =+AA21/T21 | AC21: 653.33991 | AD21: =+U21-AC21 | AE21: =+AD21/AC21 | AG21: =SUM(-'Raw financials'!AA16,'Raw financials'!AA17,'Raw financials'!AA22,'Raw financials'!AA25,'Raw financials'!AA26,'Raw financials'!AA30,-'Raw financials'!AA31) | AH21: =B21-AG21 | AI21: =SUM(-'Raw financials'!AB16,'Raw financials'!AB17,'Raw financials'!AB22,'Raw financials'!AB25,'Raw financials'!AB26,'Raw financials'!AB30,-'Raw financials'!AB31) | AJ21: =C21-AI21 | AK21: =SUM(-'Raw financials'!AC16,'Raw financials'!AC17,'Raw financials'!AC22,'Raw financials'!AC25,'Raw financials'!AC26,'Raw financials'!AC30,-'Raw financials'!AC31) | AL21: =D21-AK21 | AM21: =SUM(-'Raw financials'!AD16,'Raw financials'!AD17,'Raw financials'!AD22,'Raw financials'!AD25,'Raw financials'!AD26,'Raw financials'!AD30,-'Raw financials'!AD31) | AN21: =E21-AM21 | AO21: =SUM(-'Raw financials'!AE16,'Raw financials'!AE17,'Raw financials'!AE22,'Raw financials'!AE25,'Raw financials'!AE26,'Raw financials'!AE30,-'Raw financials'!AE31) | AP21: =F21-AO21 | AQ21: =SUM(-'Raw financials'!AF16,'Raw financials'!AF17,'Raw financials'!AF22,'Raw financials'!AF25,'Raw financials'!AF26,'Raw financials'!AF30,-'Raw financials'!AF31) | AR21: =G21-AQ21 | AS21: =SUM(-'Raw financials'!AG16,'Raw financials'!AG17,'Raw financials'!AG22,'Raw financials'!AG25,'Raw financials'!AG26,'Raw financials'!AG30,-'Raw financials'!AG31) | AT21: =H21-AS21 | AU21: =SUM(-'Raw financials'!AH16,'Raw financials'!AH17,'Raw financials'!AH22,'Raw financials'!AH25,'Raw financials'!AH26,'Raw financials'!AH30,-'Raw financials'!AH31) | AV21: =I21-AU21 | AW21: =SUM(-'Raw financials'!AI16,'Raw financials'!AI17,'Raw financials'!AI22,'Raw financials'!AI25,'Raw financials'!AI26,'Raw financials'!AI30,-'Raw financials'!AI31) | AX21: =J21-AW21 | AY21: =SUM(-'Raw financials'!AJ16,'Raw financials'!AJ17,'Raw financials'!AJ22,'Raw financials'!AJ25,'Raw financials'!AJ26,'Raw financials'!AJ30,-'Raw financials'!AJ31) | AZ21: =K21-AY21 | BA21: =SUM(-'Raw financials'!AK16,'Raw financials'!AK17,'Raw financials'!AK22,'Raw financials'!AK25,'Raw financials'!AK26,'Raw financials'!AK30,-'Raw financials'!AK31) | BB21: =L21-BA21 | BC21: =SUM(-'Raw financials'!AL16,'Raw financials'!AL17,'Raw financials'!AL22,'Raw financials'!AL25,'Raw financials'!AL26,'Raw financials'!AL30,-'Raw financials'!AL31) | BD21: =M21-BC21 | BE21: =SUM(-'Raw financials'!AM16,'Raw financials'!AM17,'Raw financials'!AM22,'Raw financials'!AM25,'Raw financials'!AM26,'Raw financials'!AM30,-'Raw financials'!AM31) | BF21: =N21-BE21 | BG21: =SUM(-'Raw financials'!AN16,'Raw financials'!AN17,'Raw financials'!AN22,'Raw financials'!AN25,'Raw financials'!AN26,'Raw financials'!AN30,-'Raw financials'!AN31) | BH21: =O21-BG21 | BI21: =SUM(-'Raw financials'!AO16,'Raw financials'!AO17,'Raw financials'!AO22,'Raw financials'!AO25,'Raw financials'!AO26,'Raw financials'!AO30,-'Raw financials'!AO31) | BJ21: =P21-BI21 | BK21: =SUM(-'Raw financials'!AP16,'Raw financials'!AP17,'Raw financials'!AP22,'Raw financials'!AP25,'Raw financials'!AP26,'Raw financials'!AP30,-'Raw financials'!AP31) | BL21: =Q21-BK21 | BM21: =SUM(-'Raw financials'!AQ16,'Raw financials'!AQ17,'Raw financials'!AQ22,'Raw financials'!AQ25,'Raw financials'!AQ26,'Raw financials'!AQ30,-'Raw financials'!AQ31) | BN21: =R21-BM21 | BO21: =SUM(-'Raw financials'!AR16,'Raw financials'!AR17,'Raw financials'!AR22,'Raw financials'!AR25,'Raw financials'!AR26,'Raw financials'!AR30,-'Raw financials'!AR31) | BP21: =S21-BO21 | BQ21: =SUM(-'Raw financials'!AS16,'Raw financials'!AS17,'Raw financials'!AS22,'Raw financials'!AS25,'Raw financials'!AS26,'Raw financials'!AS30,-'Raw financials'!AS31)-705.08+289.34423726 | BR21: =T21-BQ21 | BT21: =U21-BS21 | BU21: =BT21-BR21 | BV21: =BU21/BR21 | BW21: =BT21/T21 | BX21: =BT21/U21 | BZ21: =SUM(-'Raw financials'!BN16,'Raw financials'!BN17,'Raw financials'!BN22,'Raw financials'!BN25,'Raw financials'!BN26,'Raw financials'!BN30,-'Raw financials'!BN31) | CA21: =SUM(-'Raw financials'!BO16,'Raw financials'!BO17,'Raw financials'!BO22,'Raw financials'!BO25,'Raw financials'!BO26,'Raw financials'!BO30,-'Raw financials'!BO31) | CB21: =SUM(-'Raw financials'!BP16,'Raw financials'!BP17,'Raw financials'!BP22,'Raw financials'!BP25,'Raw financials'!BP26,'Raw financials'!BP30,-'Raw financials'!BP31) | CC21: =SUM(-'Raw financials'!BQ16,'Raw financials'!BQ17,'Raw financials'!BQ22,'Raw financials'!BQ25,'Raw financials'!BQ26,'Raw financials'!BQ30,-'Raw financials'!BQ31) | CD21: =SUM(-'Raw financials'!BR16,'Raw financials'!BR17,'Raw financials'!BR22,'Raw financials'!BR25,'Raw financials'!BR26,'Raw financials'!BR30,-'Raw financials'!BR31) | CE21: =SUM(-'Raw financials'!BS16,'Raw financials'!BS17,'Raw financials'!BS22,'Raw financials'!BS25,'Raw financials'!BS26,'Raw financials'!BS30,-'Raw financials'!BS31) | CF21: =SUM(-'Raw financials'!BT16,'Raw financials'!BT17,'Raw financials'!BT22,'Raw financials'!BT25,'Raw financials'!BT26,'Raw financials'!BT30,-'Raw financials'!BT31) | CG21: =SUM(-'Raw financials'!BU16,'Raw financials'!BU17,'Raw financials'!BU22,'Raw financials'!BU25,'Raw financials'!BU26,'Raw financials'!BU30,-'Raw financials'!BU31) | ... EY21: =SUM(-'Raw financials'!EM16,'Raw financials'!EM17,'Raw financials'!EM22,'Raw financials'!EM25,'Raw financials'!EM26,'Raw financials'!EM30,-'Raw financials'!EM31) | FB21: =+FA21-EW21 | FC21: =+FB21/EW21 | FD21: =+FA21/T21 | FE21: =+FA21/U21
A22: Profit before tax | B22: =B15+B17+B18+B20+B21 | C22: =C15+C17+C18+C20+C21 | D22: =D15+D17+D18+D20+D21 | E22: =E15+E17+E18+E20+E21 | F22: =F15+F17+F18+F20+F21 | G22: =G15+G17+G18+G20+G21 | H22: =H15+H17+H18+H20+H21 | I22: =I15+I17+I18+I20+I21 | ... Z22: =Z15+Z17+Z18+Z20+Z21 | AA22: =+U22-T22 | AB22: =+AA22/T22 | AC22: 5790.3514 | AD22: =+U22-AC22 | AE22: =+AD22/AC22 | AG22: =AG15+AG17+AG18+AG20+AG21 | AH22: =AH15+AH17+AH18+AH20+AH21 | AI22: =AI15+AI17+AI18+AI20+AI21 | AJ22: =AJ15+AJ17+AJ18+AJ20+AJ21 | AK22: =AK15+AK17+AK18+AK20+AK21 | AL22: =AL15+AL17+AL18+AL20+AL21 | AM22: =AM15+AM17+AM18+AM20+AM21 | AN22: =AN15+AN17+AN18+AN20+AN21 | ... BR22: =BR15+BR17+BR18+BR20+BR21 | BT22: =BT15+BT17+BT18+BT20+BT21 | BU22: =BT22-BR22 | BV22: =BU22/BR22 | BW22: =BT22/T22 | BX22: =BT22/U22 | BZ22: =BZ15+BZ17+BZ18+BZ20+BZ21 | CA22: =CA15+CA17+CA18+CA20+CA21 | CB22: =CB15+CB17+CB18+CB20+CB21 | CC22: =CC15+CC17+CC18+CC20+CC21 | CD22: =CD15+CD17+CD18+CD20+CD21 | CE22: =CE15+CE17+CE18+CE20+CE21 | CF22: =CF15+CF17+CF18+CF20+CF21 | CG22: =CG15+CG17+CG18+CG20+CG21 | ... EY22: =EY15+EY17+EY18+EY20+EY21 | FB22: =+FA22-EW22 | FC22: =+FB22/EW22 | FD22: =+FA22/T22 | FE22: =+FA22/U22
A23: Tax | B23: =-'Raw financials'!B36 | C23: =-'Raw financials'!C36 | D23: =-'Raw financials'!D36 | E23: =-'Raw financials'!E36 | F23: =-'Raw financials'!F36 | G23: =-'Raw financials'!G36 | H23: =-'Raw financials'!H36 | I23: =-'Raw financials'!I36 | ... T23: =-'Raw financials'!T36 | U23: =U22*-U24 | V23: =V22*-V24 | W23: =W22*-W24 | X23: =X22*-X24 | Y23: =Y22*-Y24 | Z23: =Z22*-Z24 | AA23: =+U23-T23 | AB23: =+AA23/T23 | AC23: -889.54814 | AD23: =+U23-AC23 | AG23: =-'Raw financials'!AA36 | AH23: =B23-AG23 | AI23: =-'Raw financials'!AB36 | AJ23: =C23-AI23 | AK23: =-'Raw financials'!AC36 | AL23: =D23-AK23 | AM23: =-'Raw financials'!AD36 | AN23: =E23-AM23 | AO23: =-'Raw financials'!AE36 | AP23: =F23-AO23 | AQ23: =-'Raw financials'!AF36 | AR23: =G23-AQ23 | AS23: =-'Raw financials'!AG36 | AT23: =H23-AS23 | AU23: =-'Raw financials'!AH36 | AV23: =I23-AU23 | AW23: =-'Raw financials'!AI36 | AX23: =J23-AW23 | AY23: =-'Raw financials'!AJ36 | AZ23: =K23-AY23 | BA23: =-'Raw financials'!AK36 | BB23: =L23-BA23 | BC23: =-'Raw financials'!AL36 | BD23: =M23-BC23 | BE23: =-'Raw financials'!AM36 | BF23: =N23-BE23 | BG23: =-'Raw financials'!AN36 | BH23: =O23-BG23 | BI23: =-'Raw financials'!AO36 | BJ23: =P23-BI23 | BK23: =-'Raw financials'!AP36 | BL23: =Q23-BK23 | BM23: =-'Raw financials'!AQ36 | BN23: =R23-BM23 | BO23: =-'Raw financials'!AR36 | BP23: =S23-BO23 | BQ23: =-'Raw financials'!AS36 | BR23: =T23-BQ23 | BT23: =U23-BS23 | BU23: =BT23-BR23 | BV23: =BU23/BR23 | BW23: =BT23/T23 | BX23: =BT23/U23 | BZ23: =-'Raw financials'!BN36 | CA23: =-'Raw financials'!BO36 | CB23: =-'Raw financials'!BP36 | CC23: =-'Raw financials'!BQ36 | CD23: =-'Raw financials'!BR36 | CE23: =-'Raw financials'!BS36 | CF23: =-'Raw financials'!BT36 | CG23: =-'Raw financials'!BU36 | ... EY23: =-'Raw financials'!EM36 | FB23: =+FA23-EW23 | FC23: =+FB23/EW23 | FD23: =+FA23/T23 | FE23: =+FA23/U23
A24: Tax rate | B24: =-B23/B22 | C24: =-C23/C22 | D24: =-D23/D22 | E24: =-E23/E22 | F24: =-F23/F22 | G24: =-G23/G22 | H24: =-H23/H22 | I24: =-I23/I22 | ... T24: =-T23/T22 | U24: =T24 | V24: =U24 | W24: =V24 | X24: =W24 | Y24: =X24 | Z24: =Y24 | AG24: =-AG23/AG22 | AH24: =-AH23/AH22 | AI24: =-AI23/AI22 | AJ24: =-AJ23/AJ22 | AK24: =-AK23/AK22 | AL24: =-AL23/AL22 | AM24: =-AM23/AM22 | AN24: =-AN23/AN22 | ... BR24: =-BR23/BR22 | BT24: =-BT23/BT22 | BU24: =BT24-BR24 | BV24: =BU24/BR24 | BW24: =BT24/T24 | BX24: =BT24/U24 | BZ24: =-BZ23/BZ22 | CA24: =-CA23/CA22 | CB24: =-CB23/CB22 | CC24: =-CC23/CC22 | CD24: =-CD23/CD22 | CE24: =-CE23/CE22 | CF24: =-CF23/CF22 | CG24: =-CG23/CG22 | ... EY24: =-EY23/EY22
A25: Profit after tax | B25: =B22+B23 | C25: =C22+C23 | D25: =D22+D23 | E25: =E22+E23 | F25: =F22+F23 | G25: =G22+G23 | H25: =H22+H23 | I25: =I22+I23 | ... Z25: =Z22+Z23 | AA25: =+U25-T25 | AB25: =+AA25/T25 | AC25: 4900.8032 | AD25: =+U25-AC25 | AE25: =+AD25/AC25 | AG25: =AG22+AG23 | AH25: =AH22+AH23 | AI25: =AI22+AI23 | AJ25: =AJ22+AJ23 | AK25: =AK22+AK23 | AL25: =AL22+AL23 | AM25: =AM22+AM23 | AN25: =AN22+AN23 | ... BR25: =BR22+BR23 | BT25: =BT22+BT23 | BU25: =BT25-BR25 | BV25: =BU25/BR25 | BW25: =BT25/T25 | BX25: =BT25/U25 | BZ25: =BZ22+BZ23 | CA25: =CA22+CA23 | CB25: =CB22+CB23 | CC25: =CC22+CC23 | CD25: =CD22+CD23 | CE25: =CE22+CE23 | CF25: =CF22+CF23 | CG25: =CG22+CG23 | ... EY25: =EY22+EY23 | FB25: =+FA25-EW25 | FC25: =+FB25/EW25 | FD25: =+FA25/T25 | FE25: =+FA25/U25
A26: Minority interest | B26: =-'Raw financials'!B43 | C26: =-'Raw financials'!C43 | D26: =-'Raw financials'!D43 | E26: =-'Raw financials'!E43 | F26: =-'Raw financials'!F43 | G26: =-'Raw financials'!G43 | H26: =-'Raw financials'!H43 | I26: =-'Raw financials'!I43 | ... T26: =-'Raw financials'!T43 | U26: =U25*-U27 | V26: =V25*-V27 | W26: =W25*-W27 | X26: =X25*-X27 | Y26: =Y25*-Y27 | Z26: =Z25*-Z27 | AA26: =+U26-T26 | AB26: =+AA26/T26 | AC26: -544.74239 | AG26: =-'Raw financials'!AA43 | AH26: =B26-AG26 | AI26: =-'Raw financials'!AB43 | AJ26: =C26-AI26 | AK26: =-'Raw financials'!AC43 | AL26: =D26-AK26 | AM26: =-'Raw financials'!AD43 | AN26: =E26-AM26 | AO26: =-'Raw financials'!AE43 | AP26: =F26-AO26 | AQ26: =-'Raw financials'!AF43 | AR26: =G26-AQ26 | AS26: =-'Raw financials'!AG43 | AT26: =H26-AS26 | AU26: =-'Raw financials'!AH43 | AV26: =I26-AU26 | AW26: =-'Raw financials'!AI43 | AX26: =J26-AW26 | AY26: =-'Raw financials'!AJ43 | AZ26: =K26-AY26 | BA26: =-'Raw financials'!AK43 | BB26: =L26-BA26 | BC26: =-'Raw financials'!AL43 | BD26: =M26-BC26 | BE26: =-'Raw financials'!AM43 | BF26: =N26-BE26 | BG26: =-'Raw financials'!AN43 | BH26: =O26-BG26 | BI26: =-'Raw financials'!AO43 | BJ26: =P26-BI26 | BK26: =-'Raw financials'!AP43 | BL26: =Q26-BK26 | BM26: =-'Raw financials'!AQ43 | BN26: =R26-BM26 | BO26: =-'Raw financials'!AR43 | BP26: =S26-BO26 | BQ26: =-'Raw financials'!AS43 | BR26: =T26-BQ26 | BT26: =U26-BS26 | BU26: =BT26-BR26 | BV26: =BU26/BR26 | BW26: =BT26/T26 | BX26: =BT26/U26 | BZ26: =-'Raw financials'!BN43 | CA26: =-'Raw financials'!BO43 | CB26: =-'Raw financials'!BP43 | CC26: =-'Raw financials'!BQ43 | CD26: =-'Raw financials'!BR43 | CE26: =-'Raw financials'!BS43 | CF26: =-'Raw financials'!BT43 | CG26: =-'Raw financials'!BU43 | ... EY26: =-'Raw financials'!EM43 | FB26: =+FA26-EW26 | FC26: =+FB26/EW26 | FD26: =+FA26/T26 | FE26: =+FA26/U26
A27: % of PAT | B27: =-B26/B25 | C27: =-C26/C25 | D27: =-D26/D25 | E27: =-E26/E25 | F27: =-F26/F25 | G27: =-G26/G25 | H27: =-H26/H25 | I27: =-I26/I25 | ... T27: =-T26/T25 | U27: =T27 | V27: =U27 | W27: =V27 | X27: =W27 | Y27: =X27 | Z27: =Y27 | AG27: =-AG26/AG25 | AH27: =-AH26/AH25 | AI27: =-AI26/AI25 | AJ27: =-AJ26/AJ25 | AK27: =-AK26/AK25 | AL27: =-AL26/AL25 | AM27: =-AM26/AM25 | AN27: =-AN26/AN25 | ... BR27: =-BR26/BR25 | BT27: =-BT26/BT25 | BU27: =BT27-BR27 | BV27: =BU27/BR27 | BW27: =BT27/T27 | BX27: =BT27/U27 | BZ27: =-BZ26/BZ25 | CA27: =-CA26/CA25 | CB27: =-CB26/CB25 | CC27: =-CC26/CC25 | CD27: =-CD26/CD25 | CE27: =-CE26/CE25 | CF27: =-CF26/CF25 | CG27: =-CG26/CG25 | ... EY27: =-EY26/EY25 | FB27: =+FA27-EW27 | FC27: =+FB27/EW27 | FD27: =+FA27/T27 | FE27: =+FA27/U27
A28: Reported net profit | B28: =B25+B26 | C28: =C25+C26 | D28: =D25+D26 | E28: =E25+E26 | F28: =F25+F26 | G28: =G25+G26 | H28: =H25+H26 | I28: =I25+I26 | ... Z28: =Z25+Z26 | AA28: =+U28-T28 | AB28: =+AA28/T28 | AC28: 4356.0608 | AG28: =AG25+AG26 | AH28: =AH25+AH26 | AI28: =AI25+AI26 | AJ28: =AJ25+AJ26 | AK28: =AK25+AK26 | AL28: =AL25+AL26 | AM28: =AM25+AM26 | AN28: =AN25+AN26 | ... BR28: =BR25+BR26 | BT28: =BT25+BT26 | BU28: =BT28-BR28 | BV28: =BU28/BR28 | BW28: =BT28/T28 | BX28: =BT28/U28 | BZ28: =BZ25+BZ26 | CA28: =CA25+CA26 | CB28: =CB25+CB26 | CC28: =CC25+CC26 | CD28: =CD25+CD26 | CE28: =CE25+CE26 | CF28: =CF25+CF26 | CG28: =CG25+CG26 | ... EY28: =EY25+EY26 | FB28: =+FA28-EW28 | FC28: =+FB28/EW28 | FD28: =+FA28/T28 | FE28: =+FA28/U28
A29: YoY | Q29: =Q28/P28-1 | R29: =R28/Q28-1 | S29: =S28/R28-1 | T29: =T28/S28-1 | U29: =U28/T28-1 | V29: =V28/U28-1 | W29: =W28/V28-1 | X29: =X28/W28-1 | ... Z29: =Z28/Y28-1 | AC29: 0.49072955 | BM29: =BM28/BK28-1 | BN29: =BN28/BL28-1 | BO29: =BO28/BM28-1 | BP29: =BP28/BN28-1 | BQ29: =BQ28/BO28-1 | BR29: =BR28/BP28-1 | BT29: =BT28/BR28-1 | DX29: =DX28/DT28-1 | DY29: =DY28/DU28-1 | DZ29: =DZ28/DV28-1 | EA29: =EA28/DW28-1 | EB29: =EB28/DX28-1 | EC29: =EC28/DY28-1 | ED29: =ED28/DZ28-1 | EE29: =EE28/EA28-1 | ... EY29: =EY28/EU28-1
A30: NPM | B30: =+B28/B4 | C30: =+C28/C4 | D30: =+D28/D4 | E30: =+E28/E4 | F30: =+F28/F4 | G30: =+G28/G4 | H30: =+H28/H4 | I30: =+I28/I4 | ... Z30: =+Z28/Z4 | AC30: 0.053543599 | BM30: =+BM28/BM4 | BN30: =+BN28/BN4 | BO30: =+BO28/BO4 | BP30: =+BP28/BP4 | BQ30: =+BQ28/BQ4 | BR30: =+BR28/BR4 | BT30: =+BT28/BT4 | BZ30: =+BZ28/BZ4 | CA30: =+CA28/CA4 | CB30: =+CB28/CB4 | CC30: =+CC28/CC4 | CD30: =+CD28/CD4 | CE30: =+CE28/CE4 | CF30: =+CF28/CF4 | CG30: =+CG28/CG4 | ... EY30: =+EY28/EY4
A31: ESOP target
A32: YoY
A33: Diff vs. UBS-Se
A35: EPS - basic | B35: ='Raw financials'!B50 | C35: ='Raw financials'!C50 | D35: ='Raw financials'!D50 | E35: ='Raw financials'!E50 | F35: ='Raw financials'!F50 | G35: ='Raw financials'!G50 | H35: ='Raw financials'!H50 | I35: ='Raw financials'!I50 | ... T35: ='Raw financials'!T50 | U35: =U28/U43*U45 | V35: =V28/V43*V45 | W35: =W28/W43*W45 | X35: =X28/X43*X45 | Y35: =Y28/Y43*Y45 | Z35: =Z28/Z43*Z45 | AG35: ='Raw financials'!AA50 | AH35: =B35-AG35 | AI35: ='Raw financials'!AB50 | AJ35: =C35-AI35 | AK35: ='Raw financials'!AC50 | AL35: =D35-AK35 | AM35: ='Raw financials'!AD50 | AN35: =E35-AM35 | AO35: ='Raw financials'!AE50 | AP35: =F35-AO35 | AQ35: ='Raw financials'!AF50 | AR35: =G35-AQ35 | AS35: ='Raw financials'!AG50 | AT35: =H35-AS35 | AU35: ='Raw financials'!AH50 | AV35: =I35-AU35 | AW35: ='Raw financials'!AI50 | AX35: =J35-AW35 | AY35: ='Raw financials'!AJ50 | AZ35: =K35-AY35 | BA35: ='Raw financials'!AK50 | BB35: =L35-BA35 | BC35: ='Raw financials'!AL50 | BD35: =M35-BC35 | BE35: ='Raw financials'!AM50 | BF35: =N35-BE35 | BG35: ='Raw financials'!AN50 | BH35: =O35-BG35 | BI35: ='Raw financials'!AO50 | BJ35: =P35-BI35 | BK35: ='Raw financials'!AP50 | BL35: =Q35-BK35 | BM35: ='Raw financials'!AQ50 | BN35: =R35-BM35 | BO35: ='Raw financials'!AR50 | BP35: =S35-BO35 | BQ35: ='Raw financials'!AS50 | BR35: =T35-BQ35 | BT35: =U35-BS35
A36: EPS - diluted | B36: ='Raw financials'!B51 | C36: ='Raw financials'!C51 | D36: ='Raw financials'!D51 | E36: ='Raw financials'!E51 | F36: ='Raw financials'!F51 | G36: ='Raw financials'!G51 | H36: ='Raw financials'!H51 | I36: ='Raw financials'!I51 | ... T36: ='Raw financials'!T51 | U36: =U28/U44*U45 | V36: =V28/V44*V45 | W36: =W28/W44*W45 | X36: =X28/X44*X45 | Y36: =Y28/Y44*Y45 | Z36: =Z28/Z44*Z45 | AG36: ='Raw financials'!AA51 | AH36: =B36-AG36 | AI36: ='Raw financials'!AB51 | AJ36: =C36-AI36 | AK36: ='Raw financials'!AC51 | AL36: =D36-AK36 | AM36: ='Raw financials'!AD51 | AN36: =E36-AM36 | AO36: ='Raw financials'!AE51 | AP36: =F36-AO36 | AQ36: ='Raw financials'!AF51 | AR36: =G36-AQ36 | AS36: ='Raw financials'!AG51 | AT36: =H36-AS36 | AU36: ='Raw financials'!AH51 | AV36: =I36-AU36 | AW36: ='Raw financials'!AI51 | AX36: =J36-AW36 | AY36: ='Raw financials'!AJ51 | AZ36: =K36-AY36 | BA36: ='Raw financials'!AK51 | BB36: =L36-BA36 | BC36: ='Raw financials'!AL51 | BD36: =M36-BC36 | BE36: ='Raw financials'!AM51 | BF36: =N36-BE36 | BG36: ='Raw financials'!AN51 | BH36: =O36-BG36 | BI36: ='Raw financials'!AO51 | BJ36: =P36-BI36 | BK36: ='Raw financials'!AP51 | BL36: =Q36-BK36 | BM36: ='Raw financials'!AQ51 | BN36: =R36-BM36 | BO36: ='Raw financials'!AR51 | BP36: =S36-BO36 | BQ36: ='Raw financials'!AS51 | BR36: =T36-BQ36 | BT36: =U36-BS36
A37: BPS - YE | B37: =+B89/B42 | C37: =+C89/C42 | D37: =+D89/D42 | E37: =+E89/E42 | F37: =+F89/F42 | G37: =+G89/G42 | H37: =+H89/H42 | I37: =+I89/I42 | ... Z37: =+Z89/Z42
A38: Dividend 现金分红 | B38: 90 | C38: 196.08 | D38: 17.64 | E38: 160.31 | F38: 260.5 | G38: 320.62 | H38: 220.42 | I38: 360.69 | J38: 210.32 | K38: 140.21 | L38: 0 | M38: 0 | N38: 339.99 | O38: 639.35 | P38: 561.53 | Q38: 717.33 | R38: 1044.71 | S38: 1480.81 | T38: 1366.32 | U38: =U28*U40 | V38: =V28*V40 | W38: =W28*W40 | X38: =X28*X40 | Y38: =Y28*Y40 | Z38: =Z28*Z40
A39: DPS | B39: =B38/B42 | C39: =C38/C42 | D39: =D38/D42 | E39: =E38/E42 | F39: =F38/F42 | G39: =G38/G42 | H39: =H38/H42 | I39: =I38/I42 | ... Z39: =Z38/Z42
A40: Payout ratio | B40: =B38/B28 | C40: =C38/C28 | D40: =D38/D28 | E40: =E38/E28 | F40: =F38/F28 | G40: =G38/G28 | H40: =H38/H28 | I40: =I38/I28 | ... T40: =T38/T28 | U40: =T40+1% | V40: =U40+1% | W40: =V40+1% | X40: =+W40 | Y40: =+X40 | Z40: =+Y40
A42: Numbers of shares - YE | B42: =+B84 | C42: =+C84 | D42: =+D84 | E42: =+E84 | F42: =+F84 | G42: =+G84 | H42: =+H84 | I42: =+I84 | ... T42: =+T84 | U42: 3458 | V42: =U42 | W42: =V42 | X42: =W42 | Y42: =X42 | Z42: =Y42 | AG42: =+AG84 | AH42: =+AG42 | AI42: =+AI84 | AJ42: =+AI42 | AK42: =+AK84 | AL42: =+AK42 | AM42: =+AM84 | AN42: =+AM42 | AO42: =+AO84 | AP42: =+AO42 | AQ42: =+AQ84 | AR42: =+AQ42 | AS42: =+AS84 | AT42: =+AS42 | AU42: =+AU84 | AV42: =+AU42 | AW42: =+AW84 | AX42: =+AW42 | AY42: =+AY84 | AZ42: =+AY42 | BA42: =+BA84 | BB42: =+BA42 | BC42: =+BC84 | BD42: =+BC42 | BE42: =+BE84 | BF42: =+BE42 | BG42: =+BG84 | BH42: =+BG42 | BI42: =+BI84 | BJ42: =+BI42 | BK42: =+BK84 | BL42: =+BK42 | BM42: =+BM84 | BN42: =+BM42 | BO42: =+BO84 | BP42: =+BO42 | BQ42: =+BQ84 | BR42: =+BQ42 | BT42: =+BS42
A43: Numbers of shares - Average | B43: =MIN(B28/B35,B42) | C43: =MIN(C28/C35,C42) | D43: =MIN(D28/D35,D42) | E43: =MIN(E28/E35,E42) | F43: =MIN(F28/F35,F42) | G43: =MIN(G28/G35,G42) | H43: =MIN(H28/H35,H42) | I43: =MIN(I28/I35,I42) | ... T43: =MIN(T28/T35,T42) | U43: =AVERAGE(T42:U42) | V43: =AVERAGE(U42:V42) | W43: =AVERAGE(V42:W42) | X43: =AVERAGE(W42:X42) | Y43: =AVERAGE(X42:Y42) | Z43: =AVERAGE(Y42:Z42) | AG43: =MIN(AG28/AG35,AG42) | AH43: =MIN(AH28/AH35,AH42) | AI43: =MIN(AI28/AI35,AI42) | AJ43: =MIN(AJ28/AJ35,AJ42) | AK43: =MIN(AK28/AK35,AK42) | AL43: =MIN(AL28/AL35,AL42) | AM43: =MIN(AM28/AM35,AM42) | AN43: =MIN(AN28/AN35,AN42) | ... BR43: =MIN(BR28/BR35,BR42) | BT43: =MIN(BT28/BT35,BT42)
A44: Numbers of shares - Diluted | B44: =MIN(B28/B36,B42) | C44: =MIN(C28/C36,C42) | D44: =MIN(D28/D36,D42) | E44: =MIN(E28/E36,E42) | F44: =MIN(F28/F36,F42) | G44: =MIN(G28/G36,G42) | H44: =MIN(H28/H36,H42) | I44: =MIN(I28/I36,I42) | ... T44: =MIN(T28/T36,T42) | U44: =+U43 | V44: =+V43 | W44: =+W43 | X44: =+X43 | Y44: =+Y43 | Z44: =+Z43 | AG44: =MIN(AG28/AG36,AG42) | AH44: =MIN(AH28/AH36,AH42) | AI44: =MIN(AI28/AI36,AI42) | AJ44: =MIN(AJ28/AJ36,AJ42) | AK44: =MIN(AK28/AK36,AK42) | AL44: =MIN(AL28/AL36,AL42) | AM44: =MIN(AM28/AM36,AM42) | AN44: =MIN(AN28/AN36,AN42) | ... BR44: =MIN(BR28/BR36,BR42) | BT44: =MIN(BT28/BT36,BT42)
A45: Adjusting factor | B45: 1 | C45: 1 | D45: 1 | E45: 1 | F45: 1 | G45: 1 | H45: 1 | I45: 1 | J45: 1 | K45: 1 | L45: 1 | M45: 1 | N45: 1 | O45: 1 | P45: 1 | Q45: 1 | R45: 1 | S45: 1 | T45: 1 | U45: 1 | V45: 1 | W45: 1 | X45: 1 | Y45: 1 | Z45: 1
A46: Balance Sheet
A47: Cash | B47: ='Raw financials'!B243 | C47: ='Raw financials'!C243 | D47: ='Raw financials'!D243 | E47: ='Raw financials'!E243 | F47: ='Raw financials'!F243 | G47: ='Raw financials'!G243 | H47: ='Raw financials'!H243 | I47: ='Raw financials'!I243 | ... T47: ='Raw financials'!T243 | U47: =U133 | V47: =V133 | W47: =W133 | X47: =X133 | Y47: =Y133 | Z47: =Z133 | AA47: =+U47-T47 | AB47: =+AA47/T47 | AC47: 26981.386 | AD47: =+X47-W47 | AE47: =+AD47/W47 | AG47: ='Raw financials'!AA243 | AH47: =+B47 | AI47: ='Raw financials'!AB243 | AJ47: =+C47 | AK47: ='Raw financials'!AC243 | AL47: =+D47 | AM47: ='Raw financials'!AD243 | AN47: =+E47 | AO47: ='Raw financials'!AE243 | AP47: =+F47 | AQ47: ='Raw financials'!AF243 | AR47: =+G47 | AS47: ='Raw financials'!AG243 | AT47: =+H47 | AU47: ='Raw financials'!AH243 | AV47: =+I47 | AW47: ='Raw financials'!AI243 | AX47: =+J47 | AY47: ='Raw financials'!AJ243 | AZ47: =+K47 | BA47: ='Raw financials'!AK243 | BB47: =+L47 | BC47: ='Raw financials'!AL243 | BD47: =+M47 | BE47: ='Raw financials'!AM243 | BF47: =+N47 | BG47: ='Raw financials'!AN243 | BH47: =+O47 | BI47: ='Raw financials'!AO243 | BJ47: =+P47 | BK47: ='Raw financials'!AP243 | BL47: =+Q47 | BM47: ='Raw financials'!AQ243 | BN47: =+R47 | BO47: ='Raw financials'!AR243 | BP47: =+S47 | BQ47: ='Raw financials'!AS243 | BR47: =+T47 | BT47: =+U47 | BU47: =BT47-BR47 | BV47: =BU47/BR47 | BZ47: ='Raw financials'!BN243 | CA47: ='Raw financials'!BO243 | CB47: ='Raw financials'!BP243 | CC47: ='Raw financials'!BQ243 | CD47: ='Raw financials'!BR243 | CE47: ='Raw financials'!BS243 | CF47: ='Raw financials'!BT243 | CG47: ='Raw financials'!BU243 | ... DX47: ='Raw financials'!DL243 | DZ47: ='Raw financials'!DN243 | EA47: ='Raw financials'!DO243 | EB47: ='Raw financials'!DP243 | EC47: ='Raw financials'!DQ243 | ED47: ='Raw financials'!DR243 | EE47: ='Raw financials'!DS243 | EF47: ='Raw financials'!DT243 | EG47: ='Raw financials'!DU243 | ... EY47: ='Raw financials'!EM243 | FB47: =+FA47-EW47 | FC47: =+FB47/EW47
A48: Restricted cash | B48: ='Raw financials'!B55-Model!B47 | C48: ='Raw financials'!C55-Model!C47 | D48: ='Raw financials'!D55-Model!D47 | E48: ='Raw financials'!E55-Model!E47 | F48: ='Raw financials'!F55-Model!F47 | G48: ='Raw financials'!G55-Model!G47 | H48: ='Raw financials'!H55-Model!H47 | I48: ='Raw financials'!I55-Model!I47 | ... T48: ='Raw financials'!T55-Model!T47 | U48: =+T48 | V48: =+U48 | W48: =+V48 | X48: =+W48 | Y48: =+X48 | Z48: =+Y48 | AA48: =+U48-T48 | AB48: =+AA48/T48 | AC48: 4353.0891 | AD48: =+X48-W48 | AE48: =+AD48/W48 | AG48: ='Raw financials'!AA55-Model!AG47 | AH48: =+B48 | AI48: ='Raw financials'!AB55-Model!AI47 | AJ48: =+C48 | AK48: ='Raw financials'!AC55-Model!AK47 | AL48: =+D48 | AM48: ='Raw financials'!AD55-Model!AM47 | AN48: =+E48 | AO48: ='Raw financials'!AE55-Model!AO47 | AP48: =+F48 | AQ48: ='Raw financials'!AF55-Model!AQ47 | AR48: =+G48 | AS48: ='Raw financials'!AG55-Model!AS47 | AT48: =+H48 | AU48: ='Raw financials'!AH55-Model!AU47 | AV48: =+I48 | AW48: ='Raw financials'!AI55-Model!AW47 | AX48: =+J48 | AY48: ='Raw financials'!AJ55-Model!AY47 | AZ48: =+K48 | BA48: ='Raw financials'!AK55-Model!BA47 | BB48: =+L48 | BC48: ='Raw financials'!AL55-Model!BC47 | BD48: =+M48 | BE48: ='Raw financials'!AM55-Model!BE47 | BF48: =+N48 | BG48: ='Raw financials'!AN55-Model!BG47 | BH48: =+O48 | BI48: ='Raw financials'!AO55-Model!BI47 | BJ48: =+P48 | BK48: ='Raw financials'!AP55-Model!BK47 | BL48: =+Q48 | BM48: ='Raw financials'!AQ55-Model!BM47 | BN48: =+R48 | BO48: ='Raw financials'!AR55-Model!BO47 | BP48: =+S48 | BQ48: ='Raw financials'!AS55-Model!BQ47 | BR48: =+T48 | BT48: =+U48 | BU48: =BT48-BR48 | BV48: =BU48/BR48 | BZ48: ='Raw financials'!BN55-Model!BZ47 | CA48: ='Raw financials'!BO55-Model!CA47 | CB48: ='Raw financials'!BP55-Model!CB47 | CC48: ='Raw financials'!BQ55-Model!CC47 | CD48: ='Raw financials'!BR55-Model!CD47 | CE48: ='Raw financials'!BS55-Model!CE47 | CF48: ='Raw financials'!BT55-Model!CF47 | CG48: ='Raw financials'!BU55-Model!CG47 | ... DW48: ='Raw financials'!DK55-Model!DW47 | DZ48: ='Raw financials'!DN55-Model!DZ47 | EA48: ='Raw financials'!DO55-Model!EA47 | EB48: ='Raw financials'!DP55-Model!EB47 | EC48: ='Raw financials'!DQ55-Model!EC47 | ED48: ='Raw financials'!DR55-Model!ED47 | EE48: ='Raw financials'!DS55-Model!EE47 | EF48: ='Raw financials'!DT55-Model!EF47 | EG48: ='Raw financials'!DU55-Model!EG47 | ... EY48: ='Raw financials'!EM55-Model!EY47 | FB48: =+FA48-EW48 | FC48: =+FB48/EW48
A49: Accounts receivable & contract assets | B49: =SUM('Raw financials'!B60,'Raw financials'!B71) | C49: =SUM('Raw financials'!C60,'Raw financials'!C71) | D49: =SUM('Raw financials'!D60,'Raw financials'!D71) | E49: =SUM('Raw financials'!E60,'Raw financials'!E71) | F49: =SUM('Raw financials'!F60,'Raw financials'!F71) | G49: =SUM('Raw financials'!G60,'Raw financials'!G71) | H49: =SUM('Raw financials'!H60,'Raw financials'!H71) | I49: =SUM('Raw financials'!I60,'Raw financials'!I71) | ... T49: =SUM('Raw financials'!T60,'Raw financials'!T71) | U49: =Driver!J142 | V49: =Driver!K142 | W49: =Driver!L142 | X49: =Driver!M142 | Y49: =Driver!N142 | Z49: =Driver!O142 | AA49: =+U49-T49 | AB49: =+AA49/T49 | AC49: 31287.985 | AD49: =+X49-W49 | AE49: =+AD49/W49 | AG49: =SUM('Raw financials'!AA60,'Raw financials'!AA71) | AH49: =+B49 | AI49: =SUM('Raw financials'!AB60,'Raw financials'!AB71) | AJ49: =+C49 | AK49: =SUM('Raw financials'!AC60,'Raw financials'!AC71) | AL49: =+D49 | AM49: =SUM('Raw financials'!AD60,'Raw financials'!AD71) | AN49: =+E49 | AO49: =SUM('Raw financials'!AE60,'Raw financials'!AE71) | AP49: =+F49 | AQ49: =SUM('Raw financials'!AF60,'Raw financials'!AF71) | AR49: =+G49 | AS49: =SUM('Raw financials'!AG60,'Raw financials'!AG71) | AT49: =+H49 | AU49: =SUM('Raw financials'!AH60,'Raw financials'!AH71) | AV49: =+I49 | AW49: =SUM('Raw financials'!AI60,'Raw financials'!AI71) | AX49: =+J49 | AY49: =SUM('Raw financials'!AJ60,'Raw financials'!AJ71) | AZ49: =+K49 | BA49: =SUM('Raw financials'!AK60,'Raw financials'!AK71) | BB49: =+L49 | BC49: =SUM('Raw financials'!AL60,'Raw financials'!AL71) | BD49: =+M49 | BE49: =SUM('Raw financials'!AM60,'Raw financials'!AM71) | BF49: =+N49 | BG49: =SUM('Raw financials'!AN60,'Raw financials'!AN71) | BH49: =+O49 | BI49: =SUM('Raw financials'!AO60,'Raw financials'!AO71) | BJ49: =+P49 | BK49: =SUM('Raw financials'!AP60,'Raw financials'!AP71) | BL49: =+Q49 | BM49: =SUM('Raw financials'!AQ60,'Raw financials'!AQ71) | BN49: =+R49 | BO49: =SUM('Raw financials'!AR60,'Raw financials'!AR71) | BP49: =+S49 | BQ49: =SUM('Raw financials'!AS60,'Raw financials'!AS71) | BR49: =+T49 | BT49: =+U49 | BU49: =BT49-BR49 | BV49: =BU49/BR49 | BZ49: =SUM('Raw financials'!BN60,'Raw financials'!BN71) | CA49: =SUM('Raw financials'!BO60,'Raw financials'!BO71) | CB49: =SUM('Raw financials'!BP60,'Raw financials'!BP71) | CC49: =SUM('Raw financials'!BQ60,'Raw financials'!BQ71) | CD49: =SUM('Raw financials'!BR60,'Raw financials'!BR71) | CE49: =SUM('Raw financials'!BS60,'Raw financials'!BS71) | CF49: =SUM('Raw financials'!BT60,'Raw financials'!BT71) | CG49: =SUM('Raw financials'!BU60,'Raw financials'!BU71) | ... DW49: =SUM('Raw financials'!DK60,'Raw financials'!DK71) | DZ49: =SUM('Raw financials'!DN60,'Raw financials'!DN71) | EA49: =SUM('Raw financials'!DO60,'Raw financials'!DO71) | EB49: =SUM('Raw financials'!DP60,'Raw financials'!DP71) | EC49: =SUM('Raw financials'!DQ60,'Raw financials'!DQ71) | ED49: =SUM('Raw financials'!DR60,'Raw financials'!DR71) | EE49: =SUM('Raw financials'!DS60,'Raw financials'!DS71) | EF49: =SUM('Raw financials'!DT60,'Raw financials'!DT71) | EG49: =SUM('Raw financials'!DU60,'Raw financials'!DU71) | ... EY49: =SUM('Raw financials'!EM60,'Raw financials'!EM71) | FB49: =+FA49-EW49 | FC49: =+FB49/EW49
A50: Other receivables | B50: =SUM('Raw financials'!B59,'Raw financials'!B61,'Raw financials'!B63) | C50: =SUM('Raw financials'!C59,'Raw financials'!C61,'Raw financials'!C63) | D50: =SUM('Raw financials'!D59,'Raw financials'!D61,'Raw financials'!D63) | E50: =SUM('Raw financials'!E59,'Raw financials'!E61,'Raw financials'!E63) | F50: =SUM('Raw financials'!F59,'Raw financials'!F61,'Raw financials'!F63) | G50: =SUM('Raw financials'!G59,'Raw financials'!G61,'Raw financials'!G63) | H50: =SUM('Raw financials'!H59,'Raw financials'!H61,'Raw financials'!H63) | I50: =SUM('Raw financials'!I59,'Raw financials'!I61,'Raw financials'!I63) | ... T50: =SUM('Raw financials'!T59,'Raw financials'!T61,'Raw financials'!T63) | U50: =Driver!J144 | V50: =Driver!K144 | W50: =Driver!L144 | X50: =Driver!M144 | Y50: =Driver!N144 | Z50: =Driver!O144 | AA50: =+U50-T50 | AB50: =+AA50/T50 | AC50: 4316.9227 | AD50: =+X50-W50 | AE50: =+AD50/W50 | AG50: =SUM('Raw financials'!AA59,'Raw financials'!AA61,'Raw financials'!AA64,'Raw financials'!AA65,'Raw financials'!AA66) | AH50: =+B50 | AI50: =SUM('Raw financials'!AB59,'Raw financials'!AB61,'Raw financials'!AB64,'Raw financials'!AB65,'Raw financials'!AB66) | AJ50: =+C50 | AK50: =SUM('Raw financials'!AC59,'Raw financials'!AC61,'Raw financials'!AC64,'Raw financials'!AC65,'Raw financials'!AC66) | AL50: =+D50 | AM50: =SUM('Raw financials'!AD59,'Raw financials'!AD61,'Raw financials'!AD64,'Raw financials'!AD65,'Raw financials'!AD66) | AN50: =+E50 | AO50: =SUM('Raw financials'!AE59,'Raw financials'!AE61,'Raw financials'!AE64,'Raw financials'!AE65,'Raw financials'!AE66) | AP50: =+F50 | AQ50: =SUM('Raw financials'!AF59,'Raw financials'!AF61,'Raw financials'!AF64,'Raw financials'!AF65,'Raw financials'!AF66) | AR50: =+G50 | AS50: =SUM('Raw financials'!AG59,'Raw financials'!AG61,'Raw financials'!AG64,'Raw financials'!AG65,'Raw financials'!AG66) | AT50: =+H50 | AU50: =SUM('Raw financials'!AH59,'Raw financials'!AH61,'Raw financials'!AH64,'Raw financials'!AH65,'Raw financials'!AH66) | AV50: =+I50 | AW50: =SUM('Raw financials'!AI59,'Raw financials'!AI61,'Raw financials'!AI64,'Raw financials'!AI65,'Raw financials'!AI66) | AX50: =+J50 | AY50: =SUM('Raw financials'!AJ59,'Raw financials'!AJ61,'Raw financials'!AJ64,'Raw financials'!AJ65,'Raw financials'!AJ66) | AZ50: =+K50 | BA50: =SUM('Raw financials'!AK59,'Raw financials'!AK61,'Raw financials'!AK64,'Raw financials'!AK65,'Raw financials'!AK66) | BB50: =+L50 | BC50: =SUM('Raw financials'!AL59,'Raw financials'!AL61,'Raw financials'!AL64,'Raw financials'!AL65,'Raw financials'!AL66) | BD50: =+M50 | BE50: =SUM('Raw financials'!AM59,'Raw financials'!AM61,'Raw financials'!AM64,'Raw financials'!AM65,'Raw financials'!AM66) | BF50: =+N50 | BG50: =SUM('Raw financials'!AN59,'Raw financials'!AN61,'Raw financials'!AN64,'Raw financials'!AN65,'Raw financials'!AN66) | BH50: =+O50 | BI50: =SUM('Raw financials'!AO59,'Raw financials'!AO61,'Raw financials'!AO64,'Raw financials'!AO65,'Raw financials'!AO66) | BJ50: =+P50 | BK50: =SUM('Raw financials'!AP59,'Raw financials'!AP61,'Raw financials'!AP64,'Raw financials'!AP65,'Raw financials'!AP66) | BL50: =+Q50 | BM50: =SUM('Raw financials'!AQ59,'Raw financials'!AQ61,'Raw financials'!AQ64,'Raw financials'!AQ65,'Raw financials'!AQ66) | BN50: =+R50 | BO50: =SUM('Raw financials'!AR59,'Raw financials'!AR61,'Raw financials'!AR64,'Raw financials'!AR65,'Raw financials'!AR66) | BP50: =+S50 | BQ50: =SUM('Raw financials'!AS59,'Raw financials'!AS61,'Raw financials'!AS64,'Raw financials'!AS65,'Raw financials'!AS66) | BR50: =+T50 | BT50: =+U50 | BU50: =BT50-BR50 | BV50: =BU50/BR50 | BZ50: =SUM('Raw financials'!BN59,'Raw financials'!BN61,'Raw financials'!BN64,'Raw financials'!BN65,'Raw financials'!BN66) | CA50: =SUM('Raw financials'!BO59,'Raw financials'!BO61,'Raw financials'!BO64,'Raw financials'!BO65,'Raw financials'!BO66) | CB50: =SUM('Raw financials'!BP59,'Raw financials'!BP61,'Raw financials'!BP64,'Raw financials'!BP65,'Raw financials'!BP66) | CC50: =SUM('Raw financials'!BQ59,'Raw financials'!BQ61,'Raw financials'!BQ64,'Raw financials'!BQ65,'Raw financials'!BQ66) | CD50: =SUM('Raw financials'!BR59,'Raw financials'!BR61,'Raw financials'!BR64,'Raw financials'!BR65,'Raw financials'!BR66) | CE50: =SUM('Raw financials'!BS59,'Raw financials'!BS61,'Raw financials'!BS64,'Raw financials'!BS65,'Raw financials'!BS66) | CF50: =SUM('Raw financials'!BT59,'Raw financials'!BT61,'Raw financials'!BT64,'Raw financials'!BT65,'Raw financials'!BT66) | CG50: =SUM('Raw financials'!BU59,'Raw financials'!BU61,'Raw financials'!BU64,'Raw financials'!BU65,'Raw financials'!BU66) | ... DW50: =SUM('Raw financials'!DK59,'Raw financials'!DK61,'Raw financials'!DK64,'Raw financials'!DK65,'Raw financials'!DK66) | DZ50: =SUM('Raw financials'!DN59,'Raw financials'!DN61,'Raw financials'!DN64,'Raw financials'!DN65,'Raw financials'!DN66) | EA50: =SUM('Raw financials'!DO59,'Raw financials'!DO61,'Raw financials'!DO63) | EB50: =SUM('Raw financials'!DP59,'Raw financials'!DP61,'Raw financials'!DP63) | EC50: =SUM('Raw financials'!DQ59,'Raw financials'!DQ61,'Raw financials'!DQ63) | ED50: =SUM('Raw financials'!DR59,'Raw financials'!DR61,'Raw financials'!DR63) | EE50: =SUM('Raw financials'!DS59,'Raw financials'!DS61,'Raw financials'!DS63) | EF50: =SUM('Raw financials'!DT59,'Raw financials'!DT61,'Raw financials'!DT63) | EG50: =SUM('Raw financials'!DU59,'Raw financials'!DU61,'Raw financials'!DU63) | EH50: =SUM('Raw financials'!DV59,'Raw financials'!DV61,'Raw financials'!DV63) | ... EY50: =SUM('Raw financials'!EM59,'Raw financials'!EM61,'Raw financials'!EM63) | FB50: =+FA50-EW50 | FC50: =+FB50/EW50
A51: Inventory | B51: ='Raw financials'!B68 | C51: ='Raw financials'!C68 | D51: ='Raw financials'!D68 | E51: ='Raw financials'!E68 | F51: ='Raw financials'!F68 | G51: ='Raw financials'!G68 | H51: ='Raw financials'!H68 | I51: ='Raw financials'!I68 | ... T51: ='Raw financials'!T68 | U51: =Driver!J146 | V51: =Driver!K146 | W51: =Driver!L146 | X51: =Driver!M146 | Y51: =Driver!N146 | Z51: =Driver!O146 | AA51: =+U51-T51 | AB51: =+AA51/T51 | AC51: 25106.81 | AD51: =+X51-W51 | AE51: =+AD51/W51 | AG51: ='Raw financials'!AA68 | AH51: =+B51 | AI51: ='Raw financials'!AB68 | AJ51: =+C51 | AK51: ='Raw financials'!AC68 | AL51: =+D51 | AM51: ='Raw financials'!AD68 | AN51: =+E51 | AO51: ='Raw financials'!AE68 | AP51: =+F51 | AQ51: ='Raw financials'!AF68 | AR51: =+G51 | AS51: ='Raw financials'!AG68 | AT51: =+H51 | AU51: ='Raw financials'!AH68 | AV51: =+I51 | AW51: ='Raw financials'!AI68 | AX51: =+J51 | AY51: ='Raw financials'!AJ68 | AZ51: =+K51 | BA51: ='Raw financials'!AK68 | BB51: =+L51 | BC51: ='Raw financials'!AL68 | BD51: =+M51 | BE51: ='Raw financials'!AM68 | BF51: =+N51 | BG51: ='Raw financials'!AN68 | BH51: =+O51 | BI51: ='Raw financials'!AO68 | BJ51: =+P51 | BK51: ='Raw financials'!AP68 | BL51: =+Q51 | BM51: ='Raw financials'!AQ68 | BN51: =+R51 | BO51: ='Raw financials'!AR68 | BP51: =+S51 | BQ51: ='Raw financials'!AS68 | BR51: =+T51 | BT51: =+U51 | BU51: =BT51-BR51 | BV51: =BU51/BR51 | BZ51: ='Raw financials'!BN68 | CA51: ='Raw financials'!BO68 | CB51: ='Raw financials'!BP68 | CC51: ='Raw financials'!BQ68 | CD51: ='Raw financials'!BR68 | CE51: ='Raw financials'!BS68 | CF51: ='Raw financials'!BT68 | CG51: ='Raw financials'!BU68 | ... DW51: ='Raw financials'!DK68 | DZ51: ='Raw financials'!DN68 | EA51: ='Raw financials'!DO68 | EB51: ='Raw financials'!DP68 | EC51: ='Raw financials'!DQ68 | ED51: ='Raw financials'!DR68 | EE51: ='Raw financials'!DS68 | EF51: ='Raw financials'!DT68 | EG51: ='Raw financials'!DU68 | ... EY51: ='Raw financials'!EM68 | FB51: =+FA51-EW51 | FC51: =+FB51/EW51
A52: Fixed assets available-for-sale | B52: =+'Raw financials'!B72 | C52: =+'Raw financials'!C72 | D52: =+'Raw financials'!D72 | E52: =+'Raw financials'!E72 | F52: =+'Raw financials'!F72 | G52: =+'Raw financials'!G72 | H52: =+'Raw financials'!H72 | I52: =+'Raw financials'!I72 | ... T52: =+'Raw financials'!T72 | U52: =+T52 | V52: =+U52 | W52: =+V52 | X52: =+W52 | Y52: =+X52 | Z52: =+Y52 | AA52: =+U52-T52 | AB52: =+AA52/T52 | AC52: 0 | AD52: =+X52-W52 | AE52: =+AD52/W52 | AG52: =+'Raw financials'!AA72 | AH52: =+B52 | AI52: =+'Raw financials'!AB72 | AJ52: =+C52 | AK52: =+'Raw financials'!AC72 | AL52: =+D52 | AM52: =+'Raw financials'!AD72 | AN52: =+E52 | AO52: =+'Raw financials'!AE72 | AP52: =+F52 | AQ52: =+'Raw financials'!AF72 | AR52: =+G52 | AS52: =+'Raw financials'!AG72 | AT52: =+H52 | AU52: =+'Raw financials'!AH72 | AV52: =+I52 | AW52: =+'Raw financials'!AI72 | AX52: =+J52 | AY52: =+'Raw financials'!AJ72 | AZ52: =+K52 | BA52: =+'Raw financials'!AK72 | BB52: =+L52 | BC52: =+'Raw financials'!AL72 | BD52: =+M52 | BE52: =+'Raw financials'!AM72 | BF52: =+N52 | BG52: =+'Raw financials'!AN72 | BH52: =+O52 | BI52: =+'Raw financials'!AO72 | BJ52: =+P52 | BK52: =+'Raw financials'!AP72 | BL52: =+Q52 | BM52: =+'Raw financials'!AQ72 | BN52: =+R52 | BO52: =+'Raw financials'!AR72 | BP52: =+S52 | BQ52: =+'Raw financials'!AS72 | BR52: =+T52 | BT52: =+U52 | BU52: =BT52-BR52 | BV52: =BU52/BR52 | BZ52: =+'Raw financials'!BN72 | CA52: =+'Raw financials'!BO72 | CB52: =+'Raw financials'!BP72 | CC52: =+'Raw financials'!BQ72 | CD52: =+'Raw financials'!BR72 | CE52: =+'Raw financials'!BS72 | CF52: =+'Raw financials'!BT72 | CG52: =+'Raw financials'!BU72 | ... DW52: =+'Raw financials'!DK72 | DZ52: =+'Raw financials'!DN72 | EA52: =+'Raw financials'!DO72 | EB52: =+'Raw financials'!DP72 | EC52: =+'Raw financials'!DQ72 | ED52: =+'Raw financials'!DR72 | EE52: =+'Raw financials'!DS72 | EF52: =+'Raw financials'!DT72 | EG52: =+'Raw financials'!DU72 | ... EY52: =+'Raw financials'!EM72 | FB52: =+FA52-EW52 | FC52: =+FB52/EW52
A53: Other current assets | B53: =SUM('Raw financials'!B56,'Raw financials'!B62,'Raw financials'!B67,'Raw financials'!B72,'Raw financials'!B73,'Raw financials'!B75,'Raw financials'!B76) | C53: =SUM('Raw financials'!C56,'Raw financials'!C62,'Raw financials'!C67,'Raw financials'!C72,'Raw financials'!C73,'Raw financials'!C75,'Raw financials'!C76) | D53: =SUM('Raw financials'!D56,'Raw financials'!D62,'Raw financials'!D67,'Raw financials'!D72,'Raw financials'!D73,'Raw financials'!D75,'Raw financials'!D76) | E53: =SUM('Raw financials'!E56,'Raw financials'!E62,'Raw financials'!E67,'Raw financials'!E72,'Raw financials'!E73,'Raw financials'!E75,'Raw financials'!E76) | F53: =SUM('Raw financials'!F56,'Raw financials'!F62,'Raw financials'!F67,'Raw financials'!F72,'Raw financials'!F73,'Raw financials'!F75,'Raw financials'!F76) | G53: =SUM('Raw financials'!G56,'Raw financials'!G62,'Raw financials'!G67,'Raw financials'!G72,'Raw financials'!G73,'Raw financials'!G75,'Raw financials'!G76) | H53: =SUM('Raw financials'!H56,'Raw financials'!H62,'Raw financials'!H67,'Raw financials'!H72,'Raw financials'!H73,'Raw financials'!H75,'Raw financials'!H76) | I53: =SUM('Raw financials'!I56,'Raw financials'!I62,'Raw financials'!I67,'Raw financials'!I72,'Raw financials'!I73,'Raw financials'!I75,'Raw financials'!I76) | ... T53: =SUM('Raw financials'!T56,'Raw financials'!T62,'Raw financials'!T67,'Raw financials'!T72,'Raw financials'!T73,'Raw financials'!T75,'Raw financials'!T76) | U53: =T53 | V53: =U53 | W53: =V53 | X53: =W53 | Y53: =X53 | Z53: =Y53 | AA53: =+U53-T53 | AB53: =+AA53/T53 | AC53: 14736.701 | AD53: =+X53-W53 | AE53: =+AD53/W53 | AG53: =SUM('Raw financials'!AA74,'Raw financials'!AA56,'Raw financials'!AA62,'Raw financials'!AA67,'Raw financials'!AA72,'Raw financials'!AA73,'Raw financials'!AA75,'Raw financials'!AA76,'Raw financials'!AA77) | AH53: =+B53 | AI53: =SUM('Raw financials'!AB74,'Raw financials'!AB56,'Raw financials'!AB62,'Raw financials'!AB67,'Raw financials'!AB72,'Raw financials'!AB73,'Raw financials'!AB75,'Raw financials'!AB76,'Raw financials'!AB77) | AJ53: =+C53 | AK53: =SUM('Raw financials'!AC74,'Raw financials'!AC56,'Raw financials'!AC62,'Raw financials'!AC67,'Raw financials'!AC72,'Raw financials'!AC73,'Raw financials'!AC75,'Raw financials'!AC76,'Raw financials'!AC77) | AL53: =+D53 | AM53: =SUM('Raw financials'!AD74,'Raw financials'!AD56,'Raw financials'!AD62,'Raw financials'!AD67,'Raw financials'!AD72,'Raw financials'!AD73,'Raw financials'!AD75,'Raw financials'!AD76,'Raw financials'!AD77) | AN53: =+E53 | AO53: =SUM('Raw financials'!AE74,'Raw financials'!AE56,'Raw financials'!AE62,'Raw financials'!AE67,'Raw financials'!AE72,'Raw financials'!AE73,'Raw financials'!AE75,'Raw financials'!AE76,'Raw financials'!AE77) | AP53: =+F53 | AQ53: =SUM('Raw financials'!AF74,'Raw financials'!AF56,'Raw financials'!AF62,'Raw financials'!AF67,'Raw financials'!AF72,'Raw financials'!AF73,'Raw financials'!AF75,'Raw financials'!AF76,'Raw financials'!AF77) | AR53: =+G53 | AS53: =SUM('Raw financials'!AG74,'Raw financials'!AG56,'Raw financials'!AG62,'Raw financials'!AG67,'Raw financials'!AG72,'Raw financials'!AG73,'Raw financials'!AG75,'Raw financials'!AG76,'Raw financials'!AG77) | AT53: =+H53 | AU53: =SUM('Raw financials'!AH74,'Raw financials'!AH56,'Raw financials'!AH62,'Raw financials'!AH67,'Raw financials'!AH72,'Raw financials'!AH73,'Raw financials'!AH75,'Raw financials'!AH76,'Raw financials'!AH77) | AV53: =+I53 | AW53: =SUM('Raw financials'!AI74,'Raw financials'!AI56,'Raw financials'!AI62,'Raw financials'!AI67,'Raw financials'!AI72,'Raw financials'!AI73,'Raw financials'!AI75,'Raw financials'!AI76,'Raw financials'!AI77) | AX53: =+J53 | AY53: =SUM('Raw financials'!AJ74,'Raw financials'!AJ56,'Raw financials'!AJ62,'Raw financials'!AJ67,'Raw financials'!AJ72,'Raw financials'!AJ73,'Raw financials'!AJ75,'Raw financials'!AJ76,'Raw financials'!AJ77) | AZ53: =+K53 | BA53: =SUM('Raw financials'!AK74,'Raw financials'!AK56,'Raw financials'!AK62,'Raw financials'!AK67,'Raw financials'!AK72,'Raw financials'!AK73,'Raw financials'!AK75,'Raw financials'!AK76,'Raw financials'!AK77) | BB53: =+L53 | BC53: =SUM('Raw financials'!AL74,'Raw financials'!AL56,'Raw financials'!AL62,'Raw financials'!AL67,'Raw financials'!AL72,'Raw financials'!AL73,'Raw financials'!AL75,'Raw financials'!AL76,'Raw financials'!AL77) | BD53: =+M53 | BE53: =SUM('Raw financials'!AM74,'Raw financials'!AM56,'Raw financials'!AM62,'Raw financials'!AM67,'Raw financials'!AM72,'Raw financials'!AM73,'Raw financials'!AM75,'Raw financials'!AM76,'Raw financials'!AM77) | BF53: =+N53 | BG53: =SUM('Raw financials'!AN74,'Raw financials'!AN56,'Raw financials'!AN62,'Raw financials'!AN67,'Raw financials'!AN72,'Raw financials'!AN73,'Raw financials'!AN75,'Raw financials'!AN76,'Raw financials'!AN77) | BH53: =+O53 | BI53: =SUM('Raw financials'!AO74,'Raw financials'!AO56,'Raw financials'!AO62,'Raw financials'!AO67,'Raw financials'!AO72,'Raw financials'!AO73,'Raw financials'!AO75,'Raw financials'!AO76,'Raw financials'!AO77) | BJ53: =+P53 | BK53: =SUM('Raw financials'!AP74,'Raw financials'!AP56,'Raw financials'!AP62,'Raw financials'!AP67,'Raw financials'!AP72,'Raw financials'!AP73,'Raw financials'!AP75,'Raw financials'!AP76,'Raw financials'!AP77) | BL53: =+Q53 | BM53: =SUM('Raw financials'!AQ74,'Raw financials'!AQ56,'Raw financials'!AQ62,'Raw financials'!AQ67,'Raw financials'!AQ72,'Raw financials'!AQ73,'Raw financials'!AQ75,'Raw financials'!AQ76,'Raw financials'!AQ77) | BN53: =+R53 | BO53: =SUM('Raw financials'!AR74,'Raw financials'!AR56,'Raw financials'!AR62,'Raw financials'!AR67,'Raw financials'!AR72,'Raw financials'!AR73,'Raw financials'!AR75,'Raw financials'!AR76,'Raw financials'!AR77) | BP53: =+S53 | BQ53: =SUM('Raw financials'!AS74,'Raw financials'!AS56,'Raw financials'!AS62,'Raw financials'!AS67,'Raw financials'!AS72,'Raw financials'!AS73,'Raw financials'!AS75,'Raw financials'!AS76,'Raw financials'!AS77) | BR53: =+T53 | BT53: =+U53 | BU53: =BT53-BR53 | BV53: =BU53/BR53 | BZ53: =SUM('Raw financials'!BN74,'Raw financials'!BN56,'Raw financials'!BN62,'Raw financials'!BN67,'Raw financials'!BN72,'Raw financials'!BN73,'Raw financials'!BN75,'Raw financials'!BN76,'Raw financials'!BN77) | CA53: =SUM('Raw financials'!BO74,'Raw financials'!BO56,'Raw financials'!BO62,'Raw financials'!BO67,'Raw financials'!BO72,'Raw financials'!BO73,'Raw financials'!BO75,'Raw financials'!BO76,'Raw financials'!BO77) | CB53: =SUM('Raw financials'!BP74,'Raw financials'!BP56,'Raw financials'!BP62,'Raw financials'!BP67,'Raw financials'!BP72,'Raw financials'!BP73,'Raw financials'!BP75,'Raw financials'!BP76,'Raw financials'!BP77) | CC53: =SUM('Raw financials'!BQ74,'Raw financials'!BQ56,'Raw financials'!BQ62,'Raw financials'!BQ67,'Raw financials'!BQ72,'Raw financials'!BQ73,'Raw financials'!BQ75,'Raw financials'!BQ76,'Raw financials'!BQ77) | CD53: =SUM('Raw financials'!BR74,'Raw financials'!BR56,'Raw financials'!BR62,'Raw financials'!BR67,'Raw financials'!BR72,'Raw financials'!BR73,'Raw financials'!BR75,'Raw financials'!BR76,'Raw financials'!BR77) | CE53: =SUM('Raw financials'!BS74,'Raw financials'!BS56,'Raw financials'!BS62,'Raw financials'!BS67,'Raw financials'!BS72,'Raw financials'!BS73,'Raw financials'!BS75,'Raw financials'!BS76,'Raw financials'!BS77) | CF53: =SUM('Raw financials'!BT74,'Raw financials'!BT56,'Raw financials'!BT62,'Raw financials'!BT67,'Raw financials'!BT72,'Raw financials'!BT73,'Raw financials'!BT75,'Raw financials'!BT76,'Raw financials'!BT77) | CG53: =SUM('Raw financials'!BU74,'Raw financials'!BU56,'Raw financials'!BU62,'Raw financials'!BU67,'Raw financials'!BU72,'Raw financials'!BU73,'Raw financials'!BU75,'Raw financials'!BU76,'Raw financials'!BU77) | ... DW53: =SUM('Raw financials'!DK74,'Raw financials'!DK56,'Raw financials'!DK62,'Raw financials'!DK67,'Raw financials'!DK72,'Raw financials'!DK73,'Raw financials'!DK75,'Raw financials'!DK76,'Raw financials'!DK77) | DZ53: =SUM('Raw financials'!DN74,'Raw financials'!DN56,'Raw financials'!DN62,'Raw financials'!DN67,'Raw financials'!DN72,'Raw financials'!DN73,'Raw financials'!DN75,'Raw financials'!DN76,'Raw financials'!DN77) | EA53: =SUM('Raw financials'!DO74,'Raw financials'!DO56,'Raw financials'!DO62,'Raw financials'!DO67,'Raw financials'!DO72,'Raw financials'!DO73,'Raw financials'!DO75,'Raw financials'!DO76,'Raw financials'!DO77) | EB53: =SUM('Raw financials'!DP74,'Raw financials'!DP56,'Raw financials'!DP62,'Raw financials'!DP67,'Raw financials'!DP72,'Raw financials'!DP73,'Raw financials'!DP75,'Raw financials'!DP76,'Raw financials'!DP77) | EC53: =SUM('Raw financials'!DQ74,'Raw financials'!DQ56,'Raw financials'!DQ62,'Raw financials'!DQ67,'Raw financials'!DQ72,'Raw financials'!DQ73,'Raw financials'!DQ75,'Raw financials'!DQ76,'Raw financials'!DQ77) | ED53: =SUM('Raw financials'!DR74,'Raw financials'!DR56,'Raw financials'!DR62,'Raw financials'!DR67,'Raw financials'!DR72,'Raw financials'!DR73,'Raw financials'!DR75,'Raw financials'!DR76,'Raw financials'!DR77) | EE53: =SUM('Raw financials'!DS74,'Raw financials'!DS56,'Raw financials'!DS62,'Raw financials'!DS67,'Raw financials'!DS72,'Raw financials'!DS73,'Raw financials'!DS75,'Raw financials'!DS76,'Raw financials'!DS77) | EF53: =SUM('Raw financials'!DT74,'Raw financials'!DT56,'Raw financials'!DT62,'Raw financials'!DT67,'Raw financials'!DT72,'Raw financials'!DT73,'Raw financials'!DT75,'Raw financials'!DT76,'Raw financials'!DT77) | EG53: =SUM('Raw financials'!DU74,'Raw financials'!DU56,'Raw financials'!DU62,'Raw financials'!DU67,'Raw financials'!DU72,'Raw financials'!DU73,'Raw financials'!DU75,'Raw financials'!DU76,'Raw financials'!DU77) | ... EY53: =SUM('Raw financials'!EM74,'Raw financials'!EM56,'Raw financials'!EM62,'Raw financials'!EM67,'Raw financials'!EM72,'Raw financials'!EM73,'Raw financials'!EM75,'Raw financials'!EM76,'Raw financials'!EM77) | FB53: =+FA53-EW53 | FC53: =+FB53/EW53
A54: Total current assets | B54: =SUM(B47:B53) | C54: =SUM(C47:C53) | D54: =SUM(D47:D53) | E54: =SUM(E47:E53) | F54: =SUM(F47:F53) | G54: =SUM(G47:G53) | H54: =SUM(H47:H53) | I54: =SUM(I47:I53) | ... Z54: =SUM(Z47:Z53) | AA54: =+U54-T54 | AB54: =+AA54/T54 | AC54: 106782.89 | AD54: =+X54-W54 | AE54: =+AD54/W54 | AG54: =SUM(AG47:AG53) | AH54: =SUM(AH47:AH53) | AI54: =SUM(AI47:AI53) | AJ54: =SUM(AJ47:AJ53) | AK54: =SUM(AK47:AK53) | AL54: =SUM(AL47:AL53) | AM54: =SUM(AM47:AM53) | AN54: =SUM(AN47:AN53) | ... BR54: =SUM(BR47:BR53) | BT54: =SUM(BT47:BT53) | BU54: =BT54-BR54 | BV54: =BU54/BR54 | BZ54: =SUM(BZ47:BZ53) | CA54: =SUM(CA47:CA53) | CB54: =SUM(CB47:CB53) | CC54: =SUM(CC47:CC53) | CD54: =SUM(CD47:CD53) | CE54: =SUM(CE47:CE53) | CF54: =SUM(CF47:CF53) | CG54: =SUM(CG47:CG53) | ... DW54: =SUM(DW47:DW53) | DZ54: =SUM(DZ47:DZ53) | EA54: =SUM(EA47:EA53) | EB54: =SUM(EB47:EB53) | EC54: =SUM(EC47:EC53) | ED54: =SUM(ED47:ED53) | EE54: =SUM(EE47:EE53) | EF54: =SUM(EF47:EF53) | EG54: =SUM(EG47:EG53) | ... EY54: =SUM(EY47:EY53) | FB54: =+FA54-EW54 | FC54: =+FB54/EW54
A56: Financial assets | B56: =SUM('Raw financials'!B81,'Raw financials'!B84,'Raw financials'!B86,'Raw financials'!B87,'Raw financials'!B89) | C56: =SUM('Raw financials'!C81,'Raw financials'!C84,'Raw financials'!C86,'Raw financials'!C87,'Raw financials'!C89) | D56: =SUM('Raw financials'!D81,'Raw financials'!D84,'Raw financials'!D86,'Raw financials'!D87,'Raw financials'!D89) | E56: =SUM('Raw financials'!E81,'Raw financials'!E84,'Raw financials'!E86,'Raw financials'!E87,'Raw financials'!E89) | F56: =SUM('Raw financials'!F81,'Raw financials'!F84,'Raw financials'!F86,'Raw financials'!F87,'Raw financials'!F89) | G56: =SUM('Raw financials'!G81,'Raw financials'!G84,'Raw financials'!G86,'Raw financials'!G87,'Raw financials'!G89) | H56: =SUM('Raw financials'!H81,'Raw financials'!H84,'Raw financials'!H86,'Raw financials'!H87,'Raw financials'!H89) | I56: =SUM('Raw financials'!I81,'Raw financials'!I84,'Raw financials'!I86,'Raw financials'!I87,'Raw financials'!I89) | ... T56: =SUM('Raw financials'!T81,'Raw financials'!T84,'Raw financials'!T86,'Raw financials'!T87,'Raw financials'!T89) | U56: =T56 | V56: =U56 | W56: =V56 | X56: =W56 | Y56: =X56 | Z56: =Y56 | AA56: =+U56-T56 | AB56: =+AA56/T56 | AC56: 24813.791 | AD56: =+X56-W56 | AE56: =+AD56/W56 | AG56: =SUM('Raw financials'!AA81,'Raw financials'!AA84,'Raw financials'!AA85,'Raw financials'!AA86,'Raw financials'!AA87,'Raw financials'!AA89) | AH56: =+B56 | AI56: =SUM('Raw financials'!AB81,'Raw financials'!AB84,'Raw financials'!AB85,'Raw financials'!AB86,'Raw financials'!AB87,'Raw financials'!AB89) | AJ56: =+C56 | AK56: =SUM('Raw financials'!AC81,'Raw financials'!AC84,'Raw financials'!AC85,'Raw financials'!AC86,'Raw financials'!AC87,'Raw financials'!AC89) | AL56: =+D56 | AM56: =SUM('Raw financials'!AD81,'Raw financials'!AD84,'Raw financials'!AD85,'Raw financials'!AD86,'Raw financials'!AD87,'Raw financials'!AD89) | AN56: =+E56 | AO56: =SUM('Raw financials'!AE81,'Raw financials'!AE84,'Raw financials'!AE85,'Raw financials'!AE86,'Raw financials'!AE87,'Raw financials'!AE89) | AP56: =+F56 | AQ56: =SUM('Raw financials'!AF81,'Raw financials'!AF84,'Raw financials'!AF85,'Raw financials'!AF86,'Raw financials'!AF87,'Raw financials'!AF89) | AR56: =+G56 | AS56: =SUM('Raw financials'!AG81,'Raw financials'!AG84,'Raw financials'!AG85,'Raw financials'!AG86,'Raw financials'!AG87,'Raw financials'!AG89) | AT56: =+H56 | AU56: =SUM('Raw financials'!AH81,'Raw financials'!AH84,'Raw financials'!AH85,'Raw financials'!AH86,'Raw financials'!AH87,'Raw financials'!AH89) | AV56: =+I56 | AW56: =SUM('Raw financials'!AI81,'Raw financials'!AI84,'Raw financials'!AI85,'Raw financials'!AI86,'Raw financials'!AI87,'Raw financials'!AI89) | AX56: =+J56 | AY56: =SUM('Raw financials'!AJ81,'Raw financials'!AJ84,'Raw financials'!AJ85,'Raw financials'!AJ86,'Raw financials'!AJ87,'Raw financials'!AJ89) | AZ56: =+K56 | BA56: =SUM('Raw financials'!AK81,'Raw financials'!AK84,'Raw financials'!AK85,'Raw financials'!AK86,'Raw financials'!AK87,'Raw financials'!AK89) | BB56: =+L56 | BC56: =SUM('Raw financials'!AL81,'Raw financials'!AL84,'Raw financials'!AL85,'Raw financials'!AL86,'Raw financials'!AL87,'Raw financials'!AL89) | BD56: =+M56 | BE56: =SUM('Raw financials'!AM81,'Raw financials'!AM84,'Raw financials'!AM85,'Raw financials'!AM86,'Raw financials'!AM87,'Raw financials'!AM89) | BF56: =+N56 | BG56: =SUM('Raw financials'!AN81,'Raw financials'!AN84,'Raw financials'!AN85,'Raw financials'!AN86,'Raw financials'!AN87,'Raw financials'!AN89) | BH56: =+O56 | BI56: =SUM('Raw financials'!AO81,'Raw financials'!AO84,'Raw financials'!AO85,'Raw financials'!AO86,'Raw financials'!AO87,'Raw financials'!AO89) | BJ56: =+P56 | BK56: =SUM('Raw financials'!AP81,'Raw financials'!AP84,'Raw financials'!AP85,'Raw financials'!AP86,'Raw financials'!AP87,'Raw financials'!AP89) | BL56: =+Q56 | BM56: =SUM('Raw financials'!AQ81,'Raw financials'!AQ84,'Raw financials'!AQ85,'Raw financials'!AQ86,'Raw financials'!AQ87,'Raw financials'!AQ89) | BN56: =+R56 | BO56: =SUM('Raw financials'!AR81,'Raw financials'!AR84,'Raw financials'!AR85,'Raw financials'!AR86,'Raw financials'!AR87,'Raw financials'!AR89) | BP56: =+S56 | BQ56: =SUM('Raw financials'!AS81,'Raw financials'!AS84,'Raw financials'!AS85,'Raw financials'!AS86,'Raw financials'!AS87,'Raw financials'!AS89) | BR56: =+T56 | BT56: =+U56 | BU56: =BT56-BR56 | BV56: =BU56/BR56 | BZ56: =SUM('Raw financials'!BN81,'Raw financials'!BN84,'Raw financials'!BN85,'Raw financials'!BN86,'Raw financials'!BN87,'Raw financials'!BN89) | CA56: =SUM('Raw financials'!BO81,'Raw financials'!BO84,'Raw financials'!BO85,'Raw financials'!BO86,'Raw financials'!BO87,'Raw financials'!BO89) | CB56: =SUM('Raw financials'!BP81,'Raw financials'!BP84,'Raw financials'!BP85,'Raw financials'!BP86,'Raw financials'!BP87,'Raw financials'!BP89) | CC56: =SUM('Raw financials'!BQ81,'Raw financials'!BQ84,'Raw financials'!BQ85,'Raw financials'!BQ86,'Raw financials'!BQ87,'Raw financials'!BQ89) | CD56: =SUM('Raw financials'!BR81,'Raw financials'!BR84,'Raw financials'!BR85,'Raw financials'!BR86,'Raw financials'!BR87,'Raw financials'!BR89) | CE56: =SUM('Raw financials'!BS81,'Raw financials'!BS84,'Raw financials'!BS85,'Raw financials'!BS86,'Raw financials'!BS87,'Raw financials'!BS89) | CF56: =SUM('Raw financials'!BT81,'Raw financials'!BT84,'Raw financials'!BT85,'Raw financials'!BT86,'Raw financials'!BT87,'Raw financials'!BT89) | CG56: =SUM('Raw financials'!BU81,'Raw financials'!BU84,'Raw financials'!BU85,'Raw financials'!BU86,'Raw financials'!BU87,'Raw financials'!BU89) | ... DW56: =SUM('Raw financials'!DK81,'Raw financials'!DK84,'Raw financials'!DK85,'Raw financials'!DK86,'Raw financials'!DK87,'Raw financials'!DK89) | DZ56: =SUM('Raw financials'!DN81,'Raw financials'!DN84,'Raw financials'!DN85,'Raw financials'!DN86,'Raw financials'!DN87,'Raw financials'!DN89) | EA56: =SUM('Raw financials'!DO81,'Raw financials'!DO84,'Raw financials'!DO85,'Raw financials'!DO86,'Raw financials'!DO87,'Raw financials'!DO89) | EB56: =SUM('Raw financials'!DP81,'Raw financials'!DP84,'Raw financials'!DP85,'Raw financials'!DP86,'Raw financials'!DP87,'Raw financials'!DP89) | EC56: =SUM('Raw financials'!DQ81,'Raw financials'!DQ84,'Raw financials'!DQ85,'Raw financials'!DQ86,'Raw financials'!DQ87,'Raw financials'!DQ89) | ED56: =SUM('Raw financials'!DR81,'Raw financials'!DR84,'Raw financials'!DR85,'Raw financials'!DR86,'Raw financials'!DR87,'Raw financials'!DR89) | EE56: =SUM('Raw financials'!DS81,'Raw financials'!DS84,'Raw financials'!DS85,'Raw financials'!DS86,'Raw financials'!DS87,'Raw financials'!DS89) | EF56: =SUM('Raw financials'!DT81,'Raw financials'!DT84,'Raw financials'!DT85,'Raw financials'!DT86,'Raw financials'!DT87,'Raw financials'!DT89) | EG56: =SUM('Raw financials'!DU81,'Raw financials'!DU84,'Raw financials'!DU85,'Raw financials'!DU86,'Raw financials'!DU87,'Raw financials'!DU89) | ... EY56: =SUM('Raw financials'!EM81,'Raw financials'!EM84,'Raw financials'!EM85,'Raw financials'!EM86,'Raw financials'!EM87,'Raw financials'!EM89) | FB56: =+FA56-EW56 | FC56: =+FB56/EW56
A57: Long term receivables | B57: ='Raw financials'!B90 | C57: ='Raw financials'!C90 | D57: ='Raw financials'!D90 | E57: ='Raw financials'!E90 | F57: ='Raw financials'!F90 | G57: ='Raw financials'!G90 | H57: ='Raw financials'!H90 | I57: ='Raw financials'!I90 | ... T57: ='Raw financials'!T90 | U57: =T57 | V57: =U57 | W57: =V57 | X57: =W57 | Y57: =X57 | Z57: =Y57 | AA57: =+U57-T57 | AB57: =+AA57/T57 | AC57: 21.8791 | AD57: =+X57-W57 | AE57: =+AD57/W57 | AG57: ='Raw financials'!AA90 | AH57: =+B57 | AI57: ='Raw financials'!AB90 | AJ57: =+C57 | AK57: ='Raw financials'!AC90 | AL57: =+D57 | AM57: ='Raw financials'!AD90 | AN57: =+E57 | AO57: ='Raw financials'!AE90 | AP57: =+F57 | AQ57: ='Raw financials'!AF90 | AR57: =+G57 | AS57: ='Raw financials'!AG90 | AT57: =+H57 | AU57: ='Raw financials'!AH90 | AV57: =+I57 | AW57: ='Raw financials'!AI90 | AX57: =+J57 | AY57: ='Raw financials'!AJ90 | AZ57: =+K57 | BA57: ='Raw financials'!AK90 | BB57: =+L57 | BC57: ='Raw financials'!AL90 | BD57: =+M57 | BE57: ='Raw financials'!AM90 | BF57: =+N57 | BG57: ='Raw financials'!AN90 | BH57: =+O57 | BI57: ='Raw financials'!AO90 | BJ57: =+P57 | BK57: ='Raw financials'!AP90 | BL57: =+Q57 | BM57: ='Raw financials'!AQ90 | BN57: =+R57 | BO57: ='Raw financials'!AR90 | BP57: =+S57 | BQ57: ='Raw financials'!AS90 | BR57: =+T57 | BT57: =+U57 | BU57: =BT57-BR57 | BV57: =BU57/BR57 | BZ57: ='Raw financials'!BN90 | CA57: ='Raw financials'!BO90 | CB57: ='Raw financials'!BP90 | CC57: ='Raw financials'!BQ90 | CD57: ='Raw financials'!BR90 | CE57: ='Raw financials'!BS90 | CF57: ='Raw financials'!BT90 | CG57: ='Raw financials'!BU90 | ... DW57: ='Raw financials'!DK90 | DZ57: ='Raw financials'!DN90 | EA57: ='Raw financials'!DO90 | EB57: ='Raw financials'!DP90 | EC57: ='Raw financials'!DQ90 | ED57: ='Raw financials'!DR90 | EE57: ='Raw financials'!DS90 | EF57: ='Raw financials'!DT90 | EG57: ='Raw financials'!DU90 | ... EY57: ='Raw financials'!EM90 | FB57: =+FA57-EW57 | FC57: =+FB57/EW57
A58: Long term investment and investment property | B58: =SUM('Raw financials'!B91:B92) | C58: =SUM('Raw financials'!C91:C92) | D58: =SUM('Raw financials'!D91:D92) | E58: =SUM('Raw financials'!E91:E92) | F58: =SUM('Raw financials'!F91:F92) | G58: =SUM('Raw financials'!G91:G92) | H58: =SUM('Raw financials'!H91:H92) | I58: =SUM('Raw financials'!I91:I92) | ... T58: =SUM('Raw financials'!T91:T92) | U58: =T58 | V58: =U58 | W58: =V58 | X58: =W58 | Y58: =X58 | Z58: =Y58 | AA58: =+U58-T58 | AB58: =+AA58/T58 | AC58: 3068.2095 | AD58: =+X58-W58 | AE58: =+AD58/W58 | AG58: =SUM('Raw financials'!AA91:AA92) | AH58: =+B58 | AI58: =SUM('Raw financials'!AB91:AB92) | AJ58: =+C58 | AK58: =SUM('Raw financials'!AC91:AC92) | AL58: =+D58 | AM58: =SUM('Raw financials'!AD91:AD92) | AN58: =+E58 | AO58: =SUM('Raw financials'!AE91:AE92) | AP58: =+F58 | AQ58: =SUM('Raw financials'!AF91:AF92) | AR58: =+G58 | AS58: =SUM('Raw financials'!AG91:AG92) | AT58: =+H58 | AU58: =SUM('Raw financials'!AH91:AH92) | AV58: =+I58 | AW58: =SUM('Raw financials'!AI91:AI92) | AX58: =+J58 | AY58: =SUM('Raw financials'!AJ91:AJ92) | AZ58: =+K58 | BA58: =SUM('Raw financials'!AK91:AK92) | BB58: =+L58 | BC58: =SUM('Raw financials'!AL91:AL92) | BD58: =+M58 | BE58: =SUM('Raw financials'!AM91:AM92) | BF58: =+N58 | BG58: =SUM('Raw financials'!AN91:AN92) | BH58: =+O58 | BI58: =SUM('Raw financials'!AO91:AO92) | BJ58: =+P58 | BK58: =SUM('Raw financials'!AP91:AP92) | BL58: =+Q58 | BM58: =SUM('Raw financials'!AQ91:AQ92) | BN58: =+R58 | BO58: =SUM('Raw financials'!AR91:AR92) | BP58: =+S58 | BQ58: =SUM('Raw financials'!AS91:AS92) | BR58: =+T58 | BT58: =+U58 | BU58: =BT58-BR58 | BV58: =BU58/BR58 | BZ58: =SUM('Raw financials'!BN91:BN92) | CA58: =SUM('Raw financials'!BO91:BO92) | CB58: =SUM('Raw financials'!BP91:BP92) | CC58: =SUM('Raw financials'!BQ91:BQ92) | CD58: =SUM('Raw financials'!BR91:BR92) | CE58: =SUM('Raw financials'!BS91:BS92) | CF58: =SUM('Raw financials'!BT91:BT92) | CG58: =SUM('Raw financials'!BU91:BU92) | ... DW58: =SUM('Raw financials'!DK91:DK92) | DZ58: =SUM('Raw financials'!DN91:DN92) | EA58: =SUM('Raw financials'!DO91:DO92) | EB58: =SUM('Raw financials'!DP91:DP92) | EC58: =SUM('Raw financials'!DQ91:DQ92) | ED58: =SUM('Raw financials'!DR91:DR92) | EE58: =SUM('Raw financials'!DS91:DS92) | EF58: =SUM('Raw financials'!DT91:DT92) | EG58: =SUM('Raw financials'!DU91:DU92) | ... EY58: =SUM('Raw financials'!EM91:EM92) | FB58: =+FA58-EW58 | FC58: =+FB58/EW58
A59: PPE | B59: ='Raw financials'!B93 | C59: ='Raw financials'!C93 | D59: ='Raw financials'!D93 | E59: ='Raw financials'!E93 | F59: ='Raw financials'!F93 | G59: ='Raw financials'!G93 | H59: ='Raw financials'!H93 | I59: ='Raw financials'!I93 | ... T59: ='Raw financials'!T93 | U59: =Driver!J108 | V59: =Driver!K108 | W59: =Driver!L108 | X59: =Driver!M108 | Y59: =Driver!N108 | Z59: =Driver!O108 | AA59: =+U59-T59 | AB59: =+AA59/T59 | AC59: 6200.5949 | AD59: =+X59-W59 | AE59: =+AD59/W59 | AG59: ='Raw financials'!AA94+'Raw financials'!AA95 | AH59: =+B59 | AI59: ='Raw financials'!AB94+'Raw financials'!AB95 | AJ59: =+C59 | AK59: ='Raw financials'!AC94+'Raw financials'!AC95 | AL59: =+D59 | AM59: ='Raw financials'!AD94+'Raw financials'!AD95 | AN59: =+E59 | AO59: ='Raw financials'!AE94+'Raw financials'!AE95 | AP59: =+F59 | AQ59: ='Raw financials'!AF94+'Raw financials'!AF95 | AR59: =+G59 | AS59: ='Raw financials'!AG94+'Raw financials'!AG95 | AT59: =+H59 | AU59: ='Raw financials'!AH94+'Raw financials'!AH95 | AV59: =+I59 | AW59: ='Raw financials'!AI94+'Raw financials'!AI95 | AX59: =+J59 | AY59: ='Raw financials'!AJ94+'Raw financials'!AJ95 | AZ59: =+K59 | BA59: ='Raw financials'!AK94+'Raw financials'!AK95 | BB59: =+L59 | BC59: ='Raw financials'!AL94+'Raw financials'!AL95 | BD59: =+M59 | BE59: ='Raw financials'!AM94+'Raw financials'!AM95 | BF59: =+N59 | BG59: ='Raw financials'!AN94+'Raw financials'!AN95 | BH59: =+O59 | BI59: ='Raw financials'!AO94+'Raw financials'!AO95 | BJ59: =+P59 | BK59: ='Raw financials'!AP94+'Raw financials'!AP95 | BL59: =+Q59 | BM59: ='Raw financials'!AQ94+'Raw financials'!AQ95 | BN59: =+R59 | BO59: ='Raw financials'!AR94+'Raw financials'!AR95 | BP59: =+S59 | BQ59: ='Raw financials'!AS94+'Raw financials'!AS95 | BR59: =+T59 | BT59: =+U59 | BU59: =BT59-BR59 | BV59: =BU59/BR59 | BZ59: ='Raw financials'!BN94+'Raw financials'!BN95 | CA59: ='Raw financials'!BO94+'Raw financials'!BO95 | CB59: ='Raw financials'!BP94+'Raw financials'!BP95 | CC59: ='Raw financials'!BQ94+'Raw financials'!BQ95 | CD59: ='Raw financials'!BR94+'Raw financials'!BR95 | CE59: ='Raw financials'!BS94+'Raw financials'!BS95 | CF59: ='Raw financials'!BT94+'Raw financials'!BT95 | CG59: ='Raw financials'!BU94+'Raw financials'!BU95 | ... DW59: ='Raw financials'!DK94+'Raw financials'!DK95 | DZ59: ='Raw financials'!DN93 | EA59: ='Raw financials'!DO93 | EB59: ='Raw financials'!DP93 | EC59: ='Raw financials'!DQ93 | ED59: ='Raw financials'!DR93 | EE59: ='Raw financials'!DS93 | EF59: ='Raw financials'!DT93 | EG59: ='Raw financials'!DU93 | ... EY59: ='Raw financials'!EM93 | FB59: =+FA59-EW59 | FC59: =+FB59/EW59
A60: Construction in progress | B60: ='Raw financials'!B96 | C60: ='Raw financials'!C96 | D60: ='Raw financials'!D96 | E60: ='Raw financials'!E96 | F60: ='Raw financials'!F96 | G60: ='Raw financials'!G96 | H60: ='Raw financials'!H96 | I60: ='Raw financials'!I96 | ... T60: ='Raw financials'!T96 | U60: =Driver!J115 | V60: =Driver!K115 | W60: =Driver!L115 | X60: =Driver!M115 | Y60: =Driver!N115 | Z60: =Driver!O115 | AA60: =+U60-T60 | AB60: =+AA60/T60 | AC60: 2559.4288 | AD60: =+X60-W60 | AE60: =+AD60/W60 | AG60: ='Raw financials'!AA97+'Raw financials'!AA98 | AH60: =+B60 | AI60: ='Raw financials'!AB97+'Raw financials'!AB98 | AJ60: =+C60 | AK60: ='Raw financials'!AC97+'Raw financials'!AC98 | AL60: =+D60 | AM60: ='Raw financials'!AD97+'Raw financials'!AD98 | AN60: =+E60 | AO60: ='Raw financials'!AE97+'Raw financials'!AE98 | AP60: =+F60 | AQ60: ='Raw financials'!AF97+'Raw financials'!AF98 | AR60: =+G60 | AS60: ='Raw financials'!AG97+'Raw financials'!AG98 | AT60: =+H60 | AU60: ='Raw financials'!AH97+'Raw financials'!AH98 | AV60: =+I60 | AW60: ='Raw financials'!AI97+'Raw financials'!AI98 | AX60: =+J60 | AY60: ='Raw financials'!AJ97+'Raw financials'!AJ98 | AZ60: =+K60 | BA60: ='Raw financials'!AK97+'Raw financials'!AK98 | BB60: =+L60 | BC60: ='Raw financials'!AL97+'Raw financials'!AL98 | BD60: =+M60 | BE60: ='Raw financials'!AM97+'Raw financials'!AM98 | BF60: =+N60 | BG60: ='Raw financials'!AN97+'Raw financials'!AN98 | BH60: =+O60 | BI60: ='Raw financials'!AO97+'Raw financials'!AO98 | BJ60: =+P60 | BK60: ='Raw financials'!AP97+'Raw financials'!AP98 | BL60: =+Q60 | BM60: ='Raw financials'!AQ97+'Raw financials'!AQ98 | BN60: =+R60 | BO60: ='Raw financials'!AR97+'Raw financials'!AR98 | BP60: =+S60 | BQ60: ='Raw financials'!AS97+'Raw financials'!AS98 | BR60: =+T60 | BT60: =+U60 | BU60: =BT60-BR60 | BV60: =BU60/BR60 | BZ60: ='Raw financials'!BN97+'Raw financials'!BN98 | CA60: ='Raw financials'!BO97+'Raw financials'!BO98 | CB60: ='Raw financials'!BP97+'Raw financials'!BP98 | CC60: ='Raw financials'!BQ97+'Raw financials'!BQ98 | CD60: ='Raw financials'!BR97+'Raw financials'!BR98 | CE60: ='Raw financials'!BS97+'Raw financials'!BS98 | CF60: ='Raw financials'!BT97+'Raw financials'!BT98 | CG60: ='Raw financials'!BU97+'Raw financials'!BU98 | ... DW60: ='Raw financials'!DK97+'Raw financials'!DK98 | DZ60: ='Raw financials'!DN96 | EA60: ='Raw financials'!DO96 | EB60: ='Raw financials'!DP96 | EC60: ='Raw financials'!DQ96 | ED60: ='Raw financials'!DR96 | EE60: ='Raw financials'!DS96 | EF60: ='Raw financials'!DT96 | EG60: ='Raw financials'!DU96 | ... EY60: ='Raw financials'!EM96 | FB60: =+FA60-EW60 | FC60: =+FB60/EW60
A61: Intangible assets | B61: =SUM('Raw financials'!B101:B102) | C61: =SUM('Raw financials'!C101:C102) | D61: =SUM('Raw financials'!D101:D102) | E61: =SUM('Raw financials'!E101:E102) | F61: =SUM('Raw financials'!F101:F102) | G61: =SUM('Raw financials'!G101:G102) | H61: =SUM('Raw financials'!H101:H102) | I61: =SUM('Raw financials'!I101:I102) | ... T61: =SUM('Raw financials'!T101:T102) | U61: =T61-U108+Driver!J121 | V61: =U61-V108+Driver!K121 | W61: =V61-W108+Driver!L121 | X61: =W61-X108+Driver!M121 | Y61: =X61-Y108+Driver!N121 | Z61: =Y61-Z108+Driver!O121 | AA61: =+U61-T61 | AB61: =+AA61/T61 | AC61: 2731.4557 | AD61: =+X61-W61 | AE61: =+AD61/W61 | AG61: =SUM('Raw financials'!AA101:AA102) | AH61: =+B61 | AI61: =SUM('Raw financials'!AB101:AB102) | AJ61: =+C61 | AK61: =SUM('Raw financials'!AC101:AC102) | AL61: =+D61 | AM61: =SUM('Raw financials'!AD101:AD102) | AN61: =+E61 | AO61: =SUM('Raw financials'!AE101:AE102) | AP61: =+F61 | AQ61: =SUM('Raw financials'!AF101:AF102) | AR61: =+G61 | AS61: =SUM('Raw financials'!AG101:AG102) | AT61: =+H61 | AU61: =SUM('Raw financials'!AH101:AH102) | AV61: =+I61 | AW61: =SUM('Raw financials'!AI101:AI102) | AX61: =+J61 | AY61: =SUM('Raw financials'!AJ101:AJ102) | AZ61: =+K61 | BA61: =SUM('Raw financials'!AK101:AK102) | BB61: =+L61 | BC61: =SUM('Raw financials'!AL101:AL102) | BD61: =+M61 | BE61: =SUM('Raw financials'!AM101:AM102) | BF61: =+N61 | BG61: =SUM('Raw financials'!AN101:AN102) | BH61: =+O61 | BI61: =SUM('Raw financials'!AO101:AO102) | BJ61: =+P61 | BK61: =SUM('Raw financials'!AP101:AP102) | BL61: =+Q61 | BM61: =SUM('Raw financials'!AQ101:AQ102) | BN61: =+R61 | BO61: =SUM('Raw financials'!AR101:AR102) | BP61: =+S61 | BQ61: =SUM('Raw financials'!AS101:AS102) | BR61: =+T61 | BT61: =+U61 | BU61: =BT61-BR61 | BV61: =BU61/BR61 | BZ61: =SUM('Raw financials'!BN101:BN102) | CA61: =SUM('Raw financials'!BO101:BO102) | CB61: =SUM('Raw financials'!BP101:BP102) | CC61: =SUM('Raw financials'!BQ101:BQ102) | CD61: =SUM('Raw financials'!BR101:BR102) | CE61: =SUM('Raw financials'!BS101:BS102) | CF61: =SUM('Raw financials'!BT101:BT102) | CG61: =SUM('Raw financials'!BU101:BU102) | ... DW61: =SUM('Raw financials'!DK101:DK102) | DZ61: =SUM('Raw financials'!DN101:DN102) | EA61: =SUM('Raw financials'!DO101:DO102) | EB61: =SUM('Raw financials'!DP101:DP102) | EC61: =SUM('Raw financials'!DQ101:DQ102) | ED61: =SUM('Raw financials'!DR101:DR102) | EE61: =SUM('Raw financials'!DS101:DS102) | EF61: =SUM('Raw financials'!DT101:DT102) | EG61: =SUM('Raw financials'!DU101:DU102) | ... EY61: =SUM('Raw financials'!EM101:EM102) | FB61: =+FA61-EW61 | FC61: =+FB61/EW61
A62: Goodwill | B62: ='Raw financials'!B106 | C62: ='Raw financials'!C106 | D62: ='Raw financials'!D106 | E62: ='Raw financials'!E106 | F62: ='Raw financials'!F106 | G62: ='Raw financials'!G106 | H62: ='Raw financials'!H106 | I62: ='Raw financials'!I106 | ... T62: ='Raw financials'!T106 | U62: =T62 | V62: =U62 | W62: =V62 | X62: =W62 | Y62: =X62 | Z62: =Y62 | AA62: =+U62-T62 | AB62: =+AA62/T62 | AC62: 0 | AD62: =+X62-W62 | AE62: =+AD62/W62 | AG62: ='Raw financials'!AA106 | AH62: =+B62 | AI62: ='Raw financials'!AB106 | AJ62: =+C62 | AK62: ='Raw financials'!AC106 | AL62: =+D62 | AM62: ='Raw financials'!AD106 | AN62: =+E62 | AO62: ='Raw financials'!AE106 | AP62: =+F62 | AQ62: ='Raw financials'!AF106 | AR62: =+G62 | AS62: ='Raw financials'!AG106 | AT62: =+H62 | AU62: ='Raw financials'!AH106 | AV62: =+I62 | AW62: ='Raw financials'!AI106 | AX62: =+J62 | AY62: ='Raw financials'!AJ106 | AZ62: =+K62 | BA62: ='Raw financials'!AK106 | BB62: =+L62 | BC62: ='Raw financials'!AL106 | BD62: =+M62 | BE62: ='Raw financials'!AM106 | BF62: =+N62 | BG62: ='Raw financials'!AN106 | BH62: =+O62 | BI62: ='Raw financials'!AO106 | BJ62: =+P62 | BK62: ='Raw financials'!AP106 | BL62: =+Q62 | BM62: ='Raw financials'!AQ106 | BN62: =+R62 | BO62: ='Raw financials'!AR106 | BP62: =+S62 | BQ62: ='Raw financials'!AS106 | BR62: =+T62 | BT62: =+U62 | BU62: =BT62-BR62 | BV62: =BU62/BR62 | BZ62: ='Raw financials'!BN106 | CA62: ='Raw financials'!BO106 | CB62: ='Raw financials'!BP106 | CC62: ='Raw financials'!BQ106 | CD62: ='Raw financials'!BR106 | CE62: ='Raw financials'!BS106 | CF62: ='Raw financials'!BT106 | CG62: ='Raw financials'!BU106 | ... DW62: ='Raw financials'!DK106 | DZ62: ='Raw financials'!DN106 | EA62: ='Raw financials'!DO106 | EB62: ='Raw financials'!DP106 | EC62: ='Raw financials'!DQ106 | ED62: ='Raw financials'!DR106 | EE62: ='Raw financials'!DS106 | EF62: ='Raw financials'!DT106 | EG62: ='Raw financials'!DU106 | ... EY62: ='Raw financials'!EM106 | FB62: =+FA62-EW62 | FC62: =+FB62/EW62
A63: Deferred tax asset | B63: ='Raw financials'!B108 | C63: ='Raw financials'!C108 | D63: ='Raw financials'!D108 | E63: ='Raw financials'!E108 | F63: ='Raw financials'!F108 | G63: ='Raw financials'!G108 | H63: ='Raw financials'!H108 | I63: ='Raw financials'!I108 | ... T63: ='Raw financials'!T108 | U63: =T63 | V63: =U63 | W63: =V63 | X63: =W63 | Y63: =X63 | Z63: =Y63 | AA63: =+U63-T63 | AB63: =+AA63/T63 | AC63: 3320.5671 | AD63: =+X63-W63 | AE63: =+AD63/W63 | AG63: ='Raw financials'!AA108 | AH63: =+B63 | AI63: ='Raw financials'!AB108 | AJ63: =+C63 | AK63: ='Raw financials'!AC108 | AL63: =+D63 | AM63: ='Raw financials'!AD108 | AN63: =+E63 | AO63: ='Raw financials'!AE108 | AP63: =+F63 | AQ63: ='Raw financials'!AF108 | AR63: =+G63 | AS63: ='Raw financials'!AG108 | AT63: =+H63 | AU63: ='Raw financials'!AH108 | AV63: =+I63 | AW63: ='Raw financials'!AI108 | AX63: =+J63 | AY63: ='Raw financials'!AJ108 | AZ63: =+K63 | BA63: ='Raw financials'!AK108 | BB63: =+L63 | BC63: ='Raw financials'!AL108 | BD63: =+M63 | BE63: ='Raw financials'!AM108 | BF63: =+N63 | BG63: ='Raw financials'!AN108 | BH63: =+O63 | BI63: ='Raw financials'!AO108 | BJ63: =+P63 | BK63: ='Raw financials'!AP108 | BL63: =+Q63 | BM63: ='Raw financials'!AQ108 | BN63: =+R63 | BO63: ='Raw financials'!AR108 | BP63: =+S63 | BQ63: ='Raw financials'!AS108 | BR63: =+T63 | BT63: =+U63 | BU63: =BT63-BR63 | BV63: =BU63/BR63 | BZ63: ='Raw financials'!BN108 | CA63: ='Raw financials'!BO108 | CB63: ='Raw financials'!BP108 | CC63: ='Raw financials'!BQ108 | CD63: ='Raw financials'!BR108 | CE63: ='Raw financials'!BS108 | CF63: ='Raw financials'!BT108 | CG63: ='Raw financials'!BU108 | ... DW63: ='Raw financials'!DK108 | DZ63: ='Raw financials'!DN108 | EA63: ='Raw financials'!DO108 | EB63: ='Raw financials'!DP108 | EC63: ='Raw financials'!DQ108 | ED63: ='Raw financials'!DR108 | EE63: ='Raw financials'!DS108 | EF63: ='Raw financials'!DT108 | EG63: ='Raw financials'!DU108 | ... EY63: ='Raw financials'!EM108 | FB63: =+FA63-EW63 | FC63: =+FB63/EW63
A64: Other non-current assets | B64: =SUM('Raw financials'!B103,'Raw financials'!B104,'Raw financials'!B107,'Raw financials'!B109) | C64: =SUM('Raw financials'!C103,'Raw financials'!C104,'Raw financials'!C107,'Raw financials'!C109) | D64: =SUM('Raw financials'!D103,'Raw financials'!D104,'Raw financials'!D107,'Raw financials'!D109) | E64: =SUM('Raw financials'!E103,'Raw financials'!E104,'Raw financials'!E107,'Raw financials'!E109) | F64: =SUM('Raw financials'!F103,'Raw financials'!F104,'Raw financials'!F107,'Raw financials'!F109) | G64: =SUM('Raw financials'!G103,'Raw financials'!G104,'Raw financials'!G107,'Raw financials'!G109) | H64: =SUM('Raw financials'!H103,'Raw financials'!H104,'Raw financials'!H107,'Raw financials'!H109) | I64: =SUM('Raw financials'!I103,'Raw financials'!I104,'Raw financials'!I107,'Raw financials'!I109) | ... T64: =SUM('Raw financials'!T103,'Raw financials'!T104,'Raw financials'!T107,'Raw financials'!T109) | U64: =T64 | V64: =U64 | W64: =V64 | X64: =W64 | Y64: =X64 | Z64: =Y64 | AA64: =+U64-T64 | AB64: =+AA64/T64 | AC64: 7601.3349 | AD64: =+X64-W64 | AE64: =+AD64/W64 | AG64: =SUM('Raw financials'!AA103,'Raw financials'!AA104,'Raw financials'!AA107,'Raw financials'!AA109) | AH64: =+B64 | AI64: =SUM('Raw financials'!AB103,'Raw financials'!AB104,'Raw financials'!AB107,'Raw financials'!AB109) | AJ64: =+C64 | AK64: =SUM('Raw financials'!AC103,'Raw financials'!AC104,'Raw financials'!AC107,'Raw financials'!AC109) | AL64: =+D64 | AM64: =SUM('Raw financials'!AD103,'Raw financials'!AD104,'Raw financials'!AD107,'Raw financials'!AD109) | AN64: =+E64 | AO64: =SUM('Raw financials'!AE103,'Raw financials'!AE104,'Raw financials'!AE107,'Raw financials'!AE109) | AP64: =+F64 | AQ64: =SUM('Raw financials'!AF103,'Raw financials'!AF104,'Raw financials'!AF107,'Raw financials'!AF109) | AR64: =+G64 | AS64: =SUM('Raw financials'!AG103,'Raw financials'!AG104,'Raw financials'!AG107,'Raw financials'!AG109) | AT64: =+H64 | AU64: =SUM('Raw financials'!AH103,'Raw financials'!AH104,'Raw financials'!AH107,'Raw financials'!AH109) | AV64: =+I64 | AW64: =SUM('Raw financials'!AI103,'Raw financials'!AI104,'Raw financials'!AI107,'Raw financials'!AI109) | AX64: =+J64 | AY64: =SUM('Raw financials'!AJ103,'Raw financials'!AJ104,'Raw financials'!AJ107,'Raw financials'!AJ109) | AZ64: =+K64 | BA64: =SUM('Raw financials'!AK103,'Raw financials'!AK104,'Raw financials'!AK107,'Raw financials'!AK109) | BB64: =+L64 | BC64: =SUM('Raw financials'!AL103,'Raw financials'!AL104,'Raw financials'!AL107,'Raw financials'!AL109) | BD64: =+M64 | BE64: =SUM('Raw financials'!AM103,'Raw financials'!AM104,'Raw financials'!AM107,'Raw financials'!AM109) | BF64: =+N64 | BG64: =SUM('Raw financials'!AN103,'Raw financials'!AN104,'Raw financials'!AN107,'Raw financials'!AN109) | BH64: =+O64 | BI64: =SUM('Raw financials'!AO103,'Raw financials'!AO104,'Raw financials'!AO107,'Raw financials'!AO109) | BJ64: =+P64 | BK64: =SUM('Raw financials'!AP103,'Raw financials'!AP104,'Raw financials'!AP107,'Raw financials'!AP109) | BL64: =+Q64 | BM64: =SUM('Raw financials'!AQ103,'Raw financials'!AQ104,'Raw financials'!AQ107,'Raw financials'!AQ109) | BN64: =+R64 | BO64: =SUM('Raw financials'!AR103,'Raw financials'!AR104,'Raw financials'!AR107,'Raw financials'!AR109) | BP64: =+S64 | BQ64: =SUM('Raw financials'!AS103,'Raw financials'!AS104,'Raw financials'!AS107,'Raw financials'!AS109) | BR64: =+T64 | BT64: =+U64 | BU64: =BT64-BR64 | BV64: =BU64/BR64 | BZ64: =SUM('Raw financials'!BN103,'Raw financials'!BN104,'Raw financials'!BN107,'Raw financials'!BN109) | CA64: =SUM('Raw financials'!BO103,'Raw financials'!BO104,'Raw financials'!BO107,'Raw financials'!BO109) | CB64: =SUM('Raw financials'!BP103,'Raw financials'!BP104,'Raw financials'!BP107,'Raw financials'!BP109) | CC64: =SUM('Raw financials'!BQ103,'Raw financials'!BQ104,'Raw financials'!BQ107,'Raw financials'!BQ109) | CD64: =SUM('Raw financials'!BR103,'Raw financials'!BR104,'Raw financials'!BR107,'Raw financials'!BR109) | CE64: =SUM('Raw financials'!BS103,'Raw financials'!BS104,'Raw financials'!BS107,'Raw financials'!BS109) | CF64: =SUM('Raw financials'!BT103,'Raw financials'!BT104,'Raw financials'!BT107,'Raw financials'!BT109) | CG64: =SUM('Raw financials'!BU103,'Raw financials'!BU104,'Raw financials'!BU107,'Raw financials'!BU109) | ... DW64: =SUM('Raw financials'!DK103,'Raw financials'!DK104,'Raw financials'!DK107,'Raw financials'!DK109) | DZ64: =SUM('Raw financials'!DN103,'Raw financials'!DN104,'Raw financials'!DN107,'Raw financials'!DN109) | EA64: =SUM('Raw financials'!DO103,'Raw financials'!DO104,'Raw financials'!DO107,'Raw financials'!DO109) | EB64: =SUM('Raw financials'!DP103,'Raw financials'!DP104,'Raw financials'!DP107,'Raw financials'!DP109) | EC64: =SUM('Raw financials'!DQ103,'Raw financials'!DQ104,'Raw financials'!DQ107,'Raw financials'!DQ109) | ED64: =SUM('Raw financials'!DR103,'Raw financials'!DR104,'Raw financials'!DR107,'Raw financials'!DR109) | EE64: =SUM('Raw financials'!DS103,'Raw financials'!DS104,'Raw financials'!DS107,'Raw financials'!DS109) | EF64: =SUM('Raw financials'!DT103,'Raw financials'!DT104,'Raw financials'!DT107,'Raw financials'!DT109) | EG64: =SUM('Raw financials'!DU103,'Raw financials'!DU104,'Raw financials'!DU107,'Raw financials'!DU109) | ... EY64: =SUM('Raw financials'!EM103,'Raw financials'!EM104,'Raw financials'!EM107,'Raw financials'!EM109) | FB64: =+FA64-EW64 | FC64: =+FB64/EW64
A65: Total non-current assets | B65: =SUM(B56:B64) | C65: =SUM(C56:C64) | D65: =SUM(D56:D64) | E65: =SUM(E56:E64) | F65: =SUM(F56:F64) | G65: =SUM(G56:G64) | H65: =SUM(H56:H64) | I65: =SUM(I56:I64) | ... Z65: =SUM(Z56:Z64) | AA65: =+U65-T65 | AB65: =+AA65/T65 | AC65: 50317.261 | AD65: =+X65-W65 | AE65: =+AD65/W65 | AG65: =SUM(AG56:AG64) | AH65: =SUM(AH56:AH64) | AI65: =SUM(AI56:AI64) | AJ65: =SUM(AJ56:AJ64) | AK65: =SUM(AK56:AK64) | AL65: =SUM(AL56:AL64) | AM65: =SUM(AM56:AM64) | AN65: =SUM(AN56:AN64) | ... BR65: =SUM(BR56:BR64) | BT65: =SUM(BT56:BT64) | BU65: =BT65-BR65 | BV65: =BU65/BR65 | BZ65: =SUM(BZ56:BZ64) | CA65: =SUM(CA56:CA64) | CB65: =SUM(CB56:CB64) | CC65: =SUM(CC56:CC64) | CD65: =SUM(CD56:CD64) | CE65: =SUM(CE56:CE64) | CF65: =SUM(CF56:CF64) | CG65: =SUM(CG56:CG64) | ... DW65: =SUM(DW56:DW64) | DZ65: =SUM(DZ56:DZ64) | EA65: =SUM(EA56:EA64) | EB65: =SUM(EB56:EB64) | EC65: =SUM(EC56:EC64) | ED65: =SUM(ED56:ED64) | EE65: =SUM(EE56:EE64) | EF65: =SUM(EF56:EF64) | EG65: =SUM(EG56:EG64) | ... EY65: =SUM(EY56:EY64) | FB65: =+FA65-EW65 | FC65: =+FB65/EW65
A67: Total Assets | B67: =B54+B65 | C67: =C54+C65 | D67: =D54+D65 | E67: =E54+E65 | F67: =F54+F65 | G67: =G54+G65 | H67: =H54+H65 | I67: =I54+I65 | ... Z67: =Z54+Z65 | AA67: =+U67-T67 | AB67: =+AA67/T67 | AC67: 157100.15 | AD67: =+X67-W67 | AE67: =+AD67/W67 | AG67: =AG54+AG65 | AH67: =AH54+AH65 | AI67: =AI54+AI65 | AJ67: =AJ54+AJ65 | AK67: =AK54+AK65 | AL67: =AL54+AL65 | AM67: =AM54+AM65 | AN67: =AN54+AN65 | ... BR67: =BR54+BR65 | BT67: =BT54+BT65 | BU67: =BT67-BR67 | BV67: =BU67/BR67 | BZ67: =BZ54+BZ65 | CA67: =CA54+CA65 | CB67: =CB54+CB65 | CC67: =CC54+CC65 | CD67: =CD54+CD65 | CE67: =CE54+CE65 | CF67: =CF54+CF65 | CG67: =CG54+CG65 | ... DW67: =DW54+DW65 | DZ67: =DZ54+DZ65 | EA67: =EA54+EA65 | EB67: =EB54+EB65 | EC67: =EC54+EC65 | ED67: =ED54+ED65 | EE67: =EE54+EE65 | EF67: =EF54+EF65 | EG67: =EG54+EG65 | ... EY67: =EY54+EY65 | FB67: =+FA67-EW67 | FC67: =+FB67/EW67
A69: Short term borrowing | B69: ='Raw financials'!B117 | C69: ='Raw financials'!C117 | D69: ='Raw financials'!D117 | E69: ='Raw financials'!E117 | F69: ='Raw financials'!F117 | G69: ='Raw financials'!G117 | H69: ='Raw financials'!H117 | I69: ='Raw financials'!I117 | ... T69: ='Raw financials'!T117 | U69: =T69 | V69: =U69 | W69: =V69 | X69: =W69 | Y69: =X69 | Z69: =Y69 | AA69: =+U69-T69 | AB69: =+AA69/T69 | AC69: 75.08 | AD69: =+X69-W69 | AE69: =+AD69/W69 | AG69: ='Raw financials'!AA117 | AH69: =+B69 | AI69: ='Raw financials'!AB117 | AJ69: =+C69 | AK69: ='Raw financials'!AC117 | AL69: =+D69 | AM69: ='Raw financials'!AD117 | AN69: =+E69 | AO69: ='Raw financials'!AE117 | AP69: =+F69 | AQ69: ='Raw financials'!AF117 | AR69: =+G69 | AS69: ='Raw financials'!AG117 | AT69: =+H69 | AU69: ='Raw financials'!AH117 | AV69: =+I69 | AW69: ='Raw financials'!AI117 | AX69: =+J69 | AY69: ='Raw financials'!AJ117 | AZ69: =+K69 | BA69: ='Raw financials'!AK117 | BB69: =+L69 | BC69: ='Raw financials'!AL117 | BD69: =+M69 | BE69: ='Raw financials'!AM117 | BF69: =+N69 | BG69: ='Raw financials'!AN117 | BH69: =+O69 | BI69: ='Raw financials'!AO117 | BJ69: =+P69 | BK69: ='Raw financials'!AP117 | BL69: =+Q69 | BM69: ='Raw financials'!AQ117 | BN69: =+R69 | BO69: ='Raw financials'!AR117 | BP69: =+S69 | BQ69: ='Raw financials'!AS117 | BR69: =+T69 | BT69: =+U69 | BU69: =BT69-BR69 | BV69: =BU69/BR69 | BZ69: ='Raw financials'!BN117 | CA69: ='Raw financials'!BO117 | CB69: ='Raw financials'!BP117 | CC69: ='Raw financials'!BQ117 | CD69: ='Raw financials'!BR117 | CE69: ='Raw financials'!BS117 | CF69: ='Raw financials'!BT117 | CG69: ='Raw financials'!BU117 | ... DW69: ='Raw financials'!DK117 | DZ69: ='Raw financials'!DN117 | EA69: ='Raw financials'!DO117 | EB69: ='Raw financials'!DP117 | EC69: ='Raw financials'!DQ117 | ED69: ='Raw financials'!DR117 | EE69: ='Raw financials'!DS117 | EF69: ='Raw financials'!DT117 | EG69: ='Raw financials'!DU117 | ... EY69: ='Raw financials'!EM117 | FB69: =+FA69-EW69 | FC69: =+FB69/EW69
A70: Accounts payable | B70: ='Raw financials'!B122 | C70: ='Raw financials'!C122 | D70: ='Raw financials'!D122 | E70: ='Raw financials'!E122 | F70: ='Raw financials'!F122 | G70: ='Raw financials'!G122 | H70: ='Raw financials'!H122 | I70: ='Raw financials'!I122 | ... T70: ='Raw financials'!T122 | U70: =Driver!J148 | V70: =Driver!K148 | W70: =Driver!L148 | X70: =Driver!M148 | Y70: =Driver!N148 | Z70: =Driver!O148 | AA70: =+U70-T70 | AB70: =+AA70/T70 | AC70: 28751.212 | AD70: =+X70-W70 | AE70: =+AD70/W70 | AG70: ='Raw financials'!AA122 | AH70: =+B70 | AI70: ='Raw financials'!AB122 | AJ70: =+C70 | AK70: ='Raw financials'!AC122 | AL70: =+D70 | AM70: ='Raw financials'!AD122 | AN70: =+E70 | AO70: ='Raw financials'!AE122 | AP70: =+F70 | AQ70: ='Raw financials'!AF122 | AR70: =+G70 | AS70: ='Raw financials'!AG122 | AT70: =+H70 | AU70: ='Raw financials'!AH122 | AV70: =+I70 | AW70: ='Raw financials'!AI122 | AX70: =+J70 | AY70: ='Raw financials'!AJ122 | AZ70: =+K70 | BA70: ='Raw financials'!AK122 | BB70: =+L70 | BC70: ='Raw financials'!AL122 | BD70: =+M70 | BE70: ='Raw financials'!AM122 | BF70: =+N70 | BG70: ='Raw financials'!AN122 | BH70: =+O70 | BI70: ='Raw financials'!AO122 | BJ70: =+P70 | BK70: ='Raw financials'!AP122 | BL70: =+Q70 | BM70: ='Raw financials'!AQ122 | BN70: =+R70 | BO70: ='Raw financials'!AR122 | BP70: =+S70 | BQ70: ='Raw financials'!AS122 | BR70: =+T70 | BT70: =+U70 | BU70: =BT70-BR70 | BV70: =BU70/BR70 | BZ70: ='Raw financials'!BN122 | CA70: ='Raw financials'!BO122 | CB70: ='Raw financials'!BP122 | CC70: ='Raw financials'!BQ122 | CD70: ='Raw financials'!BR122 | CE70: ='Raw financials'!BS122 | CF70: ='Raw financials'!BT122 | CG70: ='Raw financials'!BU122 | ... DW70: ='Raw financials'!DK122 | DZ70: ='Raw financials'!DN120 | EA70: ='Raw financials'!DO122 | EB70: ='Raw financials'!DP122 | EC70: ='Raw financials'!DQ122 | ED70: ='Raw financials'!DR122 | EE70: ='Raw financials'!DS122 | EF70: ='Raw financials'!DT122 | EG70: ='Raw financials'!DU122 | EH70: ='Raw financials'!DV122 | ... EY70: ='Raw financials'!EM122 | FB70: =+FA70-EW70 | FC70: =+FB70/EW70
A71: Advance payment / contract liabilities | B71: =SUM('Raw financials'!B123,'Raw financials'!B124) | C71: =SUM('Raw financials'!C123,'Raw financials'!C124) | D71: =SUM('Raw financials'!D123,'Raw financials'!D124) | E71: =SUM('Raw financials'!E123,'Raw financials'!E124) | F71: =SUM('Raw financials'!F123,'Raw financials'!F124) | G71: =SUM('Raw financials'!G123,'Raw financials'!G124) | H71: =SUM('Raw financials'!H123,'Raw financials'!H124) | I71: =SUM('Raw financials'!I123,'Raw financials'!I124) | ... T71: =SUM('Raw financials'!T123,'Raw financials'!T124) | U71: =T71 | V71: =U71 | W71: =V71 | X71: =W71 | Y71: =X71 | Z71: =Y71 | AA71: =+U71-T71 | AB71: =+AA71/T71 | AC71: 40665.997 | AD71: =+X71-W71 | AE71: =+AD71/W71 | AG71: =SUM('Raw financials'!AA123,'Raw financials'!AA124) | AH71: =+B71 | AI71: =SUM('Raw financials'!AB123,'Raw financials'!AB124) | AJ71: =+C71 | AK71: =SUM('Raw financials'!AC123,'Raw financials'!AC124) | AL71: =+D71 | AM71: =SUM('Raw financials'!AD123,'Raw financials'!AD124) | AN71: =+E71 | AO71: =SUM('Raw financials'!AE123,'Raw financials'!AE124) | AP71: =+F71 | AQ71: =SUM('Raw financials'!AF123,'Raw financials'!AF124) | AR71: =+G71 | AS71: =SUM('Raw financials'!AG123,'Raw financials'!AG124) | AT71: =+H71 | AU71: =SUM('Raw financials'!AH123,'Raw financials'!AH124) | AV71: =+I71 | AW71: =SUM('Raw financials'!AI123,'Raw financials'!AI124) | AX71: =+J71 | AY71: =SUM('Raw financials'!AJ123,'Raw financials'!AJ124) | AZ71: =+K71 | BA71: =SUM('Raw financials'!AK123,'Raw financials'!AK124) | BB71: =+L71 | BC71: =SUM('Raw financials'!AL123,'Raw financials'!AL124) | BD71: =+M71 | BE71: =SUM('Raw financials'!AM123,'Raw financials'!AM124) | BF71: =+N71 | BG71: =SUM('Raw financials'!AN123,'Raw financials'!AN124) | BH71: =+O71 | BI71: =SUM('Raw financials'!AO123,'Raw financials'!AO124) | BJ71: =+P71 | BK71: =SUM('Raw financials'!AP123,'Raw financials'!AP124) | BL71: =+Q71 | BM71: =SUM('Raw financials'!AQ123,'Raw financials'!AQ124) | BN71: =+R71 | BO71: =SUM('Raw financials'!AR123,'Raw financials'!AR124) | BP71: =+S71 | BQ71: =SUM('Raw financials'!AS123,'Raw financials'!AS124) | BR71: =+T71 | BT71: =+U71 | BU71: =BT71-BR71 | BV71: =BU71/BR71 | BZ71: =SUM('Raw financials'!BN123,'Raw financials'!BN124) | CA71: =SUM('Raw financials'!BO123,'Raw financials'!BO124) | CB71: =SUM('Raw financials'!BP123,'Raw financials'!BP124) | CC71: =SUM('Raw financials'!BQ123,'Raw financials'!BQ124) | CD71: =SUM('Raw financials'!BR123,'Raw financials'!BR124) | CE71: =SUM('Raw financials'!BS123,'Raw financials'!BS124) | CF71: =SUM('Raw financials'!BT123,'Raw financials'!BT124) | CG71: =SUM('Raw financials'!BU123,'Raw financials'!BU124) | ... DW71: =SUM('Raw financials'!DK123,'Raw financials'!DK124) | DZ71: =SUM('Raw financials'!DN123,'Raw financials'!DN124) | EA71: =SUM('Raw financials'!DO123,'Raw financials'!DO124) | EB71: =SUM('Raw financials'!DP123,'Raw financials'!DP124) | EC71: =SUM('Raw financials'!DQ123,'Raw financials'!DQ124) | ED71: =SUM('Raw financials'!DR123,'Raw financials'!DR124) | EE71: =SUM('Raw financials'!DS123,'Raw financials'!DS124) | EF71: =SUM('Raw financials'!DT123,'Raw financials'!DT124) | EG71: =SUM('Raw financials'!DU123,'Raw financials'!DU124) | ... EY71: =SUM('Raw financials'!EM123,'Raw financials'!EM124) | FB71: =+FA71-EW71 | FC71: =+FB71/EW71
A72: Other payables | B72: =SUM('Raw financials'!B121,'Raw financials'!B126,'Raw financials'!B127,'Raw financials'!B128) | C72: =SUM('Raw financials'!C121,'Raw financials'!C126,'Raw financials'!C127,'Raw financials'!C128) | D72: =SUM('Raw financials'!D121,'Raw financials'!D126,'Raw financials'!D127,'Raw financials'!D128) | E72: =SUM('Raw financials'!E121,'Raw financials'!E126,'Raw financials'!E127,'Raw financials'!E128) | F72: =SUM('Raw financials'!F121,'Raw financials'!F126,'Raw financials'!F127,'Raw financials'!F128) | G72: =SUM('Raw financials'!G121,'Raw financials'!G126,'Raw financials'!G127,'Raw financials'!G128) | H72: =SUM('Raw financials'!H121,'Raw financials'!H126,'Raw financials'!H127,'Raw financials'!H128) | I72: =SUM('Raw financials'!I121,'Raw financials'!I126,'Raw financials'!I127,'Raw financials'!I128) | ... T72: =SUM('Raw financials'!T121,'Raw financials'!T126,'Raw financials'!T127,'Raw financials'!T128) | U72: =Driver!J150 | V72: =Driver!K150 | W72: =Driver!L150 | X72: =Driver!M150 | Y72: =Driver!N150 | Z72: =Driver!O150 | AA72: =+U72-T72 | AB72: =+AA72/T72 | AC72: 21988.496 | AD72: =+X72-W72 | AE72: =+AD72/W72 | AG72: =SUM('Raw financials'!AA121,'Raw financials'!AA126,'Raw financials'!AA127,'Raw financials'!AA129,'Raw financials'!AA130,'Raw financials'!AA131) | AH72: =+B72 | AI72: =SUM('Raw financials'!AB121,'Raw financials'!AB126,'Raw financials'!AB127,'Raw financials'!AB129,'Raw financials'!AB130,'Raw financials'!AB131) | AJ72: =+C72 | AK72: =SUM('Raw financials'!AC121,'Raw financials'!AC126,'Raw financials'!AC127,'Raw financials'!AC129,'Raw financials'!AC130,'Raw financials'!AC131) | AL72: =+D72 | AM72: =SUM('Raw financials'!AD121,'Raw financials'!AD126,'Raw financials'!AD127,'Raw financials'!AD129,'Raw financials'!AD130,'Raw financials'!AD131) | AN72: =+E72 | AO72: =SUM('Raw financials'!AE121,'Raw financials'!AE126,'Raw financials'!AE127,'Raw financials'!AE129,'Raw financials'!AE130,'Raw financials'!AE131) | AP72: =+F72 | AQ72: =SUM('Raw financials'!AF121,'Raw financials'!AF126,'Raw financials'!AF127,'Raw financials'!AF129,'Raw financials'!AF130,'Raw financials'!AF131) | AR72: =+G72 | AS72: =SUM('Raw financials'!AG121,'Raw financials'!AG126,'Raw financials'!AG127,'Raw financials'!AG129,'Raw financials'!AG130,'Raw financials'!AG131) | AT72: =+H72 | AU72: =SUM('Raw financials'!AH121,'Raw financials'!AH126,'Raw financials'!AH127,'Raw financials'!AH129,'Raw financials'!AH130,'Raw financials'!AH131) | AV72: =+I72 | AW72: =SUM('Raw financials'!AI121,'Raw financials'!AI126,'Raw financials'!AI127,'Raw financials'!AI129,'Raw financials'!AI130,'Raw financials'!AI131) | AX72: =+J72 | AY72: =SUM('Raw financials'!AJ121,'Raw financials'!AJ126,'Raw financials'!AJ127,'Raw financials'!AJ129,'Raw financials'!AJ130,'Raw financials'!AJ131) | AZ72: =+K72 | BA72: =SUM('Raw financials'!AK121,'Raw financials'!AK126,'Raw financials'!AK127,'Raw financials'!AK129,'Raw financials'!AK130,'Raw financials'!AK131) | BB72: =+L72 | BC72: =SUM('Raw financials'!AL121,'Raw financials'!AL126,'Raw financials'!AL127,'Raw financials'!AL129,'Raw financials'!AL130,'Raw financials'!AL131) | BD72: =+M72 | BE72: =SUM('Raw financials'!AM121,'Raw financials'!AM126,'Raw financials'!AM127,'Raw financials'!AM129,'Raw financials'!AM130,'Raw financials'!AM131) | BF72: =+N72 | BG72: =SUM('Raw financials'!AN121,'Raw financials'!AN126,'Raw financials'!AN127,'Raw financials'!AN129,'Raw financials'!AN130,'Raw financials'!AN131) | BH72: =+O72 | BI72: =SUM('Raw financials'!AO121,'Raw financials'!AO126,'Raw financials'!AO127,'Raw financials'!AO129,'Raw financials'!AO130,'Raw financials'!AO131) | BJ72: =+P72 | BK72: =SUM('Raw financials'!AP121,'Raw financials'!AP126,'Raw financials'!AP127,'Raw financials'!AP129,'Raw financials'!AP130,'Raw financials'!AP131) | BL72: =+Q72 | BM72: =SUM('Raw financials'!AQ121,'Raw financials'!AQ126,'Raw financials'!AQ127,'Raw financials'!AQ129,'Raw financials'!AQ130,'Raw financials'!AQ131) | BN72: =+R72 | BO72: =SUM('Raw financials'!AR121,'Raw financials'!AR126,'Raw financials'!AR127,'Raw financials'!AR129,'Raw financials'!AR130,'Raw financials'!AR131) | BP72: =+S72 | BQ72: =SUM('Raw financials'!AS121,'Raw financials'!AS126,'Raw financials'!AS127,'Raw financials'!AS129,'Raw financials'!AS130,'Raw financials'!AS131) | BR72: =+T72 | BT72: =+U72 | BU72: =BT72-BR72 | BV72: =BU72/BR72 | BZ72: =SUM('Raw financials'!BN121,'Raw financials'!BN126,'Raw financials'!BN127,'Raw financials'!BN129,'Raw financials'!BN130,'Raw financials'!BN131) | CA72: =SUM('Raw financials'!BO121,'Raw financials'!BO126,'Raw financials'!BO127,'Raw financials'!BO129,'Raw financials'!BO130,'Raw financials'!BO131) | CB72: =SUM('Raw financials'!BP121,'Raw financials'!BP126,'Raw financials'!BP127,'Raw financials'!BP129,'Raw financials'!BP130,'Raw financials'!BP131) | CC72: =SUM('Raw financials'!BQ121,'Raw financials'!BQ126,'Raw financials'!BQ127,'Raw financials'!BQ129,'Raw financials'!BQ130,'Raw financials'!BQ131) | CD72: =SUM('Raw financials'!BR121,'Raw financials'!BR126,'Raw financials'!BR127,'Raw financials'!BR129,'Raw financials'!BR130,'Raw financials'!BR131) | CE72: =SUM('Raw financials'!BS121,'Raw financials'!BS126,'Raw financials'!BS127,'Raw financials'!BS129,'Raw financials'!BS130,'Raw financials'!BS131) | CF72: =SUM('Raw financials'!BT121,'Raw financials'!BT126,'Raw financials'!BT127,'Raw financials'!BT129,'Raw financials'!BT130,'Raw financials'!BT131) | CG72: =SUM('Raw financials'!BU121,'Raw financials'!BU126,'Raw financials'!BU127,'Raw financials'!BU129,'Raw financials'!BU130,'Raw financials'!BU131) | ... DW72: =SUM('Raw financials'!DK121,'Raw financials'!DK126,'Raw financials'!DK127,'Raw financials'!DK129,'Raw financials'!DK130,'Raw financials'!DK131) | DZ72: =SUM('Raw financials'!DN121,'Raw financials'!DN126,'Raw financials'!DN127,'Raw financials'!DN129,'Raw financials'!DN130,'Raw financials'!DN131) | EA72: =SUM('Raw financials'!DO121,'Raw financials'!DO126,'Raw financials'!DO127,'Raw financials'!DO128) | EB72: =SUM('Raw financials'!DP121,'Raw financials'!DP126,'Raw financials'!DP127,'Raw financials'!DP128) | EC72: =SUM('Raw financials'!DQ121,'Raw financials'!DQ126,'Raw financials'!DQ127,'Raw financials'!DQ128) | ED72: =SUM('Raw financials'!DR121,'Raw financials'!DR126,'Raw financials'!DR127,'Raw financials'!DR128) | EE72: =SUM('Raw financials'!DS121,'Raw financials'!DS126,'Raw financials'!DS127,'Raw financials'!DS128) | EF72: =SUM('Raw financials'!DT121,'Raw financials'!DT126,'Raw financials'!DT127,'Raw financials'!DT128) | EG72: =SUM('Raw financials'!DU121,'Raw financials'!DU126,'Raw financials'!DU127,'Raw financials'!DU128) | EH72: =SUM('Raw financials'!DV121,'Raw financials'!DV126,'Raw financials'!DV127,'Raw financials'!DV128) | ... EY72: =SUM('Raw financials'!EM121,'Raw financials'!EM126,'Raw financials'!EM127,'Raw financials'!EM128) | FB72: =+FA72-EW72 | FC72: =+FB72/EW72
A73: LT borrowing mature in 1 year | B73: ='Raw financials'!B133 | C73: ='Raw financials'!C133 | D73: ='Raw financials'!D133 | E73: ='Raw financials'!E133 | F73: ='Raw financials'!F133 | G73: ='Raw financials'!G133 | H73: ='Raw financials'!H133 | I73: ='Raw financials'!I133 | ... T73: ='Raw financials'!T133 | U73: =T73 | V73: =U73 | W73: =V73 | X73: =W73 | Y73: =X73 | Z73: =Y73 | AA73: =+U73-T73 | AB73: =+AA73/T73 | AC73: 331.4051 | AD73: =+X73-W73 | AE73: =+AD73/W73 | AG73: ='Raw financials'!AA133 | AH73: =+B73 | AI73: ='Raw financials'!AB133 | AJ73: =+C73 | AK73: ='Raw financials'!AC133 | AL73: =+D73 | AM73: ='Raw financials'!AD133 | AN73: =+E73 | AO73: ='Raw financials'!AE133 | AP73: =+F73 | AQ73: ='Raw financials'!AF133 | AR73: =+G73 | AS73: ='Raw financials'!AG133 | AT73: =+H73 | AU73: ='Raw financials'!AH133 | AV73: =+I73 | AW73: ='Raw financials'!AI133 | AX73: =+J73 | AY73: ='Raw financials'!AJ133 | AZ73: =+K73 | BA73: ='Raw financials'!AK133 | BB73: =+L73 | BC73: ='Raw financials'!AL133 | BD73: =+M73 | BE73: ='Raw financials'!AM133 | BF73: =+N73 | BG73: ='Raw financials'!AN133 | BH73: =+O73 | BI73: ='Raw financials'!AO133 | BJ73: =+P73 | BK73: ='Raw financials'!AP133 | BL73: =+Q73 | BM73: ='Raw financials'!AQ133 | BN73: =+R73 | BO73: ='Raw financials'!AR133 | BP73: =+S73 | BQ73: ='Raw financials'!AS133 | BR73: =+T73 | BT73: =+U73 | BU73: =BT73-BR73 | BV73: =BU73/BR73 | BZ73: ='Raw financials'!BN133 | CA73: ='Raw financials'!BO133 | CB73: ='Raw financials'!BP133 | CC73: ='Raw financials'!BQ133 | CD73: ='Raw financials'!BR133 | CE73: ='Raw financials'!BS133 | CF73: ='Raw financials'!BT133 | CG73: ='Raw financials'!BU133 | ... DW73: ='Raw financials'!DK133 | DZ73: ='Raw financials'!DN133 | EA73: ='Raw financials'!DO133 | EB73: ='Raw financials'!DP133 | EC73: ='Raw financials'!DQ133 | ED73: ='Raw financials'!DR133 | EE73: ='Raw financials'!DS133 | EF73: ='Raw financials'!DT133 | EG73: ='Raw financials'!DU133 | ... EY73: ='Raw financials'!EM133 | FB73: =+FA73-EW73 | FC73: =+FB73/EW73
A74: Other current liabilities | B74: =SUM('Raw financials'!B118,'Raw financials'!B119,'Raw financials'!B137,'Raw financials'!B138) | C74: =SUM('Raw financials'!C118,'Raw financials'!C119,'Raw financials'!C137,'Raw financials'!C138) | D74: =SUM('Raw financials'!D118,'Raw financials'!D119,'Raw financials'!D137,'Raw financials'!D138) | E74: =SUM('Raw financials'!E118,'Raw financials'!E119,'Raw financials'!E137,'Raw financials'!E138) | F74: =SUM('Raw financials'!F118,'Raw financials'!F119,'Raw financials'!F137,'Raw financials'!F138) | G74: =SUM('Raw financials'!G118,'Raw financials'!G119,'Raw financials'!G137,'Raw financials'!G138) | H74: =SUM('Raw financials'!H118,'Raw financials'!H119,'Raw financials'!H137,'Raw financials'!H138) | I74: =SUM('Raw financials'!I118,'Raw financials'!I119,'Raw financials'!I137,'Raw financials'!I138) | ... T74: =SUM('Raw financials'!T118,'Raw financials'!T119,'Raw financials'!T137,'Raw financials'!T138) | U74: =T74 | V74: =U74 | W74: =V74 | X74: =W74 | Y74: =X74 | Z74: =Y74 | AA74: =+U74-T74 | AB74: =+AA74/T74 | AC74: 4015.5016 | AD74: =+X74-W74 | AE74: =+AD74/W74 | AG74: =SUM('Raw financials'!AA119,'Raw financials'!AA118,'Raw financials'!AA134,'Raw financials'!AA137,'Raw financials'!AA138) | AH74: =+B74 | AI74: =SUM('Raw financials'!AB119,'Raw financials'!AB118,'Raw financials'!AB134,'Raw financials'!AB137,'Raw financials'!AB138) | AJ74: =+C74 | AK74: =SUM('Raw financials'!AC119,'Raw financials'!AC118,'Raw financials'!AC134,'Raw financials'!AC137,'Raw financials'!AC138) | AL74: =+D74 | AM74: =SUM('Raw financials'!AD119,'Raw financials'!AD118,'Raw financials'!AD134,'Raw financials'!AD137,'Raw financials'!AD138) | AN74: =+E74 | AO74: =SUM('Raw financials'!AE119,'Raw financials'!AE118,'Raw financials'!AE134,'Raw financials'!AE137,'Raw financials'!AE138) | AP74: =+F74 | AQ74: =SUM('Raw financials'!AF119,'Raw financials'!AF118,'Raw financials'!AF134,'Raw financials'!AF137,'Raw financials'!AF138) | AR74: =+G74 | AS74: =SUM('Raw financials'!AG119,'Raw financials'!AG118,'Raw financials'!AG134,'Raw financials'!AG137,'Raw financials'!AG138) | AT74: =+H74 | AU74: =SUM('Raw financials'!AH119,'Raw financials'!AH118,'Raw financials'!AH134,'Raw financials'!AH137,'Raw financials'!AH138) | AV74: =+I74 | AW74: =SUM('Raw financials'!AI119,'Raw financials'!AI118,'Raw financials'!AI134,'Raw financials'!AI137,'Raw financials'!AI138) | AX74: =+J74 | AY74: =SUM('Raw financials'!AJ119,'Raw financials'!AJ118,'Raw financials'!AJ134,'Raw financials'!AJ137,'Raw financials'!AJ138) | AZ74: =+K74 | BA74: =SUM('Raw financials'!AK119,'Raw financials'!AK118,'Raw financials'!AK134,'Raw financials'!AK137,'Raw financials'!AK138) | BB74: =+L74 | BC74: =SUM('Raw financials'!AL119,'Raw financials'!AL118,'Raw financials'!AL134,'Raw financials'!AL137,'Raw financials'!AL138) | BD74: =+M74 | BE74: =SUM('Raw financials'!AM119,'Raw financials'!AM118,'Raw financials'!AM134,'Raw financials'!AM137,'Raw financials'!AM138) | BF74: =+N74 | BG74: =SUM('Raw financials'!AN119,'Raw financials'!AN118,'Raw financials'!AN134,'Raw financials'!AN137,'Raw financials'!AN138) | BH74: =+O74 | BI74: =SUM('Raw financials'!AO119,'Raw financials'!AO118,'Raw financials'!AO134,'Raw financials'!AO137,'Raw financials'!AO138) | BJ74: =+P74 | BK74: =SUM('Raw financials'!AP119,'Raw financials'!AP118,'Raw financials'!AP134,'Raw financials'!AP137,'Raw financials'!AP138) | BL74: =+Q74 | BM74: =SUM('Raw financials'!AQ119,'Raw financials'!AQ118,'Raw financials'!AQ134,'Raw financials'!AQ137,'Raw financials'!AQ138) | BN74: =+R74 | BO74: =SUM('Raw financials'!AR119,'Raw financials'!AR118,'Raw financials'!AR134,'Raw financials'!AR137,'Raw financials'!AR138) | BP74: =+S74 | BQ74: =SUM('Raw financials'!AS119,'Raw financials'!AS118,'Raw financials'!AS134,'Raw financials'!AS137,'Raw financials'!AS138) | BR74: =+T74 | BT74: =+U74 | BU74: =BT74-BR74 | BV74: =BU74/BR74 | BZ74: =SUM('Raw financials'!BN119,'Raw financials'!BN118,'Raw financials'!BN134,'Raw financials'!BN137,'Raw financials'!BN138) | CA74: =SUM('Raw financials'!BO119,'Raw financials'!BO118,'Raw financials'!BO134,'Raw financials'!BO137,'Raw financials'!BO138) | CB74: =SUM('Raw financials'!BP119,'Raw financials'!BP118,'Raw financials'!BP134,'Raw financials'!BP137,'Raw financials'!BP138) | CC74: =SUM('Raw financials'!BQ119,'Raw financials'!BQ118,'Raw financials'!BQ134,'Raw financials'!BQ137,'Raw financials'!BQ138) | CD74: =SUM('Raw financials'!BR119,'Raw financials'!BR118,'Raw financials'!BR134,'Raw financials'!BR137,'Raw financials'!BR138) | CE74: =SUM('Raw financials'!BS119,'Raw financials'!BS118,'Raw financials'!BS134,'Raw financials'!BS137,'Raw financials'!BS138) | CF74: =SUM('Raw financials'!BT119,'Raw financials'!BT118,'Raw financials'!BT134,'Raw financials'!BT137,'Raw financials'!BT138) | CG74: =SUM('Raw financials'!BU119,'Raw financials'!BU118,'Raw financials'!BU134,'Raw financials'!BU137,'Raw financials'!BU138) | ... DW74: =SUM('Raw financials'!DK119,'Raw financials'!DK118,'Raw financials'!DK134,'Raw financials'!DK137,'Raw financials'!DK138) | DZ74: =SUM('Raw financials'!DN119,'Raw financials'!DN118,'Raw financials'!DN134,'Raw financials'!DN137,'Raw financials'!DN138) | EA74: =SUM('Raw financials'!DO119,'Raw financials'!DO118,'Raw financials'!DO134,'Raw financials'!DO137,'Raw financials'!DO138) | EB74: =SUM('Raw financials'!DP119,'Raw financials'!DP118,'Raw financials'!DP134,'Raw financials'!DP137,'Raw financials'!DP138) | EC74: =SUM('Raw financials'!DQ119,'Raw financials'!DQ118,'Raw financials'!DQ134,'Raw financials'!DQ137,'Raw financials'!DQ138) | ED74: =SUM('Raw financials'!DR119,'Raw financials'!DR118,'Raw financials'!DR134,'Raw financials'!DR137,'Raw financials'!DR138) | EE74: =SUM('Raw financials'!DS119,'Raw financials'!DS118,'Raw financials'!DS134,'Raw financials'!DS137,'Raw financials'!DS138) | EF74: =SUM('Raw financials'!DT119,'Raw financials'!DT118,'Raw financials'!DT134,'Raw financials'!DT137,'Raw financials'!DT138) | EG74: =SUM('Raw financials'!DU119,'Raw financials'!DU118,'Raw financials'!DU134,'Raw financials'!DU137,'Raw financials'!DU138) | ... EY74: =SUM('Raw financials'!EM119,'Raw financials'!EM118,'Raw financials'!EM134,'Raw financials'!EM137,'Raw financials'!EM138) | FB74: =+FA74-EW74 | FC74: =+FB74/EW74
A75: Total current liabilities | B75: =SUM(B69:B74) | C75: =SUM(C69:C74) | D75: =SUM(D69:D74) | E75: =SUM(E69:E74) | F75: =SUM(F69:F74) | G75: =SUM(G69:G74) | H75: =SUM(H69:H74) | I75: =SUM(I69:I74) | ... Z75: =SUM(Z69:Z74) | AA75: =+U75-T75 | AB75: =+AA75/T75 | AC75: 95827.691 | AD75: =+X75-W75 | AE75: =+AD75/W75 | AG75: =SUM(AG69:AG74) | AH75: =SUM(AH69:AH74) | AI75: =SUM(AI69:AI74) | AJ75: =SUM(AJ69:AJ74) | AK75: =SUM(AK69:AK74) | AL75: =SUM(AL69:AL74) | AM75: =SUM(AM69:AM74) | AN75: =SUM(AN69:AN74) | ... BR75: =SUM(BR69:BR74) | BT75: =SUM(BT69:BT74) | BU75: =BT75-BR75 | BV75: =BU75/BR75 | BZ75: =SUM(BZ69:BZ74) | CA75: =SUM(CA69:CA74) | CB75: =SUM(CB69:CB74) | CC75: =SUM(CC69:CC74) | CD75: =SUM(CD69:CD74) | CE75: =SUM(CE69:CE74) | CF75: =SUM(CF69:CF74) | CG75: =SUM(CG69:CG74) | ... DW75: =SUM(DW69:DW74) | DZ75: =SUM(DZ69:DZ74) | EA75: =SUM(EA69:EA74) | EB75: =SUM(EB69:EB74) | EC75: =SUM(EC69:EC74) | ED75: =SUM(ED69:ED74) | EE75: =SUM(EE69:EE74) | EF75: =SUM(EF69:EF74) | EG75: =SUM(EG69:EG74) | ... EY75: =SUM(EY69:EY74) | FB75: =+FA75-EW75 | FC75: =+FB75/EW75
A77: Long term borrowing and bonds payable | B77: =SUM('Raw financials'!B143:B144) | C77: =SUM('Raw financials'!C143:C144) | D77: =SUM('Raw financials'!D143:D144) | E77: =SUM('Raw financials'!E143:E144) | F77: =SUM('Raw financials'!F143:F144) | G77: =SUM('Raw financials'!G143:G144) | H77: =SUM('Raw financials'!H143:H144) | I77: =SUM('Raw financials'!I143:I144) | ... T77: =SUM('Raw financials'!T143:T144) | U77: =+T77 | V77: =+U77 | W77: =+V77 | X77: =+W77 | Y77: =+X77 | Z77: =+Y77 | AA77: =+U77-T77 | AB77: =+AA77/T77 | AC77: 2167.1769 | AD77: =+X77-W77 | AE77: =+AD77/W77 | AG77: =SUM('Raw financials'!AA143:AA144) | AH77: =+B77 | AI77: =SUM('Raw financials'!AB143:AB144) | AJ77: =+C77 | AK77: =SUM('Raw financials'!AC143:AC144) | AL77: =+D77 | AM77: =SUM('Raw financials'!AD143:AD144) | AN77: =+E77 | AO77: =SUM('Raw financials'!AE143:AE144) | AP77: =+F77 | AQ77: =SUM('Raw financials'!AF143:AF144) | AR77: =+G77 | AS77: =SUM('Raw financials'!AG143:AG144) | AT77: =+H77 | AU77: =SUM('Raw financials'!AH143:AH144) | AV77: =+I77 | AW77: =SUM('Raw financials'!AI143:AI144) | AX77: =+J77 | AY77: =SUM('Raw financials'!AJ143:AJ144) | AZ77: =+K77 | BA77: =SUM('Raw financials'!AK143:AK144) | BB77: =+L77 | BC77: =SUM('Raw financials'!AL143:AL144) | BD77: =+M77 | BE77: =SUM('Raw financials'!AM143:AM144) | BF77: =+N77 | BG77: =SUM('Raw financials'!AN143:AN144) | BH77: =+O77 | BI77: =SUM('Raw financials'!AO143:AO144) | BJ77: =+P77 | BK77: =SUM('Raw financials'!AP143:AP144) | BL77: =+Q77 | BM77: =SUM('Raw financials'!AQ143:AQ144) | BN77: =+R77 | BO77: =SUM('Raw financials'!AR143:AR144) | BP77: =+S77 | BQ77: =SUM('Raw financials'!AS143:AS144) | BR77: =+T77 | BT77: =+U77 | BU77: =BT77-BR77 | BV77: =BU77/BR77 | BZ77: =SUM('Raw financials'!BN143:BN144) | CA77: =SUM('Raw financials'!BO143:BO144) | CB77: =SUM('Raw financials'!BP143:BP144) | CC77: =SUM('Raw financials'!BQ143:BQ144) | CD77: =SUM('Raw financials'!BR143:BR144) | CE77: =SUM('Raw financials'!BS143:BS144) | CF77: =SUM('Raw financials'!BT143:BT144) | CG77: =SUM('Raw financials'!BU143:BU144) | ... DW77: =SUM('Raw financials'!DK143:DK144) | DZ77: =SUM('Raw financials'!DN143:DN144) | EA77: =SUM('Raw financials'!DO143:DO144) | EB77: =SUM('Raw financials'!DP143:DP144) | EC77: =SUM('Raw financials'!DQ143:DQ144) | ED77: =SUM('Raw financials'!DR143:DR144) | EE77: =SUM('Raw financials'!DS143:DS144) | EF77: =SUM('Raw financials'!DT143:DT144) | EG77: =SUM('Raw financials'!DU143:DU144) | ... EY77: =SUM('Raw financials'!EM143:EM144) | FB77: =+FA77-EW77 | FC77: =+FB77/EW77
A78: Long term payables | B78: ='Raw financials'!B146 | C78: ='Raw financials'!C146 | D78: ='Raw financials'!D146 | E78: ='Raw financials'!E146 | F78: ='Raw financials'!F146 | G78: ='Raw financials'!G146 | H78: ='Raw financials'!H146 | I78: ='Raw financials'!I146 | ... T78: ='Raw financials'!T146 | U78: =T78 | V78: =U78 | W78: =V78 | X78: =W78 | Y78: =X78 | Z78: =Y78 | AA78: =+U78-T78 | AB78: =+AA78/T78 | AC78: 0.24 | AD78: =+X78-W78 | AE78: =+AD78/W78 | AG78: ='Raw financials'!AA147+'Raw financials'!AA148 | AH78: =+B78 | AI78: ='Raw financials'!AB147+'Raw financials'!AB148 | AJ78: =+C78 | AK78: ='Raw financials'!AC147+'Raw financials'!AC148 | AL78: =+D78 | AM78: ='Raw financials'!AD147+'Raw financials'!AD148 | AN78: =+E78 | AO78: ='Raw financials'!AE147+'Raw financials'!AE148 | AP78: =+F78 | AQ78: ='Raw financials'!AF147+'Raw financials'!AF148 | AR78: =+G78 | AS78: ='Raw financials'!AG147+'Raw financials'!AG148 | AT78: =+H78 | AU78: ='Raw financials'!AH147+'Raw financials'!AH148 | AV78: =+I78 | AW78: ='Raw financials'!AI147+'Raw financials'!AI148 | AX78: =+J78 | AY78: ='Raw financials'!AJ147+'Raw financials'!AJ148 | AZ78: =+K78 | BA78: ='Raw financials'!AK147+'Raw financials'!AK148 | BB78: =+L78 | BC78: ='Raw financials'!AL147+'Raw financials'!AL148 | BD78: =+M78 | BE78: ='Raw financials'!AM147+'Raw financials'!AM148 | BF78: =+N78 | BG78: ='Raw financials'!AN147+'Raw financials'!AN148 | BH78: =+O78 | BI78: ='Raw financials'!AO147+'Raw financials'!AO148 | BJ78: =+P78 | BK78: ='Raw financials'!AP147+'Raw financials'!AP148 | BL78: =+Q78 | BM78: ='Raw financials'!AQ147+'Raw financials'!AQ148 | BN78: =+R78 | BO78: ='Raw financials'!AR147+'Raw financials'!AR148 | BP78: =+S78 | BQ78: ='Raw financials'!AS147+'Raw financials'!AS148 | BR78: =+T78 | BT78: =+U78 | BU78: =BT78-BR78 | BV78: =BU78/BR78 | BZ78: ='Raw financials'!BN147+'Raw financials'!BN148 | CA78: ='Raw financials'!BO147+'Raw financials'!BO148 | CB78: ='Raw financials'!BP147+'Raw financials'!BP148 | CC78: ='Raw financials'!BQ147+'Raw financials'!BQ148 | CD78: ='Raw financials'!BR147+'Raw financials'!BR148 | CE78: ='Raw financials'!BS147+'Raw financials'!BS148 | CF78: ='Raw financials'!BT147+'Raw financials'!BT148 | CG78: ='Raw financials'!BU147+'Raw financials'!BU148 | ... DW78: ='Raw financials'!DK147+'Raw financials'!DK148 | DZ78: ='Raw financials'!DN146 | EA78: ='Raw financials'!DO146 | EB78: ='Raw financials'!DP146 | EC78: ='Raw financials'!DQ146 | ED78: ='Raw financials'!DR146 | EE78: ='Raw financials'!DS146 | EF78: ='Raw financials'!DT146 | EG78: ='Raw financials'!DU146 | ... EY78: ='Raw financials'!EM146 | FB78: =+FA78-EW78 | FC78: =+FB78/EW78
A79: Other LT payable | B79: =SUM('Raw financials'!B149) | C79: =SUM('Raw financials'!C149) | D79: =SUM('Raw financials'!D149) | E79: =SUM('Raw financials'!E149) | F79: =SUM('Raw financials'!F149) | G79: =SUM('Raw financials'!G149) | H79: =SUM('Raw financials'!H149) | I79: =SUM('Raw financials'!I149) | ... T79: =SUM('Raw financials'!T149) | U79: =T79 | V79: =U79 | W79: =V79 | X79: =W79 | Y79: =X79 | Z79: =Y79 | AA79: =+U79-T79 | AB79: =+AA79/T79 | AC79: 1003.1062 | AD79: =+X79-W79 | AE79: =+AD79/W79 | AG79: =SUM('Raw financials'!AA149) | AH79: =+B79 | AI79: =SUM('Raw financials'!AB149) | AJ79: =+C79 | AK79: =SUM('Raw financials'!AC149) | AL79: =+D79 | AM79: =SUM('Raw financials'!AD149) | AN79: =+E79 | AO79: =SUM('Raw financials'!AE149) | AP79: =+F79 | AQ79: =SUM('Raw financials'!AF149) | AR79: =+G79 | AS79: =SUM('Raw financials'!AG149) | AT79: =+H79 | AU79: =SUM('Raw financials'!AH149) | AV79: =+I79 | AW79: =SUM('Raw financials'!AI149) | AX79: =+J79 | AY79: =SUM('Raw financials'!AJ149) | AZ79: =+K79 | BA79: =SUM('Raw financials'!AK149) | BB79: =+L79 | BC79: =SUM('Raw financials'!AL149) | BD79: =+M79 | BE79: =SUM('Raw financials'!AM149) | BF79: =+N79 | BG79: =SUM('Raw financials'!AN149) | BH79: =+O79 | BI79: =SUM('Raw financials'!AO149) | BJ79: =+P79 | BK79: =SUM('Raw financials'!AP149) | BL79: =+Q79 | BM79: =SUM('Raw financials'!AQ149) | BN79: =+R79 | BO79: =SUM('Raw financials'!AR149) | BP79: =+S79 | BQ79: =SUM('Raw financials'!AS149) | BR79: =+T79 | BT79: =+U79 | BU79: =BT79-BR79 | BV79: =BU79/BR79 | BZ79: =SUM('Raw financials'!BN149) | CA79: =SUM('Raw financials'!BO149) | CB79: =SUM('Raw financials'!BP149) | CC79: =SUM('Raw financials'!BQ149) | CD79: =SUM('Raw financials'!BR149) | CE79: =SUM('Raw financials'!BS149) | CF79: =SUM('Raw financials'!BT149) | CG79: =SUM('Raw financials'!BU149) | ... DW79: =SUM('Raw financials'!DK149) | DZ79: =SUM('Raw financials'!DN149) | EA79: =SUM('Raw financials'!DO149) | EB79: =SUM('Raw financials'!DP149) | EC79: =SUM('Raw financials'!DQ149) | ED79: =SUM('Raw financials'!DR149) | EE79: =SUM('Raw financials'!DS149) | EF79: =SUM('Raw financials'!DT149) | EG79: =SUM('Raw financials'!DU149) | ... EY79: =SUM('Raw financials'!EM149) | FB79: =+FA79-EW79 | FC79: =+FB79/EW79
A80: Deferred tax liabilities | B80: ='Raw financials'!B151 | C80: ='Raw financials'!C151 | D80: ='Raw financials'!D151 | E80: ='Raw financials'!E151 | F80: ='Raw financials'!F151 | G80: ='Raw financials'!G151 | H80: ='Raw financials'!H151 | I80: ='Raw financials'!I151 | ... T80: ='Raw financials'!T151 | U80: =T80 | V80: =U80 | W80: =V80 | X80: =W80 | Y80: =X80 | Z80: =Y80 | AA80: =+U80-T80 | AB80: =+AA80/T80 | AC80: 229.8504 | AD80: =+X80-W80 | AE80: =+AD80/W80 | AG80: ='Raw financials'!AA151 | AH80: =+B80 | AI80: ='Raw financials'!AB151 | AJ80: =+C80 | AK80: ='Raw financials'!AC151 | AL80: =+D80 | AM80: ='Raw financials'!AD151 | AN80: =+E80 | AO80: ='Raw financials'!AE151 | AP80: =+F80 | AQ80: ='Raw financials'!AF151 | AR80: =+G80 | AS80: ='Raw financials'!AG151 | AT80: =+H80 | AU80: ='Raw financials'!AH151 | AV80: =+I80 | AW80: ='Raw financials'!AI151 | AX80: =+J80 | AY80: ='Raw financials'!AJ151 | AZ80: =+K80 | BA80: ='Raw financials'!AK151 | BB80: =+L80 | BC80: ='Raw financials'!AL151 | BD80: =+M80 | BE80: ='Raw financials'!AM151 | BF80: =+N80 | BG80: ='Raw financials'!AN151 | BH80: =+O80 | BI80: ='Raw financials'!AO151 | BJ80: =+P80 | BK80: ='Raw financials'!AP151 | BL80: =+Q80 | BM80: ='Raw financials'!AQ151 | BN80: =+R80 | BO80: ='Raw financials'!AR151 | BP80: =+S80 | BQ80: ='Raw financials'!AS151 | BR80: =+T80 | BT80: =+U80 | BU80: =BT80-BR80 | BV80: =BU80/BR80 | BZ80: ='Raw financials'!BN151 | CA80: ='Raw financials'!BO151 | CB80: ='Raw financials'!BP151 | CC80: ='Raw financials'!BQ151 | CD80: ='Raw financials'!BR151 | CE80: ='Raw financials'!BS151 | CF80: ='Raw financials'!BT151 | CG80: ='Raw financials'!BU151 | ... DW80: ='Raw financials'!DK151 | DZ80: ='Raw financials'!DN151 | EA80: ='Raw financials'!DO151 | EB80: ='Raw financials'!DP151 | EC80: ='Raw financials'!DQ151 | ED80: ='Raw financials'!DR151 | EE80: ='Raw financials'!DS151 | EF80: ='Raw financials'!DT151 | EG80: ='Raw financials'!DU151 | ... EY80: ='Raw financials'!EM151 | FB80: =+FA80-EW80 | FC80: =+FB80/EW80
A81: Other non-current liabilities | B81: =SUM('Raw financials'!B145,'Raw financials'!B150,'Raw financials'!B152,'Raw financials'!B153) | C81: =SUM('Raw financials'!C145,'Raw financials'!C150,'Raw financials'!C152,'Raw financials'!C153) | D81: =SUM('Raw financials'!D145,'Raw financials'!D150,'Raw financials'!D152,'Raw financials'!D153) | E81: =SUM('Raw financials'!E145,'Raw financials'!E150,'Raw financials'!E152,'Raw financials'!E153) | F81: =SUM('Raw financials'!F145,'Raw financials'!F150,'Raw financials'!F152,'Raw financials'!F153) | G81: =SUM('Raw financials'!G145,'Raw financials'!G150,'Raw financials'!G152,'Raw financials'!G153) | H81: =SUM('Raw financials'!H145,'Raw financials'!H150,'Raw financials'!H152,'Raw financials'!H153) | I81: =SUM('Raw financials'!I145,'Raw financials'!I150,'Raw financials'!I152,'Raw financials'!I153) | ... T81: =SUM('Raw financials'!T145,'Raw financials'!T150,'Raw financials'!T152,'Raw financials'!T153) | U81: =T81 | V81: =U81 | W81: =V81 | X81: =W81 | Y81: =X81 | Z81: =Y81 | AA81: =+U81-T81 | AB81: =+AA81/T81 | AC81: 6553.6941 | AD81: =+X81-W81 | AE81: =+AD81/W81 | AG81: =SUM('Raw financials'!AA145,'Raw financials'!AA150,'Raw financials'!AA152,'Raw financials'!AA153) | AH81: =+B81 | AI81: =SUM('Raw financials'!AB145,'Raw financials'!AB150,'Raw financials'!AB152,'Raw financials'!AB153) | AJ81: =+C81 | AK81: =SUM('Raw financials'!AC145,'Raw financials'!AC150,'Raw financials'!AC152,'Raw financials'!AC153) | AL81: =+D81 | AM81: =SUM('Raw financials'!AD145,'Raw financials'!AD150,'Raw financials'!AD152,'Raw financials'!AD153) | AN81: =+E81 | AO81: =SUM('Raw financials'!AE145,'Raw financials'!AE150,'Raw financials'!AE152,'Raw financials'!AE153) | AP81: =+F81 | AQ81: =SUM('Raw financials'!AF145,'Raw financials'!AF150,'Raw financials'!AF152,'Raw financials'!AF153) | AR81: =+G81 | AS81: =SUM('Raw financials'!AG145,'Raw financials'!AG150,'Raw financials'!AG152,'Raw financials'!AG153) | AT81: =+H81 | AU81: =SUM('Raw financials'!AH145,'Raw financials'!AH150,'Raw financials'!AH152,'Raw financials'!AH153) | AV81: =+I81 | AW81: =SUM('Raw financials'!AI145,'Raw financials'!AI150,'Raw financials'!AI152,'Raw financials'!AI153) | AX81: =+J81 | AY81: =SUM('Raw financials'!AJ145,'Raw financials'!AJ150,'Raw financials'!AJ152,'Raw financials'!AJ153) | AZ81: =+K81 | BA81: =SUM('Raw financials'!AK145,'Raw financials'!AK150,'Raw financials'!AK152,'Raw financials'!AK153) | BB81: =+L81 | BC81: =SUM('Raw financials'!AL145,'Raw financials'!AL150,'Raw financials'!AL152,'Raw financials'!AL153) | BD81: =+M81 | BE81: =SUM('Raw financials'!AM145,'Raw financials'!AM150,'Raw financials'!AM152,'Raw financials'!AM153) | BF81: =+N81 | BG81: =SUM('Raw financials'!AN145,'Raw financials'!AN150,'Raw financials'!AN152,'Raw financials'!AN153) | BH81: =+O81 | BI81: =SUM('Raw financials'!AO145,'Raw financials'!AO150,'Raw financials'!AO152,'Raw financials'!AO153) | BJ81: =+P81 | BK81: =SUM('Raw financials'!AP145,'Raw financials'!AP150,'Raw financials'!AP152,'Raw financials'!AP153) | BL81: =+Q81 | BM81: =SUM('Raw financials'!AQ145,'Raw financials'!AQ150,'Raw financials'!AQ152,'Raw financials'!AQ153) | BN81: =+R81 | BO81: =SUM('Raw financials'!AR145,'Raw financials'!AR150,'Raw financials'!AR152,'Raw financials'!AR153) | BP81: =+S81 | BQ81: =SUM('Raw financials'!AS145,'Raw financials'!AS150,'Raw financials'!AS152,'Raw financials'!AS153) | BR81: =+T81 | BT81: =+U81 | BU81: =BT81-BR81 | BV81: =BU81/BR81 | BZ81: =SUM('Raw financials'!BN145,'Raw financials'!BN150,'Raw financials'!BN152,'Raw financials'!BN153) | CA81: =SUM('Raw financials'!BO145,'Raw financials'!BO150,'Raw financials'!BO152,'Raw financials'!BO153) | CB81: =SUM('Raw financials'!BP145,'Raw financials'!BP150,'Raw financials'!BP152,'Raw financials'!BP153) | CC81: =SUM('Raw financials'!BQ145,'Raw financials'!BQ150,'Raw financials'!BQ152,'Raw financials'!BQ153) | CD81: =SUM('Raw financials'!BR145,'Raw financials'!BR150,'Raw financials'!BR152,'Raw financials'!BR153) | CE81: =SUM('Raw financials'!BS145,'Raw financials'!BS150,'Raw financials'!BS152,'Raw financials'!BS153) | CF81: =SUM('Raw financials'!BT145,'Raw financials'!BT150,'Raw financials'!BT152,'Raw financials'!BT153) | CG81: =SUM('Raw financials'!BU145,'Raw financials'!BU150,'Raw financials'!BU152,'Raw financials'!BU153) | ... DW81: =SUM('Raw financials'!DK145,'Raw financials'!DK150,'Raw financials'!DK152,'Raw financials'!DK153) | DZ81: =SUM('Raw financials'!DN145,'Raw financials'!DN150,'Raw financials'!DN152,'Raw financials'!DN153) | EA81: =SUM('Raw financials'!DO145,'Raw financials'!DO150,'Raw financials'!DO152,'Raw financials'!DO153) | EB81: =SUM('Raw financials'!DP145,'Raw financials'!DP150,'Raw financials'!DP152,'Raw financials'!DP153) | EC81: =SUM('Raw financials'!DQ145,'Raw financials'!DQ150,'Raw financials'!DQ152,'Raw financials'!DQ153) | ED81: =SUM('Raw financials'!DR145,'Raw financials'!DR150,'Raw financials'!DR152,'Raw financials'!DR153) | EE81: =SUM('Raw financials'!DS145,'Raw financials'!DS150,'Raw financials'!DS152,'Raw financials'!DS153) | EF81: =SUM('Raw financials'!DT145,'Raw financials'!DT150,'Raw financials'!DT152,'Raw financials'!DT153) | EG81: =SUM('Raw financials'!DU145,'Raw financials'!DU150,'Raw financials'!DU152,'Raw financials'!DU153) | ... EY81: =SUM('Raw financials'!EM145,'Raw financials'!EM150,'Raw financials'!EM152,'Raw financials'!EM153) | FB81: =+FA81-EW81 | FC81: =+FB81/EW81
A82: Total non-current liabilities | B82: =SUM(B77:B81) | C82: =SUM(C77:C81) | D82: =SUM(D77:D81) | E82: =SUM(E77:E81) | F82: =SUM(F77:F81) | G82: =SUM(G77:G81) | H82: =SUM(H77:H81) | I82: =SUM(I77:I81) | ... Z82: =SUM(Z77:Z81) | AA82: =+U82-T82 | AB82: =+AA82/T82 | AC82: 9954.0676 | AD82: =+X82-W82 | AE82: =+AD82/W82 | AG82: =SUM(AG77:AG81) | AH82: =SUM(AH77:AH81) | AI82: =SUM(AI77:AI81) | AJ82: =SUM(AJ77:AJ81) | AK82: =SUM(AK77:AK81) | AL82: =SUM(AL77:AL81) | AM82: =SUM(AM77:AM81) | AN82: =SUM(AN77:AN81) | ... BR82: =SUM(BR77:BR81) | BT82: =SUM(BT77:BT81) | BU82: =BT82-BR82 | BV82: =BU82/BR82 | BZ82: =SUM(BZ77:BZ81) | CA82: =SUM(CA77:CA81) | CB82: =SUM(CB77:CB81) | CC82: =SUM(CC77:CC81) | CD82: =SUM(CD77:CD81) | CE82: =SUM(CE77:CE81) | CF82: =SUM(CF77:CF81) | CG82: =SUM(CG77:CG81) | ... DW82: =SUM(DW77:DW81) | DZ82: =SUM(DZ77:DZ81) | EA82: =SUM(EA77:EA81) | EB82: =SUM(EB77:EB81) | EC82: =SUM(EC77:EC81) | ED82: =SUM(ED77:ED81) | EE82: =SUM(EE77:EE81) | EF82: =SUM(EF77:EF81) | EG82: =SUM(EG77:EG81) | ... EY82: =SUM(EY77:EY81) | FB82: =+FA82-EW82 | FC82: =+FB82/EW82
A84: Paid-in capital | B84: ='Raw financials'!B161 | C84: ='Raw financials'!C161 | D84: ='Raw financials'!D161 | E84: ='Raw financials'!E161 | F84: ='Raw financials'!F161 | G84: ='Raw financials'!G161 | H84: ='Raw financials'!H161 | I84: ='Raw financials'!I161 | ... T84: ='Raw financials'!T161 | U84: =U42 | V84: =U84 | W84: =V84 | X84: =W84 | Y84: =X84 | Z84: =Y84 | AA84: =+U84-T84 | AB84: =+AA84/T84 | AC84: 3458 | AD84: =+X84-W84 | AE84: =+AD84/W84 | AG84: ='Raw financials'!AA161 | AH84: =+B84 | AI84: ='Raw financials'!AB161 | AJ84: =+C84 | AK84: ='Raw financials'!AC161 | AL84: =+D84 | AM84: ='Raw financials'!AD161 | AN84: =+E84 | AO84: ='Raw financials'!AE161 | AP84: =+F84 | AQ84: ='Raw financials'!AF161 | AR84: =+G84 | AS84: ='Raw financials'!AG161 | AT84: =+H84 | AU84: ='Raw financials'!AH161 | AV84: =+I84 | AW84: ='Raw financials'!AI161 | AX84: =+J84 | AY84: ='Raw financials'!AJ161 | AZ84: =+K84 | BA84: ='Raw financials'!AK161 | BB84: =+L84 | BC84: ='Raw financials'!AL161 | BD84: =+M84 | BE84: ='Raw financials'!AM161 | BF84: =+N84 | BG84: ='Raw financials'!AN161 | BH84: =+O84 | BI84: ='Raw financials'!AO161 | BJ84: =+P84 | BK84: ='Raw financials'!AP161 | BL84: =+Q84 | BM84: ='Raw financials'!AQ161 | BN84: =+R84 | BO84: ='Raw financials'!AR161 | BP84: =+S84 | BQ84: ='Raw financials'!AS161 | BR84: =+T84 | BT84: =+U84 | BU84: =BT84-BR84 | BV84: =BU84/BR84 | BZ84: ='Raw financials'!BN161 | CA84: ='Raw financials'!BO161 | CB84: ='Raw financials'!BP161 | CC84: ='Raw financials'!BQ161 | CD84: ='Raw financials'!BR161 | CE84: ='Raw financials'!BS161 | CF84: ='Raw financials'!BT161 | CG84: ='Raw financials'!BU161 | ... DW84: ='Raw financials'!DK161 | DZ84: ='Raw financials'!DN161 | EA84: ='Raw financials'!DO161 | EB84: ='Raw financials'!DP161 | EC84: ='Raw financials'!DQ161 | ED84: ='Raw financials'!DR161 | EE84: ='Raw financials'!DS161 | EF84: ='Raw financials'!DT161 | EG84: ='Raw financials'!DU161 | ... EY84: ='Raw financials'!EM161 | FB84: =+FA84-EW84 | FC84: =+FB84/EW84
A85: Additional paid-in capital | B85: ='Raw financials'!B165-'Raw financials'!B166+'Raw financials'!B168 | C85: ='Raw financials'!C165-'Raw financials'!C166+'Raw financials'!C168 | D85: ='Raw financials'!D165-'Raw financials'!D166+'Raw financials'!D168 | E85: ='Raw financials'!E165-'Raw financials'!E166+'Raw financials'!E168 | F85: ='Raw financials'!F165-'Raw financials'!F166+'Raw financials'!F168 | G85: ='Raw financials'!G165-'Raw financials'!G166+'Raw financials'!G168 | H85: ='Raw financials'!H165-'Raw financials'!H166+'Raw financials'!H168 | I85: ='Raw financials'!I165-'Raw financials'!I166+'Raw financials'!I168 | ... T85: ='Raw financials'!T165-'Raw financials'!T166+'Raw financials'!T168 | U85: =T85+4116.565363-(U84-T84)+1070 | V85: =U85 | W85: =V85 | X85: =W85 | Y85: =X85 | Z85: =Y85 | AA85: =+U85-T85 | AB85: =+AA85/T85 | AC85: 16529.436 | AD85: =+X85-W85 | AE85: =+AD85/W85 | AG85: ='Raw financials'!AA165-'Raw financials'!AA166+'Raw financials'!AA168 | AH85: =+B85 | AI85: ='Raw financials'!AB165-'Raw financials'!AB166+'Raw financials'!AB168 | AJ85: =+C85 | AK85: ='Raw financials'!AC165-'Raw financials'!AC166+'Raw financials'!AC168 | AL85: =+D85 | AM85: ='Raw financials'!AD165-'Raw financials'!AD166+'Raw financials'!AD168 | AN85: =+E85 | AO85: ='Raw financials'!AE165-'Raw financials'!AE166+'Raw financials'!AE168 | AP85: =+F85 | AQ85: ='Raw financials'!AF165-'Raw financials'!AF166+'Raw financials'!AF168 | AR85: =+G85 | AS85: ='Raw financials'!AG165-'Raw financials'!AG166+'Raw financials'!AG168 | AT85: =+H85 | AU85: ='Raw financials'!AH165-'Raw financials'!AH166+'Raw financials'!AH168 | AV85: =+I85 | AW85: ='Raw financials'!AI165-'Raw financials'!AI166+'Raw financials'!AI168 | AX85: =+J85 | AY85: ='Raw financials'!AJ165-'Raw financials'!AJ166+'Raw financials'!AJ168 | AZ85: =+K85 | BA85: ='Raw financials'!AK165-'Raw financials'!AK166+'Raw financials'!AK168 | BB85: =+L85 | BC85: ='Raw financials'!AL165-'Raw financials'!AL166+'Raw financials'!AL168 | BD85: =+M85 | BE85: ='Raw financials'!AM165-'Raw financials'!AM166+'Raw financials'!AM168 | BF85: =+N85 | BG85: ='Raw financials'!AN165-'Raw financials'!AN166+'Raw financials'!AN168 | BH85: =+O85 | BI85: ='Raw financials'!AO165-'Raw financials'!AO166+'Raw financials'!AO168 | BJ85: =+P85 | BK85: ='Raw financials'!AP165-'Raw financials'!AP166+'Raw financials'!AP168 | BL85: =+Q85 | BM85: ='Raw financials'!AQ165-'Raw financials'!AQ166+'Raw financials'!AQ168 | BN85: =+R85 | BO85: ='Raw financials'!AR165-'Raw financials'!AR166+'Raw financials'!AR168 | BP85: =+S85 | BQ85: ='Raw financials'!AS165-'Raw financials'!AS166+'Raw financials'!AS168 | BR85: =+T85 | BT85: =+U85 | BU85: =BT85-BR85 | BV85: =BU85/BR85 | BZ85: ='Raw financials'!BN165-'Raw financials'!BN166+'Raw financials'!BN168 | CA85: ='Raw financials'!BO165-'Raw financials'!BO166+'Raw financials'!BO168 | CB85: ='Raw financials'!BP165-'Raw financials'!BP166+'Raw financials'!BP168 | CC85: ='Raw financials'!BQ165-'Raw financials'!BQ166+'Raw financials'!BQ168 | CD85: ='Raw financials'!BR165-'Raw financials'!BR166+'Raw financials'!BR168 | CE85: ='Raw financials'!BS165-'Raw financials'!BS166+'Raw financials'!BS168 | CF85: ='Raw financials'!BT165-'Raw financials'!BT166+'Raw financials'!BT168 | CG85: ='Raw financials'!BU165-'Raw financials'!BU166+'Raw financials'!BU168 | ... DW85: ='Raw financials'!DK165-'Raw financials'!DK166+'Raw financials'!DK168 | DZ85: ='Raw financials'!DN165-'Raw financials'!DN166+'Raw financials'!DN168 | EA85: ='Raw financials'!DO165-'Raw financials'!DO166+'Raw financials'!DO168 | EB85: ='Raw financials'!DP165-'Raw financials'!DP166+'Raw financials'!DP168 | EC85: ='Raw financials'!DQ165-'Raw financials'!DQ166+'Raw financials'!DQ168 | ED85: ='Raw financials'!DR165-'Raw financials'!DR166+'Raw financials'!DR168 | EE85: ='Raw financials'!DS165-'Raw financials'!DS166+'Raw financials'!DS168 | EF85: ='Raw financials'!DT165-'Raw financials'!DT166+'Raw financials'!DT168 | EG85: ='Raw financials'!DU165-'Raw financials'!DU166+'Raw financials'!DU168 | ... EY85: ='Raw financials'!EM165-'Raw financials'!EM166+'Raw financials'!EM168 | FB85: =+FA85-EW85 | FC85: =+FB85/EW85
A86: Other comprehensive income | B86: ='Raw financials'!B167 | C86: ='Raw financials'!C167 | D86: ='Raw financials'!D167 | E86: ='Raw financials'!E167 | F86: ='Raw financials'!F167 | G86: ='Raw financials'!G167 | H86: ='Raw financials'!H167 | I86: ='Raw financials'!I167 | ... T86: ='Raw financials'!T167 | U86: =T86 | V86: =U86 | W86: =V86 | X86: =W86 | Y86: =X86 | Z86: =Y86 | AA86: =+U86-T86 | AB86: =+AA86/T86 | AC86: -120.0822 | AD86: =+X86-W86 | AE86: =+AD86/W86 | AG86: ='Raw financials'!AA167 | AH86: =+B86 | AI86: ='Raw financials'!AB167 | AJ86: =+C86 | AK86: ='Raw financials'!AC167 | AL86: =+D86 | AM86: ='Raw financials'!AD167 | AN86: =+E86 | AO86: ='Raw financials'!AE167 | AP86: =+F86 | AQ86: ='Raw financials'!AF167 | AR86: =+G86 | AS86: ='Raw financials'!AG167 | AT86: =+H86 | AU86: ='Raw financials'!AH167 | AV86: =+I86 | AW86: ='Raw financials'!AI167 | AX86: =+J86 | AY86: ='Raw financials'!AJ167 | AZ86: =+K86 | BA86: ='Raw financials'!AK167 | BB86: =+L86 | BC86: ='Raw financials'!AL167 | BD86: =+M86 | BE86: ='Raw financials'!AM167 | BF86: =+N86 | BG86: ='Raw financials'!AN167 | BH86: =+O86 | BI86: ='Raw financials'!AO167 | BJ86: =+P86 | BK86: ='Raw financials'!AP167 | BL86: =+Q86 | BM86: ='Raw financials'!AQ167 | BN86: =+R86 | BO86: ='Raw financials'!AR167 | BP86: =+S86 | BQ86: ='Raw financials'!AS167 | BR86: =+T86 | BT86: =+U86 | BU86: =BT86-BR86 | BV86: =BU86/BR86 | BZ86: ='Raw financials'!BN167 | CA86: ='Raw financials'!BO167 | CB86: ='Raw financials'!BP167 | CC86: ='Raw financials'!BQ167 | CD86: ='Raw financials'!BR167 | CE86: ='Raw financials'!BS167 | CF86: ='Raw financials'!BT167 | CG86: ='Raw financials'!BU167 | ... DW86: ='Raw financials'!DK167 | DZ86: ='Raw financials'!DN167 | EA86: ='Raw financials'!DO167 | EB86: ='Raw financials'!DP167 | EC86: ='Raw financials'!DQ167 | ED86: ='Raw financials'!DR167 | EE86: ='Raw financials'!DS167 | EF86: ='Raw financials'!DT167 | EG86: ='Raw financials'!DU167 | ... EY86: ='Raw financials'!EM167 | FB86: =+FA86-EW86 | FC86: =+FB86/EW86
A87: Surplus reserves | B87: ='Raw financials'!B169 | C87: ='Raw financials'!C169 | D87: ='Raw financials'!D169 | E87: ='Raw financials'!E169 | F87: ='Raw financials'!F169 | G87: ='Raw financials'!G169 | H87: ='Raw financials'!H169 | I87: ='Raw financials'!I169 | ... T87: ='Raw financials'!T169 | U87: =T87 | V87: =U87 | W87: =V87 | X87: =W87 | Y87: =X87 | Z87: =Y87 | AA87: =+U87-T87 | AB87: =+AA87/T87 | AC87: 1424.8892 | AD87: =+X87-W87 | AE87: =+AD87/W87 | AG87: ='Raw financials'!AA169+'Raw financials'!AA170 | AH87: =+B87 | AI87: ='Raw financials'!AB169+'Raw financials'!AB170 | AJ87: =+C87 | AK87: ='Raw financials'!AC169+'Raw financials'!AC170 | AL87: =+D87 | AM87: ='Raw financials'!AD169+'Raw financials'!AD170 | AN87: =+E87 | AO87: ='Raw financials'!AE169+'Raw financials'!AE170 | AP87: =+F87 | AQ87: ='Raw financials'!AF169+'Raw financials'!AF170 | AR87: =+G87 | AS87: ='Raw financials'!AG169+'Raw financials'!AG170 | AT87: =+H87 | AU87: ='Raw financials'!AH169+'Raw financials'!AH170 | AV87: =+I87 | AW87: ='Raw financials'!AI169+'Raw financials'!AI170 | AX87: =+J87 | AY87: ='Raw financials'!AJ169+'Raw financials'!AJ170 | AZ87: =+K87 | BA87: ='Raw financials'!AK169+'Raw financials'!AK170 | BB87: =+L87 | BC87: ='Raw financials'!AL169+'Raw financials'!AL170 | BD87: =+M87 | BE87: ='Raw financials'!AM169+'Raw financials'!AM170 | BF87: =+N87 | BG87: ='Raw financials'!AN169+'Raw financials'!AN170 | BH87: =+O87 | BI87: ='Raw financials'!AO169+'Raw financials'!AO170 | BJ87: =+P87 | BK87: ='Raw financials'!AP169+'Raw financials'!AP170 | BL87: =+Q87 | BM87: ='Raw financials'!AQ169+'Raw financials'!AQ170 | BN87: =+R87 | BO87: ='Raw financials'!AR169+'Raw financials'!AR170 | BP87: =+S87 | BQ87: ='Raw financials'!AS169+'Raw financials'!AS170 | BR87: =+T87 | BT87: =+U87 | BU87: =BT87-BR87 | BV87: =BU87/BR87 | BZ87: ='Raw financials'!BN169+'Raw financials'!BN170 | CA87: ='Raw financials'!BO169+'Raw financials'!BO170 | CB87: ='Raw financials'!BP169+'Raw financials'!BP170 | CC87: ='Raw financials'!BQ169+'Raw financials'!BQ170 | CD87: ='Raw financials'!BR169+'Raw financials'!BR170 | CE87: ='Raw financials'!BS169+'Raw financials'!BS170 | CF87: ='Raw financials'!BT169+'Raw financials'!BT170 | CG87: ='Raw financials'!BU169+'Raw financials'!BU170 | ... DW87: ='Raw financials'!DK169+'Raw financials'!DK170 | DZ87: ='Raw financials'!DN169+'Raw financials'!DN170 | EA87: ='Raw financials'!DO169+'Raw financials'!DO170 | EB87: ='Raw financials'!DP169+'Raw financials'!DP170 | EC87: ='Raw financials'!DQ169+'Raw financials'!DQ170 | ED87: ='Raw financials'!DR169+'Raw financials'!DR170 | EE87: ='Raw financials'!DS169+'Raw financials'!DS170 | EF87: ='Raw financials'!DT169+'Raw financials'!DT170 | EG87: ='Raw financials'!DU169+'Raw financials'!DU170 | ... EY87: ='Raw financials'!EM169+'Raw financials'!EM170 | FB87: =+FA87-EW87 | FC87: =+FB87/EW87
A88: Retained earnings | B88: ='Raw financials'!B171+'Raw financials'!B172 | C88: ='Raw financials'!C171+'Raw financials'!C172 | D88: ='Raw financials'!D171+'Raw financials'!D172 | E88: ='Raw financials'!E171+'Raw financials'!E172 | F88: ='Raw financials'!F171+'Raw financials'!F172 | G88: ='Raw financials'!G171+'Raw financials'!G172 | H88: ='Raw financials'!H171+'Raw financials'!H172 | I88: ='Raw financials'!I171+'Raw financials'!I172 | ... T88: ='Raw financials'!T171+'Raw financials'!T172 | U88: =T88+U28-T38 | V88: =U88+V28-U38 | W88: =V88+W28-V38 | X88: =W88+X28-W38 | Y88: =X88+Y28-X38 | Z88: =Y88+Z28-Y38 | AA88: =+U88-T88 | AB88: =+AA88/T88 | AC88: 25680.346 | AD88: =+X88-W88 | AE88: =+AD88/W88 | AG88: ='Raw financials'!AA171+'Raw financials'!AA172 | AH88: =+B88 | AI88: ='Raw financials'!AB171+'Raw financials'!AB172 | AJ88: =+C88 | AK88: ='Raw financials'!AC171+'Raw financials'!AC172 | AL88: =+D88 | AM88: ='Raw financials'!AD171+'Raw financials'!AD172 | AN88: =+E88 | AO88: ='Raw financials'!AE171+'Raw financials'!AE172 | AP88: =+F88 | AQ88: ='Raw financials'!AF171+'Raw financials'!AF172 | AR88: =+G88 | AS88: ='Raw financials'!AG171+'Raw financials'!AG172 | AT88: =+H88 | AU88: ='Raw financials'!AH171+'Raw financials'!AH172 | AV88: =+I88 | AW88: ='Raw financials'!AI171+'Raw financials'!AI172 | AX88: =+J88 | AY88: ='Raw financials'!AJ171+'Raw financials'!AJ172 | AZ88: =+K88 | BA88: ='Raw financials'!AK171+'Raw financials'!AK172 | BB88: =+L88 | BC88: ='Raw financials'!AL171+'Raw financials'!AL172 | BD88: =+M88 | BE88: ='Raw financials'!AM171+'Raw financials'!AM172 | BF88: =+N88 | BG88: ='Raw financials'!AN171+'Raw financials'!AN172 | BH88: =+O88 | BI88: ='Raw financials'!AO171+'Raw financials'!AO172 | BJ88: =+P88 | BK88: ='Raw financials'!AP171+'Raw financials'!AP172 | BL88: =+Q88 | BM88: ='Raw financials'!AQ171+'Raw financials'!AQ172 | BN88: =+R88 | BO88: ='Raw financials'!AR171+'Raw financials'!AR172 | BP88: =+S88 | BQ88: ='Raw financials'!AS171+'Raw financials'!AS172 | BR88: =+T88 | BT88: =+U88 | BU88: =BT88-BR88 | BV88: =BU88/BR88 | BZ88: ='Raw financials'!BN171+'Raw financials'!BN172 | CA88: ='Raw financials'!BO171+'Raw financials'!BO172 | CB88: ='Raw financials'!BP171+'Raw financials'!BP172 | CC88: ='Raw financials'!BQ171+'Raw financials'!BQ172 | CD88: ='Raw financials'!BR171+'Raw financials'!BR172 | CE88: ='Raw financials'!BS171+'Raw financials'!BS172 | CF88: ='Raw financials'!BT171+'Raw financials'!BT172 | CG88: ='Raw financials'!BU171+'Raw financials'!BU172 | ... DW88: ='Raw financials'!DK171+'Raw financials'!DK172 | DZ88: ='Raw financials'!DN171+'Raw financials'!DN172 | EA88: ='Raw financials'!DO171+'Raw financials'!DO172 | EB88: ='Raw financials'!DP171+'Raw financials'!DP172 | EC88: ='Raw financials'!DQ171+'Raw financials'!DQ172 | ED88: ='Raw financials'!DR171+'Raw financials'!DR172 | EE88: ='Raw financials'!DS171+'Raw financials'!DS172 | EF88: ='Raw financials'!DT171+'Raw financials'!DT172 | EG88: ='Raw financials'!DU171+'Raw financials'!DU172 | ... EY88: ='Raw financials'!EM171+'Raw financials'!EM172 | FB88: =+FA88-EW88 | FC88: =+FB88/EW88
A89: Total shareholder's equity | B89: =SUM(B84:B88) | C89: =SUM(C84:C88) | D89: =SUM(D84:D88) | E89: =SUM(E84:E88) | F89: =SUM(F84:F88) | G89: =SUM(G84:G88) | H89: =SUM(H84:H88) | I89: =SUM(I84:I88) | ... Z89: =SUM(Z84:Z88) | AA89: =+U89-T89 | AB89: =+AA89/T89 | AC89: 46972.589 | AD89: =+X89-W89 | AE89: =+AD89/W89 | AG89: =SUM(AG84:AG88) | AH89: =SUM(AH84:AH88) | AI89: =SUM(AI84:AI88) | AJ89: =SUM(AJ84:AJ88) | AK89: =SUM(AK84:AK88) | AL89: =SUM(AL84:AL88) | AM89: =SUM(AM84:AM88) | AN89: =SUM(AN84:AN88) | ... BR89: =SUM(BR84:BR88) | BT89: =SUM(BT84:BT88) | BU89: =BT89-BR89 | BV89: =BU89/BR89 | BZ89: =SUM(BZ84:BZ88) | CA89: =SUM(CA84:CA88) | CB89: =SUM(CB84:CB88) | CC89: =SUM(CC84:CC88) | CD89: =SUM(CD84:CD88) | CE89: =SUM(CE84:CE88) | CF89: =SUM(CF84:CF88) | CG89: =SUM(CG84:CG88) | ... DW89: =SUM(DW84:DW88) | DZ89: =SUM(DZ84:DZ88) | EA89: =SUM(EA84:EA88) | EB89: =SUM(EB84:EB88) | EC89: =SUM(EC84:EC88) | ED89: =SUM(ED84:ED88) | EE89: =SUM(EE84:EE88) | EF89: =SUM(EF84:EF88) | EG89: =SUM(EG84:EG88) | ... EY89: =SUM(EY84:EY88) | FB89: =+FA89-EW89 | FC89: =+FB89/EW89
A90: Minority interest | B90: ='Raw financials'!B177 | C90: ='Raw financials'!C177 | D90: ='Raw financials'!D177 | E90: ='Raw financials'!E177 | F90: ='Raw financials'!F177 | G90: ='Raw financials'!G177 | H90: ='Raw financials'!H177 | I90: ='Raw financials'!I177 | ... T90: ='Raw financials'!T177 | U90: =T90 | V90: =U90 | W90: =V90 | X90: =W90 | Y90: =X90 | Z90: =Y90 | AA90: =+U90-T90 | AB90: =+AA90/T90 | AC90: 4345.9658 | AD90: =+X90-W90 | AE90: =+AD90/W90 | AG90: ='Raw financials'!AA177 | AH90: =+B90 | AI90: ='Raw financials'!AB177 | AJ90: =+C90 | AK90: ='Raw financials'!AC177 | AL90: =+D90 | AM90: ='Raw financials'!AD177 | AN90: =+E90 | AO90: ='Raw financials'!AE177 | AP90: =+F90 | AQ90: ='Raw financials'!AF177 | AR90: =+G90 | AS90: ='Raw financials'!AG177 | AT90: =+H90 | AU90: ='Raw financials'!AH177 | AV90: =+I90 | AW90: ='Raw financials'!AI177 | AX90: =+J90 | AY90: ='Raw financials'!AJ177 | AZ90: =+K90 | BA90: ='Raw financials'!AK177 | BB90: =+L90 | BC90: ='Raw financials'!AL177 | BD90: =+M90 | BE90: ='Raw financials'!AM177 | BF90: =+N90 | BG90: ='Raw financials'!AN177 | BH90: =+O90 | BI90: ='Raw financials'!AO177 | BJ90: =+P90 | BK90: ='Raw financials'!AP177 | BL90: =+Q90 | BM90: ='Raw financials'!AQ177 | BN90: =+R90 | BO90: ='Raw financials'!AR177 | BP90: =+S90 | BQ90: ='Raw financials'!AS177 | BR90: =+T90 | BT90: =+U90 | BU90: =BT90-BR90 | BV90: =BU90/BR90 | BZ90: ='Raw financials'!BN177 | CA90: ='Raw financials'!BO177 | CB90: ='Raw financials'!BP177 | CC90: ='Raw financials'!BQ177 | CD90: ='Raw financials'!BR177 | CE90: ='Raw financials'!BS177 | CF90: ='Raw financials'!BT177 | CG90: ='Raw financials'!BU177 | ... DW90: ='Raw financials'!DK177 | DZ90: ='Raw financials'!DN177 | EA90: ='Raw financials'!DO177 | EB90: ='Raw financials'!DP177 | EC90: ='Raw financials'!DQ177 | ED90: ='Raw financials'!DR177 | EE90: ='Raw financials'!DS177 | EF90: ='Raw financials'!DT177 | EG90: ='Raw financials'!DU177 | ... EY90: ='Raw financials'!EM177 | FB90: =+FA90-EW90 | FC90: =+FB90/EW90
A91: Total equity | B91: =B89+B90 | C91: =C89+C90 | D91: =D89+D90 | E91: =E89+E90 | F91: =F89+F90 | G91: =G89+G90 | H91: =H89+H90 | I91: =I89+I90 | ... Z91: =Z89+Z90 | AA91: =+U91-T91 | AB91: =+AA91/T91 | AC91: 51318.554 | AD91: =+X91-W91 | AE91: =+AD91/W91 | AG91: =AG89+AG90 | AH91: =AH89+AH90 | AI91: =AI89+AI90 | AJ91: =AJ89+AJ90 | AK91: =AK89+AK90 | AL91: =AL89+AL90 | AM91: =AM89+AM90 | AN91: =AN89+AN90 | ... BR91: =BR89+BR90 | BT91: =BT89+BT90 | BU91: =BT91-BR91 | BV91: =BU91/BR91 | BZ91: =BZ89+BZ90 | CA91: =CA89+CA90 | CB91: =CB89+CB90 | CC91: =CC89+CC90 | CD91: =CD89+CD90 | CE91: =CE89+CE90 | CF91: =CF89+CF90 | CG91: =CG89+CG90 | ... DW91: =DW89+DW90 | DZ91: =DZ89+DZ90 | EA91: =EA89+EA90 | EB91: =EB89+EB90 | EC91: =EC89+EC90 | ED91: =ED89+ED90 | EE91: =EE89+EE90 | EF91: =EF89+EF90 | EG91: =EG89+EG90 | ... EY91: =EY89+EY90 | FB91: =+FA91-EW91 | FC91: =+FB91/EW91
A93: Total liabilities and equity | B93: =B75+B82+B91 | C93: =C75+C82+C91 | D93: =D75+D82+D91 | E93: =E75+E82+E91 | F93: =F75+F82+F91 | G93: =G75+G82+G91 | H93: =H75+H82+H91 | I93: =I75+I82+I91 | ... Z93: =Z75+Z82+Z91 | AA93: =+U93-T93 | AB93: =+AA93/T93 | AC93: 157100.31 | AD93: =+X93-W93 | AE93: =+AD93/W93 | AG93: =AG75+AG82+AG91 | AH93: =AH75+AH82+AH91 | AI93: =AI75+AI82+AI91 | AJ93: =AJ75+AJ82+AJ91 | AK93: =AK75+AK82+AK91 | AL93: =AL75+AL82+AL91 | AM93: =AM75+AM82+AM91 | AN93: =AN75+AN82+AN91 | ... BR93: =BR75+BR82+BR91 | BT93: =BT75+BT82+BT91 | BU93: =BT93-BR93 | BV93: =BU93/BR93 | BZ93: =BZ75+BZ82+BZ91 | CA93: =CA75+CA82+CA91 | CB93: =CB75+CB82+CB91 | CC93: =CC75+CC82+CC91 | CD93: =CD75+CD82+CD91 | CE93: =CE75+CE82+CE91 | CF93: =CF75+CF82+CF91 | CG93: =CG75+CG82+CG91 | ... DW93: =DW75+DW82+DW91 | DZ93: =DZ75+DZ82+DZ91 | EA93: =EA75+EA82+EA91 | EB93: =EB75+EB82+EB91 | EC93: =EC75+EC82+EC91 | ED93: =ED75+ED82+ED91 | EE93: =EE75+EE82+EE91 | EF93: =EF75+EF82+EF91 | EG93: =EG75+EG82+EG91 | ... EY93: =EY75+EY82+EY91 | FB93: =+FA93-EW93 | FC93: =+FB93/EW93
A95: Check | B95: =ROUND(B67-B93,0) | C95: =ROUND(C67-C93,0) | D95: =ROUND(D67-D93,0) | E95: =ROUND(E67-E93,0) | F95: =ROUND(F67-F93,0) | G95: =ROUND(G67-G93,0) | H95: =ROUND(H67-H93,0) | I95: =ROUND(I67-I93,0) | ... Z95: =ROUND(Z67-Z93,0) | AG95: =ROUND(AG67-AG93,0) | AH95: =ROUND(AH67-AH93,0) | AI95: =ROUND(AI67-AI93,0) | AJ95: =ROUND(AJ67-AJ93,0) | AK95: =ROUND(AK67-AK93,0) | AL95: =ROUND(AL67-AL93,0) | AM95: =ROUND(AM67-AM93,0) | AN95: =ROUND(AN67-AN93,0) | ... BR95: =ROUND(BR67-BR93,0) | BT95: =ROUND(BT67-BT93,0) | BZ95: =ROUND(BZ67-BZ93,0) | CA95: =ROUND(CA67-CA93,0) | CB95: =ROUND(CB67-CB93,0) | CC95: =ROUND(CC67-CC93,0) | CD95: =ROUND(CD67-CD93,0) | CE95: =ROUND(CE67-CE93,0) | CF95: =ROUND(CF67-CF93,0) | CG95: =ROUND(CG67-CG93,0) | ... FA95: =ROUND(FA67-FA93,0)
V96: =V95-U95 | W96: =W95-V95 | X96: =X95-W95 | Y96: =Y95-X95 | Z96: =Z95-Y95
A97: Total liability/asset ratio | B97: =(B75+B82)/B67 | C97: =(C75+C82)/C67 | D97: =(D75+D82)/D67 | E97: =(E75+E82)/E67 | F97: =(F75+F82)/F67 | G97: =(G75+G82)/G67 | H97: =(H75+H82)/H67 | I97: =(I75+I82)/I67 | ... Z97: =(Z75+Z82)/Z67
A98: Total debt | B98: =B69+B73+B77 | C98: =C69+C73+C77 | D98: =D69+D73+D77 | E98: =E69+E73+E77 | F98: =F69+F73+F77 | G98: =G69+G73+G77 | H98: =H69+H73+H77 | I98: =I69+I73+I77 | ... Z98: =Z69+Z73+Z77
A99: Net debt/(cash) | B99: =B98-B47 | C99: =C98-C47 | D99: =D98-D47 | E99: =E98-E47 | F99: =F98-F47 | G99: =G98-G47 | H99: =H98-H47 | I99: =I98-I47 | ... Z99: =Z98-Z47
A100: Net gearing | B100: =B99/B91 | C100: =C99/C91 | D100: =D99/D91 | E100: =E99/E91 | F100: =F99/F91 | G100: =G99/G91 | H100: =H99/H91 | I100: =I99/I91 | ... Z100: =Z99/Z91
A101: ROE | B101: =B28/AVERAGE(A91:B91) | C101: =C28/AVERAGE(B91:C91) | D101: =D28/AVERAGE(C91:D91) | E101: =E28/AVERAGE(D91:E91) | F101: =F28/AVERAGE(E91:F91) | G101: =G28/AVERAGE(F91:G91) | H101: =H28/AVERAGE(G91:H91) | I101: =I28/AVERAGE(H91:I91) | ... Z101: =Z28/AVERAGE(Y91:Z91)
A102: ROIC | U102: =(U15*(1-U24))/AVERAGE(U91+U99,T91+T99) | V102: =(V15*(1-V24))/AVERAGE(V91+V99,U91+U99) | W102: =(W15*(1-W24))/AVERAGE(W91+W99,V91+V99) | X102: =(X15*(1-X24))/AVERAGE(X91+X99,W91+W99) | Y102: =(Y15*(1-Y24))/AVERAGE(Y91+Y99,X91+X99) | Z102: =(Z15*(1-Z24))/AVERAGE(Z91+Z99,Y91+Y99)
A104: Cash flow statement
A105: Net profit | B105: =B28 | C105: =C28 | D105: =D28 | E105: =E28 | F105: =F28 | G105: =G28 | H105: =H28 | I105: =I28 | ... Z105: =Z28 | AA105: =+U105-T105 | AB105: =+AA105/T105 | AC105: 4356.0608 | AD105: =+X105-W105 | AE105: =+AD105/W105 | AG105: =AG25 | AH105: =+B105-AG105 | AI105: =AI25 | AJ105: =+C105-AI105 | AK105: =AK25 | AL105: =+D105-AK105 | AM105: =AM25 | AN105: =+E105-AM105 | AO105: =AO25 | AP105: =+F105-AO105 | AQ105: =AQ25 | AR105: =+G105-AQ105 | AS105: =AS25 | AT105: =+H105-AS105 | AU105: =AU25 | AV105: =+I105-AU105 | AW105: =AW25 | AX105: =+J105-AW105 | AY105: =AY25 | AZ105: =+K105-AY105 | BA105: =BA25 | BB105: =+L105-BA105 | BC105: =BC25 | BD105: =+M105-BC105 | BE105: =BE25 | BF105: =+N105-BE105 | BG105: =BG25 | BH105: =+O105-BG105 | BI105: =BI25 | BJ105: =+P105-BI105 | BK105: =BK25 | BL105: =+Q105-BK105 | BM105: =BM25 | BN105: =+R105-BM105 | BO105: =BO25 | BP105: =+S105-BO105 | BQ105: =BQ25 | BR105: =+T105-BQ105 | BT105: =+U105-BS105 | BU105: =BT105-BR105 | BV105: =BU105/BR105 | BW105: =+BT105/T105 | BX105: =+BT105/U105 | BZ105: =BZ25 | CA105: =CA25 | CB105: =CB25 | CD105: =CD25 | CF105: =CF25 | CH105: =CH25 | CJ105: =CJ25 | CL105: =CL25 | CN105: =CN25 | CP105: =CP25 | CR105: =CR25 | CT105: =CT25 | CV105: =CV25 | CX105: =CX25 | CZ105: =CZ25 | DB105: =DB25 | DD105: =DD25 | DF105: =DF25 | DH105: =DH25 | DJ105: =DJ25 | DL105: =DL25 | DN105: =DN25 | DP105: =DP25 | DR105: =DR25 | DT105: =DT25 | DV105: =DV25 | DX105: =DX25 | DZ105: =DZ25 | EB105: =EB25 | ED105: =ED25 | EF105: =EF25 | EH105: =EH25 | EJ105: =EJ25 | EL105: =EL25 | EN105: =EN25 | EP105: =EP25 | ER105: =ER25 | ET105: =ET25 | EU105: =+BQ105-ET105 | EV105: =EV25 | EW105: =EW25 | EX105: =EX25 | EY105: =EY25 | FB105: =+FA105-EW105 | FC105: =+FB105/EW105 | FD105: =+FA105/T105 | FE105: =+FA105/U105
A106: Impairment and fair value adjustment | B106: =-B20 | C106: =-C20 | D106: =-D20 | E106: =-E20 | F106: =-F20 | G106: =-G20 | H106: =-H20 | I106: =-I20 | ... Z106: =-Z20 | AA106: =+U106-T106 | AB106: =+AA106/T106 | AC106: 574.3 | AD106: =+X106-W106 | AE106: =+AD106/W106 | AG106: =-AG20 | AH106: =+B106-AG106 | AI106: =-AI20 | AJ106: =+C106-AI106 | AK106: =-AK20 | AL106: =+D106-AK106 | AM106: =-AM20 | AN106: =+E106-AM106 | AO106: =-AO20 | AP106: =+F106-AO106 | AQ106: =-AQ20 | AR106: =+G106-AQ106 | AS106: =-AS20 | AT106: =+H106-AS106 | AU106: =-AU20 | AV106: =+I106-AU106 | AW106: =-AW20 | AX106: =+J106-AW106 | AY106: =-AY20 | AZ106: =+K106-AY106 | BA106: =-BA20 | BB106: =+L106-BA106 | BC106: =-BC20 | BD106: =+M106-BC106 | BE106: =-BE20 | BF106: =+N106-BE106 | BG106: =-BG20 | BH106: =+O106-BG106 | BI106: =-BI20 | BJ106: =+P106-BI106 | BK106: =-BK20 | BL106: =+Q106-BK106 | BM106: =-BM20 | BN106: =+R106-BM106 | BO106: =-BO20 | BP106: =+S106-BO106 | BQ106: =-BQ20 | BR106: =+T106-BQ106 | BT106: =+U106-BS106 | BU106: =BT106-BR106 | BV106: =BU106/BR106 | BW106: =+BT106/T106 | BX106: =+BT106/U106 | BZ106: =-BZ20 | CA106: =-CA20 | CB106: =-CB20 | CD106: =-CD20 | CF106: =-CF20 | CH106: =-CH20 | CJ106: =-CJ20 | CL106: =-CL20 | CN106: =-CN20 | CP106: =-CP20 | CR106: =-CR20 | CT106: =-CT20 | CV106: =-CV20 | CX106: =-CX20 | CZ106: =-CZ20 | DB106: =-DB20 | DD106: =-DD20 | DF106: =-DF20 | DH106: =-DH20 | DJ106: =-DJ20 | DL106: =-DL20 | DN106: =-DN20 | DP106: =-DP20 | DR106: =-DR20 | DT106: =-DT20 | DV106: =-DV20 | DX106: =-DX20 | DZ106: =-DZ20 | EB106: =-EB20 | ED106: =-ED20 | EF106: =-EF20 | EH106: =-EH20 | EJ106: =-EJ20 | EL106: =-EL20 | EN106: =-EN20 | EP106: =-EP20 | ER106: =-ER20 | ET106: =-ET20 | EU106: =+BQ106-ET106 | EV106: =-EV20 | EW106: =-EW20 | EX106: =-EX20 | EY106: =-EY20 | FB106: =+FA106-EW106 | FC106: =+FB106/EW106 | FD106: =+FA106/T106 | FE106: =+FA106/U106
A107: Depreciation | B107: ='Raw financials'!B248 | C107: ='Raw financials'!C248 | D107: ='Raw financials'!D248 | E107: ='Raw financials'!E248 | F107: ='Raw financials'!F248 | G107: ='Raw financials'!G248 | H107: ='Raw financials'!H248 | I107: ='Raw financials'!I248 | ... T107: ='Raw financials'!T248 | U107: =-Driver!J102 | V107: =-Driver!K102 | W107: =-Driver!L102 | X107: =-Driver!M102 | Y107: =-Driver!N102 | Z107: =-Driver!O102 | AA107: =+U107-T107 | AB107: =+AA107/T107 | AC107: 837.24983 | AD107: =+X107-W107 | AE107: =+AD107/W107 | AG107: ='Raw financials'!AA248 | AH107: =+B107-AG107 | AI107: ='Raw financials'!AB248 | AJ107: =+C107-AI107 | AK107: ='Raw financials'!AC248 | AL107: =+D107-AK107 | AM107: ='Raw financials'!AD248 | AN107: =+E107-AM107 | AO107: ='Raw financials'!AE248 | AP107: =+F107-AO107 | AQ107: ='Raw financials'!AF248 | AR107: =+G107-AQ107 | AS107: ='Raw financials'!AG248 | AT107: =+H107-AS107 | AU107: ='Raw financials'!AH248 | AV107: =+I107-AU107 | AW107: ='Raw financials'!AI248 | AX107: =+J107-AW107 | AY107: ='Raw financials'!AJ248 | AZ107: =+K107-AY107 | BA107: ='Raw financials'!AK248 | BB107: =+L107-BA107 | BC107: ='Raw financials'!AL248 | BD107: =+M107-BC107 | BE107: ='Raw financials'!AM248 | BF107: =+N107-BE107 | BG107: ='Raw financials'!AN248 | BH107: =+O107-BG107 | BI107: ='Raw financials'!AO248 | BJ107: =+P107-BI107 | BK107: ='Raw financials'!AP248 | BL107: =+Q107-BK107 | BM107: ='Raw financials'!AQ248 | BN107: =+R107-BM107 | BO107: ='Raw financials'!AR248 | BP107: =+S107-BO107 | BQ107: ='Raw financials'!AS248 | BR107: =+T107-BQ107 | BT107: =+U107-BS107 | BU107: =BT107-BR107 | BV107: =BU107/BR107 | BW107: =+BT107/T107 | BX107: =+BT107/U107 | BZ107: =I107/2 | CA107: =J107/2 | CB107: =K107/2 | CD107: =K107/2 | CF107: =L107/2 | CH107: =M107/2 | CJ107: =N107/2 | CL107: =O107/2 | CN107: =P107/2 | CP107: =Q107/2 | CR107: =R107/2 | CT107: =S107/2 | CV107: =T107/2 | CX107: =U107/2 | CZ107: =V107/2 | DB107: =W107/2 | DD107: =X107/2 | DF107: =Y107/2 | DH107: =AF107/2 | DJ107: =AG107/2 | DL107: =AI107/2 | DN107: =AK107/2 | DP107: =AM107/2 | DR107: =AO107/2 | DT107: =AQ107/2 | DV107: =AS107/2 | DX107: =AU107/2 | DZ107: =AW107/2 | EB107: =AY107/2 | ED107: =BA107/2 | EF107: =BC107/2 | EH107: =BE107/2 | EJ107: =BG107/2 | EL107: =BI107/2 | EN107: =BK107/2 | EP107: =BM107/2 | ER107: =BO107/2 | ET107: =BQ107/2 | EU107: =+BQ107-ET107 | EV107: =BR107/2 | EW107: =+T107/4 | EX107: =+U107/4 | EY107: =+V107/4 | FB107: =+FA107-EW107 | FC107: =+FB107/EW107 | FD107: =+FA107/T107 | FE107: =+FA107/U107
A108: Amortization | B108: =SUM('Raw financials'!B249:B251) | C108: =SUM('Raw financials'!C249:C251) | D108: =SUM('Raw financials'!D249:D251) | E108: =SUM('Raw financials'!E249:E251) | F108: =SUM('Raw financials'!F249:F251) | G108: =SUM('Raw financials'!G249:G251) | H108: =SUM('Raw financials'!H249:H251) | I108: =SUM('Raw financials'!I249:I251) | ... T108: =SUM('Raw financials'!T249:T251) | U108: =-Driver!J119 | V108: =-Driver!K119 | W108: =-Driver!L119 | X108: =-Driver!M119 | Y108: =-Driver!N119 | Z108: =-Driver!O119 | AA108: =+U108-T108 | AB108: =+AA108/T108 | AC108: 296.41561 | AD108: =+X108-W108 | AE108: =+AD108/W108 | AG108: =SUM('Raw financials'!AA249:AA251) | AH108: =+B108-AG108 | AI108: =SUM('Raw financials'!AB249:AB251) | AJ108: =+C108-AI108 | AK108: =SUM('Raw financials'!AC249:AC251) | AL108: =+D108-AK108 | AM108: =SUM('Raw financials'!AD249:AD251) | AN108: =+E108-AM108 | AO108: =SUM('Raw financials'!AE249:AE251) | AP108: =+F108-AO108 | AQ108: =SUM('Raw financials'!AF249:AF251) | AR108: =+G108-AQ108 | AS108: =SUM('Raw financials'!AG249:AG251) | AT108: =+H108-AS108 | AU108: =SUM('Raw financials'!AH249:AH251) | AV108: =+I108-AU108 | AW108: =SUM('Raw financials'!AI249:AI251) | AX108: =+J108-AW108 | AY108: =SUM('Raw financials'!AJ249:AJ251) | AZ108: =+K108-AY108 | BA108: =SUM('Raw financials'!AK249:AK251) | BB108: =+L108-BA108 | BC108: =SUM('Raw financials'!AL249:AL251) | BD108: =+M108-BC108 | BE108: =SUM('Raw financials'!AM249:AM251) | BF108: =+N108-BE108 | BG108: =SUM('Raw financials'!AN249:AN251) | BH108: =+O108-BG108 | BI108: =SUM('Raw financials'!AO249:AO251) | BJ108: =+P108-BI108 | BK108: =SUM('Raw financials'!AP249:AP251) | BL108: =+Q108-BK108 | BM108: =SUM('Raw financials'!AQ249:AQ251) | BN108: =+R108-BM108 | BO108: =SUM('Raw financials'!AR249:AR251) | BP108: =+S108-BO108 | BQ108: =SUM('Raw financials'!AS249:AS251) | BR108: =+T108-BQ108 | BT108: =+U108-BS108 | BU108: =BT108-BR108 | BV108: =BU108/BR108 | BW108: =+BT108/T108 | BX108: =+BT108/U108 | BZ108: =I108/2 | CA108: =J108/2 | CB108: =K108/2 | CD108: =K108/2 | CF108: =L108/2 | CH108: =M108/2 | CJ108: =N108/2 | CL108: =O108/2 | CN108: =P108/2 | CP108: =Q108/2 | CR108: =R108/2 | CT108: =S108/2 | CV108: =T108/2 | CX108: =U108/2 | CZ108: =V108/2 | DB108: =W108/2 | DD108: =X108/2 | DF108: =Y108/2 | DH108: =AF108/2 | DJ108: =AG108/2 | DL108: =AI108/2 | DN108: =AK108/2 | DP108: =AM108/2 | DR108: =AO108/2 | DT108: =AQ108/2 | DV108: =AS108/2 | DX108: =AU108/2 | DZ108: =AW108/2 | EB108: =AY108/2 | ED108: =BA108/2 | EF108: =BC108/2 | EH108: =BE108/2 | EJ108: =BG108/2 | EL108: =BI108/2 | EN108: =BK108/2 | EP108: =BM108/2 | ER108: =BO108/2 | ET108: =BQ108/2 | EU108: =+BQ108-ET108 | EV108: =BR108/2 | EW108: =+T108/4 | EX108: =+U108/4 | EY108: =+V108/4 | FB108: =+FA108-EW108 | FC108: =+FB108/EW108 | FD108: =+FA108/T108 | FE108: =+FA108/U108
A109: Disposal (gain)/losses | B109: =SUM('Raw financials'!B254:B256) | C109: =SUM('Raw financials'!C254:C256) | D109: =SUM('Raw financials'!D254:D256) | E109: =SUM('Raw financials'!E254:E256) | F109: =SUM('Raw financials'!F254:F256) | G109: =SUM('Raw financials'!G254:G256) | H109: =SUM('Raw financials'!H254:H256) | I109: =SUM('Raw financials'!I254:I256) | ... T109: =SUM('Raw financials'!T254:T256) | U109: 0 | V109: 0 | W109: 0 | X109: 0 | Y109: 0 | Z109: 0 | AA109: =+U109-T109 | AB109: =+AA109/T109 | AC109: 0 | AD109: =+X109-W109 | AE109: =+AD109/W109 | AG109: =SUM('Raw financials'!AA254:AA256) | AH109: =+B109-AG109 | AI109: =SUM('Raw financials'!AB254:AB256) | AJ109: =+C109-AI109 | AK109: =SUM('Raw financials'!AC254:AC256) | AL109: =+D109-AK109 | AM109: =SUM('Raw financials'!AD254:AD256) | AN109: =+E109-AM109 | AO109: =SUM('Raw financials'!AE254:AE256) | AP109: =+F109-AO109 | AQ109: =SUM('Raw financials'!AF254:AF256) | AR109: =+G109-AQ109 | AS109: =SUM('Raw financials'!AG254:AG256) | AT109: =+H109-AS109 | AU109: =SUM('Raw financials'!AH254:AH256) | AV109: =+I109-AU109 | AW109: =SUM('Raw financials'!AI254:AI256) | AX109: =+J109-AW109 | AY109: =SUM('Raw financials'!AJ254:AJ256) | AZ109: =+K109-AY109 | BA109: =SUM('Raw financials'!AK254:AK256) | BB109: =+L109-BA109 | BC109: =SUM('Raw financials'!AL254:AL256) | BD109: =+M109-BC109 | BE109: =SUM('Raw financials'!AM254:AM256) | BF109: =+N109-BE109 | BG109: =SUM('Raw financials'!AN254:AN256) | BH109: =+O109-BG109 | BI109: =SUM('Raw financials'!AO254:AO256) | BJ109: =+P109-BI109 | BK109: =SUM('Raw financials'!AP254:AP256) | BL109: =+Q109-BK109 | BM109: =SUM('Raw financials'!AQ254:AQ256) | BN109: =+R109-BM109 | BO109: =SUM('Raw financials'!AR254:AR256) | BP109: =+S109-BO109 | BQ109: =SUM('Raw financials'!AS254:AS256) | BR109: =+T109-BQ109 | BT109: =+U109-BS109 | BU109: =BT109-BR109 | BV109: =BU109/BR109 | BW109: =+BT109/T109 | BX109: =+BT109/U109 | BZ109: =I109/2 | CA109: =J109/2 | CB109: =K109/2 | CD109: =K109/2 | CF109: =L109/2 | CH109: =M109/2 | CJ109: =N109/2 | CL109: =O109/2 | CN109: =P109/2 | CP109: =Q109/2 | CR109: =R109/2 | CT109: =S109/2 | CV109: =T109/2 | CX109: =U109/2 | CZ109: =V109/2 | DB109: =W109/2 | DD109: =X109/2 | DF109: =Y109/2 | DH109: =AF109/2 | DJ109: =AG109/2 | DL109: =AI109/2 | DN109: =AK109/2 | DP109: =AM109/2 | DR109: =AO109/2 | DT109: =AQ109/2 | DV109: =AS109/2 | DX109: =AU109/2 | DZ109: =AW109/2 | EB109: =AY109/2 | ED109: =BA109/2 | EF109: =BC109/2 | EH109: =BE109/2 | EJ109: =BG109/2 | EL109: =BI109/2 | EN109: =BK109/2 | EP109: =BM109/2 | ER109: =BO109/2 | ET109: =BQ109/2 | EU109: =+BQ109-ET109 | EV109: =BR109/2 | EW109: =+T109/4 | EX109: =+U109/4 | EY109: =+V109/4 | FB109: =+FA109-EW109 | FC109: =+FB109/EW109 | FD109: =+FA109/T109 | FE109: =+FA109/U109
A110: Net finance costs ("-" gains) | B110: ='Raw financials'!B257 | C110: ='Raw financials'!C257 | D110: ='Raw financials'!D257 | E110: ='Raw financials'!E257 | F110: ='Raw financials'!F257 | G110: ='Raw financials'!G257 | H110: ='Raw financials'!H257 | I110: ='Raw financials'!I257 | ... T110: ='Raw financials'!T257 | U110: =-U17 | V110: =-V17 | W110: =-W17 | X110: =-X17 | Y110: =-Y17 | Z110: =-Z17 | AA110: =+U110-T110 | AB110: =+AA110/T110 | AC110: 28.840856 | AD110: =+X110-W110 | AE110: =+AD110/W110 | AG110: ='Raw financials'!AA257 | AH110: =+B110-AG110 | AI110: ='Raw financials'!AB257 | AJ110: =+C110-AI110 | AK110: ='Raw financials'!AC257 | AL110: =+D110-AK110 | AM110: ='Raw financials'!AD257 | AN110: =+E110-AM110 | AO110: ='Raw financials'!AE257 | AP110: =+F110-AO110 | AQ110: ='Raw financials'!AF257 | AR110: =+G110-AQ110 | AS110: ='Raw financials'!AG257 | AT110: =+H110-AS110 | AU110: ='Raw financials'!AH257 | AV110: =+I110-AU110 | AW110: ='Raw financials'!AI257 | AX110: =+J110-AW110 | AY110: ='Raw financials'!AJ257 | AZ110: =+K110-AY110 | BA110: ='Raw financials'!AK257 | BB110: =+L110-BA110 | BC110: ='Raw financials'!AL257 | BD110: =+M110-BC110 | BE110: ='Raw financials'!AM257 | BF110: =+N110-BE110 | BG110: ='Raw financials'!AN257 | BH110: =+O110-BG110 | BI110: ='Raw financials'!AO257 | BJ110: =+P110-BI110 | BK110: ='Raw financials'!AP257 | BL110: =+Q110-BK110 | BM110: ='Raw financials'!AQ257 | BN110: =+R110-BM110 | BO110: ='Raw financials'!AR257 | BP110: =+S110-BO110 | BQ110: ='Raw financials'!AS257 | BR110: =+T110-BQ110 | BT110: =+U110-BS110 | BU110: =BT110-BR110 | BV110: =BU110/BR110 | BW110: =+BT110/T110 | BX110: =+BT110/U110 | BZ110: =-BZ125 | CA110: =-CA125 | CB110: =-CB125 | CD110: =-CD125 | CF110: =-CF125 | CH110: =-CH125 | CJ110: =-CJ125 | CL110: =-CL125 | CN110: =-CN125 | CP110: =-CP125 | CR110: =-CR125 | CT110: =-CT125 | CV110: =-CV125 | CX110: =-CX125 | CZ110: =-CZ125 | DB110: =-DB125 | DD110: =-DD125 | DF110: =-DF125 | DH110: =-DH125 | DJ110: =-DJ125 | DL110: =-DL125 | DN110: =-DN125 | DP110: =-DP125 | DR110: =-DR125 | DT110: =-DT125 | DV110: =-DV125 | DX110: =-DX125 | DZ110: =-DZ125 | EB110: =-EB125 | ED110: =-ED125 | EF110: =-EF125 | EH110: =-EH125 | EJ110: =-EJ125 | EL110: =-EL125 | EN110: =-EN125 | EP110: =-EP125 | ER110: =-ER125 | ET110: =-ET125 | EU110: =+BQ110-ET110 | EV110: =-EV125 | EW110: =-EW125 | EX110: =-EX125 | EY110: =-EY125 | FB110: =+FA110-EW110 | FC110: =+FB110/EW110 | FD110: =+FA110/T110 | FE110: =+FA110/U110
...

Sheet Driver
AF1: H125
A2: Rmb m | B2: 2017 | C2: 2018 | D2: 2019 | E2: 2020 | F2: =E2+1 | G2: =F2+1 | H2: =G2+1 | I2: =H2+1 | J2: =I2+1 | K2: =J2+1 | L2: =K2+1 | M2: =L2+1 | ... O2: =N2+1 | P2: 25-28 | AB2: H124 | AC2: H224 | AD2: H125 | AE2: H225E | AF2: Change | AG2: Change % | AH2: % of last year | AI2: % of FY
A3: P&L drivers
A4: Revenue
A5: By product | L5: =+L7+4000 | M5: =+M7+6000 | N5: =7500+N7
A6: High-efficient clean energy equipment | E6: 11152.33 | F6: 12786.98 | G6: 14684.57 | H6: 20589.29 | I6: 28358.2 | J6: =+J7+J8+J9 | K6: =+K7+K8+K9 | L6: =+L7+L8+L9 | M6: =+M7+M8+M9 | N6: =+N7+N8+N9 | O6: =+O7+O8+O9 | P6: =(M6/J6)^(1/3)-1 | AB6: 14065.2 | AC6: =I6-AB6 | AE6: =J6-AD6 | AF6: =AD6-AB6 | AG6: =AF6/AB6 | AH6: =AB6/I6 | AI6: =AD6/J6
A7: Gas Turbine | E7: 2019 | F7: 1734 | G7: 1831 | H7: 3789.43 | I7: 7258 | J7: =+I7*(1+U18) | K7: =+J7*(1+V18) | L7: =+K7*(1+W18) | M7: =+L7*(1+X18) | N7: =+M7*(1+Y18) | O7: =+N7*(1+Z18) | P7: =(M7/J7)^(1/3)-1 | AB7: 3607.4332 | AC7: =I7-AB7 | AE7: =J7-AD7 | AF7: =AD7-AB7 | AG7: =AF7/AB7 | AH7: =AB7/I7 | AI7: =AD7/J7
A8: Nuclear power equipment | B8: 2695.7011 | C8: 2390.1025 | D8: 2080.4074 | E8: 1805 | F8: 2229 | G8: 2057 | H8: 2902.56 | I8: 4876.71 | J8: =+I8*(1+U19) | K8: =+J8*(1+V19) | L8: =+K8*(1+W19) | M8: =+L8*(1+X19) | N8: =+M8*(1+Y19) | O8: =+N8*(1+Z19) | P8: =(M8/J8)^(1/3)-1 | AB8: 1935.5381 | AC8: =I8-AB8 | AE8: =J8-AD8 | AF8: =AD8-AB8 | AG8: =AF8/AB8 | AH8: =AB8/I8 | AI8: =AD8/J8
A9: Thermal power equipment | E9: 7328 | F9: 8824 | G9: =G6-G7-G8 | H9: =H6-H7-H8 | I9: =I6-I7-I8 | J9: =+I9*(1+U20) | K9: =+J9*(1+V20) | L9: =+K9*(1+W20) | M9: =+L9*(1+X20) | N9: =+M9*(1+Y20) | O9: =+N9*(1+Z20) | P9: =(M9/J9)^(1/3)-1 | AB9: =AB6-AB7-AB8 | AC9: =I9-AB9 | AE9: =J9-AD9 | AF9: =AD9-AB9 | AG9: =AF9/AB9 | AH9: =AB9/I9 | AI9: =AD9/J9
A10: Wind | E10: =10085.17-E11 | F10: =15138.46-F11 | G10: =14913.93-G11 | H10: =13837.89-H11 | I10: =16602.97-I11 | J10: =+I10*(1+U21) | K10: =+J10*(1+V21) | L10: =+K10*(1+W21) | M10: =+L10*(1+X21) | N10: =+M10*(1+Y21) | O10: =+N10*(1+Z21) | P10: =(M10/J10)^(1/3)-1 | AB10: =8215.03185567-AB11 | AC10: =I10-AB10 | AE10: =J10-AD10 | AF10: =AD10-AB10 | AG10: =AF10/AB10 | AH10: =AB10/I10 | AI10: =AD10/J10
A11: Hydro | E11: 2481.193 | F11: 2476.2423 | G11: 2488.9778 | H11: 2310.8088 | I11: 2955.3657 | J11: =+I11*(1+U22) | K11: =+J11*(1+V22) | L11: =+K11*(1+W22) | M11: =+L11*(1+X22) | N11: =+M11*(1+Y22) | O11: =+N11*(1+Z22) | P11: =(M11/J11)^(1/3)-1 | AB11: 1295.8126 | AC11: =I11-AB11 | AE11: =J11-AD11 | AF11: =AD11-AB11 | AG11: =AF11/AB11 | AH11: =AB11/I11 | AI11: =AD11/J11
A12: Modern manufacturing service industry (mostly O&M maintenance services) | E12: 4910.2468 | F12: 3963.3286 | G12: 4238.0845 | H12: 5383.5413 | I12: 7564.4065 | J12: =+I12*(1+U23) | K12: =+J12*(1+V23) | L12: =+K12*(1+W23) | M12: =+L12*(1+X23) | N12: =+M12*(1+Y23) | O12: =+N12*(1+Z23) | P12: =(M12/J12)^(1/3)-1 | AB12: 3521.0525 | AC12: =I12-AB12 | AE12: =J12-AD12 | AF12: =AD12-AB12 | AG12: =AF12/AB12 | AH12: =AB12/I12 | AI12: =AD12/J12
A13: Others (Engineering and others) | E13: =+E14-SUM(E6,E10:E12) | F13: =+F14-SUM(F6,F10:F12) | G13: =+G14-SUM(G6,G10:G12) | H13: =+H14-SUM(H6,H10:H12) | I13: =+I14-SUM(I6,I10:I12) | J13: =+I13*(1+U24) | K13: =+J13*(1+V24) | L13: =+K13*(1+W24) | M13: =+L13*(1+X24) | N13: =+M13*(1+Y24) | O13: =+N13*(1+Z24) | P13: =(M13/J13)^(1/3)-1 | AB13: =+AB14-SUM(AB6,AB10:AB12) | AC13: =I13-AB13 | AE13: =J13-AD13 | AF13: =AD13-AB13 | AG13: =AF13/AB13 | AH13: =AB13/I13 | AI13: =AD13/J13
A14: Total | E14: =Model!P4 | F14: =Model!Q4 | G14: =Model!R4 | H14: =Model!S4 | I14: =Model!T4 | J14: =+SUM(J6,J10:J13) | K14: =+SUM(K6,K10:K13) | L14: =+SUM(L6,L10:L13) | M14: =+SUM(M6,M10:M13) | N14: =+SUM(N6,N10:N13) | O14: =+SUM(O6,O10:O13) | P14: =(M14/J14)^(1/3)-1 | AB14: =Model!BQ4 | AC14: =I14-AB14 | AE14: =J14-AD14 | AF14: =AD14-AB14 | AG14: =AF14/AB14 | AH14: =AB14/I14 | AI14: =AD14/J14
A16: YoY growth
A17: =+A6 | F17: =+F6/E6-1 | G17: =+G6/F6-1 | H17: =+H6/G6-1 | I17: =+I6/H6-1 | J17: =+J6/I6-1 | K17: =+K6/J6-1 | L17: =+L6/K6-1 | M17: =+M6/L6-1 | ... O17: =+O6/N6-1 | U17: do not delete | AE17: =+AE6/AC6-1
A18: =A7 | F18: =+F7/E7-1 | G18: =+G7/F7-1 | H18: =+H7/G7-1 | I18: =+I7/H7-1 | J18: 0.1 | K18: 0.1 | L18: 0.55546778 | M18: 0.21712689 | N18: 0.15413066 | O18: =++N18 | P18: refer to our power equipment database | R18: 0.1 | U18: =J18+Sensitvity!J26 | V18: =K18+Sensitvity!A30 | W18: =L18+Sensitvity!A33 | X18: =M18+Sensitvity!A36 | Y18: =N18+Sensitvity!A39 | Z18: =O18+Sensitvity!A42 | AE18: =+AE7/AC7-1
A19: =A8 | F19: =+F8/E8-1 | G19: =+G8/F8-1 | H19: =+H8/G8-1 | I19: =+I8/H8-1 | J19: 0.3 | K19: =J19 | L19: 0.25 | M19: =L19 | N19: =M19 | O19: =+N19 | U19: =J19+Sensitvity!J27 | V19: =K19+Sensitvity!J30 | W19: =L19+Sensitvity!J33 | X19: =M19+Sensitvity!J36 | Y19: =N19+Sensitvity!J39 | Z19: =O19+Sensitvity!J42 | AE19: =+AE8/AC8-1
A20: =A9 | F20: =+F9/E9-1 | G20: =+G9/F9-1 | H20: =+H9/G9-1 | I20: =+I9/H9-1 | J20: 0.05 | K20: 0.05 | L20: =K20 | M20: =L20 | N20: =M20 | O20: =+N20 | U20: =J20+Sensitvity!S27 | V20: =K20+Sensitvity!S30 | W20: =L20+Sensitvity!S33 | X20: =M20+Sensitvity!S36 | Y20: =N20+Sensitvity!S39 | Z20: =O20+Sensitvity!S42 | AE20: =+AE9/AC9-1
A21: =+A10 | F21: =+F10/E10-1 | G21: =+G10/F10-1 | H21: =+H10/G10-1 | I21: =+I10/H10-1 | J21: 0.4 | K21: 0.1 | L21: =K21+5% | M21: =L21 | N21: =M21 | O21: =+N21 | U21: =J21+Sensitvity!AB27 | V21: =K21+Sensitvity!AB30 | W21: =L21+Sensitvity!AB33 | X21: =M21+Sensitvity!AB36 | Y21: =N21+Sensitvity!AB39 | Z21: =O21+Sensitvity!AB42 | AE21: =+AE10/AC10-1
A22: =+A11 | F22: =+F11/E11-1 | G22: =+G11/F11-1 | H22: =+H11/G11-1 | I22: =+I11/H11-1 | J22: 0.1 | K22: =J22 | L22: =K22 | M22: =L22 | N22: =M22 | O22: =+N22 | P22: Yarlung Zangbo hydropower project start to contribute to revenue from 2030-35 | U22: =J22+Sensitvity!AK27 | V22: =K22+Sensitvity!AK30 | W22: =L22+Sensitvity!AK33 | X22: =M22+Sensitvity!AK36 | Y22: =N22+Sensitvity!AK39 | Z22: =O22+Sensitvity!AK42 | AE22: =+AE11/AC11-1
A23: =+A12 | F23: =+F12/E12-1 | G23: =+G12/F12-1 | H23: =+H12/G12-1 | I23: =+I12/H12-1 | J23: 0.31603342 | K23: 0.27583367 | L23: 0.25236963 | M23: 0.21974603 | N23: 0.19625775 | O23: =+N23 | P23: refer to our power equipment database | U23: =J23+Sensitvity!BC27 | V23: =K23+Sensitvity!BC30 | W23: =L23+Sensitvity!BC33 | X23: =M23+Sensitvity!BC36 | Y23: =N23+Sensitvity!BC39 | Z23: =O23+Sensitvity!BC42 | AE23: =+AE12/AC12-1
A24: =+A13 | F24: =+F13/E13-1 | G24: =+G13/F13-1 | H24: =+H13/G13-1 | I24: =+I13/H13-1 | J24: 0.03 | K24: =J24 | L24: =K24 | M24: =L24 | N24: =M24 | O24: =+N24 | P24: organic growth | U24: =J24+Sensitvity!AT27 | V24: =K24+Sensitvity!AT30 | W24: =L24+Sensitvity!AT33 | X24: =M24+Sensitvity!AT36 | Y24: =N24+Sensitvity!AT39 | Z24: =O24+Sensitvity!AT42 | AE24: =+AE13/AC13-1
A25: Total | F25: =F14/E14-1 | G25: =G14/F14-1 | H25: =H14/G14-1 | I25: =I14/H14-1 | J25: =J14/I14-1 | K25: =K14/J14-1 | L25: =L14/K14-1 | M25: =M14/L14-1 | ... O25: =O14/N14-1 | AE25: =AE14/AC14-1
A27: Rev % of total
A28: =A17 | E28: =E6/E$14 | F28: =F6/F$14 | G28: =G6/G$14 | H28: =H6/H$14 | I28: =I6/I$14 | J28: =J6/J$14 | K28: =K6/K$14 | L28: =L6/L$14 | ... O28: =O6/O$14 | AB28: =AB6/AB$14 | AC28: =AC6/AC$14 | AE28: =AE6/AE$14
A29: =A7 | E29: =E7/E$14 | F29: =F7/F$14 | G29: =G7/G$14 | H29: =H7/H$14 | I29: =I7/I$14 | J29: =J7/J$14 | K29: =K7/K$14 | L29: =L7/L$14 | ... O29: =O7/O$14 | AB29: =AB7/AB$14 | AC29: =AC7/AC$14 | AE29: =AE7/AE$14
A30: =A8 | E30: =E8/E$14 | F30: =F8/F$14 | G30: =G8/G$14 | H30: =H8/H$14 | I30: =I8/I$14 | J30: =J8/J$14 | K30: =K8/K$14 | L30: =L8/L$14 | ... O30: =O8/O$14 | AB30: =AB8/AB$14 | AC30: =AC8/AC$14 | AE30: =AE8/AE$14
A31: =A9 | E31: =E9/E$14 | F31: =F9/F$14 | G31: =G9/G$14 | H31: =H9/H$14 | I31: =I9/I$14 | J31: =J9/J$14 | K31: =K9/K$14 | L31: =L9/L$14 | ... O31: =O9/O$14 | AB31: =AB9/AB$14 | AC31: =AC9/AC$14 | AE31: =AE9/AE$14
A32: =A21 | E32: =E10/E$14 | F32: =F10/F$14 | G32: =G10/G$14 | H32: =H10/H$14 | I32: =I10/I$14 | J32: =J10/J$14 | K32: =K10/K$14 | L32: =L10/L$14 | ... O32: =O10/O$14 | AB32: =AB10/AB$14 | AC32: =AC10/AC$14 | AE32: =AE10/AE$14
A33: =A22 | E33: =E11/E$14 | F33: =F11/F$14 | G33: =G11/G$14 | H33: =H11/H$14 | I33: =I11/I$14 | J33: =J11/J$14 | K33: =K11/K$14 | L33: =L11/L$14 | ... O33: =O11/O$14 | AB33: =AB11/AB$14 | AC33: =AC11/AC$14 | AE33: =AE11/AE$14
A34: =A23 | E34: =E12/E$14 | F34: =F12/F$14 | G34: =G12/G$14 | H34: =H12/H$14 | I34: =I12/I$14 | J34: =J12/J$14 | K34: =K12/K$14 | L34: =L12/L$14 | ... O34: =O12/O$14 | AB34: =AB12/AB$14 | AC34: =AC12/AC$14 | AE34: =AE12/AE$14
A35: =A24 | E35: =E13/E$14 | F35: =F13/F$14 | G35: =G13/G$14 | H35: =H13/H$14 | I35: =I13/I$14 | J35: =J13/J$14 | K35: =K13/K$14 | L35: =L13/L$14 | ... O35: =O13/O$14 | AB35: =AB13/AB$14 | AC35: =AC13/AC$14 | AE35: =AE13/AE$14
A36: Total | E36: =SUM(E28,E32:E35) | F36: =SUM(F28,F32:F35) | G36: =SUM(G28,G32:G35) | H36: =SUM(H28,H32:H35) | I36: =SUM(I28,I32:I35) | J36: =SUM(J28,J32:J35) | K36: =SUM(K28,K32:K35) | L36: =SUM(L28,L32:L35) | ... O36: =SUM(O28,O32:O35) | AB36: =SUM(AB28,AB32:AB35) | AC36: =SUM(AC28,AC32:AC35) | AE36: =SUM(AE28,AE32:AE35)
A38: COGS
A39: =+A6 | E39: -8524.26 | F39: -10008.95 | G39: -11579.67 | H39: -16198.62 | I39: -23607.8 | J39: =J50-J6 | K39: =K50-K6 | L39: =L50-L6 | M39: =M50-M6 | N39: =N50-N6 | O39: =O50-O6 | AB39: -11892.396 | AC39: =I39-AB39 | AE39: =J39-AD39 | AF39: =AD39-AB39 | AG39: =AF39/AB39 | AH39: =AB39/I39 | AI39: =AD39/J39
A40: =A7 | E40: =E51-E7 | F40: =F51-F7 | G40: =G51-G7 | H40: -3329.07 | I40: -6592.66 | J40: =J51-J7 | K40: =K51-K7 | L40: =L51-L7 | M40: =M51-M7 | N40: =N51-N7 | O40: =O51-O7 | AB40: -3201.9569 | AC40: =I40-AB40 | AE40: =J40-AD40 | AF40: =AD40-AB40 | AG40: =AF40/AB40 | AH40: =AB40/I40 | AI40: =AD40/J40
A41: =A8 | E41: =E52-E8 | F41: =F52-F8 | G41: =G52-G8 | H41: -2228.61 | I41: -3704.41 | J41: =J52-J8 | K41: =K52-K8 | L41: =L52-L8 | M41: =M52-M8 | N41: =N52-N8 | O41: =O52-O8 | AB41: -1497.3375 | AC41: =I41-AB41 | AE41: =J41-AD41 | AF41: =AD41-AB41 | AG41: =AF41/AB41 | AH41: =AB41/I41 | AI41: =AD41/J41
A42: =A9 | E42: =E53-E9 | F42: =F53-F9 | G42: =G53-G9 | H42: =H39-H40-H41 | I42: =I39-I40-I41 | J42: =J53-J9 | K42: =K53-K9 | L42: =L53-L9 | M42: =M53-M9 | N42: =N53-N9 | O42: =O53-O9 | AB42: =AB39-AB40-AB41 | AC42: =I42-AB42 | AE42: =J42-AD42 | AF42: =AD42-AB42 | AG42: =AF42/AB42 | AH42: =AB42/I42 | AI42: =AD42/J42
A43: =+A10 | E43: =-8646.79-E44 | F43: =-12970.46-F44 | G43: =-12965.12-G44 | H43: =-12198.91-H44 | I43: =-15977.7-I44 | J43: =J54-J10 | K43: =K54-K10 | L43: =L54-L10 | M43: =M54-M10 | N43: =N54-N10 | O43: =O54-O10 | AB43: =-7780.15489772-AB44 | AC43: =I43-AB43 | AE43: =J43-AD43 | AF43: =AD43-AB43 | AG43: =AF43/AB43 | AH43: =AB43/I43 | AI43: =AD43/J43
A44: =+A11 | E44: -2067.143 | F44: -2017.0697 | G44: -1955.0653 | H44: -1896.6446 | I44: -2399.2133 | J44: =J55-J11 | K44: =K55-K11 | L44: =L55-L11 | M44: =M55-M11 | N44: =N55-N11 | O44: =O55-O11 | AB44: -1103.8784 | AC44: =I44-AB44 | AE44: =J44-AD44 | AF44: =AD44-AB44 | AG44: =AF44/AB44 | AH44: =AB44/I44 | AI44: =AD44/J44
A45: =+A12 | E45: -2714.2675 | F45: -2120.8605 | G45: -1935.8185 | H45: -2696.1923 | I45: -3902.3518 | J45: =J56-J12 | K45: =K56-K12 | L45: =L56-L12 | M45: =M56-M12 | N45: =N56-N12 | O45: =O56-O12 | AB45: -1846.6853 | AC45: =I45-AB45 | AE45: =J45-AD45 | AF45: =AD45-AB45 | AG45: =AF45/AB45 | AH45: =AB45/I45 | AI45: =AD45/J45
A46: =+A13 | E46: =+E47-SUM(E39,E43:E45) | F46: =+F47-SUM(F39,F43:F45) | G46: =+G47-SUM(G39,G43:G45) | H46: =+H47-SUM(H39,H43:H45) | I46: =+I47-SUM(I39,I43:I45) | J46: =J57-J13 | K46: =K57-K13 | L46: =L57-L13 | M46: =M57-M13 | N46: =N57-N13 | O46: =O57-O13 | AB46: =+AB47-SUM(AB39,AB43:AB45) | AC46: =I46-AB46 | AE46: =J46-AD46 | AF46: =AD46-AB46 | AG46: =AF46/AB46 | AH46: =AB46/I46 | AI46: =AD46/J46
A47: Total | E47: =Model!P6 | F47: =Model!Q6 | G47: =Model!R6 | H47: =Model!S6 | I47: =Model!T6 | J47: =SUM(J39,J43:J46) | K47: =SUM(K39,K43:K46) | L47: =SUM(L39,L43:L46) | M47: =SUM(M39,M43:M46) | N47: =SUM(N39,N43:N46) | O47: =SUM(O39,O43:O46) | AB47: =Model!BQ6 | AC47: =I47-AB47 | AE47: =J47-AD47 | AF47: =AD47-AB47 | AG47: =AF47/AB47 | AH47: =AB47/I47 | AI47: =AD47/J47
A49: Gross profit
A50: =+A6 | E50: =E6+E39 | F50: =F6+F39 | G50: =G6+G39 | H50: =H6+H39 | I50: =I6+I39 | J50: =SUM(J51:J53) | K50: =SUM(K51:K53) | L50: =SUM(L51:L53) | M50: =SUM(M51:M53) | N50: =SUM(N51:N53) | O50: =SUM(O51:O53) | P50: =J50/I50-1 | AB50: =AB6+AB39 | AC50: =AC6+AC39 | AE50: =AE6+AE39 | AF50: =AD50-AB50 | AG50: =AF50/AB50 | AH50: =AB50/I50 | AI50: =AD50/J50
A51: =+A7 | E51: 330 | F51: 333 | G51: -9 | H51: =H7+H40 | I51: =I7+I40 | J51: =J7*U73 | K51: =K7*V73 | L51: =L7*W73 | M51: =M7*X73 | N51: =N7*Y73 | O51: =O7*Z73 | P51: =J51/I51-1 | AB51: =AB7+AB40 | AC51: =AC7+AC40 | AE51: =AE7+AE40 | AF51: =AD51-AB51 | AG51: =AF51/AB51 | AH51: =AB51/I51 | AI51: =AD51/J51
A52: =+A8 | E52: 359 | F52: 578 | G52: 672 | H52: =H8+H41 | I52: =I8+I41 | J52: =J8*U74 | K52: =K8*V74 | L52: =L8*W74 | M52: =M8*X74 | N52: =N8*Y74 | O52: =O8*Z74 | P52: =J52/I52-1 | AB52: =AB8+AB41 | AC52: =AC8+AC41 | AE52: =AE8+AE41 | AF52: =AD52-AB52 | AG52: =AF52/AB52 | AH52: =AB52/I52 | AI52: =AD52/J52
A53: =+A9 | E53: 1939 | F53: 1867 | G53: 2442 | H53: =H9+H42 | I53: =I9+I42 | J53: =J9*U75 | K53: =K9*V75 | L53: =L9*W75 | M53: =M9*X75 | N53: =N9*Y75 | O53: =O9*Z75 | P53: =J53/I53-1 | AB53: =AB9+AB42 | AC53: =AC9+AC42 | AE53: =AE9+AE42 | AF53: =AD53-AB53 | AG53: =AF53/AB53 | AH53: =AB53/I53 | AI53: =AD53/J53
A54: =+A10 | E54: =E10+E43 | F54: =F10+F43 | G54: =G10+G43 | H54: =H10+H43 | I54: =I10+I43 | J54: =J10*U76 | K54: =K10*V76 | L54: =L10*W76 | M54: =M10*X76 | N54: =N10*Y76 | O54: =O10*Z76 | P54: =J54/I54-1 | AB54: =AB10+AB43 | AC54: =AC10+AC43 | AE54: =AE10+AE43 | AF54: =AD54-AB54 | AG54: =AF54/AB54 | AH54: =AB54/I54 | AI54: =AD54/J54
