Workbook
Name \A: #REF!
Name _1_0cu08.PeriodMonthC: #REF!
Name _2_0cu12.PeriodT: #REF!
Name _3_0cu13.PeriodY: #REF!
Name _4_0cu14.FinancialY: #REF!
Name _5_0cu43.ActualForecast: #REF!
Name _6_0cu57.Prelim: #REF!
Name _Model_Path: "\\ubsprod.msad.ubs.net\GroupShares\GLOBAL\IB_RESEARCH_HKG\POWER\Models\Archives\CLP 84.xlsx"
Name a: #REF!
Name Additions: #REF!
Name ASSOCBAL: #REF!
Name Attributable_To_Ordinary_Shareholders: #REF!
Name Average_Shares_In_Issue: #REF!
Name b: #REF!
Name Bal_Sheet: #REF!
Name Capacity_Reserve: #REF!
Name capex: #REF!
Name capexf: #REF!
Name Capital_Employed: #REF!
Name Capital_Expenditure: #REF!
Name Cash_EPS: #REF!
Name Cash_Flow: #REF!
Name CastlePeak_Bal_Sht: #REF!
Name Combined_Bal_Sht: #REF!
Name COMPOUND_GROWTH: #REF!
Name costs: #REF!
Name cu20.ItemTypeCategory: #REF!
Name d: #REF!
Name DATES: #REF!
Name DB: "WIREHKPROD"
Name debt: #REF!
Name Depreciation_Adjustment: #REF!
Name Depreciation_Amortisation: #REF!
Name DES: #REF!
Name dev_fund: #REF!
Name Dividend_Declar: #REF!
Name Dividend_Tax_Credit: #REF!
Name Dividends_Paid: #REF!
Name earnings: #REF!
Name EPS_FRS3: #REF!
Name EPS_Fully_Diluted: #REF!
Name EPS_Pre_Exceptional: #REF!
Name Extraordinaries: #REF!
Name F.1990: #REF!
Name F.1990.09: #REF!
Name F.1990.12: #REF!
Name F.1991: #REF!
Name F.1991.09: #REF!
Name F.1991.12: #REF!
Name F.1992: #REF!
Name F.1992.12: #REF!
Name F.1993: #REF!
Name F.1993.12: #REF!
Name F.1994: #REF!
Name F.1994.12: #REF!
Name F.1995: #REF!
Name F.1995.12: #REF!
Name F.1996: #REF!
Name F.1996.12: #REF!
Name F.1997: #REF!

Sheet VA-Disclaimer

Sheet DCF
A2: Key Assumptions
A3: Hong Kong risk-free rate | B3: 0.0372 | D3: PT | E3: =S37 | R3: Terminal value and NPV
A4: Hong Kong equity risk premium | B4: 0.05 | D4: Current price | E4: 67.25 | R4: WACC | S4: =B11
A5: CLP beta (X) | B5: 0.56 | D5: Upside | E5: =E3/E4-1 | R5: Terminal return on capital | S5: =+B13
A6: CLP cost of equity (%) | B6: =B3+B4*B5 | R6: Terminal growth rate | S6: =B12
A7: CLP pre tax cost of debt (%) | B7: 0.03 | V7: Check
A8: Effective tax rate (%) | B8: 0.25 | R8: NOPAT Multiple | S8: =(S5-S6)/(S5*(S4-S6)) | V8: =+S8-S23
A9: CLP after tax cost of debt (%) | B9: =B7*(1-B8)
A10: L/T debt to total capital ratio (%) | B10: 0.175 | R10: In 2030 - Group
A11: Discount Rate (%) | B11: =B6*(1-B10)+B9*B10 | R11: EBIT, core | S11: =Final!AN15
A12: Long-term growth rate | B12: 0.02 | R12: Adjusted tax rate | S12: =-Final!AN23/(Final!AN22-Final!AN18-Final!AN19)
A13: Implied terminal ROIC | B13: =S21 | R13: NOPAT | S13: =+S11*(1-S12)
R14: Invested capital in 2029 | S14: =+N77
R15: Invested capital in 2030 | S15: =+O77
A16: Explicit cash flows forecasts | R16: Average invested capital | S16: =AVERAGE(S14:S15)
R17: Return on capital | S17: =S13/S16
A18: HK$ Million | B18: =Final!AA2 | C18: =Final!AB2 | D18: =Final!AC2 | E18: =Final!AD2 | F18: =Final!AE2 | G18: =Final!AF2 | H18: =Final!AG2 | I18: =Final!AH2 | ... O18: =Final!AN2
A19: Years ahead | B19: 0 | C19: 0 | D19: 0 | E19: 0 | F19: 0 | G19: 0 | H19: 0 | I19: 0 | J19: 0 | K19: 0 | L19: =K19+1 | M19: =L19+1 | N19: =M19+1 | O19: =N19+1 | R19: Terminal period - Group
A20: Discount factor | B20: =1/((1+$B11)^B19) | C20: =1/((1+$B11)^C19) | D20: =1/((1+$B11)^D19) | E20: =1/((1+$B11)^E19) | F20: =1/((1+$B11)^F19) | G20: =1/((1+$B11)^G19) | H20: =1/((1+$B11)^H19) | I20: =1/((1+$B11)^I19) | ... O20: =1/((1+$B11)^O19) | R20: 1st year avg invested capital | S20: =+AVERAGE(N77:O77)*(1+$B$12)
R21: Implied terminal return on capital | S21: =+S22/S20
A22: Net cash flows from operations | B22: =Final!AA121 | C22: =Final!AB121 | D22: =Final!AC121 | E22: =Final!AD121 | F22: =Final!AE121 | G22: =Final!AF121 | H22: =Final!AG121 | I22: =Final!AH121 | ... O22: =Final!AN121 | R22: 1st year NOPAT | S22: =+SUM(S65:U65)
A23: add back interest | B23: =-Final!AA119 | C23: =-Final!AB119 | D23: =-Final!AC119 | E23: =-Final!AD119 | F23: =-Final!AE119 | G23: =-Final!AF119 | H23: =-Final!AG119 | I23: =-Final!AH119 | ... O23: =-Final!AN119 | R23: Implied NOPAT multiple | S23: =+S24/S22
A24: less tax shield on interest | B24: =-$B$8*B23 | C24: =-$B$8*C23 | D24: =-$B$8*D23 | E24: =-$B$8*E23 | F24: =-$B$8*F23 | G24: =-$B$8*G23 | H24: =-$B$8*H23 | I24: =-$B$8*I23 | ... O24: =-$B$8*O23 | R24: Terminal value (undiscounted) | S24: =+SUM(S67:U67)
A25: Dividends received | B25: =Final!AA126 | C25: =Final!AB126 | D25: =Final!AC126 | E25: =Final!AD126 | F25: =Final!AE126 | G25: =Final!AF126 | H25: =Final!AG126 | I25: =Final!AH126 | ... O25: =Final!AN126 | R25: Discount rate | S25: =O20
A26: Investment in associates and investments | B26: =Final!AA125+Final!AA128 | C26: =Final!AB125+Final!AB128 | D26: =Final!AC125+Final!AC128 | E26: =Final!AD125+Final!AD128 | F26: =Final!AE125+Final!AE128 | G26: =Final!AF125+Final!AF128 | H26: =Final!AG125+Final!AG128 | I26: =Final!AH125+Final!AH128 | ... O26: =Final!AN125+Final!AN128 | R26: Terminal value | S26: =S24*S25
A27: Capital expenditure | B27: =Final!AA124 | C27: =Final!AB124 | D27: =Final!AC124 | E27: =Final!AD124 | F27: =Final!AE124 | G27: =Final!AF124 | H27: =Final!AG124 | I27: =Final!AH124 | ... O27: =Final!AN124 | R27: Dividends and interest received | S27: =S42+S43
A28: Other investing cash flows | B28: =Final!AA127 | C28: =Final!AB127 | D28: =Final!AC127 | E28: =Final!AD127 | F28: =Final!AE127 | G28: =Final!AF127 | H28: =Final!AG127 | I28: =Final!AH127 | ... O28: =Final!AN127 | R28: Explicit cash flows (2027-2030) | S28: =SUM(L30:O30)
A29: Net cash flow | B29: =SUM(B22:B28) | C29: =SUM(C22:C28) | D29: =SUM(D22:D28) | E29: =SUM(E22:E28) | F29: =SUM(F22:F28) | G29: =SUM(G22:G28) | H29: =SUM(H22:H28) | I29: =SUM(I22:I28) | ... O29: =SUM(O22:O28)
A30: Discounted cash flow | B30: =B29*B20 | C30: =C29*C20 | D30: =D29*D20 | E30: =E29*E20 | F30: =F29*F20 | G30: =G29*G20 | H30: =H29*H20 | I30: =I29*I20 | ... O30: =O29*O20 | R30: EV | S30: =SUM(S26:S28)
R31: Cash on hand and securities | S31: =Final!AI57+Final!AI58
A32: SOC component | R32: less finance lease obligations | S32: =-(Final!AI86+Final!AI77)
A33: Hong Kong EBITDA (CAPCO + CLP HK) | B33: =+SUM(SOC!AA4:AA8,SOC!AA11) | C33: =+SUM(SOC!AB4:AB8,SOC!AB11) | D33: =+SUM(SOC!AC4:AC8,SOC!AC11) | E33: =+SUM(SOC!AD4:AD8,SOC!AD11) | F33: =+SUM(SOC!AE4:AE8,SOC!AE11) | G33: =+SUM(SOC!AF4:AF8,SOC!AF11) | H33: =+SUM(SOC!AG4:AG8,SOC!AG11) | I33: =+SUM(SOC!AH4:AH8,SOC!AH11) | ... O33: =+SUM(SOC!AN4:AN8,SOC!AN11) | R33: less debt | S33: =-(Final!AI76+Final!AI85+Final!AI91+Final!AI79+Final!AI82+Final!AI89)
A34: less tax | B34: =+SOC!AA14 | C34: =+SOC!AB14 | D34: =+SOC!AC14 | E34: =+SOC!AD14 | F34: =+SOC!AE14 | G34: =+SOC!AF14 | H34: =+SOC!AG14 | I34: =+SOC!AH14 | ... O34: =+SOC!AN14 | R34: SOC liabilities | S34: =-(Final!AI90+Final!AI81+Final!AI87-Final!AI61)
A35: less SOC Capex | B35: =-Driver!AA84 | C35: =-Driver!AB84 | D35: =-Driver!AC84 | E35: =-Driver!AD84 | F35: =-Driver!AE84 | G35: =-Driver!AF84 | H35: =-Driver!AG84 | I35: =-Driver!AH84 | ... O35: =-Driver!AN84 | R35: less minority interest | S35: =-Final!AI97
A36: Add change in SOC accounts | B36: =+SUM(Final!AA110:AA116) | C36: =+SUM(Final!AB110:AB116) | D36: =+SUM(Final!AC110:AC116) | E36: =+SUM(Final!AD110:AD116) | F36: =+SUM(Final!AE110:AE116) | G36: =+SUM(Final!AF110:AF116) | H36: =+SUM(Final!AG110:AG116) | I36: =+SUM(Final!AH110:AH116) | ... O36: =+SUM(Final!AN110:AN116) | R36: NPV | S36: =SUM(S30:S35)
A37: Net SOC cash flows | B37: =SUM(B33:B36) | C37: =SUM(C33:C36) | D37: =SUM(D33:D36) | E37: =SUM(E33:E36) | F37: =SUM(F33:F36) | G37: =SUM(G33:G36) | H37: =SUM(H33:H36) | I37: =SUM(I33:I36) | ... O37: =SUM(O33:O36) | R37: NPV per share | S37: =ROUND(S36/Final!AI52,0) | T37: =S37/86-1 | U37: =S37/58-1
A38: Discounted cash flow | B38: =B37*B20 | C38: =C37*C20 | D38: =D37*D20 | E38: =E37*E20 | F38: =F37*F20 | G38: =G37*G20 | H38: =H37*H20 | I38: =I37*I20 | ... O38: =O37*O20 | R38: China IPPs and DayaBay
R39: Dividend received in 2030 | S39: =+O25
A40: Implied others consolidated net cash flow | B40: =+B29-B37-B58-B25 | C40: =+C29-C37-C58-C25 | D40: =+D29-D37-D58-D25 | E40: =+E29-E37-E58-E25 | F40: =+F29-F37-F58-F25 | G40: =+G29-G37-G58-G25 | H40: =+H29-H37-H58-H25 | I40: =+I29-I37-I58-I25 | ... O40: =+O29-O37-O58-O25 | R40: Terminal growth for div and int | S40: 0
A41: Add capex | B41: =+-(B27-B57-B35) | C41: =+-(C27-C57-C35) | D41: =+-(D27-D57-D35) | E41: =+-(E27-E57-E35) | F41: =+-(F27-F57-F35) | G41: =+-(G27-G57-G35) | H41: =+-(H27-H57-H35) | I41: =+-(I27-I57-I35) | ... O41: =+-(O27-O57-O35) | R41: Dividends Termina value | S41: =S39*(1+S40)/(S4-S40)
A42: Add back interests | B42: =-(Driver!AA109+Driver!AA110+Driver!AA111) | C42: =-(Driver!AB109+Driver!AB110+Driver!AB111) | D42: =-(Driver!AC109+Driver!AC110+Driver!AC111) | E42: =-(Driver!AD109+Driver!AD110+Driver!AD111) | F42: =-(Driver!AE109+Driver!AE110+Driver!AE111) | G42: =-(Driver!AF109+Driver!AF110+Driver!AF111) | H42: =-(Driver!AG109+Driver!AG110+Driver!AG111) | I42: =-(Driver!AH109+Driver!AH110+Driver!AH111) | ... O42: =-(Driver!AN109+Driver!AN110+Driver!AN111) | R42: Discounted dividends terminal value | S42: =+S41*O20
A43: Implied others consolidated operating cash flow | B43: =+SUM(B40:B42) | C43: =+SUM(C40:C42) | D43: =+SUM(D40:D42) | E43: =+SUM(E40:E42) | F43: =+SUM(F40:F42) | G43: =+SUM(G40:G42) | H43: =+SUM(H40:H42) | I43: =+SUM(I40:I42) | ... O43: =+SUM(O40:O42) | R43: Discounted terminal value for interest income | S43: =Driver!AN104*(1+S40)/(B11-S40)*S25
A45: CAPCO | S45: Yield | T45: PE
A46: 2019E earnings | B46: =SOC!AC40 | R46: 2023 | S46: =+Final!AG48/$S$37 | T46: =$S$36/Final!AG31
A47: 2019E PE | B47: 16 | R47: 2024 | S47: =+Final!AH48/$S$37 | T47: =$S$36/Final!AH31
A48: Market value | B48: =B46*B47 | R48: 2025 | S48: =+Final!AI48/$S$37 | T48: =$S$36/Final!AI31
G49: =37/4.3 | R49: 2026 | S49: =+Final!AJ48/$S$37 | T49: =$S$36/Final!AJ31
R50: 2027 | S50: =+Final!AK48/$S$37 | T50: =$S$36/Final!AK31
R51: 2028 | S51: =+Final!AL48/$S$37 | T51: =$S$36/Final!AL31
A53: Australia | B53: =B18 | C53: =C18 | D53: =D18 | E53: =E18 | F53: =F18 | G53: =G18 | H53: =H18 | I53: =I18 | ... O53: =O18 | R53: In 2030 | S53: Australia | T53: HK SoC | U53: Others | V53: Weighted
A54: EBIT | B54: =+Aus!AA23 | C54: =+Aus!AB23 | D54: =+Aus!AC23 | E54: =+Aus!AD23 | F54: =+Aus!AE23 | G54: =+Aus!AF23 | H54: =+Aus!AG23 | I54: =+Aus!AH23 | ... O54: =+Aus!AN23 | R54: EBIT | S54: =+O54 | T54: =+O33+SOC!AN10 | U54: =+S11-SUM(S54:T54)
A55: D&A | B55: =+Aus!AA13 | C55: =+Aus!AB13 | D55: =+Aus!AC13 | E55: =+Aus!AD13 | F55: =+Aus!AE13 | G55: =+Aus!AF13 | H55: =+Aus!AG13 | I55: =+Aus!AH13 | ... O55: =+Aus!AN13 | R55: Adjusted tax rate | S55: =Aus!AN28 | T55: 0.165 | U55: =1-U56/U54
A56: EBITDA | B56: =+B54-B55 | C56: =+C54-C55 | D56: =+D54-D55 | E56: =+E54-E55 | F56: =+F54-F55 | G56: =+G54-G55 | H56: =+H54-H55 | I56: =+I54-I55 | ... O56: =+O54-O55 | R56: NOPAT | S56: =+S54*(1-S55) | T56: =+T54*(1-T55) | U56: =+S13-SUM(S56:T56) | W56: check:
A57: Capex | B57: =-Driver!AA85 | C57: =-Driver!AB85 | D57: =-Driver!AC85 | E57: =-Driver!AD85 | F57: =-Driver!AE85 | G57: =-Driver!AF85 | H57: =-Driver!AG85 | I57: =-Driver!AH85 | ... O57: =-Driver!AN85 | R57: Invested capital in 2029 | S57: =+N79 | T57: =+N78 | U57: =+N80 | W57: =+S14-SUM(S57:U57)
A58: Net cash flows | B58: =+B56+B57 | C58: =+C56+C57 | D58: =+D56+D57 | E58: =+E56+E57 | F58: =+F56+F57 | G58: =+G56+G57 | H58: =+H56+H57 | I58: =+I56+I57 | ... O58: =+O56+O57 | R58: Invested capital in 2030 | S58: =+O79 | T58: =+O78 | U58: =+O80 | W58: =+S15-SUM(S58:U58)
A59: Discounted cashflow | B59: =+B58*B20 | C59: =+C58*C20 | D59: =+D58*D20 | E59: =+E58*E20 | F59: =+F58*F20 | G59: =+G58*G20 | H59: =+H58*H20 | I59: =+I58*I20 | ... O59: =+O58*O20 | R59: Average invested capital | S59: =AVERAGE(S57:S58) | T59: =AVERAGE(T57:T58) | U59: =+S16-SUM(S59:T59)
S60: =+S56/S59 | T60: =+T56/T59 | U60: =+U56/U59
A61: Total assets | B61: 44072 | C61: =+B61-C57+C55 | D61: =+C61-D57+D55 | E61: =+D61-E57+E55 | F61: 37839 | G61: 41673 | H61: =+G61-H57+H55 | I61: =+H61-I57+I55 | J61: =+I61-J57+J55 | K61: =+J61-K57+K55 | L61: =+K61-L57+L55 | M61: =+L61-M57+M55 | N61: =+M61-N57+N55 | O61: =+N61-O57+O55
A62: Fixed assets | B62: =Aus!AA88 | C62: =Aus!AB88 | D62: =Aus!AC88 | E62: =Aus!AD88 | F62: =Aus!AE88 | G62: =Aus!AF88 | H62: =Aus!AG88 | I62: =Aus!AH88 | ... O62: =Aus!AN88
A63: Total liabilities | B63: 10742 | C63: =+B63/B61*C61 | D63: =+C63/C61*D61 | E63: =+D63/D61*E61 | F63: 11160 | G63: 20143 | H63: =+G63/G61*H61 | I63: =+H63/H61*I61 | J63: =+I63/I61*J61 | K63: =+J63/J61*K61 | L63: =+K63/K61*L61 | M63: =+L63/L61*M61 | N63: =+M63/M61*N61 | O63: =+N63/N61*O61 | R63: 1st year avg invested capital | S63: =S59*(1+$B$12) | T63: =T59*(1+$B$12) | U63: =U59*(1+$B$12) | V63: Weighted Average
A64: Total debt | B64: =+Aus!AA84 | C64: =+Aus!AB84 | D64: =+Aus!AC84 | E64: =+Aus!AD84 | F64: =+Aus!AE84 | G64: =+Aus!AF84 | H64: =+Aus!AG84 | I64: =+Aus!AH84 | ... O64: =+Aus!AN84 | R64: Terminal return on capital | S64: 0.02 | T64: 0.08 | U64: 0.06 | V64: =+SUMPRODUCT(S64:U64,S59:U59)/SUM(S59:U59)
R65: 1st year NOPAT | S65: =S63*S64 | T65: =T63*T64 | U65: =+U63*U64
A66: ROIC (incl. carbon tax impact) | B66: =Aus!AA94 | C66: =Aus!AB94 | D66: =Aus!AC94 | E66: =Aus!AD94 | F66: =Aus!AE94 | G66: =Aus!AF94 | H66: =Aus!AG94 | I66: =Aus!AH94 | ... O66: =Aus!AN94 | R66: NOPAT multiple | S66: =(S64-$B$12)/(S64*($S$4-$B$12)) | T66: =(T64-$B$12)/(T64*($S$4-$B$12)) | U66: =(U64-$B$12)/(U64*($S$4-$B$12))
R67: Terminal value (undiscounted) | S67: =S65*S66 | T67: =T65*T66 | U67: =U65*U66
R68: Discount rate | S68: =+S25 | T68: =+S68 | U68: =+T68
A69: Total assets breakdown | B69: =+Final!AA75 | C69: =+Final!AB75 | D69: =+Final!AC75 | E69: =+Final!AD75 | F69: =+Final!AE75 | G69: =+Final!AF75 | H69: =+Final!AG75 | I69: =+Final!AH75 | ... O69: =+Final!AN75 | R69: Terminal value (discounted) | S69: =+S67*S68 | T69: =+T67*T68 | U69: =+S26-SUM(S69:T69)
A70: HK (CAPCO and CLP) | B70: =ROAFNA!AA18 | C70: =ROAFNA!AB18 | D70: =ROAFNA!AC18 | E70: =ROAFNA!AD18 | F70: =ROAFNA!AE18 | G70: =ROAFNA!AF18 | H70: =ROAFNA!AG18 | I70: =ROAFNA!AH18 | ... O70: =ROAFNA!AN18
A71: Australia | B71: =+B61 | C71: =+C61 | D71: =+D61 | E71: =+E61 | F71: =+F61 | G71: =+G61 | H71: =+H61 | I71: =+I61 | ... O71: =+O61 | R71: Explicit cash flows (2019-2030) | S71: =SUM(I59:O59)*$V$72 | T71: =SUM(I38:O38)*$V$72 | U71: =+S28-SUM(S71:T71)
A72: Others | B72: =+B69-SUM(B70:B71) | C72: =+C69-SUM(C70:C71) | D72: =+D69-SUM(D70:D71) | E72: =+E69-SUM(E70:E71) | F72: =+F69-SUM(F70:F71) | G72: =+G69-SUM(G70:G71) | H72: =+H69-SUM(H70:H71) | I72: =+I69-SUM(I70:I71) | ... O72: =+O69-SUM(O70:O71) | R72: Dividend + interests income | S72: 0 | T72: 0 | U72: =+S27 | V72: 1
R74: EV | S74: =+S71+S69+S72 | T74: =+T71+T69+T72 | U74: =+U71+U69+U72 | W74: check:
A75: Non-fixed assets | B75: =+B69-SUM(Final!AA65,Final!AA66,Final!AA67,Final!AA68) | C75: =+C69-SUM(Final!AB65,Final!AB66,Final!AB67,Final!AB68) | D75: =+D69-SUM(Final!AC65,Final!AC66,Final!AC67,Final!AC68) | E75: =+E69-SUM(Final!AD65,Final!AD66,Final!AD67,Final!AD68) | F75: =+F69-SUM(Final!AE65,Final!AE66,Final!AE67,Final!AE68) | G75: =+G69-SUM(Final!AF65,Final!AF66,Final!AF67,Final!AF68) | H75: =+H69-SUM(Final!AG65,Final!AG66,Final!AG67,Final!AG68) | I75: =+I69-SUM(Final!AH65,Final!AH66,Final!AH67,Final!AH68) | ... O75: =+O69-SUM(Final!AN65,Final!AN66,Final!AN67,Final!AN68) | R75: Net debt | S75: =-G64 | T75: =S32+S33+S34-S75+S31-U75 | U75: =-5573-6785 | W75: =SUM(S74:U74)-S30
R76: MI | T76: =+S35-U76 | U76: =-Final!AC127 | Y76: NPV by segments:
A77: Estimated Invested capital breakdown | B77: =+Final!AA144 | C77: =+Final!AB144 | D77: =+Final!AC144 | E77: =+Final!AD144 | F77: =+Final!AE144 | G77: =+Final!AF144 | H77: =+Final!AG144 | I77: =+Final!AH144 | ... O77: =+Final!AN144 | R77: NPV | S77: =+S74+S75+S76 | T77: =+T74+T75+T76 | U77: =+U74+U75+U76 | Y77: Australia | Z77: =S77 | AA77: =Z77/SUM($Z$77:$Z$79)
A78: Hong Kong | B78: =+B70 | C78: =+C70 | D78: =+D70 | E78: =+E70 | F78: =+F70 | G78: =+G70 | H78: =+H70 | I78: =+I70 | ... O78: =+O70 | R78: NPV per share | S78: =ROUND(2*S77/Final!AB52,0)/2 | T78: =ROUND(2*T77/Final!AB52,0)/2 | U78: =ROUND(2*U77/Final!AB52,0)/2 | Y78: Hong Kong | Z78: =T77 | AA78: =Z78/SUM($Z$77:$Z$79)
A79: Australia | B79: =Aus!AA88+Aus!AA93 | C79: =Aus!AB88+Aus!AB93 | D79: =Aus!AC88+Aus!AC93 | E79: =Aus!AD88+Aus!AD93 | F79: =Aus!AE88+Aus!AE93 | G79: =Aus!AF88+Aus!AF93 | H79: =Aus!AG88+Aus!AG93 | I79: =Aus!AH88+Aus!AH93 | ... O79: =Aus!AN88+Aus!AN93 | S79: =+S78/SUM($S$78:$U$78) | T79: =+T78/SUM($S$78:$U$78) | U79: =+U78/SUM($S$78:$U$78) | Y79: Others | Z79: =U77 | AA79: =Z79/SUM($Z$77:$Z$79)
A80: Others | B80: =+B77-SUM(B78:B79) | C80: =+C77-SUM(C78:C79) | D80: =+D77-SUM(D78:D79) | E80: =+E77-SUM(E78:E79) | F80: =+F77-SUM(F78:F79) | G80: =+G77-SUM(G78:G79) | H80: =+H77-SUM(H78:H79) | I80: =+I77-SUM(I78:I79) | ... O80: =+O77-SUM(O78:O79) | S80: =+S77/7.8
A82: NOPAT breakdown | B82: =(Final!AA20-Final!AA19-Final!AA18)*(1+Final!AA23/(Final!AA22-Final!AA18-Final!AA19)) | C82: =(Final!AB20-Final!AB19-Final!AB18)*(1+Final!AB23/(Final!AB22-Final!AB18-Final!AB19)) | D82: =(Final!AC20-Final!AC19-Final!AC18)*(1+Final!AC23/(Final!AC22-Final!AC18-Final!AC19)) | E82: =(Final!AD20-Final!AD19-Final!AD18)*(1+Final!AD23/(Final!AD22-Final!AD18-Final!AD19)) | F82: =(Final!AE20-Final!AE19-Final!AE18)*(1+Final!AE23/(Final!AE22-Final!AE18-Final!AE19)) | G82: =(Final!AF20-Final!AF19-Final!AF18)*(1+Final!AF23/(Final!AF22-Final!AF18-Final!AF19)) | H82: =(Final!AG20-Final!AG19-Final!AG18)*(1+Final!AG23/(Final!AG22-Final!AG18-Final!AG19)) | I82: =(Final!AH20-Final!AH19-Final!AH18)*(1+Final!AH23/(Final!AH22-Final!AH18-Final!AH19)) | ... O82: =(Final!AN20-Final!AN19-Final!AN18)*(1+Final!AN23/(Final!AN22-Final!AN18-Final!AN19)) | R82: EV/EBITDA 2024E | S82: =+S74/I56 | T82: =T74/I33 | W82: check:
A83: Hong Kong (CLP and CAPCO) | B83: =+(B33+SOC!AA10)*(1-16.5%) | C83: =+(C33+SOC!AB10)*(1-16.5%) | D83: =+(D33+SOC!AC10)*(1-16.5%) | E83: =+(E33+SOC!AD10)*(1-16.5%) | F83: =+(F33+SOC!AE10)*(1-16.5%) | G83: =+(G33+SOC!AF10)*(1-16.5%) | H83: =+(H33+SOC!AG10)*(1-16.5%) | I83: =+(I33+SOC!AH10)*(1-16.5%) | ... O83: =+(O33+SOC!AN10)*(1-16.5%) | R83: EV/EBITDA 2025E | S83: =+S74/J56 | T83: =+T74/J33 | W83: =+S36-SUM(S77:U77)
A84: Australia | B84: =+B54*(1-Aus!AA28) | C84: =+C54*(1-Aus!AB28) | D84: =+D54*(1-Aus!AC28) | E84: =+E54*(1-Aus!AD28) | F84: =+F54*(1-Aus!AE28) | G84: =+G54*(1-Aus!AF28) | H84: =+H54*(1-Aus!AG28) | I84: =+I54*(1-Aus!AH28) | ... O84: =+O54*(1-Aus!AN28) | R84: PE-2024E | S84: =S77/Aus!AH29 | T84: =T$77/Driver!AH51 | U84: =U77/SUM(Driver!AA53:AA57)
A85: Others | B85: =B82-B83-B84 | C85: =C82-C83-C84 | D85: =D82-D83-D84 | E85: =E82-E83-E84 | F85: =F82-F83-F84 | G85: =G82-G83-G84 | H85: =H82-H83-H84 | I85: =I82-I83-I84 | ... O85: =O82-O83-O84 | R85: PE-2025E | S85: =S77/Aus!AI29 | T85: =T$77/Driver!AI51 | U85: =U77/SUM(Driver!AB53:AB57)
B86: =+B82-SUM(B83:B85) | C86: =+C82-SUM(C83:C85) | D86: =+D82-SUM(D83:D85) | E86: =+E82-SUM(E83:E85) | F86: =+F82-SUM(F83:F85) | G86: =+G82-SUM(G83:G85) | H86: =+H82-SUM(H83:H85) | I86: =+I82-SUM(I83:I85) | ... O86: =+O82-SUM(O83:O85) | R86: PE-2026E | S86: =S77/Aus!AJ29 | T86: =T$77/Driver!AJ51 | U86: =U77/SUM(Driver!AC53:AC57)
A87: ROIC | R87: EV/NFA - 2025 | T87: =T74/ROAFNA!AI3
A88: Group | B88: =B82/AVERAGE(B77:B77) | C88: =C82/AVERAGE(B77:C77) | D88: =D82/AVERAGE(C77:D77) | E88: =E82/AVERAGE(D77:E77) | F88: =F82/AVERAGE(E77:F77) | G88: =G82/AVERAGE(F77:G77) | H88: =H82/AVERAGE(G77:H77) | I88: =I82/AVERAGE(H77:I77) | J88: =J82/AVERAGE(I77:J77) | ... O88: =O82/AVERAGE(N77:O77)
A89: HK | B89: =B83/(AVERAGE(B78:B78)) | C89: =C83/(AVERAGE(B78:C78)) | D89: =D83/(AVERAGE(C78:D78)) | E89: =E83/(AVERAGE(D78:E78)) | F89: =F83/(AVERAGE(E78:F78)) | G89: =G83/(AVERAGE(F78:G78)) | H89: =H83/(AVERAGE(G78:H78)) | I89: =I83/(AVERAGE(H78:I78)) | J89: =J83/(AVERAGE(I78:J78)) | ... O89: =O83/(AVERAGE(N78:O78))
A90: Australia | B90: =+B66 | C90: =+C66 | D90: =+D66 | E90: =+E66 | F90: =+F66 | G90: =+G66 | H90: =+H66 | I90: =+I66 | ... O90: =+O66
A91: Others | B91: =+B85/AVERAGE(B80:B80) | C91: =+C85/AVERAGE(B80:C80) | D91: =+D85/AVERAGE(C80:D80) | E91: =+E85/AVERAGE(D80:E80) | F91: =+F85/AVERAGE(E80:F80) | G91: =+G85/AVERAGE(F80:G80) | H91: =+H85/AVERAGE(G80:H80) | I91: =+I85/AVERAGE(H80:I80) | J91: =+J85/AVERAGE(I80:J80) | ... O91: =+O85/AVERAGE(N80:O80)
T92: incl. CAPCO for HK
A93: Effective tax rate | B93: =-Final!AA23/(Final!AA22-Final!AA18-Final!AA19) | C93: =-Final!AB23/(Final!AB22-Final!AB18-Final!AB19) | D93: =-Final!AC23/(Final!AC22-Final!AC18-Final!AC19) | E93: =-Final!AD23/(Final!AD22-Final!AD18-Final!AD19) | F93: =-Final!AE23/(Final!AE22-Final!AE18-Final!AE19) | G93: =-Final!AF23/(Final!AF22-Final!AF18-Final!AF19) | H93: =-Final!AG23/(Final!AG22-Final!AG18-Final!AG19) | I93: =-Final!AH23/(Final!AH22-Final!AH18-Final!AH19) | ... O93: =-Final!AN23/(Final!AN22-Final!AN18-Final!AN19) | R93: EV mix | S93: =S74/$S$30 | T93: =T74/$S$30 | U93: =U74/$S$30
A97: Valuation of CAPCO
A98: (HK$ m) | B98: =B53 | C98: =C53 | D98: =D53 | E98: =E53 | F98: =F53 | G98: =G53 | H98: =H53 | I98: =I53 | ... O98: =O53
A99: 100% CAPCO earnings | B99: =SOC!AA40 | C99: =SOC!AB40 | D99: =SOC!AC40 | E99: =SOC!AD40 | F99: =SOC!AE40 | G99: =SOC!AF40 | H99: =SOC!AG40 | I99: =SOC!AH40 | ... O99: =SOC!AN40
A100: Add: interest expenses | B100: =-SOC!AA9*SOC!AA37 | C100: =-SOC!AB9*SOC!AB37 | D100: =-SOC!AC9*SOC!AC37 | E100: =-SOC!AD9*SOC!AD37 | F100: =-SOC!AE9*SOC!AE37 | G100: =-SOC!AF9*SOC!AF37 | H100: =-SOC!AG9*SOC!AG37 | I100: =-SOC!AH9*SOC!AH37 | ... O100: =-SOC!AN9*SOC!AN37
A101: Less: tax shield on interest | B101: =-SOC!AA15*B100 | C101: =-SOC!AB15*C100 | D101: =-SOC!AC15*D100 | E101: =-SOC!AD15*E100 | F101: =-SOC!AE15*F100 | G101: =-SOC!AF15*G100 | H101: =-SOC!AG15*H100 | I101: =-SOC!AH15*I100 | ... O101: =-SOC!AN15*O100
A102: CAPCO cash earnings | B102: =SUM(B99:B101) | C102: =SUM(C99:C101) | D102: =SUM(D99:D101) | E102: =SUM(E99:E101) | F102: =SUM(F99:F101) | G102: =SUM(G99:G101) | H102: =SUM(H99:H101) | I102: =SUM(I99:I101) | ... O102: =SUM(O99:O101)
A103: Less: Capex | B103: =-ROAFNA!AA56 | C103: =-ROAFNA!AB56 | D103: =-ROAFNA!AC56 | E103: =-ROAFNA!AD56 | F103: =-ROAFNA!AE56 | G103: =-ROAFNA!AF56 | H103: =-ROAFNA!AG56 | I103: =-ROAFNA!AH56 | ... O103: =-ROAFNA!AN56
A104: Free cash flows | B104: =SUM(B102:B103) | C104: =SUM(C102:C103) | D104: =SUM(D102:D103) | E104: =SUM(E102:E103) | F104: =SUM(F102:F103) | G104: =SUM(G102:G103) | H104: =SUM(H102:H103) | I104: =SUM(I102:I103) | ... O104: =SUM(O102:O103)
A105: Discount factor | B105: =+B20 | C105: =+C20 | D105: =+D20 | E105: =+E20 | F105: =+F20 | G105: =+G20 | H105: =+H20 | I105: =+I20 | ... O105: =+O20
A106: Discounted free cash flows | B106: =B104*B20 | C106: =C104*C20 | D106: =D104*D20 | E106: =E104*E20 | F106: =F104*F20 | G106: =G104*G20 | H106: =H104*H20 | I106: =I104*I20 | ... O106: =O104*O20
A108: Terminal period:
A109: Average net fixed assets in 2022
...

Sheet Final
I1: * = 15 months to 31 December 1999 | AC1: DCF | AD1: =DCF!E3 | AE1: =AE99 | AF1: =AF99 | AG1: =AG99 | AH1: =AH99 | AI1: =AI99 | AJ1: =AJ99 | AK1: =AK99 | AL1: =AL99 | ... AN1: =AN99
B2: 1992 | C2: 1993 | D2: 1994 | E2: 1995 | F2: 1996 | G2: 1997 | H2: 1998 | I2: 1999* | J2: 2000 | K2: 2001 | L2: 2002 | M2: 2003 | N2: 2004 | O2: 2005 | P2: 2006 | Q2: 2007 | R2: 2008 | S2: 2009 | T2: 2010 | U2: 2011 | V2: 2012 | W2: 2013 | X2: 2014 | Y2: 2015 | Z2: 2016 | AA2: 2017 | AB2: 2018 | AC2: 2019 | AD2: 2020 | AE2: 2021 | AF2: 2022 | AG2: 2023 | AH2: 2024 | AI2: 2025E | AJ2: 2026E | AK2: 2027E | AL2: 2028E | AM2: 2029E | AN2: 2030E
A3: Income Statement
A4: SOC revenue | B4: =Driver!B4+Driver!B5 | C4: =Driver!C4+Driver!C5 | D4: =Driver!D4+Driver!D5 | E4: =Driver!E4+Driver!E5 | F4: =Driver!F4+Driver!F5 | G4: =Driver!G4+Driver!G5 | H4: =Driver!H4+Driver!H5 | I4: =Driver!I4+Driver!I5 | ... AN4: =Driver!AN4+Driver!AN5
A5: Overseas power revenues | B5: =SUM(Driver!B6:B9) | C5: =SUM(Driver!C6:C9) | D5: =SUM(Driver!D6:D9) | E5: =SUM(Driver!E6:E9) | F5: =SUM(Driver!F6:F9) | G5: =SUM(Driver!G6:G9) | H5: =SUM(Driver!H6:H9) | I5: =SUM(Driver!I6:I9) | ... AN5: =SUM(Driver!AN6:AN9)
A6: Other non-SOC revenue | B6: =B7-SUM(B4:B5) | C6: =C7-SUM(C4:C5) | D6: =D7-SUM(D4:D5) | E6: =E7-SUM(E4:E5) | F6: =F7-SUM(F4:F5) | G6: =G7-SUM(G4:G5) | H6: =H7-SUM(H4:H5) | I6: =I7-SUM(I4:I5) | ... AC6: =AC7-SUM(AC4:AC5) | AD6: =Driver!AD10 | AE6: =Driver!AE10 | AF6: =Driver!AF10 | AG6: =Driver!AG10 | AH6: =Driver!AH10 | AI6: =Driver!AI10 | AJ6: =Driver!AJ10 | AK6: =Driver!AK10 | ... AN6: =Driver!AN10
A7: Total revenue | B7: 13402 | C7: 14745 | D7: 15345 | E7: 16960 | F7: 18534 | G7: 20900 | H7: 22869 | I7: 29035 | J7: 24451 | K7: 24999 | L7: 26134 | M7: 28248 | N7: 30784 | O7: 38584 | P7: 45702 | Q7: 50789 | R7: 54297 | S7: 50668 | T7: 58410 | U7: 91634 | V7: 104861 | W7: 104530 | X7: 92259 | Y7: 80700 | Z7: 79434 | AA7: 92073 | AB7: 91425 | AC7: 85689 | AD7: 79590 | AE7: 83959 | AF7: 100662 | AG7: 87169 | AH7: 90964 | AI7: =SUM(AI4:AI6) | AJ7: =SUM(AJ4:AJ6) | AK7: =SUM(AK4:AK6) | AL7: =SUM(AL4:AL6) | AM7: =SUM(AM4:AM6) | AN7: =SUM(AN4:AN6)
A9: Operating costs | B9: =B14-B13-B12 | C9: =C14-C13-C12 | D9: =D14-D13-D12 | E9: =E14-E13-E12 | F9: =F14-F13-F12 | G9: =G14-G13-G12 | H9: =H14-H13-H12 | I9: =I14-I13-I12 | ... AH9: =AH14-AH13-AH12 | AI9: =AI10-AI7 | AJ9: =AJ10-AJ7 | AK9: =AK10-AK7 | AL9: =AL10-AL7 | AM9: =AM10-AM7 | AN9: =AN10-AN7
A10: EBITDA | B10: =B7+B9 | C10: =C7+C9 | D10: =D7+D9 | E10: =E7+E9 | F10: =F7+F9 | G10: =G7+G9 | H10: =H7+H9 | I10: =I7+I9 | ... AH10: =AH7+AH9 | AI10: =AI15-AI12 | AJ10: =AJ15-AJ12 | AK10: =AK15-AK12 | AL10: =AL15-AL12 | AM10: =AM15-AM12 | AN10: =AN15-AN12
A12: Depreciation and amortisation | B12: -852 | C12: -953 | D12: -783 | E12: -888 | F12: -1002 | G12: -1155 | H12: -1270 | I12: -1704 | J12: -1474 | K12: -1624 | L12: -1749 | M12: -2357 | N12: =-2529-41 | O12: -2896 | P12: -4968 | Q12: -4650 | R12: -4055 | S12: -4332 | T12: -5065 | U12: -6353 | V12: -7021 | W12: -7592 | X12: -6791 | Y12: -6765 | Z12: -6909 | AA12: -7368 | AB12: -8005 | AC12: -8118 | AD12: -8476 | AE12: -9308 | AF12: -8904 | AG12: -8594 | AH12: -9276 | AI12: =Driver!AI26 | AJ12: =Driver!AJ26 | AK12: =Driver!AK26 | AL12: =Driver!AL26 | AM12: =Driver!AM26 | AN12: =Driver!AN26
A13: SOC adjustments (until 2004) | B13: -616 | C13: -908 | D13: 221 | E13: 310 | F13: 319 | G13: 186.501 | H13: -1714.2821 | I13: -1787 | J13: -2276 | K13: -1506 | L13: -1643 | M13: -835 | N13: -348 | O13: 0 | P13: 0 | Q13: 0 | R13: 0 | S13: 0 | T13: 0 | U13: 0 | V13: 0 | W13: 0 | X13: 0 | Y13: 0 | Z13: 0 | AA13: =Z13 | AB13: =AA13 | AC13: =AB13 | AD13: =AC13 | AE13: =AD13 | AF13: =AE13 | AG13: =AF13 | AH13: =AG13 | ... AN13: =AM13
A14: Total operating expenses | B14: -10591 | C14: -11554 | D14: -12089 | E14: -13611 | F14: -14805 | G14: -16909.499 | H14: -18331.282 | I14: -23200 | J14: -20406 | K14: -20557 | L14: -20941 | M14: -22471 | N14: -23028 | O14: -29889 | P14: -33590 | Q14: -39607 | R14: -41717 | S14: -39880 | T14: -46413 | U14: -76461 | V14: -91760 | W14: -95624 | X14: =-79389+2025 | Y14: -58680 | Z14: -62288 | AA14: -73375 | AB14: -73263 | AC14: -71659 | AD14: -64874 | AE14: -71748 | AF14: -95378 | AG14: -71985 | AH14: -76061 | AI14: =AI9+AI12 | AJ14: =AJ9+AJ12 | AK14: =AK9+AK12 | AL14: =AL9+AL12 | AM14: =AM9+AM12 | AN14: =AN9+AN12
A15: Net operating income | B15: =B10+B12+B13 | C15: =C10+C12+C13 | D15: =D10+D12+D13 | E15: =E10+E12+E13 | F15: =F10+F12+F13 | G15: =G10+G12+G13 | H15: =H10+H12+H13 | I15: =I10+I12+I13 | ... AH15: =AH10+AH12+AH13 | AI15: =AI20-AI16-AI17-AI18-AI19 | AJ15: =AJ20-AJ16-AJ17-AJ18-AJ19 | AK15: =AK20-AK16-AK17-AK18-AK19 | AL15: =AL20-AL16-AL17-AL18-AL19 | AM15: =AM20-AM16-AM17-AM18-AM19 | AN15: =AN20-AN16-AN17-AN18-AN19
A16: Other Income, net | B16: 67 | C16: 70 | D16: 116 | E16: 160 | F16: 136 | G16: 137.899 | H16: 186.33419 | I16: -0.47599889 | J16: 517.36527 | K16: 56.6 | L16: -256.8 | M16: 469.73297 | N16: 52 | O16: 66 | P16: 55 | Q16: 2122 | R16: 727 | S16: 153 | T16: 400 | U16: -1985 | V16: 0 | W16: 0 | X16: 0 | Y16: 0 | Z16: 0 | AA16: =Z16 | AB16: =AA16 | AC16: -6381 | AD16: 0 | AE16: -1110 | AF16: -4312 | AG16: -5868 | AH16: 0 | AI16: =AH16 | AJ16: =AI16 | AK16: =AJ16 | AL16: =AK16 | AM16: =AL16 | AN16: =AM16
A17: Property | B17: 0 | C17: 0 | D17: 0 | E17: 1286 | F17: 0 | G17: 0 | H17: 1837 | I17: 626 | J17: 1357 | K17: 1752 | L17: 595 | M17: 291 | N17: 187 | O17: 267 | P17: 44 | Q17: 0 | R17: 0 | S17: 0 | T17: 0 | U17: 0 | V17: 0 | W17: 0 | X17: 0 | Y17: 0 | Z17: 0 | AA17: 0 | AB17: 0 | AC17: =+AB17 | AD17: =+AC17 | AE17: =+AD17 | AF17: =+AE17 | AG17: =+AF17 | AH17: =+AG17 | AI17: =+AH17 | AJ17: =+AI17 | ... AN17: =+AM17
A18: Other jointly controlled entities | B18: 1100 | C18: 1195 | D18: 1433 | E18: 1653 | F18: 1847 | G18: 1972.6 | H18: 2097.8 | I18: 2732.2919 | J18: 2215.6 | K18: 2339 | L18: 2992 | M18: 3399 | N18: 3181 | O18: 2832 | P18: 2892 | Q18: 3024 | R18: 2624 | S18: 2675 | T18: 2080 | U18: 2929 | V18: 2405 | W18: 2671 | X18: 1562 | Y18: 1357 | Z18: 737 | AA18: 508 | AB18: 518 | AC18: 885 | AD18: 797 | AE18: -97 | AF18: 325 | AG18: 1147 | AH18: 845 | AI18: =Driver!AI38 | AJ18: =Driver!AJ38 | AK18: =Driver!AK38 | AL18: =Driver!AL38 | AM18: =Driver!AM38 | AN18: =Driver!AN38
A19: Electricity associates | B19: 0 | C19: 0 | D19: 0 | E19: 0 | F19: 0 | G19: 0 | H19: 15 | I19: 7 | J19: -895.36527 | K19: 14 | L19: 30 | M19: 102 | N19: 236 | O19: 140 | P19: 114 | Q19: 1 | R19: -27 | S19: -354 | T19: 813 | U19: 681 | V19: 579 | W19: 612 | X19: 796 | Y19: 888 | Z19: 904 | AA19: 950 | AB19: 1818 | AC19: 1828 | AD19: 1725 | AE19: 2071 | AF19: 2135 | AG19: 2049 | AH19: 1810 | AI19: =Driver!AI39 | AJ19: =Driver!AJ39 | AK19: =Driver!AK39 | AL19: =Driver!AL39 | AM19: =Driver!AM39 | AN19: =Driver!AN39
A20: EBIT | B20: =SUM(B15:B19) | C20: =SUM(C15:C19) | D20: =SUM(D15:D19) | E20: =SUM(E15:E19) | F20: =SUM(F15:F19) | G20: =SUM(G15:G19) | H20: =SUM(H15:H19) | I20: =SUM(I15:I19) | ... AH20: =SUM(AH15:AH19) | AI20: =AI22-AI21 | AJ20: =AJ22-AJ21 | AK20: =AK22-AK21 | AL20: =AL22-AL21 | AM20: =AM22-AM21 | AN20: =AN22-AN21
A21: Net finance costs | B21: -67 | C21: -48 | D21: -16 | E21: -48 | F21: -50 | G21: 565 | H21: 973 | I21: 612 | J21: -94 | K21: -158 | L21: -156 | M21: -640.22069 | N21: -983 | O21: -1489 | P21: -4624 | Q21: -4881 | R21: -4121 | S21: -3408 | T21: -4111 | U21: -5859 | V21: -6101 | W21: -6349 | X21: -4049 | Y21: -3936 | Z21: -2124 | AA21: =-2180+151 | AB21: =-2049+192 | AC21: =-1983+162 | AD21: =-1873+136 | AE21: =-1744+108 | AF21: =-2085+243 | AG21: =-2139+270 | AH21: =+-2254+235 | AI21: =Driver!AI106 | AJ21: =Driver!AJ106 | AK21: =Driver!AK106 | AL21: =Driver!AL106 | AM21: =Driver!AM106 | AN21: =Driver!AN106
A22: Pretax profits | B22: =B20+B21 | C22: =C20+C21 | D22: =D20+D21 | E22: =E20+E21 | F22: =F20+F21 | G22: =G20+G21 | H22: =H20+H21 | I22: =I20+I21 | ... AH22: =AH20+AH21 | AI22: =AI24-AI23 | AJ22: =AJ24-AJ23 | AK22: =AK24-AK23 | AL22: =AL24-AL23 | AM22: =AM24-AM23 | AN22: =AN24-AN23
A23: Tax | B23: -738 | C23: -856 | D23: -583 | E23: -726 | F23: -826 | G23: -892 | H23: -1509 | I23: -1483 | J23: -1378 | K23: -1189 | L23: -1293 | M23: -1712 | N23: -1815 | O23: 922 | P23: -683 | Q23: -837 | R23: -1349 | S23: -1665 | T23: -844 | U23: -1650 | V23: -1692 | W23: 232 | X23: -1268 | Y23: -3580 | Z23: -2855 | AA23: -2780 | AB23: -4014 | AC23: -2787 | AD23: -2993 | AE23: -1965 | AF23: -103 | AG23: -2973 | AH23: -2821 | AI23: =Driver!AI48 | AJ23: =Driver!AJ48 | AK23: =Driver!AK48 | AL23: =Driver!AL48 | AM23: =Driver!AM48 | AN23: =Driver!AN48
A24: Profit after tax | B24: =B22+B23 | C24: =C22+C23 | D24: =D22+D23 | E24: =E22+E23 | F24: =F22+F23 | G24: =G22+G23 | H24: =H22+H23 | I24: =I22+I23 | ... AH24: =AH22+AH23 | AI24: =AI27-AI25-AI26 | AJ24: =AJ27-AJ25-AJ26 | AK24: =AK27-AK25-AK26 | AL24: =AL27-AL25-AL26 | AM24: =AM27-AM25-AM26 | AN24: =AN27-AN25-AN26
A25: Minority interests | B25: 0 | C25: 0 | D25: 0 | E25: 0 | F25: 0 | G25: 0 | H25: 0 | I25: 0 | J25: 0 | K25: 0 | L25: 0 | M25: 0 | N25: 0 | O25: 1 | P25: -10 | Q25: -3 | R25: -11 | S25: 7 | T25: -3 | U25: -1 | V25: 20 | W25: -12 | X25: =-563 | Y25: =-846 | Z25: =-850 | AA25: -849 | AB25: -827 | AC25: -885 | AD25: -914 | AE25: -845 | AF25: -424 | AG25: -876 | AH25: -840 | AI25: =-SOC!AI40*30%+CN!AI17+India!AI18 | AJ25: =-SOC!AJ40*30%+CN!AJ17+India!AJ18 | AK25: =-SOC!AK40*30%+CN!AK17+India!AK18 | AL25: =-SOC!AL40*30%+CN!AL17+India!AL18 | AM25: =-SOC!AM40*30%+CN!AM17+India!AM18 | AN25: =-SOC!AN40*30%+CN!AN17+India!AN18
A26: Perpetual capital costs | B26: 0 | C26: 0 | D26: 0 | E26: 0 | F26: 0 | G26: 0 | H26: 0 | I26: 0 | J26: 0 | K26: 0 | L26: 0 | M26: 0 | N26: 0 | O26: 0 | P26: 0 | Q26: 0 | R26: 0 | S26: 0 | T26: 0 | U26: 0 | V26: 0 | W26: 0 | X26: -152 | Y26: -247 | Z26: -247 | AA26: -249 | AB26: -250 | AC26: -212 | AD26: -138 | AE26: -138 | AF26: -139 | AG26: -139 | AH26: -136 | AI26: =AH26 | AJ26: =AI26 | AK26: =AJ26 | AL26: =AK26 | AM26: =AL26 | AN26: =AM26
A27: Net profits (reported) | B27: =B24+B25+B26 | C27: =C24+C25+C26 | D27: =D24+D25+D26 | E27: =E24+E25+E26 | F27: =F24+F25+F26 | G27: =G24+G25+G26 | H27: =H24+H25+H26 | I27: =I24+I25+I26 | ... AH27: =AH24+AH25+AH26 | AI27: =AI31+SUM(AI28:AI30) | AJ27: =AJ31+SUM(AJ28:AJ30) | AK27: =AK31+SUM(AK28:AK30) | AL27: =AL31+SUM(AL28:AL30) | AM27: =AM31+SUM(AM28:AM30) | AN27: =AN31+SUM(AN28:AN30)
A28: Disposal or tax consolidation gains | N28: 0 | O28: 2004 | P28: =343+888-823+204 | Q28: =1030+1146-457-299-126 | R28: =432+127-108+225+389-24 | S28: =-1-16-346-15+171+153+39-131 | T28: 1345 | U28: 876 | V28: 105 | W28: 600 | X28: =1953 | Y28: 6619 | Z28: =643-146+83 | AA28: 0 | AB28: 0 | AC28: 0 | AD28: 0 | AE28: 0 | AF28: 0 | AG28: 0 | AH28: 0 | AI28: 0 | AJ28: 0 | AK28: 0 | AL28: 0 | AM28: 0 | AN28: 0
A29: Write-down of investments | J29: =-130-900 | N29: 0 | T29: -258 | U29: -2125 | V29: -409 | W29: -372 | X29: -158 | Y29: -243 | Z29: -174 | AA29: 0 | AB29: 0 | AC29: 0 | AD29: 0 | AE29: 0 | AF29: 0 | AG29: 0 | AH29: 0 | AI29: 0 | AJ29: 0 | AK29: 0 | AL29: 0 | AM29: 0 | AN29: 0
A30: Other one-offs | D30: 0 | E30: 1286 | H30: =2729.05205003452-1186 | I30: =521.84-2 | J30: 1132 | K30: 1468 | L30: 546 | M30: 240 | N30: 373 | O30: 267 | P30: 44 | T30: -19 | U30: 225 | V30: -790 | W30: -3475 | X30: -636 | Y30: -2239 | Z30: =377-Z28-Z29 | AA30: =369+573-AA29-AA28 | AB30: =18-450-AB29-AB28 | AC30: =-6381-83-AC29-AC28 | AD30: =-121-AD29-AD28 | AE30: =-1026-AE29-AE28 | AF30: =-3699-AF29-AF28 | AG30: =-5597-AG29-AG28 | AH30: =94-AH29-AH28 | AI30: 0 | AJ30: 0 | AK30: 0 | AL30: 0 | AM30: 0 | AN30: 0
A31: Net profits (recurring) | B31: =B27-SUM(B28:B30) | C31: =C27-SUM(C28:C30) | D31: =D27-SUM(D28:D30) | E31: =E27-SUM(E28:E30) | F31: =F27-SUM(F28:F30) | G31: =G27-SUM(G28:G30) | H31: =H27-SUM(H28:H30) | I31: =I27-SUM(I28:I30) | ... AH31: =AH27-SUM(AH28:AH30) | AI31: =Driver!AI58 | AJ31: =Driver!AJ58 | AK31: =Driver!AK58 | AL31: =Driver!AL58 | AM31: =Driver!AM58 | AN31: =Driver!AN58
A32: YoY | C32: =C31/B31-1 | D32: =D31/C31-1 | E32: =E31/D31-1 | F32: =F31/E31-1 | G32: =G31/F31-1 | H32: =H31/G31-1 | I32: =I31/H31-1 | J32: =J31/I31-1 | ... AN32: =AN31/AM31-1
AA33: =5914/AA31 | AB33: =7886/AB31 | AC33: =5474/AC31
A34: EPS (recurring) | B34: =B31/B53 | C34: =C31/C53 | D34: =D31/D53 | E34: =E31/E53 | F34: =F31/F53 | G34: =G31/G53 | H34: =H31/H53 | I34: =I31/I53 | J34: =J31/J53 | K34: =K31/K51 | L34: =L31/L51 | M34: =M31/M51 | N34: =N31/N51 | O34: =O31/O51 | P34: =P31/P51 | Q34: =Q31/Q51 | R34: =R31/R51 | ... AN34: =AN31/AN51
A35: EPS (reported) | B35: =B27/B53 | C35: =C27/C53 | D35: =D27/D53 | E35: =E27/E53 | F35: =F27/F53 | G35: =G27/G53 | H35: =H27/H53 | I35: =I27/I53 | J35: =J27/J53 | K35: =K27/K51 | L35: =L27/L51 | M35: =M27/M51 | N35: =N27/N51 | O35: =O27/O51 | P35: =P27/P51 | Q35: =Q27/Q51 | R35: =R27/R51 | ... AN35: =AN27/AN51
A37: Dividend
A38: Interim ordinary dividend | B38: 1095 | C38: 1294 | D38: 1553 | E38: 1792 | F38: 1911 | G38: 2369 | H38: 2673 | I38: 3582 | J38: 2497 | K38: 2605 | L38: 2746 | M38: 2962 | N38: 3251 | O38: 3468 | P38: 3612 | Q38: 3757 | R38: 3757 | S38: 3753 | T38: =1251*3 | U38: 3753 | V38: 3825 | W38: 4017 | X38: 4093 | Y38: 4169 | Z38: 4320 | AA38: 4472 | AB38: 4623 | AC38: 4775 | AD38: 4775 | AE38: 4775 | AF38: 4775 | AG38: 4775 | AH38: 4775 | AI38: =AH38/AH41*AI41 | AJ38: =AI38/AI41*AJ41 | AK38: =AJ38/AJ41*AK41 | AL38: =AK38/AK41*AL41 | AM38: =AL38/AL41*AM41 | AN38: =AM38/AM41*AN41
A39: Final ordinary dividend | B39: 630 | C39: 697 | D39: 736 | E39: 736 | F39: 876 | G39: 1145 | H39: 1175 | I39: 1041 | J39: 1040 | K39: 1059 | L39: 1228 | M39: 1565 | N39: 1758 | O39: 1999 | P39: 2144 | Q39: 2216 | R39: 2214 | S39: 2214 | T39: 2214 | U39: 2310 | V39: 2476 | W39: 2476 | X39: 2526 | Y39: 2653 | Z39: 2754 | AA39: 2880 | AB39: 3007 | AC39: 3007 | AD39: 3057 | AE39: 3057 | AF39: 3057 | AG39: 3057 | AH39: 3183 | AI39: =AI41-AI38 | AJ39: =AJ41-AJ38 | AK39: =AK41-AK38 | AL39: =AL41-AL38 | AM39: =AM41-AM38 | AN39: =AN41-AN38
A40: Special dividend | B40: 0 | C40: 0 | D40: 0 | E40: 697 | F40: 0 | G40: 0 | H40: =1293+245 | I40: 520 | J40: =562+562 | K40: 1469 | L40: 554 | M40: 241 | N40: 361 | O40: 265 | P40: 48 | Q40: 0 | R40: 0 | S40: 0 | T40: 0 | U40: 0 | V40: 0 | W40: 0 | X40: 0 | Y40: 0 | Z40: 0
A41: Total dividend | B41: =SUM(B38:B40) | C41: =SUM(C38:C40) | D41: =SUM(D38:D40) | E41: =SUM(E38:E40) | F41: =SUM(F38:F40) | G41: =SUM(G38:G40) | H41: =SUM(H38:H40) | I41: =SUM(I38:I40) | ... AH41: =SUM(AH38:AH40) | AI41: =AI48*AI51 | AJ41: =AJ48*AJ51 | AK41: =AK48*AK51 | AL41: =AL48*AL51 | AM41: =AM48*AM51 | AN41: =AN48*AN51
A42: Dividend payout ratio | B42: =B41/B31 | C42: =C41/C31 | D42: =D41/D31 | E42: =E41/E31 | F42: =F41/F31 | G42: =G41/G31 | H42: =H41/H31 | I42: =I41/I31 | ... AN42: =AN41/AN31
A44: DPS
A45: Interim DPS (HK$) | B45: =B38/B53 | C45: =C38/C53 | D45: =D38/D53 | E45: =E38/E53 | F45: =F38/F53 | G45: =G38/G53 | H45: =H38/H53 | I45: =I38/I53 | J45: =J38/J53 | K45: =K38/K51 | L45: =3*0.38 | M45: =M38/M51 | N45: =N38/N51 | O45: =O38/O51 | P45: =P38/P51 | Q45: =Q38/Q51 | R45: =R38/R51 | S45: =S38/S51 | T45: =T38/T51 | ... AN45: =AN38/AN51
A46: Final DPS (HK$) | B46: =B48-B45-B47 | C46: =C48-C45-C47 | D46: =D48-D45-D47 | E46: =E48-E45-E47 | F46: =F48-F45-F47 | G46: =G48-G45-G47 | H46: =H48-H45-H47 | I46: =I48-I45-I47 | ... S46: =S48-S45-S47 | T46: =T39/T51 | U46: =U39/U51 | V46: =V39/V51 | W46: =W39/W51 | X46: =X39/X51 | Y46: =Y39/Y51 | Z46: =Z48-Z45-Z47 | AA46: =AA48-AA45-AA47 | AB46: =AB48-AB45-AB47 | AC46: =AC48-AC45-AC47 | AD46: =AD48-AD45-AD47 | AE46: =AE48-AE45-AE47 | AF46: =AF48-AF45-AF47 | AG46: =AG48-AG45-AG47 | ... AN46: =AN48-AN45-AN47
A47: Special dividend | B47: =B40/B53 | C47: =C40/C53 | D47: =D40/D53 | E47: =E40/E53 | F47: =F40/F53 | G47: =G40/G53 | H47: =H40/H53 | I47: =I40/I53 | J47: =J40/J53 | K47: 0.61 | AR47: 2022 | AS47: =AR47+1 | AT47: =AS47+1 | AU47: =AT47+1 | AV47: =AU47+1 | AW47: =AV47+1 | AX47: =AW47+1
A48: Total DPS (HK$) | B48: 0.72212376 | C48: 0.83347734 | D48: 0.95822684 | E48: 1.3500575 | F48: 1.1667008 | G48: 1.233 | H48: 1.817 | I48: 1.892 | J48: =J41/J53 | K48: 2.1 | L48: 1.88 | M48: 1.98 | N48: 2.23 | O48: 2.38 | P48: 2.41 | Q48: 2.48 | R48: 2.48 | S48: 2.48 | T48: 2.48 | U48: 2.52 | V48: =SUM(V45:V46) | W48: =SUM(W45:W46) | X48: =SUM(X45:X46) | Y48: =SUM(Y45:Y46) | Z48: =Z41/Z51 | AA48: =AA41/AA51 | AB48: =AB41/AB51 | AC48: =AC41/AC51 | AD48: =AD41/AD51 | AE48: =AE41/AE51 | AF48: =AF41/AF51 | AG48: =AG41/AG51 | AH48: =AH41/AH51 | AI48: =AH48*(1+AI49) | AJ48: =AI48*(1+AJ49) | AK48: =AJ48*(1+AK49) | AL48: =AK48*(1+AL49) | AM48: =AL48*(1+AM49) | AN48: =AM48*(1+AN49) | AQ48: New UBSe | AR48: =AF48 | AS48: =AG48 | AT48: =AH48 | AU48: =AI48 | AV48: =AJ48 | AW48: =AK48 | AX48: =AL48
A49: Recurring DPS growth | C49: =(C45+C46)/(B45+B46)-1 | D49: =(D45+D46)/(C45+C46)-1 | E49: =(E45+E46)/(D45+D46)-1 | F49: =(F45+F46)/(E45+E46)-1 | G49: =(G45+G46)/(F45+F46)-1 | H49: =(H45+H46)/(G45+G46)-1 | I49: =(I45+I46)/(H45+H46)-1 | J49: =(J45+J46)/(I45+I46)-1 | ... AH49: =(AH45+AH46)/(AG45+AG46)-1 | AI49: 0 | AJ49: 0.03 | AK49: =AJ49 | AL49: =AK49 | AM49: =AL49 | AN49: =AM49 | AQ49: Old UBSe | AU49: =AT48*1.03 | AV49: =AU49*1.03 | AW49: =AV49*1.03 | AX49: =AW49*1.03
A51: Avg shares outstanding (mn) | B51: 1658.88 | C51: 1658.88 | D51: 1990.656 | E51: 1990.656 | F51: 1990.656 | G51: 2287.891 | H51: 2479.523 | I51: 2380.191 | J51: 2081.227 | K51: 2486.583 | L51: 2408.783 | M51: 2408.2459 | N51: 2408.2459 | O51: 2408.2459 | P51: =AVERAGE(O52,P52) | Q51: 2408.246 | R51: 2407.873 | S51: 2406.1434 | T51: 2406.1434 | U51: 2406.143 | V51: 2410.088 | W51: =+AVERAGE(V52:W52) | X51: =AVERAGE(W52,X52) | Y51: =AVERAGE(X52,Y52) | Z51: =AVERAGE(Y52,Z52) | AA51: =AVERAGE(Z52,AA52) | AB51: =AVERAGE(AA52,AB52) | AC51: =AVERAGE(AB52,AC52) | AD51: =AVERAGE(AC52,AD52) | AE51: =AVERAGE(AD52,AE52) | ... AN51: =AVERAGE(AM52,AN52)
A52: Closing shares outstanding (mn) | B52: 1658.88 | C52: 1658.88 | D52: 1990.656 | E52: 1990.656 | F52: 1990.656 | G52: 2488.32 | H52: 2448.5025 | I52: 2081.227 | J52: 2081.227 | K52: 2421.4864 | L52: 2408.2459 | M52: 2408.2459 | N52: 2408.2459 | O52: 2408.2459 | P52: =O52 | Q52: 2408.2459 | R52: 2406.1434 | S52: 2406.1434 | T52: 2406.1434 | U52: =T52 | V52: =U52+120.30717 | W52: =V52 | X52: =W52 | Y52: =X52 | Z52: =Y52 | AA52: =Z52 | AB52: =AA52 | AC52: =AB52 | AD52: =AC52 | ... AN52: =AM52
A53: Adj. no. of shares -end (mn) | B53: =+B52*1.2*1.2 | C53: =+C52*1.2*1.2 | D53: =+D52*1.2 | E53: =+E52*1.2 | F53: =+F52*1.2 | G53: =+G52*1.2 | H53: =+H52*1.2 | I53: =+I52*1.2 | J53: =+J52*1.2 | K53: =+K52 | L53: =+L52 | M53: =+M52 | N53: =+N52 | O53: =+O52 | P53: =+P52 | Q53: =+Q52 | R53: =+R52 | ... AN53: =+AN52
A55: ROE | D55: =+D31/(SUM(C96:D97)/2) | E55: =+E31/(SUM(D96:E97)/2) | F55: =+F31/(SUM(E96:F97)/2) | G55: =+G31/(SUM(F96:G97)/2) | H55: =+H31/(SUM(G96:H97)/2) | I55: =+I31/(SUM(H96:I97)/2) | J55: =+J31/(SUM(I96:J97)/2) | K55: =+K31/(SUM(J96:K97)/2) | ... AN55: =+AN31/(SUM(AM96:AN97)/2)
A56: Balance sheet | AE56: =33888-AE64
A57: Cash and equivalents | B57: 161 | C57: 2122 | D57: 2016 | E57: 1160 | F57: 2058 | G57: 18011 | H57: =8990+5797 | I57: =588+330 | J57: =2162+10 | K57: 80 | L57: 516 | M57: 787 | N57: 2520 | O57: 2041 | P57: 1613 | Q57: 2779 | R57: 782 | S57: 7994 | T57: 4756 | U57: 3866 | V57: 13026 | W57: 5233 | X57: 4393 | Y57: 3799 | Z57: =4467+200 | AA57: =6529+3401 | AB57: =7365+4761 | AC57: =7881+445 | AD57: =10158+1550 | AE57: =8199+61 | AF57: =4251+35 | AG57: =5182+22 | AH57: =4976+23 | AI57: =AH57+AI140 | AJ57: =AI57+AJ140 | AK57: =AJ57+AK140 | AL57: =AK57+AL140 | AM57: =AL57+AM140 | AN57: =AM57+AN140
A58: Marketable securities | B58: 0 | C58: 0 | D58: 0 | E58: 0 | F58: 0 | G58: 0 | H58: 0 | I58: 0 | J58: 0 | K58: 0 | L58: 671 | M58: 10 | N58: 0 | O58: 0 | P58: 0 | Q58: 0 | R58: 0 | S58: 0 | T58: 336 | U58: 0 | V58: 0 | W58: 0 | X58: 0 | Y58: 0 | Z58: 0 | AA58: 0 | AB58: =AA58 | AC58: =AB58 | AD58: =AC58 | AE58: =AD58 | AF58: =AE58 | AG58: =AF58 | AH58: =AG58 | AI58: =AH58 | ... AN58: =AM58
A59: Derivative instruments | B59: 0 | C59: 0 | D59: 0 | E59: 0 | F59: 0 | G59: 0 | H59: 0 | I59: 0 | J59: 0 | K59: 0 | L59: 0 | M59: 0 | N59: 0 | O59: 1302 | P59: 1131 | Q59: 2427 | R59: 1374 | S59: 1472 | T59: 1609 | U59: 2158 | V59: 1759 | W59: 1005 | X59: 659 | Y59: 600 | Z59: 692 | AA59: 1137 | AB59: 799 | AC59: 1035 | AD59: 1816 | AE59: 1475 | AF59: 2107 | AG59: 1077 | AH59: 900 | AI59: =AH59 | AJ59: =AI59 | AK59: =AJ59 | AL59: =AK59 | AM59: =AL59 | AN59: =AM59
A60: Accounts and lease receivables | B60: 1171 | C60: 1330 | D60: 1339 | E60: 1260 | F60: 1443 | G60: =1532+136 | H60: 2288 | I60: 1724 | J60: 1571 | K60: 1581 | L60: 1256 | M60: 4424 | N60: 3564 | O60: 5505 | P60: =8799+126 | Q60: =7121+152 | R60: =8239+128 | S60: =9018+130 | T60: =11118+144 | U60: =19419+142 | V60: =18552+1991+158 | W60: =997+17953+49 | X60: =1086+15719+50 | Y60: =52+13812+902 | Z60: =1424+13799+51 | AA60: =1047+15427+148 | AB60: =847+15917 | AC60: =12986+996 | AD60: =13002+1019 | AE60: =15404+1166+546 | AF60: =17314+804 | AG60: =13650+1151 | AH60: =14114+1055 | AI60: =AH60*AI7/AH7 | AJ60: =AI60*AJ7/AI7 | AK60: =AJ60*AK7/AJ7 | AL60: =AK60*AL7/AK7 | AM60: =AL60*AM7/AL7 | AN60: =AM60*AN7/AM7
A61: Fuel clause account | B61: 0 | C61: 0 | D61: 0 | E61: 0 | F61: 0 | G61: 0 | H61: 0 | I61: 0 | J61: 0 | K61: 0 | L61: 0 | M61: 0 | N61: 0 | O61: 0 | P61: 0 | Q61: 132 | R61: 0 | S61: 0 | T61: 0 | U61: 0 | V61: 0 | W61: 0 | X61: 0 | Y61: 0 | Z61: 0 | AA61: ='SOC Accounts'!AA8-AA72 | AB61: ='SOC Accounts'!AB8-AB72 | AC61: ='SOC Accounts'!AC8-AC72 | AD61: ='SOC Accounts'!AD8-AD72 | AE61: ='SOC Accounts'!AE8 | AF61: ='SOC Accounts'!AF8 | AG61: ='SOC Accounts'!AG8 | AH61: ='SOC Accounts'!AH8 | AI61: ='SOC Accounts'!AI8 | AJ61: ='SOC Accounts'!AJ8 | AK61: ='SOC Accounts'!AK8 | AL61: ='SOC Accounts'!AL8 | ... AN61: ='SOC Accounts'!AN8
A62: Inventories | B62: 45 | C62: 35 | D62: 38 | E62: 43 | F62: 43 | G62: 43 | H62: 42 | I62: 41 | J62: 41 | K62: 43 | L62: 67 | M62: 230 | N62: 299 | O62: 596 | P62: 647 | Q62: 667 | R62: 662 | S62: 715 | T62: 751 | U62: 1470 | V62: 1667 | W62: 1482 | X62: 3618 | Y62: 3110 | Z62: 2565 | AA62: 3050 | AB62: 2840 | AC62: 2510 | AD62: 2872 | AE62: 2941 | AF62: 3696 | AG62: 3327 | AH62: 3513 | AI62: =AH62*AI7/AH7 | AJ62: =AI62*AJ7/AI7 | AK62: =AJ62*AK7/AJ7 | AL62: =AK62*AL7/AK7 | AM62: =AL62*AM7/AL7 | AN62: =AM62*AN7/AM7
A63: Property under development | T63: 0 | U63: 0 | V63: 0 | W63: 0 | X63: 0 | Y63: 0 | Z63: 0 | AA63: 2971 | AB63: 2971 | AC63: 2973 | AD63: 2976 | AE63: 2980 | AF63: 2711 | AG63: 2193 | AH63: 1888 | AI63: =AH63 | AJ63: =AI63 | AK63: =AJ63 | AL63: =AK63 | AM63: =AL63 | AN63: =AM63
A64: Total current assets | B64: =SUM(B57:B62) | C64: =SUM(C57:C62) | D64: =SUM(D57:D62) | E64: =SUM(E57:E62) | F64: =SUM(F57:F62) | G64: =SUM(G57:G62) | H64: =SUM(H57:H62) | I64: =SUM(I57:I62) | ... S64: =SUM(S57:S62) | T64: =SUM(T57:T63) | U64: =SUM(U57:U62) | V64: =SUM(V57:V62) | W64: =SUM(W57:W62) | X64: =SUM(X57:X62) | Y64: =SUM(Y57:Y62) | Z64: =SUM(Z57:Z62) | AA64: =SUM(AA57:AA63) | AB64: =SUM(AB57:AB63) | AC64: =SUM(AC57:AC63) | AD64: =SUM(AD57:AD63) | AE64: =SUM(AE57:AE63) | AF64: =SUM(AF57:AF63) | AG64: =SUM(AG57:AG63) | AH64: =SUM(AH57:AH63) | ... AN64: =SUM(AN57:AN63)
A65: Net fixed assets & leasehold land | B65: 17255 | C65: 19040 | D65: 21119 | E65: 23537 | F65: 25507 | G65: 26917 | H65: 27503 | I65: 28903 | J65: 30692 | K65: 33577 | L65: 36550 | M65: 54157 | N65: 57748 | O65: 63049 | P65: 85653 | Q65: 88609 | R65: 89123 | S65: 98858 | T65: 117460 | U65: 130382 | V65: 134329 | W65: =126876+1806 | X65: =128133+5696 | Y65: =127801+5542 | Z65: =130189+5444 | AA65: =137207+5345 | AB65: =141309+5432 | AC65: =143615+6050 | AD65: =148454+7061 | AE65: =154058+7130 | AF65: =147267+7582 | AG65: =152786+7993 | AH65: =158532+10183 | AI65: =Driver!AI72 | AJ65: =Driver!AJ72 | AK65: =Driver!AK72 | AL65: =Driver!AL72 | AM65: =Driver!AM72 | AN65: =Driver!AN72
A66: Intangible assets | B66: 0 | C66: 0 | D66: 0 | E66: 0 | F66: 0 | G66: 0 | H66: 0 | I66: 0 | J66: 0 | K66: 0 | L66: 0 | M66: -1017 | N66: -1022 | O66: 7949 | P66: 7326 | Q66: 8135 | R66: 6324 | S66: 8105 | T66: 9150 | U66: 27369 | V66: 28479 | W66: 23847 | X66: 31129 | Y66: 28257 | Z66: 27653 | AA66: 29087 | AB66: 26910 | AC66: 20111 | AD66: 20559 | AE66: 19710 | AF66: 18451 | AG66: 12854 | AH66: 12445 | AI66: =AH66+Driver!AI24 | AJ66: =AI66+Driver!AJ24 | AK66: =AJ66+Driver!AK24 | AL66: =AK66+Driver!AL24 | AM66: =AL66+Driver!AM24 | AN66: =AM66+Driver!AN24
A67: Jointly controlled entities | B67: 4498 | C67: 5112 | D67: 5056 | E67: 4973 | F67: 5206 | G67: 5826 | H67: 7932 | I67: 10854 | J67: 12155 | K67: 15786 | L67: 18982 | M67: 14687 | N67: 14998 | O67: 16519 | P67: 19163 | Q67: 17684 | R67: 17791 | S67: 18838 | T67: 20476 | U67: 18226 | V67: 19197 | W67: 19940 | X67: 11176 | Y67: 11250 | Z67: 9971 | AA67: 10383 | AB67: 9674 | AC67: 9999 | AD67: 11017 | AE67: 10602 | AF67: 11748 | AG67: 12518 | AH67: 12188 | AI67: =Driver!AI121 | AJ67: =Driver!AJ121 | AK67: =Driver!AK121 | AL67: =Driver!AL121 | AM67: =Driver!AM121 | AN67: =Driver!AN121
A68: Associates | B68: 0 | C68: 0 | D68: 0 | E68: 0 | F68: 0 | G68: 0 | H68: 1952 | I68: 2156 | J68: 1172.6347 | K68: 1229.6347 | L68: 1426 | M68: 1593 | N68: 1640 | O68: 1641 | P68: 18 | Q68: 299 | R68: 242 | S68: 1813 | T68: 2378 | U68: 1465 | V68: 1856 | W68: 1675 | X68: 786 | Y68: 785 | Z68: 813 | AA68: 8081 | AB68: 7746 | AC68: 8708 | AD68: 9181 | AE68: 8769 | AF68: 9090 | AG68: 9380 | AH68: 8486 | AI68: =Driver!AI130 | AJ68: =Driver!AJ130 | AK68: =Driver!AK130 | AL68: =Driver!AL130 | AM68: =Driver!AM130 | AN68: =Driver!AN130
A69: Lease receivables | B69: 0 | C69: 0 | D69: 0 | E69: 0 | F69: 0 | G69: 0 | H69: 0 | I69: 0 | J69: 0 | K69: 0 | L69: 0 | M69: 0 | N69: 0 | O69: 0 | P69: 2740 | Q69: 3130 | R69: 2387 | S69: 2379 | T69: 2286 | U69: 1847 | V69: 1665 | W69: 989 | X69: 898 | Y69: 799 | Z69: 713 | AA69: 620 | AB69: 0 | AC69: =AB69 | AD69: =AC69 | AE69: =AD69 | AF69: =AE69 | AG69: =AF69 | AH69: =AG69 | AI69: =AH69 | AJ69: =AI69 | ... AN69: =AM69
A70: Deferred tax assets | B70: 0 | C70: 0 | D70: 0 | E70: 0 | F70: 0 | G70: 0 | H70: 0 | I70: 0 | J70: 0 | K70: 0 | L70: 0 | M70: 952 | N70: 1043 | O70: 2537 | P70: 3305 | Q70: 3915 | R70: 2992 | S70: 3355 | T70: 4210 | U70: 1276 | V70: 1025 | W70: 3084 | X70: 3828 | Y70: 1690 | Z70: 981 | AA70: 929 | AB70: 835 | AC70: 524 | AD70: 571 | AE70: 376 | AF70: 2132 | AG70: 2041 | AH70: 1625 | AI70: =AH70 | AJ70: =AI70 | AK70: =AJ70 | AL70: =AK70 | AM70: =AL70 | AN70: =AM70
A71: Employee retirement plan assets | B71: 0 | C71: 0 | D71: 0 | E71: 0 | F71: 0 | G71: 0 | H71: 0 | I71: 0 | J71: 0 | K71: 1194 | L71: 1138 | M71: 0 | N71: 0 | O71: 0 | P71: 0 | Q71: 0 | R71: 0 | S71: 0 | T71: 0 | U71: 0 | V71: 0 | W71: 0 | X71: 0 | Y71: 0 | Z71: 0 | AA71: =Z71 | AB71: =AA71 | AC71: =AB71 | AD71: =AC71 | AE71: =AD71 | AF71: =AE71 | AG71: =AF71 | AH71: =AG71 | ... AN71: =AM71
A72: Fuel clause account | B72: 0 | C72: 0 | D72: 0 | E72: 0 | F72: 152 | G72: 867 | H72: 631 | I72: 327 | J72: 37 | K72: 0 | L72: 0 | M72: 0 | N72: 0 | O72: 0 | P72: 0 | Q72: 0 | R72: 800 | S72: 14 | T72: 294 | U72: 212 | V72: 337 | W72: 0 | X72: 0 | Y72: 0 | Z72: 0 | AA72: ='SOC Accounts'!AA8 | AB72: ='SOC Accounts'!AB8 | AC72: ='SOC Accounts'!AC8 | AD72: ='SOC Accounts'!AD8 | AE72: =AE61-'SOC Accounts'!AE8 | AF72: =AF61-'SOC Accounts'!AF8 | AG72: =AG61-'SOC Accounts'!AG8 | AH72: =AH61-'SOC Accounts'!AH8 | AI72: =AI61-'SOC Accounts'!AI8 | AJ72: =AJ61-'SOC Accounts'!AJ8 | AK72: =AK61-'SOC Accounts'!AK8 | AL72: =AL61-'SOC Accounts'!AL8 | ... AN72: =AN61-'SOC Accounts'!AN8
A73: Derivative instruments | B73: 0 | C73: 0 | D73: 0 | E73: 0 | F73: 0 | G73: 0 | H73: 0 | I73: 0 | J73: 0 | K73: 0 | L73: 0 | M73: 0 | N73: 0 | O73: 260 | P73: 425 | Q73: 675 | R73: 1505 | S73: 1821 | T73: 2736 | U73: 5027 | V73: 3285 | W73: 3118 | X73: 3120 | Y73: 1078 | Z73: 1519 | AA73: 956 | AB73: 1000 | AC73: 1389 | AD73: 1697 | AE73: 2007 | AF73: 1943 | AG73: 1173 | AH73: 1134 | AI73: =AH73 | AJ73: =AI73 | AK73: =AJ73 | AL73: =AK73 | AM73: =AL73 | AN73: =AM73
A74: Investment securities and others | B74: 0 | C74: 0 | D74: 0 | E74: 0 | F74: 0 | G74: 0 | H74: 0 | I74: 773 | J74: 643 | K74: 731 | L74: 287 | M74: 9 | N74: =M74 | O74: 506 | P74: 145 | Q74: 552 | R74: 482 | S74: =1692+327 | T74: =1512+139 | U74: =1288+141 | V74: =1289+141 | W74: =1263+147+2221 | X74: =2554+1707+111 | Y74: =2669+1644+174 | Z74: =3788+1528+181 | AA74: =349+298+1186 | AB74: =300+604+1204 | AC74: =1280+1121 | AD74: =1300+1000 | AE74: =966+2303 | AF74: =909+2443 | AG74: =884+2492 | AH74: =817+1464 | AI74: =AH74+Driver!AI74-Driver!AH74 | AJ74: =AI74+Driver!AJ74-Driver!AI74 | AK74: =AJ74+Driver!AK74-Driver!AJ74 | AL74: =AK74+Driver!AL74-Driver!AK74 | AM74: =AL74+Driver!AM74-Driver!AL74 | AN74: =AM74+Driver!AN74-Driver!AM74
A75: Total assets | B75: =SUM(B64:B74) | C75: =SUM(C64:C74) | D75: =SUM(D64:D74) | E75: =SUM(E64:E74) | F75: =SUM(F64:F74) | G75: =SUM(G64:G74) | H75: =SUM(H64:H74) | I75: =SUM(I64:I74) | ... AN75: =SUM(AN64:AN74)
A76: Current and short-term debt | B76: 436 | C76: 169 | D76: 490 | E76: 1022 | F76: 298 | G76: 1147 | H76: 199 | I76: 403 | J76: 77 | K76: 1499 | L76: 570 | M76: 1095 | N76: 1178 | O76: 3508 | P76: 4264 | Q76: 2868 | R76: 3313 | S76: 6892 | T76: 7816 | U76: 12596 | V76: 6895 | W76: 7118 | X76: 9636 | Y76: 13189 | Z76: 10651 | AA76: 8472 | AB76: 13535 | AC76: 13551 | AD76: 8747 | AE76: 10512 | AF76: 11314 | AG76: 12572 | AH76: 15849 | AI76: =AH76 | AJ76: =AI76 | AK76: =AJ76 | AL76: =AK76 | AM76: =AL76 | AN76: =AM76
A77: Finance lease obligations | B77: 0 | C77: 0 | D77: 0 | E77: 0 | F77: 0 | G77: 0 | H77: 0 | I77: 0 | J77: 0 | K77: 0 | L77: 0 | M77: 0 | N77: 0 | O77: 0 | P77: 1945 | Q77: 1431 | R77: 1403 | S77: 1523 | T77: 1995 | U77: 2200 | V77: 2406 | W77: 2763 | X77: 1 | Y77: 0 | Z77: 0 | AA77: 0 | AB77: 0 | AC77: =AB77 | AD77: =AC77 | AE77: =AD77 | AF77: =AE77 | AG77: =AF77 | AH77: =AG77 | AI77: =AH77 | AJ77: =AI77 | ... AN77: =AM77
A78: Income taxation payable | B78: 378 | C78: 686 | D78: 240 | E78: 237 | F78: 448 | G78: 506 | H78: 931 | I78: 227 | J78: 668 | K78: 166 | L78: 196 | M78: 64 | N78: 403 | O78: 376 | P78: 186 | Q78: 237 | R78: 366 | S78: 208 | T78: 165 | U78: 143 | V78: 233 | W78: 141 | X78: 790 | Y78: 651 | Z78: 792 | AA78: 762 | AB78: 1399 | AC78: 1522 | AD78: 1699 | AE78: 1349 | AF78: 1577 | AG78: 1063 | AH78: 775 | AI78: =AH78-AI23+AI120 | AJ78: =AI78-AJ23+AJ120 | AK78: =AJ78-AK23+AK120 | AL78: =AK78-AL23+AL120 | AM78: =AL78-AM23+AM120 | AN78: =AM78-AN23+AN120
A79: Customer deposits | B79: 1228 | C79: 1345 | D79: 1489 | E79: 1593 | F79: 1678 | G79: 1786 | H79: 1897 | I79: 2046 | J79: 2179 | K79: 2450 | L79: 2684 | M79: 2878 | N79: 3119 | O79: 3308 | P79: 3417 | Q79: 3589 | R79: 3722 | S79: 3854 | T79: 3979 | U79: 4297 | V79: 4420 | W79: 4506 | X79: 4653 | Y79: 4829 | Z79: 4999 | AA79: 5221 | AB79: 5476 | AC79: 5679 | AD79: 5908 | AE79: 6254 | AF79: 6633 | AG79: 6880 | AH79: 7207 | AI79: =AH79*AH79/AG79 | AJ79: =AI79*AI79/AH79 | AK79: =AJ79*AJ79/AI79 | AL79: =AK79*AK79/AJ79 | AM79: =AL79*AL79/AK79 | AN79: =AM79*AM79/AL79
A80: Dividends payable | B80: 630 | C80: 697 | D80: 736 | E80: 736 | F80: 876 | G80: 1145 | H80: 1420 | I80: 1561 | J80: 1602 | K80: 2528 | L80: 0 | M80: 0 | N80: 0 | O80: 0 | P80: 0 | Q80: 0 | R80: 0 | S80: 0 | T80: 0 | U80: 0 | V80: 0 | W80: 0 | X80: 0 | Y80: 0 | Z80: 0 | AA80: 0 | AB80: 0 | AC80: 0 | AD80: 0 | AE80: 0 | AF80: 0 | AG80: 0 | AH80: 0 | AI80: 0 | AJ80: 0 | AK80: 0 | AL80: 0 | AM80: 0 | AN80: 0
A81: Fuel clause account | T81: 0 | U81: 0 | V81: 0 | W81: 0 | X81: 0 | Y81: 0 | Z81: 0 | AA81: 2212 | AB81: 901 | AC81: 1131 | AD81: 346 | AE81: ='SOC Accounts'!AE9 | AF81: ='SOC Accounts'!AF9 | AG81: ='SOC Accounts'!AG9 | AH81: ='SOC Accounts'!AH9 | AI81: ='SOC Accounts'!AI9 | AJ81: ='SOC Accounts'!AJ9 | AK81: ='SOC Accounts'!AK9 | AL81: ='SOC Accounts'!AL9 | ... AN81: ='SOC Accounts'!AN9
A82: Derivative instruments | B82: 0 | C82: 0 | D82: 0 | E82: 0 | F82: 0 | G82: 0 | H82: 0 | I82: 0 | J82: 0 | K82: 0 | L82: 0 | M82: 0 | N82: 0 | O82: 1134 | P82: 1285 | Q82: 1689 | R82: 1198 | S82: 1035 | T82: 932 | U82: 2212 | V82: 1762 | W82: 1279 | X82: 709 | Y82: 595 | Z82: 977 | AA82: 789 | AB82: 1262 | AC82: 993 | AD82: 1166 | AE82: 1302 | AF82: 5310 | AG82: 1658 | AH82: 1185 | AI82: =AH82 | AJ82: =AI82 | AK82: =AJ82 | AL82: =AK82 | AM82: =AL82 | AN82: =AM82
A83: Trade and other payables | B83: 1553 | C83: 2958 | D83: 3529 | E83: 2720 | F83: 2618 | G83: =2340+136 | H83: 2235 | I83: 1681 | J83: 2469 | K83: 2678 | L83: =3091+115 | M83: 3994 | N83: 4216 | O83: 6079 | P83: 5893 | Q83: 6023 | R83: 5919 | S83: 8926 | T83: 11344 | U83: 16990 | V83: 21732 | W83: 19325 | X83: 21619 | Y83: 19023 | Z83: 19921 | AA83: 18978 | AB83: 19061 | AC83: 17586 | AD83: 18141 | AE83: 18381 | AF83: 19627 | AG83: 20306 | AH83: 19788 | AI83: =+AH83/(AH10-AH7)*(AI10-AI7) | AJ83: =+AI83/(AI10-AI7)*(AJ10-AJ7) | AK83: =+AJ83/(AJ10-AJ7)*(AK10-AK7) | AL83: =+AK83/(AK10-AK7)*(AL10-AL7) | AM83: =+AL83/(AL10-AL7)*(AM10-AM7) | AN83: =+AM83/(AM10-AM7)*(AN10-AN7)
A84: Total current liabilities | B84: =SUM(B76:B83) | C84: =SUM(C76:C83) | D84: =SUM(D76:D83) | E84: =SUM(E76:E83) | F84: =SUM(F76:F83) | G84: =SUM(G76:G83) | H84: =SUM(H76:H83) | I84: =SUM(I76:I83) | ... AN84: =SUM(AN76:AN83)
A85: Long-term debt | B85: 819 | C85: 888 | D85: 1007 | E85: 648 | F85: 3021 | G85: 2756 | H85: 2545 | I85: 2375 | J85: 2501 | K85: 4068 | L85: 8727 | M85: 17602 | N85: 17596 | O85: 25883 | P85: 26014 | Q85: 25492 | R85: 23383 | S85: 32539 | T85: 36807 | U85: 52925 | V85: 59303 | W85: 48933 | X85: 57799 | Y85: 42294 | Z85: 40995 | AA85: 48869 | AB85: 41763 | AC85: 38798 | AD85: 45601 | AE85: 47703 | AF85: 47903 | AG85: 44943 | AH85: 49305 | AI85: =Driver!AI93-AI76 | AJ85: =Driver!AJ93-AJ76 | AK85: =Driver!AK93-AK76 | AL85: =Driver!AL93-AL76 | AM85: =Driver!AM93-AM76 | AN85: =Driver!AN93-AN76
A86: Long-term finance lease obligations | P86: 20865 | Q86: 20785 | R86: 20362 | S86: 20332 | T86: 25105 | U86: 25196 | V86: 24649 | W86: 25213 | X86: 26 | Y86: 0 | Z86: 0 | AA86: =Z86 | AB86: =AA86 | AC86: =AB86 | AD86: =AC86 | AE86: =AD86 | AF86: =AE86 | AG86: =AF86 | AH86: =AG86 | ... AN86: =AM86
A87: Fuel clause account | B87: 107 | C87: 630 | D87: 682 | E87: 409 | F87: 0 | G87: 0 | H87: 0 | I87: 0 | J87: 0 | K87: 448 | L87: 512 | M87: 874 | N87: 762 | O87: 323 | P87: 294 | Q87: 0 | R87: 0 | S87: 0 | T87: 0 | U87: 0 | V87: 0 | W87: 1464 | X87: 2966 | Y87: 2226 | Z87: 2867 | AA87: 0 | AB87: 0 | AC87: 0 | AD87: 0 | AE87: 0 | AF87: 0 | AG87: 0 | AH87: 0 | AI87: 0 | AJ87: 0 | AK87: 0 | AL87: 0 | AM87: 0 | AN87: 0
A88: Deferred taxes | B88: 1560 | C88: 1738 | D88: 1963 | E88: 2222 | F88: 2454 | G88: 2639 | H88: 2759 | I88: 2920 | J88: 3110 | K88: 3391 | L88: 3610 | M88: 4614 | N88: 5084 | O88: 5472 | P88: 6054 | Q88: 6344 | R88: 6435 | S88: 7009 | T88: 7590 | U88: 7979 | V88: 8370 | W88: 8548 | X88: 13418 | Y88: 13476 | Z88: 13819 | AA88: 14275 | AB88: 14650 | AC88: 15117 | AD88: 15429 | AE88: 15886 | AF88: 16246 | AG88: 16752 | AH88: 17348 | AI88: =AH88 | AJ88: =AI88 | AK88: =AJ88 | AL88: =AK88 | AM88: =AL88 | AN88: =AM88
A89: Derivative instruments | M89: 0 | N89: 0 | O89: 444 | P89: 735 | Q89: 559 | R89: 837 | S89: 617 | T89: 1079 | U89: 5082 | V89: 4084 | W89: 3440 | X89: 3062 | Y89: 2802 | Z89: 1580 | AA89: 1640 | AB89: 1547 | AC89: 1305 | AD89: 2135 | AE89: 1364 | AF89: 1405 | AG89: 1719 | AH89: 1388 | AI89: =AH89 | AJ89: =AI89 | AK89: =AJ89 | AL89: =AK89 | AM89: =AL89 | AN89: =AM89
A90: Scheme of control liabilities | B90: ='SOC Accounts'!B21+'SOC Accounts'!B34 | C90: ='SOC Accounts'!C21+'SOC Accounts'!C34 | D90: ='SOC Accounts'!D21+'SOC Accounts'!D34 | E90: ='SOC Accounts'!E21+'SOC Accounts'!E34 | F90: ='SOC Accounts'!F21+'SOC Accounts'!F34 | G90: ='SOC Accounts'!G21+'SOC Accounts'!G34 | H90: ='SOC Accounts'!H21+'SOC Accounts'!H34 | I90: ='SOC Accounts'!I21+'SOC Accounts'!I34 | ... U90: ='SOC Accounts'!U21+'SOC Accounts'!U34 | V90: ='SOC Accounts'!V21+'SOC Accounts'!V34+'SOC Accounts'!V42 | W90: ='SOC Accounts'!W21+'SOC Accounts'!W34+'SOC Accounts'!W42 | X90: ='SOC Accounts'!X21+'SOC Accounts'!X34+'SOC Accounts'!X42 | Y90: ='SOC Accounts'!Y21+'SOC Accounts'!Y34+'SOC Accounts'!Y42 | Z90: ='SOC Accounts'!Z21+'SOC Accounts'!Z34+'SOC Accounts'!Z42 | AA90: 977 | AB90: 998 | AC90: 1500 | AD90: 2374 | AE90: 3440 | AF90: 3094 | AG90: 2643 | AH90: 3172 | AI90: ='SOC Accounts'!AI21+'SOC Accounts'!AI34+'SOC Accounts'!AI42-'SOC Accounts'!AI41 | AJ90: ='SOC Accounts'!AJ21+'SOC Accounts'!AJ34+'SOC Accounts'!AJ42-'SOC Accounts'!AJ41 | AK90: ='SOC Accounts'!AK21+'SOC Accounts'!AK34+'SOC Accounts'!AK42-'SOC Accounts'!AK41 | AL90: ='SOC Accounts'!AL21+'SOC Accounts'!AL34+'SOC Accounts'!AL42-'SOC Accounts'!AL41 | AM90: ='SOC Accounts'!AM21+'SOC Accounts'!AM34+'SOC Accounts'!AM42-'SOC Accounts'!AM41 | AN90: ='SOC Accounts'!AN21+'SOC Accounts'!AN34+'SOC Accounts'!AN42-'SOC Accounts'!AN41
A91: Deferred creditors and others | B91: 0 | C91: 68 | D91: 1 | E91: 3 | F91: 2 | G91: 0 | H91: 0 | I91: 0 | J91: 766 | K91: 766 | L91: 670 | M91: 646 | N91: 522 | O91: 934 | P91: 877 | Q91: 964 | R91: 945 | S91: 1074 | T91: 1276 | U91: 2673 | V91: 2456 | W91: 1446 | X91: 2894 | Y91: 2938 | Z91: 2744 | AA91: =2987+1462 | AB91: =3558+1432 | AC91: =3513+1599 | AD91: =3963+2752 | AE91: =4346+2563 | AF91: =4375+2848 | AG91: =5047+3086 | AH91: =4696+2882 | AI91: =AH91 | AJ91: =AI91 | AK91: =AJ91 | AL91: =AK91 | AM91: =AL91 | AN91: =AM91
A92: Total long-term liabilities | B92: =SUM(B85:B91) | C92: =SUM(C85:C91) | D92: =SUM(D85:D91) | E92: =SUM(E85:E91) | F92: =SUM(F85:F91) | G92: =SUM(G85:G91) | H92: =SUM(H85:H91) | I92: =SUM(I85:I91) | ... AN92: =SUM(AN85:AN91)
A94: Share capital and share premium | B94: 8294 | C94: 8294 | D94: 9953 | E94: 9953 | F94: 9953 | G94: 26150 | H94: 25605 | I94: 23768 | J94: 23768 | K94: 23388 | L94: 13205 | M94: 13205 | N94: 13205 | O94: 13205 | P94: 13205 | Q94: 13205 | R94: 13195 | S94: 13195 | T94: 13195 | U94: 13195 | V94: 20751 | W94: 20751 | X94: 23243 | Y94: 23243 | Z94: 23243 | AA94: 23243 | AB94: 23243 | AC94: 23243 | AD94: 23243 | AE94: 23243 | AF94: 23243 | AG94: 23243 | AH94: 23243 | AI94: =AH94 | AJ94: =AI94 | AK94: =AJ94 | AL94: =AK94 | AM94: =AL94 | AN94: =AM94
A95: Total retained earnings | B95: 4570 | C95: 6131 | D95: 6389 | E95: 8838 | F95: 10887 | G95: 13147 | H95: 14862 | I95: 7142 | J95: 8050 | K95: =8058+1194 | L95: =23582+101 | M95: =25230+1806 | N95: =28875+2119 | O95: =2264+34690 | P95: =2192+40441 | Q95: =2216+48480 | R95: =2214+47608 | S95: =2214+55352 | T95: =2214+64252 | U95: =2310+65754 | V95: =2476+67900 | W95: =2476+64134 | X95: =2526+62244 | Y95: 69875 | Z95: 74767 | AA95: 85454 | AB95: 85810 | AC95: 82212 | AD95: 88957 | AE95: 89791 | AF95: 82255 | AG95: 79088 | AH95: 80812 | AI95: =AH95+AI27+AI133+AI132-(AI94-AH94) | AJ95: =AI95+AJ27+AJ133+AJ132-(AJ94-AI94) | AK95: =AJ95+AK27+AK133+AK132-(AK94-AJ94) | AL95: =AK95+AL27+AL133+AL132-(AL94-AK94) | AM95: =AL95+AM27+AM133+AM132-(AM94-AL94) | AN95: =AM95+AN27+AN133+AN132-(AN94-AM94)
A96: Total shareholders’ equity | B96: =B95+B94 | C96: =C95+C94 | D96: =D95+D94 | E96: =E95+E94 | F96: =F95+F94 | G96: =G95+G94 | H96: =H95+H94 | I96: =I95+I94 | ... AN96: =AN95+AN94
A97: Minority Interests | B97: 0 | C97: 0 | D97: 10 | E97: 10 | F97: 10 | G97: 0 | H97: 0 | I97: 0 | J97: 0 | K97: 0 | L97: 0 | M97: 393 | N97: 0 | O97: 111 | P97: 78 | Q97: 95 | R97: 105 | S97: 107 | T97: 97 | U97: 93 | V97: 74 | W97: 120 | X97: =2155+5791 | Y97: =2023+5791 | Z97: =5791+1972 | AA97: =7019+5791 | AB97: =10088+5791 | AC97: =9987+3887 | AD97: =3887+9885 | AE97: =3887+9788 | AF97: =3887+6309 | AG97: =3887+6164 | AH97: 6063 | AI97: =AH97-AI25-AI26+AI135 | AJ97: =AI97-AJ25-AJ26+AJ135 | AK97: =AJ97-AK25-AK26+AK135 | AL97: =AK97-AL25-AL26+AL135 | AM97: =AL97-AM25-AM26+AM135 | AN97: =AM97-AN25-AN26+AN135
A98: Total liabilities and shareholders’ equity | B98: =B96+B92+B84+B97 | C98: =C96+C92+C84+C97 | D98: =D96+D92+D84+D97 | E98: =E96+E92+E84+E97 | F98: =F96+F92+F84+F97 | G98: =G96+G92+G84+G97 | H98: =H96+H92+H84+H97 | I98: =I96+I92+I84+I97 | ... AN98: =AN96+AN92+AN84+AN97
A99: * change to December year end from 1999 | B99: =B98-B75 | C99: =C98-C75 | D99: =D98-D75 | E99: =E98-E75 | F99: =F98-F75 | G99: =G98-G75 | H99: =H98-H75 | I99: =I98-I75 | ... AN99: =AN98-AN75
T100: =+T99-S99 | U100: =+U99-T99 | V100: =+V99-U99 | W100: =+W99-V99 | X100: =+X99-W99 | Y100: =+Y99-X99 | Z100: =+Z99-Y99 | AA100: =+AA99-Z99 | ... AN100: =+AN99-AM99
A101: Cash flow statement
A102: Profit before tax | B102: =B22 | C102: =C22 | D102: =D22 | E102: =E22 | F102: =F22 | G102: =G22 | H102: =H22 | I102: =I22 | ... AN102: =AN22
A103: Net interest expense (income) | B103: =-B21 | C103: =-C21 | D103: =-D21 | E103: =-E21 | F103: =-F21 | G103: =-G21 | H103: =-H21 | I103: =-I21 | J103: =-J21-20 | K103: =-K21-7 | L103: =-L21-5 | M103: =-M21-66 | N103: =-N21-218 | O103: =-O21-230 | P103: =4762-138 | Q103: 5024 | R103: =4245-124 | S103: =3477-69 | T103: =4212-101 | U103: =6005-146 | V103: =6423-322-104 | W103: =6522-173-61 | X103: =4180-131-48 | Y103: =4106-170-46 | Z103: =2261-137-43 | AA103: =2180-151-9 | AB103: =2049-192-13 | AC103: =1983-162-13 | AD103: 1873 | AE103: =1744-108-15 | AF103: =2085-243-14 | AG103: =2139-270-15 | AH103: =2254-235-15 | AI103: =-Driver!AI106 | AJ103: =-Driver!AJ106 | AK103: =-Driver!AK106 | AL103: =-Driver!AL106 | AM103: =-Driver!AM106 | AN103: =-Driver!AN106
A104: Less earnings from JCE/Associates | B104: -1100 | C104: -1195 | D104: -1433 | E104: -2939 | F104: -1847 | G104: -1972.6 | H104: -3949.8 | I104: -3365.2919 | J104: -2678.2347 | K104: -4162 | L104: -3360 | M104: -3792 | N104: -3604 | O104: -3239 | P104: -3050 | Q104: -3025 | R104: -2597 | S104: -2415 | T104: -2893 | U104: -3610 | V104: -2984 | W104: -3283 | X104: -2333 | Y104: -2245 | Z104: -1641 | AA104: -1458 | AB104: -2336 | AC104: -2713 | AD104: -2522 | AE104: -1974 | AF104: -2460 | AG104: -3196 | AH104: -2655 | AI104: =-Driver!AI37 | AJ104: =-Driver!AJ37 | AK104: =-Driver!AK37 | AL104: =-Driver!AL37 | AM104: =-Driver!AM37 | AN104: =-Driver!AN37
A105: Depreciation and amortisation | B105: =-B12 | C105: =-C12 | D105: =-D12 | E105: =-E12 | F105: =-F12 | G105: =-G12 | H105: =-H12 | I105: =-I12 | ... R105: =-R12 | S105: 4332 | T105: =-T12 | U105: =-U12 | V105: =-V12 | W105: =-W12 | X105: =-X12 | Y105: =-Y12 | Z105: =-Z12 | AA105: =-AA12 | ... AN105: =-AN12
A106: Loss (gain) on asset disposals | B106: 0 | C106: 0 | D106: 33 | E106: 36 | F106: 14 | G106: 5 | H106: 52 | I106: =87-35 | J106: =100-7 | K106: =107-52 | L106: 79 | M106: =152+16 | N106: =212-214+38 | O106: =103-128-37 | P106: =216-25-8 | Q106: =353+211-1030-1092 | R106: =131+140-502-225 | S106: =299+172-153 | T106: =204+183-400 | U106: =3233+122-319-457 | V106: =1429+151 | W106: =6289+173-751+23-24 | X106: =3264+282-245-7363+5338 | Y106: =2462+74+343+42-8900-99 | Z106: =397-78-386+146 | AA106: =443+407-369 | AB106: =912+416-18 | AC106: =6782+424+83 | AD106: =599+358+121 | AE106: =586+386+34-386 | AF106: =265+241+57+185 | AG106: =6220+393+25 | AH106: =504+582+67 | AI106: =-Final!AI28 | AJ106: =-Final!AJ28 | AK106: =-Final!AK28 | AL106: =-Final!AL28 | AM106: =-Final!AM28 | AN106: =-Final!AN28
A107: Hedging costs | B107: 0 | C107: 0 | D107: 0 | E107: 0 | F107: 0 | G107: 0 | H107: 0 | I107: 0 | J107: 0 | K107: 0 | L107: -28 | M107: 32 | N107: 52 | O107: 241 | P107: 33 | Q107: 49 | R107: 168 | S107: -48 | T107: -64 | U107: 134 | V107: 568 | W107: -284 | X107: -513 | Y107: 362 | Z107: -211 | AA107: -416 | AB107: -522 | AC107: -230 | AD107: -1150 | AE107: -1805 | AF107: 1922 | AG107: -2911 | AH107: -1297 | AI107: 0 | AJ107: =AI107 | AK107: =AJ107 | AL107: =AK107 | AM107: =AL107 | AN107: =AM107
...

Sheet Driver
A1: HK$ m | B1: =Final!B2 | C1: =Final!C2 | D1: =Final!D2 | E1: =Final!E2 | F1: =Final!F2 | G1: =Final!G2 | H1: =Final!H2 | I1: =Final!I2 | ... AN1: =Final!AN2
A2: Income Statements
A3: Revenue
A4: Hong Kong | B4: =SOC!B4 | C4: =SOC!C4 | D4: =SOC!D4 | E4: =SOC!E4 | F4: =SOC!F4 | G4: =SOC!G4 | H4: =SOC!H4 | I4: =SOC!I4 | ... AG4: =SOC!AG4 | AH4: ='HK Sales'!AH8 | AI4: ='HK Sales'!AI8 | AJ4: ='HK Sales'!AJ8 | AK4: ='HK Sales'!AK8 | AL4: ='HK Sales'!AL8 | AM4: ='HK Sales'!AM8 | AN4: ='HK Sales'!AN8
A5: Transfer from development fund | O5: -527 | P5: 202 | Q5: 353 | R5: -193 | S5: -143 | T5: -76 | U5: 586 | V5: -304 | W5: 641 | X5: -1020 | Y5: 181 | Z5: 260 | AA5: 98 | AB5: -322 | AC5: 714 | AD5: 660 | AE5: 1183 | AF5: 604 | AG5: -48 | AH5: 505 | AI5: =SOC!AI23 | AJ5: =SOC!AJ23 | AK5: =SOC!AK23 | AL5: =SOC!AL23 | AM5: =SOC!AM23 | AN5: =SOC!AN23
A6: Australia | B6: =Aus!B5 | C6: =Aus!C5 | D6: =Aus!D5 | E6: =Aus!E5 | F6: =Aus!F5 | G6: =Aus!G5 | H6: =Aus!H5 | I6: =Aus!I5 | ... AN6: =Aus!AN5
A7: China | B7: =CN!B4 | C7: =CN!C4 | D7: =CN!D4 | E7: =CN!E4 | F7: =CN!F4 | G7: =CN!G4 | H7: =CN!H4 | I7: =CN!I4 | ... AN7: =CN!AN4
A8: India | B8: =India!B5 | C8: =India!C5 | D8: =India!D5 | E8: =India!E5 | F8: =India!F5 | G8: =India!G5 | H8: =India!H5 | I8: =India!I5 | ... AN8: =India!AN5
A9: SEA and Taiwan | B9: =SEA!B5 | C9: =SEA!C5 | D9: =SEA!D5 | E9: =SEA!E5 | F9: =SEA!F5 | G9: =SEA!G5 | H9: =SEA!H5 | I9: =SEA!I5 | ... AN9: =SEA!AN5
A10: Others | B10: =B11-SUM(B4:B9) | C10: =C11-SUM(C4:C9) | D10: =D11-SUM(D4:D9) | E10: =E11-SUM(E4:E9) | F10: =F11-SUM(F4:F9) | G10: =G11-SUM(G4:G9) | H10: =H11-SUM(H4:H9) | I10: =I11-SUM(I4:I9) | ... AH10: =AH11-SUM(AH4:AH9) | AI10: =AH10 | AJ10: =AI10 | AK10: =AJ10 | AL10: =AK10 | AM10: =AL10 | AN10: =AM10
A11: Total revenue | B11: =Final!B7 | C11: =Final!C7 | D11: =Final!D7 | E11: =Final!E7 | F11: =Final!F7 | G11: =Final!G7 | H11: =Final!H7 | I11: =Final!I7 | ... AH11: =Final!AH7 | AI11: =SUM(AI4:AI10) | AJ11: =SUM(AJ4:AJ10) | AK11: =SUM(AK4:AK10) | AL11: =SUM(AL4:AL10) | AM11: =SUM(AM4:AM10) | AN11: =SUM(AN4:AN10)
A13: D&A
A14: Hong Kong | O14: =SOC!O10 | P14: =SOC!P10 | Q14: =SOC!Q10 | R14: =SOC!R10 | S14: =SOC!S10 | T14: =SOC!T10 | U14: =SOC!U10 | V14: =SOC!V10 | ... AN14: =SOC!AN10
A15: Australia | B15: =Aus!B15 | C15: =Aus!C15 | D15: =Aus!D15 | E15: =Aus!E15 | F15: =Aus!F15 | G15: =Aus!G15 | H15: =Aus!H15 | I15: =Aus!I15 | ... AN15: =Aus!AN15
A16: China | B16: =CN!B11 | C16: =CN!C11 | D16: =CN!D11 | E16: =CN!E11 | F16: =CN!F11 | G16: =CN!G11 | H16: =CN!H11 | I16: =CN!I11 | ... AN16: =CN!AN11
A17: India | B17: =India!B8 | C17: =India!C8 | D17: =India!D8 | E17: =India!E8 | F17: =India!F8 | G17: =India!G8 | H17: =India!H8 | I17: =India!I8 | ... AD17: =India!AD8 | AE17: -671 | AF17: -283 | AG17: 0 | AH17: 0 | AI17: =India!AI8 | AJ17: =India!AJ8 | AK17: =India!AK8 | AL17: =India!AL8 | AM17: =India!AM8 | AN17: =India!AN8
A18: SEA and Taiwan | B18: =SEA!B9 | C18: =SEA!C9 | D18: =SEA!D9 | E18: =SEA!E9 | F18: =SEA!F9 | G18: =SEA!G9 | H18: =SEA!H9 | I18: =SEA!I9 | ... AN18: =SEA!AN9
A19: Others | B19: =B20-SUM(B14:B18) | C19: =C20-SUM(C14:C18) | D19: =D20-SUM(D14:D18) | E19: =E20-SUM(E14:E18) | F19: =F20-SUM(F14:F18) | G19: =G20-SUM(G14:G18) | H19: =H20-SUM(H14:H18) | I19: =I20-SUM(I14:I18) | ... AH19: =AH20-SUM(AH14:AH18) | AI19: =AH19 | AJ19: =AI19 | AK19: =AJ19 | AL19: =AK19 | AM19: =AL19 | AN19: =AM19
A20: Total Depreciation | B20: =B26-B24 | C20: =C26-C24 | D20: =D26-D24 | E20: =E26-E24 | F20: =F26-F24 | G20: =G26-G24 | H20: =H26-H24 | I20: =I26-I24 | ... AH20: =AH26-AH24 | AI20: =SUM(AI14:AI19) | AJ20: =SUM(AJ14:AJ19) | AK20: =SUM(AK14:AK19) | AL20: =SUM(AL14:AL19) | AM20: =SUM(AM14:AM19) | AN20: =SUM(AN14:AN19)
A22: Australia | B22: =Aus!B14 | C22: =Aus!C14 | D22: =Aus!D14 | E22: =Aus!E14 | F22: =Aus!F14 | G22: =Aus!G14 | H22: =Aus!H14 | I22: =Aus!I14 | ... AN22: =Aus!AN14
A23: China | B23: =CN!B10 | C23: =CN!C10 | D23: =CN!D10 | E23: =CN!E10 | F23: =CN!F10 | G23: =CN!G10 | H23: =CN!H10 | I23: =CN!I10 | ... AN23: =CN!AN10
A24: Total Amortization | B24: =B22+B23 | C24: =C22+C23 | D24: =D22+D23 | E24: =E22+E23 | F24: =F22+F23 | G24: =G22+G23 | H24: =H22+H23 | I24: =I22+I23 | ... AN24: =AN22+AN23
A26: Total D&A | B26: =Final!B12 | C26: =Final!C12 | D26: =Final!D12 | E26: =Final!E12 | F26: =Final!F12 | G26: =Final!G12 | H26: =Final!H12 | I26: =Final!I12 | ... AH26: =Final!AH12 | AI26: =AI20+AI24 | AJ26: =AJ20+AJ24 | AK26: =AK20+AK24 | AL26: =AL20+AL24 | AM26: =AM20+AM24 | AN26: =AN20+AN24
A28: Operating Income before JCEs | B28: =Final!B15 | C28: =Final!C15 | D28: =Final!D15 | E28: =Final!E15 | F28: =Final!F15 | G28: =Final!G15 | H28: =Final!H15 | I28: =Final!I15 | ... AN28: =Final!AN15
A30: JCEs
A31: Hong Kong
A32: Australia | T32: =Aus!T9+Aus!T10 | U32: =Aus!U9+Aus!U10 | V32: =Aus!V9+Aus!V10 | W32: =Aus!W9+Aus!W10 | X32: =Aus!X9+Aus!X10 | Y32: =Aus!Y9+Aus!Y10 | Z32: =Aus!Z9+Aus!Z10 | AA32: =Aus!AA9+Aus!AA10 | ... AN32: =Aus!AN9+Aus!AN10
A33: China | T33: =CN!T6+CN!T7 | U33: =CN!U6+CN!U7 | V33: =CN!V6+CN!V7 | W33: =CN!W6+CN!W7 | X33: =CN!X6+CN!X7 | Y33: =CN!Y6+CN!Y7 | Z33: =CN!Z6+CN!Z7 | AA33: =CN!AA6+CN!AA7 | ... AN33: =CN!AN6+CN!AN7
A34: India | T34: 0 | U34: 0 | V34: 0 | W34: 0 | X34: 0 | Y34: 0 | Z34: 0 | AA34: 0 | AB34: 0 | AC34: 0 | AD34: 0 | AE34: 0 | AF34: 0 | AG34: 0 | AH34: 0 | AI34: 0 | AJ34: 0 | AK34: 0 | AL34: 0 | AM34: 0 | AN34: 0
A35: SEA and Taiwan | T35: =SEA!T7 | U35: =SEA!U7 | V35: =SEA!V7 | W35: =SEA!W7 | X35: =SEA!X7 | Y35: =SEA!Y7 | Z35: =SEA!Z7 | AA35: =SEA!AA7 | ... AN35: =SEA!AN7
A36: Others | T36: =T37-SUM(T32:T35) | U36: =U37-SUM(U32:U35) | V36: =V37-SUM(V32:V35) | W36: =W37-SUM(W32:W35) | X36: =X37-SUM(X32:X35) | Y36: =Y37-SUM(Y32:Y35) | Z36: =Z37-SUM(Z32:Z35) | AA36: =AA37-SUM(AA32:AA35) | ... AH36: =AH37-SUM(AH32:AH35) | AI36: =AH36 | AJ36: =AI36 | AK36: =AJ36 | AL36: =AK36 | AM36: =AL36 | AN36: =AM36
A37: Total earnings from JCEs | B37: =Final!B18+Final!B19 | C37: =Final!C18+Final!C19 | D37: =Final!D18+Final!D19 | E37: =Final!E18+Final!E19 | F37: =Final!F18+Final!F19 | G37: =Final!G18+Final!G19 | H37: =Final!H18+Final!H19 | I37: =Final!I18+Final!I19 | ... AG37: =Final!AG18+Final!AG19 | AH37: 2655 | AI37: =SUM(AI32:AI36) | AJ37: =SUM(AJ32:AJ36) | AK37: =SUM(AK32:AK36) | AL37: =SUM(AL32:AL36) | AM37: =SUM(AM32:AM36) | AN37: =SUM(AN32:AN36)
A38: Earnings from JV | B38: =Final!B18 | C38: =Final!C18 | D38: =Final!D18 | E38: =Final!E18 | F38: =Final!F18 | G38: =Final!G18 | H38: =Final!H18 | I38: =Final!I18 | ... AH38: =Final!AH18 | AI38: =AI37-AI39 | AJ38: =AJ37-AJ39 | AK38: =AK37-AK39 | AL38: =AL37-AL39 | AM38: =AM37-AM39 | AN38: =AN37-AN39
A39: Earnings from Associates | B39: =Final!B19 | C39: =Final!C19 | D39: =Final!D19 | E39: =Final!E19 | F39: =Final!F19 | G39: =Final!G19 | H39: =Final!H19 | I39: =Final!I19 | ... AH39: =Final!AH19 | AI39: =CN!AI7+Aus!AI10 | AJ39: =CN!AJ7+Aus!AJ10 | AK39: =CN!AK7+Aus!AK10 | AL39: =CN!AL7+Aus!AL10 | AM39: =CN!AM7+Aus!AM10 | AN39: =CN!AN7+Aus!AN10
A41: Taxation
A42: Hong Kong | B42: =SOC!B14 | C42: =SOC!C14 | D42: =SOC!D14 | E42: =SOC!E14 | F42: =SOC!F14 | G42: =SOC!G14 | H42: =SOC!H14 | I42: =SOC!I14 | ... AN42: =SOC!AN14
A43: Australia | B43: =Aus!B27 | C43: =Aus!C27 | D43: =Aus!D27 | E43: =Aus!E27 | F43: =Aus!F27 | G43: =Aus!G27 | H43: =Aus!H27 | I43: =Aus!I27 | ... AN43: =Aus!AN27
A44: China | B44: =CN!B16 | C44: =CN!C16 | D44: =CN!D16 | E44: =CN!E16 | F44: =CN!F16 | G44: =CN!G16 | H44: =CN!H16 | I44: =CN!I16 | ... AN44: =CN!AN16
A45: India | B45: =India!B17 | C45: =India!C17 | D45: =India!D17 | E45: =India!E17 | F45: =India!F17 | G45: =India!G17 | H45: =India!H17 | I45: =India!I17 | ... AN45: =India!AN17
A46: SEA and Taiwan | B46: =SEA!B17 | C46: =SEA!C17 | D46: =SEA!D17 | E46: =SEA!E17 | F46: =SEA!F17 | G46: =SEA!G17 | H46: =SEA!H17 | I46: =SEA!I17 | ... AN46: =SEA!AN17
A47: Others | B47: =B48-SUM(B42:B46) | C47: =C48-SUM(C42:C46) | D47: =D48-SUM(D42:D46) | E47: =E48-SUM(E42:E46) | F47: =F48-SUM(F42:F46) | G47: =G48-SUM(G42:G46) | H47: =H48-SUM(H42:H46) | I47: =I48-SUM(I42:I46) | ... AH47: =AH48-SUM(AH42:AH46) | AI47: =AH47 | AJ47: =AI47 | AK47: =AJ47 | AL47: =AK47 | AM47: =AL47 | AN47: =AM47
A48: Total | B48: =Final!B23 | C48: =Final!C23 | D48: =Final!D23 | E48: =Final!E23 | F48: =Final!F23 | G48: =Final!G23 | H48: =Final!H23 | I48: =Final!I23 | ... AH48: =Final!AH23 | AI48: =SUM(AI42:AI47) | AJ48: =SUM(AJ42:AJ47) | AK48: =SUM(AK42:AK47) | AL48: =SUM(AL42:AL47) | AM48: =SUM(AM42:AM47) | AN48: =SUM(AN42:AN47)
A50: Recurring earnings
A51: Hong Kong | B51: =SOC!B46 | C51: =SOC!C46 | D51: =SOC!D46 | E51: =SOC!E46 | F51: =SOC!F46 | G51: =SOC!G46 | H51: =SOC!H46 | I51: =SOC!I46 | ... AN51: =SOC!AN46
A52: Australia | B52: =Aus!B29 | C52: =Aus!C29 | D52: =Aus!D29 | E52: =Aus!E29 | F52: =Aus!F29 | G52: =Aus!G29 | H52: =Aus!H29 | I52: =Aus!I29 | ... AN52: =Aus!AN29
A53: China | B53: =CN!B20 | C53: =CN!C20 | D53: =CN!D20 | E53: =CN!E20 | F53: =CN!F20 | G53: =CN!G20 | H53: =CN!H20 | I53: =CN!I20 | ... AN53: =CN!AN20
A54: India | B54: =India!B19 | C54: =India!C19 | D54: =India!D19 | E54: =India!E19 | F54: =India!F19 | G54: =India!G19 | H54: =India!H19 | I54: =India!I19 | ... AN54: =India!AN19
A55: SEA and Taiwan | B55: =SEA!B18 | C55: =SEA!C18 | D55: =SEA!D18 | E55: =SEA!E18 | F55: =SEA!F18 | G55: =SEA!G18 | H55: =SEA!H18 | I55: =SEA!I18 | ... AN55: =SEA!AN18
A56: Sales to Guangdong | T56: 2 | U56: -4 | V56: 41 | W56: =125-17-CN!W41 | X56: =71-66-CN!X41 | Y56: -5 | Z56: 56 | AA56: 65 | AB56: 35 | AC56: 0 | AD56: =AC56 | AE56: =AD56 | AF56: =AE56 | AG56: =AF56 | AH56: =AG56 | AI56: =AH56 | AJ56: =AI56 | AK56: =AJ56 | ... AN56: =AM56
A57: Others | B57: =B58-SUM(B51:B56) | C57: =C58-SUM(C51:C56) | D57: =D58-SUM(D51:D56) | E57: =E58-SUM(E51:E56) | F57: =F58-SUM(F51:F56) | G57: =G58-SUM(G51:G56) | H57: =H58-SUM(H51:H56) | I57: =I58-SUM(I51:I56) | ... AH57: =AH58-SUM(AH51:AH56) | AI57: =AH57*1.03 | AJ57: =AI57*1.03 | AK57: =AJ57*1.03 | AL57: =AK57*1.03 | AM57: =AL57*1.03 | AN57: =AM57*1.03
A58: Total | B58: =Final!B31 | C58: =Final!C31 | D58: =Final!D31 | E58: =Final!E31 | F58: =Final!F31 | G58: =Final!G31 | H58: =Final!H31 | I58: =Final!I31 | ... AH58: =Final!AH31 | AI58: =SUM(AI51:AI57) | AJ58: =SUM(AJ51:AJ57) | AK58: =SUM(AK51:AK57) | AL58: =SUM(AL51:AL57) | AM58: =SUM(AM51:AM57) | AN58: =SUM(AN51:AN57)
A60: Hong Kong | C60: =C51/B51-1 | D60: =D51/C51-1 | E60: =E51/D51-1 | F60: =F51/E51-1 | G60: =G51/F51-1 | H60: =H51/G51-1 | I60: =I51/H51-1 | J60: =J51/I51-1 | ... AN60: =AN51/AM51-1
A61: Australia | O61: =O52/N52-1 | P61: =P52/O52-1 | Q61: =Q52/P52-1 | R61: =R52/Q52-1 | S61: =S52/R52-1 | T61: =T52/S52-1 | U61: =U52/T52-1 | V61: =V52/U52-1 | ... AN61: =AN52/AM52-1
A62: China | M62: =M53/L53-1 | N62: =N53/M53-1 | O62: =O53/N53-1 | P62: =P53/O53-1 | Q62: =Q53/P53-1 | R62: =R53/Q53-1 | S62: =S53/R53-1 | T62: =T53/S53-1 | ... AN62: =AN53/AM53-1
A63: India | P63: =P54/O54-1 | Q63: =Q54/P54-1 | R63: =R54/Q54-1 | S63: =S54/R54-1 | T63: =T54/S54-1 | U63: =U54/T54-1 | V63: =V54/U54-1 | W63: =W54/V54-1 | ... AN63: =AN54/AM54-1
A64: SEA and Taiwan | P64: =P55/O55-1 | Q64: =Q55/P55-1 | R64: =R55/Q55-1 | S64: =S55/R55-1 | T64: =T55/S55-1 | U64: =U55/T55-1 | V64: =V55/U55-1 | W64: =W55/V55-1 | ... AN64: =AN55/AM55-1
A65: Others | C65: =C57/B57-1 | D65: =D57/C57-1 | E65: =E57/D57-1 | F65: =F57/E57-1 | G65: =G57/F57-1 | H65: =H57/G57-1 | I65: =I57/H57-1 | J65: =J57/I57-1 | ... AN65: =AN57/AM57-1
A66: YoY growth | C66: =C58/B58-1 | D66: =D58/C58-1 | E66: =E58/D58-1 | F66: =F58/E58-1 | G66: =G58/F58-1 | H66: =H58/G58-1 | I66: =I58/H58-1 | J66: =J58/I58-1 | ... AN66: =AN58/AM58-1
A68: Balance Sheet
A69: PPE
A70: Gross Fixed Assets | B70: 22219 | C70: 24710 | D70: 27468 | E70: 30684 | F70: 33560 | G70: 35984 | H70: 37690 | I70: 40576 | J70: 43523 | K70: 47713 | L70: 52079 | M70: 76206 | N70: 81930 | O70: 90685 | P70: 137985 | Q70: 145170 | R70: 146785 | S70: 162050 | T70: 186145 | U70: 206384 | V70: 215972 | W70: 216947 | X70: 224774 | Y70: =221703+6272 | Z70: =228517+6344 | AA70: =243075+6441 | AB70: =248668+6704 | AC70: =255682+6050+295+1272 | AD70: =268541+7061+352 | AE70: =279895+7130+342 | AF70: =271066+7582+352 | AG70: =282945+7993+376 | AH70: =292564+10183+343 | AI70: =AH70+AI90 | AJ70: =AI70+AJ90 | AK70: =AJ70+AK90 | AL70: =AK70+AL90 | AM70: =AL70+AM90 | AN70: =AM70+AN90
A71: Accumulated Depreciation | B71: -4964 | C71: -5670 | D71: -6349 | E71: -7147 | F71: -8053 | G71: -9067 | H71: -10187 | I71: -11673 | J71: -12831 | K71: -14136 | L71: -15529 | M71: -22049 | N71: -24182 | O71: -27636 | P71: -52332 | Q71: -56561 | R71: -57662 | S71: -63192 | T71: -68685 | U71: -76002 | V71: -81643 | W71: -88265 | X71: -90945 | Y71: =-93902-730 | Z71: =-98328-900 | AA71: =-105868-1096 | AB71: =-107359-1272 | AC71: =-112067-1272-295 | AD71: =-120087-352 | AE71: =-125837-342 | AF71: =-123799-352 | AG71: =-130159-376 | AH71: =-134032-343 | AI71: =AH71+AI20 | AJ71: =AI71+AJ20 | AK71: =AJ71+AK20 | AL71: =AK71+AL20 | AM71: =AL71+AM20 | AN71: =AM71+AN20
A72: Net fixed assets | B72: =Final!B65 | C72: =Final!C65 | D72: =Final!D65 | E72: =Final!E65 | F72: =Final!F65 | G72: =Final!G65 | H72: =Final!H65 | I72: =Final!I65 | ... AA72: =Final!AA65 | AB72: =AB70+AB71 | AC72: =AC70+AC71 | AD72: =AD70+AD71 | AE72: =AE70+AE71 | AF72: =AF70+AF71 | AG72: =AG70+AG71 | AH72: =AH70+AH71 | AI72: =AI70+AI71 | ... AN72: =AN70+AN71
B73: =B70+B71-B72 | C73: =C70+C71-C72 | D73: =D70+D71-D72 | E73: =E70+E71-E72 | F73: =F70+F71-F72 | G73: =G70+G71-G72 | H73: =H70+H71-H72 | I73: =I70+I71-I72 | ... Z73: =Z70+Z71-Z72 | AA73: =AA75-SUM(AA76:AA81) | AB73: =AB75-SUM(AB76:AB81) | AC73: =AC75-SUM(AC76:AC81) | AD73: =AD75-SUM(AD76:AD81) | AE73: =AE75-SUM(AE76:AE81) | AF73: =AF75-SUM(AF76:AF81) | AG73: =AG75-SUM(AG76:AG81) | AH73: =AH75-SUM(AH76:AH81) | ... AN73: =AN75-SUM(AN76:AN81)
A74: Investment properties | S74: 0 | T74: 0 | U74: 0 | V74: 0 | W74: 2221 | X74: 2554 | Y74: 2669 | Z74: 3788 | AA74: 1186 | AB74: 1204 | AC74: 1121 | AD74: 1000 | AE74: 966 | AF74: 909 | AG74: 884 | AH74: 817 | AI74: =AH74 | AJ74: =AI74 | AK74: =AJ74 | AL74: =AK74 | AM74: =AL74 | AN74: =AM74
A75: Net fixed assets and IP | B75: =B72+B74 | C75: =C72+C74 | D75: =D72+D74 | E75: =E72+E74 | F75: =F72+F74 | G75: =G72+G74 | H75: =H72+H74 | I75: =I72+I74 | ... AN75: =AN72+AN74
A76: Hong Kong | B76: =ROAFNA!B46 | C76: =ROAFNA!C46 | D76: =ROAFNA!D46 | E76: =ROAFNA!E46 | F76: =ROAFNA!F46 | G76: =ROAFNA!G46 | H76: =ROAFNA!H46 | I76: =ROAFNA!I46 | ... AN76: =ROAFNA!AN46
A77: Australia | B77: =Aus!B88 | C77: =Aus!C88 | D77: =Aus!D88 | E77: =Aus!E88 | F77: =Aus!F88 | G77: =Aus!G88 | H77: =Aus!H88 | I77: =Aus!I88 | ... AN77: =Aus!AN88
A78: China | B78: =CN!B157 | C78: =CN!C157 | D78: =CN!D157 | E78: =CN!E157 | F78: =CN!F157 | G78: =CN!G157 | H78: =CN!H157 | I78: =CN!I157 | ... AN78: =CN!AN157
A79: India | B79: =India!B50 | C79: =India!C50 | D79: =India!D50 | E79: =India!E50 | F79: =India!F50 | G79: =India!G50 | H79: =India!H50 | I79: =India!I50 | ... AN79: =India!AN50
A80: SEA and Taiwan | B80: 0 | C80: 0 | D80: 0 | E80: 0 | F80: 0 | G80: 0 | H80: 0 | I80: 0 | J80: 0 | K80: 0 | L80: 0 | M80: 0 | N80: 0 | O80: 0 | P80: 0 | Q80: 0 | R80: 0 | S80: 0 | T80: 0 | U80: 0 | V80: 0 | W80: 0 | X80: 0 | Y80: 0 | Z80: 0 | AA80: 0 | AB80: 0 | AC80: 0 | AD80: 0 | AE80: 0 | AF80: 0 | AG80: 0 | AH80: 0 | AI80: 0 | AJ80: 0 | AK80: 0 | AL80: 0 | AM80: 0 | AN80: 0
A81: Others | B81: =B75-SUM(B76:B80) | C81: =C75-SUM(C76:C80) | D81: =D75-SUM(D76:D80) | E81: =E75-SUM(E76:E80) | F81: =F75-SUM(F76:F80) | G81: =G75-SUM(G76:G80) | H81: =H75-SUM(H76:H80) | I81: =I75-SUM(I76:I80) | ... AH81: =AH75-SUM(AH76:AH80) | AI81: =AH81+AI89+AI19 | AJ81: =AI81+AJ89+AJ19 | AK81: =AJ81+AK89+AK19 | AL81: =AK81+AL89+AL19 | AM81: =AL81+AM89+AM19 | AN81: =AM81+AN89+AN19
A83: CAPEX | AP83: Australia
A84: Hong Kong | B84: =ROAFNA!B59 | C84: =ROAFNA!C59 | D84: =ROAFNA!D59 | E84: =ROAFNA!E59 | F84: =ROAFNA!F59 | G84: =ROAFNA!G59 | H84: =ROAFNA!H59 | I84: =ROAFNA!I59 | ... AN84: =ROAFNA!AN59 | AP84: Renewable | AQ84: 3000 | AR84: 6 | AS84: 0
A85: Australia | B85: =Aus!B91 | C85: =Aus!C91 | D85: =Aus!D91 | E85: =Aus!E91 | F85: =Aus!F91 | G85: =Aus!G91 | H85: =Aus!H91 | I85: =Aus!I91 | ... AN85: =Aus!AN91 | AP85: flexible | AQ85: =1600*2 | AR85: 2 | AS85: =AQ85*AR85
A86: China | B86: =CN!B160 | C86: =CN!C160 | D86: =CN!D160 | E86: =CN!E160 | F86: =CN!F160 | G86: =CN!G160 | H86: =CN!H160 | I86: =CN!I160 | ... AN86: =CN!AN160 | AP86: Total | AQ86: =SUM(AQ84:AQ85) | AS86: =SUM(AS84:AS85)
A87: India | B87: =India!B53 | C87: =India!C53 | D87: =India!D53 | E87: =India!E53 | F87: =India!F53 | G87: =India!G53 | H87: =India!H53 | I87: =India!I53 | ... AN87: =India!AN53 | AP87: Annual | AS87: =AS86/6
A88: SEA and Taiwan | B88: =0 | C88: =0 | D88: =0 | E88: =0 | F88: =0 | G88: =0 | H88: =0 | I88: =0 | ... AN88: =0 | AP88: 50% ownership | AS88: =AS87*0.5
A89: Others | K89: =K90-SUM(K84:K88) | L89: =L90-SUM(L84:L88) | M89: =M90-SUM(M84:M88) | N89: =N90-SUM(N84:N88) | O89: =O90-SUM(O84:O88) | P89: =P90-SUM(P84:P88) | Q89: =Q90-SUM(Q84:Q88) | R89: =R90-SUM(R84:R88) | ... AH89: =AH90-SUM(AH84:AH88) | AI89: 0 | AJ89: =AI89 | AK89: =AJ89 | AL89: =AK89 | AM89: =AL89 | AN89: =AM89
A90: Total | K90: 4741 | L90: 5134 | M90: 5594 | N90: 5823 | O90: 5640 | P90: 9228 | Q90: 8426 | R90: 7928 | S90: 9837 | T90: 20222 | U90: 18639 | V90: 12281 | W90: 13196 | X90: 10733 | Y90: 11483 | Z90: 10501 | AA90: 12646 | AB90: 11698 | AC90: 11390 | AD90: 12368 | AE90: 14156 | AF90: 15855 | AG90: 15402 | AH90: 15971 | AI90: =SUM(AI84:AI89) | AJ90: =SUM(AJ84:AJ89) | AK90: =SUM(AK84:AK89) | AL90: =SUM(AL84:AL89) | AM90: =SUM(AM84:AM89) | AN90: =SUM(AN84:AN89) | AP90: China
AP91: Renewable | AQ91: 4700 | AR91: 3.5 | AS91: =AQ91*AR91
A92: Debt | AP92: Annual | AS92: =AS91/5
A93: Total Debt | B93: =Final!B76+Final!B85 | C93: =Final!C76+Final!C85 | D93: =Final!D76+Final!D85 | E93: =Final!E76+Final!E85 | F93: =Final!F76+Final!F85 | G93: =Final!G76+Final!G85 | H93: =Final!H76+Final!H85 | I93: =Final!I76+Final!I85 | ... AH93: =Final!AH76+Final!AH85 | AI93: =SUM(AI94:AI99) | AJ93: =SUM(AJ94:AJ99) | AK93: =SUM(AK94:AK99) | AL93: =SUM(AL94:AL99) | AM93: =SUM(AM94:AM99) | AN93: =SUM(AN94:AN99) | AP93: 50% ownership | AS93: =AS92*0.5
A94: Hong Kong | B94: =ROAFNA!B35 | C94: =ROAFNA!C35 | D94: =ROAFNA!D35 | E94: =ROAFNA!E35 | F94: =ROAFNA!F35 | G94: =ROAFNA!G35 | H94: =ROAFNA!H35 | I94: =ROAFNA!I35 | ... AN94: =ROAFNA!AN35
A95: Australia | B95: =Aus!B84 | C95: =Aus!C84 | D95: =Aus!D84 | E95: =Aus!E84 | F95: =Aus!F84 | G95: =Aus!G84 | H95: =Aus!H84 | I95: =Aus!I84 | ... AN95: =Aus!AN84 | AP95: India
A96: China | B96: =CN!B163 | C96: =CN!C163 | D96: =CN!D163 | E96: =CN!E163 | F96: =CN!F163 | G96: =CN!G163 | H96: =CN!H163 | I96: =CN!I163 | ... AN96: =CN!AN163 | AP96: Renewable | AQ96: 8000 | AR96: 3.5 | AS96: =AQ96*AR96
A97: India | B97: =India!B59 | C97: =India!C59 | D97: =India!D59 | E97: =India!E59 | F97: =India!F59 | G97: =India!G59 | H97: =India!H59 | I97: =India!I59 | ... AN97: =India!AN59 | AP97: Annual | AS97: =AS96/5
A98: SEA and Taiwan | B98: 0 | C98: 0 | D98: 0 | E98: 0 | F98: 0 | G98: 0 | H98: 0 | I98: 0 | J98: 0 | K98: 0 | L98: 0 | M98: 0 | N98: 0 | O98: 0 | P98: 0 | Q98: 0 | R98: 0 | S98: 0 | T98: 0 | U98: 0 | V98: 0 | W98: 0 | X98: 0 | Y98: 0 | Z98: 0 | AA98: 0 | AB98: 0 | AC98: 0 | AD98: 0 | AE98: 0 | AF98: 0 | AG98: 0 | AH98: 0 | AI98: 0 | AJ98: 0 | AK98: 0 | AL98: 0 | AM98: 0 | AN98: 0 | AP98: 50% ownership | AS98: =AS97*0.5
A99: Unallocated | B99: =B93-SUM(B94:B98) | C99: =C93-SUM(C94:C98) | D99: =D93-SUM(D94:D98) | E99: =E93-SUM(E94:E98) | F99: =F93-SUM(F94:F98) | G99: =G93-SUM(G94:G98) | H99: =H93-SUM(H94:H98) | I99: =I93-SUM(I94:I98) | ... AD99: =AD93-SUM(AD94:AD98) | AE99: 0 | AF99: 0 | AG99: 0 | AH99: 0 | AI99: 0 | AJ99: 0 | AK99: 0 | AL99: 0 | AM99: 0 | AN99: 0
A100: Cash | B100: =Final!B57 | C100: =Final!C57 | D100: =Final!D57 | E100: =Final!E57 | F100: =Final!F57 | G100: =Final!G57 | H100: =Final!H57 | I100: =Final!I57 | ... AN100: =Final!AN57
A101: Net debt | B101: =B93-B100 | C101: =C93-C100 | D101: =D93-D100 | E101: =E93-E100 | F101: =F93-F100 | G101: =G93-G100 | H101: =H93-H100 | I101: =I93-I100 | ... AN101: =AN93-AN100 | AP101: Total | AS101: =AS88+AS93+AS98
A103: Interest expense | B103: -67 | C103: -70 | D103: -116 | E103: -160 | F103: -136 | G103: -137 | H103: -186 | I103: -247 | J103: -204 | K103: -187 | L103: -189 | M103: -688 | N103: -1046 | O103: -1613 | P103: -4762 | Q103: -5041 | R103: -4245 | S103: -3477 | T103: -4212 | U103: -6005 | V103: -6423 | W103: -6522 | X103: -4180 | Y103: -4106 | Z103: -2261 | AA103: -2180 | AB103: -2049 | AC103: -1983 | AD103: -1873 | AE103: -1744 | AF103: -2085 | AG103: -2139 | AH103: -2254 | AI103: =AI106-AI104 | AJ103: =AJ106-AJ104 | AK103: =AK106-AK104 | AL103: =AL106-AL104 | AM103: =AM106-AM104 | AN103: =AN106-AN104
A104: Interest income | B104: 0 | C104: 22 | D104: 100 | E104: 112 | F104: 86 | G104: 702 | H104: 1159 | I104: 859 | J104: 110 | K104: 29 | L104: 33 | M104: 47.779307 | N104: 63 | O104: 124 | P104: 138 | Q104: 160 | R104: 124 | S104: 69 | T104: 101 | U104: 146 | V104: 322 | W104: 173 | X104: 131 | Y104: 170 | Z104: 137 | AA104: 151 | AB104: 192 | AC104: 162 | AD104: 136 | AE104: 108 | AF104: 243 | AG104: 270 | AH104: 235 | AI104: =AH100*AVERAGE(AF105:AH105) | AJ104: =AI100*AVERAGE(AG105:AI105) | AK104: =AJ100*AVERAGE(AH105:AJ105) | AL104: =AK100*AVERAGE(AI105:AK105) | AM104: =AL100*AVERAGE(AJ105:AL105) | AN104: =AM100*AVERAGE(AK105:AM105)
A105: Interest income yield % | AB105: =AB104/AVERAGE(AA100:AB100) | AC105: =AC104/AC100 | AD105: =AD104/AD100 | AE105: =AE104/AE100 | AF105: =AF104/AF100 | AG105: =AG104/AG100 | AH105: =AH104/AH100 | AI105: =AI104/AI100 | AJ105: =AJ104/AJ100 | ... AN105: =AN104/AN100
A106: Net financial costs | B106: =Final!B21 | C106: =Final!C21 | D106: =Final!D21 | E106: =Final!E21 | F106: =Final!F21 | G106: =Final!G21 | H106: =Final!H21 | I106: =Final!I21 | ... AH106: =Final!AH21 | AI106: =SUM(AI107:AI112) | AJ106: =SUM(AJ107:AJ112) | AK106: =SUM(AK107:AK112) | AL106: =SUM(AL107:AL112) | AM106: =SUM(AM107:AM112) | AN106: =SUM(AN107:AN112)
A107: Hong Kong | B107: =ROAFNA!B36 | C107: =ROAFNA!C36 | D107: =ROAFNA!D36 | E107: =ROAFNA!E36 | F107: =ROAFNA!F36 | G107: =ROAFNA!G36 | H107: =ROAFNA!H36 | I107: =ROAFNA!I36 | ... AN107: =ROAFNA!AN36
A108: Australia | B108: =Aus!B24 | C108: =Aus!C24 | D108: =Aus!D24 | E108: =Aus!E24 | F108: =Aus!F24 | G108: =Aus!G24 | H108: =Aus!H24 | I108: =Aus!I24 | ... AN108: =Aus!AN24
A109: China | B109: =CN!B14 | C109: =CN!C14 | D109: =CN!D14 | E109: =CN!E14 | F109: =CN!F14 | G109: =CN!G14 | H109: =CN!H14 | I109: =CN!I14 | ... AN109: =CN!AN14
A110: India | B110: =India!B15 | C110: =India!C15 | D110: =India!D15 | E110: =India!E15 | F110: =India!F15 | G110: =India!G15 | H110: =India!H15 | I110: =India!I15 | ... AN110: =India!AN15
A111: SEA and Taiwan | B111: =SEA!B15 | C111: =SEA!C15 | D111: =SEA!D15 | E111: =SEA!E15 | F111: =SEA!F15 | G111: =SEA!G15 | H111: =SEA!H15 | I111: =SEA!I15 | ... AN111: =SEA!AN15
...

Sheet SOC
A1: SoC Income statement
B2: 1992 | C2: 1993 | D2: 1994 | E2: 1995 | F2: 1996 | G2: 1997 | H2: 1998 | I2: 1999R | J2: 2000 | K2: 2001 | L2: 2002 | M2: =Final!M2 | N2: =Final!N2 | O2: =Final!O2 | P2: =Final!P2 | Q2: =Final!Q2 | R2: =Final!R2 | S2: =Final!S2 | T2: =Final!T2 | ... AN2: =Final!AN2
A4: SoC revenues | B4: 13229 | C4: 14573 | D4: 14903 | E4: 16758 | F4: 18295 | G4: 20638 | H4: 22547 | I4: 28642 | J4: 24224 | K4: 24806 | L4: 25844 | M4: 25739 | N4: 26773 | O4: 28836 | P4: 29091 | Q4: 29331 | R4: =23755+6631 | S4: 28437 | T4: 30016 | U4: 30928 | V4: 33944 | W4: 33184 | X4: 36092 | Y4: 38205 | Z4: 37223 | AA4: 39259 | AB4: =32023+9063 | AC4: 40633 | AD4: 41905 | AE4: 45379 | AF4: 51103 | AG4: 50455 | AH4: 50804 | AI4: ='HK Sales'!AI8 | AJ4: ='HK Sales'!AJ8 | AK4: ='HK Sales'!AK8 | AL4: ='HK Sales'!AL8 | AM4: ='HK Sales'!AM8 | AN4: ='HK Sales'!AN8
A6: Fuel costs | B6: -2922 | C6: -3064 | D6: -1923 | E6: -2085 | F6: -2226 | G6: -3045 | H6: -2801 | I6: -3600 | J6: -2912 | K6: -2897 | L6: -3268 | M6: -2901 | N6: -3482 | O6: -4153 | P6: -4363 | Q6: -4905 | R6: =-1744-5024 | S6: -7029 | T6: -7848 | U6: -8784 | V6: -10061 | W6: -9645 | X6: -10375 | Y6: -12682 | Z6: -10978 | AA6: -11901 | AB6: =-10021-3081 | AC6: -13150 | AD6: -13790 | AE6: -15667 | AF6: -21939 | AG6: -20974 | AH6: -19713 | AI6: ='SOC Accounts'!AI69 | AJ6: ='SOC Accounts'!AJ69 | AK6: ='SOC Accounts'!AK69 | AL6: ='SOC Accounts'!AL69 | AM6: ='SOC Accounts'!AM69 | AN6: ='SOC Accounts'!AN69
A7: Operating costs | B7: =-4471-B10 | C7: =-4788-C10 | D7: =-4360-D10 | E7: -2782 | F7: -2747 | G7: -2472 | H7: -2329 | I7: -3098 | J7: -2636 | K7: -2965 | L7: -2848 | M7: -2817 | N7: -3166 | O7: -3106 | P7: -3328 | Q7: -3342 | R7: =-811-2389 | S7: -3102 | T7: -3467 | U7: -3516 | V7: -3698 | W7: -3711 | X7: -3842 | Y7: -4068 | Z7: -4312 | AA7: -4405 | AB7: =-3385-1149 | AC7: -5036 | AD7: -5170 | AE7: -5186 | AF7: -5027 | AG7: -5336 | AH7: -5571 | AI7: ='SOC Accounts'!AI48 | AJ7: ='SOC Accounts'!AJ48 | AK7: ='SOC Accounts'!AK48 | AL7: ='SOC Accounts'!AL48 | AM7: ='SOC Accounts'!AM48 | AN7: ='SOC Accounts'!AN48
A8: Purchase of nuclear power | B8: 0 | C8: 0 | D8: -2841 | E8: -3255 | F8: -3771 | G8: -3683 | H8: -3645 | I8: -4835 | J8: -4587 | K8: -5013 | L8: -4976 | M8: -5134 | N8: -4763 | O8: -5029 | P8: -5040 | Q8: -4971 | R8: =-1088-3943 | S8: -5237 | T8: -5003 | U8: -4879 | V8: -4636 | W8: -4619 | X8: -4867 | Y8: -5203 | Z8: -5198 | AA8: -5380 | AB8: =-4564-979 | AC8: -5643 | AD8: -5582 | AE8: -5678 | AF8: -5822 | AG8: -5802 | AH8: -5800 | AI8: ='SOC Accounts'!AI45 | AJ8: ='SOC Accounts'!AJ45 | AK8: ='SOC Accounts'!AK45 | AL8: ='SOC Accounts'!AL45 | AM8: ='SOC Accounts'!AM45 | AN8: ='SOC Accounts'!AN45
A9: Operating interest | B9: 0 | C9: 0 | D9: 0 | E9: -371 | F9: -410 | G9: -951 | H9: -1131 | I9: -1473 | J9: -1097 | K9: -931 | L9: -617 | M9: -459 | N9: -415 | O9: -543 | P9: -718 | Q9: -739 | R9: =-142-395 | S9: -537 | T9: -677 | U9: -742 | V9: -783 | W9: -863 | X9: -834 | Y9: -940 | Z9: -997 | AA9: -994 | AB9: =-750-246 | AC9: -978 | AD9: -976 | AE9: -857 | AF9: -800 | AG9: -1154 | AH9: -1407 | AI9: =AH9+AH17-AI17 | AJ9: =AI9+AI17-AJ17 | AK9: =AJ9+AJ17-AK17 | AL9: =AK9+AK17-AL17 | AM9: =AL9+AL17-AM17 | AN9: =AM9+AM17-AN17
A10: Depreciation | B10: -1777 | C10: -1893 | D10: -1489 | E10: -1624 | F10: -1797 | G10: -2277 | H10: -2522 | I10: -3360 | J10: -3025 | K10: -3026 | L10: -3164 | M10: -3439 | N10: -3452 | O10: -3746 | P10: -4117 | Q10: -3699 | R10: =-771-2234 | S10: -3149 | T10: -3427 | U10: -3863 | V10: -4146 | W10: -4475 | X10: -3901 | Y10: -4143 | Z10: -4375 | AA10: -4706 | AB10: =-3778-1153 | AC10: -4753 | AD10: -5011 | AE10: -5434 | AF10: -5313 | AG10: -5380 | AH10: -5683 | AI10: =ROAFNA!AI49 | AJ10: =ROAFNA!AJ49 | AK10: =ROAFNA!AK49 | AL10: =ROAFNA!AL49 | AM10: =ROAFNA!AM49 | AN10: =ROAFNA!AN49
A11: Misc | B11: 0 | C11: 0 | D11: 0 | E11: -158 | F11: -279 | G11: =-238-317 | H11: =-23+1 | I11: =-18-91 | J11: -99 | K11: 1 | L11: 0 | M11: -494 | N11: -176 | O11: 0 | P11: =O11 | Q11: =P11 | R11: -60 | S11: -246 | T11: -224 | U11: -282 | V11: -229 | W11: -52 | X11: =10 | Y11: 57 | Z11: 109 | AA11: 56 | AB11: =88-219 | AC11: -188 | AD11: -141 | AE11: -111 | AF11: -73 | AG11: -120 | AH11: -80 | AI11: =AH11 | AJ11: =AI11 | AK11: =AJ11 | AL11: =AK11 | AM11: =AL11 | AN11: =AM11
A12: Total operating expenses | B12: =SUM(B6:B11) | C12: =SUM(C6:C11) | D12: =SUM(D6:D11) | E12: =SUM(E6:E11) | F12: =SUM(F6:F11) | G12: =SUM(G6:G11) | H12: =SUM(H6:H11) | I12: =SUM(I6:I11) | ... AN12: =SUM(AN6:AN11)
A13: Pretax profits | B13: =B4+B12 | C13: =C4+C12 | D13: =D4+D12 | E13: =E4+E12 | F13: =F4+F12 | G13: =G4+G12 | H13: =H4+H12 | I13: =I4+I12 | ... AN13: =AN4+AN12
A14: Taxation | B14: -962 | C14: -1110 | D14: -826 | E14: -1016 | F14: -1135 | G14: -1202 | H14: -1512 | I14: =-1341-378 | J14: -1418 | K14: -1138 | L14: -1478 | M14: -1652 | N14: -1967 | O14: -2102 | P14: -1878 | Q14: -1909 | R14: =-1514-338 | S14: -1554 | T14: -1597 | U14: -1528 | V14: -1772 | W14: -1649 | X14: -2048 | Y14: -1865 | Z14: -1895 | AA14: -1989 | AB14: =-1589-412 | AC14: -1853 | AD14: -1904 | AE14: -2100 | AF14: -1924 | AG14: -1933 | AH14: -2112 | AI14: =-AI13*AI15 | AJ14: =-AJ13*AJ15 | AK14: =-AK13*AK15 | AL14: =-AL13*AL15 | AM14: =-AM13*AM15 | AN14: =-AN13*AN15
A15: Tax rate (%) | B15: =-B14/B13 | C15: =-C14/C13 | D15: =-D14/D13 | E15: =-E14/E13 | F15: =-F14/F13 | G15: =-G14/G13 | H15: =-H14/H13 | I15: =-I14/I13 | ... AH15: =-AH14/AH13 | AI15: =AH15 | AJ15: =AI15 | AK15: =AJ15 | AL15: =AK15 | AM15: =AL15 | AN15: =AM15
A16: Profit after taxation | B16: =B13+B14 | C16: =C13+C14 | D16: =D13+D14 | E16: =E13+E14 | F16: =F13+F14 | G16: =G13+G14 | H16: =H13+H14 | I16: =I13+I14 | ... AN16: =AN13+AN14
A17: Interest on borrowed capital | B17: 455 | C17: 463 | D17: 511 | E17: 813 | F17: 1138 | G17: 1283 | H17: 1246 | I17: 1479 | J17: 1170 | K17: 1005 | L17: 818 | M17: 679 | N17: 679 | O17: 769 | P17: 754 | Q17: 728 | R17: =165+443 | S17: 625 | T17: 763 | U17: 841 | V17: 859 | W17: 887 | X17: 856 | Y17: 920 | Z17: 952 | AA17: 976 | AB17: =266+789 | AC17: 1100 | AD17: 1111 | AE17: 1018 | AF17: 1115 | AG17: 1539 | AH17: 1700 | AI17: =-ROAFNA!AI41 | AJ17: =-ROAFNA!AJ41 | AK17: =-ROAFNA!AK41 | AL17: =-ROAFNA!AL41 | AM17: =-ROAFNA!AM41 | AN17: =-ROAFNA!AN41
A18: Adjustment for performance (incentives)/penaties | S18: -41 | T18: -43 | U18: -45 | V18: -47 | W18: -48 | X18: -49 | Y18: -51 | Z18: -53 | AA18: -54 | AB18: =-16-89 | AC18: -392 | AD18: -416 | AE18: -438 | AF18: -448 | AG18: -642 | AH18: -481 | AI18: =+AH18 | AJ18: =+AI18 | AK18: =+AJ18 | AL18: =+AK18 | AM18: =+AL18 | AN18: =+AM18
A19: Increase in customer deposits | I19: =2+1 | J19: 10 | K19: 8 | L19: 1 | M19: 0 | N19: 0 | O19: 12 | P19: 35 | Q19: 33 | R19: 2 | S19: 0 | T19: 0 | U19: 0 | V19: =U19 | W19: =V19 | X19: =W19 | Y19: =X19 | Z19: =Y19 | AA19: 0 | AB19: 1 | AC19: 4 | AD19: 0 | AE19: =AD19 | AF19: 4 | AG19: 37 | AH19: 39 | AI19: 0 | AJ19: 0 | AK19: 0 | AL19: 0 | AM19: 0 | AN19: 0
A20: China sales | B20: -211 | C20: -246 | D20: -79 | E20: -78 | F20: -19 | G20: -22 | H20: =G20 | I20: =-21-4 | J20: -16 | K20: -69 | L20: -5 | M20: 367 | N20: 35 | O20: -188 | P20: -186 | Q20: -160 | R20: =-92-33 | S20: -115 | T20: -73 | U20: -62 | V20: -43 | W20: -64 | X20: -54 | Y20: -68 | Z20: -69 | AA20: -79 | AB20: -43 | AC20: 0 | AD20: =AC20 | AE20: =AD20 | AF20: =AE20 | AG20: 0 | AH20: =AG20 | AI20: =AH20 | AJ20: =AI20 | AK20: =AJ20 | AL20: =AK20 | AM20: =AL20 | AN20: =AM20
A21: SoC net income | B21: =SUM(B16:B20) | C21: =SUM(C16:C20) | D21: =SUM(D16:D20) | E21: =SUM(E16:E20) | F21: =SUM(F16:F20) | G21: =SUM(G16:G20) | H21: =SUM(H16:H20) | I21: =SUM(I16:I20) | ... AN21: =SUM(AN16:AN20)
A22: Charge for asset decommissioning | B22: 0 | C22: 0 | D22: 0 | E22: 0 | F22: 0 | G22: 0 | H22: 0 | I22: 0 | J22: 0 | K22: 0 | L22: 0 | M22: 0 | N22: 0 | O22: 0 | P22: 0 | Q22: 0 | R22: 0 | S22: 0 | T22: 0 | U22: 0 | V22: 0 | W22: 0 | X22: 0 | Y22: 0 | Z22: 0 | AA22: 0 | AB22: 0 | AC22: 0 | AD22: 0 | AE22: 0 | AF22: 0 | AG22: 0 | AH22: 0 | AI22: 0 | AJ22: 0 | AK22: 0 | AL22: 0 | AM22: 0 | AN22: 0
A23: Transfer from/(to) development fund | B23: =B25-B21-B22 | C23: =C25-C21-C22 | D23: =D25-D21-D22 | E23: =E25-E21-E22 | F23: =F25-F21-F22 | G23: =G25-G21-G22 | H23: =H25-H21-H22 | I23: =I25-I21-I22 | ... AH23: =AH25-AH21-AH22 | AI23: =MIN(AI25-AI21-AI22,('SOC Accounts'!AH21+'SOC Accounts'!AI20+'SOC Accounts'!AI19)) | AJ23: =MIN(AJ25-AJ21-AJ22,('SOC Accounts'!AI21+'SOC Accounts'!AJ20+'SOC Accounts'!AJ19)) | AK23: =MIN(AK25-AK21-AK22,('SOC Accounts'!AJ21+'SOC Accounts'!AK20+'SOC Accounts'!AK19)) | AL23: =MIN(AL25-AL21-AL22,('SOC Accounts'!AK21+'SOC Accounts'!AL20+'SOC Accounts'!AL19)) | AM23: =MIN(AM25-AM21-AM22,('SOC Accounts'!AL21+'SOC Accounts'!AM20+'SOC Accounts'!AM19)) | AN23: =MIN(AN25-AN21-AN22,('SOC Accounts'!AM21+'SOC Accounts'!AN20+'SOC Accounts'!AN19))
A24: Transfer from/(to) development fund (theoretical) | V24: =V25-V21-V22-V23 | W24: =W25-W21-W22-W23 | X24: =X25-X21-X22-X23 | Y24: =Y25-Y21-Y22-Y23 | Z24: =Z25-Z21-Z22-Z23 | AA24: =AA25-AA21-AA22-AA23 | AB24: =AB25-AB21-AB22-AB23 | AC24: 0 | AD24: =+AC24 | AE24: =+AD24 | AF24: =+AE24 | AG24: =+AF24 | AH24: =+AG24 | AI24: =+AH24 | AJ24: =+AI24 | AK24: =+AJ24 | ... AN24: =+AM24
A25: Permitted return | B25: =ROAFNA!B14 | C25: =ROAFNA!C14 | D25: =ROAFNA!D14 | E25: =ROAFNA!E14 | F25: =ROAFNA!F14 | G25: =ROAFNA!G14 | H25: =ROAFNA!H14 | I25: =ROAFNA!I14 | ... AN25: =ROAFNA!AN14
A26: Interest on borrowed capital | B26: =-B17 | C26: =-C17 | D26: =-D17 | E26: =-E17 | F26: =-F17 | G26: =-G17 | H26: =-H17 | I26: =-I17 | ... AN26: =-AN17
A27: Adjustment for performance incentives/penaties | S27: =-S18 | T27: =-T18 | U27: =-U18 | V27: =-V18 | W27: =-W18 | X27: =-X18 | Y27: =-Y18 | Z27: =-Z18 | ... AN27: =-AN18
A28: Interest on increase in customers deposits | B28: 0 | C28: 0 | D28: 0 | E28: 0 | F28: 0 | G28: 0 | H28: 0 | I28: -3 | J28: =-J19 | K28: =-K19 | L28: =-L19 | M28: =-M19 | N28: =-N19 | O28: =-O19 | P28: =-P19 | Q28: =-Q19 | ... AN28: =-AN19
A29: Transfer to special provision account | B29: 0 | C29: 0 | D29: 0 | E29: 0 | F29: 0 | G29: 0 | H29: 0 | I29: 0 | J29: 0 | K29: 0 | L29: 0 | M29: 0 | N29: 0 | O29: 0 | P29: 0 | Q29: 0 | R29: 0 | S29: 0 | T29: 0 | U29: 0 | V29: =U29 | W29: =V29 | X29: =W29 | Y29: =X29 | Z29: =Y29 | AA29: =Z29 | AB29: =AA29 | AC29: =AB29 | ... AN29: =AM29
A30: Transfer to rate reduction reserve | B30: -243 | C30: -283 | D30: -272 | E30: -215 | F30: -174 | G30: -134 | H30: -158 | I30: -290 | J30: -280 | K30: -305 | L30: -319 | M30: -287 | N30: -253 | O30: -274 | P30: -265 | Q30: -202 | R30: -132 | S30: -3 | T30: -3 | U30: -2 | V30: -2 | W30: -1 | X30: 8 | Y30: -2 | Z30: -2 | AA30: -4 | AB30: =-4-7 | AC30: -22 | AD30: -18 | AE30: -3 | AF30: -40 | AG30: -114 | AH30: -124 | AI30: =-'SOC Accounts'!AI32 | AJ30: =-'SOC Accounts'!AJ32 | AK30: =-'SOC Accounts'!AK32 | AL30: =-'SOC Accounts'!AL32 | AM30: =-'SOC Accounts'!AM32 | AN30: =-'SOC Accounts'!AN32
A31: Net return | B31: =SUM(B25:B30) | C31: =SUM(C25:C30) | D31: =SUM(D25:D30) | E31: =SUM(E25:E30) | F31: =SUM(F25:F30) | G31: =SUM(G25:G30) | H31: =SUM(H25:H30) | I31: =SUM(I25:I30) | J31: =SUM(J25:J30)+J32 | K31: =SUM(K25:K30) | L31: =SUM(L25:L30) | M31: =SUM(M25:M30) | N31: =SUM(N25:N30) | O31: =SUM(O25:O30) | P31: =SUM(P25:P30) | Q31: =SUM(Q25:Q30) | R31: =SUM(R25:R30) | ... W31: =SUM(W25:W30) | X31: =SUM(X26:X30)+MIN(X21,X25) | Y31: =SUM(Y26:Y30)+MIN(SUM(Y21:Y24),Y25) | Z31: =SUM(Z26:Z30)+MIN(SUM(Z21:Z24),Z25) | AA31: =SUM(AA26:AA30)+MIN(SUM(AA21:AA24),AA25) | AB31: =SUM(AB26:AB30)+MIN(SUM(AB21:AB24),AB25) | AC31: =SUM(AC26:AC30)+MIN(SUM(AC21:AC24),AC25) | AD31: =SUM(AD26:AD30)+MIN(SUM(AD21:AD24),AD25) | AE31: =SUM(AE26:AE30)+MIN(SUM(AE21:AE24),AE25) | AF31: =SUM(AF26:AF30)+MIN(SUM(AF21:AF24),AF25) | ... AN31: =SUM(AN26:AN30)+MIN(SUM(AN21:AN24),AN25)
A32: Contribution to CESF / EEF | AA32: -22 | AB32: =-16-48 | AC32: -195 | AD32: -201 | AE32: -208 | AF32: -218 | AG32: -230 | AH32: -238 | AI32: =AI18*AH32/AH18 | AJ32: =AJ18*AI32/AI18 | AK32: =AK18*AJ32/AJ18 | AL32: =AL18*AK32/AK18 | AM32: =AM18*AL32/AL18 | AN32: =AN18*AM32/AM18
A33: Net return | AA33: =SUM(AA31:AA32) | AB33: =SUM(AB31:AB32) | AC33: =SUM(AC31:AC32) | AD33: =SUM(AD31:AD32) | AE33: =SUM(AE31:AE32) | AF33: =SUM(AF31:AF32) | AG33: =SUM(AG31:AG32) | AH33: =SUM(AH31:AH32) | ... AN33: =SUM(AN31:AN32)
AC34: =AC33/AB33-1 | AD34: =AD33/AC33-1 | AE34: =AE33/AD33-1 | AF34: =AF33/AE33-1 | AG34: =AG33/AF33-1 | AH34: =AH33/AG33-1 | AI34: =AI33/AH33-1 | AJ34: =AJ33/AI33-1 | ... AN34: =AN33/AM33-1
A35: Profits split between CLP and CAPCO
A36: CLP Power HK portion (%) | B36: =B39/B$41 | C36: =C39/C$41 | D36: =D39/D$41 | E36: =E39/E$41 | F36: =F39/F$41 | G36: =G39/G$41 | H36: =H39/H$41 | I36: =I39/I$41 | ... AH36: =AH39/AH$41 | AI36: =AH36+0.005 | AJ36: =AI36+0.005 | AK36: =AJ36+0.005 | AL36: =AK36+0.005 | AM36: =AL36+0.005 | AN36: =AM36+0.005
A37: CAPCO portion (%) | B37: =B40/B$41 | C37: =C40/C$41 | D37: =D40/D$41 | E37: =E40/E$41 | F37: =F40/F$41 | G37: =G40/G$41 | H37: =H40/H$41 | I37: =I40/I$41 | ... O37: =O40/O$41 | P37: =1-P36 | Q37: =1-Q36 | R37: =1-R36 | S37: =1-S36 | T37: =1-T36 | U37: =1-U36 | V37: =1-V36 | W37: =1-W36 | ... AN37: =1-AN36
A39: CLP Power HK (T&D) | B39: 2048 | C39: 2320 | D39: 2629 | E39: 2973 | F39: 3265 | G39: 3514 | H39: 3712 | I39: =960+3803 | J39: 3955 | K39: 4188 | L39: 4517 | M39: 4895 | N39: 5363 | O39: 5626 | P39: 5878 | Q39: 6242 | R39: =1174+5041 | S39: 4894 | T39: 4985 | U39: 5139 | V39: 5425 | W39: 5744 | X39: 6070 | Y39: 6319 | Z39: 6547 | AA39: 6763 | AB39: =5149+1369 | AC39: 5582 | AD39: 5769 | AE39: 6078 | AF39: 6239 | AG39: 6351 | AH39: 6536 | AI39: =AI$33*AI36 | AJ39: =AJ$33*AJ36 | AK39: =AK$33*AK36 | AL39: =AL$33*AL36 | AM39: =AM$33*AM36 | AN39: =AN$33*AN36
A40: CAPCO (Generation) | B40: 1999 | C40: 2137 | D40: 2466 | E40: 2726 | F40: 2965 | G40: 3104 | H40: 3137 | I40: =3115+758 | J40: 2969 | K40: 3074 | L40: 3232 | M40: 3456 | N40: 3552 | O40: 3542 | P40: 3520 | Q40: 3515 | R40: =2710+618 | S40: 2674 | T40: 2860 | U40: 2999 | V40: 3074 | W40: 3054 | X40: 3080 | Y40: 3096 | Z40: 3110 | AA40: 3114 | AB40: =2367+654 | AC40: 2707 | AD40: 2824 | AE40: 2985 | AF40: 3177 | AG40: 3229 | AH40: 3115 | AI40: =AI$33*AI37 | AJ40: =AJ$33*AJ37 | AK40: =AK$33*AK37 | AL40: =AL$33*AL37 | AM40: =AM$33*AM37 | AN40: =AN$33*AN37
A41: Total net return | B41: =SUM(B39:B40) | C41: =SUM(C39:C40) | D41: =SUM(D39:D40) | E41: =SUM(E39:E40) | F41: =SUM(F39:F40) | G41: =SUM(G39:G40) | H41: =SUM(H39:H40) | I41: =SUM(I39:I40) | ... AN41: =SUM(AN39:AN40)
A43: CLP's portion in CAPCO | B43: =B45/B40 | C43: =C45/C40 | D43: =D45/D40 | E43: =E45/E40 | F43: =F45/F40 | G43: =G45/G40 | H43: =H45/H40 | I43: =I45/I40 | ... AH43: =AH45/AH40 | AI43: =AH43 | AJ43: =AI43 | AK43: =AJ43 | AL43: =AK43 | AM43: =AL43 | AN43: =AM43
A44: CLP's share in CLP Power HK | B44: =B39 | C44: =C39 | D44: =D39 | E44: =E39 | F44: =F39 | G44: =G39 | H44: =H39 | I44: =I39 | ... M44: =M39 | N44: 5363 | O44: 5626 | P44: =P39 | Q44: =Q39 | R44: =R39 | S44: =S39 | T44: =T39 | U44: =U39 | V44: =V39 | W44: =W39 | ... Z44: =Z39 | AA44: 6763 | AB44: =AB39 | AC44: 5582 | AD44: 5769 | AE44: 6078 | AF44: 6239 | AG44: 6351 | AH44: 6536 | AI44: =AI39 | AJ44: =AJ39 | AK44: =AK39 | AL44: =AL39 | AM44: =AM39 | AN44: =AN39
A45: CLP's share in CAPCO | B45: 806 | C45: 859 | D45: 991 | E45: 1094 | F45: 1190 | G45: =G40*0.4+4 | H45: =H40*0.4+4 | I45: =I40*0.4+4 | J45: =J40*0.4+4 | K45: =K40*0.4+4 | L45: =L40*0.4+4 | M45: 1386 | N45: 1425 | O45: 1421 | P45: 1412 | Q45: 1410 | R45: =247+1087 | S45: 1070 | T45: 1144 | U45: 1200 | V45: 1229 | W45: 1222 | X45: 1852 | Y45: 2167 | Z45: 2177 | AA45: 2180 | AB45: =1656+458 | AC45: 1895 | AD45: 1977 | AE45: 2089 | AF45: 2224 | AG45: 2261 | AH45: 2180 | AI45: =AI40*AI43 | AJ45: =AJ40*AJ43 | AK45: =AK40*AK43 | AL45: =AL40*AL43 | AM45: =AM40*AM43 | AN45: =AN40*AN43
A46: SOC Profits | B46: =SUM(B44:B45) | C46: =SUM(C44:C45) | D46: =SUM(D44:D45) | E46: =SUM(E44:E45) | F46: =SUM(F44:F45) | G46: =SUM(G44:G45) | H46: =SUM(H44:H45) | I46: =SUM(I44:I45) | ... R46: =SUM(R44:R45) | S46: 5964 | T46: 6129 | U46: 6339 | V46: 6654 | W46: 6966 | X46: =SUM(X44:X45) | Y46: =SUM(Y44:Y45) | Z46: =SUM(Z44:Z45) | AA46: =SUM(AA44:AA45) | AB46: =SUM(AB44:AB45) | AC46: =SUM(AC44:AC45) | AD46: =SUM(AD44:AD45) | AE46: =SUM(AE44:AE45) | ... AN46: =SUM(AN44:AN45)

Sheet HK Sales
A1: CLP Scheme of Control Revenue | AQ1: Quarterly Sales
A2: Electricity Revenue: | B2: 1992 | C2: 1993 | D2: 1994 | E2: 1995 | F2: 1996 | G2: =Final!G2 | H2: =Final!H2 | I2: =Final!I2 | J2: =Final!J2 | K2: =Final!K2 | L2: =Final!L2 | M2: =Final!M2 | N2: =Final!N2 | ... AN2: =Final!AN2 | AR2: Q116 | AS2: Q117
A3: Gross electricity revenue (Basic tariff x GWh) | B3: =B36*B13/100 | C3: =C36*C13/100 | D3: =D36*D13/100 | E3: =E36*E13/100 | F3: =F36*F13/100 | G3: =G36*G13/100 | H3: =H36*H13/100 | I3: =I36*I13/100 | ... AN3: =AN36*AN13/100 | AQ3: Residential | AR3: =AS3+210 | AS3: =AS11*$AS$8
A4: Transfer from (to) fuel cost adjustment | B4: =+'SOC Accounts'!B5 | C4: =+'SOC Accounts'!C5 | D4: =+'SOC Accounts'!D5 | E4: =+'SOC Accounts'!E5 | F4: =+'SOC Accounts'!F5 | G4: =+'SOC Accounts'!G5 | H4: =+'SOC Accounts'!H5 | I4: =+'SOC Accounts'!I5 | ... AN4: =+'SOC Accounts'!AN5 | AQ4: Commercial | AR4: =AS4-23 | AS4: =AS12*$AS$8
A5: Export to China | B5: =+B6-B3-B4 | C5: =+C6-C3-C4 | D5: =+D6-D3-D4 | E5: =+E6-E3-E4 | F5: =+F6-F3-F4 | G5: =+G6-G3-G4 | H5: =+H6-H3-H4 | I5: =+I6-I3-I4 | ... AH5: =+AH6-AH3-AH4 | AI5: =AI29*AI37 | AJ5: =AJ29*AJ37 | AK5: =AK29*AK37 | AL5: =AL29*AL37 | AM5: =AM29*AM37 | AN5: =AN29*AN37 | AQ5: Infrastructure & Public Services | AR5: =AS5-66 | AS5: =AS13*$AS$8
A6: Sales of electricity | B6: =+#REF! | C6: =+#REF! | D6: =+#REF! | E6: =+#REF! | F6: =+F8-F7 | G6: =+G8-G7 | H6: =+H8-H7 | I6: =+I8-I7 | J6: 24163 | K6: 24725 | L6: 25770 | M6: 25677 | N6: 26661 | O6: 28750 | P6: 29004 | Q6: 29236 | R6: 30288 | S6: 28349 | T6: 29917 | U6: 30824 | V6: 33842 | W6: 33064 | X6: 35969 | Y6: 38087 | Z6: 37120 | AA6: 39161 | AB6: 40982 | AC6: 40473 | AD6: 41798 | AE6: 45222 | AF6: 50919 | AG6: 50288 | AH6: 50649 | AI6: =SUM(AI3:AI5) | AJ6: =SUM(AJ3:AJ5) | AK6: =SUM(AK3:AK5) | AL6: =SUM(AL3:AL5) | AM6: =SUM(AM3:AM5) | AN6: =SUM(AN3:AN5) | AQ6: Manufacturing | AR6: =AS6-3 | AS6: =AS14*$AS$8
A7: Sundry income | B7: 60 | C7: 26 | D7: 22 | E7: 25 | F7: 27 | G7: 36 | H7: 56 | I7: 92 | J7: =J8-J6 | K7: =K8-K6 | L7: =L8-L6 | M7: =M8-M6 | N7: =N8-N6 | O7: =O8-O6 | P7: =P8-P6 | Q7: =Q8-Q6 | ... AG7: =AG8-AG6 | AH7: =AG7 | AI7: =AH7 | AJ7: =AI7 | AK7: =AJ7 | AL7: =AK7 | AM7: =AL7 | AN7: =AM7
A8: Total SOC revenue | B8: =SOC!B4 | C8: =SOC!C4 | D8: =SOC!D4 | E8: =SOC!E4 | F8: =SOC!F4 | G8: =SOC!G4 | H8: =SOC!H4 | I8: =SOC!I4 | ... AG8: =SOC!AG4 | AH8: =+AH6+AH7 | AI8: =+AI6+AI7 | AJ8: =+AJ6+AJ7 | AK8: =+AK6+AK7 | AL8: =+AL6+AL7 | AM8: =+AM6+AM7 | AN8: =+AN6+AN7 | AQ8: Total | AR8: =SUM(AR3:AR7) | AS8: 6512
A9: YoY | C9: =C8/B8-1 | D9: =D8/C8-1 | E9: =E8/D8-1 | F9: =F8/E8-1 | G9: =G8/F8-1 | H9: =H8/G8-1 | I9: =4/5*I8/H8-1 | J9: =J8/(4/5*I8)-1 | K9: =K8/J8-1 | L9: =L8/K8-1 | M9: =M8/L8-1 | N9: =N8/M8-1 | O9: =O8/N8-1 | P9: =P8/O8-1 | Q9: =Q8/P8-1 | R9: =R8/Q8-1 | ... AN9: =AN8/AM8-1 | AQ9: China | AS9: 174
A11: Actual Tariffs at Year End (Cents per kWh) | AQ11: Residential | AR11: =AR3/$AR$8 | AS11: 0.24
AQ12: Commercial | AR12: =AR4/$AR$8 | AS12: 0.42
A13: Basic Tariff | B13: 63.81 | C13: 65.85 | D13: 71.96 | E13: 77.31 | F13: 82.42 | G13: 86.35 | H13: 89.09 | I13: 89.15 | J13: 88.57 | K13: 88.6 | L13: 88.5 | M13: 88.4 | N13: 88.1 | O13: 88.2 | P13: 88 | Q13: 88.1 | R13: 85.6 | S13: 77.5 | T13: 80.1 | U13: 80 | V13: 84.2 | W13: 84 | X13: 88.6 | Y13: 87.1 | Z13: 88.9 | AA13: 92.2 | AB13: =94.5*0.75+91*0.25 | AC13: 91 | AD13: 92.3 | AE13: 93.6 | AF13: 93.3 | AG13: 93.1 | AH13: 95.8 | AI13: =AH13*(1+AI14) | AJ13: =AI13*(1+AJ14) | AK13: =AJ13*(1+AK14) | AL13: =AK13*(1+AL14) | AM13: =AL13*(1+AM14) | AN13: =AM13*(1+AN14) | AQ13: Infrastructure & Public Services | AR13: =AR5/$AR$8 | AS13: 0.28
A14: YoY | C14: =(D13/C13)-1 | D14: =(E13/D13)-1 | E14: =(E13/D13)-1 | F14: =(F13/E13)-1 | G14: =(G13/F13)-1 | H14: =(H13/G13)-1 | I14: =(I13/H13)-1 | J14: =(J13/I13)-1 | K14: =(K13/J13)-1 | L14: =(L13/K13)-1 | ... AH14: =(AH13/AG13)-1 | AI14: 0.02 | AJ14: =AI14 | AK14: =AJ14 | AL14: =AK14 | AM14: =AL14 | AN14: =AM14 | AQ14: Manufacturing | AR14: =AR6/$AR$8 | AS14: 0.06
A15: Special rebates | D15: -1.93 | G15: -0.73 | H15: -1.82 | I15: -2.2 | J15: =I15 | K15: =J15 | L15: =K15 | M15: =L15 | N15: 0 | O15: =N15 | P15: -1.8 | Q15: -1.8 | R15: -1.6 | S15: 0 | T15: 0 | U15: 0 | V15: 0 | W15: 0 | X15: 0 | Y15: 0 | Z15: 0 | AA15: 0 | AB15: =AA15 | AC15: =AB15 | AD15: 0 | AE15: 0 | AF15: =AF22/AF36*100 | AG15: =AG22/AG36*100 | AH15: =AH22/AH36*100 | AI15: =AH15 | AJ15: =AI15 | AK15: =AJ15 | AL15: =AK15 | AM15: =AL15 | AN15: =AM15 | AQ15: Total | AR15: =SUM(AR11:AR14) | AS15: =SUM(AS11:AS14)
A16: Fuel Clause Charge/(Rebate) | B16: -3.36 | C16: -2.5 | D16: -3.79 | E16: -4.5 | F16: -4.5 | G16: -1.27 | H16: 0.99 | I16: 2.2 | J16: 2.2 | K16: =J16 | L16: 1.9 | M16: 1.9 | N16: -0.3 | O16: 0.2 | P16: 2 | Q16: =P16 | R16: 7.3 | S16: 11.8 | T16: 11.5 | U16: 14.1 | V16: 17.8 | W16: 22.4 | X16: 22.4 | Y16: =27-3.8 | Z16: 24.3 | AA16: 21 | AB16: =22*0.75+27.8*0.25 | AC16: 27.8 | AD16: 28.4 | AE16: 30.2 | AF16: 46.1 | AG16: 58.4 | AH16: 44.3 | AI16: =AH16 | AJ16: =+AI16 | AK16: =+AJ16 | AL16: =+AK16 | AM16: =+AL16 | AN16: =+AM16
A17: Rate Reduction Rebate | B17: -1.17 | C17: -1.6 | D17: -1.6 | E17: -0.96 | F17: -0.6 | G17: -0.6 | H17: -0.6 | I17: -0.6 | J17: -0.6 | K17: -0.6 | L17: -0.6 | M17: -0.6 | N17: -0.6 | O17: -1.1 | P17: =O17 | Q17: =P17 | R17: -0.8 | S17: -0.2 | T17: 0 | U17: 0 | V17: 0 | W17: 0 | X17: 0 | Y17: 0 | Z17: 0 | AA17: 0 | AB17: 0 | AC17: 0 | AD17: 0 | AE17: 0 | AF17: 0 | AG17: 0 | AH17: 0 | AI17: 0 | AJ17: 0 | AK17: 0 | AL17: 0 | AM17: 0 | AN17: 0 | AQ17: YoY
A18: Rent & Rates Special Rebate | V18: -3.3 | W18: -1.7 | X18: 0 | Y18: 0 | Z18: 0 | AA18: 0 | AB18: -1.1 | AC18: -0.1 | AD18: -1.2 | AE18: 0 | AF18: -1.3 | AG18: -0.4 | AH18: 0 | AI18: 0 | AJ18: 0 | AK18: 0 | AL18: 0 | AM18: 0 | AN18: 0 | AQ18: Residential | AS18: =AS3/AR3-1
A19: Net Tariff | B19: =B13+SUM(B15:B18) | C19: =C13+SUM(C15:C18) | D19: =D13+SUM(D15:D18) | E19: =E13+SUM(E15:E18) | F19: =F13+SUM(F15:F18) | G19: =G13+SUM(G15:G18) | H19: =H13+SUM(H15:H18) | I19: =I13+SUM(I15:I18) | ... AN19: =AN13+SUM(AN15:AN18) | AQ19: Commercial | AS19: =AS4/AR4-1
A20: YoY | C20: =(C19/B19)-1 | D20: =(D19/C19)-1 | E20: =(E19/D19)-1 | F20: =(F19/E19)-1 | G20: =(G19/F19)-1 | H20: =(H19/G19)-1 | I20: =(I19/H19)-1 | J20: =(J19/I19)-1 | ... AN20: =(AN19/AM19)-1 | AQ20: Infrastructure & Public Services | AS20: =AS5/AR5-1
AQ21: Manufacturing | AS21: =AS6/AR6-1
A22: Total value of special rebate | B22: =B15*B36/100 | C22: =C15*C36/100 | D22: =D15*D36/100 | E22: =E15*E36/100 | F22: =F15*F36/100 | G22: =G15*G36/100 | H22: =H15*H36/100 | I22: =I15*I36/100 | J22: =J15*J36/100-387 | K22: =K15*K36/100-340-609 | L22: =-(558+41+626) | M22: -910 | N22: =8-1-15 | O22: -13 | P22: -551 | Q22: -462 | R22: -494 | S22: 0 | T22: 0 | U22: =U15*U36/100 | V22: =V15*V36/100 | W22: =W15*W36/100 | X22: =X15*X36/100 | Y22: =Y15*Y36/100 | Z22: =Z15*Z36/100 | AA22: =AA15*AA36/100 | AB22: =AB15*AB36/100 | ... AE22: =AE15*AE36/100 | AF22: -715 | AG22: -271 | AH22: -20 | AI22: =AI15*AI36/100 | AJ22: =AJ15*AJ36/100 | AK22: =AK15*AK36/100 | AL22: =AL15*AL36/100 | AM22: =AM15*AM36/100 | AN22: =AN15*AN36/100 | AQ22: Total | AS22: =AS8/AR8-1
A23: Total value of rate reduction rebate | B23: =B17*B36/100 | C23: =C17*C36/100 | D23: =D17*D36/100 | E23: =E17*E36/100 | F23: =F17*F36/100 | G23: =G17*G36/100 | H23: =H17*H36/100 | I23: =I17*I36/100 | J23: =J17*J36/100 | K23: =K17*K36/100-99 | L23: =L17*L36/100-5 | M23: =M17*M36/100-5 | N23: =N17*N36/100-5 | O23: -334 | P23: -340 | Q23: =-94-339 | R23: =-246+1 | S23: =0-72 | T23: 0 | U23: =U17*U36/100 | V23: =V17*V36/100 | W23: =W17*W36/100 | X23: =X17*X36/100 | Y23: =Y17*Y36/100 | Z23: =Z17*Z36/100 | AA23: =AA17*AA36/100 | AB23: =AB17*AB36/100 | ... AN23: =AN17*AN36/100
A25: Check: tariff stablisation fund | B25: ='SOC Accounts'!B21 | C25: ='SOC Accounts'!C21 | D25: ='SOC Accounts'!D21 | E25: ='SOC Accounts'!E21 | F25: ='SOC Accounts'!F21 | G25: ='SOC Accounts'!G21 | H25: ='SOC Accounts'!H21 | I25: ='SOC Accounts'!I21 | ... AN25: ='SOC Accounts'!AN21
A26: Check: fuel clause account (neg is payable) | B26: ='SOC Accounts'!B7 | C26: ='SOC Accounts'!C7 | D26: ='SOC Accounts'!D7 | E26: ='SOC Accounts'!E7 | F26: ='SOC Accounts'!F7 | G26: ='SOC Accounts'!G7 | H26: ='SOC Accounts'!H7 | I26: ='SOC Accounts'!I7 | ... AN26: ='SOC Accounts'!AN7
A27: Check: rate reduction reserve | B27: ='SOC Accounts'!B34 | C27: ='SOC Accounts'!C34 | D27: ='SOC Accounts'!D34 | E27: ='SOC Accounts'!E34 | F27: ='SOC Accounts'!F34 | G27: ='SOC Accounts'!G34 | H27: ='SOC Accounts'!H34 | I27: ='SOC Accounts'!I34 | ... AN27: ='SOC Accounts'!AN34
A29: Implied export tariff/kWh | B29: =#REF!/B37 | C29: =#REF!/C37 | D29: =#REF!/D37 | E29: =#REF!/E37 | F29: =#REF!/F37 | G29: =#REF!/G37 | H29: =#REF!/H37 | I29: =#REF!/I37 | J29: =J5/J37 | K29: =K5/K37 | L29: =L5/L37 | M29: =M5/M37 | N29: =N5/N37 | O29: =O5/O37 | P29: =P5/P37 | Q29: =Q5/Q37 | ... AB29: =AB5/AB37 | AC29: 0 | AD29: =AC29 | AE29: =AD29 | AF29: =AE29 | AG29: =AF29 | AH29: =AG29 | AI29: =AH29 | AJ29: =AI29 | AK29: =AJ29 | ... AN29: =AM29
A31: Demand (Gwh)
A32: Commercial | B32: 6071 | C32: 6567 | D32: 7096 | E32: 7603 | F32: 8038 | G32: 8542 | H32: 9157 | I32: 11785 | J32: 10014 | K32: 10378 | L32: 10661 | M32: 10698 | N32: 11086 | O32: 11428 | P32: 11957 | Q32: 12144 | R32: 12312 | S32: 12488 | T32: 12642 | U32: 12670 | V32: 12917 | W32: 12935 | X32: 13099 | Y32: 13209 | Z32: 13234 | AA32: 13220 | AB32: 13425 | AC32: 13584 | AD32: 12878 | AE32: 13423 | AF32: 13233 | AG32: 13673 | AH32: 13882 | AI32: =AH32*(1+AI41) | AJ32: =AI32*(1+AJ41) | AK32: =AJ32*(1+AK41) | AL32: =AK32*(1+AL41) | AM32: =AL32*(1+AM41) | AN32: =AM32*(1+AN41)
A33: Domestic | B33: 4195 | C33: 4733 | D33: 5024 | E33: 5382 | F33: 5723 | G33: 5811 | H33: 6524 | I33: 7854 | J33: 6608 | K33: 6752 | L33: 6930 | M33: 7180 | N33: 7149 | O33: 7525 | P33: 7469 | Q33: 7724 | R33: 7890 | S33: 8331 | T33: 8457 | U33: 8594 | V33: 8900 | W33: 8658 | X33: 9450 | Y33: 9228 | Z33: 9394 | AA33: 9217 | AB33: 9191 | AC33: 9451 | AD33: 10298 | AE33: 10525 | AF33: 10113 | AG33: 9929 | AH33: 10204 | AI33: =AH33*(1+AI42) | AJ33: =AI33*(1+AJ42) | AK33: =AJ33*(1+AK42) | AL33: =AK33*(1+AL42) | AM33: =AL33*(1+AM42) | AN33: =AM33*(1+AN42)
A34: Industrial | B34: 5170 | C34: 4915 | D34: 4654 | E34: 4344 | F34: 4162 | G34: 3928 | H34: 3776 | I34: 4270 | J34: 3488 | K34: 3245 | L34: 3085 | M34: 2856 | N34: 2833 | O34: 2734 | P34: 2653 | Q34: 2418 | R34: 2202 | S34: 1938 | T34: 1952 | U34: 1886 | V34: 1890 | W34: 1832 | X34: 1791 | Y34: 1791 | Z34: 1751 | AA34: 1740 | AB34: 1704 | AC34: 1663 | AD34: 1616 | AE34: 1665 | AF34: 1615 | AG34: 1594 | AH34: 1573 | AI34: =AH34*(1+AI43) | AJ34: =AI34*(1+AJ43) | AK34: =AJ34*(1+AK43) | AL34: =AK34*(1+AL43) | AM34: =AL34*(1+AM43) | AN34: =AM34*(1+AN43)
A35: Government & others | B35: 3368 | C35: 3607 | D35: 3808 | E35: 4059 | F35: 4395 | G35: 4736 | H35: 5424 | I35: 7207 | J35: 6197 | K35: 6575 | L35: 7036 | M35: 7301 | N35: 7564 | O35: 7695 | P35: 7482 | Q35: 7676 | R35: 7661 | S35: 7813 | T35: 7878 | U35: 8018 | V35: 8288 | W35: 8358 | X35: 8585 | Y35: 8802 | Z35: 8858 | AA35: 8987 | AB35: 9342 | AC35: 9586 | AD35: 9171 | AE35: 9742 | AF35: 9863 | AG35: 10196 | AH35: 10466 | AI35: =AH35*(1+AI44) | AJ35: =AI35*(1+AJ44) | AK35: =AJ35*(1+AK44) | AL35: =AK35*(1+AL44) | AM35: =AL35*(1+AM44) | AN35: =AM35*(1+AN44)
A36: Total local | B36: =SUM(B32:B35) | C36: =SUM(C32:C35) | D36: =SUM(D32:D35) | E36: =SUM(E32:E35) | F36: =SUM(F32:F35) | G36: =SUM(G32:G35) | H36: =SUM(H32:H35) | I36: =SUM(I32:I35) | ... AN36: =SUM(AN32:AN35)
A37: China | B37: =B38-B36 | C37: 5777 | D37: 1714 | E37: 1728 | F37: 520 | G37: 557 | H37: 601 | I37: 781 | J37: 1181 | K37: 1581 | L37: 2175 | M37: 3008.025 | N37: 3087 | O37: 4497 | P37: 4528 | Q37: 4035 | R37: 3552 | S37: 3731 | T37: 2609 | U37: 2957 | V37: 1838 | W37: 1650 | X37: 1226 | Y37: 1187 | Z37: 1205 | AA37: 1341 | AB37: 556 | AC37: 0 | AD37: 0 | AE37: =AD37*(1+AE46) | AF37: =AE37*(1+AF46) | AG37: =AF37*(1+AG46) | AH37: =AG37*(1+AH46) | AI37: =AH37*(1+AI46) | AJ37: =AI37*(1+AJ46) | AK37: =AJ37*(1+AK46) | AL37: =AK37*(1+AL46) | ... AN37: =AM37*(1+AN46)
A38: Total local and China | B38: 23191 | C38: =SUM(C36:C37) | D38: =SUM(D36:D37) | E38: =SUM(E36:E37) | F38: =SUM(F36:F37) | G38: =SUM(G36:G37) | H38: =SUM(H36:H37) | I38: =SUM(I36:I37) | J38: =SUM(J36:J37) | ... AN38: =SUM(AN36:AN37)
A40: YOY Change (%)
A41: Commercial | B41: na | C41: =(C32/B32)-1 | D41: =(D32/C32)-1 | E41: =(E32/D32)-1 | F41: =(F32/E32)-1 | G41: =(G32/F32)-1 | H41: =(H32/G32)-1 | I41: =(I32/H32*4/5)-1 | J41: =(J32/I32*5/4)-1 | K41: =K32/J32-1 | L41: =L32/K32-1 | M41: =M32/L32-1 | N41: =N32/M32-1 | O41: =O32/N32-1 | P41: =P32/O32-1 | Q41: =Q32/P32-1 | R41: =R32/Q32-1 | ... AG41: =AG32/AF32-1 | AH41: =AG41 | AI41: =AH41 | AJ41: =AI41 | AK41: =AJ41 | AL41: =AK41 | AM41: =AL41 | AN41: =AM41
A42: Domestic | B42: na | C42: =(C33/B33)-1 | D42: =(D33/C33)-1 | E42: =(E33/D33)-1 | F42: =(F33/E33)-1 | G42: =(G33/F33)-1 | H42: =(H33/G33)-1 | I42: =(I33/H33*4/5)-1 | J42: =(J33/I33*5/4)-1 | K42: =K33/J33-1 | L42: =L33/K33-1 | M42: =M33/L33-1 | N42: =N33/M33-1 | O42: =O33/N33-1 | P42: =P33/O33-1 | Q42: =Q33/P33-1 | R42: =R33/Q33-1 | ... AG42: =AG33/AF33-1 | AH42: =AG42 | AI42: =AH42 | AJ42: =AI42 | AK42: =AJ42 | AL42: =AK42 | AM42: =AL42 | AN42: =AM42
A43: Industrial | B43: na | C43: =(C34/B34)-1 | D43: =(D34/C34)-1 | E43: =(E34/D34)-1 | F43: =(F34/E34)-1 | G43: =(G34/F34)-1 | H43: =(H34/G34)-1 | I43: =(I34/H34*4/5)-1 | J43: =(J34/I34*5/4)-1 | K43: =K34/J34-1 | L43: =L34/K34-1 | M43: =M34/L34-1 | N43: =N34/M34-1 | O43: =O34/N34-1 | P43: =P34/O34-1 | Q43: =Q34/P34-1 | R43: =R34/Q34-1 | ... AG43: =AG34/AF34-1 | AH43: =AG43 | AI43: =AH43 | AJ43: =AI43 | AK43: =AJ43 | AL43: =AK43 | AM43: =AL43 | AN43: =AM43
A44: Government and others | D44: =(D35/C35)-1 | E44: =(E35/D35)-1 | F44: =(F35/E35)-1 | G44: =(G35/F35)-1 | H44: =(H35/G35)-1 | I44: =(I35/H35)-1 | J44: =(J35/I35)-1 | K44: =(K35/J35)-1 | ... AG44: =(AG35/AF35)-1 | AH44: =AG44 | AI44: =AH44 | AJ44: =AI44 | AK44: =AJ44 | AL44: =AK44 | AM44: =AL44 | AN44: =AM44
A45: Total local | B45: na | C45: =(C36/B36)-1 | D45: =(D36/C36)-1 | E45: =(E36/D36)-1 | F45: =(F36/E36)-1 | G45: =(G36/F36)-1 | H45: =(H36/G36)-1 | I45: =(I36/H36*4/5)-1 | J45: =(J36/I36*5/4)-1 | K45: =K36/J36-1 | L45: =L36/K36-1 | M45: =M36/L36-1 | N45: =N36/M36-1 | O45: =O36/N36-1 | P45: =(P36/O36)-1 | Q45: =(Q36/P36)-1 | R45: =(R36/Q36)-1 | S45: =(S36/R36)-1 | T45: =(T36/S36)-1 | U45: =(U36/T36)-1 | V45: =(V36/U36)-1 | W45: =(W36/V36)-1 | ... AN45: =(AN36/AM36)-1
A46: China | D46: =D37/C37-1 | E46: =E37/D37-1 | F46: =F37/E37-1 | G46: =G37/F37-1 | H46: =H37/G37-1 | I46: =(I37/H37*4/5)-1 | J46: =(J37/I37*5/4)-1 | K46: =K37/J37-1 | L46: =L37/K37-1 | M46: =M37/L37-1 | N46: =N37/M37-1 | O46: =O37/N37-1 | P46: =P37/O37-1 | Q46: =Q37/P37-1 | R46: =R37/Q37-1 | ... AC46: =AC37/AB37-1 | AD46: 0 | AE46: 0 | AF46: 0 | AG46: 0 | AH46: =AG46 | AI46: =AH46 | AJ46: =AI46 | AK46: =AJ46 | AL46: =AK46 | AM46: =AL46 | AN46: =AM46
A47: Total local and China | C47: =C38/B38-1 | D47: =D38/C38-1 | E47: =E38/D38-1 | F47: =F38/E38-1 | G47: =G38/F38-1 | H47: =H38/G38-1 | I47: =(I38/H38*4/5)-1 | J47: =(J38/I38*5/4)-1 | K47: =K38/J38-1 | L47: =L38/K38-1 | M47: =M38/L38-1 | N47: =N38/M38-1 | O47: =O38/N38-1 | P47: =P38/O38-1 | Q47: =Q38/P38-1 | R47: =R38/Q38-1 | ... AN47: =AN38/AM38-1
A49: Percentage of sales
A50: Commercial | B50: =B32/B$36 | C50: =C32/C$36 | D50: =D32/D$36 | E50: =E32/E$36 | F50: =F32/F$36 | G50: =G32/G$36 | H50: =H32/H$36 | I50: =I32/I$36 | ... AN50: =AN32/AN$36
A51: Domestic | B51: =B33/B$36 | C51: =C33/C$36 | D51: =D33/D$36 | E51: =E33/E$36 | F51: =F33/F$36 | G51: =G33/G$36 | H51: =H33/H$36 | I51: =I33/I$36 | ... AN51: =AN33/AN$36
A52: Industrial | B52: =B34/B$36 | C52: =C34/C$36 | D52: =D34/D$36 | E52: =E34/E$36 | F52: =F34/F$36 | G52: =G34/G$36 | H52: =H34/H$36 | I52: =I34/I$36 | ... AN52: =AN34/AN$36
A53: Government & others | B53: =B35/B$36 | C53: =C35/C$36 | D53: =D35/D$36 | E53: =E35/E$36 | F53: =F35/F$36 | G53: =G35/G$36 | H53: =H35/H$36 | I53: =I35/I$36 | ... AN53: =AN35/AN$36
A54: Total local | B54: =SUM(B50:B53) | C54: =SUM(C50:C53) | D54: =SUM(D50:D53) | E54: =SUM(E50:E53) | F54: =SUM(F50:F53) | G54: =SUM(G50:G53) | H54: =SUM(H50:H53) | I54: =SUM(I50:I53) | ... AN54: =SUM(AN50:AN53)
A55: China | B55: =B37/B$38 | C55: =C37/C$38 | D55: =D37/D$38 | E55: =E37/E$38 | F55: =F37/F$38 | G55: =G37/G$38 | H55: =H37/H$38 | I55: =I37/I$38 | ... AN55: =AN37/AN$38
A56: Total local and China | B56: =B38/B$38 | C56: =C38/C$38 | D56: =D38/D$38 | E56: =E38/E$38 | F56: =F38/F$38 | G56: =G38/G$38 | H56: =H38/H$38 | I56: =I38/I$38 | ... AN56: =AN38/AN$38

Sheet SOC Accounts
A1: Year ended December (HK$m) | B1: ='HK Sales'!B$2 | C1: ='HK Sales'!C$2 | D1: ='HK Sales'!D$2 | E1: ='HK Sales'!E$2 | F1: ='HK Sales'!F$2 | G1: ='HK Sales'!G$2 | H1: ='HK Sales'!H$2 | I1: ='HK Sales'!I$2 | ... AN1: ='HK Sales'!AN$2
A3: Fuel Clause Recovery
A4: Opening balance | B4: 107 | C4: =B7 | D4: =C7 | E4: =D7 | F4: =E7 | G4: =F7 | H4: =G7 | I4: =H7 | J4: =I7 | ... AN4: =AM7
A5: Transferred from Profit & Loss Account | B5: =B7-B6-B4 | C5: =C7-C6-C4 | D5: =D7-D6-D4 | E5: =E7-E6-E4 | F5: =F7-F6-F4 | G5: =G7-G6-G4 | H5: =H7-H6-H4 | I5: =I7-I6-I4 | ... AH5: =AH7-AH6-AH4 | AI5: =-AI13*('HK Sales'!AI38-AI56) | AJ5: =-AJ13*('HK Sales'!AJ38-AJ56) | AK5: =-AK13*('HK Sales'!AK38-AK56) | AL5: =-AL13*('HK Sales'!AL38-AL56) | AM5: =-AM13*('HK Sales'!AM38-AM56) | AN5: =-AN13*('HK Sales'!AN38-AN56)
A6: Charge/(Rebate) during the year | B6: =-'HK Sales'!B16*'HK Sales'!B36/100 | C6: =-'HK Sales'!C16*'HK Sales'!C36/100 | D6: =-'HK Sales'!D16*'HK Sales'!D36/100 | E6: =-'HK Sales'!E16*'HK Sales'!E36/100 | F6: =-'HK Sales'!F16*'HK Sales'!F36/100 | G6: =-'HK Sales'!G16*'HK Sales'!G36/100 | H6: =-'HK Sales'!H16*'HK Sales'!H36/100 | I6: =-'HK Sales'!I16*'HK Sales'!I36/100 | ... AN6: =-'HK Sales'!AN16*'HK Sales'!AN36/100
A7: Closing balance | B7: =B8-B9 | C7: =C8-C9 | D7: =D8-D9 | E7: =E8-E9 | F7: =F8-F9 | G7: =G8-G9 | H7: =H8-H9 | I7: =I8-I9 | ... L7: =L8-L9 | M7: -874 | N7: -762 | O7: -323 | P7: -294 | Q7: 132 | R7: 800 | S7: 14 | T7: 294 | U7: 212 | V7: 337 | W7: -1464 | X7: -2966 | Y7: -2226 | Z7: -2867 | AA7: -2212 | AB7: -901 | AC7: -1131 | AD7: -346 | AE7: 1116 | AF7: 3543 | AG7: 328 | AH7: 370 | AI7: =SUM(AI4:AI6) | AJ7: =SUM(AJ4:AJ6) | AK7: =SUM(AK4:AK6) | AL7: =SUM(AL4:AL6) | AM7: =SUM(AM4:AM6) | AN7: =SUM(AN4:AN6)
A8: Receivable | B8: 0 | C8: 0 | D8: 0 | E8: 0 | F8: 152 | G8: 867 | H8: 631 | I8: 327 | J8: 37 | K8: 0 | L8: 0 | M8: =IF(M7<0,0,M7) | N8: =IF(N7<0,0,N7) | O8: =IF(O7<0,0,O7) | P8: =IF(P7<0,0,P7) | Q8: =IF(Q7<0,0,Q7) | R8: =IF(R7<0,0,R7) | S8: =IF(S7<0,0,S7) | T8: =IF(T7<0,0,T7) | ... AN8: =IF(AN7<0,0,AN7)
A9: Payable | B9: 107 | C9: 630 | D9: 682 | E9: 409 | F9: 0 | G9: 0 | H9: 0 | I9: 0 | J9: 0 | K9: 448 | L9: 512 | M9: =M8-M7 | N9: =N8-N7 | O9: =O8-O7 | P9: =P8-P7 | Q9: =Q8-Q7 | R9: =R8-R7 | S9: =S8-S7 | T9: =T8-T7 | ... AN9: =AN8-AN7
A12: Actual fuel cost/kWh | B12: =B70 | C12: =C70 | D12: =D70 | E12: =E70 | F12: =F70 | G12: =G70 | H12: =H70 | I12: =I70 | ... AN12: =AN70
A13: Transfer from P&L/kWh | B13: =-B5/('HK Sales'!B38-B56) | C13: =-C5/('HK Sales'!C38-C56) | D13: =-D5/('HK Sales'!D38-D56) | E13: =-E5/('HK Sales'!E38-E56) | F13: =-F5/('HK Sales'!F38-F56) | G13: =-G5/('HK Sales'!G38-G56) | H13: =-H5/('HK Sales'!H38-H56) | I13: =-I5/('HK Sales'!I38-I56) | ... AH13: =-AH5/('HK Sales'!AH38-AH56) | AI13: =AI14-AI12 | AJ13: =AJ14-AJ12 | AK13: =AK14-AK12 | AL13: =AL14-AL12 | AM13: =AM14-AM12 | AN13: =AN14-AN12
A14: Standard fuel cost/kWh | B14: =SUM(B12:B13) | C14: =SUM(C12:C13) | D14: =SUM(D12:D13) | E14: =SUM(E12:E13) | F14: =SUM(F12:F13) | G14: =SUM(G12:G13) | H14: =SUM(H12:H13) | I14: =SUM(I12:I13) | ... AH14: =SUM(AH12:AH13) | AI14: =AH14 | AJ14: =AI14 | AK14: =AJ14 | AL14: =AK14 | AM14: =AL14 | AN14: =AM14
A16: Development Fund/Tariff Stabilization Account
A17: Opening balance | B17: 2849 | C17: =B21 | D17: =C21 | E17: =D21 | F17: =E21 | G17: =F21 | H17: =G21 | I17: =H21 | J17: =I21 | ... AN17: =AM21
A18: Transfer to/from income statement | B18: 373 | C18: =-SOC!C23 | D18: =-SOC!D23 | E18: =-SOC!E23 | F18: =-SOC!F23 | G18: =-SOC!G23 | H18: =-SOC!H23 | I18: =-SOC!I23 | J18: =-SOC!J23 | ... AN18: =-SOC!AN23
A19: Rebates | C19: =C21-C20-SUM(C17:C18) | D19: =D21-D20-SUM(D17:D18) | E19: =E21-E20-SUM(E17:E18) | F19: =F21-F20-SUM(F17:F18) | G19: =G21-G20-SUM(G17:G18) | H19: =H21-H20-SUM(H17:H18) | I19: =I21-I20-SUM(I17:I18) | J19: =J21-J20-SUM(J17:J18) | ... M19: =M21-M20-SUM(M17:M18) | N19: ='HK Sales'!N22 | O19: ='HK Sales'!O22 | P19: ='HK Sales'!P22 | Q19: ='HK Sales'!Q22 | R19: ='HK Sales'!R22 | S19: ='HK Sales'!S22 | T19: ='HK Sales'!T22 | U19: ='HK Sales'!U22 | ... AN19: ='HK Sales'!AN22
A20: Other | J20: -803 | K20: 0 | R20: =-SOC!R22 | S20: =-SOC!S22 | T20: =-SOC!T22 | U20: =-SOC!U22 | V20: =-SOC!V22 | W20: =-SOC!W22-W33 | X20: =-SOC!X22-X33 | Y20: =-SOC!Y22-Y33 | Z20: =-SOC!Z22-Z33 | AA20: =-SOC!AA22-AA33 | AB20: =-SOC!AB22-AB33 | AC20: =-SOC!AC22-AC33 | AD20: =-SOC!AD22-AD33 | ... AN20: =-SOC!AN22-AN33
A21: Closing balance | B21: 3222 | C21: 3847 | D21: 2944 | E21: 2419 | F21: 1926 | G21: 1432 | H21: 2528 | I21: 3320 | J21: 2923 | K21: 3177 | L21: 3372 | M21: 2960 | N21: 3171 | O21: 3685 | P21: =SUM(P17:P20) | Q21: =SUM(Q17:Q20) | R21: =SUM(R17:R20) | S21: =SUM(S17:S20) | T21: =SUM(T17:T20) | U21: =SUM(U17:U20) | V21: =SUM(V17:V20) | W21: =SUM(W17:W20) | ... AH21: =SUM(AH17:AH20) | AI21: =MAX(0,SUM(AI17:AI20)) | AJ21: =MAX(0,SUM(AJ17:AJ20)) | AK21: =MAX(0,SUM(AK17:AK20)) | AL21: =MAX(0,SUM(AL17:AL20)) | AM21: =MAX(0,SUM(AM17:AM20)) | AN21: =MAX(0,SUM(AN17:AN20))
A23: Special provision account
A24: Opening balance | B24: 0 | C24: =B27 | D24: =C27 | E24: =D27 | F24: =E27 | G24: =F27 | H24: =G27 | I24: =H27 | J24: =I27 | ... AN24: =AM27
A25: Transferred from Profit & Loss Account | J25: =-J20
A26: Transferred to P&L | J26: =J27-SUM(J24:J25) | K26: =K27-SUM(K24:K25) | L26: =L27-SUM(L24:L25) | M26: =M27-SUM(M24:M25) | N26: -176
A27: Closing balance | B27: 0 | C27: 0 | D27: 0 | E27: 0 | F27: 0 | G27: 0 | H27: 0 | I27: 0 | J27: 766 | K27: 766 | L27: 670 | M27: 176 | N27: 0 | O27: =SUM(O24:O26) | P27: =SUM(P24:P26) | Q27: =SUM(Q24:Q26) | R27: =SUM(R24:R26) | S27: =SUM(S24:S26) | T27: =SUM(T24:T26) | U27: =SUM(U24:U26) | V27: =SUM(V24:V26) | ... AN27: =SUM(AN24:AN26)
A29: Rate Reduction Reserve
A30: Opening balance | B30: 337 | C30: =B34 | D30: =C34 | E30: =D34 | F30: =E34 | G30: =F34 | H30: =G34 | I30: =H34 | J30: =I34 | ... AN30: =AM34
A31: Interest expense charged to P&L | B31: =-SOC!B30 | C31: =-SOC!C30 | D31: =-SOC!D30 | E31: =-SOC!E30 | F31: =-SOC!F30 | G31: =-SOC!G30 | H31: =-SOC!H30 | I31: =-SOC!I30 | ... W31: =-SOC!W30 | X31: 1 | Y31: =-SOC!Y30 | Z31: =-SOC!Z30 | AA31: =-SOC!AA30 | AB31: =-SOC!AB30 | AC31: =-SOC!AC30 | AD31: =-SOC!AD30 | AE31: =-SOC!AE30 | AF31: =-SOC!AF30 | ... AH31: =-SOC!AH30 | AI31: 0 | AJ31: 0 | AK31: 0 | AL31: 0 | AM31: 0 | AN31: 0
A32: Rebates | B32: ='HK Sales'!B23 | C32: ='HK Sales'!C23 | D32: ='HK Sales'!D23 | E32: ='HK Sales'!E23 | F32: ='HK Sales'!F23 | G32: ='HK Sales'!G23 | H32: ='HK Sales'!H23 | I32: ='HK Sales'!I23 | ... AN32: ='HK Sales'!AN23
A33: Other | B33: -48 | C33: =C34-SUM(C30:C32) | D33: =D34-SUM(D30:D32) | E33: =E34-SUM(E30:E32) | F33: =F34-SUM(F30:F32) | G33: =G34-SUM(G30:G32) | H33: =H34-SUM(H30:H32) | I33: =I34-SUM(I30:I32) | J33: =J34-SUM(J30:J32) | ... O33: =O34-SUM(O30:O32) | W33: 0 | X33: -9 | Y33: -1 | Z33: -2 | AA33: -2 | AB33: -4 | AC33: -11 | AD33: -22 | AE33: -18 | AF33: -3 | AG33: -40 | AH33: -114 | AI33: =AH33 | AJ33: =AI33 | AK33: =AJ33 | AL33: =AK33 | AM33: =AL33 | AN33: =AM33
A34: Closing balance | B34: 312 | C34: 188 | D34: 115 | E34: 119 | F34: 156 | G34: 148 | H34: 154 | I34: 253 | J34: 371 | K34: 411 | L34: 458 | M34: 471 | N34: 549 | O34: 489 | P34: =SUM(P30:P33) | Q34: =SUM(Q30:Q33) | R34: =SUM(R30:R33) | S34: =SUM(S30:S33) | T34: =SUM(T30:T33) | U34: =SUM(U30:U33) | V34: =SUM(V30:V33) | W34: =SUM(W30:W33) | ... AN34: =SUM(AN30:AN33)
A36: Special rebate account
A37: Opening balance | P37: =O40 | Q37: =P40 | R37: =Q40 | S37: =R40 | T37: =S40 | U37: =T40 | V37: =U40 | W37: =V40 | ... AN37: =AM40
A38: Recovery of rents and rates | V38: =+V40-V39 | W38: 40 | X38: 72 | AA38: =AA40-AA37 | AB38: =AB40-AB37-AB39 | AC38: =AC40-AC37-AC39 | AD38: =AD40-AD37-AD39 | AE38: =AE40-AE37-AE39 | AF38: =AF40-AF37-AF39 | AG38: =AG40-AG37-AG39 | AH38: =AH40-AH37-AH39
A39: Rebate to customers | V39: ='HK Sales'!V18/100*'HK Sales'!V36 | W39: -565 | X39: ='HK Sales'!X18/100*'HK Sales'!X36 | Y39: 0 | Z39: ='HK Sales'!Z18/100*'HK Sales'!Z36 | AA39: ='HK Sales'!AA18/100*'HK Sales'!AA36 | AB39: ='HK Sales'!AB18/100*'HK Sales'!AB36 | AC39: ='HK Sales'!AC18/100*'HK Sales'!AC36 | AD39: ='HK Sales'!AD18/100*'HK Sales'!AD36 | AE39: ='HK Sales'!AE18/100*'HK Sales'!AE36 | AF39: ='HK Sales'!AF18/100*'HK Sales'!AF36 | AG39: ='HK Sales'!AG18/100*'HK Sales'!AG36 | ... AN39: ='HK Sales'!AN18/100*'HK Sales'!AN36
A40: Closing balance payable (receivable) | O40: =SUM(O37:O39) | P40: =SUM(P37:P39) | Q40: =SUM(Q37:Q39) | R40: =SUM(R37:R39) | S40: =SUM(S37:S39) | T40: =SUM(T37:T39) | U40: =SUM(U37:U39) | V40: 525 | W40: =SUM(W37:W39) | X40: =SUM(X37:X39) | Y40: =SUM(Y37:Y39) | Z40: =SUM(Z37:Z39) | AA40: 227 | AB40: 46 | AC40: 0 | AD40: 337 | AE40: 328 | AF40: 126 | AG40: 0 | AH40: 0 | AI40: =SUM(AI37:AI39) | AJ40: =SUM(AJ37:AJ39) | AK40: =SUM(AK37:AK39) | AL40: =SUM(AL37:AL39) | AM40: =SUM(AM37:AM39) | AN40: =SUM(AN37:AN39)
A41: Receivable | V41: =IF(V40>0,0,V40) | W41: =IF(W40>0,0,-W40) | X41: =IF(X40>0,0,-X40) | Y41: =IF(Y40>0,0,-Y40) | Z41: =IF(Z40>0,0,-Z40) | AA41: =IF(AA40>0,0,-AA40) | AB41: =IF(AB40>0,0,-AB40) | AC41: =IF(AC40>0,0,-AC40) | AD41: =IF(AD40>0,0,-AD40) | ... AN41: =IF(AN40>0,0,-AN40)
A42: Payable | V42: =IF(V40<0,0,V40) | W42: =IF(W40<0,0,W40) | X42: =IF(X40<0,0,X40) | Y42: =IF(Y40<0,0,Y40) | Z42: =IF(Z40<0,0,Z40) | AA42: =IF(AA40<0,0,AA40) | AB42: =IF(AB40<0,0,AB40) | AC42: =IF(AC40<0,0,AC40) | ... AN42: =IF(AN40<0,0,AN40)
A44: Operating costs
A45: Nuclear Power purchase costs | B45: =SOC!B8 | C45: =SOC!C8 | D45: =SOC!D8 | E45: =SOC!E8 | F45: =SOC!F8 | G45: =SOC!G8 | H45: =SOC!H8 | I45: =SOC!I8 | ... AH45: =SOC!AH8 | AI45: =-AI56*AI46 | AJ45: =-AJ56*AJ46 | AK45: =-AK56*AK46 | AL45: =-AL56*AL46 | AM45: =-AM56*AM46 | AN45: =-AN56*AN46
A46: Cost per kWh | D46: =-D45/D56 | E46: =-E45/E56 | F46: =-F45/F56 | G46: =-G45/G56 | H46: =-H45/H56 | I46: =-I45/I56 | J46: =-J45/J56 | K46: =-K45/K56 | ... AH46: =-AH45/AH56 | AI46: =AH46 | AJ46: =AI46 | AK46: =AJ46 | AL46: =AK46 | AM46: =AL46 | AN46: =AM46
A48: Net operating costs | B48: -2947 | C48: -3323 | D48: -2894 | E48: =SOC!E7 | F48: =SOC!F7 | G48: =SOC!G7 | H48: =SOC!H7 | I48: =SOC!I7 | J48: =SOC!J7 | K48: =SOC!K7 | L48: =SOC!L7 | ... AH48: =SOC!AH7 | AI48: =-AI49*'HK Sales'!AI38*(1+AI50) | AJ48: =-AJ49*'HK Sales'!AJ38*(1+AJ50) | AK48: =-AK49*'HK Sales'!AK38*(1+AK50) | AL48: =-AL49*'HK Sales'!AL38*(1+AL50) | AM48: =-AM49*'HK Sales'!AM38*(1+AM50) | AN48: =-AN49*'HK Sales'!AN38*(1+AN50)
A49: Price per KWh | B49: =-B48/'HK Sales'!B38 | C49: =-C48/'HK Sales'!C38 | D49: =-D48/'HK Sales'!D38 | E49: =-E48/'HK Sales'!E38 | F49: =-F48/'HK Sales'!F38 | G49: =-G48/'HK Sales'!G38 | H49: =-H48/'HK Sales'!H38 | I49: =-I48/'HK Sales'!I38 | ... AH49: =-AH48/'HK Sales'!AH38 | AI49: =AH49*(1+AI50) | AJ49: =AI49*(1+AJ50) | AK49: =AJ49*(1+AK50) | AL49: =AK49*(1+AL50) | AM49: =AL49*(1+AM50) | AN49: =AM49*(1+AN50)
A50: Inflation | C50: =C49/B49-1 | D50: =D49/C49-1 | E50: =E49/D49-1 | F50: =F49/E49-1 | G50: =G49/F49-1 | H50: =H49/G49-1 | I50: =I49/H49-1 | J50: =J49/I49-1 | ... AH50: =AH49/AG49-1 | AI50: =AH50 | AJ50: =AI50 | AK50: =AJ50 | AL50: =AK50 | AM50: =AL50 | AN50: =AM50
A52: Power sales by fuel type
A53: Total power sales | L53: =+'HK Sales'!L36 | M53: =+'HK Sales'!M38 | N53: =+'HK Sales'!N38 | O53: =+'HK Sales'!O38 | P53: =+'HK Sales'!P38 | Q53: =+'HK Sales'!Q38 | R53: =+'HK Sales'!R38 | S53: =+'HK Sales'!S38 | T53: =+'HK Sales'!T38 | ... AN53: =+'HK Sales'!AN38
A54: T&D Loss | R54: =+R55/R53-1 | S54: =+S55/S53-1 | T54: =+T55/T53-1 | U54: =+U55/U53-1 | V54: =+V55/V53-1 | W54: =+W55/W53-1 | X54: =+X55/X53-1 | Y54: =+Y55/Y53-1 | ... AH54: =+AH55/AH53-1 | AI54: =+AH54 | AJ54: =+AI54 | AK54: =+AJ54 | AL54: =+AK54 | AM54: =+AL54 | AN54: =+AM54
A55: Total power sent out | R55: =+SUM(R56:R57) | S55: =+SUM(S56:S57) | T55: =+SUM(T56:T57) | U55: =+SUM(U56:U57) | V55: =+SUM(V56:V57) | W55: =+SUM(W56:W57) | X55: =+SUM(X56:X57) | Y55: =+SUM(Y56:Y57) | ... AH55: =+SUM(AH56:AH57) | AI55: =+AI53*(1+AI54) | AJ55: =+AJ53*(1+AJ54) | AK55: =+AK53*(1+AK54) | AL55: =+AL53*(1+AL54) | AM55: =+AM53*(1+AM54) | AN55: =+AN53*(1+AN54)
A56: GNPS/GPSPS/Others | B56: 0 | C56: 0 | D56: 6430 | E56: 6755 | F56: 7467 | G56: 7361 | H56: 7825 | I56: =8819+1680 | J56: 9735 | K56: 9961 | L56: 9784 | M56: 9968 | N56: =9165+1 | O56: =10212+3 | P56: =10256+5 | Q56: =10164+6 | R56: =10653+5 | S56: =10773+5 | T56: =10350+5 | U56: =10558+5 | V56: =11172+3 | W56: =9757+4 | X56: =10084+3 | Y56: =11612+4 | Z56: =11501+4 | AA56: =12426+2 | AB56: =12501+3 | AC56: =12276+9 | AD56: =12583+45 | AE56: =12484+111 | AF56: =12289+199 | AG56: =11552+267 | AH56: =11335+316 | AI56: =AH56 | AJ56: =AI56 | AK56: =AJ56 | AL56: =AK56 | AM56: =AL56 | AN56: =AM56
A57: CAPCO output (GWh) | R57: 24324 | S57: 24920 | T57: 24552 | U57: 24955 | V57: 24102 | W57: 25084 | X57: 25597 | Y57: 24075 | Z57: 24362 | AA57: 23456 | AB57: 23032 | AC57: 23369 | AD57: 22605 | AE57: 24109 | AF57: 23602 | AG57: 24846 | AH57: 25761 | AI57: =+AI55-AI56 | AJ57: =+AJ55-AJ56 | AK57: =+AK55-AK56 | AL57: =+AL55-AL56 | AM57: =+AM55-AM56 | AN57: =+AN55-AN56
A58: Black Point (Gas fired) | S58: 8871 | T58: 10548 | U58: 7311 | V58: 6787 | W58: 5675 | X58: 5315 | Y58: 8899 | Z58: 9175 | AA58: 9550 | AB58: 9304 | AC58: 10315 | AD58: =AC58/107183*134776 | AE58: =AD58/134776*142304 | AF58: =AE58/142304*151327 | AG58: =AF58/151327*146370 | AH58: =AG58/146370*151371 | AI58: =+AI57-AI59 | AJ58: =+AJ57-AJ59 | AK58: =+AK57-AK59 | AL58: =+AL57-AL59 | AM58: =+AM57-AM59 | AN58: =+AN57-AN59
A59: Castle Peak (Coal fired) | S59: 16049 | T59: 14004 | U59: 17644 | V59: 17310 | W59: 19409 | X59: 20280 | Y59: 15176 | Z59: 15187 | AA59: 13906 | AB59: 13727 | AC59: 13052 | AD59: =AD57-AD58 | AE59: =AE57-AE58 | AF59: =AF57-AF58 | AG59: =AG57-AG58 | AH59: =AH57-AH58 | AI59: =+AI62*AVERAGE(ROAFNA!AH64:AI64)*8760/1000 | AJ59: =+AJ62*AVERAGE(ROAFNA!AI64:AJ64)*8760/1000 | AK59: =+AK62*AVERAGE(ROAFNA!AJ64:AK64)*8760/1000 | AL59: =+AL62*AVERAGE(ROAFNA!AK64:AL64)*8760/1000 | AM59: =+AM62*AVERAGE(ROAFNA!AL64:AM64)*8760/1000 | AN59: =+AN62*AVERAGE(ROAFNA!AM64:AN64)*8760/1000
A60: Utilisation rate
A61: Gas (implied) | T61: =+T58/AVERAGE(ROAFNA!S65:T65)/8760*1000 | U61: =+U58/AVERAGE(ROAFNA!T65:U65)/8760*1000 | V61: =+V58/AVERAGE(ROAFNA!U65:V65)/8760*1000 | W61: =+W58/AVERAGE(ROAFNA!V65:W65)/8760*1000 | X61: =+X58/AVERAGE(ROAFNA!W65:X65)/8760*1000 | Y61: =+Y58/AVERAGE(ROAFNA!X65:Y65)/8760*1000 | Z61: =+Z58/AVERAGE(ROAFNA!Y65:Z65)/8760*1000 | AA61: =+AA58/AVERAGE(ROAFNA!Z65:AA65)/8760*1000 | ... AN61: =+AN58/AVERAGE(ROAFNA!AM65:AN65)/8760*1000
A62: Coal | T62: =+T59/AVERAGE(ROAFNA!S64:T64)/8760*1000 | U62: =+U59/AVERAGE(ROAFNA!T64:U64)/8760*1000 | V62: =+V59/AVERAGE(ROAFNA!U64:V64)/8760*1000 | W62: =+W59/AVERAGE(ROAFNA!V64:W64)/8760*1000 | X62: =+X59/AVERAGE(ROAFNA!W64:X64)/8760*1000 | Y62: =+Y59/AVERAGE(ROAFNA!X64:Y64)/8760*1000 | Z62: =+Z59/AVERAGE(ROAFNA!Y64:Z64)/8760*1000 | AA62: =+AA59/AVERAGE(ROAFNA!Z64:AA64)/8760*1000 | ... AH62: =+AH59/AVERAGE(ROAFNA!AG64:AH64)/8760*1000 | AI62: =+MAX($AN$62,AH62-0.75%) | AJ62: =+MAX($AN$62,AI62-0.75%) | AK62: =+MAX($AN$62,AJ62-0.75%) | AL62: =+MAX($AN$62,AK62-0.75%) | AM62: =+MAX($AN$62,AL62-0.75%) | AN62: 0.3
A63: Implied fuel mix
A64: Nuclear | S64: =+(S56/S$55) | T64: =+(T56/T$55) | U64: =+(U56/U$55) | V64: =+(V56/V$55) | W64: =+(W56/W$55) | X64: =+(X56/X$55) | Y64: =+(Y56/Y$55) | Z64: =+(Z56/Z$55) | ... AN64: =+(AN56/AN$55)
A65: Gas | S65: =+(S58/S$55) | T65: =+(T58/T$55) | U65: =+(U58/U$55) | V65: =+(V58/V$55) | W65: =+(W58/W$55) | X65: =+(X58/X$55) | Y65: =+(Y58/Y$55) | Z65: =+(Z58/Z$55) | ... AN65: =+(AN58/AN$55)
A66: Coal | S66: =+(S59/S$55) | T66: =+(T59/T$55) | U66: =+(U59/U$55) | V66: =+(V59/V$55) | W66: =+(W59/W$55) | X66: =+(X59/X$55) | Y66: =+(Y59/Y$55) | Z66: =+(Z59/Z$55) | ... AN66: =+(AN59/AN$55)
A68: Fuel costs
A69: Total fuel costs | B69: =SOC!B6 | C69: =SOC!C6 | D69: =SOC!D6 | E69: =SOC!E6 | F69: =SOC!F6 | G69: =SOC!G6 | H69: =SOC!H6 | I69: =SOC!I6 | ... AH69: =SOC!AH6 | AI69: =AI76+AI82 | AJ69: =AJ76+AJ82 | AK69: =AK76+AK82 | AL69: =AL76+AL82 | AM69: =AM76+AM82 | AN69: =AN76+AN82
A70: Price per KWh | B70: =-B69/('HK Sales'!B38-B56) | C70: =-C69/('HK Sales'!C38-C56) | D70: =-D69/('HK Sales'!D38-D56) | E70: =-E69/('HK Sales'!E38-E56) | F70: =-F69/('HK Sales'!F38-F56) | G70: =-G69/('HK Sales'!G38-G56) | H70: =-H69/('HK Sales'!H38-H56) | I70: =-I69/('HK Sales'!I38-I56) | ... AN70: =-AN69/('HK Sales'!AN38-AN56)
A71: Unit fuel costs by fuel type (HK$/kWh)
A72: Nuclear | S72: =+S46 | T72: =+T46 | U72: =+U46 | V72: =+V46 | W72: =+W46 | X72: =+X46 | Y72: =+Y46 | Z72: =+Z46 | ... AN72: =+AN46
A73: Gas | S73: =-S82/S58 | T73: =-T82/T58 | U73: =-U82/U58 | V73: =-V82/V58 | W73: =-W82/W58 | X73: =-X82/X58 | Y73: =-Y82/Y58 | Z73: =-Z82/Z58 | ... AN73: =-AN82/AN58
A74: Coal | S74: =-S76/S59 | T74: =-T76/T59 | U74: =-U76/U59 | V74: =-V76/V59 | W74: =-W76/W59 | X74: =-X76/X59 | Y74: =-Y76/Y59 | Z74: =-Z76/Z59 | ... AN74: =-AN76/AN59
A76: Total cost of coal | S76: =+S69-S82 | T76: =+T69-T82 | U76: =+U69-U82 | V76: =+V69-V82 | W76: =+W69-W82 | X76: =+X69-X82 | Y76: -3419 | Z76: -2832 | AA76: -3770 | AB76: -4613 | AC76: -3654 | AD76: -1270 | AE76: -2486 | AF76: -6288 | AG76: -4671 | AH76: -2608 | AI76: =-AI77*AI80*7.8*AI59/1000000 | AJ76: =-AJ77*AJ80*7.8*AJ59/1000000 | AK76: =-AK77*AK80*7.8*AK59/1000000 | AL76: =-AL77*AL80*7.8*AL59/1000000 | AM76: =-AM77*AM80*7.8*AM59/1000000 | AN76: =-AN77*AN80*7.8*AN59/1000000
A77: Coal cost (US$/t) | S77: =-S76/S79/7.8 | T77: =-T76/T79/7.8 | U77: =-U76/U79/7.8 | V77: =-V76/V79/7.8 | W77: =-W76/W79/7.8 | X77: =-X76/X79/7.8 | Y77: =-Y76/Y79/7.8 | Z77: =-Z76/Z79/7.8 | ... AH77: =-AH76/AH79/7.8 | AI77: =+AH77/80*82 | AJ77: =+AI77 | AK77: =+AJ77 | AL77: =+AK77 | AM77: =+AL77 | AN77: =+AM77
A78: Consumption of coal (TJ) | S78: 169753 | T78: 148229 | U78: 188407 | V78: 182651 | W78: 205198 | X78: 215367 | Y78: 161988 | Z78: 160661 | AA78: 148065 | AB78: 150310 | AC78: 141830 | AD78: 63505 | AE78: 75307 | AF78: 77172 | AG78: 76699 | AH78: 69394 | AI78: =+AI80*AI59/34.1208 | AJ78: =+AJ80*AJ59/34.1208 | AK78: =+AK80*AK59/34.1208 | AL78: =+AL80*AL59/34.1208 | AM78: =+AM80*AM59/34.1208 | AN78: =+AN80*AN59/34.1208
A79: Consumption of coal (mt) | S79: =+S78*34.1208/1000000 | T79: =+T78*34.1208/1000000 | U79: =+U78*34.1208/1000000 | V79: =+V78*34.1208/1000000 | W79: =+W78*34.1208/1000000 | X79: =+X78*34.1208/1000000 | Y79: =+Y78*34.1208/1000000 | Z79: =+Z78*34.1208/1000000 | ... AE79: =+AE78*34.1208/1000000 | AF79: =+AF80*AF59/1000000 | AG79: =+AG80*AG59/1000000 | AH79: =+AH80*AH59/1000000 | AI79: =+AI80*AI59/1000000 | AJ79: =+AJ80*AJ59/1000000 | AK79: =+AK80*AK59/1000000 | AL79: =+AL80*AL59/1000000 | AM79: =+AM80*AM59/1000000 | AN79: =+AN80*AN59/1000000
A80: Coal consumption, output based (g/kWh) | S80: =++S78*34.1208/S59 | T80: =++T78*34.1208/T59 | U80: =++U78*34.1208/U59 | V80: =++V78*34.1208/V59 | W80: =++W78*34.1208/W59 | X80: =++X78*34.1208/X59 | Y80: =++Y78*34.1208/Y59 | Z80: =++Z78*34.1208/Z59 | ... AH80: =++AH78*34.1208/AH59 | AI80: =+AH80 | AJ80: =+AI80 | AK80: =+AJ80 | AL80: =+AK80 | AM80: =+AL80 | AN80: =+AM80
A82: Total cost of gas | S82: =-S83*7.8*S91*947.81712031332/1000000 | T82: =-T83*7.8*T91*947.81712031332/1000000 | U82: =-U83*7.8*U91*947.81712031332/1000000 | V82: =-V83*7.8*V91*947.81712031332/1000000 | W82: =-W83*7.8*W91*947.81712031332/1000000 | X82: =-X83*7.8*X91*947.81712031332/1000000 | Y82: =+Y69-Y76 | Z82: =+Z69-Z76 | AA82: =+AA69-AA76 | AB82: =+AB69-AB76 | AC82: =+AC69-AC76 | AD82: =+AD69-AD76 | AE82: =+AE69-AE76 | AF82: =+AF69-AF76 | ... AH82: =+AH69-AH76 | AI82: =-AI83*7.8*AI91*947.81712031332/1000000 | AJ82: =-AJ83*7.8*AJ91*947.81712031332/1000000 | AK82: =-AK83*7.8*AK91*947.81712031332/1000000 | AL82: =-AL83*7.8*AL91*947.81712031332/1000000 | AM82: =-AM83*7.8*AM91*947.81712031332/1000000 | AN82: =-AN83*7.8*AN91*947.81712031332/1000000
A83: Gas cost (US$/mmbtu) | S83: 6 | T83: 6 | U83: 6 | V83: =+SUMPRODUCT(V84:V86,V88:V90) | W83: =+SUMPRODUCT(W84:W86,W88:W90) | X83: =+SUMPRODUCT(X84:X86,X88:X90) | Y83: =-Y82/(7.8*Y91*947.81712031332/1000000) | Z83: =-Z82/(7.8*Z91*947.81712031332/1000000) | AA83: =-AA82/(7.8*AA91*947.81712031332/1000000) | AB83: =-AB82/(7.8*AB91*947.81712031332/1000000) | AC83: =-AC82/(7.8*AC91*947.81712031332/1000000) | AD83: =-AD82/(7.8*AD91*947.81712031332/1000000) | AE83: =-AE82/(7.8*AE91*947.81712031332/1000000) | AF83: =-AF82/(7.8*AF91*947.81712031332/1000000) | ... AH83: =-AH82/(7.8*AH91*947.81712031332/1000000) | AI83: =+SUMPRODUCT(AI84:AI86,AI88:AI90) | AJ83: =+SUMPRODUCT(AJ84:AJ86,AJ88:AJ90) | AK83: =+SUMPRODUCT(AK84:AK86,AK88:AK90) | AL83: =+SUMPRODUCT(AL84:AL86,AL88:AL90) | AM83: =+SUMPRODUCT(AM84:AM86,AM88:AM90) | AN83: =+SUMPRODUCT(AN84:AN86,AN88:AN90)
A84: Yacheng (US$/mmbtu) | V84: 6.5 | W84: =+V84 | X84: =+W84 | Y84: =+X84 | Z84: =+Y84 | AA84: 10 | AB84: 12 | AC84: =+AB84 | AD84: =+AC84*0.85 | AE84: =+AD84 | AF84: =+AE84 | AG84: =+AF84 | AH84: =+AG84 | AI84: =+AH84 | AJ84: =+AI84 | AK84: =+AJ84 | AL84: =+AK84 | ... AN84: =+AM84
A85: South China Sea Gas (US$/mmbtu) | V85: 15 | W85: 15 | X85: 15 | Y85: 13 | Z85: =+Y85 | AA85: =+Z85 | AB85: =+AA85 | AC85: =+AB85 | AD85: =+AC85*0.85 | AE85: =+AD85 | AF85: =+AE85 | AG85: =+AF85 | AH85: =+AG85 | AI85: =+AH85 | AJ85: =+AI85 | AK85: =+AJ85 | AL85: =+AK85 | ... AN85: =+AM85
A86: West-to-East II pipeline (US$/mmbtu) | V86: 19 | W86: 19 | X86: 19 | Y86: =+(Y83-Y84*Y88-Y85*Y89)/Y90 | Z86: =+(Z83-Z84*Z88-Z85*Z89)/Z90 | AA86: =+(AA83-AA84*AA88-AA85*AA89)/AA90 | AB86: =+(AB83-AB84*AB88-AB85*AB89)/AB90 | AC86: 17 | AD86: =+AC86 | AE86: =+AD86 | AF86: =+AE86 | AG86: =+AF86 | AH86: =+AG86 | AI86: =+AH86 | AJ86: =+AI86 | AK86: =+AJ86 | ... AN86: =+AM86
A87: % of gas from
A88: Yacheng | U88: 1 | V88: 0.8 | W88: 0.45 | X88: 0.3 | Y88: 0.15 | Z88: 0.15 | AA88: 0.17 | AB88: 0.15 | AC88: =+AB88 | AD88: =+AC88 | AE88: =+AD88 | AF88: =+AE88 | AG88: =+AF88 | AH88: =+AG88 | AI88: =+AH88 | AJ88: =+AI88 | ... AN88: =+AM88
A89: South China Sea Gas (short term) | U89: 0 | V89: =1-V88 | W89: 0.25 | X89: 0.3 | Y89: 0.15 | Z89: 0.1 | AA89: 0.05 | AB89: 0.1 | AC89: =+AB89 | AD89: =+AC89 | AE89: =+AD89 | AF89: 0.3 | AG89: =+AF89 | AH89: =+AG89 | AI89: =+AH89 | AJ89: =+AI89 | AK89: =+AJ89 | AL89: =+AK89 | AM89: =+AL89 | AN89: =+AM89
A90: West-to-East II pipeline | U90: 0 | V90: 0 | W90: 0.3 | X90: 0.4 | Y90: 0.7 | Z90: =1-Z89-Z88 | AA90: =1-AA89-AA88 | AB90: =1-AB89-AB88 | AC90: =1-AC89-AC88 | AD90: =1-AD89-AD88 | AE90: =1-AE89-AE88 | AF90: =1-AF89-AF88 | AG90: =1-AG89-AG88 | ... AN90: =1-AN89-AN88
A91: Gas consumption (TJ) | S91: 70291 | T91: 82971 | U91: 57639 | V91: 50408 | W91: 45141 | X91: 42433 | Y91: 71406 | Z91: 74559 | AA91: 75807 | AB91: 72969 | AC91: =80648+47 | AD91: 131244 | AE91: 132609 | AF91: 128453 | AG91: 135670 | AH91: 146100 | AI91: =+AI92*AI58 | AJ91: =+AJ92*AJ58 | AK91: =+AK92*AK58 | AL91: =+AL92*AL58 | AM91: =+AM92*AM58 | AN91: =+AN92*AN58
A92: Gas consumption, output based (J/kWh) | S92: =+S91/S58 | T92: =+T91/T58 | U92: =+U91/U58 | V92: =+V91/V58 | W92: =+W91/W58 | X92: =+X91/X58 | Y92: =+Y91/Y58 | Z92: =+Z91/Z58 | ... AH92: =+AH91/AH58 | AI92: =+AH92 | AJ92: =+AI92 | AK92: =+AJ92 | AL92: =+AK92 | AM92: =+AL92 | AN92: =+AM92
A94: Emission (t/fuel consumption, output based)
A95: Black point
A96: SO2 | S96: =+S124*1000/(S$91)*1000 | T96: =+T124*1000/(T$91)*1000 | U96: =+U124*1000/(U$91)*1000 | V96: =+V124*1000/(V$91)*1000 | W96: =+W124*1000/(W$91)*1000 | X96: =+X124*1000/(X$91)*1000 | Y96: =+Y124*1000/(Y$91)*1000 | Z96: =+Z124*1000/(Z$91)*1000 | ... AH96: =+AH124*1000/(AH$91)*1000 | AI96: =+AH96 | AJ96: =+AI96 | AK96: =+AJ96 | AL96: =+AK96 | AM96: =+AL96 | AN96: =+AM96
A97: NOx | S97: =+S125*1000/(S$91) | T97: =+T125*1000/(T$91) | U97: =+U125*1000/(U$91) | V97: =+V125*1000/(V$91) | W97: =+W125*1000/(W$91) | X97: =+X125*1000/(X$91) | Y97: =+Y125*1000/(Y$91) | Z97: =+Z125*1000/(Z$91) | ... AH97: =+AH125*1000/(AH$91) | AI97: =+AH97 | AJ97: =+AI97 | AK97: =+AJ97 | AL97: =+AK97 | AM97: =+AL97 | AN97: =+AM97
A98: Particulate (Respirable) | S98: =+S126*1000/(S$58) | T98: =+T126*1000/(T$58) | U98: =+U126*1000/(U$58) | V98: =+V126*1000/(V$58) | W98: =+W126*1000/(W$58) | X98: =+X126*1000/(X$58) | Y98: =+Y126*1000/(Y$58) | Z98: =+Z126*1000/(Z$58) | ... AH98: =+AH126*1000/(AH$58) | AI98: =+AH98 | AJ98: =+AI98 | AK98: =+AJ98 | AL98: =+AK98 | AM98: =+AL98 | AN98: =+AM98
A99: Castle Peak
A100: SO2 | S100: =+S128/(S$79) | T100: =+T128/(T$79) | U100: =+U128/(U$79) | V100: =+V128/(V$79) | W100: =+W128/(W$79) | X100: =+X128/(X$79) | Y100: =+Y128/(Y$79) | Z100: =+Z128/(Z$79) | ... AH100: =+AH128/(AH$79) | AI100: =+AH100 | AJ100: =+AI100 | AK100: =+AJ100 | AL100: =+AK100 | AM100: =+AL100 | AN100: =+AM100
A101: NOx | S101: =+S129/(S$79) | T101: =+T129/(T$79) | U101: =+U129/(U$79) | V101: =+V129/(V$79) | W101: =+W129/(W$79) | X101: =+X129/(X$79) | Y101: =+Y129/(Y$79) | Z101: =+Z129/(Z$79) | ... AH101: =+AH129/(AH$79) | AI101: =+AH101 | AJ101: =+AI101 | AK101: =+AJ101 | AL101: =+AK101 | AM101: =+AL101 | AN101: =+AM101
A102: Particulate (Respirable) | S102: =+S130/(S$79) | T102: =+T130/(T$79) | U102: =+U130/(U$79) | V102: =+V130/(V$79) | W102: =+W130/(W$79) | X102: =+X130/(X$79) | Y102: =+Y130/(Y$79) | Z102: =+Z130/(Z$79) | ... AH102: =+AH130/(AH$79) | AI102: =+AH102 | AJ102: =+AI102 | AK102: =+AJ102 | AL102: =+AK102 | AM102: =+AL102 | AN102: =+AM102
A104: Higher or (lower) than government (kT)
A105: Overall
A106: SO2 | Y106: =+IF(Y120-Y134<0, "OK", "FAIL") | AA106: =+IF(AA120-AA134<0, "OK", "FAIL") | AC106: =+IF(AC120-AC134<0, "OK", "FAIL")
A107: NOx | Y107: =+IF(Y121-Y135<0, "OK", "FAIL") | AA107: =+IF(AA121-AA135<0, "OK", "FAIL") | AC107: =+IF(AC121-AC135<0, "OK", "FAIL")
A108: Particulate (Respirable) | Y108: =+IF(Y122-Y136<0, "OK", "FAIL") | AA108: =+IF(AA122-AA136<0, "OK", "FAIL") | AC108: =+IF(AC122-AC136<0, "OK", "FAIL")
A109: Black point
A110: SO2 | Y110: =+IF(Y124-Y138<0, "OK", "FAIL") | AA110: =+IF(AA124-AA138<0, "OK", "FAIL") | AC110: =+IF(AC124-AC138<0, "OK", "FAIL")
A111: NOx | Y111: =+IF(Y125-Y139<0, "OK", "FAIL") | AA111: =+IF(AA125-AA139<0, "OK", "FAIL") | AC111: =+IF(AC125-AC139<0, "OK", "FAIL")
A112: Particulate (Respirable) | Y112: =+IF(Y126-Y140<0, "OK", "FAIL") | AA112: =+IF(AA126-AA140<0, "OK", "FAIL") | AC112: =+IF(AC126-AC140<0, "OK", "FAIL")
A113: Castle Peak
A114: SO2 | Y114: =+IF(Y128-Y142<0, "OK", "FAIL") | AA114: =+IF(AA128-AA142<0, "OK", "FAIL") | AC114: =+IF(AC128-AC142<0, "OK", "FAIL")
A115: NOx | Y115: =+IF(Y129-Y143<0, "OK", "FAIL") | AA115: =+IF(AA129-AA143<0, "OK", "FAIL") | AC115: =+IF(AC129-AC143<0, "OK", "FAIL")
...

Sheet ROAFNA
A1: SoC Permitted Return
B2: 1992 | C2: 1993 | D2: 1994 | E2: 1995 | F2: 1996 | G2: =Final!G2 | H2: =Final!H2 | I2: =Final!I2 | J2: =Final!J2 | K2: =Final!K2 | L2: =Final!L2 | M2: =Final!M2 | N2: =Final!N2 | ... AN2: =Final!AN2
A3: Closing net fixed assets | B3: =B18 | C3: =C18 | D3: =D18 | E3: =E18 | F3: =F18 | G3: =G18 | H3: =H18 | I3: =I18 | ... AN3: =AN18
A4: Average net fixed assets | B4: =(B3+31829)/2 | C4: =(C3+B3)/2 | D4: =(D3+C3)/2 | E4: =(E3+D3)/2 | F4: =(F3+E3)/2 | G4: =(G3+F3)/2 | H4: =(H3+G3)/2 | I4: =(I3+H3)/2 | J4: =(J3+I3)/2 | ... AN4: =(AN3+AM3)/2
A5: %+/- | D5: =D4/C4-1 | E5: =E4/D4-1 | F5: =F4/E4-1 | G5: =G4/F4-1 | H5: =H4/G4-1 | I5: =I4/H4-1 | J5: =J4/I4-1 | K5: =K4/J4-1 | ... AN5: =AN4/AM4-1
A6: Allowed return | C6: 0.135 | D6: =C6 | E6: =D6 | F6: =E6 | G6: =F6 | H6: =G6 | I6: =H6 | J6: =I6 | K6: =J6 | ... Q6: =P6 | R6: =Q6*0.75+9.99%*0.25 | S6: 0.0999 | T6: =S6 | U6: =T6 | V6: =+V7/AVERAGE(U3,V3) | W6: =V6 | X6: =W6 | Y6: =X6 | Z6: =Y6 | AA6: =Z6 | AB6: =10565/AB4 | AC6: 0.08 | AD6: =AC6 | AE6: =AD6 | AF6: =AE6 | AG6: =AF6 | AH6: =AG6 | AI6: =AH6 | AJ6: =AI6 | AK6: =AJ6 | ... AN6: =AM6 | AR6: 2025 | AS6: 2026 | AT6: 2027 | AU6: 2028 | AV6: 2029 | AW6: 2030
A7: Return on ANFA | C7: =C6*C4 | D7: =D6*D4 | E7: =E6*E4 | F7: =F6*F4 | G7: =G6*G4 | H7: =H6*H4 | I7: =I6*I4*5/4 | J7: =J6*J4 | K7: =K6*K4 | L7: =L6*L4 | M7: =M6*M4 | N7: =N6*N4 | O7: =O6*O4 | P7: =P6*P4 | Q7: =Q6*Q4 | ... U7: =U6*U4 | V7: 9313 | W7: =W6*W4 | X7: =X6*X4 | Y7: =Y6*Y4 | Z7: =Z6*Z4 | AA7: =AA6*AA4 | AB7: =AB6*AB4 | AC7: =AC6*AC4 | AD7: =AD6*AD4 | ... AN7: =AN6*AN4 | AR7: =Final!AI31 | AS7: =Final!AJ31 | AT7: =Final!AK31 | AU7: =Final!AL31 | AV7: =Final!AM31 | AW7: =Final!AN31
AR8: 14491.093 | AS8: 14684.33 | AT8: 14871.342 | AU8: 15052.59 | AV8: 15228.538 | AW8: 15399.657
A9: Shareholder investments post 79 | C9: =C12/C11 | D9: =D12/D11 | E9: =E12/E11 | F9: =F12/F11 | G9: =G12/G11 | H9: =H12/H11 | I9: =(I12*4/5)/I11 | J9: =J12/J11 | K9: =K12/K11 | L9: =L12/L11 | M9: =M12/M11 | N9: =N12/N11 | O9: =O12/O11 | P9: =P12/P11 | Q9: =Q12/Q11 | R9: =R12/R11
A10: Growth in post-79 shareholder invest | D10: =D9/C9-1 | E10: =E9/D9-1 | F10: =F9/E9-1 | G10: =G9/F9-1 | H10: =H9/G9-1 | I10: =I9/H9-1 | J10: =J9/I9-1 | K10: =K9/J9-1 | ... R10: =R9/Q9-1
A11: Allowed return | C11: 0.015 | D11: =C11 | E11: =D11 | F11: =E11 | G11: =F11 | H11: =G11 | I11: =H11 | J11: =I11 | K11: =J11 | ... Q11: =P11 | R11: =Q11*9/12
C12: =C14-C7 | D12: =D14-D7 | E12: =E14-E7 | F12: =F14-F7 | G12: =G14-G7 | H12: =H14-H7 | I12: =I14-I7 | J12: =J14-J7 | ... R12: =R14-R7
A14: Permitted return for the year | B14: 4745 | C14: 5203 | D14: 5878 | E14: 6727 | F14: 7542 | G14: 8034.501 | H14: 8252.7179 | I14: =8323+2085 | J14: 8384 | K14: 8580 | L14: 8887 | M14: 9317 | N14: 9847 | O14: 10223 | P14: 10452 | Q14: 10720 | R14: =8317+1968 | S14: 8155 | T14: 8568 | U14: 8936 | V14: 9313 | W14: 9638 | X14: 9958 | Y14: 10286 | Z14: 10558 | AA14: 10825 | AB14: =2253+8312 | AC14: 9218 | AD14: 9507 | AE14: 9854 | AF14: 10345 | AG14: 10858 | AH14: 11271 | AI14: =AI7 | AJ14: =AJ7 | AK14: =AK7 | AL14: =AL7 | AM14: =AM7 | AN14: =AN7 | AR14: =AR7/AR8-1 | AS14: =AS7/AS8-1 | AT14: =AT7/AT8-1 | AU14: =AU7/AU8-1 | AV14: =AV7/AV8-1 | AW14: =AW7/AW8-1
A15: Growth in Permitted Return | C15: =C14/B14-1 | D15: =D14/C14-1 | E15: =E14/D14-1 | F15: =F14/E14-1 | G15: =G14/F14-1 | H15: =H14/G14-1 | I15: =I14*4/5/H14-1 | J15: =J14/(I14*4/5)-1 | K15: =K14/J14-1 | L15: =L14/K14-1 | M15: =M14/L14-1 | N15: =N14/M14-1 | O15: =O14/N14-1 | P15: =P14/O14-1 | Q15: =Q14/P14-1 | R15: =R14/Q14-1 | ... AN15: =AN14/AM14-1
A17: Balance Sheet
A18: Net fixed assets | B18: 33622 | C18: 37916 | D18: 43131 | E18: 49875 | F18: 54945 | G18: 57221 | H18: 57721 | I18: 57976 | J18: 58709 | K18: 60636 | L18: 63115 | M18: 66711 | N18: 69882 | O18: 71890 | P18: 73156 | Q18: 75239 | R18: 79445 | S18: 83811 | T18: 87713 | U18: 91187 | V18: 95243 | W18: 97918 | X18: 101420 | Y18: 104479 | Z18: 106886 | AA18: 109824 | AB18: 113295 | AC18: 117157 | AD18: 120523 | AE18: 125827 | AF18: 132792 | AG18: 138657 | AH18: 143124 | AI18: =AH18+AI53+AI49 | AJ18: =AI18+AJ53+AJ49 | AK18: =AJ18+AK53+AK49 | AL18: =AK18+AL53+AL49 | AM18: =AL18+AM53+AM49 | AN18: =AM18+AN53+AN49 | AR18: =DCF!$S$37
A19: Other assets | B19: 1801 | C19: 1840 | D19: 1417 | E19: 1610 | F19: 2095 | G19: 3131 | H19: 3822 | I19: 2441 | J19: 1705 | K19: 1636 | L19: 1650 | M19: =1650+298 | N19: =2382+298 | O19: =3040+808 | P19: =3402+934 | Q19: =3504+533 | R19: =3612+1552 | S19: =3929+774 | T19: =4367+1698 | U19: =4913+2310 | V19: =1904+11530 | W19: =1091+6778 | X19: =6770+684 | Y19: =382+5327 | Z19: =440+4061 | AA19: =268+7606 | AB19: =198+6559 | AC19: =213+4231 | AD19: =351+6350 | AE19: =134+8359 | AF19: =74+9681 | AG19: =16+5706 | AH19: =4223+36 | AI19: =AH19 | AJ19: =AI19 | AK19: =AJ19 | AL19: =AK19 | AM19: =AL19 | AN19: =AM19
A20: Total assets | B20: =SUM(B18:B19) | C20: =SUM(C18:C19) | D20: =SUM(D18:D19) | E20: =SUM(E18:E19) | F20: =SUM(F18:F19) | G20: =SUM(G18:G19) | H20: =SUM(H18:H19) | I20: =SUM(I18:I19) | ... AN20: =SUM(AN18:AN19)
A22: Current liabilities | B22: 6567 | C22: 7153 | D22: 8991 | E22: 8558 | F22: 9022 | G22: 10415 | H22: 9304 | I22: 7017 | J22: 7978 | K22: 9306 | L22: 10992 | M22: 9557 | N22: 9740 | O22: 12723 | P22: 10257 | Q22: 14429 | R22: 14394 | S22: 17658 | T22: 15194 | U22: 17439 | V22: 22248 | W22: 17142 | X22: 18518 | Y22: 18565 | Z22: 21474 | AA22: 22565 | AB22: 24699 | AC22: 28115 | AD22: 23046 | AE22: 25311 | AF22: 27881 | AG22: 32472 | AH22: 28641 | AI22: =AH22 | AJ22: =AI22 | AK22: =AJ22 | AL22: =AK22 | AM22: =AL22 | AN22: =AM22
A23: Exchange fluctuation | B23: -445 | C23: 15 | D23: 12 | E23: 6 | F23: 6 | G23: -6 | H23: -31 | I23: -88 | J23: -128 | K23: -49 | L23: -38 | M23: 46 | N23: 34 | O23: 63 | P23: -5 | Q23: -51 | R23: 165 | S23: 346 | T23: 962 | U23: 1428 | V23: 907 | W23: 939 | X23: 565 | Y23: -113 | Z23: 279 | AA23: 21 | AB23: -81 | AC23: -9 | AD23: -555 | AE23: -606 | AF23: -465 | AG23: -1183 | AH23: -647 | AI23: =AH23 | AJ23: =AI23 | AK23: =AJ23 | AL23: =AK23 | AM23: =AL23 | AN23: =AM23
A24: Long term borrowing | B24: 5845 | C24: 6925 | D24: 7877 | E24: 13113 | F24: 17797 | G24: 17825 | H24: 17871 | I24: 16654 | J24: 15092 | K24: 14437 | L24: 13916 | M24: 13893 | N24: 15084 | O24: 13720 | P24: 16161 | Q24: 13828 | R24: 16616 | S24: 21598 | T24: 25248 | U24: 25283 | V24: 28254 | W24: 26873 | X24: 28340 | Y24: 30730 | Z24: 28885 | AA24: 34251 | AB24: 32274 | AC24: 29792 | AD24: 37146 | AE24: 38328 | AF24: 40680 | AG24: 35967 | AH24: 40860 | AI24: =AH24+1000 | AJ24: =AI24+1000 | AK24: =AJ24+1000 | AL24: =AK24 | AM24: =AL24 | AN24: =AM24
A25: Deferred liabilities | B25: 3328 | C25: 3598 | D25: 4929 | E25: 5868 | F25: 5945 | G25: 6360 | H25: 6424 | I25: 6222 | J25: 6268 | K25: 6561 | L25: 6947 | M25: 8459 | N25: 8844 | O25: 8978 | P25: 9305 | Q25: 8549 | R25: 9312 | S25: 10062 | T25: 10909 | U25: 11778 | V25: 13486 | W25: 15747 | X25: 17937 | Y25: 17764 | Z25: 17816 | AA25: 15379 | AB25: 15650 | AC25: 16020 | AD25: 17761 | AE25: 18244 | AF25: 18995 | AG25: 20230 | AH25: 20709 | AI25: =AH25/AH22*AI22 | AJ25: =AI25/AI22*AJ22 | AK25: =AJ25/AJ22*AK22 | AL25: =AK25/AK22*AL22 | AM25: =AL25/AL22*AM22 | AN25: =AM25/AM22*AN22
A26: Special provision account | B26: ='SOC Accounts'!B27 | C26: ='SOC Accounts'!C27 | D26: ='SOC Accounts'!D27 | E26: ='SOC Accounts'!E27 | F26: ='SOC Accounts'!F27 | G26: ='SOC Accounts'!G27 | H26: ='SOC Accounts'!H27 | I26: ='SOC Accounts'!I27 | ... AN26: ='SOC Accounts'!AN27
A27: Development fund | B27: 3222 | C27: 3847 | D27: 2944 | E27: 2419 | F27: ='SOC Accounts'!F21 | G27: ='SOC Accounts'!G21 | H27: ='SOC Accounts'!H21 | I27: ='SOC Accounts'!I21 | J27: ='SOC Accounts'!J21 | K27: ='SOC Accounts'!K21 | L27: ='SOC Accounts'!L21 | M27: ='SOC Accounts'!M21 | ... AN27: ='SOC Accounts'!AN21
A29: Capital | B29: 16906 | C29: 18218 | D29: 19795 | E29: 21521 | F29: 22344 | G29: 24326 | H29: 25447 | I29: 27292 | J29: 27515 | K29: 28074 | L29: 28906 | M29: 33568 | N29: 35689 | O29: 36569 | P29: 38842 | Q29: 40404 | R29: 42366 | S29: 37197 | T29: 39960 | U29: 41845 | V29: 43070 | W29: 45067 | X29: 42456 | Y29: 42307 | Z29: 42147 | AA29: 44736 | AB29: 46569 | AC29: 46205 | AD29: 47807 | AE29: 49934 | AF29: 52528 | AG29: 54364 | AH29: 56036 | AI29: =AI20-SUM(AI22:AI27) | AJ29: =AJ20-SUM(AJ22:AJ27) | AK29: =AK20-SUM(AK22:AK27) | AL29: =AL20-SUM(AL22:AL27) | AM29: =AM20-SUM(AM22:AM27) | AN29: =AN20-SUM(AN22:AN27)
A30: Equity + Liability | B30: =SUM(B22:B29) | C30: =SUM(C22:C29) | D30: =SUM(D22:D29) | E30: =SUM(E22:E29) | F30: =SUM(F22:F29) | G30: =SUM(G22:G29) | H30: =SUM(H22:H29) | I30: =SUM(I22:I29) | ... AN30: =SUM(AN22:AN29)
B31: =B20-B30 | C31: =C20-C30 | D31: =D20-D30 | E31: =E20-E30 | F31: =F20-F30 | G31: =G20-G30 | H31: =H20-H30 | I31: =I20-I30 | ... AN31: =AN20-AN30
A32: Key drivers - Borrowing
A33: Borrowing - CLP Power HK | B33: 1255 | C33: 1057 | D33: 1497 | E33: 1670 | F33: 3319 | G33: 3903 | H33: 2744 | I33: 2778 | J33: 2433 | K33: 4240 | L33: 6742 | M33: 7451 | N33: 8642 | O33: 11475 | P33: 13053 | Q33: 13613 | R33: 14848 | S33: 22429 | T33: 25603 | U33: 27391 | V33: 33435 | W33: 28283 | X33: 34780 | Y33: 35002 | Z33: =Z35-Z34 | AA33: =AA35-AA34 | AB33: =AB35-AB34 | AC33: =AC35-AC34 | AD33: =AD35-AD34 | AE33: =AE35-AE34 | AF33: =AF35-AF34 | AG33: =AG35-AG34 | ... AN33: =AN35-AN34
A34: Borrowing - CAPCO | K34: 13864 | L34: 11832 | M34: 9770 | N34: 9585 | O34: 8072 | P34: 6343 | Q34: 7035 | R34: 7767 | S34: =8329-200 | T34: =5947-200 | U34: =5622-200 | V34: =6486-200 | W34: =6119-200 | X34: 5855 | Y34: 5974 | Z34: =Y34 | AA34: =Z34+500*7.8 | AB34: =AA34 | AC34: =AB34 | AD34: =AC34 | AE34: =AD34 | AF34: =AE34 | AG34: =AF34 | AH34: =AG34 | AI34: =AH34 | ... AN34: =AM34
A35: CLP's HK Segment | B35: =B33 | C35: =C33 | D35: =D33 | E35: =E33 | F35: =F33 | G35: =G33 | H35: =H33 | I35: =I33 | ... W35: =W33 | X35: =+X33+X34 | Y35: =+Y33+Y34 | Z35: 37814 | AA35: 40361 | AB35: 38636 | AC35: 41171 | AD35: 43257 | AE35: 46351 | AF35: 48559 | AG35: 47835 | AH35: 56024 | AI35: =AI24-AH24+AH35 | AJ35: =AJ24-AI24+AI35 | AK35: =AK24-AJ24+AJ35 | AL35: =AL24-AK24+AK35 | AM35: =AM24-AL24+AL35 | AN35: =AN24-AM24+AM35
A36: Net finance costs - CLP HK segment | B36: -67 | C36: -48 | D36: -16 | E36: -48 | F36: -50 | G36: 565 | H36: 973 | I36: 612 | J36: -94 | K36: -158 | L36: -156 | M36: -640.22069 | N36: -983 | O36: -1489 | P36: =-4624-P37 | Q36: =-4881-Q37-Driver!Q110-Driver!Q111 | R36: =-3409+15-R37 | S36: =-2673+11-S37 | T36: =-3115+1-T37 | U36: =-3508+2-U37 | V36: =-3565+8-V37 | W36: =-3685+11-W37 | X36: =-1954+9-X37 | Y36: =-1110+2 | Z36: -1020 | AA36: -1049 | AB36: -1011 | AC36: =-1014+1 | AD36: =-1012+16 | AE36: =-907+39 | AF36: =-973+136 | AG36: =-1428+159 | AH36: =-1579+119 | AI36: =-AI38*AH35 | AJ36: =-AJ38*AI35 | AK36: =-AK38*AJ35 | AL36: =-AL38*AK35 | AM36: =-AM38*AL35 | AN36: =-AN38*AM35
A37: Finance lease charge | C37: 0 | D37: 0 | E37: 0 | F37: 0 | G37: 0 | H37: 0 | I37: 0 | J37: 0 | K37: 0 | L37: 0 | M37: 0 | N37: 0 | O37: 0 | P37: -3020 | Q37: -3422 | R37: -2930 | S37: -2190 | T37: -2471 | U37: -2735 | V37: -2735 | W37: -2753 | X37: -922 | Y37: 0 | Z37: 0 | AA37: 0 | AB37: 0 | AC37: 0 | AD37: 0 | AE37: 0 | AF37: 0 | AG37: 0 | AH37: 0 | AI37: 0 | AJ37: 0 | AK37: 0 | AL37: 0 | AM37: 0 | AN37: 0
A38: Interest expense rate | R38: =-R36/AVERAGE(Q35:R35) | S38: =-S36/AVERAGE(R35:S35) | T38: =-T36/AVERAGE(S35:T35) | U38: =-U36/AVERAGE(T35:U35) | V38: =-V36/AVERAGE(U35:V35) | W38: =-W36/AVERAGE(V35:W35) | X38: =-X36/AVERAGE(W35:X35) | Y38: =-Y36/AVERAGE(X35:Y35) | ... AH38: =-AH36/AVERAGE(AG35:AH35) | AI38: =AH38-0.2% | AJ38: =AI38-0.2% | AK38: =AJ38 | AL38: =AK38 | AM38: =AL38 | AN38: =AM38
A39: Check with SoC interest expense | R39: =R36-R41 | S39: =S36-S41 | T39: =T36-T41 | U39: =U36-U41 | V39: =V36-V41 | W39: =W36-W41 | X39: =X36-X41 | Y39: =Y36-Y41 | ... AN39: =AN36-AN41
A41: Net finance costs - SoC | B41: =-SOC!B17 | C41: =-SOC!C17 | D41: =-SOC!D17 | E41: =-SOC!E17 | F41: =-SOC!F17 | G41: =-SOC!G17 | H41: =-SOC!H17 | I41: =-SOC!I17 | ... AH41: =-SOC!AH17 | AI41: =AVERAGE(AH24:AI24)*AI42 | AJ41: =AVERAGE(AI24:AJ24)*AJ42 | AK41: =AVERAGE(AJ24:AK24)*AK42 | AL41: =AVERAGE(AK24:AL24)*AL42 | AM41: =AVERAGE(AL24:AM24)*AM42 | AN41: =AVERAGE(AM24:AN24)*AN42
A42: Interest rate (%) | C42: =C41/AVERAGE(B24:C24) | D42: =D41/AVERAGE(C24:D24) | E42: =E41/AVERAGE(D24:E24) | F42: =F41/AVERAGE(E24:F24) | G42: =G41/AVERAGE(F24:G24) | H42: =H41/AVERAGE(G24:H24) | I42: =I41/AVERAGE(H24:I24) | J42: =J41/AVERAGE(I24:J24) | ... AH42: =AH41/AVERAGE(AG24:AH24) | AI42: =(2.5%+0.75%)*-1 | AJ42: =-(1.9%+0.75%) | AK42: =AJ42 | AL42: =AK42 | AM42: =AL42 | AN42: =AM42
A44: Fixed Assets and CAPEX
A45: Fixed Assets
A46: Net fixed assets - CLP | B46: 17184 | C46: 18960 | D46: 21028 | E46: 23407 | F46: 25375 | G46: 26720 | H46: 27268 | I46: 28624 | J46: 30347 | K46: 33197 | L46: 36273 | M46: 39258 | N46: 42415 | O46: 45099 | P46: 47516 | Q46: 49684 | R46: 52132 | S46: 54712 | T46: 57247 | U46: 60142 | V46: 63599 | W46: 67057 | X46: 101420 | Y46: 104479 | Z46: 106886 | AA46: =AA18 | AB46: =AB18 | AC46: =AC18 | AD46: =AD18 | AE46: =AE18 | AF46: =AF18 | AG46: =AG18 | AH46: =AH18 | ... AN46: =AN18
A47: Net fixed assets - CAPCO | B47: =B18-B46 | C47: =C18-C46 | D47: =D18-D46 | E47: =E18-E46 | F47: =F18-F46 | G47: =G18-G46 | H47: =H18-H46 | I47: =I18-I46 | ... W47: =W18-W46 | X47: =W47/W18*X18 | Y47: =X47/X18*Y18 | Z47: =Y47/Y18*Z18 | AA47: =Z47/Z18*AA18 | AB47: =AA47/AA18*AB18 | AC47: =AB47/AB18*AC18 | AD47: =AC47/AC18*AD18 | AE47: =AD47/AD18*AE18 | ... AN47: =AM47/AM18*AN18
A48: CLP's share (%) | B48: =B46/B18 | C48: =C46/C18 | D48: =D46/D18 | E48: =E46/E18 | F48: =F46/F18 | G48: =G46/G18 | H48: =H46/H18 | I48: =I46/I18 | ... AN48: =AN46/AN18
A49: Total Depreciation | B49: =SOC!B10 | C49: =SOC!C10 | D49: =SOC!D10 | E49: =SOC!E10 | F49: =SOC!F10 | G49: =SOC!G10 | H49: =SOC!H10 | I49: =SOC!I10 | ... AH49: =SOC!AH10 | AI49: =-AH18*AI50 | AJ49: =-AI18*AJ50 | AK49: =-AJ18*AK50 | AL49: =-AK18*AL50 | AM49: =-AL18*AM50 | AN49: =-AM18*AN50
A50: Depreciation rate (%) | C50: =-C49/AVERAGE(B18:C18) | D50: =-D49/AVERAGE(C18:D18) | E50: =-E49/AVERAGE(D18:E18) | F50: =-F49/AVERAGE(E18:F18) | G50: =-G49/AVERAGE(F18:G18) | H50: =-H49/AVERAGE(G18:H18) | I50: =-I49/AVERAGE(H18:I18) | J50: =-J49/AVERAGE(I18:J18) | ... AH50: =-AH49/AVERAGE(AG18:AH18) | AI50: =AH50 | AJ50: =AI50 | AK50: =AJ50 | AL50: =AK50 | AM50: =AL50 | AN50: =AM50
A52: CAPEX
A53: Total SoC capex | B53: 3833 | C53: 6346 | D53: 6831 | E53: 8664 | F53: 7129 | G53: 4857 | H53: 3090 | I53: 3720 | J53: 3671 | K53: 5172 | L53: 5861 | M53: 7273 | N53: 6961 | O53: 6005 | P53: 5673 | Q53: 6123 | R53: 7665 | S53: 7798 | T53: 7748 | U53: 7774 | V53: 8621 | W53: 7479 | X53: 7800 | Y53: 7630 | Z53: 7292 | AA53: 8068 | AB53: 8922 | AC53: 9097 | AD53: 8882 | AE53: 11222 | AF53: 12573 | AG53: 11670 | AH53: 10818 | AI53: =AI57 | AJ53: =AJ57 | AK53: =AK57 | AL53: =AL57 | AM53: =AM57 | AN53: =AN57
A54: CAPEX - CLP Power HK | B54: 2982 | C54: 2785 | D54: 2943 | E54: 3396 | F54: 3037 | G54: 2618 | H54: 1921 | I54: 3148 | J54: 3402 | K54: 4653 | L54: 4923 | M54: 5125 | N54: 5278 | O54: 4849 | P54: 4788 | Q54: 4745 | R54: 4379 | S54: 4447 | T54: 4552 | U54: 4903 | V54: 5650 | W54: 5680 | X54: 5615 | Y54: 5152 | Z54: 4996 | AA54: 4523 | AB54: 4411 | AC54: 4584 | AD54: 4528 | AE54: 4869 | AF54: 6007 | AG54: 6759 | AH54: 8010 | AI54: =+AI57/$U$94*$U$91 | AJ54: =+AJ57/$U$94*$U$91 | AK54: =+AK57/$U$94*$U$91 | AL54: =+AL57/$U$94*$U$91 | AM54: =AL54-AL55+AM55 | AN54: =AM54-AM55+AN55
A55: CCGT new build | AA55: =3575/21*12 | AB55: =3575/21*9+(5547-3575)/15*3 | AC55: =5547-AA55-AB55+800 | AD55: 1000 | AE55: 1000 | AF55: =AE55 | AG55: =AF55 | AH55: =AG55
A56: CAPEX - CAPCO | B56: =B53-B54 | C56: =C53-C54 | D56: =D53-D54 | E56: =E53-E54 | F56: =F53-F54 | G56: =G53-G54 | H56: =H53-H54 | I56: =I53-I54 | ... Z56: =Z53-Z54 | AA56: 3545 | AB56: 4511 | AC56: 4513 | AD56: 4354 | AE56: 6353 | AF56: 6566 | AG56: 4911 | AH56: 2808 | AI56: =+AI57-AI54 | AJ56: =+AJ57-AJ54 | AK56: =+AK57-AK54 | AL56: =+AL57-AL54 | AM56: =AL56 | AN56: =AM56
A57: CLP consolidated CAPEX | B57: =B54 | C57: =C54 | D57: =D54 | E57: =E54 | F57: =F54 | G57: =G54 | H57: =H54 | I57: =I54 | ... W57: =W54 | X57: =X54+X56 | Y57: =Y54+Y56 | Z57: =Z54+Z56 | AA57: =AA54+AA56 | AB57: =AB54+AB56 | AC57: =AC54+AC56 | AD57: =AD54+AD56 | AE57: =AE54+AE56 | ... AH57: =AH54+AH56 | AI57: =+AI59-AI58 | AJ57: =+AJ59-AJ58 | AK57: =+AK59-AK58 | AL57: =+AL59-AL58 | AM57: =+AM59-AM58 | AN57: =+AN59-AN58
A58: Addition to leased assets | P58: =277+3029 | Q58: =70+535 | R58: =73+1045 | S58: =110+1494 | T58: =1774+5259 | U58: =176+153+2364 | V58: =246+1748 | W58: =363+3139 | X58: 0 | Y58: 0 | Z58: 0 | AA58: 0 | AB58: 0 | AC58: 0 | AD58: 0 | AE58: 0 | AF58: 0 | AG58: 0 | AH58: 0 | AI58: 0 | AJ58: 0 | AK58: 0 | AL58: 0 | AM58: 0 | AN58: 0
A59: CLP capex - HK Segment | B59: =B57+B58 | C59: =C57+C58 | D59: =D57+D58 | E59: =E57+E58 | F59: =F57+F58 | G59: =G57+G58 | H59: =H57+H58 | I59: =I57+I58 | ... AH59: =AH57+AH58 | AI59: =+$V$94/5 | AJ59: =+$V$94/5 | AK59: =+$V$94/5 | AL59: =+V94-SUM(AH59:AK59) | AM59: =+$V$94/5 | AN59: =+$V$94/5
A61: Capacity
A63: Attributable installed capacity available to HK | B63: 6432 | C63: 6430 | D63: 7540 | E63: 6890 | F63: 7515 | G63: 7638 | H63: 7950.5 | I63: 8263 | J63: 8263 | K63: 8263 | L63: 8263 | M63: 8263 | N63: 8263 | O63: 8575.5 | P63: 8888 | Q63: 8888 | R63: 8888 | S63: 8888 | T63: 8888 | U63: 8888 | V63: 8888 | W63: 8888 | X63: 8888 | Y63: 8888 | Z63: 8913 | AA63: 8913 | AB63: =SUM(AB64:AB68) | AC63: =SUM(AC64:AC68) | AD63: =SUM(AD64:AD68) | AE63: =SUM(AE64:AE68) | AF63: =SUM(AF64:AF68) | AG63: =SUM(AG64:AG68) | AH63: =AG63+AH70 | AI63: =AH63+AI70 | AJ63: =AI63+AJ70 | AK63: =AJ63+AK70 | AL63: =AK63+AL70 | AM63: =AL63+AM70 | AN63: =AM63+AN70
A64: Coal-fired (CAPCO) | P64: =+Q64 | Q64: =+R64 | R64: =+S64 | S64: =+T64 | T64: 4108 | U64: 4108 | V64: 4108 | W64: 4108 | X64: 4108 | Y64: 4108 | Z64: 4108 | AA64: 4108 | AB64: 4108 | AC64: =+AB64+AC71 | AD64: =+AC64+AD71 | AE64: =+AD64+AE71 | AF64: =+AE64+AF71 | AG64: =+AF64+AG71 | AH64: =+AG64+AH71 | AI64: =+AH64+AI71 | AJ64: =+AI64+AJ71 | ... AN64: =+AM64+AN71
A65: Gas-fired (Black Point) | P65: =+Q65 | Q65: =+R65 | R65: =+S65 | S65: =+T65 | T65: 2500 | U65: 2500 | V65: 2500 | W65: 2500 | X65: 2500 | Y65: 2500 | Z65: 2525 | AA65: 2525 | AB65: 2575 | AC65: 2600 | AD65: 3175 | AE65: 3225 | AF65: 3250 | AG65: 3250 | AH65: =+AG65+AH72 | AI65: =+AH65+AI72 | AJ65: =+AI65+AJ72 | AK65: =+AJ65+AK72 | AL65: =+AK65+AL72 | AM65: =+AL65+AM72 | AN65: =+AM65+AN72
A66: Oil (Penny Bay) | P66: =+Q66 | Q66: =+R66 | R66: =+S66 | S66: =+T66 | T66: 300 | U66: 300 | V66: 300 | W66: 300 | X66: 300 | Y66: 300 | Z66: 300 | AA66: 300 | AB66: 300 | AC66: 300 | AD66: 300 | AE66: 300 | AF66: =+AE66+AF73 | AG66: =+AF66+AG73 | AH66: =+AG66+AH73 | AI66: =+AH66+AI73 | AJ66: =+AI66+AJ73 | AK66: =+AJ66+AK73 | AL66: =+AK66+AL73 | AM66: =+AL66+AM73 | AN66: =+AM66+AN73
A67: Nuclear (Daya Bay) | P67: =CN!P70 | Q67: =CN!Q70 | R67: =CN!R70 | S67: =CN!S70 | T67: =CN!T70 | U67: =CN!U70 | V67: =CN!V70 | W67: =CN!W70 | ... Z67: =CN!Z70 | AA67: 1380 | AB67: 1577 | AC67: =CN!AC70 | AD67: =CN!AD70 | AE67: =CN!AE70 | AF67: =CN!AF70 | AG67: =CN!AG70 | AH67: =CN!AH70 | AI67: =CN!AI70 | AJ67: =CN!AJ70 | ... AN67: =CN!AN70
A68: Pumped storage | P68: =+Q68 | Q68: =+R68 | R68: =+S68 | S68: =+T68 | T68: 600 | U68: 600 | V68: 600 | W68: 600 | X68: 600 | Y68: 600 | Z68: 600 | AA68: 600 | AB68: 600 | AC68: =+AB68+AC75 | AD68: =+AC68+AD75 | AE68: =+AD68+AE75 | AF68: =+AE68+AF75 | AG68: =+AF68+AG75 | AH68: =+AG68+AH75 | AI68: =+AH68+AI75 | AJ68: =+AI68+AJ75 | ... AN68: =+AM68+AN75
A70: Net capacity additions | C70: =C63-B63 | D70: =D63-C63 | E70: =E63-D63 | F70: =F63-E63 | G70: =G63-F63 | H70: =H63-G63 | I70: =I63-H63 | J70: =J63-I63 | ... AG70: =AG63-AF63 | AH70: =+SUM(AH71:AH75) | AI70: =+SUM(AI71:AI75) | AJ70: =+SUM(AJ71:AJ75) | AK70: =+SUM(AK71:AK75) | AL70: =+SUM(AL71:AL75) | AM70: =+SUM(AM71:AM75) | AN70: =+SUM(AN71:AN75)
A71: Coal-fired (CAPCO) | Q71: =+Q64-P64 | R71: =+R64-Q64 | S71: =+S64-R64 | T71: =T64-S64 | U71: =U64-T64 | V71: =V64-U64 | W71: =W64-V64 | X71: =X64-W64 | Y71: =Y64-X64 | Z71: =Z64-Y64 | AA71: =AA64-Z64 | AB71: =AB64-AA64 | AC71: =+AB71 | AD71: =+AC71 | AE71: =+AD71 | AF71: =+AE71 | AG71: =+AF71 | AH71: -1050 | AI71: 0 | AJ71: =+AI71 | AK71: =+AJ71 | AL71: =+AK71 | AM71: =+AL71 | AN71: =+AM71
A72: Gas-fired (Black Point) | Q72: =+Q65-P65 | R72: =+R65-Q65 | S72: =+S65-R65 | T72: =T65-S65 | U72: =U65-T65 | V72: =V65-U65 | W72: =W65-V65 | X72: =X65-W65 | Y72: =Y65-X65 | Z72: =Z65-Y65 | AA72: =AA65-Z65 | ... AG72: =AG65-AF65 | AH72: 0 | AI72: 0 | AJ72: 0 | AK72: 0 | AL72: 550 | AM72: 0 | AN72: 0
A73: Oil (Penny Bay) | Q73: =+Q66-P66 | R73: =+R66-Q66 | S73: =+S66-R66 | T73: =T66-S66 | U73: =U66-T66 | V73: =V66-U66 | W73: =W66-V66 | X73: =X66-W66 | Y73: =Y66-X66 | Z73: =Z66-Y66 | AA73: =AA66-Z66 | AB73: =AB66-AA66 | AC73: =+AB73 | AD73: =+AC73 | AE73: =+AD73 | AF73: =+AE73 | AG73: =+AF73 | AH73: =+AG73 | AI73: =+AH73 | AJ73: =+AI73 | ... AN73: =+AM73
A74: Nuclear (Daya Bay) | Q74: =+Q67-P67 | R74: =+R67-Q67 | S74: =+S67-R67 | T74: =T67-S67 | U74: =U67-T67 | V74: =V67-U67 | W74: =W67-V67 | X74: =X67-W67 | Y74: =Y67-X67 | Z74: =Z67-Y67 | AA74: =AA67-Z67 | ... AD74: =AD67-AC67 | AE74: =+AD74 | AF74: =+AE74 | AG74: =+AF74 | AH74: =+AG74 | AI74: =+AH74 | AJ74: =+AI74 | AK74: =+AJ74 | AL74: =+AK74 | ... AN74: =+AM74
A75: Pumped storage | Q75: =+Q68-P68 | R75: =+R68-Q68 | S75: =+S68-R68 | T75: =T68-S68 | U75: =U68-T68 | V75: =V68-U68 | W75: =W68-V68 | X75: =X68-W68 | Y75: =Y68-X68 | Z75: =Z68-Y68 | AA75: =AA68-Z68 | AB75: =AB68-AA68 | AC75: =+AB75 | AD75: =+AC75 | AE75: =+AD75 | AF75: =+AE75 | AG75: =+AF75 | AH75: =+AG75 | AI75: =+AH75 | AJ75: =+AI75 | ... AN75: =+AM75
A77: Local peak demand | B77: 4365 | C77: 4432 | D77: 4730 | E77: 4720 | F77: 4998 | G77: 5066 | H77: 5304 | I77: 5354 | J77: 5598 | K77: 5844 | L77: 5829 | M77: 5874 | N77: 6329 | O77: 6475 | P77: 6435 | Q77: 6284 | R77: 6749 | S77: 6389 | T77: 6766 | U77: 6702 | V77: 6769 | W77: 6699 | X77: 7030 | Y77: 6878 | Z77: 6841 | AA77: 7155 | AB77: 7036 | AC77: 7206 | AD77: 7264 | AE77: 7477 | AF77: 7720 | AG77: 7452 | AH77: 7336 | AI77: =AH77*(1+AI81) | AJ77: =AI77*(1+AJ81) | AK77: =AJ77*(1+AK81) | AL77: =AK77*(1+AL81) | AM77: =AL77*(1+AM81) | AN77: =AM77*(1+AN81)
A78: System demand | B78: 5289 | C78: 5244 | D78: 5948 | E78: 6083 | F78: 5088 | G78: 5184 | H78: 5422 | I78: 5455 | J78: 6828 | K78: 7062 | L78: 6897 | M78: 7646 | N78: 7862 | O78: 7817 | P78: 8318 | Q78: 7730 | R78: 8199 | S78: 7616 | T78: 7349 | U78: 7798 | V78: 7431 | W78: 7615 | X78: 7502 | Y78: 7582 | Z78: 7509 | AA78: 8183 | AB78: 7316 | AC78: 7206 | AD78: 7264 | AE78: 7477 | AF78: 7720 | AG78: 7452 | AH78: 7336 | AI78: =AI77+AI79 | AJ78: =AJ77+AJ79 | AK78: =AK77+AK79 | AL78: =AL77+AL79 | AM78: =AM77+AM79 | AN78: =AN77+AN79
A79: Implied China demand at local peak | B79: =B78-B77 | C79: =C78-C77 | D79: =D78-D77 | E79: =E78-E77 | F79: =F78-F77 | G79: =G78-G77 | H79: =H78-H77 | I79: =I78-I77 | ... AE79: =AE78-AE77 | AF79: =AE79*(1+AF83) | AG79: =AF79*(1+AG83) | AH79: =AG79*(1+AH83) | AI79: =AH79*(1+AI83) | AJ79: =AI79*(1+AJ83) | AK79: =AJ79*(1+AK83) | AL79: =AK79*(1+AL83) | AM79: =AL79*(1+AM83) | AN79: =AM79*(1+AN83)
A81: Local peak demand growth | B81: =B77/4180-1 | C81: =C77/B77-1 | D81: =D77/C77-1 | E81: =E77/D77-1 | F81: =F77/E77-1 | G81: =G77/F77-1 | H81: =H77/G77-1 | I81: =I77/H77-1 | J81: =J77/I77-1 | ... AH81: =AH77/AG77-1 | AI81: =AH81 | AJ81: =AI81 | AK81: =AJ81 | AL81: =AK81 | AM81: =AL81 | AN81: =AM81
A82: System peak demand growth | B82: =B78/4828-1 | C82: =C78/B78-1 | D82: =D78/C78-1 | E82: =E78/D78-1 | F82: =F78/E78-1 | G82: =G78/F78-1 | H82: =H78/G78-1 | I82: =I78/H78-1 | J82: =J78/I78-1 | ... AN82: =AN78/AM78-1
A83: China demand growth | B83: =B79/(4828-4180)-1 | C83: =C79/B79-1 | D83: =D79/C79-1 | E83: =E79/D79-1 | F83: =F79/E79-1 | G83: =G79/F79-1 | H83: =H79/G79-1 | I83: =I79/H79-1 | J83: =J79/I79-1 | ... AC83: =AC79/AB79-1 | AD83: 0 | AE83: 0 | AF83: 0 | AG83: 0 | AH83: 0 | AI83: =AH83 | AJ83: =AI83 | AK83: =AJ83 | AL83: =AK83 | AM83: =AL83 | AN83: =AM83
A85: Local reserve margin | B85: =B63/B77-1 | C85: =C63/C77-1 | D85: =D63/D77-1 | E85: =E63/E77-1 | F85: =F63/F77-1 | G85: =G63/G77-1 | H85: =H63/H77-1 | I85: =I63/I77-1 | ... AN85: =AN63/AN77-1
A86: System reserve margin, post China demand | B86: =B63/B78-1 | C86: =C63/C78-1 | D86: =D63/D78-1 | E86: =E63/E78-1 | F86: =F63/F78-1 | G86: =G63/G78-1 | H86: =H63/H78-1 | I86: =I63/I78-1 | ... AN86: =AN63/AN78-1
A88: Updated 2014-18 PDP (Jul 2018)
A89: https://www.google.com/url?sa=t&rct=j&q=&esrc=s&source=web&cd=1&ved=2ahUKEwi649Oeo-PjAhWHPXAKHcpyCBUQFjAAegQIABAC&url=https%3A%2F%2Fwww.clpgroup.com%2Fen%2FMedia-Resources-site%2FCurrent%2520Releases%2F20180703_en.pdf&usg=AOvVaw3JugD4oY5Ns32PMBU-Giat
T90: 2013-18 | U90: 2018-23 | V90: 2023-28
A91: Gneration | T91: 22562 | U91: 25429
A92: T&D | T92: 10703 | U92: =26496+3152
A93: Others | T93: 836 | U93: =1018
A94: Total | T94: =SUM(T91:T93) | U94: =SUM(U91:U93) | V94: 52900
A97: LNG terminal
A99: 2004 | T99: Start discussion - propose a landbased LNG terminal
A100: 2007 | T100: Environmental Impact Assessment Report (EIA) and Environmental Permit (EP) are approved
A101: 2008 | T101: Rejected by HK Government (US$10bn onshore plant)
A102: On hold | T102: HK cooperated with mainland to facilitate the supply of natural gas from Turkmenistan, through Second West-to-East Pipeline
A103: 2016.05 | T103: FSRU LNG terminal - LNG storage tanks, LNG regasification units, subsea pipeline
T104: HK Offshore LNG Terminal: a FSRU and two subsea pipelines
A105: 2019 | T105: Construction start
A106: 2020 | T106: Start operation by end-2020
T107: Already submit for government approval
T108: 3-5 mtpa | U108: capacity
A109: Current source:
A110: Yacheng 13-1 (CLP)
A111: Turkmenistan (CLP)
A112: Guangdong Dapeng LNG (HKEI)
A114: CAPEX (HK$ million) | T114: 4000
A115: CLP's share | T115: 0.7
A116: CLP's CAPEX | T116: =T114*T115 | U116: =T116/5
A117: % of increase in HK SoC net fixed asset 2021 | T117: =T116/AE4
A118: Permitted Return | T118: =T116*0.08
...

Sheet CN
A1: China | B1: =Final!B2 | C1: =Final!C2 | D1: =Final!D2 | E1: =Final!E2 | F1: =Final!F2 | G1: =Final!G2 | H1: =Final!H2 | I1: =Final!I2 | ... AN1: =Final!AN2
A2: Rmb/HKD - Avg | W2: 1.2629 | X2: 1.2573 | Y2: 1.23208 | Z2: 1.16487 | AA2: 1.15711 | AB2: 1.18249 | AC2: 1.1345911 | AD2: 1.1244981 | AE2: 1.2046 | AF2: 1.1647 | AG2: 1.1074 | AH2: 1.0894701 | AI2: 1.07711 | AJ2: 1.1071429 | AK2: =AJ2 | AL2: =AK2 | AM2: =AL2 | AN2: =AM2
A3: Financial Statement (HK$ m)
A4: Revenue | I4: 357 | J4: 588 | K4: 706 | L4: 0 | M4: 0 | N4: 0 | O4: 17 | P4: 131 | Q4: 124 | R4: 169 | S4: 180 | T4: 305 | U4: 625 | V4: 943 | W4: 991 | X4: 909 | Y4: 937 | Z4: 1197 | AA4: 1305 | AB4: 1495 | AC4: 1674 | AD4: 1708 | AE4: 1800 | AF4: 1877 | AG4: 1846 | AH4: 1801 | AI4: =AI8-AI5-AI6-AI7 | AJ4: =AJ8-AJ5-AJ6-AJ7 | AK4: =AK8-AK5-AK6-AK7 | AL4: =AL8-AL5-AL6-AL7 | AM4: =AM8-AM5-AM6-AM7 | AN4: =AN8-AN5-AN6-AN7
A5: Cash costs | I5: =-72-I4-I9 | J5: =-48-J4-J9 | K5: =-69-K4-K9 | L5: =-118-L4-L9 | M5: =-145-M4-M9 | N5: =-181-N4-N9 | O5: =-132-O4-O9 | P5: =-70-P4-P9 | Q5: =-87-Q4-Q9 | R5: =282-R4-R9 | S5: =-100-S4-S9 | T5: =412-T4-T9 | U5: =147-U4-U9 | V5: =220-V4-V9 | W5: =620-W4 | X5: =501-X4 | Y5: =786-Y4 | Z5: =951-Z4 | AA5: =1212-AA4 | AB5: =1346-AB4 | AC5: =1405-AC4 | AD5: =1590-AD4 | AE5: =1539-AE4 | AF5: =1260-AF4 | AG5: =1369-AG4 | AH5: =1434-AH4 | AI5: =AH5 | AJ5: =AI5 | AK5: =AJ5 | AL5: =AK5 | AM5: =AL5 | AN5: =AM5
A6: Share of result - JV | I6: 780 | J6: 806 | K6: 1137 | L6: 1086 | M6: 1290 | N6: 1194 | O6: 1102 | P6: 1058 | Q6: 1112 | R6: 889 | S6: 1218 | T6: 816 | U6: 645 | V6: 898 | W6: 1188 | X6: 891 | Y6: 1031 | Z6: 461 | AA6: 339 | AB6: 354 | AC6: 558 | AD6: 493 | AE6: -271 | AF6: 327 | AG6: 234 | AH6: 152 | AI6: =AI32-AH32+AH6 | AJ6: =AJ32-AI32+AI6 | AK6: =AK32-AJ32+AJ6 | AL6: =AL32-AK32+AK6 | AM6: =AM32-AL32+AL6 | AN6: =AN32-AM32+AM6 | AP6: CSEC Guohua (30%), Fangchenggang (70%), ShenGang Nuatural Gas pipeline (40%), Shandong Zhonghua Power (29.4%)
A7: Share of result - Associates | J7: 0 | K7: 0 | L7: 0 | M7: 0 | N7: 0 | O7: 0 | P7: 0 | Q7: 0 | R7: 0 | S7: 94 | T7: 804 | U7: 639 | V7: 579 | W7: 612 | X7: 796 | Y7: 888 | Z7: 907 | AA7: 961 | AB7: 1863 | AC7: 1828 | AD7: 1725 | AE7: 2071 | AF7: 2135 | AG7: 2049 | AH7: 1810 | AI7: =AI29 | AJ7: =AJ29 | AK7: =AK29 | AL7: =AL29 | AM7: =AM29 | AN7: =AN29 | AP7: GNPJVC - Daya Bay (25%)
A8: EBITDAF | B8: =SUM(B4:B7) | C8: =SUM(C4:C7) | D8: =SUM(D4:D7) | E8: =SUM(E4:E7) | F8: =SUM(F4:F7) | G8: =SUM(G4:G7) | H8: =SUM(H4:H7) | I8: =SUM(I4:I7) | ... AH8: =SUM(AH4:AH7) | AI8: =AI12-AI9 | AJ8: =AJ12-AJ9 | AK8: =AK12-AK9 | AL8: =AL12-AL9 | AM8: =AM12-AM9 | AN8: =AN12-AN9
A9: D&A | I9: =-26-4 | J9: =-4-32 | K9: =-5-46 | L9: =-49-2 | M9: -2 | N9: -2 | O9: -7 | P9: -36 | Q9: -39 | R9: -51 | S9: -68 | T9: -81 | U9: -148 | V9: -209 | W9: -213 | X9: -412 | Y9: -517 | Z9: -583 | AA9: -638 | AB9: -696 | AC9: -735 | AD9: -747 | AE9: -807 | AF9: -814 | AG9: -825 | AH9: -840 | AI9: =AI10+AI11 | AJ9: =AJ10+AJ11 | AK9: =AK10+AK11 | AL9: =AL10+AL11 | AM9: =AM10+AM11 | AN9: =AN10+AN11
A10: - Amortisation | Q10: 0 | R10: 0 | S10: 0 | T10: 0 | U10: 0 | V10: 0 | W10: 0 | X10: -181 | Y10: -272 | Z10: -273 | AA10: -274 | AB10: -274 | AC10: -276 | AD10: -255 | AE10: -276 | AF10: -279 | AG10: -280 | AH10: -282 | AI10: =AH10 | AJ10: =AI10 | AK10: =AJ10 | AL10: =AK10 | AM10: =AL10 | AN10: =AM10
A11: - Depreciation | Q11: =Q9-Q10 | R11: =R9-R10 | S11: =S9-S10 | T11: =T9-T10 | U11: =U9-U10 | V11: =V9-V10 | W11: =W9-W10 | X11: =X9-X10 | ... AH11: =AH9-AH10 | AI11: =AI158 | AJ11: =AJ158 | AK11: =AK158 | AL11: =AL158 | AM11: =AM158 | AN11: =AN158
A12: EBITF (ACOI) | B12: =B8+B9 | C12: =C8+C9 | D12: =D8+D9 | E12: =E8+E9 | F12: =F8+F9 | G12: =G8+G9 | H12: =H8+H9 | I12: =I8+I9 | ... AG12: =AG8+AG9 | AH12: =AH15-AH13-AH14 | AI12: =AI15-AI13-AI14 | AJ12: =AJ15-AJ13-AJ14 | AK12: =AK15-AK13-AK14 | AL12: =AL15-AL13-AL14 | AM12: =AM15-AM13-AM14 | AN12: =AN15-AN13-AN14
A13: Fair value adjustment | R13: 0 | S13: 0 | T13: 0 | U13: 0 | V13: 0 | W13: 0 | X13: 0 | Y13: 0 | Z13: 0 | AA13: 0 | AB13: 0 | AC13: 0 | AD13: 0 | AE13: 0 | AF13: 0 | AG13: 0 | AH13: 0 | AI13: 0 | AJ13: 0 | AK13: 0 | AL13: 0 | AM13: 0 | AN13: 0
A14: Net financial costs | S14: =-35+5 | T14: =-49+1 | U14: =-135+4 | V14: =-213+5 | W14: =-205+4 | X14: =-211+9 | Y14: =-206+59 | Z14: =-200+44 | AA14: =-241+39 | AB14: =-269+34 | AC14: =-276+28 | AD14: =-255+18 | AE14: =-253+14 | AF14: =-245+9 | AG14: =-209+14 | AH14: =-180+14 | AI14: =-AI164*AH163 | AJ14: =-AJ164*AI163 | AK14: =-AK164*AJ163 | AL14: =-AL164*AK163 | AM14: =-AM164*AL163 | AN14: =-AN164*AM163
A15: PBT | B15: =B12+B13+B14 | C15: =C12+C13+C14 | D15: =D12+D13+D14 | E15: =E12+E13+E14 | F15: =F12+F13+F14 | G15: =G12+G13+G14 | H15: =H12+H13+H14 | I15: =I12+I13+I14 | ... AG15: =AG12+AG13+AG14 | AH15: =AH18-AH16-AH17 | AI15: =AI18-AI16-AI17 | AJ15: =AJ18-AJ16-AJ17 | AK15: =AK18-AK16-AK17 | AL15: =AL18-AL16-AL17 | AM15: =AM18-AM16-AM17 | AN15: =AN18-AN16-AN17
A16: Taxation | S16: -70 | T16: -147 | U16: -68 | V16: -112 | W16: -151 | X16: -102 | Y16: -147 | Z16: -67 | AA16: -151 | AB16: -267 | AC16: -305 | AD16: -314 | AE16: -329 | AF16: -356 | AG16: -379 | AH16: -328 | AI16: =AH16/AH18*AI18 | AJ16: =AI16/AI18*AJ18 | AK16: =AJ16/AJ18*AK18 | AL16: =AK16/AK18*AL18 | AM16: =AL16/AL18*AM18 | AN16: =AM16/AM18*AN18
A17: Minority interest | S17: 7 | T17: -3 | U17: -1 | V17: 20 | W17: -12 | X17: -14 | Y17: -9 | Z17: -19 | AA17: -13 | AB17: -10 | AC17: =-15 | AD17: -7 | AE17: -3 | AF17: -9 | AG17: -8 | AH17: -10 | AI17: =AH17 | AJ17: =AI17 | AK17: =AJ17 | AL17: =AK17 | AM17: =AL17 | AN17: =AM17
A18: Reported NP | B18: =B15+B16+B17 | C18: =C15+C16+C17 | D18: =D15+D16+D17 | E18: =E15+E16+E17 | F18: =F15+F16+F17 | G18: =G15+G16+G17 | H18: =H15+H16+H17 | I18: =I15+I16+I17 | ... AG18: =AG15+AG16+AG17 | AH18: =AH20-AH19 | AI18: =AI20-AI19 | AJ18: =AJ20-AJ19 | AK18: =AK20-AK19 | AL18: =AL20-AL19 | AM18: =AM20-AM19 | AN18: =AN20-AN19
A19: One-off items | S19: 0 | T19: 0 | U19: 0 | V19: 0 | W19: -372 | X19: -158 | Y19: -243 | Z19: -174 | AA19: 0 | AB19: 0 | AC19: 0 | AD19: 0 | AE19: 0 | AF19: -185 | AG19: -115 | AH19: 0 | AI19: 0 | AJ19: 0 | AK19: 0 | AL19: 0 | AM19: 0 | AN19: 0
A20: Recurring NP | B20: =B42 | C20: =C42 | D20: =D42 | E20: =E42 | F20: =F42 | G20: =G42 | H20: =H42 | I20: =I18+I19 | J20: =J18+J19 | K20: =K18+K19 | L20: =L18+L19 | M20: =M18+M19 | N20: =N18+N19 | O20: =O18+O19 | P20: =P18+P19 | ... V20: =V18+V19 | W20: =W18-W19 | X20: =X18-X19 | Y20: =Y18-Y19 | Z20: =Z18-Z19 | AA20: =AA18-AA19 | AB20: =AB18-AB19 | AC20: =AC18-AC19 | AD20: =AD18-AD19 | ... AG20: =AG18-AG19 | AH20: =AH42 | AI20: =AI42 | AJ20: =AJ42 | AK20: =AK42 | AL20: =AL42 | AM20: =AM42 | AN20: =AN42
A21: YoY | M21: =M20/L20-1 | N21: =N20/M20-1 | O21: =O20/N20-1 | P21: =P20/O20-1 | Q21: =Q20/P20-1 | R21: =R20/Q20-1 | S21: =S20/R20-1 | T21: =T20/S20-1 | ... AN21: =AN20/AM20-1
A23: Performance by segment
A24: Recurring NP by segment
A25: Renewable | B25: =SUM(B26:B28) | C25: =SUM(C26:C28) | D25: =SUM(D26:D28) | E25: =SUM(E26:E28) | F25: =SUM(F26:F28) | G25: =SUM(G26:G28) | H25: =SUM(H26:H28) | I25: =SUM(I26:I28) | ... AN25: =SUM(AN26:AN28)
A26: Wind | W26: 192 | X26: 144 | Y26: 151 | Z26: 202 | AA26: 245 | AB26: 314 | AC26: 270 | AD26: 306 | AE26: 305 | AF26: 313 | AG26: 308 | AH26: 312 | AI26: =AI66*AI79*AI$2 | AJ26: =AJ66*AJ79*AJ$2 | AK26: =AK66*AK79*AK$2 | AL26: =AL66*AL79*AL$2 | AM26: =AM66*AM79*AM$2 | AN26: =AN66*AN79*AN$2 | AO26: =AI26/AH26-1 | AP26: 161 | AQ26: 228 | AR26: =AP26/AQ26-1
A27: Hydro | W27: 129 | X27: 107 | Y27: 87 | Z27: 121 | AA27: 100 | AB27: 93 | AC27: 104 | AD27: 88 | AE27: 45 | AF27: 112 | AG27: 101 | AH27: 111 | AI27: =AI67*AI80*AI$2 | AJ27: =AJ67*AJ80*AJ$2 | AK27: =AK67*AK80*AK$2 | AL27: =AL67*AL80*AL$2 | AM27: =AM67*AM80*AM$2 | AN27: =AN67*AN80*AN$2 | AO27: =AI27/AH27-1 | AP27: 50 | AQ27: 36 | AR27: =AP27/AQ27-1
A28: Solar | W28: 85 | X28: -7 | Y28: 79 | Z28: 81 | AA28: 96 | AB28: 123 | AC28: 173 | AD28: 171 | AE28: 195 | AF28: 185 | AG28: 194 | AH28: 148 | AI28: =AI68*AI81*AI$2 | AJ28: =AJ68*AJ81*AJ$2 | AK28: =AK68*AK81*AK$2 | AL28: =AL68*AL81*AL$2 | AM28: =AM68*AM81*AM$2 | AN28: =AN68*AN81*AN$2 | AO28: =AI28/AH28-1 | AP28: 84 | AQ28: 87 | AR28: =AP28/AQ28-1
A29: Nuclear | B29: =SUM(B30:B31) | C29: =SUM(C30:C31) | D29: =SUM(D30:D31) | E29: =SUM(E30:E31) | F29: =SUM(F30:F31) | G29: =SUM(G30:G31) | H29: =SUM(H30:H31) | I29: =SUM(I30:I31) | ... Z29: =SUM(Z30:Z31) | AA29: 913 | AB29: 1720 | AC29: 1688 | AD29: 1594 | AE29: 1908 | AF29: 1965 | AG29: 1888 | AH29: =SUM(AH30:AH31) | AI29: =SUM(AI30:AI31) | AJ29: =SUM(AJ30:AJ31) | AK29: =SUM(AK30:AK31) | AL29: =SUM(AL30:AL31) | AM29: =SUM(AM30:AM31) | AN29: =SUM(AN30:AN31) | AO29: =AI29/AH29-1
A30: Daya Bay | B30: 0 | C30: 0 | D30: 135 | E30: 218 | F30: 296 | G30: 350 | H30: 423 | I30: 578 | J30: 551 | K30: 700 | L30: 676 | M30: 696 | N30: 663 | O30: 698 | P30: 691 | Q30: 723 | R30: 830 | S30: 715 | T30: 804 | U30: 639 | V30: 579 | W30: 602 | X30: 774 | Y30: 844 | Z30: 863 | AA30: =AA29-AA31 | AB30: =AB29-AB31 | AC30: =AC29-AC31 | AD30: 933 | AE30: 963 | AF30: 970 | AG30: 943 | AH30: 911 | AI30: =AI70*AI83*AI$2 | AJ30: =AJ70*AJ83*AJ$2 | AK30: =AK70*AK83*AK$2 | AL30: =AL70*AL83*AL$2 | AM30: =AM70*AM83*AM$2 | AN30: =AN70*AN83*AN$2 | AO30: =AI30/AH30-1 | AP30: 433 | AQ30: 344 | AR30: =AP30/AQ30-1
A31: Yangjiang | W31: 0 | X31: 0 | Y31: 0 | Z31: 0 | AA31: 34 | AB31: 800 | AC31: 750 | AD31: 661 | AE31: 945 | AF31: 995 | AG31: 945 | AH31: 760 | AI31: =AI71*AI84*AI$2 | AJ31: =AJ71*AJ84*AJ$2 | AK31: =AK71*AK84*AK$2 | AL31: =AL71*AL84*AL$2 | AM31: =AM71*AM84*AM$2 | AN31: =AN71*AN84*AN$2 | AO31: =AI31/AH31-1 | AP31: 328 | AQ31: 492 | AR31: =AP31/AQ31-1
A32: Thermal | B32: =SUM(B33:B35) | C32: =SUM(C33:C35) | D32: =SUM(D33:D35) | E32: =SUM(E33:E35) | F32: =SUM(F33:F35) | G32: =SUM(G33:G35) | H32: =SUM(H33:H35) | I32: =SUM(I33:I35) | ... AC32: =SUM(AC33:AC35) | AD32: 203 | AE32: -572 | AF32: 45 | AG32: -11 | AH32: 5 | AI32: =SUM(AI33:AI35) | AJ32: =SUM(AJ33:AJ35) | AK32: =SUM(AK33:AK35) | AL32: =SUM(AL33:AL35) | AM32: =SUM(AM33:AM35) | AN32: =SUM(AN33:AN35)
A33: Shandong (29.4%) | W33: 312 | X33: 426 | Y33: 558 | Z33: 250 | AA33: 58 | AB33: 13 | AC33: -6 | AD33: -7 | AE33: -321 | AF33: 7 | AG33: 6 | AH33: 6 | AI33: =AI73*AI86*AI$2 | AJ33: =AJ73*AJ86*AJ$2 | AK33: =AK73*AK86*AK$2 | AL33: =AL73*AL86*AL$2 | AM33: =AM73*AM86*AM$2 | AN33: =AN73*AN86*AN$2
A34: Guohua (30%) | W34: 302 | X34: 0 | Y34: 316 | Z34: 170 | AA34: 67 | AB34: 15 | AC34: 33 | AD34: -1 | AE34: -149 | AF34: 98 | AG34: -17 | AH34: -1 | AI34: =AI74*AI87*AI$2 | AJ34: =AJ74*AJ87*AJ$2 | AK34: =AK74*AK87*AK$2 | AL34: =AL74*AL87*AL$2 | AM34: =AM74*AM87*AM$2 | AN34: =AN74*AN87*AN$2 | AP34: 870 | AQ34: 988 | AR34: =AP34/AQ34-1
A35: Fangchenggang (70%) | W35: 563 | X35: 293 | Y35: 67 | Z35: 9 | AA35: -80 | AB35: 8 | AC35: 237 | AD35: 211 | AE35: -102 | AF35: -60 | AG35: 0 | AH35: 0 | AI35: =AI75*AI88*AI$2 | AJ35: =AJ75*AJ88*AJ$2 | AK35: =AK75*AK88*AK$2 | AL35: =AL75*AL88*AL$2 | AM35: =AM75*AM88*AM$2 | AN35: =AN75*AN88*AN$2
A36: OPEX | W36: -70 | X36: -80 | Y36: -92 | Z36: -120 | AA36: =-161-AA37-AA38 | AB36: =-123-AB37-AB38 | AC36: =-222-AC37-AC38 | AD36: =-129-AD37-AD38 | AE36: =-221-AE37-AE38 | AF36: =-343-AF37 | AG36: =-335-AG37 | AH36: =-332-AH37 | AI36: =AH36/AH2*AI2*1.03 | AJ36: =AI36/AI2*AJ2*1.03 | AK36: =AJ36/AJ2*AK2*1.03 | AL36: =AK36/AK2*AL2*1.03 | AM36: =AL36/AL2*AM2*1.03 | AN36: =AM36/AM2*AN2*1.03
A37: Development expenditure | W37: -33 | X37: -23 | Y37: -9 | Z37: -16 | AA37: -16 | AB37: =AA37 | AC37: =AB37 | AD37: =AC37 | AE37: =AD37 | AF37: =AE37 | AG37: =AF37 | AH37: =AG37 | AI37: =AH37 | ... AN37: =AM37
A38: RMB exchange loss | W38: =24+25 | X38: =-29-26 | Y38: -24 | Z38: -39 | AA38: -39 | AB38: 0 | AC38: 0 | AD38: 0 | AE38: 0 | AF38: 0 | AG38: 0 | AH38: 0 | AI38: 0 | AJ38: 0 | AK38: 0 | AL38: 0 | AM38: 0 | AN38: 0
A39: CLPe | W39: 0 | X39: 0 | Y39: 0 | Z39: 0 | AA39: 0 | AB39: 0 | AC39: 0 | AD39: 0 | AE39: 0 | AF39: -48 | AG39: -72 | AH39: -64 | AI39: 0 | AJ39: 0 | AK39: 0 | AL39: 0 | AM39: 0 | AN39: 0
A40: Total recurring NP (excl. PSDC) | B40: =B25+B29+B32+B36+B37+B38 | C40: =C25+C29+C32+C36+C37+C38 | D40: =D25+D29+D32+D36+D37+D38 | E40: =E25+E29+E32+E36+E37+E38 | F40: =F25+F29+F32+F36+F37+F38 | G40: =G25+G29+G32+G36+G37+G38 | H40: =H25+H29+H32+H36+H37+H38 | I40: =I42-I41 | J40: =J42-J41 | K40: =K42-K41 | L40: =L42-L41 | M40: =M42-M41 | N40: =N42-N41 | O40: =O42-O41 | P40: =P42-P41 | ... V40: =V42-V41 | W40: =W25+W29+W32+W36+W37+W38 | X40: =X25+X29+X32+X36+X37+X38 | Y40: =Y25+Y29+Y32+Y36+Y37+Y38 | Z40: =Z25+Z29+Z32+Z36+Z37+Z38 | AA40: =AA25+AA29+AA32+AA36+AA37+AA38 | AB40: =AB25+AB29+AB32+AB36+AB37+AB38 | AC40: =AC25+AC29+AC32+AC36+AC37+AC38 | AD40: =AD25+AD29+AD32+AD36+AD37+AD38 | AE40: =AE25+AE29+AE32+AE36+AE37+AE38 | AF40: =AF25+AF29+AF32+AF36+AF37+AF39 | AG40: =AG25+AG29+AG32+AG36+AG37+AG39 | AH40: =AH25+AH29+AH32+AH36+AH37+AH39 | AI40: =AI25+AI29+AI32+AI36+AI37+AI39 | AJ40: =AJ25+AJ29+AJ32+AJ36+AJ37+AJ39 | AK40: =AK25+AK29+AK32+AK36+AK37+AK39 | AL40: =AL25+AL29+AL32+AL36+AL37+AL39 | AM40: =AM25+AM29+AM32+AM36+AM37+AM39 | AN40: =AN25+AN29+AN32+AN36+AN37+AN39
A41: NP from PSDC & HK branch line | B41: 62 | C41: 67 | D41: 74 | E41: 90 | F41: 87 | G41: 84 | H41: 81 | I41: 88 | J41: 75 | K41: 72 | L41: 70 | M41: 67 | N41: 64 | O41: 62 | P41: 60 | Q41: -11 | R41: 101 | S41: 33 | T41: 73 | U41: 76 | V41: 80 | W41: =W42-W40 | X41: =X42-X40 | Y41: 151 | Z41: 147 | AA41: 270 | AB41: 192 | AC41: 211 | AD41: 270 | AE41: 301 | AF41: 263 | AG41: 287 | AH41: 201 | AI41: =AH41 | AJ41: =AI41 | AK41: =AJ41 | AL41: =AK41 | AM41: =AL41 | AN41: =AM41
A42: Total recurring NP | B42: =B40+B41 | C42: =C40+C41 | D42: =D40+D41 | E42: =E40+E41 | F42: =F40+F41 | G42: =G40+G41 | H42: =H40+H41 | I42: =I20 | J42: =J20 | K42: =K20 | L42: =L20 | M42: =M20 | N42: =N20 | O42: =O20 | P42: =P20 | ... X42: =X20 | Y42: =Y40+Y41 | Z42: =Z40+Z41 | AA42: =AA40+AA41 | AB42: =AB40+AB41 | AC42: =AC40+AC41 | AD42: =AD40+AD41 | AE42: =AE40+AE41 | AF42: =AF40+AF41 | ... AN42: =AN40+AN41
A43: YoY | R43: =R42/Q42-1 | S43: =S42/R42-1 | T43: =T42/S42-1 | U43: =U42/T42-1 | V43: =V42/U42-1 | W43: =W42/V42-1 | X43: =X42/W42-1 | Y43: =Y42/X42-1 | ... AN43: =AN42/AM42-1
A45: Earnings by segment (HK$ m)
A46: Renewable | B46: =SUM(B47:B49) | C46: =SUM(C47:C49) | D46: =SUM(D47:D49) | E46: =SUM(E47:E49) | F46: =SUM(F47:F49) | G46: =SUM(G47:G49) | H46: =SUM(H47:H49) | I46: =SUM(I47:I49) | ... AA46: =SUM(AA47:AA49)
A47: Wind | W47: 192 | X47: 144 | Y47: 151 | Z47: 202
A48: Hydro | W48: 129 | X48: 107 | Y48: 87 | Z48: 121
A49: Solar | W49: 85 | X49: -7 | Y49: 79 | Z49: 81
A50: Nuclear | B50: =SUM(B51:B52) | C50: =SUM(C51:C52) | D50: =SUM(D51:D52) | E50: =SUM(E51:E52) | F50: =SUM(F51:F52) | G50: =SUM(G51:G52) | H50: =SUM(H51:H52) | I50: =SUM(I51:I52) | ... Z50: =SUM(Z51:Z52)
A51: Daya Bay | W51: 602 | X51: 774 | Y51: 844 | Z51: 863
A52: Yangjiang | W52: 0 | X52: 0 | Y52: 0 | Z52: 0
A53: Thermal | B53: =SUM(B54:B56) | C53: =SUM(C54:C56) | D53: =SUM(D54:D56) | E53: =SUM(E54:E56) | F53: =SUM(F54:F56) | G53: =SUM(G54:G56) | H53: =SUM(H54:H56) | I53: =SUM(I54:I56) | ... Z53: =SUM(Z54:Z56)
A54: Shandong | W54: 312 | X54: 426 | Y54: 558 | Z54: 250
A55: Guohua | W55: 302 | X55: 0 | Y55: 316 | Z55: 170
A56: Fangchenggang | W56: 563 | X56: 293 | Y56: 67 | Z56: 9
A57: OPEX | W57: -70 | X57: -80 | Y57: -92 | Z57: -120
A58: Development expenditure | W58: -33 | X58: -23 | Y58: -9 | Z58: -16
A59: RMB exchange loss | W59: =24+25 | X59: =-29-26 | Y59: -24 | Z59: -39
A60: Total NP (excl. PSDC) | W60: =W46+W50+W53+W57+W58+W59 | X60: =X46+X50+X53+X57+X58+X59 | Y60: =Y46+Y50+Y53+Y57+Y58+Y59 | Z60: =Z46+Z50+Z53+Z57+Z58+Z59
A61: NP from PSDC & HK branch line | W61: =W62-W60 | X61: 30 | Y61: 151 | Z61: 147
A62: Total NP | W62: =W20 | X62: =X60+X61 | Y62: =Y60+Y61 | Z62: =Z60+Z61
A64: Attributable capacity by segments
A65: Renewable | B65: =SUM(B66:B68) | C65: =SUM(C66:C68) | D65: =SUM(D66:D68) | E65: =SUM(E66:E68) | F65: =SUM(F66:F68) | G65: =SUM(G66:G68) | H65: =SUM(H66:H68) | I65: =SUM(I66:I68) | ... AN65: =SUM(AN66:AN68)
A66: Wind | Q66: =Q132+Q134 | R66: =R132+R134 | S66: =S132+S134 | T66: =T132+T134 | U66: =U132+U134 | V66: =V132+V134 | W66: =W132+W134 | X66: =X132+X134 | ... AN66: =AN132+AN134
A67: Hydro | Q67: =Q131 | R67: =R131 | S67: =S131 | T67: =T131 | U67: =U131 | V67: =V131 | W67: =W131 | X67: =X131 | ... AN67: =AN131
A68: Solar | Q68: =Q135 | R68: =R135 | S68: =S135 | T68: =T135 | U68: =U135 | V68: =V135 | W68: =W135 | X68: =X135 | ... AN68: =AN135 | AU68: =AC28/AC68
A69: Nuclear | B69: =SUM(B70:B71) | C69: =SUM(C70:C71) | D69: =SUM(D70:D71) | E69: =SUM(E70:E71) | F69: =SUM(F70:F71) | G69: =SUM(G70:G71) | H69: =SUM(H70:H71) | I69: =SUM(I70:I71) | ... AN69: =SUM(AN70:AN71)
A70: Daya Bay | P70: =P125 | Q70: =Q125 | R70: =R125 | S70: =S125 | T70: =T125 | U70: =U125 | V70: =V125 | W70: =W125 | ... AN70: =AN125
A71: Yangjiang | Q71: 0 | R71: 0 | S71: 0 | T71: 0 | U71: 0 | V71: 0 | W71: 0 | X71: 0 | Y71: 0 | Z71: =Z136 | AA71: =AA136 | AB71: =AB136 | AC71: =AC136 | AD71: =AD136 | AE71: =AE136 | AF71: =AF136 | AG71: =AG136 | ... AN71: =AN136
A72: Thermal | B72: =SUM(B73:B75) | C72: =SUM(C73:C75) | D72: =SUM(D73:D75) | E72: =SUM(E73:E75) | F72: =SUM(F73:F75) | G72: =SUM(G73:G75) | H72: =SUM(H73:H75) | I72: =SUM(I73:I75) | ... AN72: =SUM(AN73:AN75)
A73: Shandong | Q73: =Q128 | R73: =R128 | S73: =S128 | T73: =T128 | U73: =U128 | V73: =V128 | W73: =W128 | X73: =X128 | ... AG73: =AG128 | AH73: 0 | AI73: =AH73 | AJ73: =AI73 | AK73: =AJ73 | AL73: =AK73 | AM73: =AL73 | AN73: =AM73
A74: Guohua | Q74: =Q129 | R74: =R129 | S74: =S129 | T74: =T129 | U74: =U129 | V74: =V129 | W74: =W129 | X74: =X129 | ... AN74: =AN129
A75: Fangchenggang | Q75: =Q127 | R75: =R127 | S75: =S127 | T75: =T127 | U75: =U127 | V75: =V127 | W75: =W127 | X75: =X127 | ... AN75: =AN127
A77: Unit EBIT (Rmb m/MW)
A78: Renewable | B78: =SUM(B79:B81) | C78: =SUM(C79:C81) | D78: =SUM(D79:D81) | E78: =SUM(E79:E81) | F78: =SUM(F79:F81) | G78: =SUM(G79:G81) | H78: =SUM(H79:H81) | I78: =SUM(I79:I81) | ... P78: =SUM(P79:P81)
A79: Wind | W79: =W26/W66/W$2 | X79: =X26/X66/X$2 | Y79: =Y26/Y66/Y$2 | Z79: =Z26/Z66/Z$2 | AA79: =AA26/AA66/AA$2 | AB79: =AB26/AB66/AB$2 | AC79: =AC26/AC66/AC$2 | AD79: =AD26/AD66/AD$2 | ... AH79: =AH26/AH66/AH$2 | AI79: =AH79*0.6 | AJ79: =AI79 | AK79: =AJ79 | AL79: =AK79 | AM79: =AL79 | AN79: =AM79
A80: Hydro | W80: =W27/W67/W$2 | X80: =X27/X67/X$2 | Y80: =Y27/Y67/Y$2 | Z80: =Z27/Z67/Z$2 | AA80: =AA27/AA67/AA$2 | AB80: =AB27/AB67/AB$2 | AC80: =AC27/AC67/AC$2 | AD80: =AD27/AD67/AD$2 | ... AH80: =AH27/AH67/AH$2 | AI80: =AH80*1.1 | AJ80: =AI80 | AK80: =AJ80 | AL80: =AK80 | AM80: =AL80 | AN80: =AM80
A81: Solar | W81: =W28/W68/W$2 | X81: =X28/X68/X$2 | Y81: =Y28/Y68/Y$2 | Z81: =Z28/Z68/Z$2 | AA81: =AA28/AA68/AA$2 | AB81: =AB28/AB68/AB$2 | AC81: =AC28/AC68/AC$2 | AD81: =AD28/AD68/AD$2 | ... AH81: =AH28/AH68/AH$2 | AI81: =AH81*0.65 | AJ81: =AI81 | AK81: =AJ81 | AL81: =AK81 | AM81: =AL81 | AN81: =AM81
A82: Nuclear | B82: =SUM(B83:B84) | C82: =SUM(C83:C84) | D82: =SUM(D83:D84) | E82: =SUM(E83:E84) | F82: =SUM(F83:F84) | G82: =SUM(G83:G84) | H82: =SUM(H83:H84) | I82: =SUM(I83:I84) | ... P82: =SUM(P83:P84)
A83: Daya Bay | W83: =W30/W70/W$2 | X83: =X30/X70/X$2 | Y83: =Y30/Y70/Y$2 | Z83: =Z30/Z70/Z$2 | AA83: =AA30/AA70/AA$2 | AB83: =AB30/AB70/AB$2 | AC83: =AC30/AC70/AC$2 | AD83: =AD30/AD70/AD$2 | ... AH83: =AH30/AH70/AH$2 | AI83: =AH83 | AJ83: =AI83 | AK83: =AJ83 | AL83: =AK83 | AM83: =AL83 | AN83: =AM83
A84: Yangjiang | AA84: =AA31/AA71/AA$2*12 | AB84: =AB31/AB71/AB$2 | AC84: =AC31/AC71/AC$2 | AD84: =AD31/AD71/AD$2 | AE84: =AE31/AE71/AE$2 | AF84: =AF31/AF71/AF$2 | AG84: =AG31/AG71/AG$2 | AH84: =AH31/AH71/AH$2 | AI84: =AH84*0.8 | AJ84: =AI84 | AK84: =AJ84 | AL84: =AK84 | AM84: =AL84 | AN84: =AM84
A85: Thermal | B85: =SUM(B86:B88) | C85: =SUM(C86:C88) | D85: =SUM(D86:D88) | E85: =SUM(E86:E88) | F85: =SUM(F86:F88) | G85: =SUM(G86:G88) | H85: =SUM(H86:H88) | I85: =SUM(I86:I88) | ... P85: =SUM(P86:P88)
A86: Shandong | W86: =W33/W73/W$2 | X86: =X33/X73/X$2 | Y86: =Y33/Y73/Y$2 | Z86: =Z33/Z73/Z$2 | AA86: =AA33/AA73/AA$2 | AB86: =AB33/AB73/AB$2 | AC86: =AC33/AC73/AC$2 | AD86: =AD33/AD73/AD$2 | ... AG86: =AG33/AG73/AG$2 | AH86: 0 | AI86: =AH86 | AJ86: =AI86 | AK86: =AJ86 | AL86: =AK86 | AM86: =AL86 | AN86: =AM86
A87: Guohua | W87: =W34/W74/W$2 | X87: =X34/X74/X$2 | Y87: =Y34/Y74/Y$2 | Z87: =Z34/Z74/Z$2 | AA87: =AA34/AA74/AA$2 | AB87: =AB34/AB74/AB$2 | AC87: =AC34/AC74/AC$2 | AD87: =AD34/AD74/AD$2 | ... AH87: =AH34/AH74/AH$2 | AI87: =AH87 | AJ87: =AI87 | AK87: =AJ87 | AL87: =AK87 | AM87: =AL87 | AN87: =AM87
A88: Fangchenggang | W88: =W35/W75/W$2 | X88: =X35/X75/X$2 | Y88: =Y35/Y75/Y$2 | Z88: =Z35/Y75/Z$2 | AA88: =AA35/Z75/AA$2 | AB88: =AB35/AA75/AB$2 | AC88: =AC35/AB75/AC$2 | AD88: =AD35/AC75/AD$2 | AE88: =AE35/AD75/AE$2 | AF88: =AF35/AE75/AF$2 | AG88: 0 | AH88: 0 | AI88: =AH88 | AJ88: =AI88 | AK88: =AJ88 | AL88: =AK88 | AM88: =AL88 | AN88: =AM88
A90: Key drivers
A91: Consolidated Capacity (MW)
A92: Operational capacity
A93: Daya Bay (n) | Q93: 1968 | R93: 1968 | S93: 1968 | T93: 1968 | U93: 1968 | V93: 1968 | W93: 1968 | X93: 1968 | Y93: 1968 | Z93: 1968 | AA93: 1968
A94: Pumped Storage (h) | Q94: 1200 | R94: 1200 | S94: 1200 | T94: 1200 | U94: 1200 | V94: 1200 | W94: 1200 | X94: 1200 | Y94: 1200 | Z94: 1200 | AA94: 1200
A95: Fangchenggang (c) | Q95: 1200 | R95: 1260 | S95: 1260 | T95: 1260 | U95: 1260 | V95: 1260 | W95: 1260 | X95: 1260 | Y95: 1260 | Z95: 2580 | AA95: 2580
A96: Shandong SZPC (c) | Q96: 3000 | R96: 3060 | S96: 3060 | T96: 3060 | U96: 3060 | V96: 3060 | W96: 3060 | X96: 3060 | Y96: 3060 | Z96: 3060 | AA96: 3060
A97: Guohua & Shenmu (c) | Q97: 2300 | R97: 5830 | S97: 5870 | T97: 7870 | U97: 7870 | V97: 7870 | W97: 7870 | X97: 7900 | Y97: 7660 | Z97: 7660 | AA97: 7690
A98: Anshun II (c) | Q98: 600 | R98: 600 | S98: 600 | T98: 0 | U98: 0 | V98: 0 | W98: 0 | X98: 0 | Y98: 0 | Z98: 0 | AA98: 0
A99: Hydro projects (h) | Q99: 106 | R99: 125 | S99: 175 | T99: 175 | U99: 505 | V99: 505 | W99: 505 | X99: 508 | Y99: 509 | Z99: 509 | AA99: 509
A100: Wind projects (w) | Q100: 141 | R100: 329 | S100: 626 | T100: 889 | U100: 989 | V100: 1036 | W100: 1084 | X100: 1133 | Y100: 1133 | Z100: 1331 | AA100: 1354
A101: Boxing Biomass | Q101: 0 | R101: 14 | S101: 14 | T101: 15 | U101: 15 | V101: 15 | W101: 0 | X101: 0 | Y101: 0 | Z101: 0 | AA101: 0
A102: CGN Wind (w) | Q102: 0 | R102: 0 | S102: 0 | T102: 1342 | U102: 1969 | V102: 2001 | W102: 1794 | X102: 1794 | Y102: 1794 | Z102: 1993 | AA102: 0
A103: Solar projects | W103: 85 | X103: =85+42 | Y103: 262 | Z103: 262 | AA103: 275
A104: Yangjiang (n) | Z104: 0 | AA104: 4344
A106: Total operational capacity | Q106: =SUM(Q93:Q105) | R106: =SUM(R93:R105) | S106: =SUM(S93:S105) | T106: =SUM(T93:T105) | U106: =SUM(U93:U105) | V106: =SUM(V93:V105) | W106: =SUM(W93:W105) | X106: =SUM(X93:X105) | ... AN106: =SUM(AN93:AN105)
...

Sheet Aus
A1: Energy Australia | B1: =Final!B2 | C1: =Final!C2 | D1: =Final!D2 | E1: =Final!E2 | F1: =Final!F2 | G1: =Final!G2 | H1: =Final!H2 | I1: =Final!I2 | ... AN1: =Final!AN2 | AR1: 2010 | AS1: 2011 | AT1: 2012 | AU1: 2013 | AV1: 2014 | AW1: 2015 | AX1: 2016 | AY1: 2017E | AZ1: 2018E | BA1: 2019E | BB1: 2020E | BC1: 2021E | BD1: 2022E
A2: HKD/AUD | I2: 5.005919 | J2: 4.5166006 | K2: 4.0330318 | L2: 4.2376917 | M2: 5.0547042 | N2: 5.7283256 | O2: 5.9287106 | P2: 5.8501471 | Q2: 6.5284702 | R2: 6.5063465 | S2: 6.0511883 | T2: =0.9204*7.7689 | U2: 8.039206 | V2: 8.035115 | W2: 7.4429 | X2: 6.9735 | Y2: 5.7897271 | Z2: 5.7615 | AA2: 5.9958 | AB2: 5.8376 | AC2: 5.4482867 | AD2: 5.362175 | AE2: 5.8392 | AF2: =1/0.1842 | AG2: =1/0.1924 | AH2: =1/0.1943 | AI2: 5.1462 | AJ2: =0.67*7.8 | AK2: =AJ2 | AL2: =AK2 | AM2: =AL2 | AN2: =AM2
AQ3: EBITDAF (recurring) | AR3: =T11 | AS3: =U11 | AT3: =V11 | AU3: =W11 | AV3: =X11 | AW3: =Y11 | AX3: =Z11 | AY3: =AA11 | ... BD3: =AF11
A4: Financial Statements | AQ4: D&A | AR4: =T13 | AS4: =U13 | AT4: =V13 | AU4: =W13 | AV4: =X13 | AW4: =Y13 | AX4: =Z13 | AY4: =AA13 | ... BD4: =AF13
A5: Revenue | N5: 2000 | O5: 8045 | P5: 13770 | Q5: 18018 | R5: 19432 | S5: 19166 | T5: 25182 | U5: 56325 | V5: 66843 | W5: 64976 | X5: 50895 | Y5: 35707 | Z5: 36441 | AA5: 45895 | AB5: 43013 | AC5: 38752 | AD5: 32357 | AE5: 32271 | AF5: 41839 | AG5: 33190 | AH5: 37097 | AI5: =AI11-AI8-AI9-AI10 | AJ5: =AJ11-AJ8-AJ9-AJ10 | AK5: =AK11-AK8-AK9-AK10 | AL5: =AL11-AL8-AL9-AL10 | AM5: =AM11-AM8-AM9-AM10 | AN5: =AN11-AN8-AN9-AN10 | AQ5: EBITF (recurring) | AR5: =T16 | AS5: =U16 | AT5: =V16 | AU5: =W16 | AV5: =X16 | AW5: =Y16 | AX5: =Z16 | AY5: =AA16 | ... BD5: =AF16
