Workbook
Name __Hub2: #REF!
Name __Hub3: #REF!
Name __Hub4: #REF!
Name __xx028: #REF!
Name __xx030: #REF!
Name __xx031: #REF!
Name __xx032: #REF!
Name __xx033: #REF!
Name __xx034: #REF!
Name __xx035: #REF!
Name __xx036: #REF!
Name __xx037: #REF!
Name __xx038: #REF!
Name __xx039: #REF!
Name __xx040: #REF!
Name __xx041: #REF!
Name __xx042: #REF!
Name __xx043: #REF!
Name __xx044: #REF!
Name __xx045: #REF!
Name __xx046: #REF!
Name __xx047: #REF!
Name __xx050: #REF!
Name __xx051: #REF!
Name __xx052: #REF!
Name __xx053: #REF!
Name __xx054: #REF!
Name __xx055: #REF!
Name __xx056: #REF!
Name __xx057: #REF!
Name __xx058: #REF!
Name __xx059: #REF!
Name __xx060: #REF!
Name __xx061: #REF!
Name __xx062: #REF!
Name __xx063: #REF!
Name __xx064: #REF!
Name __xx100: #REF!
Name __xx101: #REF!
Name __xx200: #REF!
Name __xx201: #REF!
Name __xx300: #REF!
Name __xx301: #REF!
Name __xx302: #REF!
Name __xx400: #REF!
Name __xx600: #REF!
Name _Hub2: #REF!
Name _Hub3: #REF!
Name _Hub4: #REF!
Name _Model_Path: "\\Ubsprod.msad.ubs.net\groupshares\GLOBAL\IB_RESEARCH_HKG\TRANSPORT\Ian - ASEAN Airlines\Cathay Pacific\Cathay Pacific Model Live.xlsx"
Name _xx028: #REF!
Name _xx030: #REF!
Name _xx031: #REF!
Name _xx032: #REF!
Name _xx033: #REF!
Name _xx034: #REF!
Name _xx035: #REF!
Name _xx036: #REF!
Name _xx037: #REF!
Name _xx038: #REF!

Sheet VA-Disclaimer

Sheet Valuation
A1: Valuation of Cathay Pacific (293 HK)
A2: Source: Company Data, UBS estimates
A5: Date | B5: =MAX(SharePrice!$A:$A) | AK5: =YEAR(AK4)
A6: Year to December | B6: 2020 | C6: 2021 | D6: 2022 | E6: 2023 | F6: 2024 | G6: 2025 | H6: 2026 | I6: =H6+1 | J6: =I6+1 | K6: =J6+1 | M6: Year | N6: =+CXMODEL!C3 | O6: =+CXMODEL!D3 | P6: =+CXMODEL!E3 | Q6: =+CXMODEL!F3 | R6: =+CXMODEL!G3 | S6: =+CXMODEL!H3 | T6: =+CXMODEL!I3 | U6: =+CXMODEL!J3 | ... BD6: =+CXMODEL!AS3
A7: ROE (ex pref) | B7: =AU9 | C7: =AV9 | D7: =AW9 | E7: =AX9 | F7: =AY9 | G7: =AZ9 | H7: =BA9 | I7: =BB9 | ... K7: =BD9 | M7: Net profit | N7: =+CXMODEL!C159 | O7: =+CXMODEL!D159 | P7: =+CXMODEL!E159 | Q7: =+CXMODEL!F159 | R7: =+CXMODEL!G159 | S7: =+CXMODEL!H159 | T7: =+CXMODEL!I159 | U7: =+CXMODEL!J159 | ... BD7: =+CXMODEL!AS159
A8: 2011-19 average | B8: =AVERAGE(AL9:AT9) | M8: Period-end equity (ex pref) | N8: =+CXMODEL!C215-CXMODEL!C218 | O8: =+CXMODEL!D215-CXMODEL!D218 | P8: =+CXMODEL!E215-CXMODEL!E218 | Q8: =+CXMODEL!F215-CXMODEL!F218 | R8: =+CXMODEL!G215-CXMODEL!G218 | S8: =+CXMODEL!H215-CXMODEL!H218 | T8: =+CXMODEL!I215-CXMODEL!I218 | U8: =+CXMODEL!J215-CXMODEL!J218 | ... BD8: =+CXMODEL!AS215-CXMODEL!AS218
A9: 2026-29E average | B9: =AVERAGE(H7:K7) | M9: ROE (RHS) | O9: =O7/AVERAGE(O8,N8) | P9: =P7/AVERAGE(P8,O8) | Q9: =Q7/AVERAGE(Q8,P8) | R9: =R7/AVERAGE(R8,Q8) | S9: =S7/AVERAGE(S8,R8) | T9: =T7/AVERAGE(T8,S8) | U9: =U7/AVERAGE(U8,T8) | V9: =V7/AVERAGE(V8,U8) | ... BD9: =BD7/AVERAGE(BD8,BC8)
M10: Net debt | N10: =+CXMODEL!C213 | O10: =+CXMODEL!D213 | P10: =+CXMODEL!E213 | Q10: =+CXMODEL!F213 | R10: =+CXMODEL!G213 | S10: =+CXMODEL!H213 | T10: =+CXMODEL!I213 | U10: =+CXMODEL!J213 | ... BD10: =+CXMODEL!AS213
M11: Capitalised operating leases | N11: =+CXMODEL!C214 | O11: =+CXMODEL!D214 | P11: =+CXMODEL!E214 | Q11: =+CXMODEL!F214 | R11: =+CXMODEL!G214 | S11: =+CXMODEL!H214 | T11: =+CXMODEL!I214 | U11: =+CXMODEL!J214 | ... BD11: =+CXMODEL!AS214
M12: Net debt incl. capitalised leases | N12: =+N10+N11 | O12: =+O10+O11 | P12: =+P10+P11 | Q12: =+Q10+Q11 | R12: =+R10+R11 | S12: =+S10+S11 | T12: =+T10+T11 | U12: =+U10+U11 | ... BD12: =+BD10+BD11
A13: Sustainable ROE | B13: =AVERAGE(B8,B9) | M13: Net gearing (LHS) | N13: =N12/N8 | O13: =O12/O8 | P13: =P12/P8 | Q13: =Q12/Q8 | R13: =R12/R8 | S13: =S12/S8 | T13: =T12/T8 | U13: =U12/U8 | ... BD13: =BD12/BD8
A14: Risk-free rate | B14: 0.04
A15: Equity risk premium | B15: 0.05
A16: Beta | B16: =SharePrice!$I$3
A17: COE | B17: =B14+B15*B16
A18: g | B18: 0
A19: Target Price to book (x) | B19: =(B13-B18)/(B17-B18)
A21: BV per share (HK$) | B21: =+CXMODEL!AJ221 | C21: =+CXMODEL!AK221 | D21: =+CXMODEL!AL221 | E21: =+CXMODEL!AM221 | F21: =+CXMODEL!AN221 | G21: =+CXMODEL!AO221 | H21: =+CXMODEL!AP221 | I21: =+CXMODEL!AQ221 | ... K21: =+CXMODEL!AS221
A22: DPS (HK$) | B22: =CXMODEL!AJ168 | C22: =CXMODEL!AK168 | D22: =CXMODEL!AL168 | E22: =CXMODEL!AM168 | F22: =CXMODEL!AN168 | G22: =CXMODEL!AO168 | H22: =CXMODEL!AP168 | I22: =CXMODEL!AQ168 | ... K22: =CXMODEL!AS168
A23: Time weight of 2026E BVPS | B23: =(DATE(H$6,12,31)-B$5)/(DATE(I$6,12,31)-DATE(H$6,12,31))
A24: Time weight of 2027E BVPS | B24: =1-B23
A25: NTM BVPS (HK$/sh) | B25: =B23*H21+B24*I21
A27: Price Target | B27: =ROUND(B25*B19,1)
A29: RATINGS
A30: Spot price | B30: =INDEX(SharePrice!$B:$B,MATCH(B$5,SharePrice!$A:$A,0),1,1)
A32: Upside (Downside) | B32: =+B27/B30-1
A34: Add: Dividend yield (2026E) | B34: =H22/B30
A35: Less: Market return assumption | B35: 0.08
A37: Forecast excess return | B37: =B32+B34-B35
A38: Rating | B38: =IF(B37>6%, "BUY",IF(B37<-6%,"SELL","NEUTRAL"))
A40: Previous PT (26/6/2026) | B40: 16.9
A41: PT change % | B41: =B27/B40-1
A43: Implied by spot price | E43: =E$6 | F43: =F$6 | G43: =G$6 | H43: =H$6 | I43: =I$6 | J43: =J$6 | K43: =K$6
A44: P/B | E44: =+$B$30/E$21 | F44: =+$B$30/F$21 | G44: =+$B$30/G$21 | H44: =+$B$30/H$21 | I44: =+$B$30/I$21 | J44: =+$B$30/J$21 | K44: =+$B$30/K$21
A45: EV/EBITDA | E45: =(+($B$30*CXMODEL!$AJ$170)+$BA$10)/(CXMODEL!AM133+CXMODEL!AM129) | F45: =(+($B$30*CXMODEL!$AJ$170)+$BA$10)/(CXMODEL!AN133+CXMODEL!AN129) | G45: =(+($B$30*CXMODEL!$AJ$170)+$AZ$10)/(CXMODEL!AO133+CXMODEL!AO129) | H45: =(+($B$30*CXMODEL!$AJ$170)+$BA$10)/(CXMODEL!AP133+CXMODEL!AP129) | I45: =(+($B$30*CXMODEL!$AJ$170)+$BA$10)/(CXMODEL!AQ133+CXMODEL!AQ129) | J45: =(+($B$30*CXMODEL!$AJ$170)+$BA$10)/(CXMODEL!AR133+CXMODEL!AR129) | K45: =(+($B$30*CXMODEL!$AJ$170)+$BA$10)/(CXMODEL!AS133+CXMODEL!AS129)
A46: P/E | E46: =+$B$30/CXMODEL!AM$165 | F46: =+$B$30/CXMODEL!AN$165 | G46: =+$B$30/CXMODEL!AO$165 | H46: =+$B$30/CXMODEL!AP$165 | I46: =+$B$30/CXMODEL!AQ$165 | J46: =+$B$30/CXMODEL!AR$165 | K46: =+$B$30/CXMODEL!AS$165
A47: Div Yield | E47: =E22/$B$30 | F47: =F22/$B$30 | G47: =G22/$B$30 | H47: =H22/$B$30 | I47: =I22/$B$30 | J47: =J22/$B$30 | K47: =K22/$B$30
A48: Implied by target PT | E48: =E$6 | F48: =F$6 | G48: =G$6 | H48: =H$6 | I48: =I$6 | J48: =J$6 | K48: =K$6
A49: P/B | E49: =+$B$27/E$21 | F49: =+$B$27/F$21 | G49: =+$B$27/G$21 | H49: =+$B$27/H$21 | I49: =+$B$27/I$21 | J49: =+$B$27/J$21 | K49: =+$B$27/K$21
A50: EV/EBITDA | E50: =(+($B$27*CXMODEL!$AJ$170)+$BA$10)/(CXMODEL!AM133+CXMODEL!AM129) | F50: =(+($B$27*CXMODEL!$AJ$170)+$BA$10)/(CXMODEL!AN133+CXMODEL!AN129) | G50: =(+($B$27*CXMODEL!$AJ$170)+$AZ$10)/(CXMODEL!AO133+CXMODEL!AO129) | H50: =(+($B$27*CXMODEL!$AJ$170)+$BA$10)/(CXMODEL!AP133+CXMODEL!AP129) | I50: =(+($B$27*CXMODEL!$AJ$170)+$BA$10)/(CXMODEL!AQ133+CXMODEL!AQ129) | J50: =(+($B$27*CXMODEL!$AJ$170)+$BA$10)/(CXMODEL!AR133+CXMODEL!AR129) | K50: =(+($B$27*CXMODEL!$AJ$170)+$BA$10)/(CXMODEL!AS133+CXMODEL!AS129)
A51: P/E | E51: =+$B$27/CXMODEL!AM$165 | F51: =+$B$27/CXMODEL!AN$165 | G51: =+$B$27/CXMODEL!AO$165 | H51: =+$B$27/CXMODEL!AP$165 | I51: =+$B$27/CXMODEL!AQ$165 | J51: =+$B$27/CXMODEL!AR$165 | K51: =+$B$27/CXMODEL!AS$165
A52: Div Yield | E52: =E22/$B$27 | F52: =F22/$B$27 | G52: =G22/$B$27 | H52: =H22/$B$27 | I52: =I22/$B$27 | J52: =J22/$B$27 | K52: =K22/$B$27

Sheet CXMODEL
B1: Cathay Pacific
A2: Range names | AX2: FY96 Annual Split | BB2: FY97 Annual Split | BF2: FY98 Annual Split | BJ2: FY99 Annual Split | BN2: FY00 Annual Split | BR2: FY01 Annual Split | BV2: FY02 Annual Split | BZ2: FY03 Annual Split | CD2: FY04 Annual Split | CH2: FY05 Annual Split | CL2: FY06 Annual Split | CP2: FY07 Annual Split | CS2: Restated | CU2: FY08 Annual Split | CY2: FY09 Annual Split | DC2: FY10 Annual Split | DG2: FY11 Annual Split | DK2: FY12 Annual Split | DO2: FY13 Annual Split | DS2: FY14 Annual Split | DW2: FY15 Annual Split | EA2: FY16 Annual Split | EE2: FY17 Annual Split | EI2: FY18 Annual Split | EM2: FY19 Annual Split | EQ2: FY20 Annual Split | EU2: FY21 Annual Split | EY2: FY22 Annual Split | FC2: FY23 Annual Split | FG2: FY24 Annual Split | FK2: FY26 Annual Split | FO2: FY26 Annual Split
A3: date | B3: Year to December | C3: 1987A | D3: 1988A | E3: 1989A | F3: 1990A | G3: 1991A | H3: 1992A | I3: 1993A | J3: 1994A | K3: 1995A | L3: 1996A | M3: 1997A | N3: 1998A | O3: 1999A | P3: 2000A | Q3: 2001A | R3: 2002A | S3: 2003A | T3: 2004A | U3: 2005A | V3: 2006A | W3: 2007A | X3: 2008A | Y3: 2009A | Z3: 2010A | AA3: 2011A | AB3: 2012A | AC3: 2013A | AD3: 2014A | AE3: 2015A | AF3: 2016A | AG3: 2017A | AH3: 2018A | AI3: 2019A | AJ3: 2020A | AK3: 2021A | AL3: 2022A | AM3: 2023A | AN3: 2024A | AO3: 2025E | AP3: 2026E | AQ3: 2027E | AR3: 2028E | AS3: 2029E | AT3: 2030E | AV3: 1H1996 | AW3: 2H1996 | AX3: FY1996 | AZ3: 1H1997 | BA3: 2H1997 | BB3: FY1997 | BD3: 1H1998 | BE3: 2H1998 | BF3: FY1998 | BH3: 1H1999 | BI3: 2H1999 | BJ3: FY1999 | BL3: 1H2000 | BM3: 2H2000 | BN3: FY2000 | BP3: 1H2001A | BQ3: 2H2001A | BR3: FY2001A | BT3: 1H2002A | BU3: 2H2002A | BV3: FY2002A | BX3: 1H2003A | BY3: 2H2003A | BZ3: FY2003A | CB3: 1H2004A | CC3: 2H2004A | CD3: FY2004A | CF3: 1H2005A | CG3: 2H2005A | CH3: FY2005A | CJ3: 1H2006A | CK3: 2H2006A | CL3: FY2006A | CN3: 1H2007A | CO3: 2H2007A | CP3: FY2007A | CR3: 1H2008A | CS3: 1H2008A | CT3: 2H2008E | CU3: FY2008E | CW3: 1H2009A | CX3: 2H2009A | CY3: FY2009A | DA3: 1H2010A | DB3: 2H2010A | DC3: FY2010A | DE3: 1H2011A | DF3: 2H2011A | DG3: FY2011A | DI3: 1H2012A | DJ3: 2H2012A | DK3: FY2012E | DM3: 1H2013A | DN3: 2H2013A | DO3: FY2013A | DQ3: 1H2014A | DR3: 2H2014A | DS3: FY2014A | DU3: 1H2015A | DV3: 2H2015A | DW3: FY2015A | DY3: 1H2016A | DZ3: 2H2016A | EA3: FY2016A | EC3: 1H2017A | ED3: 2H2017A | EE3: FY2017A | EG3: 1H2018A | EH3: 2H2018A | EI3: =AH3 | EK3: 1H2019A | EL3: 2H2019A | EM3: =AI3 | EO3: 1H2020A | EP3: 2H2020A | EQ3: =AJ3 | ES3: 1H2021A | ET3: 2H2021A | EU3: =AK3 | EW3: 1H2022A | EX3: 2H2022A | EY3: =AL3 | FA3: 1H2023A | FB3: 2H2023A | FC3: =AM3 | FE3: 1H2024A | FF3: 2H2024A | FG3: =AN3 | FI3: 1H2025A | FJ3: 2H2025A | FK3: =AO3 | FM3: 1H2026A | FN3: 2H2026E | FO3: =AP3
A4: atk | B4: atk | C4: 3751 | D4: 4353 | E4: 4753 | F4: 5429 | G4: 5621 | H4: 6466 | I4: 7212 | J4: 8052 | K4: 8946 | L4: 10018 | M4: 10399 | N4: 10857 | O4: 10867 | P4: 11630.254 | Q4: 12335.052 | R4: 12820.27 | S4: 13355 | T4: 15794 | U4: 17751.456 | V4: 19684 | W4: 23077.462 | X4: 24409.874 | Y4: 22249 | Z4: 24461 | AA4: 26383.685 | AB4: 26249.947 | AC4: 26259.191 | AD4: 28440 | AE4: 30047.974 | AF4: 30462.325 | AG4: 31438.522 | AH4: 32387.156 | AI4: 33077.043 | AJ4: 14620 | AK4: 11354 | AL4: 10100 | AM4: 21225 | AN4: 24836 | AO4: =+AO52+AO22*0.09 | AP4: =+AP52+AP22*0.09 | AQ4: =+AQ52+AQ22*0.09 | AR4: =+AR52+AR22*0.09 | AS4: =+AS52+AS22*0.09 | AT4: =+AT52+AT22*0.09 | AV4: 4752 | AW4: =AX4-AV4 | AX4: =L4 | AZ4: 5074 | BA4: =BB4-AZ4 | BB4: =M4 | BD4: 5208 | BE4: =BF4-BD4 | BF4: =N4 | BH4: 5267 | BI4: =BJ4-BH4 | BJ4: =O4 | BL4: 5482.507 | BM4: =BN4-BL4 | BN4: =P4 | BP4: 5936 | BQ4: =BR4-BP4 | BR4: =Q4 | BT4: 5750 | BU4: =BV4-BT4 | BV4: =R4 | BX4: 6086.99 | BY4: =BZ4-BX4 | BZ4: =S4 | CB4: 7493.4 | CC4: =CD4-CB4 | CD4: =T4 | CF4: 8446 | CG4: =CH4-CF4 | CH4: =U4 | CJ4: 9125.674 | CK4: =CL4-CJ4 | CL4: =V4 | CN4: 10975 | CO4: =CP4-CN4 | CP4: =W4 | CR4: 12080.723 | CS4: 12080.723 | CT4: =CU4-CR4 | CU4: =X4 | CW4: 11034.701 | CX4: =CY4-CW4 | CY4: =Y4 | CZ4: =1-8.7 | DA4: 11435.63 | DB4: =+DC4-DA4 | DC4: =Z4 | DE4: 12846.427 | DF4: =+DG4-DE4 | DG4: =AA4 | DI4: 12943.769 | DJ4: =+DK4-DI4 | DK4: =AB4 | DM4: 12520.226 | DN4: =+DO4-DM4 | DO4: =AC4 | DQ4: 13544.749 | DR4: =+DS4-DQ4 | DS4: =AD4 | DU4: 14598 | DV4: =+DW4-DU4 | DW4: =AE4 | DY4: 14928.859 | DZ4: =+EA4-DY4 | EA4: =AF4 | EC4: 15189.63 | ED4: =+EE4-EC4 | EE4: =AG4 | EG4: 15746.849 | EH4: =+EI4-EG4 | EI4: =AH4 | EK4: 16317.62 | EL4: =+EM4-EK4 | EM4: =AI4 | EO4: 8594.749 | EP4: =+EQ4-EO4 | EQ4: =AJ4 | ES4: 4454 | ET4: =+EU4-ES4 | EU4: =AK4 | EW4: 3094 | EX4: =+EY4-EW4 | EY4: =AL4 | FA4: 9628 | FB4: =+FC4-FA4 | FC4: =AM4 | FE4: 11822 | FF4: =+FG4-FE4 | FG4: =AN4 | FI4: 13699 | FJ4: =+FK4-FI4 | FK4: =AO4 | FM4: 14739 | FN4: =+FN52+FN22*0.09 | FO4: =AP4
A5: capacity growth | B5: Change in overall capacity (ATK) | D5: =D4/C4-1 | E5: =E4/D4-1 | F5: =F4/E4-1 | G5: =G4/F4-1 | H5: =H4/G4-1 | I5: =I4/H4-1 | J5: =J4/I4-1 | K5: =K4/J4-1 | L5: =0.1198 | M5: =M4/L4-1 | N5: =N4/M4-1 | O5: =O4/N4-1 | P5: =P4/O4-1 | Q5: =Q4/P4-1 | R5: =R4/Q4-1 | S5: =S4/R4-1 | T5: =T4/S4-1 | ... AK5: =AK4/AJ4-1 | AL5: =+AL4/AK4-1 | AM5: =+AM4/AL4-1 | AN5: =+AN4/AM4-1 | AO5: =+AO4/AN4-1 | AP5: =+AP4/AO4-1 | AQ5: =+AQ4/AP4-1 | AR5: =+AR4/AQ4-1 | AS5: =+AS4/AR4-1 | AT5: =+AT4/AS4-1 | AX5: =L5 | AZ5: =AZ4/AV4-1 | BA5: =BA4/AW4-1 | BB5: =M5 | BD5: =BD4/AZ4-1 | BE5: =BE4/BA4-1 | BF5: =N5 | BH5: =BH4/BD4-1 | BI5: =BI4/BE4-1 | BJ5: =O5 | BL5: =BL4/BH4-1 | BM5: =BM4/BI4-1 | BN5: =P5 | BP5: =BP4/BL4-1 | BQ5: =BQ4/BM4-1 | BR5: =Q5 | BT5: =BT4/BP4-1 | BU5: =BU4/BQ4-1 | BV5: =R5 | BX5: =BX4/BT4-1 | BY5: =BY4/BU4-1 | BZ5: =S5 | CB5: =CB4/BX4-1 | CC5: =CC4/BY4-1 | CD5: =T5 | CF5: =CF4/CB4-1 | CG5: =CG4/CC4-1 | CH5: =U5 | CJ5: =CJ4/CF4-1 | CK5: =CK4/CG4-1 | CL5: =V5 | CN5: =CN4/CJ4-1 | CO5: =CO4/CK4-1 | CP5: =W5 | CR5: =CR4/CN4-1 | CS5: =CS4/CN4-1 | CT5: =CT4/CO4-1 | CU5: =X5 | CW5: =CW4/CS4-1 | CX5: =CX4/CT4-1 | CY5: =Y5 | DA5: =DA4/CW4-1 | DB5: =DB4/CX4-1 | DC5: =Z5 | DE5: =DE4/DA4-1 | DF5: =DF4/DB4-1 | DG5: =AA5 | DI5: =+DI4/DE4-1 | DJ5: =DJ4/DF4-1 | DK5: =AB5 | DM5: =+DM4/DI4-1 | DN5: =DN4/DJ4-1 | DO5: =AC5 | DQ5: =+DQ4/DM4-1 | DR5: =+DR4/DN4-1 | DS5: =AD5 | DU5: =+DU4/DQ4-1 | DV5: =+DV4/DR4-1 | DW5: =AE5 | DY5: =+DY4/DU4-1 | DZ5: =+DZ4/DV4-1 | EA5: =AF5 | EC5: =+EC4/DY4-1 | ED5: =+ED4/DZ4-1 | EE5: =AG5 | EG5: =+EG4/EC4-1 | EH5: =+EH4/ED4-1 | EI5: =AH5 | EK5: =+EK4/EG4-1 | EL5: =+EL4/EH4-1 | EM5: =AI5 | EO5: =+EO4/EK4-1 | EP5: =+EP4/EL4-1 | EQ5: =+EQ4/EM4-1 | ES5: =+ES4/EO4-1 | ET5: =+ET4/EP4-1 | EU5: =+EU4/EQ4-1 | EW5: =+EW4/ES4-1 | EX5: =+EX4/ET4-1 | EY5: =+EY4/EU4-1 | FA5: =+FA4/EW4-1 | FB5: =+FB4/EX4-1 | FC5: =+FC4/EY4-1 | FE5: =+FE4/FA4-1 | FF5: =+FF4/FB4-1 | FG5: =+FG4/FC4-1 | FI5: =+FI4/FE4-1 | FJ5: =+FJ4/FF4-1 | FK5: =+FK4/FG4-1 | FM5: =+FM4/FI4-1 | FN5: =+FN4/FJ4-1 | FO5: =+FO4/FK4-1
B7: Overall ask | C7: =+C22+C37 | D7: =+D22+D37 | E7: =+E22+E37 | F7: =+F22+F37 | G7: =+G22+G37 | H7: =+H22+H37 | I7: =+I22+I37 | J7: =+J22+J37 | ... AT7: =+AT22+AT37 | BD7: =+BD22+BD37 | BE7: =+BE22+BE37 | BF7: =+BF22+BF37 | BH7: =+BH22+BH37 | BI7: =+BI22+BI37 | BJ7: =+BJ22+BJ37 | BL7: =+BL22+BL37 | BM7: =+BM22+BM37 | BN7: =+BN22+BN37 | BP7: =+BP22+BP37 | BQ7: =+BQ22+BQ37 | BR7: =+BR22+BR37 | BT7: =+BT22+BT37 | BU7: =+BU22+BU37 | BV7: =+BV22+BV37 | BX7: =+BX22+BX37 | BY7: =+BY22+BY37 | BZ7: =+BZ22+BZ37 | CB7: =+CB22+CB37 | CC7: =+CC22+CC37 | CD7: =+CD22+CD37 | CF7: =+CF22+CF37 | CG7: =+CG22+CG37 | CH7: =+CH22+CH37 | CJ7: =+CJ22+CJ37 | CK7: =+CK22+CK37 | CL7: =+CL22+CL37 | CN7: =+CN22+CN37 | CO7: =+CO22+CO37 | CP7: =+CP22+CP37 | CR7: =+CR22+CR37 | CS7: =+CS22+CS37 | CT7: =+CT22+CT37 | CU7: =+CU22+CU37 | CW7: =+CW22+CW37 | CX7: =+CX22+CX37 | CY7: =+CY22+CY37 | DA7: =+DA22+DA37 | DB7: =+DB22+DB37 | DC7: =+DC22+DC37 | DE7: =+DE22+DE37 | DF7: =+DF22+DF37 | DG7: =+DG22+DG37 | DI7: =+DI22+DI37 | DJ7: =+DJ22+DJ37 | DK7: =+DK22+DK37 | DM7: =+DM22+DM37 | DN7: =+DN22+DN37 | DO7: =+DO22+DO37 | DQ7: =+DQ22+DQ37 | DR7: =+DR22+DR37 | DS7: =+DS22+DS37 | DU7: =+DU22+DU37 | DV7: =+DV22+DV37 | DW7: =+DW22+DW37 | DY7: =+DY22+DY37 | DZ7: =+DZ22+DZ37 | EA7: =+EA22+EA37 | EC7: =+EC22+EC37 | ED7: =+ED22+ED37 | EE7: =+EE22+EE37 | EG7: =+EG22+EG37 | EH7: =+EH22+EH37 | EI7: =+EI22+EI37 | EK7: =+EK22+EK37 | EL7: =+EL22+EL37 | EM7: =+EM22+EM37 | EO7: =+EO22+EO37 | EP7: =+EP22+EP37 | EQ7: =+EQ22+EQ37 | ES7: =+ES22+ES37 | ET7: =+ET22+ET37 | EU7: =+EU22+EU37 | EW7: =+EW22+EW37 | EX7: =+EX22+EX37 | EY7: =+EY22+EY37 | FA7: =+FA22+FA37 | FB7: =+FB22+FB37 | FC7: =+FC22+FC37 | FE7: =+FE22+FE37 | FF7: =+FF22+FF37 | FG7: =+FG22+FG37 | FI7: =+FI22+FI37 | FJ7: =+FJ22+FJ37 | FK7: =+FK22+FK37 | FM7: =+FM22+FM37 | FN7: =+FN22+FN37 | FO7: =+FO22+FO37
B8: YoY change in overall capacity (ASK) | D8: =D7/C7-1 | E8: =E7/D7-1 | F8: =F7/E7-1 | G8: =G7/F7-1 | H8: =H7/G7-1 | I8: =I7/H7-1 | J8: =J7/I7-1 | K8: =K7/J7-1 | ... AT8: =AT7/AS7-1 | BH8: =BH7/BD7-1 | BI8: =BI7/BE7-1 | BJ8: =BJ7/BF7-1 | BL8: =BL7/BH7-1 | BM8: =BM7/BI7-1 | BN8: =BN7/BJ7-1 | BP8: =BP7/BL7-1 | BQ8: =BQ7/BM7-1 | BR8: =BR7/BN7-1 | BT8: =BT7/BP7-1 | BU8: =BU7/BQ7-1 | BV8: =BV7/BR7-1 | BX8: =BX7/BT7-1 | BY8: =BY7/BU7-1 | BZ8: =BZ7/BV7-1 | CB8: =CB7/BX7-1 | CC8: =CC7/BY7-1 | CD8: =CD7/BZ7-1 | CF8: =CF7/CB7-1 | CG8: =CG7/CC7-1 | CH8: =CH7/CD7-1 | CJ8: =CJ7/CF7-1 | CK8: =CK7/CG7-1 | CL8: =CL7/CH7-1 | CN8: =CN7/CJ7-1 | CO8: =CO7/CK7-1 | CP8: =CP7/CL7-1 | CR8: =CR7/CN7-1 | CS8: =CS7/CN7-1 | CT8: =CT7/CO7-1 | CU8: =CU7/CP7-1 | CW8: =CW7/CS7-1 | CX8: =CX7/CT7-1 | CY8: =CY7/CU7-1 | DA8: =DA7/CW7-1 | DB8: =DB7/CX7-1 | DC8: =DC7/CY7-1 | DE8: =DE7/DA7-1 | DF8: =DF7/DB7-1 | DG8: =DG7/DC7-1 | DI8: =DI7/DE7-1 | DJ8: =DJ7/DF7-1 | DK8: =DK7/DG7-1 | DM8: =DM7/DI7-1 | DN8: =DN7/DJ7-1 | DO8: =DO7/DK7-1 | DQ8: =DQ7/DM7-1 | DR8: =DR7/DN7-1 | DS8: =DS7/DO7-1 | DU8: =DU7/DQ7-1 | DV8: =DV7/DR7-1 | DW8: =DW7/DS7-1 | DY8: =DY7/DU7-1 | DZ8: =DZ7/DV7-1 | EA8: =EA7/DW7-1 | EC8: =EC7/DY7-1 | ED8: =ED7/DZ7-1 | EE8: =EE7/EA7-1 | EG8: =EG7/EC7-1 | EH8: =EH7/ED7-1 | EI8: =EI7/EE7-1 | EK8: =EK7/EG7-1 | EL8: =EL7/EH7-1 | EM8: =EM7/EI7-1 | EO8: =EO7/EK7-1 | EP8: =EP7/EL7-1 | EQ8: =EQ7/EM7-1 | ES8: =ES7/EO7-1 | ET8: =ET7/EP7-1 | EU8: =EU7/EQ7-1 | EW8: =EW7/ES7-1 | EX8: =EX7/ET7-1 | EY8: =EY7/EU7-1 | FA8: =FA7/EW7-1 | FB8: =FB7/EX7-1 | FC8: =FC7/EY7-1 | FE8: =FE7/FA7-1 | FF8: =FF7/FB7-1 | FG8: =FG7/FC7-1 | FI8: =FI7/FE7-1 | FJ8: =FJ7/FF7-1 | FK8: =FK7/FG7-1 | FM8: =FM7/FI7-1 | FN8: =FN7/FJ7-1 | FO8: =FO7/FK7-1
B9: Overall rpk | C9: =+C24+C39 | D9: =+D24+D39 | E9: =+E24+E39 | F9: =+F24+F39 | G9: =+G24+G39 | H9: =+H24+H39 | I9: =+I24+I39 | J9: =+J24+J39 | ... AT9: =+AT24+AT39 | BD9: =+BD24+BD39 | BE9: =+BE24+BE39 | BF9: =+BF24+BF39 | BH9: =+BH24+BH39 | BI9: =+BI24+BI39 | BJ9: =+BJ24+BJ39 | BL9: =+BL24+BL39 | BM9: =+BM24+BM39 | BN9: =+BN24+BN39 | BP9: =+BP24+BP39 | BQ9: =+BQ24+BQ39 | BR9: =+BR24+BR39 | BT9: =+BT24+BT39 | BU9: =+BU24+BU39 | BV9: =+BV24+BV39 | BX9: =+BX24+BX39 | BY9: =+BY24+BY39 | BZ9: =+BZ24+BZ39 | CB9: =+CB24+CB39 | CC9: =+CC24+CC39 | CD9: =+CD24+CD39 | CF9: =+CF24+CF39 | CG9: =+CG24+CG39 | CH9: =+CH24+CH39 | CJ9: =+CJ24+CJ39 | CK9: =+CK24+CK39 | CL9: =+CL24+CL39 | CN9: =+CN24+CN39 | CO9: =+CO24+CO39 | CP9: =+CP24+CP39 | CR9: =+CR24+CR39 | CS9: =+CS24+CS39 | CT9: =+CT24+CT39 | CU9: =+CU24+CU39 | CW9: =+CW24+CW39 | CX9: =+CX24+CX39 | CY9: =+CY24+CY39 | DA9: =+DA24+DA39 | DB9: =+DB24+DB39 | DC9: =+DC24+DC39 | DE9: =+DE24+DE39 | DF9: =+DF24+DF39 | DG9: =+DG24+DG39 | DI9: =+DI24+DI39 | DJ9: =+DJ24+DJ39 | DK9: =+DK24+DK39 | DM9: =+DM24+DM39 | DN9: =+DN24+DN39 | DO9: =+DO24+DO39 | DQ9: =+DQ24+DQ39 | DR9: =+DR24+DR39 | DS9: =+DS24+DS39 | DU9: =+DU24+DU39 | DV9: =+DV24+DV39 | DW9: =+DW24+DW39 | DY9: =+DY24+DY39 | DZ9: =+DZ24+DZ39 | EA9: =+EA24+EA39 | EC9: =+EC24+EC39 | ED9: =+ED24+ED39 | EE9: =+EE24+EE39 | EG9: =+EG24+EG39 | EH9: =+EH24+EH39 | EI9: =+EI24+EI39 | EK9: =+EK24+EK39 | EL9: =+EL24+EL39 | EM9: =+EM24+EM39 | EO9: =+EO24+EO39 | EP9: =+EP24+EP39 | EQ9: =+EQ24+EQ39 | ES9: =+ES24+ES39 | ET9: =+ET24+ET39 | EU9: =+EU24+EU39 | EW9: =+EW24+EW39 | EX9: =+EX24+EX39 | EY9: =+EY24+EY39 | FA9: =+FA24+FA39 | FB9: =+FB24+FB39 | FC9: =+FC24+FC39 | FE9: =+FE24+FE39 | FF9: =+FF24+FF39 | FG9: =+FG24+FG39 | FI9: =+FI24+FI39 | FJ9: =+FJ24+FJ39 | FK9: =+FK24+FK39 | FM9: =+FM24+FM39 | FN9: =+FN24+FN39 | FO9: =+FO24+FO39
B10: YoY change in passenger traffic (RPK) | D10: =D9/C9-1 | E10: =E9/D9-1 | F10: =F9/E9-1 | G10: =G9/F9-1 | H10: =H9/G9-1 | I10: =I9/H9-1 | J10: =J9/I9-1 | K10: =K9/J9-1 | ... AT10: =AT9/AS9-1 | BH10: =BH9/BD9-1 | BI10: =BI9/BE9-1 | BJ10: =BJ9/BF9-1 | BL10: =BL9/BH9-1 | BM10: =BM9/BI9-1 | BN10: =BN9/BJ9-1 | BP10: =BP9/BL9-1 | BQ10: =BQ9/BM9-1 | BR10: =BR9/BN9-1 | BT10: =BT9/BP9-1 | BU10: =BU9/BQ9-1 | BV10: =BV9/BR9-1 | BX10: =BX9/BT9-1 | BY10: =BY9/BU9-1 | BZ10: =BZ9/BV9-1 | CB10: =CB9/BX9-1 | CC10: =CC9/BY9-1 | CD10: =CD9/BZ9-1 | CF10: =CF9/CB9-1 | CG10: =CG9/CC9-1 | CH10: =CH9/CD9-1 | CJ10: =CJ9/CF9-1 | CK10: =CK9/CG9-1 | CL10: =CL9/CH9-1 | CN10: =CN9/CJ9-1 | CO10: =CO9/CK9-1 | CP10: =CP9/CL9-1 | CR10: =CR9/CN9-1 | CS10: =CS9/CN9-1 | CT10: =CT9/CO9-1 | CU10: =CU9/CP9-1 | CW10: =CW9/CS9-1 | CX10: =CX9/CT9-1 | CY10: =CY9/CU9-1 | DA10: =DA9/CW9-1 | DB10: =DB9/CX9-1 | DC10: =DC9/CY9-1 | DE10: =DE9/DA9-1 | DF10: =DF9/DB9-1 | DG10: =DG9/DC9-1 | DI10: =DI9/DE9-1 | DJ10: =DJ9/DF9-1 | DK10: =DK9/DG9-1 | DM10: =DM9/DI9-1 | DN10: =DN9/DJ9-1 | DO10: =DO9/DK9-1 | DQ10: =DQ9/DM9-1 | DR10: =DR9/DN9-1 | DS10: =DS9/DO9-1 | DU10: =DU9/DQ9-1 | DV10: =DV9/DR9-1 | DW10: =DW9/DS9-1 | DY10: =DY9/DU9-1 | DZ10: =DZ9/DV9-1 | EA10: =EA9/DW9-1 | EC10: =EC9/DY9-1 | ED10: =ED9/DZ9-1 | EE10: =EE9/EA9-1 | EG10: =EG9/EC9-1 | EH10: =EH9/ED9-1 | EI10: =EI9/EE9-1 | EK10: =EK9/EG9-1 | EL10: =EL9/EH9-1 | EM10: =EM9/EI9-1 | EO10: =EO9/EK9-1 | EP10: =EP9/EL9-1 | EQ10: =EQ9/EM9-1 | ES10: =ES9/EO9-1 | ET10: =ET9/EP9-1 | EU10: =EU9/EQ9-1 | EW10: =EW9/ES9-1 | EX10: =EX9/ET9-1 | EY10: =EY9/EU9-1 | FA10: =FA9/EW9-1 | FB10: =FB9/EX9-1 | FC10: =FC9/EY9-1 | FE10: =FE9/FA9-1 | FF10: =FF9/FB9-1 | FG10: =FG9/FC9-1 | FI10: =FI9/FE9-1 | FJ10: =FJ9/FF9-1 | FK10: =FK9/FG9-1 | FM10: =FM9/FI9-1 | FN10: =FN9/FJ9-1 | FO10: =FO9/FK9-1
B11: Overall Passenger nos (000s) | C11: =+C26+C41 | D11: =+D26+D41 | E11: =+E26+E41 | F11: =+F26+F41 | G11: =+G26+G41 | H11: =+H26+H41 | I11: =+I26+I41 | J11: =+J26+J41 | ... AT11: =+AT26+AT41 | BF11: =+BF26+BF41 | BH11: =+BH26+BH41 | BI11: =+BI26+BI41 | BJ11: =+BJ26+BJ41 | BL11: =+BL26+BL41 | BM11: =+BM26+BM41 | BN11: =+BN26+BN41 | BP11: =+BP26+BP41 | BQ11: =+BQ26+BQ41 | BR11: =+BR26+BR41 | BT11: =+BT26+BT41 | BU11: =+BU26+BU41 | BV11: =+BV26+BV41 | BX11: =+BX26+BX41 | BY11: =+BY26+BY41 | BZ11: =+BZ26+BZ41 | CB11: =+CB26+CB41 | CC11: =+CC26+CC41 | CD11: =+CD26+CD41 | CF11: =+CF26+CF41 | CG11: =+CG26+CG41 | CH11: =+CH26+CH41 | CJ11: =+CJ26+CJ41 | CK11: =+CK26+CK41 | CL11: =+CL26+CL41 | CN11: =+CN26+CN41 | CO11: =+CO26+CO41 | CP11: =+CP26+CP41 | CR11: =+CR26+CR41 | CS11: =+CS26+CS41 | CT11: =+CT26+CT41 | CU11: =+CU26+CU41 | CW11: =+CW26+CW41 | CX11: =+CX26+CX41 | CY11: =+CY26+CY41 | DA11: =+DA26+DA41 | DB11: =+DB26+DB41 | DC11: =+DC26+DC41 | DE11: =+DE26+DE41 | DF11: =+DF26+DF41 | DG11: =+DG26+DG41 | DI11: =+DI26+DI41 | DJ11: =+DJ26+DJ41 | DK11: =+DK26+DK41 | DM11: =+DM26+DM41 | DN11: =+DN26+DN41 | DO11: =+DO26+DO41 | DQ11: =+DQ26+DQ41 | DR11: =+DR26+DR41 | DS11: =+DS26+DS41 | DU11: =+DU26+DU41 | DV11: =+DV26+DV41 | DW11: =+DW26+DW41 | DY11: =+DY26+DY41 | DZ11: =+DZ26+DZ41 | EA11: =+EA26+EA41 | EC11: =+EC26+EC41 | ED11: =+ED26+ED41 | EE11: =+EE26+EE41 | EG11: =+EG26+EG41 | EH11: =+EH26+EH41 | EI11: =+EI26+EI41 | EK11: =+EK26+EK41 | EL11: =+EL26+EL41 | EM11: =+EM26+EM41 | EO11: =+EO26+EO41 | EP11: =+EP26+EP41 | EQ11: =+EQ26+EQ41 | ES11: =+ES26+ES41 | ET11: =+ET26+ET41 | EU11: =+EU26+EU41 | EW11: =+EW26+EW41 | EX11: =+EX26+EX41 | EY11: =+EY26+EY41 | FA11: =+FA26+FA41 | FB11: =+FB26+FB41 | FC11: =+FC26+FC41 | FE11: =+FE26+FE41 | FF11: =+FF26+FF41 | FG11: =+FG26+FG41 | FI11: =+FI26+FI41 | FJ11: =+FJ26+FJ41 | FK11: =+FK26+FK41 | FM11: =+FM26+FM41 | FN11: =+FN26+FN41 | FO11: =+FO26+FO41
B12: Overall Trip length (kms) | C12: =C9/C11*1000 | D12: =D9/D11*1000 | E12: =E9/E11*1000 | F12: =F9/F11*1000 | G12: =G9/G11*1000 | H12: =H9/H11*1000 | I12: =I9/I11*1000 | J12: =J9/J11*1000 | ... AT12: =AT9/AT11*1000 | BF12: =BF9/BF11*1000 | BH12: =BH9/BH11*1000 | BI12: =BI9/BI11*1000 | BJ12: =BJ9/BJ11*1000 | BL12: =BL9/BL11*1000 | BM12: =BM9/BM11*1000 | BN12: =BN9/BN11*1000 | BP12: =BP9/BP11*1000 | BQ12: =BQ9/BQ11*1000 | BR12: =BR9/BR11*1000 | BT12: =BT9/BT11*1000 | BU12: =BU9/BU11*1000 | BV12: =BV9/BV11*1000 | BX12: =BX9/BX11*1000 | BY12: =BY9/BY11*1000 | BZ12: =BZ9/BZ11*1000 | CB12: =CB9/CB11*1000 | CC12: =CC9/CC11*1000 | CD12: =CD9/CD11*1000 | CF12: =CF9/CF11*1000 | CG12: =CG9/CG11*1000 | CH12: =CH9/CH11*1000 | CJ12: =CJ9/CJ11*1000 | CK12: =CK9/CK11*1000 | CL12: =CL9/CL11*1000 | CN12: =CN9/CN11*1000 | CO12: =CO9/CO11*1000 | CP12: =CP9/CP11*1000 | CR12: =CR9/CR11*1000 | CS12: =CS9/CS11*1000 | CT12: =CT9/CT11*1000 | CU12: =CU9/CU11*1000 | CW12: =CW9/CW11*1000 | CX12: =CX9/CX11*1000 | CY12: =CY9/CY11*1000 | DA12: =DA9/DA11*1000 | DB12: =DB9/DB11*1000 | DC12: =DC9/DC11*1000 | DE12: =DE9/DE11*1000 | DF12: =DF9/DF11*1000 | DG12: =DG9/DG11*1000 | DI12: =DI9/DI11*1000 | DJ12: =DJ9/DJ11*1000 | DK12: =DK9/DK11*1000 | DM12: =DM9/DM11*1000 | DN12: =DN9/DN11*1000 | DO12: =DO9/DO11*1000 | DQ12: =DQ9/DQ11*1000 | DR12: =DR9/DR11*1000 | DS12: =DS9/DS11*1000 | DU12: =DU9/DU11*1000 | DV12: =DV9/DV11*1000 | DW12: =DW9/DW11*1000 | DY12: =DY9/DY11*1000 | DZ12: =DZ9/DZ11*1000 | EA12: =EA9/EA11*1000 | EC12: =EC9/EC11*1000 | ED12: =ED9/ED11*1000 | EE12: =EE9/EE11*1000 | EG12: =EG9/EG11*1000 | EH12: =EH9/EH11*1000 | EI12: =EI9/EI11*1000 | EK12: =EK9/EK11*1000 | EL12: =EL9/EL11*1000 | EM12: =EM9/EM11*1000 | EO12: =EO9/EO11*1000 | EP12: =EP9/EP11*1000 | EQ12: =EQ9/EQ11*1000 | ES12: =ES9/ES11*1000 | ET12: =ET9/ET11*1000 | EU12: =EU9/EU11*1000 | EW12: =EW9/EW11*1000 | EX12: =EX9/EX11*1000 | EY12: =EY9/EY11*1000 | FA12: =FA9/FA11*1000 | FB12: =FB9/FB11*1000 | FC12: =FC9/FC11*1000 | FE12: =FE9/FE11*1000 | FF12: =FF9/FF11*1000 | FG12: =FG9/FG11*1000 | FI12: =FI9/FI11*1000 | FJ12: =FJ9/FJ11*1000 | FK12: =FK9/FK11*1000 | FM12: =FM9/FM11*1000 | FN12: =FN9/FN11*1000 | FO12: =FO9/FO11*1000
B13: Overall Passenger load factor | C13: =C9/C7 | D13: =D9/D7 | E13: =E9/E7 | F13: =F9/F7 | G13: =G9/G7 | H13: =H9/H7 | I13: =I9/I7 | J13: =J9/J7 | ... AT13: =AT9/AT7 | BD13: =BD9/BD7 | BE13: =BE9/BE7 | BF13: =BF9/BF7 | BH13: =BH9/BH7 | BI13: =BI9/BI7 | BJ13: =BJ9/BJ7 | BL13: =BL9/BL7 | BM13: =BM9/BM7 | BN13: =BN9/BN7 | BP13: =BP9/BP7 | BQ13: =BQ9/BQ7 | BR13: =BR9/BR7 | BT13: =BT9/BT7 | BU13: =BU9/BU7 | BV13: =BV9/BV7 | BX13: =BX9/BX7 | BY13: =BY9/BY7 | BZ13: =BZ9/BZ7 | CB13: =CB9/CB7 | CC13: =CC9/CC7 | CD13: =CD9/CD7 | CF13: =CF9/CF7 | CG13: =CG9/CG7 | CH13: =CH9/CH7 | CJ13: =CJ9/CJ7 | CK13: =CK9/CK7 | CL13: =CL9/CL7 | CN13: =CN9/CN7 | CO13: =CO9/CO7 | CP13: =CP9/CP7 | CR13: =CR9/CR7 | CS13: =CS9/CS7 | CT13: =CT9/CT7 | CU13: =CU9/CU7 | CW13: =CW9/CW7 | CX13: =CX9/CX7 | CY13: =CY9/CY7 | DA13: =DA9/DA7 | DB13: =DB9/DB7 | DC13: =DC9/DC7 | DE13: =DE9/DE7 | DF13: =DF9/DF7 | DG13: =DG9/DG7 | DI13: =DI9/DI7 | DJ13: =DJ9/DJ7 | DK13: =DK9/DK7 | DM13: =DM9/DM7 | DN13: =DN9/DN7 | DO13: =DO9/DO7 | DQ13: =DQ9/DQ7 | DR13: =DR9/DR7 | DS13: =DS9/DS7 | DU13: =DU9/DU7 | DV13: =DV9/DV7 | DW13: =DW9/DW7 | DY13: =DY9/DY7 | DZ13: =DZ9/DZ7 | EA13: =EA9/EA7 | EC13: =EC9/EC7 | ED13: =ED9/ED7 | EE13: =EE9/EE7 | EG13: =EG9/EG7 | EH13: =EH9/EH7 | EI13: =EI9/EI7 | EK13: =EK9/EK7 | EL13: =EL9/EL7 | EM13: =EM9/EM7 | EO13: =EO9/EO7 | EP13: =EP9/EP7 | EQ13: =EQ9/EQ7 | ES13: =ES9/ES7 | ET13: =ET9/ET7 | EU13: =EU9/EU7 | EW13: =EW9/EW7 | EX13: =EX9/EX7 | EY13: =EY9/EY7 | FA13: =FA9/FA7 | FB13: =FB9/FB7 | FC13: =FC9/FC7 | FE13: =FE9/FE7 | FF13: =FF9/FF7 | FG13: =FG9/FG7 | FI13: =FI9/FI7 | FJ13: =FJ9/FJ7 | FK13: =FK9/FK7 | FM13: =FM9/FM7 | FN13: =FN9/FN7 | FO13: =FO9/FO7
B14: Overall pax yield | C14: =C20/C9 | D14: =D20/D9 | E14: =E20/E9 | F14: =F20/F9 | G14: =G20/G9 | H14: =H20/H9 | I14: =I20/I9 | J14: =J20/J9 | ... AT14: =AT20/AT9 | BD14: =BD20/BD9 | BE14: =BE20/BE9 | BF14: =BF20/BF9 | BH14: =BH20/BH9 | BI14: =BI20/BI9 | BJ14: =BJ20/BJ9 | BL14: =BL20/BL9 | BM14: =BM20/BM9 | BN14: =BN20/BN9 | BP14: =BP20/BP9 | BQ14: =BQ20/BQ9 | BR14: =BR20/BR9 | BT14: =BT20/BT9 | BU14: =BU20/BU9 | BV14: =BV20/BV9 | BX14: =BX20/BX9 | BY14: =BY20/BY9 | BZ14: =BZ20/BZ9 | CB14: =CB20/CB9 | CC14: =CC20/CC9 | CD14: =CD20/CD9 | CF14: =CF20/CF9 | CG14: =CG20/CG9 | CH14: =CH20/CH9 | CJ14: =CJ20/CJ9 | CK14: =CK20/CK9 | CL14: =CL20/CL9 | CN14: =CN20/CN9 | CO14: =CO20/CO9 | CP14: =CP20/CP9 | CR14: =CR20/CR9 | CS14: =CS20/CS9 | CT14: =CT20/CT9 | CU14: =CU20/CU9 | CW14: =CW20/CW9 | CX14: =CX20/CX9 | CY14: =CY20/CY9 | DA14: =DA20/DA9 | DB14: =DB20/DB9 | DC14: =DC20/DC9 | DE14: =DE20/DE9 | DF14: =DF20/DF9 | DG14: =DG20/DG9 | DI14: =DI20/DI9 | DJ14: =DJ20/DJ9 | DK14: =DK20/DK9 | DM14: =DM20/DM9 | DN14: =DN20/DN9 | DO14: =DO20/DO9 | DQ14: =DQ20/DQ9 | DR14: =DR20/DR9 | DS14: =DS20/DS9 | DU14: =DU20/DU9 | DV14: =DV20/DV9 | DW14: =DW20/DW9 | DY14: =DY20/DY9 | DZ14: =DZ20/DZ9 | EA14: =EA20/EA9 | EC14: =EC20/EC9 | ED14: =ED20/ED9 | EE14: =EE20/EE9 | EG14: =EG20/EG9 | EH14: =EH20/EH9 | EI14: =EI20/EI9 | EK14: =EK20/EK9 | EL14: =EL20/EL9 | EM14: =EM20/EM9 | EO14: =EO20/EO9 | EP14: =EP20/EP9 | EQ14: =EQ20/EQ9 | ES14: =ES20/ES9 | ET14: =ET20/ET9 | EU14: =EU20/EU9 | EW14: =EW20/EW9 | EX14: =EX20/EX9 | EY14: =EY20/EY9 | FA14: =FA20/FA9 | FB14: =FB20/FB9 | FC14: =FC20/FC9 | FE14: =FE20/FE9 | FF14: =FF20/FF9 | FG14: =FG20/FG9 | FI14: =FI20/FI9 | FJ14: =FJ20/FJ9 | FK14: =FK20/FK9 | FM14: =FM20/FM9 | FN14: =FN20/FN9 | FO14: =FO20/FO9
B15: YoY change in passenger yield | D15: =D14/C14-1 | E15: =E14/D14-1 | F15: =F14/E14-1 | G15: =G14/F14-1 | H15: =H14/G14-1 | I15: =I14/H14-1 | J15: =J14/I14-1 | K15: =K14/J14-1 | ... AT15: =AT14/AS14-1 | BH15: =BH14/BD14-1 | BI15: =BI14/BE14-1 | BJ15: =BJ14/BF14-1 | BL15: =BL14/BH14-1 | BM15: =BM14/BI14-1 | BN15: =BN14/BJ14-1 | BP15: =BP14/BL14-1 | BQ15: =BQ14/BM14-1 | BR15: =BR14/BN14-1 | BT15: =BT14/BP14-1 | BU15: =BU14/BQ14-1 | BV15: =BV14/BR14-1 | BX15: =BX14/BT14-1 | BY15: =BY14/BU14-1 | BZ15: =BZ14/BV14-1 | CB15: =CB14/BX14-1 | CC15: =CC14/BY14-1 | CD15: =CD14/BZ14-1 | CF15: =CF14/CB14-1 | CG15: =CG14/CC14-1 | CH15: =CH14/CD14-1 | CJ15: =CJ14/CF14-1 | CK15: =CK14/CG14-1 | CL15: =CL14/CH14-1 | CN15: =CN14/CJ14-1 | CO15: =CO14/CK14-1 | CP15: =CP14/CL14-1 | CR15: =CR14/CN14-1 | CS15: =CS14/CN14-1 | CT15: =CT14/CO14-1 | CU15: =CU14/CP14-1 | CW15: =CW14/CS14-1 | CX15: =CX14/CT14-1 | CY15: =CY14/CU14-1 | DA15: =DA14/CW14-1 | DB15: =DB14/CX14-1 | DC15: =DC14/CY14-1 | DE15: =DE14/DA14-1 | DF15: =DF14/DB14-1 | DG15: =DG14/DC14-1 | DI15: =DI14/DE14-1 | DJ15: =DJ14/DF14-1 | DK15: =DK14/DG14-1 | DM15: =DM14/DI14-1 | DN15: =DN14/DJ14-1 | DO15: =DO14/DK14-1 | DQ15: =DQ14/DM14-1 | DR15: =DR14/DN14-1 | DS15: =DS14/DO14-1 | DU15: =DU14/DQ14-1 | DV15: =DV14/DR14-1 | DW15: =DW14/DS14-1 | DY15: =DY14/DU14-1 | DZ15: =DZ14/DV14-1 | EA15: =EA14/DW14-1 | EC15: =EC14/DY14-1 | ED15: =ED14/DZ14-1 | EE15: =EE14/EA14-1 | EG15: =EG14/EC14-1 | EH15: =EH14/ED14-1 | EI15: =EI14/EE14-1 | EK15: =EK14/EG14-1 | EL15: =EL14/EH14-1 | EM15: =EM14/EI14-1 | EO15: =EO14/EK14-1 | EP15: =EP14/EL14-1 | EQ15: =EQ14/EM14-1 | ES15: =ES14/EO14-1 | ET15: =ET14/EP14-1 | EU15: =EU14/EQ14-1 | EW15: =EW14/ES14-1 | EX15: =EX14/ET14-1 | EY15: =EY14/EU14-1 | FA15: =FA14/EW14-1 | FB15: =FB14/EX14-1 | FC15: =FC14/EY14-1 | FE15: =FE14/FA14-1 | FF15: =FF14/FB14-1 | FG15: =FG14/FC14-1 | FI15: =FI14/FE14-1 | FJ15: =FJ14/FF14-1 | FK15: =FK14/FG14-1 | FM15: =FM14/FI14-1 | FN15: =FN14/FJ14-1 | FO15: =FO14/FK14-1
B16: Overall unit revenue (RASK) | C16: =C20/C7 | D16: =D20/D7 | E16: =E20/E7 | F16: =F20/F7 | G16: =G20/G7 | H16: =H20/H7 | I16: =I20/I7 | J16: =J20/J7 | ... AT16: =AT20/AT7 | BD16: =BD20/BD7 | BE16: =BE20/BE7 | BF16: =BF20/BF7 | BH16: =BH20/BH7 | BI16: =BI20/BI7 | BJ16: =BJ20/BJ7 | BL16: =BL20/BL7 | BM16: =BM20/BM7 | BN16: =BN20/BN7 | BP16: =BP20/BP7 | BQ16: =BQ20/BQ7 | BR16: =BR20/BR7 | BT16: =BT20/BT7 | BU16: =BU20/BU7 | BV16: =BV20/BV7 | BX16: =BX20/BX7 | BY16: =BY20/BY7 | BZ16: =BZ20/BZ7 | CB16: =CB20/CB7 | CC16: =CC20/CC7 | CD16: =CD20/CD7 | CF16: =CF20/CF7 | CG16: =CG20/CG7 | CH16: =CH20/CH7 | CJ16: =CJ20/CJ7 | CK16: =CK20/CK7 | CL16: =CL20/CL7 | CN16: =CN20/CN7 | CO16: =CO20/CO7 | CP16: =CP20/CP7 | CR16: =CR20/CR7 | CS16: =CS20/CS7 | CT16: =CT20/CT7 | CU16: =CU20/CU7 | CW16: =CW20/CW7 | CX16: =CX20/CX7 | CY16: =CY20/CY7 | DA16: =DA20/DA7 | DB16: =DB20/DB7 | DC16: =DC20/DC7 | DE16: =DE20/DE7 | DF16: =DF20/DF7 | DG16: =DG20/DG7 | DI16: =DI20/DI7 | DJ16: =DJ20/DJ7 | DK16: =DK20/DK7 | DM16: =DM20/DM7 | DN16: =DN20/DN7 | DO16: =DO20/DO7 | DQ16: =DQ20/DQ7 | DR16: =DR20/DR7 | DS16: =DS20/DS7 | DU16: =DU20/DU7 | DV16: =DV20/DV7 | DW16: =DW20/DW7 | DY16: =DY20/DY7 | DZ16: =DZ20/DZ7 | EA16: =EA20/EA7 | EC16: =EC20/EC7 | ED16: =ED20/ED7 | EE16: =EE20/EE7 | EG16: =EG20/EG7 | EH16: =EH20/EH7 | EI16: =EI20/EI7 | EK16: =EK20/EK7 | EL16: =EL20/EL7 | EM16: =EM20/EM7 | EO16: =EO20/EO7 | EP16: =EP20/EP7 | EQ16: =EQ20/EQ7 | ES16: =ES20/ES7 | ET16: =ET20/ET7 | EU16: =EU20/EU7 | EW16: =EW20/EW7 | EX16: =EX20/EX7 | EY16: =EY20/EY7 | FA16: =FA20/FA7 | FB16: =FB20/FB7 | FC16: =FC20/FC7 | FE16: =FE20/FE7 | FF16: =FF20/FF7 | FG16: =FG20/FG7 | FI16: =FI20/FI7 | FJ16: =FJ20/FJ7 | FK16: =FK20/FK7 | FM16: =FM20/FM7 | FN16: =FN20/FN7 | FO16: =FO20/FO7
B17: YoY change in RASK | D17: =D16/C16-1 | E17: =E16/D16-1 | F17: =F16/E16-1 | G17: =G16/F16-1 | H17: =H16/G16-1 | I17: =I16/H16-1 | J17: =J16/I16-1 | K17: =K16/J16-1 | ... AT17: =AT16/AS16-1 | BH17: =BH16/BD16-1 | BI17: =BI16/BE16-1 | BJ17: =BJ16/BF16-1 | BL17: =BL16/BH16-1 | BM17: =BM16/BI16-1 | BN17: =BN16/BJ16-1 | BP17: =BP16/BL16-1 | BQ17: =BQ16/BM16-1 | BR17: =BR16/BN16-1 | BT17: =BT16/BP16-1 | BU17: =BU16/BQ16-1 | BV17: =BV16/BR16-1 | BX17: =BX16/BT16-1 | BY17: =BY16/BU16-1 | BZ17: =BZ16/BV16-1 | CB17: =CB16/BX16-1 | CC17: =CC16/BY16-1 | CD17: =CD16/BZ16-1 | CF17: =CF16/CB16-1 | CG17: =CG16/CC16-1 | CH17: =CH16/CD16-1 | CJ17: =CJ16/CF16-1 | CK17: =CK16/CG16-1 | CL17: =CL16/CH16-1 | CN17: =CN16/CJ16-1 | CO17: =CO16/CK16-1 | CP17: =CP16/CL16-1 | CR17: =CR16/CN16-1 | CS17: =CS16/CN16-1 | CT17: =CT16/CO16-1 | CU17: =CU16/CP16-1 | CW17: =CW16/CS16-1 | CX17: =CX16/CT16-1 | CY17: =CY16/CU16-1 | DA17: =DA16/CW16-1 | DB17: =DB16/CX16-1 | DC17: =DC16/CY16-1 | DE17: =DE16/DA16-1 | DF17: =DF16/DB16-1 | DG17: =DG16/DC16-1 | DI17: =DI16/DE16-1 | DJ17: =DJ16/DF16-1 | DK17: =DK16/DG16-1 | DM17: =DM16/DI16-1 | DN17: =DN16/DJ16-1 | DO17: =DO16/DK16-1 | DQ17: =DQ16/DM16-1 | DR17: =DR16/DN16-1 | DS17: =DS16/DO16-1 | DU17: =DU16/DQ16-1 | DV17: =DV16/DR16-1 | DW17: =DW16/DS16-1 | DY17: =DY16/DU16-1 | DZ17: =DZ16/DV16-1 | EA17: =EA16/DW16-1 | EC17: =EC16/DY16-1 | ED17: =ED16/DZ16-1 | EE17: =EE16/EA16-1 | EG17: =EG16/EC16-1 | EH17: =EH16/ED16-1 | EI17: =EI16/EE16-1 | EK17: =EK16/EG16-1 | EL17: =EL16/EH16-1 | EM17: =EM16/EI16-1 | EO17: =EO16/EK16-1 | EP17: =EP16/EL16-1 | EQ17: =EQ16/EM16-1 | ES17: =ES16/EO16-1 | ET17: =ET16/EP16-1 | EU17: =EU16/EQ16-1 | EW17: =EW16/ES16-1 | EX17: =EX16/ET16-1 | EY17: =EY16/EU16-1 | FA17: =FA16/EW16-1 | FB17: =FB16/EX16-1 | FC17: =FC16/EY16-1 | FE17: =FE16/FA16-1 | FF17: =FF16/FB16-1 | FG17: =FG16/FC16-1 | FI17: =FI16/FE16-1 | FJ17: =FJ16/FF16-1 | FK17: =FK16/FG16-1 | FM17: =FM16/FI16-1 | FN17: =FN16/FJ16-1 | FO17: =FO16/FK16-1
B18: Average airfare ticket price | C18: =+C20/C11*1000 | D18: =+D20/D11*1000 | E18: =+E20/E11*1000 | F18: =+F20/F11*1000 | G18: =+G20/G11*1000 | H18: =+H20/H11*1000 | I18: =+I20/I11*1000 | J18: =+J20/J11*1000 | ... AT18: =+AT20/AT11*1000 | BH18: =+BH20/BH11*1000 | BI18: =+BI20/BI11*1000 | BJ18: =+BJ20/BJ11*1000 | BL18: =+BL20/BL11*1000 | BM18: =+BM20/BM11*1000 | BN18: =+BN20/BN11*1000 | BP18: =+BP20/BP11*1000 | BQ18: =+BQ20/BQ11*1000 | BR18: =+BR20/BR11*1000 | BT18: =+BT20/BT11*1000 | BU18: =+BU20/BU11*1000 | BV18: =+BV20/BV11*1000 | BX18: =+BX20/BX11*1000 | BY18: =+BY20/BY11*1000 | BZ18: =+BZ20/BZ11*1000 | CB18: =+CB20/CB11*1000 | CC18: =+CC20/CC11*1000 | CD18: =+CD20/CD11*1000 | CF18: =+CF20/CF11*1000 | CG18: =+CG20/CG11*1000 | CH18: =+CH20/CH11*1000 | CJ18: =+CJ20/CJ11*1000 | CK18: =+CK20/CK11*1000 | CL18: =+CL20/CL11*1000 | CN18: =+CN20/CN11*1000 | CO18: =+CO20/CO11*1000 | CP18: =+CP20/CP11*1000 | CR18: =+CR20/CR11*1000 | CS18: =+CS20/CS11*1000 | CT18: =+CT20/CT11*1000 | CU18: =+CU20/CU11*1000 | CW18: =+CW20/CW11*1000 | CX18: =+CX20/CX11*1000 | CY18: =+CY20/CY11*1000 | DA18: =+DA20/DA11*1000 | DB18: =+DB20/DB11*1000 | DC18: =+DC20/DC11*1000 | DE18: =+DE20/DE11*1000 | DF18: =+DF20/DF11*1000 | DG18: =+DG20/DG11*1000 | DI18: =+DI20/DI11*1000 | DJ18: =+DJ20/DJ11*1000 | DK18: =+DK20/DK11*1000 | DM18: =+DM20/DM11*1000 | DN18: =+DN20/DN11*1000 | DO18: =+DO20/DO11*1000 | DQ18: =+DQ20/DQ11*1000 | DR18: =+DR20/DR11*1000 | DS18: =+DS20/DS11*1000 | DU18: =+DU20/DU11*1000 | DV18: =+DV20/DV11*1000 | DW18: =+DW20/DW11*1000 | DY18: =+DY20/DY11*1000 | DZ18: =+DZ20/DZ11*1000 | EA18: =+EA20/EA11*1000 | EC18: =+EC20/EC11*1000 | ED18: =+ED20/ED11*1000 | EE18: =+EE20/EE11*1000 | EG18: =+EG20/EG11*1000 | EH18: =+EH20/EH11*1000 | EI18: =+EI20/EI11*1000 | EK18: =+EK20/EK11*1000 | EL18: =+EL20/EL11*1000 | EM18: =+EM20/EM11*1000 | EO18: =+EO20/EO11*1000 | EP18: =+EP20/EP11*1000 | EQ18: =+EQ20/EQ11*1000 | ES18: =+ES20/ES11*1000 | ET18: =+ET20/ET11*1000 | EU18: =+EU20/EU11*1000 | EW18: =+EW20/EW11*1000 | EX18: =+EX20/EX11*1000 | EY18: =+EY20/EY11*1000 | FA18: =+FA20/FA11*1000 | FB18: =+FB20/FB11*1000 | FC18: =+FC20/FC11*1000 | FE18: =+FE20/FE11*1000 | FF18: =+FF20/FF11*1000 | FG18: =+FG20/FG11*1000 | FI18: =+FI20/FI11*1000 | FJ18: =+FJ20/FJ11*1000 | FK18: =+FK20/FK11*1000 | FM18: =+FM20/FM11*1000 | FN18: =+FN20/FN11*1000 | FO18: =+FO20/FO11*1000
B19: YoY change in average airfare ticket price | D19: =D18/C18-1 | E19: =E18/D18-1 | F19: =F18/E18-1 | G19: =G18/F18-1 | H19: =H18/G18-1 | I19: =I18/H18-1 | J19: =J18/I18-1 | K19: =K18/J18-1 | ... AT19: =AT18/AS18-1 | BL19: =BL18/BH18-1 | BM19: =BM18/BI18-1 | BN19: =BN18/BJ18-1 | BP19: =BP18/BL18-1 | BQ19: =BQ18/BM18-1 | BR19: =BR18/BN18-1 | BT19: =BT18/BP18-1 | BU19: =BU18/BQ18-1 | BV19: =BV18/BR18-1 | BX19: =BX18/BT18-1 | BY19: =BY18/BU18-1 | BZ19: =BZ18/BV18-1 | CB19: =CB18/BX18-1 | CC19: =CC18/BY18-1 | CD19: =CD18/BZ18-1 | CF19: =CF18/CB18-1 | CG19: =CG18/CC18-1 | CH19: =CH18/CD18-1 | CJ19: =CJ18/CF18-1 | CK19: =CK18/CG18-1 | CL19: =CL18/CH18-1 | CN19: =CN18/CJ18-1 | CO19: =CO18/CK18-1 | CP19: =CP18/CL18-1 | CR19: =CR18/CN18-1 | CS19: =CS18/CN18-1 | CT19: =CT18/CO18-1 | CU19: =CU18/CP18-1 | CW19: =CW18/CS18-1 | CX19: =CX18/CT18-1 | CY19: =CY18/CU18-1 | DA19: =DA18/CW18-1 | DB19: =DB18/CX18-1 | DC19: =DC18/CY18-1 | DE19: =DE18/DA18-1 | DF19: =DF18/DB18-1 | DG19: =DG18/DC18-1 | DI19: =DI18/DE18-1 | DJ19: =DJ18/DF18-1 | DK19: =DK18/DG18-1 | DM19: =DM18/DI18-1 | DN19: =DN18/DJ18-1 | DO19: =DO18/DK18-1 | DQ19: =DQ18/DM18-1 | DR19: =DR18/DN18-1 | DS19: =DS18/DO18-1 | DU19: =DU18/DQ18-1 | DV19: =DV18/DR18-1 | DW19: =DW18/DS18-1 | DY19: =DY18/DU18-1 | DZ19: =DZ18/DV18-1 | EA19: =EA18/DW18-1 | EC19: =EC18/DY18-1 | ED19: =ED18/DZ18-1 | EE19: =EE18/EA18-1 | EG19: =EG18/EC18-1 | EH19: =EH18/ED18-1 | EI19: =EI18/EE18-1 | EK19: =EK18/EG18-1 | EL19: =EL18/EH18-1 | EM19: =EM18/EI18-1 | EO19: =EO18/EK18-1 | EP19: =EP18/EL18-1 | EQ19: =EQ18/EM18-1 | ES19: =ES18/EO18-1 | ET19: =ET18/EP18-1 | EU19: =EU18/EQ18-1 | EW19: =EW18/ES18-1 | EX19: =EX18/ET18-1 | EY19: =EY18/EU18-1 | FA19: =FA18/EW18-1 | FB19: =FB18/EX18-1 | FC19: =FC18/EY18-1 | FE19: =FE18/FA18-1 | FF19: =FF18/FB18-1 | FG19: =FG18/FC18-1 | FI19: =FI18/FE18-1 | FJ19: =FJ18/FF18-1 | FK19: =FK18/FG18-1 | FM19: =FM18/FI18-1 | FN19: =FN18/FJ18-1 | FO19: =FO18/FK18-1
B20: Overall Passenger Revenue | C20: =+C35+C50 | D20: =+D35+D50 | E20: =+E35+E50 | F20: =+F35+F50 | G20: =+G35+G50 | H20: =+H35+H50 | I20: =+I35+I50 | J20: =+J35+J50 | ... AT20: =+AT35+AT50 | BD20: =+BD35+BD50 | BE20: =+BE35+BE50 | BF20: =+BF35+BF50 | BH20: =+BH35+BH50 | BI20: =+BI35+BI50 | BJ20: =+BJ35+BJ50 | BL20: =+BL35+BL50 | BM20: =+BM35+BM50 | BN20: =+BN35+BN50 | BP20: =+BP35+BP50 | BQ20: =+BQ35+BQ50 | BR20: =+BR35+BR50 | BT20: =+BT35+BT50 | BU20: =+BU35+BU50 | BV20: =+BV35+BV50 | BX20: =+BX35+BX50 | BY20: =+BY35+BY50 | BZ20: =+BZ35+BZ50 | CB20: =+CB35+CB50 | CC20: =+CC35+CC50 | CD20: =+CD35+CD50 | CF20: =+CF35+CF50 | CG20: =+CG35+CG50 | CH20: =+CH35+CH50 | CJ20: =+CJ35+CJ50 | CK20: =+CK35+CK50 | CL20: =+CL35+CL50 | CN20: =+CN35+CN50 | CO20: =+CO35+CO50 | CP20: =+CP35+CP50 | CR20: =+CR35+CR50 | CS20: =+CS35+CS50 | CT20: =+CT35+CT50 | CU20: =+CU35+CU50 | CW20: =+CW35+CW50 | CX20: =+CX35+CX50 | CY20: =+CY35+CY50 | DA20: =+DA35+DA50 | DB20: =+DB35+DB50 | DC20: =+DC35+DC50 | DE20: =+DE35+DE50 | DF20: =+DF35+DF50 | DG20: =+DG35+DG50 | DI20: =+DI35+DI50 | DJ20: =+DJ35+DJ50 | DK20: =+DK35+DK50 | DM20: =+DM35+DM50 | DN20: =+DN35+DN50 | DO20: =+DO35+DO50 | DQ20: =+DQ35+DQ50 | DR20: =+DR35+DR50 | DS20: =+DS35+DS50 | DU20: =+DU35+DU50 | DV20: =+DV35+DV50 | DW20: =+DW35+DW50 | DY20: =+DY35+DY50 | DZ20: =+DZ35+DZ50 | EA20: =+EA35+EA50 | EC20: =+EC35+EC50 | ED20: =+ED35+ED50 | EE20: =+EE35+EE50 | EG20: =+EG35+EG50 | EH20: =+EH35+EH50 | EI20: =+EI35+EI50 | EK20: =+EK35+EK50 | EL20: =+EL35+EL50 | EM20: =+EM35+EM50 | EO20: =+EO35+EO50 | EP20: =+EP35+EP50 | EQ20: =+EQ35+EQ50 | ES20: =+ES35+ES50 | ET20: =+ET35+ET50 | EU20: =+EU35+EU50 | EW20: =+EW35+EW50 | EX20: =+EX35+EX50 | EY20: =+EY35+EY50 | FA20: =+FA35+FA50 | FB20: =+FB35+FB50 | FC20: =+FC35+FC50 | FE20: =+FE35+FE50 | FF20: =+FF35+FF50 | FG20: =+FG35+FG50 | FI20: =+FI35+FI50 | FJ20: =+FJ35+FJ50 | FK20: =+FK35+FK50 | FM20: =+FM35+FM50 | FN20: =+FN35+FN50 | FO20: =+FO35+FO50
A22: ask | B22: FSC's ask | C22: 23455 | D22: 26038 | E22: 28477 | F22: 32214 | G22: 33186 | H22: 37428 | I22: 41552 | J22: 45892 | K22: 49334 | L22: 54306 | M22: 57104 | N22: 60295 | O22: 58114 | P22: 61908.551 | Q22: 62790.254 | R22: 63050.052 | S22: 59280.17 | T22: 74062.4 | U22: 82766.395 | V22: 91769 | W22: 102461.79 | X22: 115478.34 | Y22: 111167 | Z22: 115748 | AA22: 126340.02 | AB22: 129594.86 | AC22: 127215.38 | AD22: 134711 | AE22: 142680.58 | AF22: 146085.48 | AG22: 150138.11 | AH22: 155362.02 | AI22: 163243.91 | AJ22: 34609 | AK22: 13228 | AL22: 20056 | AM22: 85607 | AN22: 111789 | AO22: =SUM(FI22:FJ22) | AP22: =SUM(FM22:FN22) | AQ22: =+AP22*(1+AQ23) | AR22: =+AQ22*(1+AR23) | AS22: =+AR22*(1+AS23) | AT22: =+AS22*(1+AT23) | AX22: =L22 | AZ22: 28172 | BA22: =BB22-AZ22 | BB22: =M22 | BD22: 28928 | BE22: =BF22-BD22 | BF22: =N22 | BH22: 28801 | BI22: =BJ22-BH22 | BJ22: =O22 | BL22: 29839.107 | BM22: =BN22-BL22 | BN22: =P22 | BP22: 32419 | BQ22: =BR22-BP22 | BR22: =Q22 | BT22: 29537.302 | BU22: =BV22-BT22 | BV22: =R22 | BX22: 26831.5 | BY22: =BZ22-BX22 | BZ22: =S22 | CB22: 35249.9 | CC22: =CD22-CB22 | CD22: =T22 | CF22: 39535 | CG22: =CH22-CF22 | CH22: =U22 | CJ22: 43813.693 | CK22: =CL22-CJ22 | CL22: =V22 | CN22: 49836 | CO22: =CP22-CN22 | CP22: =W22 | CR22: 56949.234 | CS22: 56949.234 | CT22: =CU22-CR22 | CU22: =X22 | CW22: 55749.52 | CX22: =CY22-CW22 | CY22: =Y22 | DA22: 55680.314 | DB22: =+DC22-DA22 | DC22: =Z22 | DE22: 61135.663 | DF22: =+DG22-DE22 | DG22: =AA22 | DI22: 65350.956 | DJ22: =+DK22-DI22 | DK22: =AB22 | DM22: 62186.792 | DN22: =+DO22-DM22 | DO22: =AC22 | DQ22: 65474.415 | DR22: =DS22-DQ22 | DS22: =AD22 | DU22: 69689.145 | DV22: =DW22-DU22 | DW22: =AE22 | DY22: 72646.509 | DZ22: =EA22-DY22 | EA22: =AF22 | EC22: 73444.073 | ED22: =EE22-EC22 | EE22: =AG22 | EG22: 75770.382 | EH22: =EI22-EG22 | EI22: =AH22 | EK22: 80814.422 | EL22: =EM22-EK22 | EM22: =AI22 | EO22: =SUMIFS(Monthly!$10:$10,Monthly!$8:$8,">="&DATE(MID(EO$3,3,4),1,1),Monthly!$8:$8,"<="&DATE(MID(EO$3,3,4),6,30)) | EP22: =EQ22-EO22 | EQ22: =AJ22 | ES22: =SUMIFS(Monthly!$10:$10,Monthly!$8:$8,">="&DATE(MID(ES$3,3,4),1,1),Monthly!$8:$8,"<="&DATE(MID(ES$3,3,4),6,30)) | ET22: =EU22-ES22 | EU22: =AK22 | EW22: =SUMIFS(Monthly!$10:$10,Monthly!$8:$8,">="&DATE(MID(EW$3,3,4),1,1),Monthly!$8:$8,"<="&DATE(MID(EW$3,3,4),6,30)) | EX22: =+EY22-EW22 | EY22: =AL22 | FA22: =SUMIFS(Monthly!$10:$10,Monthly!$8:$8,">="&DATE(MID(FA$3,3,4),1,1),Monthly!$8:$8,"<="&DATE(MID(FA$3,3,4),6,30)) | FB22: =+FC22-FA22 | FC22: =AM22 | FE22: =SUMIFS(Monthly!$10:$10,Monthly!$8:$8,">="&DATE(MID(FE$3,3,4),1,1),Monthly!$8:$8,"<="&DATE(MID(FE$3,3,4),6,30)) | FF22: =+FG22-FE22 | FG22: =AN22 | FI22: =SUMIFS(Monthly!$10:$10,Monthly!$8:$8,">="&DATE(MID(FI$3,3,4),1,1),Monthly!$8:$8,"<="&DATE(MID(FI$3,3,4),6,30)) | FJ22: =+FK22-FI22 | FK22: =AO22 | FM22: =SUMIFS(Monthly!$10:$10,Monthly!$8:$8,">="&DATE(MID(FM$3,3,4),1,1),Monthly!$8:$8,"<="&DATE(MID(FM$3,3,4),6,30)) | FN22: =FJ22*(1+FN23) | FO22: =AP22
B23: YoY change in overall capacity (ASK) | D23: =D22/C22-1 | E23: =E22/D22-1 | F23: =F22/E22-1 | G23: =G22/F22-1 | H23: =H22/G22-1 | I23: =I22/H22-1 | J23: =J22/I22-1 | K23: =K22/J22-1 | ... AP23: =AP22/AO22-1 | AQ23: 0.05 | AR23: 0.05 | AS23: 0.05 | AT23: 0.05 | BB23: =BB22/AX22-1 | BD23: =BD22/AZ22-1 | BE23: =BE22/BA22-1 | BF23: =BF22/BB22-1 | BH23: =BH22/BD22-1 | BI23: =BI22/BE22-1 | BJ23: =BJ22/BF22-1 | BL23: =BL22/BH22-1 | BM23: =BM22/BI22-1 | BN23: =BN22/BJ22-1 | BP23: =BP22/BL22-1 | BQ23: =BQ22/BM22-1 | BR23: =BR22/BN22-1 | BT23: =BT22/BP22-1 | BU23: =BU22/BQ22-1 | BV23: =BV22/BR22-1 | BX23: =BX22/BT22-1 | BY23: =BY22/BU22-1 | BZ23: =BZ22/BV22-1 | CB23: =CB22/BX22-1 | CC23: =CC22/BY22-1 | CD23: =CD22/BZ22-1 | CF23: =CF22/CB22-1 | CG23: =CG22/CC22-1 | CH23: =CH22/CD22-1 | CJ23: =CJ22/CF22-1 | CK23: =CK22/CG22-1 | CL23: =CL22/CH22-1 | CN23: =CN22/CJ22-1 | CO23: =CO22/CK22-1 | CP23: =CP22/CL22-1 | CR23: =CR22/CN22-1 | CS23: =CS22/CN22-1 | CT23: =CT22/CO22-1 | CU23: =CU22/CP22-1 | CW23: =CW22/CS22-1 | CX23: =CX22/CT22-1 | CY23: =CY22/CU22-1 | DA23: =DA22/CW22-1 | DB23: =DB22/CX22-1 | DC23: =DC22/CY22-1 | DE23: =DE22/DA22-1 | DF23: =DF22/DB22-1 | DG23: =DG22/DC22-1 | DI23: =DI22/DE22-1 | DJ23: =DJ22/DF22-1 | DK23: =DK22/DG22-1 | DM23: =DM22/DI22-1 | DN23: =DN22/DJ22-1 | DO23: =DO22/DK22-1 | DQ23: =DQ22/DM22-1 | DR23: =DR22/DN22-1 | DS23: =DS22/DO22-1 | DU23: =DU22/DQ22-1 | DV23: =DV22/DR22-1 | DW23: =DW22/DS22-1 | DY23: =DY22/DU22-1 | DZ23: =DZ22/DV22-1 | EA23: =EA22/DW22-1 | EC23: =EC22/DY22-1 | ED23: =ED22/DZ22-1 | EE23: =EE22/EA22-1 | EG23: =EG22/EC22-1 | EH23: =EH22/ED22-1 | EI23: =EI22/EE22-1 | EK23: =+EK22/EG22-1 | EL23: =+EL22/EH22-1 | EM23: =AI23 | EO23: =+EO22/EK22-1 | EP23: =+EP22/EL22-1 | EQ23: =+EQ22/EM22-1 | ES23: =+ES22/EO22-1 | ET23: =+ET22/EP22-1 | EU23: =+EU22/EQ22-1 | EW23: =+EW22/ES22-1 | EX23: =+EX22/ET22-1 | EY23: =+EY22/EU22-1 | FA23: =+FA22/EW22-1 | FB23: =+FB22/EX22-1 | FC23: =+FC22/EY22-1 | FE23: =+FE22/FA22-1 | FF23: =+FF22/FB22-1 | FG23: =+FG22/FC22-1 | FI23: =+FI22/FE22-1 | FJ23: =+FJ22/FF22-1 | FK23: =+FK22/FG22-1 | FM23: =+FM22/FI22-1 | FN23: 0.09 | FO23: =+FO22/FK22-1
A24: rpk | B24: FSC's rpk | C24: 17262 | D24: 20069 | E24: 22088 | F24: 24461 | G24: 24433 | H24: 27527 | I24: 29097 | J24: 32727 | K24: 35341 | L24: 40185 | M24: 38962 | N24: 40679.125 | O24: 41502 | P24: 47152.792 | Q24: 44792.224 | R24: 49041.021 | S24: 42773.752 | T24: 57282.3 | U24: 65109.775 | V24: 72939 | W24: 81800.757 | X24: 90975.081 | Y24: 89440.308 | Z24: 96587.691 | AA24: 101535.43 | AB24: 103836.84 | AC24: 104570.79 | AD24: =AD22*0.833 | AE24: 122330.03 | AF24: 123477.75 | AG24: 126662.83 | AH24: 130629.74 | AI24: 134396.83 | AJ24: 20079 | AK24: 4120 | AL24: 14764 | AM24: 73342 | AN24: 93016 | AO24: =SUM(FI24:FJ24) | AP24: =SUM(FM24:FN24) | AQ24: =AQ28*AQ22 | AR24: =AR28*AR22 | AS24: =AS28*AS22 | AT24: =AT28*AT22 | AV24: =AX24-AW24 | AW24: 21428 | AX24: =L24 | AZ24: 20044.46 | BA24: =BB24-AZ24 | BB24: =M24 | BD24: =BD22*0.663 | BE24: =BF24-BD24 | BF24: =N24 | BH24: 19325.471 | BI24: =BJ24-BH24 | BJ24: =O24 | BL24: 22579.468 | BM24: =BN24-BL24 | BN24: =P24 | BP24: 23295 | BQ24: =BR24-BP24 | BR24: =Q24 | BT24: 23071.905 | BU24: =BV24-BT24 | BV24: =R24 | BX24: 17276.5 | BY24: =BZ24-BX24 | BZ24: =S24 | CB24: 26834.6 | CC24: =CD24-CB24 | CD24: =T24 | CF24: =CF22*0.781 | CG24: =CH24-CF24 | CH24: =U24 | CJ24: =CJ22*0.791 | CK24: =CL24-CJ24 | CL24: =V24 | CN24: 38938.113 | CO24: =CP24-CN24 | CP24: =W24 | CR24: 45579.621 | CS24: 45579.621 | CT24: =CU24-CR24 | CU24: =X24 | CW24: 43757.949 | CX24: =CY24-CW24 | CY24: =Y24 | DA24: 46783.64 | DB24: =+DC24-DA24 | DC24: =Z24 | DE24: 48476.621 | DF24: =+DG24-DE24 | DG24: =AA24 | DI24: 52348.668 | DJ24: =+DK24-DI24 | DK24: =AB24 | DM24: 50543.063 | DN24: =+DO24-DM24 | DO24: =AC24 | DQ24: 54713.1 | DR24: =+DS24-DQ24 | DS24: =AD24 | DU24: 59835.42 | DV24: =+DW24-DU24 | DW24: =AE24 | DY24: 61367.549 | DZ24: =+EA24-DY24 | EA24: =AF24 | EC24: 62241.855 | ED24: =+EE24-EC24 | EE24: =AG24 | EG24: 63809.914 | EH24: =+EI24-EG24 | EI24: =AH24 | EK24: 68078.448 | EL24: =+EM24-EK24 | EM24: =AI24 | EO24: =SUMIFS(Monthly!$46:$46,Monthly!$8:$8,">="&DATE(MID(EO$3,3,4),1,1),Monthly!$8:$8,"<="&DATE(MID(EO$3,3,4),6,30)) | EP24: =+EQ24-EO24 | EQ24: =AJ24 | ES24: =SUMIFS(Monthly!$46:$46,Monthly!$8:$8,">="&DATE(MID(ES$3,3,4),1,1),Monthly!$8:$8,"<="&DATE(MID(ES$3,3,4),6,30)) | ET24: =+EU24-ES24 | EU24: =AK24 | EW24: =SUMIFS(Monthly!$46:$46,Monthly!$8:$8,">="&DATE(MID(EW$3,3,4),1,1),Monthly!$8:$8,"<="&DATE(MID(EW$3,3,4),6,30)) | EX24: =+EY24-EW24 | EY24: =AL24 | FA24: =SUMIFS(Monthly!$46:$46,Monthly!$8:$8,">="&DATE(MID(FA$3,3,4),1,1),Monthly!$8:$8,"<="&DATE(MID(FA$3,3,4),6,30)) | FB24: =+FC24-FA24 | FC24: =AM24 | FE24: =SUMIFS(Monthly!$46:$46,Monthly!$8:$8,">="&DATE(MID(FE$3,3,4),1,1),Monthly!$8:$8,"<="&DATE(MID(FE$3,3,4),6,30)) | FF24: =+FG24-FE24 | FG24: =AN24 | FI24: 56651 | FJ24: =+FK24-FI24 | FK24: =AO24 | FM24: =SUMIFS(Monthly!$46:$46,Monthly!$8:$8,">="&DATE(MID(FM$3,3,4),1,1),Monthly!$8:$8,"<="&DATE(MID(FM$3,3,4),6,30)) | FN24: =FN22*FN28 | FO24: =AP24
A25: pax traffic growth | B25: YoY change in passenger traffic (RPK) | D25: =D24/C24-1 | E25: =E24/D24-1 | F25: =F24/E24-1 | G25: =G24/F24-1 | H25: =H24/G24-1 | I25: =I24/H24-1 | J25: =J24/I24-1 | K25: =K24/J24-1 | L25: =0.137 | M25: -0.031 | N25: =N24/M24-1 | O25: 0.027 | P25: =P24/O24-1 | Q25: =Q24/P24-1 | R25: =R24/Q24-1 | S25: =S24/R24-1 | T25: =T24/S24-1 | U25: =U24/T24-1 | V25: =V24/U24-1 | W25: =W24/V24-1 | ... AK25: =AK24/AJ24-1 | AL25: =+AL24/AK24-1 | AM25: =+AM24/AL24-1 | AN25: =+AN24/AM24-1 | AO25: =+AO24/AN24-1 | AP25: =+AP24/AO24-1 | AQ25: =+AQ24/AP24-1 | AR25: =+AR24/AQ24-1 | AS25: =+AS24/AR24-1 | AT25: =+AT24/AS24-1 | AX25: =L25 | BB25: =M25 | BD25: =BD24/AZ24-1 | BE25: =BE24/BA24-1 | BF25: =N25 | BH25: =BH24/BD24-1 | BI25: =BI24/BE24-1 | BJ25: =O25 | BL25: =BL24/BH24-1 | BM25: =BM24/BI24-1 | BN25: =P25 | BP25: =BP24/BL24-1 | BQ25: =BQ24/BM24-1 | BR25: =Q25 | BT25: =BT24/BP24-1 | BU25: =BU24/BQ24-1 | BV25: =R25 | BX25: =BX24/BT24-1 | BY25: =BY24/BU24-1 | BZ25: =S25 | CB25: =CB24/BX24-1 | CC25: =CC24/BY24-1 | CD25: =T25 | CF25: =CF24/CB24-1 | CG25: =CG24/CC24-1 | CH25: =U25 | CJ25: =CJ24/CF24-1 | CK25: =CK24/CG24-1 | CL25: =V25 | CN25: =CN24/CJ24-1 | CO25: =CO24/CK24-1 | CP25: =W25 | CR25: =CR24/CN24-1 | CS25: =CS24/CN24-1 | CT25: =CT24/CO24-1 | CU25: =X25 | CW25: =CW24/CS24-1 | CX25: =CX24/CT24-1 | CY25: =Y25 | DA25: =DA24/CW24-1 | DB25: =DB24/CX24-1 | DC25: =Z25 | DE25: =DE24/DA24-1 | DF25: =DF24/DB24-1 | DG25: =AA25 | DI25: =+DI24/DE24-1 | DJ25: =DJ24/DF24-1 | DK25: =AB25 | DM25: =+DM24/DI24-1 | DN25: =DN24/DJ24-1 | DO25: =AC25 | DQ25: =+DQ24/DM24-1 | DR25: =+DR24/DN24-1 | DS25: =AD25 | DU25: =+DU24/DQ24-1 | DV25: =+DV24/DR24-1 | DW25: =AE25 | DY25: =+DY24/DU24-1 | DZ25: =+DZ24/DV24-1 | EA25: =AF25 | EC25: =+EC24/DY24-1 | ED25: =+ED24/DZ24-1 | EE25: =AG25 | EG25: =+EG24/EC24-1 | EH25: =+EH24/ED24-1 | EI25: =AH25 | EK25: =+EK24/EG24-1 | EL25: =+EL24/EH24-1 | EM25: =AI25 | EO25: =+EO24/EK24-1 | EP25: =+EP24/EL24-1 | EQ25: =+EQ24/EM24-1 | ES25: =+ES24/EO24-1 | ET25: =+ET24/EP24-1 | EU25: =+EU24/EQ24-1 | EW25: =+EW24/ES24-1 | EX25: =+EX24/ET24-1 | EY25: =+EY24/EU24-1 | FA25: =+FA24/EW24-1 | FB25: =+FB24/EX24-1 | FC25: =+FC24/EY24-1 | FE25: =+FE24/FA24-1 | FF25: =+FF24/FB24-1 | FG25: =+FG24/FC24-1 | FI25: =+FI24/FE24-1 | FJ25: =+FJ24/FF24-1 | FK25: =+FK24/FG24-1 | FM25: =+FM24/FI24-1 | FN25: =+FN24/FJ24-1 | FO25: =+FO24/FK24-1
A26: passenger | B26: FSC's Passenger nos (000s) | C26: 5086 | D26: 6193 | E26: 7058 | F26: 7731 | G26: 7391 | H26: 8363 | I26: 8867 | J26: 9750 | K26: 10381 | L26: 10985 | M26: 10018 | N26: 10299 | O26: 10516 | P26: 11864.37 | Q26: 11268.778 | R26: 12321.256 | S26: 10058.995 | T26: 13664 | U26: 15438.243 | V26: 18097 | W26: 23253.427 | X26: 24959.429 | Y26: 24558 | Z26: 26796.249 | AA26: 27581.331 | AB26: 28960.689 | AC26: 29919.576 | AD26: 31600 | AE26: 34064.859 | AF26: 34322.693 | AG26: 34819.871 | AH26: 35468.218 | AI26: 35233.131 | AJ26: 4631 | AK26: 717 | AL26: 2804 | AM26: 17985 | AN26: 22827 | AO26: =SUM(FI26:FJ26) | AP26: =SUM(FM26:FN26) | AQ26: =AQ24/AQ27*1000 | AR26: =AR24/AR27*1000 | AS26: =AS24/AS27*1000 | AT26: =AT24/AT27*1000 | AX26: =L26 | BB26: =M26 | BE26: =BF26-BD26 | BF26: =N26 | BH26: 4919.6 | BI26: =BJ26-BH26 | BJ26: =O26 | BL26: 5757.208 | BM26: =BN26-BL26 | BN26: =P26 | BP26: 5890.989 | BQ26: =BR26-BP26 | BR26: =Q26 | BT26: 5932.699 | BU26: =BV26-BT26 | BV26: =R26 | BX26: 4018.624 | BY26: =BZ26-BX26 | BZ26: =S26 | CB26: 6404.3 | CC26: =CD26-CB26 | CD26: =T26 | CF26: 7333 | CG26: =CH26-CF26 | CH26: =U26 | CJ26: 8144.335 | CK26: =CL26-CJ26 | CL26: =V26 | CN26: 10960 | CO26: =CP26-CN26 | CP26: =W26 | CR26: 12462.541 | CS26: 12462.541 | CT26: =CU26-CR26 | CU26: =X26 | CW26: 11938.15 | CX26: =CY26-CW26 | CY26: =Y26 | DA26: 12953.548 | DB26: =+DC26-DA26 | DC26: =Z26 | DE26: 13175.861 | DF26: =+DG26-DE26 | DG26: =AA26 | DI26: 14311.778 | DJ26: =+DK26-DI26 | DK26: =AB26 | DM26: 14497.032 | DN26: =+DO26-DM26 | DO26: =AC26 | DQ26: 15436.937 | DR26: =DS26-DQ26 | DS26: =AD26 | DU26: 16800.331 | DV26: =DW26-DU26 | DW26: =AE26 | DY26: 17248.591 | DZ26: =EA26-DY26 | EA26: =AF26 | EC26: 17162.995 | ED26: =EE26-EC26 | EE26: =AG26 | EG26: 17484.704 | EH26: =EI26-EG26 | EI26: =AH26 | EK26: 18261.05 | EL26: =EM26-EK26 | EM26: =AI26 | EO26: 4389 | EP26: =EQ26-EO26 | EQ26: =AJ26 | ES26: 157 | ET26: =EU26-ES26 | EU26: =AK26 | EW26: 335 | EX26: =+EY26-EW26 | EY26: =AL26 | FA26: 7816 | FB26: =+FC26-FA26 | FC26: =AM26 | FE26: 10660 | FF26: =+FG26-FE26 | FG26: =AN26 | FI26: 13627 | FJ26: =+FK26-FI26 | FK26: =AO26 | FM26: 16006 | FN26: =FN24/FN27*1000 | FO26: =AP26
B27: FSC's Trip length (kms) | C27: =C24/C26*1000 | D27: =D24/D26*1000 | E27: =E24/E26*1000 | F27: =F24/F26*1000 | G27: =G24/G26*1000 | H27: =H24/H26*1000 | I27: =I24/I26*1000 | J27: =J24/J26*1000 | ... AP27: =AP24/AP26*1000 | AQ27: =AP27 | AR27: =AQ27 | AS27: =AR27 | AT27: =AS27 | AX27: =L27 | BB27: =M27 | BE27: =BE24/BE26*1000 | BF27: =N27 | BH27: =BH24/BH26*1000 | BI27: =BI24/BI26*1000 | BJ27: =O27 | BL27: =BL24/BL26*1000 | BM27: =BM24/BM26*1000 | BN27: =P27 | BP27: =BP24/BP26*1000 | BQ27: =BQ24/BQ26*1000 | BR27: =Q27 | BT27: =BT24/BT26*1000 | BU27: =BU24/BU26*1000 | BV27: =R27 | BX27: =BX24/BX26*1000 | BY27: =BY24/BY26*1000 | BZ27: =S27 | CB27: =CB24/CB26*1000 | CC27: =CC24/CC26*1000 | CD27: =T27 | CF27: =CF24/CF26*1000 | CG27: =CG24/CG26*1000 | CH27: =U27 | CJ27: =CJ24/CJ26*1000 | CK27: =CK24/CK26*1000 | CL27: =V27 | CN27: =CN24/CN26*1000 | CO27: =CO24/CO26*1000 | CP27: =W27 | CR27: =CR24/CR26*1000 | CS27: =CS24/CS26*1000 | CT27: =CT24/CT26*1000 | CU27: =X27 | CW27: =CW24/CW26*1000 | CX27: =CX24/CX26*1000 | CY27: =Y27 | DA27: =DA24/DA26*1000 | DB27: =DB24/DB26*1000 | DC27: =Z27 | DE27: =DE24/DE26*1000 | DF27: =DF24/DF26*1000 | DG27: =AA27 | DI27: =DI24/DI26*1000 | DJ27: =DJ24/DJ26*1000 | DK27: =AB27 | DM27: =DM24/DM26*1000 | DN27: =DN24/DN26*1000 | DO27: =AC27 | DQ27: =DQ24/DQ26*1000 | DR27: =DR24/DR26*1000 | DS27: =AD27 | DU27: =DU24/DU26*1000 | DV27: =DV24/DV26*1000 | DW27: =AE27 | DY27: =DY24/DY26*1000 | DZ27: =DZ24/DZ26*1000 | EA27: =AF27 | EC27: =EC24/EC26*1000 | ED27: =ED24/ED26*1000 | EE27: =AG27 | EG27: =EG24/EG26*1000 | EH27: =EH24/EH26*1000 | EI27: =AH27 | EK27: =EK24/EK26*1000 | EL27: =EL24/EL26*1000 | EM27: =AI27 | EO27: =EO24/EO26*1000 | EP27: =EP24/EP26*1000 | EQ27: =AJ27 | ES27: =ES24/ES26*1000 | ET27: =ET24/ET26*1000 | EU27: =AK27 | EW27: =EW24/EW26*1000 | EX27: =EX24/EX26*1000 | EY27: =AL27 | FA27: =FA24/FA26*1000 | FB27: =FB24/FB26*1000 | FC27: =AM27 | FE27: =FE24/FE26*1000 | FF27: =FF24/FF26*1000 | FG27: =AN27 | FI27: =FI24/FI26*1000 | FJ27: =FJ24/FJ26*1000 | FK27: =AO27 | FM27: =FM24/FM26*1000 | FN27: =FK27 | FO27: =AP27
A28: load factor | B28: FSC's Passenger load factor | C28: =C24/C22 | D28: =D24/D22 | E28: =E24/E22 | F28: =F24/F22 | G28: =G24/G22 | H28: =H24/H22 | I28: =I24/I22 | J28: =J24/J22 | ... AP28: =AP24/AP22 | AQ28: =AP28 | AR28: =AQ28 | AS28: =AR28 | AT28: =AS28 | AX28: =L28 | AZ28: =AZ24/AZ22 | BA28: =BA24/BA22 | BB28: =M28 | BD28: =BD24/BD22 | BE28: =BE24/BE22 | BF28: =N28 | BH28: =BH24/BH22 | BI28: =BI24/BI22 | BJ28: =O28 | BL28: =BL24/BL22 | BM28: =BM24/BM22 | BN28: =P28 | BP28: =BP24/BP22 | BQ28: =BQ24/BQ22 | BR28: =Q28 | BT28: =BT24/BT22 | BU28: =BU24/BU22 | BV28: =R28 | BX28: =BX24/BX22 | BY28: =BY24/BY22 | BZ28: =S28 | CB28: =CB24/CB22 | CC28: =CC24/CC22 | CD28: =T28 | CF28: =CF24/CF22 | CG28: =CG24/CG22 | CH28: =U28 | CJ28: =CJ24/CJ22 | CK28: =CK24/CK22 | CL28: =V28 | CN28: =CN24/CN22 | CO28: =CO24/CO22 | CP28: =W28 | CR28: =CR24/CR22 | CS28: =CS24/CS22 | CT28: =CT24/CT22 | CU28: =X28 | CW28: =CW24/CW22 | CX28: =CX24/CX22 | CY28: =Y28 | DA28: =DA24/DA22 | DB28: =DB24/DB22 | DC28: =Z28 | DE28: =DE24/DE22 | DF28: =DF24/DF22 | DG28: =AA28 | DI28: =DI24/DI22 | DJ28: =DJ24/DJ22 | DK28: =AB28 | DM28: =DM24/DM22 | DN28: =DN24/DN22 | DO28: =AC28 | DQ28: =DQ24/DQ22 | DR28: =DR24/DR22 | DS28: =AD28 | DU28: =DU24/DU22 | DV28: =DV24/DV22 | DW28: =AE28 | DY28: =DY24/DY22 | DZ28: =DZ24/DZ22 | EA28: =AF28 | EC28: =EC24/EC22 | ED28: =ED24/ED22 | EE28: =AG28 | EG28: =EG24/EG22 | EH28: =EH24/EH22 | EI28: =AH28 | EK28: =EK24/EK22 | EL28: =EL24/EL22 | EM28: =AI28 | EO28: =EO24/EO22 | EP28: =EP24/EP22 | EQ28: =EQ24/EQ22 | ES28: =ES24/ES22 | ET28: =ET24/ET22 | EU28: =EU24/EU22 | EW28: =EW24/EW22 | EX28: =EX24/EX22 | EY28: =EY24/EY22 | FA28: =FA24/FA22 | FB28: =FB24/FB22 | FC28: =FC24/FC22 | FE28: =FE24/FE22 | FF28: =FF24/FF22 | FG28: =FG24/FG22 | FI28: =FI24/FI22 | FJ28: =FJ24/FJ22 | FK28: =FK24/FK22 | FM28: =FM24/FM22 | FN28: =FJ28 | FO28: =FO24/FO22
B29: FSC's pax yield | C29: =C112/C24 | D29: =D112/D24 | E29: =E112/E24 | F29: =F112/F24 | G29: =G112/G24 | H29: =H112/H24 | I29: =I112/I24 | J29: =J112/J24 | ... AH29: =AH112/AH24 | AI29: =AI35/AI24 | AJ29: =AJ35/AJ24 | AK29: =AK35/AK24 | AL29: =AL35/AL24 | AM29: =AM35/AM24 | AN29: =AN35/AN24 | AO29: =AO35/AO24 | AP29: =AP35/AP24 | AQ29: =+AP29*(1+AQ30) | AR29: =+AQ29*(1+AR30) | AS29: =+AR29*(1+AS30) | AT29: =+AS29*(1+AT30) | AV29: =AV35/AV24 | AW29: =AW35/AW24 | AX29: =L29 | AZ29: =AZ35/AZ24 | BA29: =BA35/BA24 | BB29: =M29 | BD29: =BD35/BD24 | BE29: =BE35/BE24 | BF29: =N29 | BH29: =BH35/BH24 | BI29: =BI35/BI24 | BJ29: =O29 | BL29: =BL35/BL24 | BM29: =BM35/BM24 | BN29: =P29 | BP29: =BP35/BP24 | BQ29: =BQ35/BQ24 | BR29: =Q29 | BT29: =BT35/BT24 | BU29: =BU35/BU24 | BV29: =R29 | BX29: =BX35/BX24 | BY29: =BY35/BY24 | BZ29: =S29 | CB29: =CB35/CB24 | CC29: =CC35/CC24 | CD29: =T29 | CF29: =CF35/CF24 | CG29: =CG35/CG24 | CH29: =U29 | CJ29: =CJ35/CJ24 | CK29: =CK35/CK24 | CL29: =V29 | CN29: =CN35/CN24 | CO29: =CO35/CO24 | CP29: =W29 | CR29: =CR35/CR24 | CS29: =CS35/CS24 | CT29: =CT35/CT24 | CU29: =X29 | CW29: =CW35/CW24 | CX29: =CX35/CX24 | CY29: =Y29 | DA29: =DA35/DA24 | DB29: =DB35/DB24 | DC29: =Z29 | DE29: =DE35/DE24 | DF29: =DF35/DF24 | DG29: =AA29 | DI29: =DI35/DI24 | DJ29: =DJ35/DJ24 | DK29: =AB29 | DM29: =DM35/DM24 | DN29: =DN35/DN24 | DO29: =AC29 | DQ29: =DQ35/DQ24 | DR29: =DR35/DR24 | DS29: =AD29 | DU29: =DU35/DU24 | DV29: =DV35/DV24 | DW29: =AE29 | DY29: =DY35/DY24 | DZ29: =DZ35/DZ24 | EA29: =AF29 | EC29: =EC35/EC24 | ED29: =ED35/ED24 | EE29: =AG29 | EG29: =EG35/EG24 | EH29: =EH35/EH24 | EI29: =AH29 | EK29: =EK35/EK24 | EL29: =EL35/EL24 | EM29: =AI29 | EO29: 0.555 | EP29: =EP35/EP24 | EQ29: =AJ29 | ES29: 0.945 | ET29: =ET35/ET24 | EU29: =AK29 | EW29: 1.143 | EX29: =EX35/EX24 | EY29: =AL29 | FA29: 0.774 | FB29: =FB35/FB24 | FC29: =AM29 | FE29: 0.689 | FF29: =FF35/FF24 | FG29: =AN29 | FI29: 0.604 | FJ29: =FJ35/FJ24 | FK29: =AO29 | FM29: 0.661 | FN29: =FJ29*(1+FN30) | FO29: =AP29
A30: pax yield chg | B30: YoY change in passenger yield | D30: =D29/C29-1 | E30: =E29/D29-1 | F30: =F29/E29-1 | G30: =G29/F29-1 | H30: =H29/G29-1 | I30: =I29/H29-1 | J30: =J29/I29-1 | K30: =K29/J29-1 | L30: -0.057 | M30: =M29/L29-1 | N30: =N29/M29-1 | O30: =O29/N29-1 | P30: =P29/O29-1 | Q30: =Q29/P29-1 | R30: =R29/Q29-1 | S30: =S29/R29-1 | T30: =T29/S29-1 | ... V30: =V29/U29-1 | W30: =(45129/W24)/V29-1 | X30: =X29/W29-1 | Y30: =Y29/X29-1 | Z30: =Z29/Y29-1 | AA30: =AA29/Z29-1 | AB30: =AB29/AA29-1 | AC30: =AC29/AB29-1 | AD30: =AD29/AC29-1 | AE30: =AE29/AD29-1 | ... AP30: =AP29/AO29-1 | AQ30: -0.05 | AR30: 0 | AS30: 0 | AT30: 0 | AX30: =L30 | AZ30: =AZ29/AV29-1 | BA30: =BA29/AW29-1 | BB30: =M30 | BD30: =BD29/AZ29-1 | BE30: =BE29/BA29-1 | BF30: =N30 | BH30: -0.0075 | BI30: =BI29/BE29-1 | BJ30: =O30 | BL30: =BL29/BH29-1 | BM30: =BM29/BI29-1 | BN30: =P30 | BP30: =BP29/BL29-1 | BQ30: =BQ29/BM29-1 | BR30: =Q30 | BT30: =BT29/BP29-1 | BU30: =BU29/BQ29-1 | BV30: =R30 | BX30: =BX29/BT29-1 | BY30: =BY29/BU29-1 | BZ30: =S30 | CB30: =CB29/BX29-1 | CC30: =CC29/BY29-1 | CD30: =T30 | CF30: =CF29/CB29-1 | CG30: =CG29/CC29-1 | CH30: =U30 | CJ30: =CJ29/CF29-1 | CK30: =CK29/CG29-1 | CL30: =V30 | CN30: =CN29/CJ29-1 | CO30: =CO29/CK29-1 | CP30: =W30 | CR30: =CR29/CN29-1 | CS30: =CS29/CN29-1 | CT30: =+CT29/CO29-1 | CU30: =X30 | CW30: =CW29/CS29-1 | CX30: =CX29/CT29-1 | CY30: =Y30 | DA30: =DA29/CW29-1 | DB30: =DB29/CX29-1 | DC30: =Z30 | DE30: =DE29/DA29-1 | DF30: =DF29/DB29-1 | DG30: =AA30 | DI30: =DI29/DE29-1 | DJ30: =DJ29/DF29-1 | DK30: =AB30 | DM30: =DM29/DI29-1 | DN30: =DN29/DJ29-1 | DO30: =AC30 | DQ30: =DQ29/DM29-1 | DR30: =+DR29/DN29-1 | DS30: =AD30 | DU30: =DU29/DQ29-1 | DV30: =+DV29/DR29-1 | DW30: =AE30 | DY30: =DY29/DU29-1 | DZ30: =+DZ29/DV29-1 | EA30: =AF30 | EC30: =EC29/DY29-1 | ED30: =+ED29/DZ29-1 | EE30: =AG30 | EG30: =EG29/EC29-1 | EH30: =+EH29/ED29-1 | EI30: =AH30 | EK30: =EK29/EG29-1 | EL30: =+EL29/EH29-1 | EM30: =AI30 | EO30: =EO29/EK29-1 | EP30: =+EP29/EL29-1 | EQ30: =AJ30 | ES30: =ES29/EO29-1 | ET30: =+ET29/EP29-1 | EU30: =AK30 | EW30: =EW29/ES29-1 | EX30: =EX29/ET29-1 | EY30: =AL30 | FA30: =FA29/EW29-1 | FB30: =FB29/EX29-1 | FC30: =AM30 | FE30: =FE29/FA29-1 | FF30: =FF29/FB29-1 | FG30: =AN30 | FI30: =FI29/FE29-1 | FJ30: =FJ29/FF29-1 | FK30: =AO30 | FM30: =FM29/FI29-1 | FN30: =FM30 | FO30: =AP30
B31: FSC's unit revenue (RASK) | C31: =C35/C22 | D31: =D35/D22 | E31: =E35/E22 | F31: =F35/F22 | G31: =G35/G22 | H31: =H35/H22 | I31: =I35/I22 | J31: =J35/J22 | ... AT31: =AT35/AT22 | BD31: =BD35/BD22 | BE31: =BE35/BE22 | BF31: =BF35/BF22 | BH31: =BH35/BH22 | BI31: =BI35/BI22 | BJ31: =BJ35/BJ22 | BL31: =BL35/BL22 | BM31: =BM35/BM22 | BN31: =BN35/BN22 | BP31: =BP35/BP22 | BQ31: =BQ35/BQ22 | BR31: =BR35/BR22 | BT31: =BT35/BT22 | BU31: =BU35/BU22 | BV31: =BV35/BV22 | BX31: =BX35/BX22 | BY31: =BY35/BY22 | BZ31: =BZ35/BZ22 | CB31: =CB35/CB22 | CC31: =CC35/CC22 | CD31: =CD35/CD22 | CF31: =CF35/CF22 | CG31: =CG35/CG22 | CH31: =CH35/CH22 | CJ31: =CJ35/CJ22 | CK31: =CK35/CK22 | CL31: =CL35/CL22 | CN31: =CN35/CN22 | CO31: =CO35/CO22 | CP31: =CP35/CP22 | CR31: =CR35/CR22 | CS31: =CS35/CS22 | CT31: =CT35/CT22 | CU31: =CU35/CU22 | CW31: =CW35/CW22 | CX31: =CX35/CX22 | CY31: =CY35/CY22 | DA31: =DA35/DA22 | DB31: =DB35/DB22 | DC31: =DC35/DC22 | DE31: =DE35/DE22 | DF31: =DF35/DF22 | DG31: =DG35/DG22 | DI31: =DI35/DI22 | DJ31: =DJ35/DJ22 | DK31: =DK35/DK22 | DM31: =DM35/DM22 | DN31: =DN35/DN22 | DO31: =DO35/DO22 | DQ31: =DQ35/DQ22 | DR31: =DR35/DR22 | DS31: =DS35/DS22 | DU31: =DU35/DU22 | DV31: =DV35/DV22 | DW31: =DW35/DW22 | DY31: =DY35/DY22 | DZ31: =DZ35/DZ22 | EA31: =EA35/EA22 | EC31: =EC35/EC22 | ED31: =ED35/ED22 | EE31: =EE35/EE22 | EG31: =EG35/EG22 | EH31: =EH35/EH22 | EI31: =EI35/EI22 | EK31: =EK35/EK22 | EL31: =EL35/EL22 | EM31: =EM35/EM22 | EO31: =EO35/EO22 | EP31: =EP35/EP22 | EQ31: =EQ35/EQ22 | ES31: =ES35/ES22 | ET31: =ET35/ET22 | EU31: =EU35/EU22 | EW31: =EW35/EW22 | EX31: =EX35/EX22 | EY31: =EY35/EY22 | FA31: =FA35/FA22 | FB31: =FB35/FB22 | FC31: =FC35/FC22 | FE31: =FE35/FE22 | FF31: =FF35/FF22 | FG31: =FG35/FG22 | FI31: =FI35/FI22 | FJ31: =FJ35/FJ22 | FK31: =FK35/FK22 | FM31: =FM35/FM22 | FN31: =FN35/FN22 | FO31: =FO35/FO22
B32: YoY change in RASK | D32: =D31/C31-1 | E32: =E31/D31-1 | F32: =F31/E31-1 | G32: =G31/F31-1 | H32: =H31/G31-1 | I32: =I31/H31-1 | J32: =J31/I31-1 | K32: =K31/J31-1 | ... AT32: =AT31/AS31-1 | BH32: =BH31/BD31-1 | BI32: =BI31/BE31-1 | BJ32: =BJ31/BF31-1 | BL32: =BL31/BH31-1 | BM32: =BM31/BI31-1 | BN32: =BN31/BJ31-1 | BP32: =BP31/BL31-1 | BQ32: =BQ31/BM31-1 | BR32: =BR31/BN31-1 | BT32: =BT31/BP31-1 | BU32: =BU31/BQ31-1 | BV32: =BV31/BR31-1 | BX32: =BX31/BT31-1 | BY32: =BY31/BU31-1 | BZ32: =BZ31/BV31-1 | CB32: =CB31/BX31-1 | CC32: =CC31/BY31-1 | CD32: =CD31/BZ31-1 | CF32: =CF31/CB31-1 | CG32: =CG31/CC31-1 | CH32: =CH31/CD31-1 | CJ32: =CJ31/CF31-1 | CK32: =CK31/CG31-1 | CL32: =CL31/CH31-1 | CN32: =CN31/CJ31-1 | CO32: =CO31/CK31-1 | CP32: =CP31/CL31-1 | CR32: =CR31/CN31-1 | CS32: =CS31/CN31-1 | CT32: =CT31/CO31-1 | CU32: =CU31/CP31-1 | CW32: =CW31/CS31-1 | CX32: =CX31/CT31-1 | CY32: =CY31/CU31-1 | DA32: =DA31/CW31-1 | DB32: =DB31/CX31-1 | DC32: =DC31/CY31-1 | DE32: =DE31/DA31-1 | DF32: =DF31/DB31-1 | DG32: =DG31/DC31-1 | DI32: =DI31/DE31-1 | DJ32: =DJ31/DF31-1 | DK32: =DK31/DG31-1 | DM32: =DM31/DI31-1 | DN32: =DN31/DJ31-1 | DO32: =DO31/DK31-1 | DQ32: =DQ31/DM31-1 | DR32: =DR31/DN31-1 | DS32: =DS31/DO31-1 | DU32: =DU31/DQ31-1 | DV32: =DV31/DR31-1 | DW32: =DW31/DS31-1 | DY32: =DY31/DU31-1 | DZ32: =DZ31/DV31-1 | EA32: =EA31/DW31-1 | EC32: =EC31/DY31-1 | ED32: =ED31/DZ31-1 | EE32: =EE31/EA31-1 | EG32: =EG31/EC31-1 | EH32: =EH31/ED31-1 | EI32: =EI31/EE31-1 | EK32: =EK31/EG31-1 | EL32: =EL31/EH31-1 | EM32: =EM31/EI31-1 | EO32: =EO31/EK31-1 | EP32: =EP31/EL31-1 | EQ32: =EQ31/EM31-1 | ES32: =ES31/EO31-1 | ET32: =ET31/EP31-1 | EU32: =EU31/EQ31-1 | EW32: =EW31/ES31-1 | EX32: =EX31/ET31-1 | EY32: =EY31/EU31-1 | FA32: =FA31/EW31-1 | FB32: =FB31/EX31-1 | FC32: =FC31/EY31-1 | FE32: =FE31/FA31-1 | FF32: =FF31/FB31-1 | FG32: =FG31/FC31-1 | FI32: =FI31/FE31-1 | FJ32: =FJ31/FF31-1 | FK32: =FK31/FG31-1 | FM32: =FM31/FI31-1 | FN32: =FN31/FJ31-1 | FO32: =FO31/FK31-1
B33: Average airfare ticket price | C33: =+C35/C26*1000 | D33: =+D35/D26*1000 | E33: =+E35/E26*1000 | F33: =+F35/F26*1000 | G33: =+G35/G26*1000 | H33: =+H35/H26*1000 | I33: =+I35/I26*1000 | J33: =+J35/J26*1000 | ... AT33: =+AT35/AT26*1000 | BH33: =+BH35/BH26*1000 | BI33: =+BI35/BI26*1000 | BJ33: =+BJ35/BJ26*1000 | BL33: =+BL35/BL26*1000 | BM33: =+BM35/BM26*1000 | BN33: =+BN35/BN26*1000 | BP33: =+BP35/BP26*1000 | BQ33: =+BQ35/BQ26*1000 | BR33: =+BR35/BR26*1000 | BT33: =+BT35/BT26*1000 | BU33: =+BU35/BU26*1000 | BV33: =+BV35/BV26*1000 | BX33: =+BX35/BX26*1000 | BY33: =+BY35/BY26*1000 | BZ33: =+BZ35/BZ26*1000 | CB33: =+CB35/CB26*1000 | CC33: =+CC35/CC26*1000 | CD33: =+CD35/CD26*1000 | CF33: =+CF35/CF26*1000 | CG33: =+CG35/CG26*1000 | CH33: =+CH35/CH26*1000 | CJ33: =+CJ35/CJ26*1000 | CK33: =+CK35/CK26*1000 | CL33: =+CL35/CL26*1000 | CN33: =+CN35/CN26*1000 | CO33: =+CO35/CO26*1000 | CP33: =+CP35/CP26*1000 | CR33: =+CR35/CR26*1000 | CS33: =+CS35/CS26*1000 | CT33: =+CT35/CT26*1000 | CU33: =+CU35/CU26*1000 | CW33: =+CW35/CW26*1000 | CX33: =+CX35/CX26*1000 | CY33: =+CY35/CY26*1000 | DA33: =+DA35/DA26*1000 | DB33: =+DB35/DB26*1000 | DC33: =+DC35/DC26*1000 | DE33: =+DE35/DE26*1000 | DF33: =+DF35/DF26*1000 | DG33: =+DG35/DG26*1000 | DI33: =+DI35/DI26*1000 | DJ33: =+DJ35/DJ26*1000 | DK33: =+DK35/DK26*1000 | DM33: =+DM35/DM26*1000 | DN33: =+DN35/DN26*1000 | DO33: =+DO35/DO26*1000 | DQ33: =+DQ35/DQ26*1000 | DR33: =+DR35/DR26*1000 | DS33: =+DS35/DS26*1000 | DU33: =+DU35/DU26*1000 | DV33: =+DV35/DV26*1000 | DW33: =+DW35/DW26*1000 | DY33: =+DY35/DY26*1000 | DZ33: =+DZ35/DZ26*1000 | EA33: =+EA35/EA26*1000 | EC33: =+EC35/EC26*1000 | ED33: =+ED35/ED26*1000 | EE33: =+EE35/EE26*1000 | EG33: =+EG35/EG26*1000 | EH33: =+EH35/EH26*1000 | EI33: =+EI35/EI26*1000 | EK33: =+EK35/EK26*1000 | EL33: =+EL35/EL26*1000 | EM33: =+EM35/EM26*1000 | EO33: =+EO35/EO26*1000 | EP33: =+EP35/EP26*1000 | EQ33: =+EQ35/EQ26*1000 | ES33: =+ES35/ES26*1000 | ET33: =+ET35/ET26*1000 | EU33: =+EU35/EU26*1000 | EW33: =+EW35/EW26*1000 | EX33: =+EX35/EX26*1000 | EY33: =+EY35/EY26*1000 | FA33: =+FA35/FA26*1000 | FB33: =+FB35/FB26*1000 | FC33: =+FC35/FC26*1000 | FE33: =+FE35/FE26*1000 | FF33: =+FF35/FF26*1000 | FG33: =+FG35/FG26*1000 | FI33: =+FI35/FI26*1000 | FJ33: =+FJ35/FJ26*1000 | FK33: =+FK35/FK26*1000 | FM33: =+FM35/FM26*1000 | FN33: =+FN35/FN26*1000 | FO33: =+FO35/FO26*1000
B34: YoY change in average airfare ticket price | D34: =D33/C33-1 | E34: =E33/D33-1 | F34: =F33/E33-1 | G34: =G33/F33-1 | H34: =H33/G33-1 | I34: =I33/H33-1 | J34: =J33/I33-1 | K34: =K33/J33-1 | ... AT34: =AT33/AS33-1 | BL34: =BL33/BH33-1 | BM34: =BM33/BI33-1 | BN34: =BN33/BJ33-1 | BP34: =BP33/BL33-1 | BQ34: =BQ33/BM33-1 | BR34: =BR33/BN33-1 | BT34: =BT33/BP33-1 | BU34: =BU33/BQ33-1 | BV34: =BV33/BR33-1 | BX34: =BX33/BT33-1 | BY34: =BY33/BU33-1 | BZ34: =BZ33/BV33-1 | CB34: =CB33/BX33-1 | CC34: =CC33/BY33-1 | CD34: =CD33/BZ33-1 | CF34: =CF33/CB33-1 | CG34: =CG33/CC33-1 | CH34: =CH33/CD33-1 | CJ34: =CJ33/CF33-1 | CK34: =CK33/CG33-1 | CL34: =CL33/CH33-1 | CN34: =CN33/CJ33-1 | CO34: =CO33/CK33-1 | CP34: =CP33/CL33-1 | CR34: =CR33/CN33-1 | CS34: =CS33/CN33-1 | CT34: =CT33/CO33-1 | CU34: =CU33/CP33-1 | CW34: =CW33/CS33-1 | CX34: =CX33/CT33-1 | CY34: =CY33/CU33-1 | DA34: =DA33/CW33-1 | DB34: =DB33/CX33-1 | DC34: =DC33/CY33-1 | DE34: =DE33/DA33-1 | DF34: =DF33/DB33-1 | DG34: =DG33/DC33-1 | DI34: =DI33/DE33-1 | DJ34: =DJ33/DF33-1 | DK34: =DK33/DG33-1 | DM34: =DM33/DI33-1 | DN34: =DN33/DJ33-1 | DO34: =DO33/DK33-1 | DQ34: =DQ33/DM33-1 | DR34: =DR33/DN33-1 | DS34: =DS33/DO33-1 | DU34: =DU33/DQ33-1 | DV34: =DV33/DR33-1 | DW34: =DW33/DS33-1 | DY34: =DY33/DU33-1 | DZ34: =DZ33/DV33-1 | EA34: =EA33/DW33-1 | EC34: =EC33/DY33-1 | ED34: =ED33/DZ33-1 | EE34: =EE33/EA33-1 | EG34: =EG33/EC33-1 | EH34: =EH33/ED33-1 | EI34: =EI33/EE33-1 | EK34: =EK33/EG33-1 | EL34: =EL33/EH33-1 | EM34: =EM33/EI33-1 | EO34: =EO33/EK33-1 | EP34: =EP33/EL33-1 | EQ34: =EQ33/EM33-1 | ES34: =ES33/EO33-1 | ET34: =ET33/EP33-1 | EU34: =EU33/EQ33-1 | EW34: =EW33/ES33-1 | EX34: =EX33/ET33-1 | EY34: =EY33/EU33-1 | FA34: =FA33/EW33-1 | FB34: =FB33/EX33-1 | FC34: =FC33/EY33-1 | FE34: =FE33/FA33-1 | FF34: =FF33/FB33-1 | FG34: =FG33/FC33-1 | FI34: =FI33/FE33-1 | FJ34: =FJ33/FF33-1 | FK34: =FK33/FG33-1 | FM34: =FM33/FI33-1 | FN34: =FN33/FJ33-1 | FO34: =FO33/FK33-1
B35: FSC Passenger Revenue | C35: =+C112-C50 | D35: =+D112-D50 | E35: =+E112-E50 | F35: =+F112-F50 | G35: =+G112-G50 | H35: =+H112-H50 | I35: =+I112-I50 | J35: =+J112-J50 | ... AN35: =+AN112-AN50 | AO35: =SUM(FI35:FJ35) | AP35: =SUM(FM35:FN35) | AQ35: =AQ24*AQ29 | AR35: =AR24*AR29 | AS35: =AS24*AS29 | AT35: =AT24*AT29 | AV35: =+AV112-AV50 | AW35: =+AW112-AW50 | AX35: =+AX112-AX50 | AZ35: =+AZ112-AZ50 | BA35: =+BA112-BA50 | BB35: =+BB112-BB50 | BD35: =+BD112-BD50 | BE35: =+BE112-BE50 | BF35: =+BF112-BF50 | BH35: =+BH112-BH50 | BI35: =+BI112-BI50 | BJ35: =+BJ112-BJ50 | BL35: =+BL112-BL50 | BM35: =+BM112-BM50 | BN35: =+BN112-BN50 | BP35: =+BP112-BP50 | BQ35: =+BQ112-BQ50 | BR35: =+BR112-BR50 | BT35: =+BT112-BT50 | BU35: =+BU112-BU50 | BV35: =+BV112-BV50 | BX35: =+BX112-BX50 | BY35: =+BY112-BY50 | BZ35: =+BZ112-BZ50 | CB35: =+CB112-CB50 | CC35: =+CC112-CC50 | CD35: =+CD112-CD50 | CF35: =+CF112-CF50 | CG35: =+CG112-CG50 | CH35: =+CH112-CH50 | CJ35: =+CJ112-CJ50 | CK35: =+CK112-CK50 | CL35: =+CL112-CL50 | CN35: =+CN112-CN50 | CO35: =+CO112-CO50 | CP35: =+CP112-CP50 | CR35: =+CR112-CR50 | CS35: =+CS112-CS50 | CT35: =+CT112-CT50 | CU35: =+CU112-CU50 | CW35: =+CW112-CW50 | CX35: =+CX112-CX50 | CY35: =+CY112-CY50 | DA35: =+DA112-DA50 | DB35: =+DB112-DB50 | DC35: =+DC112-DC50 | DE35: =+DE112-DE50 | DF35: =+DF112-DF50 | DG35: =+DG112-DG50 | DI35: =+DI112-DI50 | DJ35: =+DJ112-DJ50 | DK35: =+DK112-DK50 | DM35: =+DM112-DM50 | DN35: =+DN112-DN50 | DO35: =+DO112-DO50 | DQ35: =+DQ112-DQ50 | DR35: =+DR112-DR50 | DS35: =+DS112-DS50 | DU35: =+DU112-DU50 | DV35: =+DV112-DV50 | DW35: =+DW112-DW50 | DY35: =+DY112-DY50 | DZ35: =+DZ112-DZ50 | EA35: =+EA112-EA50 | EC35: =+EC112-EC50 | ED35: =+ED112-ED50 | EE35: =+EE112-EE50 | EG35: =+EG112-EG50 | EH35: =+EH112-EH50 | EI35: =+EI112-EI50 | EK35: =+EK112-EK50 | EL35: =+EL112-EL50 | EM35: =+EM112-EM50 | EO35: =+EO112-EO50 | EP35: =+EP112-EP50 | EQ35: =+EQ112-EQ50 | ES35: =+ES112-ES50 | ET35: =+ET112-ET50 | EU35: =+EU112-EU50 | EW35: =+EW24*EW29 | EX35: =+EX112-EX50 | EY35: =+EY112-EY50 | FA35: =+FA112-FA50 | FB35: =+FB112-FB50 | FC35: =+FC112-FC50 | FE35: =+FE112-FE50 | FF35: =+FF112-FF50 | FG35: =+FG112-FG50 | FI35: =+FI112-FI50 | FJ35: =+FJ112-FJ50 | FK35: =+FK24*FK29 | FM35: =+FM24*FM29 | FN35: =+FN24*FN29 | FO35: =+FO24*FO29
B37: LCC's ask | AI37: 4583 | AJ37: 1742 | AK37: 71 | AL37: 983 | AM37: 9432 | AN37: 13764 | AO37: =SUM(FI37:FJ37) | AP37: =SUM(FM37:FN37) | AQ37: =+AP37*(1+AQ38) | AR37: =+AQ37*(1+AR38) | AS37: =+AR37*(1+AS38) | AT37: =+AS37*(1+AT38) | EL37: =EM37-EK37 | EM37: =AI37 | EO37: 1726 | EP37: =EQ37-EO37 | EQ37: =AJ37 | ES37: 26 | ET37: =EU37-ES37 | EU37: =AK37 | EW37: 69 | EX37: =EY37-EW37 | EY37: =AL37 | FA37: 4054 | FB37: =FC37-FA37 | FC37: =AM37 | FE37: 6370 | FF37: =FG37-FE37 | FG37: =AN37 | FI37: =SUMIFS(Monthly!$145:$145,Monthly!$8:$8,">="&DATE(MID(FI$3,3,4),1,1),Monthly!$8:$8,"<="&DATE(MID(FI$3,3,4),6,30)) | FJ37: =FK37-FI37 | FK37: =AO37 | FM37: =SUMIFS(Monthly!$145:$145,Monthly!$8:$8,">="&DATE(MID(FM$3,3,4),1,1),Monthly!$8:$8,"<="&DATE(MID(FM$3,3,4),6,30)) | FN37: =FJ37*(1+FN38) | FO37: =AP37
B38: YoY change in overall capacity (ASK) | AJ38: =AJ37/AI37-1 | AK38: =AK37/AJ37-1 | AL38: =AL37/AK37-1 | AM38: =AM37/AL37-1 | AN38: =AN37/AM37-1 | AO38: =AO37/AN37-1 | AP38: =AP37/AO37-1 | AQ38: 0.05 | AR38: 0.05 | AS38: 0.05 | AT38: 0.05 | EP38: =EP37/EL37-1 | EQ38: =EQ37/EM37-1 | ES38: =ES37/EO37-1 | ET38: =ET37/EP37-1 | EU38: =EU37/EQ37-1 | EW38: =EW37/ES37-1 | EX38: =EX37/ET37-1 | EY38: =EY37/EU37-1 | FA38: =FA37/EW37-1 | FB38: =FB37/EX37-1 | FC38: =FC37/EY37-1 | FE38: =FE37/FA37-1 | FF38: =FF37/FB37-1 | FG38: =FG37/FC37-1 | FI38: =FI37/FE37-1 | FJ38: =FJ37/FF37-1 | FK38: =FK37/FG37-1 | FM38: =FM37/FI37-1 | FN38: 0.08 | FO38: =FO37/FK37-1
B39: LCC's rpk | AI39: 4195 | AJ39: 1237 | AK39: 6 | AL39: 671 | AM39: 8112 | AN39: 11481 | AO39: =SUM(FI39:FJ39) | AP39: =SUM(FM39:FN39) | AQ39: =AQ43*AQ37 | AR39: =AR43*AR37 | AS39: =AS43*AS37 | AT39: =AT43*AT37 | EL39: =+EM39-EK39 | EM39: =AI39 | EO39: 1480 | EP39: =+EQ39-EO39 | EQ39: =AJ39 | ES39: 2 | ET39: =+EU39-ES39 | EU39: =AK39 | EW39: 13 | EX39: =+EY39-EW39 | EY39: =AL39 | FA39: 3465 | FB39: =+FC39-FA39 | FC39: =AM39 | FE39: 5415 | FF39: =+FG39-FE39 | FG39: =AN39 | FI39: =SUMIFS(Monthly!$149:$149,Monthly!$8:$8,">="&DATE(MID(FI$3,3,4),1,1),Monthly!$8:$8,"<="&DATE(MID(FI$3,3,4),6,30)) | FJ39: =+FK39-FI39 | FK39: =AO39 | FM39: =SUMIFS(Monthly!$149:$149,Monthly!$8:$8,">="&DATE(MID(FM$3,3,4),1,1),Monthly!$8:$8,"<="&DATE(MID(FM$3,3,4),6,30)) | FN39: =FN37*FN43 | FO39: =AP39
B40: YoY change in passenger traffic (RPK) | AJ40: =AJ39/AI39-1 | AK40: =AK39/AJ39-1 | AL40: =AL39/AK39-1 | AM40: =AM39/AL39-1 | AN40: =AN39/AM39-1 | AO40: =+AO39/AN39-1 | AP40: =+AP39/AO39-1 | AQ40: =+AQ39/AP39-1 | AR40: =+AR39/AQ39-1 | AS40: =+AS39/AR39-1 | AT40: =+AT39/AS39-1 | EP40: =EP39/EL39-1 | EQ40: =EQ39/EM39-1 | ES40: =ES39/EO39-1 | ET40: =ET39/EP39-1 | EU40: =EU39/EQ39-1 | EW40: =EW39/ES39-1 | EX40: =EX39/ET39-1 | EY40: =EY39/EU39-1 | FA40: =FA39/EW39-1 | FB40: =FB39/EX39-1 | FC40: =FC39/EY39-1 | FE40: =FE39/FA39-1 | FF40: =FF39/FB39-1 | FG40: =FG39/FC39-1 | FI40: =FI39/FE39-1 | FJ40: =FJ39/FF39-1 | FK40: =FK39/FG39-1 | FM40: =FM39/FI39-1 | FN40: =FN39/FJ39-1 | FO40: =FO39/FK39-1
B41: LCC's Passenger nos (000s) | AI41: 1888 | AJ41: 572 | AK41: 8 | AL41: 314 | AM41: 4146 | AN41: 6100 | AO41: =SUM(FI41:FJ41) | AP41: =SUM(FM41:FN41) | AQ41: =AQ39/AQ42*1000 | AR41: =AR39/AR42*1000 | AS41: =AS39/AS42*1000 | AT41: =AT39/AT42*1000 | EL41: =EM41-EK41 | EM41: =AI41 | EO41: 570 | EP41: =EQ41-EO41 | EQ41: =AJ41 | ES41: 2 | ET41: =EU41-ES41 | EU41: =AK41 | EW41: 9 | EX41: =EY41-EW41 | EY41: =AL41 | FA41: 1743 | FB41: =FC41-FA41 | FC41: =AM41 | FE41: 2839 | FF41: =FG41-FE41 | FG41: =AN41 | FI41: 3791 | FJ41: =FK41-FI41 | FK41: =AO41 | FM41: 4163 | FN41: =FN39/FN42*1000 | FO41: =AP41
B42: LCC's Trip length (kms) | AI42: =AI39*1000/AI41 | AJ42: =AJ39*1000/AJ41 | AK42: =AK39*1000/AK41 | AL42: =AL39*1000/AL41 | AM42: =AM39*1000/AM41 | AN42: =AN39*1000/AN41 | AO42: =AO39*1000/AO41 | AP42: =AP39*1000/AP41 | AQ42: =AP42 | AR42: =AQ42 | AS42: =AR42 | AT42: =AS42 | EL42: =EL39/EL41*1000 | EM42: =EM39*1000/EM41 | EO42: =EO39*1000/EO41 | EP42: =EP39/EP41*1000 | EQ42: =EQ39*1000/EQ41 | ES42: =ES39*1000/ES41 | ET42: =ET39/ET41*1000 | EU42: =EU39*1000/EU41 | EW42: =EW39*1000/EW41 | EX42: =EX39/EX41*1000 | EY42: =EY39*1000/EY41 | FA42: =FA39*1000/FA41 | FB42: =FB39/FB41*1000 | FC42: =FC39*1000/FC41 | FE42: =FE39*1000/FE41 | FF42: =FF39/FF41*1000 | FG42: =FG39*1000/FG41 | FI42: =FI39*1000/FI41 | FJ42: =FJ39/FJ41*1000 | FK42: =FK39*1000/FK41 | FM42: =FM39*1000/FM41 | FN42: =FM42 | FO42: =FO39*1000/FO41
B43: LCC's Passenger load factor | AI43: =AI39/AI37 | AJ43: =AJ39/AJ37 | AK43: =AK39/AK37 | AL43: =AL39/AL37 | AM43: =AM39/AM37 | AN43: =AN39/AN37 | AO43: =AO39/AO37 | AP43: =AP39/AP37 | AQ43: =AP43 | AR43: =AQ43 | AS43: =AR43 | AT43: =AS43 | EL43: =EL39/EL37 | EM43: =EM39/EM37 | EO43: =EO39/EO37 | EP43: =EP39/EP37 | EQ43: =EQ39/EQ37 | ES43: =ES39/ES37 | ET43: =ET39/ET37 | EU43: =EU39/EU37 | EW43: =EW39/EW37 | EX43: =EX39/EX37 | EY43: =EY39/EY37 | FA43: =FA39/FA37 | FB43: =FB39/FB37 | FC43: =FC39/FC37 | FE43: =FE39/FE37 | FF43: =FF39/FF37 | FG43: =FG39/FG37 | FI43: =FI39/FI37 | FJ43: =FJ39/FJ37 | FK43: =FK39/FK37 | FM43: =FM39/FM37 | FN43: =FJ43 | FO43: =FO39/FO37
B44: LCC's pax yield | AI44: 0.446 | AJ44: 0.514 | AK44: 1.735 | AL44: =AL50/AL39 | AM44: =AM50/AM39 | AN44: 0.522 | AO44: =AO50/AO39 | AP44: =AP50/AP39 | AQ44: =+AP44*(1+AQ45) | AR44: =+AQ44*(1+AR45) | AS44: =+AR44*(1+AS45) | AT44: =+AS44*(1+AT45) | EL44: =EL50/EL39 | EM44: =EM50/EM39 | EO44: =EO50/EO39 | EP44: nm | EQ44: =EQ50/EQ39 | ES44: 1.913 | ET44: =ET50/ET39 | EU44: =EU50/EU39 | EW44: 1.401 | EX44: =EX50/EX39 | EY44: =EY50/EY39 | FA44: 0.736 | FB44: =FB50/FB39 | FC44: =FC50/FC39 | FE44: 0.551 | FF44: =FF50/FF39 | FG44: =FG50/FG39 | FI44: 0.432 | FJ44: =FJ50/FJ39 | FK44: =FK50/FK39 | FM44: 0.543 | FN44: =FJ44*(1+FN45) | FO44: =FO50/FO39
B45: YoY change in passenger yield | AJ45: =AJ44/AI44-1 | AK45: =AK44/AJ44-1 | AL45: =AL44/AK44-1 | AM45: =AM44/AL44-1 | AN45: =AN44/AM44-1 | AO45: =AO44/AN44-1 | AP45: =AP44/AO44-1 | AQ45: =AQ30 | AR45: =AR30 | AS45: =AS30 | AT45: =AT30 | EP45: =IFERROR(EP44/EL44-1,"nm") | EQ45: =EQ44/EM44-1 | ES45: =ES44/EO44-1 | ET45: =IFERROR(ET44/EP44-1,"nm") | EU45: =EU44/EQ44-1 | EW45: =EW44/ES44-1 | EX45: =IFERROR(EX44/ET44-1,"nm") | EY45: =EY44/EU44-1 | FA45: =FA44/EW44-1 | FB45: =IFERROR(FB44/EX44-1,"nm") | FC45: =FC44/EY44-1 | FE45: =FE44/FA44-1 | FF45: =IFERROR(FF44/FB44-1,"nm") | FG45: =FG44/FC44-1 | FI45: =FI44/FE44-1 | FJ45: =IFERROR(FJ44/FF44-1,"nm") | FK45: =FK44/FG44-1 | FM45: =FM44/FI44-1 | FN45: 0.15 | FO45: =FO44/FK44-1
B46: LCC's unit revenue (RASK) | AI46: =AI50/AI37 | AJ46: =AJ50/AJ37 | AK46: =AK50/AK37 | AL46: =AL50/AL37 | AM46: =AM50/AM37 | AN46: =AN50/AN37 | AO46: =AO50/AO37 | AP46: =AP50/AP37 | ... AT46: =AT50/AT37 | EL46: =EL50/EL37 | EM46: =EM50/EM37 | EO46: =EO50/EO37 | EP46: =EP50/EP37 | EQ46: =EQ50/EQ37 | ES46: =ES50/ES37 | ET46: =ET50/ET37 | EU46: =EU50/EU37 | EW46: =EW50/EW37 | EX46: =EX50/EX37 | EY46: =EY50/EY37 | FA46: =FA50/FA37 | FB46: =FB50/FB37 | FC46: =FC50/FC37 | FE46: =FE50/FE37 | FF46: =FF50/FF37 | FG46: =FG50/FG37 | FI46: =FI50/FI37 | FJ46: =FJ50/FJ37 | FK46: =FK50/FK37 | FM46: =FM50/FM37 | FN46: =FN50/FN37 | FO46: =FO50/FO37
B47: YoY change in RASK | AJ47: =AJ46/AI46-1 | AK47: =AK46/AJ46-1 | AL47: =AL46/AK46-1 | AM47: =AM46/AL46-1 | AN47: =AN46/AM46-1 | AO47: =AO46/AN46-1 | AP47: =AP46/AO46-1 | AQ47: =AQ46/AP46-1 | ... AT47: =AT46/AS46-1 | EQ47: =EQ46/EM46-1 | ES47: =ES46/EO46-1 | ET47: =ET46/EP46-1 | EU47: =EU46/EQ46-1 | EW47: =EW46/ES46-1 | EX47: =EX46/ET46-1 | EY47: =EY46/EU46-1 | FA47: =FA46/EW46-1 | FB47: =FB46/EX46-1 | FC47: =FC46/EY46-1 | FE47: =FE46/FA46-1 | FF47: =FF46/FB46-1 | FG47: =FG46/FC46-1 | FI47: =FI46/FE46-1 | FJ47: =FJ46/FF46-1 | FK47: =FK46/FG46-1 | FM47: =FM46/FI46-1 | FN47: =FN46/FJ46-1 | FO47: =FO46/FK46-1
B48: Average airfare ticket price | AI48: =+AI50/AI41*1000 | AJ48: =+AJ50/AJ41*1000 | AK48: =+AK50/AK41*1000 | AL48: =+AL50/AL41*1000 | AM48: =+AM50/AM41*1000 | AN48: =+AN50/AN41*1000 | AO48: =+AO50/AO41*1000 | AP48: =+AP50/AP41*1000 | ... AT48: =+AT50/AT41*1000 | EL48: =+EL50/EL41*1000 | EM48: =+EM50/EM41*1000 | EO48: =+EO50/EO41*1000 | EP48: nm | EQ48: =+EQ50/EQ41*1000 | ES48: =+ES50/ES41*1000 | ET48: =+ET50/ET41*1000 | EU48: =+EU50/EU41*1000 | EW48: =+EW50/EW41*1000 | EX48: =+EX50/EX41*1000 | EY48: =+EY50/EY41*1000 | FA48: =+FA50/FA41*1000 | FB48: =+FB50/FB41*1000 | FC48: =+FC50/FC41*1000 | FE48: =+FE50/FE41*1000 | FF48: =+FF50/FF41*1000 | FG48: =+FG50/FG41*1000 | FI48: =+FI50/FI41*1000 | FJ48: =+FJ50/FJ41*1000 | FK48: =+FK50/FK41*1000 | FM48: =+FM50/FM41*1000 | FN48: =+FN50/FN41*1000 | FO48: =+FO50/FO41*1000
B49: YoY change in average airfare ticket price | AJ49: =AJ48/AI48-1 | AK49: =AK48/AJ48-1 | AL49: =AL48/AK48-1 | AM49: =AM48/AL48-1 | AN49: =AN48/AM48-1 | AO49: =AO48/AN48-1 | AP49: =AP48/AO48-1 | AQ49: =AQ48/AP48-1 | ... AT49: =AT48/AS48-1 | EP49: =IFERROR(EP48/EL48-1,"nm") | EQ49: =EQ48/EM48-1 | ES49: =ES48/EO48-1 | ET49: =IFERROR(ET48/EP48-1,"nm") | EU49: =EU48/EQ48-1 | EW49: =EW48/ES48-1 | EX49: =EX48/ET48-1 | EY49: =EY48/EU48-1 | FA49: =FA48/EW48-1 | FB49: =FB48/EX48-1 | FC49: =FC48/EY48-1 | FE49: =FE48/FA48-1 | FF49: =FF48/FB48-1 | FG49: =FG48/FC48-1 | FI49: =FI48/FE48-1 | FJ49: =FJ48/FF48-1 | FK49: =FK48/FG48-1 | FM49: =FM48/FI48-1 | FN49: =FN48/FJ48-1 | FO49: =FO48/FK48-1
B50: LCC Passenger Revenue | AI50: 1817 | AJ50: 636 | AK50: 11 | AL50: 646 | AM50: 5486 | AN50: =AN39*AN44 | AO50: =SUM(FI50:FJ50) | AP50: =SUM(FM50:FN50) | AQ50: =+AQ39*AQ44 | AR50: =+AR39*AR44 | AS50: =+AS39*AS44 | AT50: =+AT39*AT44 | EL50: =EM50-EK50 | EM50: =AI50 | EO50: 660 | EP50: =EQ50-EO50 | EQ50: =AJ50 | ES50: 3 | ET50: =EU50-ES50 | EU50: =AK50 | EW50: 18 | EX50: =EY50-EW50 | EY50: =AL50 | FA50: 2550 | FB50: =FC50-FA50 | FC50: =AM50 | FE50: 2985 | FF50: =FG50-FE50 | FG50: =AN50 | FI50: =FI39*FI44 | FJ50: =FK50-FI50 | FK50: =AO50 | FM50: =FM39*FM44 | FN50: =FN39*FN44 | FO50: =AP50
B52: Available cargo tonne kilometres (AFTK) | M52: 4965 | N52: 5119 | O52: =5337 | P52: =5740 | Q52: =5855 | R52: =6822 | S52: =7715 | T52: =8748 | U52: =9879 | V52: =10391+2080 | W52: 13335 | X52: 13425 | Y52: 11666 | Z52: 13443 | AA52: 14367 | AB52: 13926 | AC52: 14162 | AD52: 15630 | AE52: 16481 | AF52: 16572 | AG52: 17163 | AH52: 17616 | AI52: 17558 | AJ52: 11329 | AK52: 10094 | AL52: 8181 | AM52: 13069 | AN52: 14193 | AO52: =SUM(FI52:FJ52) | AP52: =SUM(FM52:FN52) | AQ52: =AP52*(1+AQ53) | AR52: =AQ52*(1+AR53) | AS52: =AR52*(1+AS53) | AT52: =AS52*(1+AT53) | CB52: 4140 | CC52: =CD52-CB52 | CD52: =T52 | CF52: 4685 | CG52: =CH52-CF52 | CH52: =U52 | CJ52: 4959 | CK52: =CL52-CJ52 | CL52: =V52 | CN52: 6236 | CO52: =CP52-CN52 | CP52: =W52 | CR52: 6666 | CS52: 6666 | CT52: =CU52-CS52 | CU52: =X52 | CW52: 5727 | CX52: =CY52-CW52 | CY52: =Y52 | DA52: 6135 | DB52: =DC52-DA52 | DC52: =Z52 | DE52: 7031 | DF52: =DG52-DE52 | DG52: =AA52 | DI52: 6729 | DJ52: =DK52-DI52 | DK52: =AB52 | DM52: 6607 | DN52: =DO52-DM52 | DO52: =AC52 | DQ52: 7318 | DR52: =DS52-DQ52 | DS52: =AD52 | DU52: 7971 | DV52: =DW52-DU52 | DW52: =AE52 | DY52: 8021 | DZ52: =EA52-DY52 | EA52: =AF52 | EC52: 8206 | ED52: =EE52-EC52 | EE52: =AG52 | EG52: 8542 | EH52: =EI52-EG52 | EI52: =AH52 | EK52: 8635 | EL52: =EM52-EK52 | EM52: =AI52 | EO52: 5958 | EP52: =EQ52-EO52 | EQ52: =AJ52 | ES52: 4058 | ET52: =EU52-ES52 | EU52: =AK52 | EW52: 2801 | EX52: =+EY52-EW52 | EY52: =AL52 | FA52: 6095 | FB52: =+FC52-FA52 | FC52: =AM52 | FE52: 6788 | FF52: =+FG52-FE52 | FG52: =AN52 | FI52: 7336 | FJ52: =+FK52-FI52 | FK52: =AO52 | FM52: =SUMIFS(Monthly!$40:$40,Monthly!$8:$8,">="&DATE(MID(FM$3,3,4),1,1),Monthly!$8:$8,"<="&DATE(MID(FM$3,3,4),6,30)) | FN52: =FJ52*(1+FN53) | FO52: =AP52
B53: Change in AFTK (YoY %) | O53: =O52/N52-1 | P53: =P52/O52-1 | Q53: =Q52/P52-1 | R53: =R52/Q52-1 | S53: =S52/R52-1 | T53: =T52/S52-1 | U53: =U52/T52-1 | V53: =V52/U52-1 | ... AP53: =AP52/AO52-1 | AQ53: 0.05 | AR53: 0.05 | AS53: 0.05 | AT53: 0.05 | CW53: =CW52/CS52-1 | CX53: =CX52/CT52-1 | CY53: =CY52/CU52-1 | DA53: =DA52/CW52-1 | DB53: =DB52/CX52-1 | DC53: =DC52/CY52-1 | DE53: =DE52/DA52-1 | DF53: =DF52/DB52-1 | DG53: =DG52/DC52-1 | DI53: =DI52/DE52-1 | DJ53: =DJ52/DF52-1 | DK53: =DK52/DG52-1 | DM53: =DM52/DI52-1 | DN53: =DN52/DJ52-1 | DO53: =DO52/DK52-1 | DQ53: =DQ52/DM52-1 | DR53: =DR52/DN52-1 | DS53: =DS52/DO52-1 | DU53: =DU52/DQ52-1 | DV53: =DV52/DR52-1 | DW53: =DW52/DS52-1 | DY53: =DY52/DU52-1 | DZ53: =DZ52/DV52-1 | EA53: =EA52/DW52-1 | EC53: =EC52/DY52-1 | ED53: =ED52/DZ52-1 | EE53: =EE52/EA52-1 | EG53: =EG52/EC52-1 | EH53: =EH52/ED52-1 | EI53: =EI52/EE52-1 | EK53: =EK52/EG52-1 | EL53: =EL52/EH52-1 | EM53: =EM52/EI52-1 | EO53: =EO52/EK52-1 | EP53: =EP52/EL52-1 | EQ53: =EQ52/EM52-1 | ES53: =ES52/EO52-1 | ET53: =ET52/EP52-1 | EU53: =EU52/EQ52-1 | EW53: =EW52/ES52-1 | EX53: =EX52/ET52-1 | EY53: =EY52/EU52-1 | FA53: =FA52/EW52-1 | FB53: =FB52/EX52-1 | FC53: =FC52/EY52-1 | FE53: =FE52/FA52-1 | FF53: =FF52/FB52-1 | FG53: =FG52/FC52-1 | FI53: =FI52/FE52-1 | FJ53: =FJ52/FF52-1 | FK53: =FK52/FG52-1 | FM53: =FM52/FI52-1 | FN53: =FM53 | FO53: =FO52/FK52-1
A54: ctk | B54: ctk | C54: 985 | D54: 1172 | E54: 1272 | F54: 1448 | G54: 1457 | H54: 1671 | I54: 1996 | J54: 2375 | K54: 2790 | L54: 3244 | M54: 3621 | N54: 3339 | O54: 3817 | P54: 4161 | Q54: 3938 | R54: 4854 | S54: 5299 | T54: 6007 | U54: 6618 | V54: 7514 | W54: 8900 | X54: =X52*X56 | Y54: =Y52*Y56 | Z54: =Z52*Z56 | AA54: =AA52*AA56 | AB54: =AB52*AB56 | AC54: =AC52*AC56 | AD54: =AD52*AD56 | AE54: 10586 | AF54: 10675 | AG54: 11633 | AH54: 12122 | AI54: 11311.09 | AJ54: 8309 | AK54: 8220 | AL54: 5774 | AM54: 8099 | AN54: 8503 | AO54: =SUM(FI54:FJ54) | AP54: =SUM(FM54:FN54) | AQ54: =+AQ52*AQ56 | AR54: =+AR52*AR56 | AS54: =+AS52*AS56 | AT54: =+AT52*AT56 | CB54: 2842.5 | CC54: =CD54-CB54 | CD54: =T54 | CF54: =4685*0.659 | CG54: =CH54-CF54 | CH54: =U54 | CJ54: =4958.893*0.677 | CK54: =CL54-CJ54 | CL54: =V54 | CN54: 4070.187 | CO54: =CP54-CN54 | CP54: =W54 | CR54: 4427.93 | CS54: 4427.93 | CT54: =CU54-CS54 | CU54: =X54 | CW54: 3789.039 | CX54: =CY54-CW54 | CY54: =Y54 | DA54: 4783.991 | DB54: =+DC54-DA54 | DC54: =Z54 | DE54: 4809.018 | DF54: =+DG54-DE54 | DG54: =AA54 | DI54: 4324.586 | DJ54: =+DK54-DI54 | DK54: =AB54 | DM54: 4124.376 | DN54: =+DO54-DM54 | DO54: =AC54 | DQ54: 4622.396 | DR54: =+DS54-DQ54 | DS54: =AD54 | DU54: 5106.627 | DV54: =+DW54-DU54 | DW54: =AE54 | DY54: 4989.796 | DZ54: =+EA54-DY54 | EA54: =AF54 | EC54: 5435.433 | ED54: =+EE54-EC54 | EE54: =AG54 | EG54: 5830.675 | EH54: =+EI54-EG54 | EI54: =AH54 | EK54: 5477 | EL54: =+EM54-EK54 | EM54: =AI54 | EO54: =SUMIFS(Monthly!$76:$76,Monthly!$8:$8,">="&DATE(MID(EO$3,3,4),1,1),Monthly!$8:$8,"<="&DATE(MID(EO$3,3,4),6,30)) | EP54: =+EQ54-EO54 | EQ54: =AJ54 | ES54: =SUMIFS(Monthly!$76:$76,Monthly!$8:$8,">="&DATE(MID(ES$3,3,4),1,1),Monthly!$8:$8,"<="&DATE(MID(ES$3,3,4),6,30)) | ET54: =+EU54-ES54 | EU54: =AK54 | EW54: 2123 | EX54: =+EY54-EW54 | EY54: =AL54 | FA54: 3886 | FB54: =+FC54-FA54 | FC54: =AM54 | FE54: 4063 | FF54: =+FG54-FE54 | FG54: =AN54 | FI54: 4302 | FJ54: =+FK54-FI54 | FK54: =AO54 | FM54: =SUMIFS(Monthly!$76:$76,Monthly!$8:$8,">="&DATE(MID(FM$3,3,4),1,1),Monthly!$8:$8,"<="&DATE(MID(FM$3,3,4),6,30)) | FN54: =FN52*FN56 | FO54: =AP54
A55: cargo traffic growth | B55: Change in cargo traffic (CTK) | D55: =D54/C54-1 | E55: =E54/D54-1 | F55: =F54/E54-1 | G55: =G54/F54-1 | H55: =H54/G54-1 | I55: =I54/H54-1 | J55: =J54/I54-1 | K55: =K54/J54-1 | L55: =0.14 | M55: =M54/L54-1 | N55: =N54/M54-1 | O55: =O54/N54-1 | P55: =P54/O54-1 | Q55: -0.053708756 | R55: =R54/Q54-1 | S55: =S54/R54-1 | T55: =T54/S54-1 | U55: =U54/T54-1 | V55: =V54/U54-1 | W55: =W54/V54-1 | X55: =X54/W54-1 | Y55: =Y54/X54-1 | ... AT55: =AT54/AS54-1 | CD55: =T55 | CF55: =CF54/CB54-1 | CG55: =CG54/CC54-1 | CH55: =U55 | CJ55: =CJ54/CF54-1 | CK55: =CK54/CG54-1 | CL55: =V55 | CN55: =CN54/CJ54-1 | CO55: =CO54/CK54-1 | CP55: =W55 | CR55: =CR54/CN54-1 | CS55: =CS54/CN54-1 | CT55: =CT54/CO54-1 | CU55: =X55 | CW55: =CW54/CR54-1 | CX55: =CX54/CT54-1 | CY55: =Y55 | DA55: =DA54/CW54-1 | DB55: =DB54/CX54-1 | DC55: =Z55 | DE55: =DE54/DA54-1 | DF55: =DF54/DB54-1 | DG55: =AA55 | DI55: =+DI54/DE54-1 | DJ55: =DJ54/DF54-1 | DK55: =AB55 | DM55: =+DM54/DI54-1 | DN55: =DN54/DJ54-1 | DO55: =AC404 | DQ55: =+DQ54/DM54-1 | DR55: =+DR54/DN54-1 | DS55: =AD55 | DU55: =+DU54/DQ54-1 | DV55: =+DV54/DR54-1 | DW55: =AE55 | DY55: =+DY54/DU54-1 | DZ55: =+DZ54/DV54-1 | EA55: =AF55 | EC55: =+EC54/DY54-1 | ED55: =+ED54/DZ54-1 | EE55: =AG55 | EG55: =+EG54/EC54-1 | EH55: =+EH54/ED54-1 | EI55: =AH55 | EK55: =+EK54/EG54-1 | EL55: =+EL54/EH54-1 | EM55: =AI55 | EO55: =+EO54/EK54-1 | EP55: =+EP54/EL54-1 | EQ55: =+EQ54/EM54-1 | ES55: =+ES54/EO54-1 | ET55: =+ET54/EP54-1 | EU55: =+EU54/EQ54-1 | EW55: =+EW54/ES54-1 | EX55: =+EX54/ET54-1 | EY55: =+EY54/EU54-1 | FA55: =+FA54/EW54-1 | FB55: =+FB54/EX54-1 | FC55: =+FC54/EY54-1 | FE55: =+FE54/FA54-1 | FF55: =+FF54/FB54-1 | FG55: =+FG54/FC54-1 | FI55: =+FI54/FE54-1 | FJ55: =+FJ54/FF54-1 | FK55: =+FK54/FG54-1 | FM55: =+FM54/FI54-1 | FN55: =+FN54/FJ54-1 | FO55: =+FO54/FK54-1
B56: Cargo load factor | M56: =M54/M52 | N56: =N54/N52 | O56: =O54/O52 | P56: =P54/P52 | Q56: =Q54/Q52 | R56: =R54/R52 | S56: =S54/S52 | T56: =T54/T52 | ... W56: =W54/W52 | X56: 0.659 | Y56: 0.708 | Z56: 0.757 | AA56: 0.672 | AB56: 0.642 | AC56: 0.618 | AD56: 0.643 | AE56: =AE54/AE52 | AF56: =AF54/AF52 | AG56: =AG54/AG52 | AH56: =AH54/AH52 | AI56: =AI54/AI52 | AJ56: =AJ54/AJ52 | AK56: =AK54/AK52 | AL56: =AL54/AL52 | ... AP56: =AP54/AP52 | AQ56: =AP56 | AR56: =AQ56 | AS56: =AR56 | AT56: =AS56 | CB56: =CB54/CB52 | CC56: =CC54/CC52 | CD56: =CD54/CD52 | CF56: =CF54/CF52 | CG56: =CG54/CG52 | CH56: =CH54/CH52 | CJ56: =CJ54/CJ52 | CK56: =CK54/CK52 | CL56: =CL54/CL52 | CN56: =CN54/CN52 | CO56: =CO54/CO52 | CP56: =CP54/CP52 | CR56: =CR54/CR52 | CS56: =CS54/CS52 | CT56: =CT54/CT52 | CU56: =CU54/CU52 | CW56: =CW54/CW52 | CX56: =CX54/CX52 | CY56: =CY54/CY52 | DA56: =DA54/DA52 | DB56: =DB54/DB52 | DC56: =DC54/DC52 | DE56: =DE54/DE52 | DF56: =DF54/DF52 | DG56: =DG54/DG52 | DI56: =DI54/DI52 | DJ56: =DJ54/DJ52 | DK56: =DK54/DK52 | DM56: =DM54/DM52 | DN56: =DN54/DN52 | DO56: =DO54/DO52 | DQ56: =DQ54/DQ52 | DR56: =DR54/DR52 | DS56: =DS54/DS52 | DU56: =DU54/DU52 | DV56: =DV54/DV52 | DW56: =DW54/DW52 | DY56: =DY54/DY52 | DZ56: =DZ54/DZ52 | EA56: =EA54/EA52 | EC56: =EC54/EC52 | ED56: =ED54/ED52 | EE56: =EE54/EE52 | EG56: =EG54/EG52 | EH56: =EH54/EH52 | EI56: =EI54/EI52 | EK56: =EK54/EK52 | EL56: =EL54/EL52 | EM56: =EM54/EM52 | EO56: =EO54/EO52 | EP56: =EP54/EP52 | EQ56: =EQ54/EQ52 | ES56: =ES54/ES52 | ET56: =ET54/ET52 | EU56: =EU54/EU52 | EW56: =EW54/EW52 | EX56: =EX54/EX52 | EY56: =EY54/EY52 | FA56: =FA54/FA52 | FB56: =FB54/FB52 | FC56: =FC54/FC52 | FE56: =FE54/FE52 | FF56: =FF54/FF52 | FG56: =FG54/FG52 | FI56: =FI54/FI52 | FJ56: =FJ54/FJ52 | FK56: =FK54/FK52 | FM56: =FM54/FM52 | FN56: =FJ56 | FO56: =FO54/FO52
B57: cargo yield | C57: =C114/C54 | D57: =D114/D54 | E57: =E114/E54 | F57: =F114/F54 | G57: =G114/G54 | H57: =H114/H54 | I57: =I114/I54 | J57: =J114/J54 | ... N57: =N114/N54 | O57: 1.85 | P57: 2.07 | Q57: 1.85 | R57: 1.8 | S57: 1.78 | T57: 1.76 | U57: 1.75 | V57: 1.7 | W57: 1.64 | X57: 2.54 | Y57: 1.86 | Z57: 2.33 | AA57: 2.42 | AB57: 2.42 | AC57: 2.32 | AD57: 2.19 | AE57: 1.9 | AF57: 1.59 | AG57: 1.77 | AH57: 2.03 | AI57: 1.87 | AJ57: 2.96 | AK57: 3.94 | AL57: 4.67 | AM57: 2.74 | AN57: 2.82 | AO57: =AO59/AO54 | AP57: =AP59/AP54 | AQ57: =AP57*(1+AQ58) | AR57: =AQ57*(1+AR58) | AS57: =AR57*(1+AS58) | AT57: =AS57*(1+AT58) | CB57: 1.72 | CC57: =CC59/CC54 | CD57: =T57 | CF57: 1.75 | CG57: =CG59/CG54 | CH57: =U57 | CJ57: 1.69 | CK57: =CK59/CK54 | CL57: =V57 | CN57: 1.63 | CO57: =CO59/CO54 | CP57: =W57 | CR57: 1.6 | CS57: 2.47 | CT57: =CT59/CT54 | CU57: =X57 | CW57: 1.66 | CX57: =CX59/CX54 | CY57: =Y57 | DA57: 2.26 | DB57: =DB59/DB54 | DC57: =Z57 | DE57: 2.42 | DF57: =DF59/DF54 | DG57: =AA57 | DI57: 2.41 | DJ57: =DJ59/DJ54 | DK57: =AB57 | DM57: 2.33 | DN57: =DN59/DN54 | DO57: =AC57 | DQ57: 2.17 | DR57: =DR59/DR54 | DS57: =AD57 | DU57: 1.93 | DV57: =DV59/DV54 | DW57: =AE57 | DY57: 1.59 | DZ57: =DZ59/DZ54 | EA57: =AF57 | EC57: 1.66 | ED57: =ED59/ED54 | EE57: =AG57 | EG57: 1.93 | EH57: =EH59/EH54 | EI57: =AH57 | EK57: 1.88 | EL57: =EL59/EL54 | EM57: =AI57 | EO57: 2.71 | EP57: =EP59/EP54 | EQ57: =AJ57 | ES57: 3.37 | ET57: =ET59/ET54 | EU57: =AK57 | EW57: 5.72 | EX57: =EX59/EX54 | EY57: =AL57 | FA57: 2.76 | FB57: =FB59/FB54 | FC57: =AM57 | FE57: 2.68 | FF57: =FF59/FF54 | FG57: =AN57 | FI57: 2.59 | FJ57: =FJ59/FJ54 | FK57: =AO57 | FM57: 3.06 | FN57: =FJ57*(1+FN58) | FO57: =AP57
A58: cargo yield chg | B58: Change in cargo yield | D58: =D57/C57-1 | E58: =E57/D57-1 | F58: =F57/E57-1 | G58: =G57/F57-1 | H58: =H57/G57-1 | I58: =I57/H57-1 | J58: =J57/I57-1 | K58: =K57/J57-1 | L58: =-0.072 | M58: -0.006 | N58: =N57/M57-1 | O58: =O57/N57-1 | P58: =P57/O57-1 | Q58: =Q57/P57-1 | R58: =R57/Q57-1 | S58: =S57/R57-1 | T58: =T57/S57-1 | U58: =U57/T57-1 | ... AP58: =AP57/AO57-1 | AQ58: -0.05 | AR58: 0 | AS58: 0 | AT58: 0 | CF58: =CF57/CB57-1 | CG58: =CG57/CC57-1 | CH58: =U58 | CJ58: =CJ57/CF57-1 | CK58: =CK57/CG57-1 | CL58: =V58 | CN58: =CN57/CJ57-1 | CO58: =CO57/CK57-1 | CP58: =W58 | CR58: =CR57/CN57-1 | CS58: =CS57/CN57-1 | CT58: =CT57/CO57-1 | CU58: =X58 | CW58: =CW57/CS57-1 | CX58: =CX57/CT57-1 | CY58: =CY57/CU57-1 | DA58: =DA57/CW57-1 | DB58: =DB57/CX57-1 | DC58: =Z58 | DE58: =DE57/DA57-1 | DF58: =DF57/DB57-1 | DG58: =AA58 | DI58: =DI57/DE57-1 | DJ58: =DJ57/DF57-1 | DK58: =AB58 | DM58: =DM57/DI57-1 | DN58: =DN57/DJ57-1 | DO58: =AC58 | DQ58: =DQ57/DM57-1 | DR58: =+DR57/DN57-1 | DS58: =AD58 | DU58: =DU57/DQ57-1 | DV58: =+DV57/DR57-1 | DW58: =AE58 | DY58: =DY57/DU57-1 | DZ58: =+DZ57/DV57-1 | EA58: =AF58 | EC58: =EC57/DY57-1 | ED58: =+ED57/DZ57-1 | EE58: =AG58 | EG58: =EG57/EC57-1 | EH58: =+EH57/ED57-1 | EI58: =AH58 | EK58: =EK57/EG57-1 | EL58: =+EL57/EH57-1 | EM58: =AI58 | EO58: =EO57/EK57-1 | EP58: =+EP57/EL57-1 | EQ58: =AJ58 | ES58: =ES57/EO57-1 | ET58: =+ET57/EP57-1 | EU58: =AK58 | EW58: =EW57/ES57-1 | EX58: =EX57/ET57-1 | EY58: =AL58 | FA58: =FA57/EW57-1 | FB58: =FB57/EX57-1 | FC58: =AM58 | FE58: =FE57/FA57-1 | FF58: =FF57/FB57-1 | FG58: =AN58 | FI58: =FI57/FE57-1 | FJ58: =FJ57/FF57-1 | FK58: =AO58 | FM58: =FM57/FI57-1 | FN58: 0.15 | FO58: =AP58
B59: Cathay Cargo Revenue | O59: =O54*O57 | P59: =P54*P57 | Q59: =Q54*Q57 | R59: =R54*R57 | S59: =S54*S57 | T59: =T54*T57 | U59: =U54*U57 | V59: =V54*V57 | ... AN59: =AN54*AN57 | AO59: =SUM(FI59:FJ59) | AP59: =SUM(FM59:FN59) | AQ59: =AQ54*AQ57 | AR59: =AR54*AR57 | AS59: =AS54*AS57 | AT59: =AT54*AT57 | CB59: =CB54*CB57 | CC59: =CD59-CB59 | CD59: =T59 | CF59: =CF54*CF57 | CG59: =CH59-CF59 | CH59: =U59 | CJ59: =CJ54*CJ57 | CK59: =CL59-CJ59 | CL59: =V59 | CN59: =CN54*CN57 | CO59: =CP59-CN59 | CP59: =W59 | CR59: =CR54*CR57 | CS59: =CS54*CS57 | CT59: =CU59-CS59 | CU59: =X59 | CW59: =CW54*CW57 | CX59: =CY59-CW59 | CY59: =Y59 | DA59: =DA54*DA57 | DB59: =DC59-DA59 | DC59: =Z59 | DE59: =DE54*DE57 | DF59: =DG59-DE59 | DG59: =AA59 | DI59: =DI54*DI57 | DJ59: =DK59-DI59 | DK59: =AB59 | DM59: =DM54*DM57 | DN59: =DO59-DM59 | DO59: =AC59 | DQ59: =DQ54*DQ57 | DR59: =DS59-DQ59 | DS59: =AD59 | DU59: =DU54*DU57 | DV59: =DW59-DU59 | DW59: =AE59 | DY59: =DY54*DY57 | DZ59: =EA59-DY59 | EA59: =AF59 | EC59: =EC54*EC57 | ED59: =EE59-EC59 | EE59: =AG59 | EG59: =EG54*EG57 | EH59: =EI59-EG59 | EI59: =AH59 | EK59: =EK54*EK57 | EL59: =EM59-EK59 | EM59: =AI59 | EO59: =EO54*EO57 | EP59: =EQ59-EO59 | EQ59: =AJ59 | ES59: =ES54*ES57 | ET59: =EU59-ES59 | EU59: =AK59 | EW59: =EW54*EW57 | EX59: =EY59-EW59 | EY59: =AL59 | FA59: =FA54*FA57 | FB59: =FC59-FA59 | FC59: =AM59 | FE59: =FE54*FE57 | FF59: =FG59-FE59 | FG59: =AN59 | FI59: =FI54*FI57 | FJ59: =FK59-FI59 | FK59: =AO59 | FM59: =FM54*FM57 | FN59: =FN54*FN57 | FO59: =AP59
B60: YoY % | P60: =P59/O59-1 | Q60: =Q59/P59-1 | R60: =R59/Q59-1 | S60: =S59/R59-1 | T60: =T59/S59-1 | U60: =U59/T59-1 | V60: =V59/U59-1 | W60: =W59/V59-1 | ... AT60: =AT59/AS59-1 | CF60: =CF59/CB59-1 | CG60: =CG59/CC59-1 | CH60: =CH59/CD59-1 | CJ60: =CJ59/CF59-1 | CK60: =CK59/CG59-1 | CL60: =CL59/CH59-1 | CN60: =CN59/CJ59-1 | CO60: =CO59/CK59-1 | CP60: =CP59/CL59-1 | CR60: =CR59/CN59-1 | CS60: =CS59/CN59-1 | CT60: =CT59/CO59-1 | CU60: =CU59/CP59-1 | CW60: =CW59/CS59-1 | CX60: =CX59/CT59-1 | CY60: =CY59/CU59-1 | DA60: =DA59/CW59-1 | DB60: =DB59/CX59-1 | DC60: =DC59/CY59-1 | DE60: =DE59/DA59-1 | DF60: =DF59/DB59-1 | DG60: =DG59/DC59-1 | DI60: =DI59/DE59-1 | DJ60: =DJ59/DF59-1 | DK60: =DK59/DG59-1 | DM60: =DM59/DI59-1 | DN60: =DN59/DJ59-1 | DO60: =DO59/DK59-1 | DQ60: =DQ59/DM59-1 | DR60: =DR59/DN59-1 | DS60: =DS59/DO59-1 | DU60: =DU59/DQ59-1 | DV60: =DV59/DR59-1 | DW60: =DW59/DS59-1 | DY60: =DY59/DU59-1 | DZ60: =DZ59/DV59-1 | EA60: =EA59/DW59-1 | EC60: =EC59/DY59-1 | ED60: =ED59/DZ59-1 | EE60: =EE59/EA59-1 | EG60: =EG59/EC59-1 | EH60: =EH59/ED59-1 | EI60: =EI59/EE59-1 | EK60: =EK59/EG59-1 | EL60: =EL59/EH59-1 | EM60: =EM59/EI59-1 | EO60: =EO59/EK59-1 | EP60: =EP59/EL59-1 | EQ60: =EQ59/EM59-1 | ES60: =ES59/EO59-1 | ET60: =ET59/EP59-1 | EU60: =EU59/EQ59-1 | EW60: =EW59/ES59-1 | EX60: =EX59/ET59-1 | EY60: =EY59/EU59-1 | FA60: =FA59/EW59-1 | FB60: =FB59/EX59-1 | FC60: =FC59/EY59-1 | FE60: =FE59/FA59-1 | FF60: =FF59/FB59-1 | FG60: =FG59/FC59-1 | FI60: =FI59/FE59-1 | FJ60: =FJ59/FF59-1 | FK60: =FK59/FG59-1 | FM60: =FM59/FI59-1 | FN60: =FN59/FJ59-1 | FO60: =FO59/FK59-1
B61: Air Hong Kong Revenue | O61: =O63-O59 | P61: =P63-P59 | Q61: =Q63-Q59 | R61: =R63-R59 | S61: =S63-S59 | T61: =T63-T59 | U61: =U63-U59 | V61: =V63-V59 | ... AN61: =AN63-AN59 | AO61: =SUM(FI61:FJ61) | AP61: =SUM(FM61:FN61) | AQ61: =AP61*(1+AQ62) | AR61: =AQ61*(1+AR62) | AS61: =AR61*(1+AS62) | AT61: =AS61*(1+AT62) | CB61: =CB63-CB59 | CC61: =CC63-CC59 | CD61: =CD63-CD59 | CF61: =CF63-CF59 | CG61: =CG63-CG59 | CH61: =CH63-CH59 | CJ61: =CJ63-CJ59 | CK61: =CK63-CK59 | CL61: =CL63-CL59 | CN61: =CN63-CN59 | CO61: =CO63-CO59 | CP61: =CP63-CP59 | CR61: =CR63-CR59 | CS61: =CS63-CS59 | CT61: =CT63-CT59 | CU61: =CU63-CU59 | CW61: =CW63-CW59 | CX61: =CX63-CX59 | CY61: =CY63-CY59 | DA61: =DA63-DA59 | DB61: =DB63-DB59 | DC61: =DC63-DC59 | DE61: =DE63-DE59 | DF61: =DF63-DF59 | DG61: =DG63-DG59 | DI61: =DI63-DI59 | DJ61: =DJ63-DJ59 | DK61: =DK63-DK59 | DM61: =DM63-DM59 | DN61: =DN63-DN59 | DO61: =DO63-DO59 | DQ61: =DQ63-DQ59 | DR61: =DR63-DR59 | DS61: =DS63-DS59 | DU61: =DU63-DU59 | DV61: =DV63-DV59 | DW61: =DW63-DW59 | DY61: =DY63-DY59 | DZ61: =DZ63-DZ59 | EA61: =EA63-EA59 | EC61: =EC63-EC59 | ED61: =ED63-ED59 | EE61: =EE63-EE59 | EG61: =EG63-EG59 | EH61: =EH63-EH59 | EI61: =EI63-EI59 | EK61: =EK63-EK59 | EL61: =EL63-EL59 | EM61: =EM63-EM59 | EO61: =EO63-EO59 | EP61: =EP63-EP59 | EQ61: =EQ63-EQ59 | ES61: =ES63-ES59 | ET61: =ET63-ET59 | EU61: =EU63-EU59 | EW61: =EW63-EW59 | EX61: =EX63-EX59 | EY61: =EY63-EY59 | FA61: =FA63-FA59 | FB61: =FB63-FB59 | FC61: =FC63-FC59 | FE61: =FE63-FE59 | FF61: =FF63-FF59 | FG61: =FG63-FG59 | FI61: =FI63-FI59 | FJ61: =FJ63-FJ59 | FK61: =FK63-FK59 | FM61: =FM63-FM59 | FN61: =FJ61*(1+FN62) | FO61: =FO63-FO59
B62: YoY % | P62: =P61/O61-1 | Q62: =Q61/P61-1 | R62: =R61/Q61-1 | S62: =S61/R61-1 | T62: =T61/S61-1 | U62: =U61/T61-1 | V62: =V61/U61-1 | W62: =W61/V61-1 | ... AP62: =AP61/AO61-1 | AQ62: =(1+AQ58)*(1+AQ55)-1 | AR62: =(1+AR58)*(1+AR55)-1 | AS62: =(1+AS58)*(1+AS55)-1 | AT62: =(1+AT58)*(1+AT55)-1 | CF62: =CF61/CB61-1 | CG62: =CG61/CC61-1 | CH62: =CH61/CD61-1 | CJ62: =CJ61/CF61-1 | CK62: =CK61/CG61-1 | CL62: =CL61/CH61-1 | CN62: =CN61/CJ61-1 | CO62: =CO61/CK61-1 | CP62: =CP61/CL61-1 | CR62: =CR61/CN61-1 | CS62: =CS61/CN61-1 | CT62: =CT61/CO61-1 | CU62: =CU61/CP61-1 | CW62: =CW61/CS61-1 | CX62: =CX61/CT61-1 | CY62: =CY61/CU61-1 | DA62: =DA61/CW61-1 | DB62: =DB61/CX61-1 | DC62: =DC61/CY61-1 | DE62: =DE61/DA61-1 | DF62: =DF61/DB61-1 | DG62: =DG61/DC61-1 | DI62: =DI61/DE61-1 | DJ62: =DJ61/DF61-1 | DK62: =DK61/DG61-1 | DM62: =DM61/DI61-1 | DN62: =DN61/DJ61-1 | DO62: =DO61/DK61-1 | DQ62: =DQ61/DM61-1 | DR62: =DR61/DN61-1 | DS62: =DS61/DO61-1 | DU62: =DU61/DQ61-1 | DV62: =DV61/DR61-1 | DW62: =DW61/DS61-1 | DY62: =DY61/DU61-1 | DZ62: =DZ61/DV61-1 | EA62: =EA61/DW61-1 | EC62: =EC61/DY61-1 | ED62: =ED61/DZ61-1 | EE62: =EE61/EA61-1 | EG62: =EG61/EC61-1 | EH62: =EH61/ED61-1 | EI62: =EI61/EE61-1 | EK62: =EK61/EG61-1 | EL62: =EL61/EH61-1 | EM62: =EM61/EI61-1 | EO62: =EO61/EK61-1 | EP62: =EP61/EL61-1 | EQ62: =EQ61/EM61-1 | ES62: =ES61/EO61-1 | ET62: =ET61/EP61-1 | EU62: =EU61/EQ61-1 | EW62: =EW61/ES61-1 | EX62: =EX61/ET61-1 | EY62: =EY61/EU61-1 | FA62: =FA61/EW61-1 | FB62: =FB61/EX61-1 | FC62: =FC61/EY61-1 | FE62: =FE61/FA61-1 | FF62: =FF61/FB61-1 | FG62: =FG61/FC61-1 | FI62: =FI61/FE61-1 | FJ62: =FJ61/FF61-1 | FK62: =FK61/FG61-1 | FM62: =FM61/FI61-1 | FN62: =(1+FN58)*(1+FN55)-1 | FO62: =FO61/FK61-1
B63: Cargo Revenue | C63: =C114 | D63: =D114 | E63: =E114 | F63: =F114 | G63: =G114 | H63: =H114 | I63: =I114 | J63: =J114 | ... AN63: =AN114 | AO63: =+AO59+AO61 | AP63: =+AP59+AP61 | AQ63: =+AQ59+AQ61 | AR63: =+AR59+AR61 | AS63: =+AS59+AS61 | AT63: =+AT59+AT61 | AV63: =AV114 | AW63: =AW114 | AX63: =AX114 | AZ63: =AZ114 | BA63: =BA114 | BB63: =BB114 | BD63: =BD114 | BE63: =BE114 | BF63: =BF114 | BH63: =BH114 | BI63: =BI114 | BJ63: =BJ114 | BL63: =BL114 | BM63: =BM114 | BN63: =BN114 | BP63: =BP114 | BQ63: =BQ114 | BR63: =BR114 | BT63: =BT114 | BU63: =BU114 | BV63: =BV114 | BX63: =BX114 | BY63: =BY114 | BZ63: =BZ114 | CB63: =CB114 | CC63: =CC114 | CD63: =CD114 | CF63: =CF114 | CG63: =CG114 | CH63: =CH114 | CJ63: =CJ114 | CK63: =CK114 | CL63: =CL114 | CN63: =CN114 | CO63: =CO114 | CP63: =CP114 | CR63: =CR114 | CS63: =CS114 | CT63: =CT114 | CU63: =CU114 | CW63: =CW114 | CX63: =CX114 | CY63: =CY114 | DA63: =DA114 | DB63: =DB114 | DC63: =DC114 | DE63: =DE114 | DF63: =DF114 | DG63: =DG114 | DI63: =DI114 | DJ63: =DJ114 | DK63: =DK114 | DM63: =DM114 | DN63: =DN114 | DO63: =DO114 | DQ63: =DQ114 | DR63: =DR114 | DS63: =DS114 | DU63: =DU114 | DV63: =DV114 | DW63: =DW114 | DY63: =DY114 | DZ63: =DZ114 | EA63: =EA114 | EC63: =EC114 | ED63: =ED114 | EE63: =EE114 | EG63: =EG114 | EH63: =EH114 | EI63: =EI114 | EK63: =EK114 | EL63: =EL114 | EM63: =EM114 | EO63: =EO114 | EP63: =EP114 | EQ63: =EQ114 | ES63: =ES114 | ET63: =ET114 | EU63: =EU114 | EW63: =EW114 | EX63: =EX114 | EY63: =EY114 | FA63: =FA114 | FB63: =FB114 | FC63: =FC114 | FE63: =FE114 | FF63: =FF114 | FG63: =FG114 | FI63: =FI114 | FJ63: =FJ114 | FK63: =FK114 | FM63: =FM114 | FN63: =FN59+FN61 | FO63: =FO114
B65: Key assumptions
A66: forex | B66: hkd / $ (avg.) | C66: 7.7926 | D66: 7.8044 | E66: 7.801 | F66: 7.786 | G66: =AVERAGEIFS(FX!$B:$B,FX!$A:$A,">="&DATE(LEFT(G$3,4),1,1),FX!$A:$A,"<="&DATE(LEFT(G$3,4),12,13)) | H66: =AVERAGEIFS(FX!$B:$B,FX!$A:$A,">="&DATE(LEFT(H$3,4),1,1),FX!$A:$A,"<="&DATE(LEFT(H$3,4),12,13)) | I66: =AVERAGEIFS(FX!$B:$B,FX!$A:$A,">="&DATE(LEFT(I$3,4),1,1),FX!$A:$A,"<="&DATE(LEFT(I$3,4),12,13)) | J66: =AVERAGEIFS(FX!$B:$B,FX!$A:$A,">="&DATE(LEFT(J$3,4),1,1),FX!$A:$A,"<="&DATE(LEFT(J$3,4),12,13)) | K66: =AVERAGEIFS(FX!$B:$B,FX!$A:$A,">="&DATE(LEFT(K$3,4),1,1),FX!$A:$A,"<="&DATE(LEFT(K$3,4),12,13)) | L66: =AVERAGEIFS(FX!$B:$B,FX!$A:$A,">="&DATE(LEFT(L$3,4),1,1),FX!$A:$A,"<="&DATE(LEFT(L$3,4),12,13)) | M66: =AVERAGEIFS(FX!$B:$B,FX!$A:$A,">="&DATE(LEFT(M$3,4),1,1),FX!$A:$A,"<="&DATE(LEFT(M$3,4),12,13)) | N66: =AVERAGEIFS(FX!$B:$B,FX!$A:$A,">="&DATE(LEFT(N$3,4),1,1),FX!$A:$A,"<="&DATE(LEFT(N$3,4),12,13)) | ... AN66: =AVERAGEIFS(FX!$B:$B,FX!$A:$A,">="&DATE(LEFT(AN$3,4),1,1),FX!$A:$A,"<="&DATE(LEFT(AN$3,4),12,13)) | AO66: =+AN66 | AP66: =+AO66 | AQ66: =+AP66 | AR66: =+AQ66 | AS66: =+AR66 | AT66: =+AS66 | EK66: =IF(VALUE(LEFT(EK$3,1))=1,AVERAGEIFS(FX!$B:$B,FX!$A:$A,">="&DATE(MID(EK$3,3,4),1,1),FX!$A:$A,"<="&DATE(MID(EK$3,3,4),6,30)),IF(VALUE(LEFT(EK$3,1))=2,AVERAGEIFS(FX!$B:$B,FX!$A:$A,">="&DATE(MID(EK$3,3,4),6,1),FX!$A:$A,"<="&DATE(MID(EK$3,3,4),12,31)),"NA")) | EL66: =IF(VALUE(LEFT(EL$3,1))=1,AVERAGEIFS(FX!$B:$B,FX!$A:$A,">="&DATE(MID(EL$3,3,4),1,1),FX!$A:$A,"<="&DATE(MID(EL$3,3,4),6,30)),IF(VALUE(LEFT(EL$3,1))=2,AVERAGEIFS(FX!$B:$B,FX!$A:$A,">="&DATE(MID(EL$3,3,4),6,1),FX!$A:$A,"<="&DATE(MID(EL$3,3,4),12,31)),"NA")) | EM66: =AI66 | EO66: =IF(VALUE(LEFT(EO$3,1))=1,AVERAGEIFS(FX!$B:$B,FX!$A:$A,">="&DATE(MID(EO$3,3,4),1,1),FX!$A:$A,"<="&DATE(MID(EO$3,3,4),6,30)),IF(VALUE(LEFT(EO$3,1))=2,AVERAGEIFS(FX!$B:$B,FX!$A:$A,">="&DATE(MID(EO$3,3,4),6,1),FX!$A:$A,"<="&DATE(MID(EO$3,3,4),12,31)),"NA")) | EP66: =IF(VALUE(LEFT(EP$3,1))=1,AVERAGEIFS(FX!$B:$B,FX!$A:$A,">="&DATE(MID(EP$3,3,4),1,1),FX!$A:$A,"<="&DATE(MID(EP$3,3,4),6,30)),IF(VALUE(LEFT(EP$3,1))=2,AVERAGEIFS(FX!$B:$B,FX!$A:$A,">="&DATE(MID(EP$3,3,4),6,1),FX!$A:$A,"<="&DATE(MID(EP$3,3,4),12,31)),"NA")) | EQ66: =AJ66 | ES66: =IF(VALUE(LEFT(ES$3,1))=1,AVERAGEIFS(FX!$B:$B,FX!$A:$A,">="&DATE(MID(ES$3,3,4),1,1),FX!$A:$A,"<="&DATE(MID(ES$3,3,4),6,30)),IF(VALUE(LEFT(ES$3,1))=2,AVERAGEIFS(FX!$B:$B,FX!$A:$A,">="&DATE(MID(ES$3,3,4),6,1),FX!$A:$A,"<="&DATE(MID(ES$3,3,4),12,31)),"NA")) | ET66: =IF(VALUE(LEFT(ET$3,1))=1,AVERAGEIFS(FX!$B:$B,FX!$A:$A,">="&DATE(MID(ET$3,3,4),1,1),FX!$A:$A,"<="&DATE(MID(ET$3,3,4),6,30)),IF(VALUE(LEFT(ET$3,1))=2,AVERAGEIFS(FX!$B:$B,FX!$A:$A,">="&DATE(MID(ET$3,3,4),6,1),FX!$A:$A,"<="&DATE(MID(ET$3,3,4),12,31)),"NA")) | EU66: =AK66 | EW66: =IF(VALUE(LEFT(EW$3,1))=1,AVERAGEIFS(FX!$B:$B,FX!$A:$A,">="&DATE(MID(EW$3,3,4),1,1),FX!$A:$A,"<="&DATE(MID(EW$3,3,4),6,30)),IF(VALUE(LEFT(EW$3,1))=2,AVERAGEIFS(FX!$B:$B,FX!$A:$A,">="&DATE(MID(EW$3,3,4),6,1),FX!$A:$A,"<="&DATE(MID(EW$3,3,4),12,31)),"NA")) | EX66: =IF(VALUE(LEFT(EX$3,1))=1,AVERAGEIFS(FX!$B:$B,FX!$A:$A,">="&DATE(MID(EX$3,3,4),1,1),FX!$A:$A,"<="&DATE(MID(EX$3,3,4),6,30)),IF(VALUE(LEFT(EX$3,1))=2,AVERAGEIFS(FX!$B:$B,FX!$A:$A,">="&DATE(MID(EX$3,3,4),6,1),FX!$A:$A,"<="&DATE(MID(EX$3,3,4),12,31)),"NA")) | EY66: =AL66 | FA66: =IF(VALUE(LEFT(FA$3,1))=1,AVERAGEIFS(FX!$B:$B,FX!$A:$A,">="&DATE(MID(FA$3,3,4),1,1),FX!$A:$A,"<="&DATE(MID(FA$3,3,4),6,30)),IF(VALUE(LEFT(FA$3,1))=2,AVERAGEIFS(FX!$B:$B,FX!$A:$A,">="&DATE(MID(FA$3,3,4),6,1),FX!$A:$A,"<="&DATE(MID(FA$3,3,4),12,31)),"NA")) | FB66: =IF(VALUE(LEFT(FB$3,1))=1,AVERAGEIFS(FX!$B:$B,FX!$A:$A,">="&DATE(MID(FB$3,3,4),1,1),FX!$A:$A,"<="&DATE(MID(FB$3,3,4),6,30)),IF(VALUE(LEFT(FB$3,1))=2,AVERAGEIFS(FX!$B:$B,FX!$A:$A,">="&DATE(MID(FB$3,3,4),6,1),FX!$A:$A,"<="&DATE(MID(FB$3,3,4),12,31)),"NA")) | FC66: =AM66 | FE66: =IF(VALUE(LEFT(FE$3,1))=1,AVERAGEIFS(FX!$B:$B,FX!$A:$A,">="&DATE(MID(FE$3,3,4),1,1),FX!$A:$A,"<="&DATE(MID(FE$3,3,4),6,30)),IF(VALUE(LEFT(FE$3,1))=2,AVERAGEIFS(FX!$B:$B,FX!$A:$A,">="&DATE(MID(FE$3,3,4),6,1),FX!$A:$A,"<="&DATE(MID(FE$3,3,4),12,31)),"NA")) | FF66: =IF(VALUE(LEFT(FF$3,1))=1,AVERAGEIFS(FX!$B:$B,FX!$A:$A,">="&DATE(MID(FF$3,3,4),1,1),FX!$A:$A,"<="&DATE(MID(FF$3,3,4),6,30)),IF(VALUE(LEFT(FF$3,1))=2,AVERAGEIFS(FX!$B:$B,FX!$A:$A,">="&DATE(MID(FF$3,3,4),6,1),FX!$A:$A,"<="&DATE(MID(FF$3,3,4),12,31)),"NA")) | FG66: =AN66 | FI66: =IF(VALUE(LEFT(FI$3,1))=1,AVERAGEIFS(FX!$B:$B,FX!$A:$A,">="&DATE(MID(FI$3,3,4),1,1),FX!$A:$A,"<="&DATE(MID(FI$3,3,4),6,30)),IF(VALUE(LEFT(FI$3,1))=2,AVERAGEIFS(FX!$B:$B,FX!$A:$A,">="&DATE(MID(FI$3,3,4),6,1),FX!$A:$A,"<="&DATE(MID(FI$3,3,4),12,31)),"NA")) | FJ66: =IF(VALUE(LEFT(FJ$3,1))=1,AVERAGEIFS(FX!$B:$B,FX!$A:$A,">="&DATE(MID(FJ$3,3,4),1,1),FX!$A:$A,"<="&DATE(MID(FJ$3,3,4),6,30)),IF(VALUE(LEFT(FJ$3,1))=2,AVERAGEIFS(FX!$B:$B,FX!$A:$A,">="&DATE(MID(FJ$3,3,4),6,1),FX!$A:$A,"<="&DATE(MID(FJ$3,3,4),12,31)),"NA")) | FK66: =AO66 | FM66: =FJ66 | FN66: =FM66 | FO66: =AP66
B67: hkd/ cny (avg.) | G67: =AVERAGEIFS(FX!$C:$C,FX!$A:$A,">="&DATE(LEFT(G$3,4),1,1),FX!$A:$A,"<="&DATE(LEFT(G$3,4),12,13)) | H67: =AVERAGEIFS(FX!$C:$C,FX!$A:$A,">="&DATE(LEFT(H$3,4),1,1),FX!$A:$A,"<="&DATE(LEFT(H$3,4),12,13)) | I67: =AVERAGEIFS(FX!$C:$C,FX!$A:$A,">="&DATE(LEFT(I$3,4),1,1),FX!$A:$A,"<="&DATE(LEFT(I$3,4),12,13)) | J67: =AVERAGEIFS(FX!$C:$C,FX!$A:$A,">="&DATE(LEFT(J$3,4),1,1),FX!$A:$A,"<="&DATE(LEFT(J$3,4),12,13)) | K67: =AVERAGEIFS(FX!$C:$C,FX!$A:$A,">="&DATE(LEFT(K$3,4),1,1),FX!$A:$A,"<="&DATE(LEFT(K$3,4),12,13)) | L67: =AVERAGEIFS(FX!$C:$C,FX!$A:$A,">="&DATE(LEFT(L$3,4),1,1),FX!$A:$A,"<="&DATE(LEFT(L$3,4),12,13)) | M67: =AVERAGEIFS(FX!$C:$C,FX!$A:$A,">="&DATE(LEFT(M$3,4),1,1),FX!$A:$A,"<="&DATE(LEFT(M$3,4),12,13)) | N67: =AVERAGEIFS(FX!$C:$C,FX!$A:$A,">="&DATE(LEFT(N$3,4),1,1),FX!$A:$A,"<="&DATE(LEFT(N$3,4),12,13)) | ... AN67: =AVERAGEIFS(FX!$C:$C,FX!$A:$A,">="&DATE(LEFT(AN$3,4),1,1),FX!$A:$A,"<="&DATE(LEFT(AN$3,4),12,13)) | AO67: =AN67 | AP67: =AO67 | AQ67: =AP67 | AR67: =AQ67 | AS67: =AR67 | AT67: =AS67 | EK67: =IF(VALUE(LEFT(EK$3,1))=1,AVERAGEIFS(FX!$C:$C,FX!$A:$A,">="&DATE(MID(EK$3,3,4),1,1),FX!$A:$A,"<="&DATE(MID(EK$3,3,4),6,30)),IF(VALUE(LEFT(EK$3,1))=2,AVERAGEIFS(FX!$C:$C,FX!$A:$A,">="&DATE(MID(EK$3,3,4),6,1),FX!$A:$A,"<="&DATE(MID(EK$3,3,4),12,31)),"NA")) | EL67: =IF(VALUE(LEFT(EL$3,1))=1,AVERAGEIFS(FX!$C:$C,FX!$A:$A,">="&DATE(MID(EL$3,3,4),1,1),FX!$A:$A,"<="&DATE(MID(EL$3,3,4),6,30)),IF(VALUE(LEFT(EL$3,1))=2,AVERAGEIFS(FX!$C:$C,FX!$A:$A,">="&DATE(MID(EL$3,3,4),6,1),FX!$A:$A,"<="&DATE(MID(EL$3,3,4),12,31)),"NA")) | EM67: =AI67 | EO67: =IF(VALUE(LEFT(EO$3,1))=1,AVERAGEIFS(FX!$C:$C,FX!$A:$A,">="&DATE(MID(EO$3,3,4),1,1),FX!$A:$A,"<="&DATE(MID(EO$3,3,4),6,30)),IF(VALUE(LEFT(EO$3,1))=2,AVERAGEIFS(FX!$C:$C,FX!$A:$A,">="&DATE(MID(EO$3,3,4),6,1),FX!$A:$A,"<="&DATE(MID(EO$3,3,4),12,31)),"NA")) | EP67: =IF(VALUE(LEFT(EP$3,1))=1,AVERAGEIFS(FX!$C:$C,FX!$A:$A,">="&DATE(MID(EP$3,3,4),1,1),FX!$A:$A,"<="&DATE(MID(EP$3,3,4),6,30)),IF(VALUE(LEFT(EP$3,1))=2,AVERAGEIFS(FX!$C:$C,FX!$A:$A,">="&DATE(MID(EP$3,3,4),6,1),FX!$A:$A,"<="&DATE(MID(EP$3,3,4),12,31)),"NA")) | EQ67: =AJ67 | ES67: =IF(VALUE(LEFT(ES$3,1))=1,AVERAGEIFS(FX!$C:$C,FX!$A:$A,">="&DATE(MID(ES$3,3,4),1,1),FX!$A:$A,"<="&DATE(MID(ES$3,3,4),6,30)),IF(VALUE(LEFT(ES$3,1))=2,AVERAGEIFS(FX!$C:$C,FX!$A:$A,">="&DATE(MID(ES$3,3,4),6,1),FX!$A:$A,"<="&DATE(MID(ES$3,3,4),12,31)),"NA")) | ET67: =IF(VALUE(LEFT(ET$3,1))=1,AVERAGEIFS(FX!$C:$C,FX!$A:$A,">="&DATE(MID(ET$3,3,4),1,1),FX!$A:$A,"<="&DATE(MID(ET$3,3,4),6,30)),IF(VALUE(LEFT(ET$3,1))=2,AVERAGEIFS(FX!$C:$C,FX!$A:$A,">="&DATE(MID(ET$3,3,4),6,1),FX!$A:$A,"<="&DATE(MID(ET$3,3,4),12,31)),"NA")) | EU67: =AK67 | EW67: =IF(VALUE(LEFT(EW$3,1))=1,AVERAGEIFS(FX!$C:$C,FX!$A:$A,">="&DATE(MID(EW$3,3,4),1,1),FX!$A:$A,"<="&DATE(MID(EW$3,3,4),6,30)),IF(VALUE(LEFT(EW$3,1))=2,AVERAGEIFS(FX!$C:$C,FX!$A:$A,">="&DATE(MID(EW$3,3,4),6,1),FX!$A:$A,"<="&DATE(MID(EW$3,3,4),12,31)),"NA")) | EX67: =IF(VALUE(LEFT(EX$3,1))=1,AVERAGEIFS(FX!$C:$C,FX!$A:$A,">="&DATE(MID(EX$3,3,4),1,1),FX!$A:$A,"<="&DATE(MID(EX$3,3,4),6,30)),IF(VALUE(LEFT(EX$3,1))=2,AVERAGEIFS(FX!$C:$C,FX!$A:$A,">="&DATE(MID(EX$3,3,4),6,1),FX!$A:$A,"<="&DATE(MID(EX$3,3,4),12,31)),"NA")) | EY67: =AL67 | FA67: =IF(VALUE(LEFT(FA$3,1))=1,AVERAGEIFS(FX!$C:$C,FX!$A:$A,">="&DATE(MID(FA$3,3,4),1,1),FX!$A:$A,"<="&DATE(MID(FA$3,3,4),6,30)),IF(VALUE(LEFT(FA$3,1))=2,AVERAGEIFS(FX!$C:$C,FX!$A:$A,">="&DATE(MID(FA$3,3,4),6,1),FX!$A:$A,"<="&DATE(MID(FA$3,3,4),12,31)),"NA")) | FB67: =IF(VALUE(LEFT(FB$3,1))=1,AVERAGEIFS(FX!$C:$C,FX!$A:$A,">="&DATE(MID(FB$3,3,4),1,1),FX!$A:$A,"<="&DATE(MID(FB$3,3,4),6,30)),IF(VALUE(LEFT(FB$3,1))=2,AVERAGEIFS(FX!$C:$C,FX!$A:$A,">="&DATE(MID(FB$3,3,4),6,1),FX!$A:$A,"<="&DATE(MID(FB$3,3,4),12,31)),"NA")) | FC67: =AM67 | FE67: =IF(VALUE(LEFT(FE$3,1))=1,AVERAGEIFS(FX!$C:$C,FX!$A:$A,">="&DATE(MID(FE$3,3,4),1,1),FX!$A:$A,"<="&DATE(MID(FE$3,3,4),6,30)),IF(VALUE(LEFT(FE$3,1))=2,AVERAGEIFS(FX!$C:$C,FX!$A:$A,">="&DATE(MID(FE$3,3,4),6,1),FX!$A:$A,"<="&DATE(MID(FE$3,3,4),12,31)),"NA")) | FF67: =IF(VALUE(LEFT(FF$3,1))=1,AVERAGEIFS(FX!$C:$C,FX!$A:$A,">="&DATE(MID(FF$3,3,4),1,1),FX!$A:$A,"<="&DATE(MID(FF$3,3,4),6,30)),IF(VALUE(LEFT(FF$3,1))=2,AVERAGEIFS(FX!$C:$C,FX!$A:$A,">="&DATE(MID(FF$3,3,4),6,1),FX!$A:$A,"<="&DATE(MID(FF$3,3,4),12,31)),"NA")) | FG67: =AN67 | FI67: =IF(VALUE(LEFT(FI$3,1))=1,AVERAGEIFS(FX!$C:$C,FX!$A:$A,">="&DATE(MID(FI$3,3,4),1,1),FX!$A:$A,"<="&DATE(MID(FI$3,3,4),6,30)),IF(VALUE(LEFT(FI$3,1))=2,AVERAGEIFS(FX!$C:$C,FX!$A:$A,">="&DATE(MID(FI$3,3,4),6,1),FX!$A:$A,"<="&DATE(MID(FI$3,3,4),12,31)),"NA")) | FJ67: =IF(VALUE(LEFT(FJ$3,1))=1,AVERAGEIFS(FX!$C:$C,FX!$A:$A,">="&DATE(MID(FJ$3,3,4),1,1),FX!$A:$A,"<="&DATE(MID(FJ$3,3,4),6,30)),IF(VALUE(LEFT(FJ$3,1))=2,AVERAGEIFS(FX!$C:$C,FX!$A:$A,">="&DATE(MID(FJ$3,3,4),6,1),FX!$A:$A,"<="&DATE(MID(FJ$3,3,4),12,31)),"NA")) | FK67: =AO67 | FM67: =FJ67 | FN67: =FM67 | FO67: =AP67
B69: Labour Assumption
A70: staff nos | B70: staff nos. | C70: =C71/D71*D70 | D70: =D71/E71*E70 | E70: =E71/F71*F70 | F70: =F71/G71*G70 | G70: =G71/H71*H70 | H70: =H71/I71*I70 | I70: =I71/J71*J70 | J70: =J71/K71*K70 | ... U70: =U71/V71*V70 | V70: 25000 | W70: 25900 | X70: 27100 | Y70: 26700 | Z70: 27500 | AA70: 29000 | AB70: 29900 | AC70: 31600 | AD70: 32900 | AE70: 33600 | AF70: 33800 | AG70: 32700 | AH70: 32400 | AI70: 34200 | AJ70: 25600 | AK70: 21600 | AL70: 21200 | AM70: 23800 | AN70: 30100 | AO70: =+FJ70 | AP70: =+FN70 | AQ70: =AP70*(1+AQ73) | AR70: =AQ70*(1+AR73) | AS70: =AR70*(1+AS73) | AT70: =AS70*(1+AT73) | AX70: =L70 | BB70: =M70 | BD70: 14812 | BE70: =BF70 | BF70: =N70 | BH70: 13321 | BI70: =BJ70 | BJ70: =O70 | BL70: 13777 | BM70: =BN70 | BN70: =P70 | BP70: 14725 | BQ70: =BR70 | BR70: =Q70 | BT70: =BR70 | BU70: =BV70 | BV70: =R70 | BX70: 14800 | BY70: =BZ70 | BZ70: =S70 | CB70: 14800 | CC70: =CD70 | CD70: =T70 | CF70: 15400 | CG70: =CH70 | CH70: =U70 | CJ70: =CL70 | CK70: =CL70 | CL70: =V70 | CP70: =W70 | CU70: =X70 | CY70: =Y70 | DC70: =Z70 | DG70: =AA70 | DI70: 29800 | DJ70: =AB70 | DK70: =AB70 | DM70: 29900 | DN70: =AC70 | DO70: =AC70 | DQ70: 32200 | DR70: =AD70 | DS70: =AD70 | DU70: 33300 | DV70: =AE70 | DW70: =AE70 | DY70: 33700 | DZ70: =AF70 | EA70: =AF70 | EC70: 33200 | ED70: =AG70 | EE70: =AG70 | EG70: 32400 | EH70: =AH70 | EI70: =AH70 | EK70: 32800 | EL70: =AI70 | EM70: =AI70 | EO70: 33000 | EP70: =AJ70 | EQ70: =AJ70 | ES70: 23100 | ET70: =AK70 | EU70: =AK70 | EW70: 20800 | EX70: =AL70 | EY70: =AL70 | FA70: 21900 | FB70: =AM70 | FC70: =AM70 | FE70: 27200 | FF70: =AN70 | FG70: =AN70 | FI70: 32200 | FJ70: =FK70 | FK70: =AO70 | FM70: 33000 | FN70: =FJ70*(1+FN73) | FO70: =AP70
B71: Cathay Pacific (Company) | C71: 8581 | D71: 10142 | E71: 11728 | F71: 12764 | G71: 12747 | H71: 13240 | I71: 13857 | J71: 14216 | K71: 14744 | L71: =K71+1013 | M71: 15747 | N71: 13971 | O71: 13159 | P71: 14328 | Q71: 14473 | R71: 14649 | S71: 14673 | T71: 15054 | U71: 15806 | V71: 18992 | W71: 19840 | X71: 21309 | Y71: 20907 | Z71: 21592 | AA71: 23015 | AB71: 23844 | AC71: 24572 | AD71: 25755 | AE71: 26833 | AF71: 26674 | AG71: 26029 | AH71: 26623 | AI71: 27342 | AJ71: 19452 | AK71: 16721 | AL71: 16462 | AM71: 18211 | AN71: 25300 | EG71: =EG4/603*1000 | EH71: =AH71 | EI71: =AH71 | EK71: =EK4/604*1000 | EL71: =AI71 | EM71: =AI71 | EO71: =EO4/325*1000 | EP71: =AJ71 | EQ71: =AJ71 | ES71: =ES4/249*1000 | ET71: =AK71 | EU71: =AK71 | EW71: =EW4/191*1000 | EX71: =AL71 | EY71: =AL71 | FA71: =FA4/569*1000 | FB71: =AM71 | FC71: =AM71 | FE71: =FE4/573*1000 | FF71: =AN71 | FG71: =AN71 | FI71: =FI4/552*1000 | FJ71: =AO71
B72: Others | C72: =C70-C71 | D72: =D70-D71 | E72: =E70-E71 | F72: =F70-F71 | G72: =G70-G71 | H72: =H70-H71 | I72: =I70-I71 | J72: =J70-J71 | ... AN72: =AN70-AN71 | EG72: =EG70-EG71 | EH72: =EH70-EH71 | EI72: =EI70-EI71 | EK72: =EK70-EK71 | EL72: =EL70-EL71 | EM72: =EM70-EM71 | EO72: =EO70-EO71 | EP72: =EP70-EP71 | EQ72: =EQ70-EQ71 | ES72: =ES70-ES71 | ET72: =ET70-ET71 | EU72: =EU70-EU71 | EW72: =EW70-EW71 | EX72: =EX70-EX71 | EY72: =EY70-EY71 | FA72: =FA70-FA71 | FB72: =FB70-FB71 | FC72: =FC70-FC71 | FE72: =FE70-FE71 | FF72: =FF70-FF71 | FG72: =FG70-FG71 | FI72: =FI70-FI71 | FJ72: =FJ70-FJ71
B73: Change in staff nos | D73: =D70/C70-1 | E73: =E70/D70-1 | F73: =F70/E70-1 | G73: =G70/F70-1 | H73: =H70/G70-1 | I73: =I70/H70-1 | J73: =J70/I70-1 | K73: =K70/J70-1 | ... AP73: =AP70/AO70-1 | AQ73: 0.05 | AR73: 0.05 | AS73: 0.05 | AT73: 0.05 | EK73: =EK70/EG70-1 | EL73: =EL70/EH70-1 | EM73: =EM70/EI70-1 | EO73: =EO70/EK70-1 | EP73: =EP70/EL70-1 | EQ73: =EQ70/EM70-1 | ES73: =ES70/EO70-1 | ET73: =ET70/EP70-1 | EU73: =EU70/EQ70-1 | EW73: =EW70/ES70-1 | EX73: =EX70/ET70-1 | EY73: =EY70/EU70-1 | FA73: =FA70/EW70-1 | FB73: =FB70/EX70-1 | FC73: =FC70/EY70-1 | FE73: =FE70/FA70-1 | FF73: =FF70/FB70-1 | FG73: =FG70/FC70-1 | FI73: =FI70/FE70-1 | FJ73: =FJ70/FF70-1 | FK73: =FK70/FG70-1 | FM73: =FM70/FI70-1 | FN73: 0.05 | FO73: =FO70/FK70-1
B74: Average Monthly Salary (HK$ per staff) | H74: =H121/H70*(1000^2)/12 | I74: =I121/I70*(1000^2)/12 | J74: =J121/J70*(1000^2)/12 | K74: =K121/K70*(1000^2)/12 | L74: =L121/L70*(1000^2)/12 | M74: =M121/M70*(1000^2)/12 | N74: =N121/N70*(1000^2)/12 | O74: =O121/O70*(1000^2)/12 | ... AT74: =AT121/AT70*(1000^2)/12 | DG74: =+DG121/DG70*1000^2/12 | DI74: =+DI121/DI70*1000^2/6 | DJ74: =+DJ121/DJ70*1000^2/6 | DK74: =+DK121/DK70*1000^2/12 | DM74: =+DM121/DM70*1000^2/6 | DN74: =+DN121/DN70*1000^2/6 | DO74: =+DO121/DO70*1000^2/12 | DQ74: =+DQ121/DQ70*1000^2/6 | DR74: =+DR121/DR70*1000^2/6 | DS74: =+DS121/DS70*1000^2/12 | DU74: =+DU121/DU70*1000^2/6 | DV74: =+DV121/DV70*1000^2/6 | DW74: =+DW121/DW70*1000^2/12 | DY74: =+DY121/DY70*1000^2/6 | DZ74: =+DZ121/DZ70*1000^2/6 | EA74: =+EA121/EA70*1000^2/12 | EC74: =+EC121/EC70*1000^2/6 | ED74: =+ED121/ED70*1000^2/6 | EE74: =+EE121/EE70*1000^2/12 | EG74: =+EG121/EG70*1000^2/6 | EH74: =+EH121/EH70*1000^2/6 | EI74: =+EI121/EI70*1000^2/12 | EK74: =+EK121/EK70*1000^2/6 | EL74: =+EL121/EL70*1000^2/6 | EM74: =+EM121/EM70*1000^2/12 | EO74: =+EO121/EO70*1000^2/6 | EP74: =+EP121/EP70*1000^2/6 | EQ74: =+EQ121/EQ70*1000^2/12 | ES74: =+ES121/ES70*1000^2/6 | ET74: =+ET121/ET70*1000^2/6 | EU74: =AK74 | EW74: =+EW121/EW70*1000^2/6 | EX74: =+EX121/EX70*1000^2/6 | EY74: =AL74 | FA74: =+FA121/FA70*1000^2/6 | FB74: =+FB121/FB70*1000^2/6 | FC74: =AM74 | FE74: =+FE121/FE70*1000^2/6 | FF74: =+FF121/FF70*1000^2/6 | FG74: =AN74 | FI74: =+FI121/FI70*1000^2/6 | FJ74: =+FJ121/FJ70*1000^2/6 | FK74: =AW74 | FM74: =+FM121/FM70*1000^2/6 | FN74: =FJ74*(1+FN75) | FO74: =AW74
B75: pay rise YoY % | I75: =I74/H74-1 | J75: =J74/I74-1 | K75: =K74/J74-1 | L75: =L74/K74-1 | M75: =M74/L74-1 | N75: =N74/M74-1 | O75: =O74/N74-1 | P75: =P74/O74-1 | ... AP75: =AP74/AO74-1 | AQ75: 0.03 | AR75: 0.03 | AS75: 0.03 | AT75: 0.03 | BH75: 0.015 | BL75: =P75 | BP75: =Q75 | BR75: =Q75 | BT75: 0 | BV75: =R75 | BX75: 0.01 | BZ75: =S75 | CB75: 0.025 | CD75: =T75 | CF75: 0.025 | CJ75: 0.025 | CL75: =V75 | CP75: =W75 | CU75: =X75 | CY75: =Y75 | DC75: =Z75 | DG75: =AA75 | DI75: 0.03 | DK75: =AB75 | DM75: 0.02 | DO75: =AC75 | DQ75: =+(DQ121/DM121)-(DQ70/DM70) | DS75: =AG75 | DU75: =+(DU121/DQ121)-(DU70/DQ70) | DW75: =AE75 | DY75: -0.01 | EA75: =AF75 | EC75: 0.03 | EE75: =AG75 | EI75: =AH75 | EK75: =(EK121/AVERAGE(EK70))/(EG121/AVERAGE(EG70))-1 | EL75: =(EL121/AVERAGE(EL70))/(EH121/AVERAGE(EH70))-1 | EM75: =AI75 | EO75: =(EO121/AVERAGE(EO70))/(EK121/AVERAGE(EK70))-1 | EP75: =(EP121/AVERAGE(EP70))/(EL121/AVERAGE(EL70))-1 | EQ75: =AJ75 | ES75: =(ES121/AVERAGE(ES70))/(EO121/AVERAGE(EO70))-1 | ET75: =(ET121/AVERAGE(ET70))/(EP121/AVERAGE(EP70))-1 | EU75: =AK75 | EW75: =(EW121/AVERAGE(EW70))/(ES121/AVERAGE(ES70))-1 | EX75: =(EX121/AVERAGE(EX70))/(ET121/AVERAGE(ET70))-1 | EY75: =AL75 | FA75: =(FA121/AVERAGE(FA70))/(EW121/AVERAGE(EW70))-1 | FB75: =(FB121/AVERAGE(FB70))/(EX121/AVERAGE(EX70))-1 | FC75: =AM75 | FE75: =FE74/FA74-1 | FF75: =(FF121/AVERAGE(FF70))/(FB121/AVERAGE(FB70))-1 | FG75: =AN75 | FI75: =FI74/FE74-1 | FJ75: =(FJ121/AVERAGE(FJ70))/(FF121/AVERAGE(FF70))-1 | FK75: =AO75 | FM75: =FM74/FI74-1 | FN75: 0.07 | FO75: =AP75
B76: staff productivity (ATK per staff) | C76: =(C4)/C70*1000 | D76: =(D4)/D70*1000 | E76: =(E4)/E70*1000 | F76: =(F4)/F70*1000 | G76: =(G4)/G70*1000 | H76: =(H4)/H70*1000 | I76: =(I4)/I70*1000 | J76: =(J4)/J70*1000 | ... AT76: =(AT4)/AT70*1000 | AX76: =L76 | BB76: =M76 | BD76: =(BD4)/BD70*1000 | BE76: =(BE4)/BE70*1000 | BF76: =N76 | BH76: =(BH4)/BH70*1000 | BI76: =(BI4)/BI70*1000 | BJ76: =O76 | BL76: =(BL4)/BL70*1000 | BM76: =(BM4)/BM70*1000 | BN76: =P76 | BP76: =(BP4)/BP70*1000 | BQ76: =(BQ4)/BQ70*1000 | BR76: =Q76 | BT76: =(BT4)/BT70*1000 | BU76: =(BU4)/BU70*1000 | BV76: =R76 | BX76: =(BX4)/BX70*1000 | BY76: =(BY4)/BY70*1000 | BZ76: =S76 | CB76: =(CB4)/CB70*1000 | CC76: =(CC4)/CC70*1000 | CD76: =T76 | CF76: =(CF4)/CF70*1000 | CG76: =(CG4)/CG70*1000 | CH76: =U76 | CJ76: =(CJ4)/CJ70*1000 | CK76: =(CK4)/CK70*1000 | CL76: =V76 | CP76: =W76 | CU76: =X76 | CY76: =Y76 | DC76: =Z76 | DG76: =AA76 | DK76: =AB76 | DO76: =AC76 | DS76: =AD76 | DW76: =AE76 | EA76: =AF76 | EE76: =AG76 | EI76: =AH76 | EK76: =(EK4)/EK70*1000 | EL76: =(EL4)/EL70*1000 | EM76: =AI76 | EO76: =(EO4)/EO70*1000 | EP76: =(EP4)/EP70*1000 | EQ76: =AJ76 | ES76: =(ES4)/ES70*1000 | ET76: =(ET4)/ET70*1000 | EU76: =AK76 | EW76: =(EW4)/EW70*1000 | EX76: =(EX4)/EX70*1000 | EY76: =AL76 | FA76: =(FA4)/FA70*1000 | FB76: =(FB4)/FB70*1000 | FC76: =AM76 | FE76: =(FE4)/FE70*1000 | FF76: =(FF4)/FF70*1000 | FG76: =AN76 | FI76: =(FI4)/FI70*1000 | FJ76: =(FJ4)/FJ70*1000 | FK76: =AO76 | FM76: =(FM4)/FM70*1000 | FN76: =(FN4)/FN70*1000 | FO76: =AP76
A77: change staff pr | B77: Change in staff productivity | D77: =D76/C76-1 | E77: =E76/D76-1 | F77: =F76/E76-1 | G77: =G76/F76-1 | H77: =H76/G76-1 | I77: =I76/H76-1 | J77: =J76/I76-1 | K77: =K76/J76-1 | ... AT77: =AT76/AS76-1 | AX77: =L77 | BB77: =M77 | BF77: =N77 | BH77: =BH76/BD76-1 | BI77: =BI76/BE76-1 | BJ77: =O77 | BL77: =BL76/BH76-1 | BM77: =BM76/BI76-1 | BN77: =P77 | BP77: =BP76/BL76-1 | BQ77: =BQ76/BM76-1 | BR77: =Q77 | BT77: =BT76/BP76-1 | BU77: =BU76/BQ76-1 | BV77: =R77 | BX77: =BX76/BT76-1 | BY77: =BY76/BU76-1 | BZ77: =S77 | CB77: =CB76/BX76-1 | CC77: =CC76/BY76-1 | CD77: =T77 | CF77: =CF76/CB76-1 | CG77: =CG76/CC76-1 | CH77: =U77 | CJ77: =CJ76/CF76-1 | CK77: =CK76/CG76-1 | CL77: =V77 | CP77: =W77 | CU77: =X77 | CY77: =Y77 | DC77: =Z77 | DG77: =AA77 | DK77: =AB77 | DO77: =AC77 | DS77: =AD77 | DW77: =AE77 | EA77: =AF77 | EE77: =AG77 | EI77: =AH77 | EM77: =AI77 | EQ77: =AJ77 | EU77: =AK77 | EY77: =AL77 | FC77: =AM77 | FG77: =AN77 | FK77: =AO77 | FO77: =AP77
B79: Fuel Cost
B80: Brent oil Price | C80: =INDEX(Fuel!$AG:$AG,MATCH(DATE(LEFT(C$3,4),12,31),Fuel!$AF:$AF,0),1,1) | D80: =INDEX(Fuel!$AG:$AG,MATCH(DATE(LEFT(D$3,4),12,31),Fuel!$AF:$AF,0),1,1) | E80: =INDEX(Fuel!$AG:$AG,MATCH(DATE(LEFT(E$3,4),12,31),Fuel!$AF:$AF,0),1,1) | F80: =INDEX(Fuel!$AG:$AG,MATCH(DATE(LEFT(F$3,4),12,31),Fuel!$AF:$AF,0),1,1) | G80: =INDEX(Fuel!$AG:$AG,MATCH(DATE(LEFT(G$3,4),12,31),Fuel!$AF:$AF,0),1,1) | H80: =INDEX(Fuel!$AG:$AG,MATCH(DATE(LEFT(H$3,4),12,31),Fuel!$AF:$AF,0),1,1) | I80: =INDEX(Fuel!$AG:$AG,MATCH(DATE(LEFT(I$3,4),12,31),Fuel!$AF:$AF,0),1,1) | J80: =INDEX(Fuel!$AG:$AG,MATCH(DATE(LEFT(J$3,4),12,31),Fuel!$AF:$AF,0),1,1) | ... AN80: =INDEX(Fuel!$AG:$AG,MATCH(DATE(LEFT(AN$3,4),12,31),Fuel!$AF:$AF,0),1,1) | AO80: =AVERAGE(FI80:FJ80) | AP80: =AVERAGE(FM80:FN80) | AQ80: 75 | AR80: 75 | AS80: 75 | AT80: 75 | EK80: =INDEX(Fuel!$AB:$AB,MATCH(EOMONTH(DATE(MID(EK$3,3,4),LEFT(EK$3)*6,1),0),Fuel!$AA:$AA,0),1,1) | EL80: =INDEX(Fuel!$AB:$AB,MATCH(EOMONTH(DATE(MID(EL$3,3,4),LEFT(EL$3)*6,1),0),Fuel!$AA:$AA,0),1,1) | EM80: =AI80 | EO80: =INDEX(Fuel!$AB:$AB,MATCH(EOMONTH(DATE(MID(EO$3,3,4),LEFT(EO$3)*6,1),0),Fuel!$AA:$AA,0),1,1) | EP80: =INDEX(Fuel!$AB:$AB,MATCH(EOMONTH(DATE(MID(EP$3,3,4),LEFT(EP$3)*6,1),0),Fuel!$AA:$AA,0),1,1) | EQ80: =AJ80 | ES80: =INDEX(Fuel!$AB:$AB,MATCH(EOMONTH(DATE(MID(ES$3,3,4),LEFT(ES$3)*6,1),0),Fuel!$AA:$AA,0),1,1) | ET80: =INDEX(Fuel!$AB:$AB,MATCH(EOMONTH(DATE(MID(ET$3,3,4),LEFT(ET$3)*6,1),0),Fuel!$AA:$AA,0),1,1) | EU80: =AK80 | EW80: =INDEX(Fuel!$AB:$AB,MATCH(EOMONTH(DATE(MID(EW$3,3,4),LEFT(EW$3)*6,1),0),Fuel!$AA:$AA,0),1,1) | EX80: =INDEX(Fuel!$AB:$AB,MATCH(EOMONTH(DATE(MID(EX$3,3,4),LEFT(EX$3)*6,1),0),Fuel!$AA:$AA,0),1,1) | EY80: =AL80 | FA80: =INDEX(Fuel!$AB:$AB,MATCH(EOMONTH(DATE(MID(FA$3,3,4),LEFT(FA$3)*6,1),0),Fuel!$AA:$AA,0),1,1) | FB80: =INDEX(Fuel!$AB:$AB,MATCH(EOMONTH(DATE(MID(FB$3,3,4),LEFT(FB$3)*6,1),0),Fuel!$AA:$AA,0),1,1) | FC80: =AM80 | FE80: =INDEX(Fuel!$AB:$AB,MATCH(EOMONTH(DATE(MID(FE$3,3,4),LEFT(FE$3)*6,1),0),Fuel!$AA:$AA,0),1,1) | FF80: =INDEX(Fuel!$AB:$AB,MATCH(EOMONTH(DATE(MID(FF$3,3,4),LEFT(FF$3)*6,1),0),Fuel!$AA:$AA,0),1,1) | FG80: =AN80 | FI80: =INDEX(Fuel!$AB:$AB,MATCH(EOMONTH(DATE(MID(FI$3,3,4),LEFT(FI$3)*6,1),0),Fuel!$AA:$AA,0),1,1) | FJ80: =INDEX(Fuel!$AB:$AB,MATCH(EOMONTH(DATE(MID(FJ$3,3,4),LEFT(FJ$3)*6,1),0),Fuel!$AA:$AA,0),1,1) | FK80: =AO80 | FM80: =INDEX(Fuel!$AB:$AB,MATCH(EOMONTH(DATE(MID(FM$3,3,4),LEFT(FM$3)*6,1),0),Fuel!$AA:$AA,0),1,1) | FN80: 80 | FO80: =AP80
B81: YoY % | D81: =D80/C80-1 | E81: =E80/D80-1 | F81: =F80/E80-1 | G81: =G80/F80-1 | H81: =H80/G80-1 | I81: =I80/H80-1 | J81: =J80/I80-1 | K81: =K80/J80-1 | ... AT81: =AT80/AS80-1 | EO81: =EO80/EK80-1 | EP81: =EP80/EL80-1 | EQ81: =EQ80/EM80-1 | ES81: =ES80/EO80-1 | ET81: =ET80/EP80-1 | EU81: =EU80/EQ80-1 | EW81: =EW80/ES80-1 | EX81: =EX80/ET80-1 | EY81: =EY80/EU80-1 | FA81: =FA80/EW80-1 | FB81: =FB80/EX80-1 | FC81: =FC80/EY80-1 | FE81: =FE80/FA80-1 | FF81: =FF80/FB80-1 | FG81: =AN81 | FI81: =FI80/FE80-1 | FJ81: =FJ80/FF80-1 | FK81: =AO81 | FM81: =FM80/FI80-1 | FN81: =FN80/FJ80-1 | FO81: =AP81
B82: Crack spread | C82: =C83-C80 | D82: =D83-D80 | E82: =E83-E80 | F82: =F83-F80 | G82: =G83-G80 | H82: =H83-H80 | I82: =I83-I80 | J82: =J83-J80 | ... AN82: =AN83-AN80 | AO82: =AVERAGE(FI82:FJ82) | AP82: =AVERAGE(FM82:FN82) | AQ82: =AVERAGE(AO82:AP82) | AR82: =AQ82 | AS82: =AR82 | AT82: =AS82 | EK82: =+EK83-EK80 | EL82: =+EL83-EL80 | EM82: =+EM83-EM80 | EO82: =+EO83-EO80 | EP82: =+EP83-EP80 | EQ82: =+EQ83-EQ80 | ES82: =+ES83-ES80 | ET82: =+ET83-ET80 | EU82: =+EU83-EU80 | EW82: =+EW83-EW80 | EX82: =+EX83-EX80 | EY82: =+EY83-EY80 | FA82: =+FA83-FA80 | FB82: =+FB83-FB80 | FC82: =+FC83-FC80 | FE82: =+FE83-FE80 | FF82: =+FF83-FF80 | FG82: =AN82 | FI82: =FI83-FI80 | FJ82: =+FJ83-FJ80 | FK82: =AO82 | FM82: =+FM83-FM80 | FN82: =FM82 | FO82: =AP82
B83: Singapore Jet Price | C83: =INDEX(Fuel!$AI:$AI,MATCH(DATE(LEFT(C$3,4),12,31),Fuel!$AF:$AF,0),1,1) | D83: =INDEX(Fuel!$AI:$AI,MATCH(DATE(LEFT(D$3,4),12,31),Fuel!$AF:$AF,0),1,1) | E83: =INDEX(Fuel!$AI:$AI,MATCH(DATE(LEFT(E$3,4),12,31),Fuel!$AF:$AF,0),1,1) | F83: =INDEX(Fuel!$AI:$AI,MATCH(DATE(LEFT(F$3,4),12,31),Fuel!$AF:$AF,0),1,1) | G83: =INDEX(Fuel!$AI:$AI,MATCH(DATE(LEFT(G$3,4),12,31),Fuel!$AF:$AF,0),1,1) | H83: =INDEX(Fuel!$AI:$AI,MATCH(DATE(LEFT(H$3,4),12,31),Fuel!$AF:$AF,0),1,1) | I83: =INDEX(Fuel!$AI:$AI,MATCH(DATE(LEFT(I$3,4),12,31),Fuel!$AF:$AF,0),1,1) | J83: =INDEX(Fuel!$AI:$AI,MATCH(DATE(LEFT(J$3,4),12,31),Fuel!$AF:$AF,0),1,1) | ... AN83: =INDEX(Fuel!$AI:$AI,MATCH(DATE(LEFT(AN$3,4),12,31),Fuel!$AF:$AF,0),1,1) | AO83: =+AO80+AO82 | AP83: =+AP80+AP82 | AQ83: =+AQ80+AQ82 | AR83: =+AR80+AR82 | AS83: =+AS80+AS82 | AT83: =+AT80+AT82 | EK83: =INDEX(Fuel!$AD:$AD,MATCH(EOMONTH(DATE(MID(EK$3,3,4),LEFT(EK$3)*6,1),0),Fuel!$AA:$AA,0),1,1) | EL83: =INDEX(Fuel!$AD:$AD,MATCH(EOMONTH(DATE(MID(EL$3,3,4),LEFT(EL$3)*6,1),0),Fuel!$AA:$AA,0),1,1) | EM83: =AI83 | EO83: =INDEX(Fuel!$AD:$AD,MATCH(EOMONTH(DATE(MID(EO$3,3,4),LEFT(EO$3)*6,1),0),Fuel!$AA:$AA,0),1,1) | EP83: =INDEX(Fuel!$AD:$AD,MATCH(EOMONTH(DATE(MID(EP$3,3,4),LEFT(EP$3)*6,1),0),Fuel!$AA:$AA,0),1,1) | EQ83: =AJ83 | ES83: =INDEX(Fuel!$AD:$AD,MATCH(EOMONTH(DATE(MID(ES$3,3,4),LEFT(ES$3)*6,1),0),Fuel!$AA:$AA,0),1,1) | ET83: =INDEX(Fuel!$AD:$AD,MATCH(EOMONTH(DATE(MID(ET$3,3,4),LEFT(ET$3)*6,1),0),Fuel!$AA:$AA,0),1,1) | EU83: =AK83 | EW83: =INDEX(Fuel!$AD:$AD,MATCH(EOMONTH(DATE(MID(EW$3,3,4),LEFT(EW$3)*6,1),0),Fuel!$AA:$AA,0),1,1) | EX83: =INDEX(Fuel!$AD:$AD,MATCH(EOMONTH(DATE(MID(EX$3,3,4),LEFT(EX$3)*6,1),0),Fuel!$AA:$AA,0),1,1) | EY83: =AL83 | FA83: =INDEX(Fuel!$AD:$AD,MATCH(EOMONTH(DATE(MID(FA$3,3,4),LEFT(FA$3)*6,1),0),Fuel!$AA:$AA,0),1,1) | FB83: =INDEX(Fuel!$AD:$AD,MATCH(EOMONTH(DATE(MID(FB$3,3,4),LEFT(FB$3)*6,1),0),Fuel!$AA:$AA,0),1,1) | FC83: =AM83 | FE83: =INDEX(Fuel!$AD:$AD,MATCH(EOMONTH(DATE(MID(FE$3,3,4),LEFT(FE$3)*6,1),0),Fuel!$AA:$AA,0),1,1) | FF83: =INDEX(Fuel!$AD:$AD,MATCH(EOMONTH(DATE(MID(FF$3,3,4),LEFT(FF$3)*6,1),0),Fuel!$AA:$AA,0),1,1) | FG83: =AN83 | FI83: =INDEX(Fuel!$AD:$AD,MATCH(EOMONTH(DATE(MID(FI$3,3,4),LEFT(FI$3)*6,1),0),Fuel!$AA:$AA,0),1,1) | FJ83: =INDEX(Fuel!$AD:$AD,MATCH(EOMONTH(DATE(MID(FJ$3,3,4),LEFT(FJ$3)*6,1),0),Fuel!$AA:$AA,0),1,1) | FK83: =AO83 | FM83: =INDEX(Fuel!$AD:$AD,MATCH(EOMONTH(DATE(MID(FM$3,3,4),LEFT(FM$3)*6,1),0),Fuel!$AA:$AA,0),1,1) | FN83: =INDEX(Fuel!$AD:$AD,MATCH(EOMONTH(DATE(MID(FN$3,3,4),LEFT(FN$3)*6,1),0),Fuel!$AA:$AA,0),1,1) | FO83: =AP83
B84: YoY % | D84: =D83/C83-1 | E84: =E83/D83-1 | F84: =F83/E83-1 | G84: =G83/F83-1 | H84: =H83/G83-1 | I84: =I83/H83-1 | J84: =J83/I83-1 | K84: =K83/J83-1 | ... AT84: =AT83/AS83-1 | EO84: =EO83/EK83-1 | EP84: =EP83/EL83-1 | EQ84: =EQ83/EM83-1 | ES84: =ES83/EO83-1 | ET84: =ET83/EP83-1 | EU84: =EU83/EQ83-1 | EW84: =EW83/ES83-1 | EX84: =EX83/ET83-1 | EY84: =EY83/EU83-1 | FA84: =FA83/EW83-1 | FB84: =FB83/EX83-1 | FC84: =FC83/EY83-1 | FE84: =FE83/FA83-1 | FF84: =FF83/FB83-1 | FG84: =AN84 | FI84: =FI83/FE83-1 | FJ84: =FJ83/FF83-1 | FK84: =AO84 | FM84: =FM83/FI83-1 | FN84: =FN83/FJ83-1 | FO84: =AP84
B85: Hedge Profiles
B86: Strike Price | AO86: =SUMPRODUCT($FI86:$FJ86,$FI$87:$FJ$87,$FI$90:$FJ$90)/SUMPRODUCT($FI$87:$FJ$87,$FI$90:$FJ$90) | AP86: =SUMPRODUCT($FM86:$FN86,$FM$87:$FN$87,$FM$90:$FN$90)/SUMPRODUCT($FM$87:$FN$87,$FM$90:$FN$90) | AQ86: =AVERAGE(65,66,67,68) | AR86: =AVERAGE(71,75) | FI86: 75 | FM86: =AVERAGE(76,70) | FN86: =AVERAGE(68,66)
B87: Hedge Ratio (%) | AO87: =SUMPRODUCT($FI$87:$FJ$87,$FI$90:$FJ$90)/SUMPRODUCT($FI$90:$FJ$90) | AP87: =SUMPRODUCT($FM$87:$FN$87,$FM$90:$FN$90)/SUMPRODUCT($FM$90:$FN$90) | AQ87: =AVERAGE(33%,31%,30%,25%) | AR87: =AVERAGE(15%,5%,0%,0%) | FI87: =AVERAGE(30%,28%) | FM87: =AVERAGE(30%,33%) | FN87: =AVERAGE(33%,35%)
B88: Post-hedge Jet Fuel Price (US$/bbl) | T88: =T122/T90/T66 | U88: =U122/U90/U66 | V88: =V122/V90/V66 | W88: =W122/W90/W66 | X88: =X122/X90/X66 | Y88: =Y122/Y90/Y66 | Z88: =Z122/Z90/Z66 | AA88: =AA122/AA90/AA66 | ... AP88: =AP122/AP90/AP66 | AQ88: =(+AQ$86+AQ82)*AQ$87+(1-AQ$87)*AQ$83 | AR88: =(+AR$86+AR82)*AR$87+(1-AR$87)*AR$83 | AS88: =(+AS$86+AS82)*AS$87+(1-AS$87)*AS$83 | AT88: =(+AT$86+AT82)*AT$87+(1-AT$87)*AT$83 | DU88: 80 | DY88: =85*0.6+47*0.4 | EC88: =89*0.51+64*0.49 | EG88: =EG122/EG90/7.8 | EH88: =EH122/EH90/7.8 | EI88: =AH88 | EK88: =EK122/EK90/7.8 | EL88: =EL122/EL90/7.8 | EM88: =AI88 | EO88: =EO122/EO90/7.8 | EP88: =EP122/EP90/7.8 | EQ88: =+AJ88 | ES88: =ES122/ES90/7.8 | ET88: =ET122/ET90/7.8 | EU88: =AK88 | EW88: =EW122/EW90/7.8 | EX88: =EX122/EX90/7.8 | EY88: =AL88 | FA88: =FA122/FA90/7.8 | FB88: =FB122/FB90/7.8 | FC88: =AM88 | FE88: 109.31 | FF88: =FF122/FF90/7.8 | FG88: =AN88 | FI88: 93.68 | FJ88: =FJ122/FJ90/7.8 | FK88: =AO88 | FM88: 138.31 | FN88: =(+FN$86+FN82)*FN$87+(1-FN$87)*FN$83 | FO88: =AP88
B89: YoY % | U89: =U88/T88-1 | V89: =V88/U88-1 | W89: =W88/V88-1 | X89: =X88/W88-1 | Y89: =Y88/X88-1 | Z89: =Z88/Y88-1 | AA89: =AA88/Z88-1 | AB89: =AB88/AA88-1 | ... AT89: =AT88/AS88-1 | EO89: =EO88/EK88-1 | EP89: =EP88/EL88-1 | EQ89: =EQ88/EM88-1 | ES89: =ES88/EO88-1 | ET89: =ET88/EP88-1 | EU89: =EU88/EQ88-1 | EW89: =EW88/ES88-1 | EX89: =EX88/ET88-1 | EY89: =EY88/EU88-1 | FA89: =FA88/EW88-1 | FB89: =FB88/EX88-1 | FC89: =FC88/EY88-1 | FE89: =FE88/FA88-1 | FF89: =FF88/FB88-1 | FG89: =AN89 | FI89: =FI88/FE88-1 | FJ89: =FJ88/FF88-1 | FK89: =AO89 | FM89: =FM88/FI88-1 | FN89: =FN88/FJ88-1 | FO89: =AP89
B90: Average fuel consumption (mn bbl) | T90: =U90/(1.112) | U90: =1160/42 | V90: 29 | W90: 35.8 | X90: 38.3 | Y90: 35.3 | Z90: 37.9 | AA90: 40.4 | AB90: 40.1 | AC90: 39.5 | AD90: 41.7 | AE90: 43.5 | AF90: 43.9 | AG90: 45.1 | AH90: 45.8 | AI90: 46.6 | AJ90: 18.7 | AK90: 15 | AL90: 13.3 | AM90: 28.8 | AN90: 35.1 | AO90: =SUM(FI90:FJ90) | AP90: =SUM(FM90:FN90) | AQ90: =AQ4/AQ92 | AR90: =AR4/AR92 | AS90: =AS4/AS92 | AT90: =AT4/AT92 | EG90: =EG4/EG92 | EH90: =EI90-EG90 | EI90: =AH90 | EK90: =EK4/EK92 | EL90: =EM90-EK90 | EM90: =AI90 | EO90: =EO4/EO92 | EP90: =EQ90-EO90 | EQ90: =+AJ90 | ES90: =ES4/ES92 | ET90: =EU90-ES90 | EU90: =AK90 | EW90: =EW4/EW92 | EX90: =EY90-EW90 | EY90: =AL90 | FA90: =FA4/FA92 | FB90: =FC90-FA90 | FC90: =AM90 | FE90: =FE122/(FE88*FE66) | FF90: =FG90-FE90 | FG90: =AN90 | FI90: =FI122/(FI88*FI66) | FJ90: =FK90-FI90 | FK90: =AO90 | FM90: =FM122/(FM88*FM66) | FN90: =FN4/FN92 | FO90: =AP90
B91: YoY % | U91: =+U90/T90-1 | V91: =+V90/U90-1 | W91: =+W90/V90-1 | X91: =+X90/W90-1 | Y91: =+Y90/X90-1 | Z91: =+Z90/Y90-1 | AA91: =+AA90/Z90-1 | AB91: =+AB90/AA90-1 | ... AT91: =+AT90/AS90-1 | EK91: =EK90/EG90-1 | EL91: =EL90/EH90-1 | EM91: =EM90/EI90-1 | EO91: =EO90/EK90-1 | EP91: =EP90/EL90-1 | EQ91: =EQ90/EM90-1 | ES91: =ES90/EO90-1 | ET91: =ET90/EP90-1 | EU91: =EU90/EQ90-1 | EW91: =EW90/ES90-1 | EX91: =EX90/ET90-1 | EY91: =EY90/EU90-1 | FA91: =FA90/EW90-1 | FB91: =FB90/EX90-1 | FC91: =FC90/EY90-1 | FE91: =FE90/FA90-1 | FF91: =FF90/FB90-1 | FG91: =AN91 | FI91: =FI90/FE90-1 | FJ91: =FJ90/FF90-1 | FK91: =AO91 | FM91: =FM90/FI90-1 | FN91: =FN90/FJ90-1 | FO91: =AP91
B92: Fuel efficiency (ATK per Barrel of fuel) | T92: =T4/T90 | U92: =U4/U90 | V92: =V4/V90 | W92: =W4/W90 | X92: =X4/X90 | Y92: =Y4/Y90 | Z92: =Z4/Z90 | AA92: =AA4/AA90 | ... AP92: =AP4/AP90 | AQ92: =AP92*(1+AQ93) | AR92: =AQ92*(1+AR93) | AS92: =AR92*(1+AS93) | AT92: =AS92*(1+AT93) | EG92: =1000^2/1390 | EH92: =EH4/EH90 | EI92: =AH92 | EK92: =1000^2/1369 | EL92: =EL4/EL90 | EM92: =AI92 | EO92: =1000^2/1253 | EP92: =EP4/EP90 | EQ92: =+AJ92 | ES92: =1000^2/1109 | ET92: =ET4/ET90 | EU92: =AK92 | EW92: =1000^2/1316 | EX92: =EX4/EX90 | EY92: =AL92 | FA92: =1000^2/1222 | FB92: =FB4/FB90 | FC92: =AM92 | FE92: =FE4/FE90 | FF92: =FF4/FF90 | FG92: =AN92 | FI92: =FI4/FI90 | FJ92: =FJ4/FJ90 | FM92: =FM4/FM90 | FN92: =FJ92
B93: YoY % | U93: =U92/T92-1 | V93: =V92/U92-1 | W93: =W92/V92-1 | X93: =X92/W92-1 | Y93: =Y92/X92-1 | Z93: =Z92/Y92-1 | AA93: =AA92/Z92-1 | AB93: =AB92/AA92-1 | ... AP93: =AP92/AO92-1 | AQ93: 0 | AR93: 0 | AS93: 0 | AT93: 0 | FE93: =FE92/FA92-1 | FF93: =FF92/FB92-1 | FI93: =FI92/FE92-1 | FJ93: =FJ92/FF92-1 | FM93: =FM92/FI92-1 | FN93: =FN92/FJ92-1
B94: Net Fuel Cost | H94: =+H122 | I94: =+I122 | J94: =+J122 | K94: =+K122 | L94: =+L122 | M94: =+M122 | N94: =+N122 | O94: =+O122 | ... AT94: =+AT122
B95: Fuel hedging gains/losses | V95: =W95-527 | W95: 933 | X95: =-7661-309 | Y95: 2758 | Z95: -41 | AA95: 1814 | AB95: 544 | AC95: 985 | AD95: -911 | AE95: -8474 | AF95: -8456 | AG95: -6377 | AH95: -1445 | AI95: -101 | AJ95: -3017 | AK95: 2336 | AL95: 3639 | AM95: 694 | AN95: 35
B97: Other assumptions
B98: Background efficiency | M98: =M4/(+M131-M129-M128-M122-M121) | N98: =N4/(+N131-N129-N128-N122-N121) | O98: =O4/(+O131-O129-O128-O122-O121) | P98: =P4/(+P131-P129-P128-P122-P121) | Q98: =Q4/(+Q131-Q129-Q128-Q122-Q121) | R98: =R4/(+R131-R129-R128-R122-R121) | S98: =S4/(+S131-S129-S128-S122-S121) | T98: =T4/(+T131-T129-T128-T122-T121) | ... AP98: =AP4/(+AP131-AP129-AP128-AP122-AP121) | AQ98: =AP98*(1+AQ99) | AR98: =AQ98*(1+AR99) | AS98: =AR98*(1+AS99) | AT98: =AS98*(1+AT99) | DU98: =DU4/(+DU131-DU129-DU128-DU122-DU121) | DV98: =DV4/(+DV131-DV129-DV128-DV122-DV121) | DY98: =DY4/(+DY131-DY129-DY128-DY122-DY121) | DZ98: =DZ4/(+DZ131-DZ129-DZ128-DZ122-DZ121) | EC98: =EC4/(+EC131-EC129-EC128-EC122-EC121) | ED98: =ED4/(+ED131-ED129-ED128-ED122-ED121) | EG98: =EG4/(+EG131-EG129-EG128-EG122-EG121) | EH98: =EH4/(+EH131-EH129-EH128-EH122-EH121) | EK98: =EK4/(+EK131-EK129-EK128-EK122-EK121) | EL98: =EL4/(+EL131-EL129-EL128-EL122-EL121) | EO98: =EO4/(+EO131-EO129-EO128-EO122-EO121) | EP98: =EP4/(+EP131-EP129-EP128-EP122-EP121) | ES98: =ES4/(+ES131-ES129-ES128-ES122-ES121) | ET98: =ET4/(+ET131-ET129-ET128-ET122-ET121) | EW98: =EW4/(+EW131-EW129-EW128-EW122-EW121) | EX98: =EX4/(+EX131-EX129-EX128-EX122-EX121) | FA98: =FA4/(+FA131-FA129-FA128-FA122-FA121) | FB98: =FB4/(+FB131-FB129-FB128-FB122-FB121) | FE98: =FE4/(+FE131-FE129-FE128-FE122-FE121) | FF98: =FF4/(+FF131-FF129-FF128-FF122-FF121) | FI98: =FI4/(+FI131-FI129-FI128-FI122-FI121) | FJ98: =FJ4/(+FJ131-FJ129-FJ128-FJ122-FJ121) | FM98: =FM4/(+FM131-FM129-FM128-FM122-FM121) | FN98: =FJ98*(1+FN99)
B99: % chg | N99: =N98/M98-1 | O99: =O98/N98-1 | P99: =P98/O98-1 | Q99: =Q98/P98-1 | R99: =R98/Q98-1 | S99: =S98/R98-1 | T99: =T98/S98-1 | U99: =U98/T98-1 | ... AP99: =AP98/AO98-1 | AQ99: -0.01 | AR99: -0.01 | AS99: -0.01 | AT99: -0.01 | FI99: =FI98/FE98-1 | FM99: =FM98/FI98-1 | FN99: 0
B100: Unit costs - ex-fuel | C100: =(C131-C122)/C4 | D100: =(D131-D122)/D4 | E100: =(E131-E122)/E4 | F100: =(F131-F122)/F4 | G100: =(G131-G122)/G4 | H100: =(H131-H122)/H4 | I100: =(I131-I122)/I4 | J100: =(J131-J122)/J4 | ... AT100: =(AT131-AT122)/AT4 | AV100: =(AV131-AV122)/AV4 | AW100: =(AW131-AW122)/AW4 | AX100: =(AX131-AX122)/AX4 | AZ100: =(AZ131-AZ122)/AZ4 | BA100: =(BA131-BA122)/BA4 | BB100: =(BB131-BB122)/BB4 | BD100: =(BD131-BD122)/BD4 | BE100: =(BE131-BE122)/BE4 | BF100: =(BF131-BF122)/BF4 | BH100: =(BH131-BH122)/BH4 | BI100: =(BI131-BI122)/BI4 | BJ100: =(BJ131-BJ122)/BJ4 | BL100: =(BL131-BL122)/BL4 | BM100: =(BM131-BM122)/BM4 | BN100: =(BN131-BN122)/BN4 | BP100: =(BP131-BP122)/BP4 | BQ100: =(BQ131-BQ122)/BQ4 | BR100: =(BR131-BR122)/BR4 | BT100: =(BT131-BT122)/BT4 | BU100: =(BU131-BU122)/BU4 | BV100: =(BV131-BV122)/BV4 | BX100: =(BX131-BX122)/BX4 | BY100: =(BY131-BY122)/BY4 | BZ100: =(BZ131-BZ122)/BZ4 | CB100: =(CB131-CB122)/CB4 | CC100: =(CC131-CC122)/CC4 | CD100: =(CD131-CD122)/CD4 | CF100: =(CF131-CF122)/CF4 | CG100: =(CG131-CG122)/CG4 | CH100: =(CH131-CH122)/CH4 | CJ100: =(CJ131-CJ122)/CJ4 | CK100: =(CK131-CK122)/CK4 | CL100: =V100 | CN100: =(CN131-CN122)/CN4 | CO100: =(CO131-CO122)/CO4 | CP100: =W100 | CR100: =(CR131-CR122)/CR4 | CT100: =(CT131-CT122)/CT4 | CU100: =X100 | CW100: =(CW131-CW122)/CW4 | CX100: =(CX131-CX122)/CX4 | CY100: =Y100 | DA100: =(DA131-DA122)/DA4 | DB100: =(DB131-DB122)/DB4 | DC100: =Z100 | DE100: =(DE131-DE122)/DE4 | DF100: =(DF131-DF122)/DF4 | DG100: =AA100 | DI100: =(DI131-DI122)/DI4 | DJ100: =(DJ131-DJ122)/DJ4 | DK100: =AB100 | DM100: =(DM131-DM122)/DM4 | DN100: =(DN131-DN122)/DN4 | DO100: =AC100 | DQ100: =(DQ131-DQ122)/DQ4 | DR100: =(DR131-DR122)/DR4 | DS100: =AG100 | DU100: =(DU131-DU122)/DU4 | DV100: =(DV131-DV122)/DV4 | DW100: =AE100 | DY100: =(DY131-DY122)/DY4 | DZ100: =(DZ131-DZ122)/DZ4 | EA100: =AF100 | EC100: =(EC131-EC122)/EC4 | ED100: =(ED131-ED122)/ED4 | EE100: =AG100 | EG100: =(EG131-EG122)/EG4 | EH100: =(EH131-EH122)/EH4 | EI100: =AH100 | EK100: =(EK131-EK122)/EK4 | EL100: =(EL131-EL122)/EL4 | EM100: =AI100 | EO100: =(EO131-EO122)/EO4 | EP100: =(EP131-EP122)/EP4 | EQ100: =AJ100 | ES100: =(ES131-ES122)/ES4 | ET100: =(ET131-ET122)/ET4 | EU100: =AK100 | EW100: =(EW131-EW122)/EW4 | EX100: =(EX131-EX122)/EX4 | EY100: =AL100 | FA100: =(FA131-FA122)/FA4 | FB100: =(FB131-FB122)/FB4 | FC100: =AM100 | FE100: =(FE131-FE122)/FE4 | FF100: =(FF131-FF122)/FF4 | FG100: =AN100 | FI100: =(FI131-FI122)/FI4 | FJ100: =(FJ131-FJ122)/FJ4 | FK100: =AO100 | FM100: =(FM131-FM122)/FM4 | FN100: =(FN131-FN122)/FN4 | FO100: =AP100
B101: YoY % | D101: =D100/C100-1 | E101: =E100/D100-1 | F101: =F100/E100-1 | G101: =G100/F100-1 | H101: =H100/G100-1 | I101: =I100/H100-1 | J101: =J100/I100-1 | K101: =K100/J100-1 | ... AT101: =AT100/AS100-1 | AZ101: =AZ100/AV100-1 | BA101: =BA100/AW100-1 | BB101: =BB100/AX100-1 | BD101: =BD100/AZ100-1 | BE101: =BE100/BA100-1 | BF101: =BF100/BB100-1 | BH101: =BH100/BD100-1 | BI101: =BI100/BE100-1 | BJ101: =BJ100/BF100-1 | BL101: =BL100/BH100-1 | BM101: =BM100/BI100-1 | BN101: =BN100/BJ100-1 | BP101: =BP100/BL100-1 | BQ101: =BQ100/BM100-1 | BR101: =BR100/BN100-1 | BT101: =BT100/BP100-1 | BU101: =BU100/BQ100-1 | BV101: =BV100/BR100-1 | BX101: =BX100/BT100-1 | BY101: =BY100/BU100-1 | BZ101: =BZ100/BV100-1 | CB101: =CB100/BX100-1 | CC101: =CC100/BY100-1 | CD101: =CD100/BZ100-1 | CF101: =CF100/CB100-1 | CG101: =CG100/CC100-1 | CH101: =CH100/CD100-1 | CJ101: =CJ100/CF100-1 | CK101: =CK100/CG100-1 | CL101: =V101 | CN101: =CN100/CJ100-1 | CO101: =CO100/CK100-1 | CP101: =W101 | CR101: =CR100/CN100-1 | CT101: =CT100/CO100-1 | CU101: =X101 | CY101: =Y101 | DA101: =DA100/CW100-1 | DB101: =DB100/CX100-1 | DC101: =Z101 | DE101: =DE100/DA100-1 | DF101: =DF100/DB100-1 | DG101: =AA101 | DI101: =DI100/DE100-1 | DJ101: =DJ100/DF100-1 | DK101: =AB101 | DM101: =DM100/DI100-1 | DN101: =DN100/DJ100-1 | DO101: =AC101 | DQ101: =DQ100/DM100-1 | DR101: =DR100/DN100-1 | DS101: =AG101 | DU101: =DU100/DQ100-1 | DV101: =DV100/DR100-1 | DW101: =AE101 | DY101: =DY100/DU100-1 | DZ101: =DZ100/DV100-1 | EA101: =AF101 | EC101: =EC100/DY100-1 | ED101: =ED100/DZ100-1 | EE101: =AG101 | EG101: =EG100/EC100-1 | EH101: =EH100/ED100-1 | EI101: =AH101 | EK101: =EK100/EG100-1 | EL101: =EL100/EH100-1 | EM101: =AI101 | EO101: =EO100/EK100-1 | EP101: =EP100/EL100-1 | EQ101: =AJ101 | ES101: =ES100/EO100-1 | ET101: =ET100/EP100-1 | EU101: =AK101 | EW101: =EW100/ES100-1 | EX101: =EX100/ET100-1 | EY101: =AL101 | FA101: =FA100/EW100-1 | FB101: =FB100/EX100-1 | FC101: =AM101 | FE101: =FE100/FA100-1 | FF101: =FF100/FB100-1 | FG101: =AN101 | FI101: =FI100/FE100-1 | FJ101: =FJ100/FF100-1 | FK101: =AO101 | FM101: =FM100/FI100-1 | FN101: =FN100/FJ100-1 | FO101: =AP101
B102: Unit costs | C102: =C131/C4 | D102: =D131/D4 | E102: =E131/E4 | F102: =F131/F4 | G102: =G131/G4 | H102: =H131/H4 | I102: =I131/I4 | J102: =J131/J4 | ... AT102: =AT131/AT4 | AV102: =AV131/AV4 | AW102: =AW131/AW4 | AX102: =AX131/AX4 | AZ102: =AZ131/AZ4 | BA102: =BA131/BA4 | BB102: =BB131/BB4 | BD102: =BD131/BD4 | BE102: =BE131/BE4 | BF102: =BF131/BF4 | BH102: =BH131/BH4 | BI102: =BI131/BI4 | BJ102: =BJ131/BJ4 | BL102: =BL131/BL4 | BM102: =BM131/BM4 | BN102: =BN131/BN4 | BP102: =BP131/BP4 | BQ102: =BQ131/BQ4 | BR102: =BR131/BR4 | BT102: =BT131/BT4 | BU102: =BU131/BU4 | BV102: =BV131/BV4 | BX102: =BX131/BX4 | BY102: =BY131/BY4 | BZ102: =BZ131/BZ4 | CB102: =CB131/CB4 | CC102: =CC131/CC4 | CD102: =CD131/CD4 | CF102: =CF131/CF4 | CG102: =CG131/CG4 | CH102: =CH131/CH4 | CJ102: =CJ131/CJ4 | CK102: =CK131/CK4 | CL102: =V102 | CN102: =CN131/CN4 | CO102: =CO131/CO4 | CP102: =W102 | CR102: =CR131/CR4 | CT102: =CT131/CT4 | CU102: =X102 | CW102: =CW131/CW4 | CX102: =CX131/CX4 | CY102: =Y102 | DA102: =DA131/DA4 | DB102: =DB131/DB4 | DC102: =Z102 | DE102: =DE131/DE4 | DF102: =DF131/DF4 | DG102: =AA102 | DI102: =DI131/DI4 | DJ102: =DJ131/DJ4 | DK102: =AB102 | DM102: =DM131/DM4 | DN102: =DN131/DN4 | DO102: =AC102 | DQ102: =DQ131/DQ4 | DR102: =DR131/DR4 | DS102: =AG102 | DU102: =DU131/DU4 | DV102: =DV131/DV4 | DW102: =AE102 | DY102: =DY131/DY4 | DZ102: =DZ131/DZ4 | EA102: =AF102 | EC102: =EC131/EC4 | ED102: =ED131/ED4 | EE102: =AG102 | EG102: =EG131/EG4 | EH102: =EH131/EH4 | EI102: =AH102 | EK102: =EK131/EK4 | EL102: =EL131/EL4 | EM102: =AI102 | EO102: =EO131/EO4 | EP102: =EP131/EP4 | EQ102: =AJ102 | ES102: =ES131/ES4 | ET102: =ET131/ET4 | EU102: =AK102 | EW102: =EW131/EW4 | EX102: =EX131/EX4 | EY102: =AL102 | FA102: =FA131/FA4 | FB102: =FB131/FB4 | FC102: =AM102 | FE102: =FE131/FE4 | FF102: =FF131/FF4 | FG102: =AN102 | FI102: =FI131/FI4 | FJ102: =FJ131/FJ4 | FK102: 0 | FM102: =FM131/FM4 | FN102: =FN131/FN4 | FO102: 0
B103: YoY % | D103: =D102/C102-1 | E103: =E102/D102-1 | F103: =F102/E102-1 | G103: =G102/F102-1 | H103: =H102/G102-1 | I103: =I102/H102-1 | J103: =J102/I102-1 | K103: =K102/J102-1 | ... AT103: =AT102/AS102-1 | AZ103: =AZ102/AV102-1 | BA103: =BA102/AW102-1 | BB103: =BB102/AX102-1 | BD103: =BD102/AZ102-1 | BE103: =BE102/BA102-1 | BF103: =BF102/BB102-1 | BH103: =BH102/BD102-1 | BI103: =BI102/BE102-1 | BJ103: =BJ102/BF102-1 | BL103: =BL102/BH102-1 | BM103: =BM102/BI102-1 | BN103: =BN102/BJ102-1 | BP103: =BP102/BL102-1 | BQ103: =BQ102/BM102-1 | BR103: =BR102/BN102-1 | BT103: =BT102/BP102-1 | BU103: =BU102/BQ102-1 | BV103: =BV102/BR102-1 | BX103: =BX102/BT102-1 | BY103: =BY102/BU102-1 | BZ103: =BZ102/BV102-1 | CB103: =CB102/BX102-1 | CC103: =CC102/BY102-1 | CD103: =CD102/BZ102-1 | CF103: =CF102/CB102-1 | CG103: =CG102/CC102-1 | CH103: =CH102/CD102-1 | CJ103: =CJ102/CF102-1 | CK103: =CK102/CG102-1 | CL103: =V103 | CN103: =CN102/CJ102-1 | CO103: =CO102/CK102-1 | CP103: =W103 | CR103: =CR102/CN102-1 | CT103: =CT102/CO102-1 | CU103: =X103 | CY103: =Y103 | DA103: =DA102/CW102-1 | DB103: =DB102/CX102-1 | DC103: =Z103 | DE103: =DE102/DA102-1 | DF103: =DF102/DB102-1 | DG103: =AA103 | DI103: =DI102/DE102-1 | DJ103: =DJ102/DF102-1 | DK103: =AB103 | DM103: =DM102/DI102-1 | DN103: =DN102/DJ102-1 | DO103: =AC103 | DQ103: =DQ102/DM102-1 | DR103: =DR102/DN102-1 | DS103: =AG103 | DU103: =DU102/DQ102-1 | DV103: =DV102/DR102-1 | DW103: =AE103 | DY103: =DY102/DU102-1 | DZ103: =DZ102/DV102-1 | EA103: =AF103 | EC103: =EC102/DY102-1 | ED103: =ED102/DZ102-1 | EE103: =AG103 | EG103: =EG102/EC102-1 | EH103: =EH102/ED102-1 | EI103: =AH103 | EK103: =EK102/EG102-1 | EL103: =EL102/EH102-1 | EM103: =AI103 | EO103: =EO102/EK102-1 | EP103: =EP102/EL102-1 | EQ103: =AJ103 | ES103: =ES102/EO102-1 | ET103: =ET102/EP102-1 | EU103: =AK103 | EW103: =EW102/ES102-1 | EX103: =EX102/ET102-1 | EY103: =AL103 | FA103: =FA102/EW102-1 | FB103: =FB102/EX102-1 | FC103: =AM103 | FE103: =FE102/FA102-1 | FF103: =FF102/FB102-1 | FG103: =AN103 | FI103: =FI102/FE102-1 | FJ103: =FJ102/FF102-1 | FK103: =AO103 | FM103: =FM102/FI102-1 | FN103: =FN102/FJ102-1 | FO103: =AP103
B104: Airline unit costs (per ATK) | H104: =(H131-H127)/H4 | I104: =(I131-I127)/I4 | J104: =(J131-J127)/J4 | K104: =(K131-K127)/K4 | L104: =(L131-L127)/L4 | M104: =(M131-M127)/M4 | N104: =(N131-N127)/N4 | O104: =(O131-O127)/O4 | ... AT104: =(AT131-AT127)/AT4 | AV104: =(AV131-AV127)/AV4 | AW104: =(AW131-AW127)/AW4 | AX104: =(AX131-AX127)/AX4 | AZ104: =(AZ131-AZ127)/AZ4 | BA104: =(BA131-BA127)/BA4 | BB104: =(BB131-BB127)/BB4 | BD104: =(BD131-BD127)/BD4 | BE104: =(BE131-BE127)/BE4 | BF104: =(BF131-BF127)/BF4 | BH104: =(BH131-BH127)/BH4 | BI104: =(BI131-BI127)/BI4 | BJ104: =(BJ131-BJ127)/BJ4 | BL104: =(BL131-BL127)/BL4 | BM104: =(BM131-BM127)/BM4 | BN104: =(BN131-BN127)/BN4 | BP104: =(BP131-BP127)/BP4 | BQ104: =(BQ131-BQ127)/BQ4 | BR104: =(BR131-BR127)/BR4 | BT104: =(BT131-BT127)/BT4 | BU104: =(BU131-BU127)/BU4 | BV104: =(BV131-BV127)/BV4 | BX104: =(BX131-BX127)/BX4 | BY104: =(BY131-BY127)/BY4 | BZ104: =(BZ131-BZ127)/BZ4 | CB104: =(CB131-CB127)/CB4 | CC104: =(CC131-CC127)/CC4 | CD104: =(CD131-CD127)/CD4 | CF104: =(CF131-CF127)/CF4 | CG104: =(CG131-CG127)/CG4 | CH104: =(CH131-CH127)/CH4 | CJ104: =(CJ131-CJ127)/CJ4 | CK104: =(CK131-CK127)/CK4 | CL104: =V104 | CN104: =(CN131-CN127)/CN4 | CO104: =(CO131-CO127)/CO4 | CP104: =W104 | CR104: =(CR131-CR127)/CR4 | CT104: =(CT131-CT127)/CT4 | CU104: =X104 | CW104: =(CW131-CW127)/CW4 | CX104: =(CX131-CX127)/CX4 | CY104: =Y104 | DA104: =(DA131-DA127)/DA4 | DB104: =(DB131-DB127)/DB4 | DC104: =Z104 | DE104: =(DE131-DE127)/DE4 | DF104: =(DF131-DF127)/DF4 | DG104: =AA104 | DI104: =(DI131-DI127)/DI4 | DJ104: =(DJ131-DJ127)/DJ4 | DK104: =AB104 | DM104: =(DM131-DM127)/DM4 | DN104: =(DN131-DN127)/DN4 | DO104: =AC104 | DQ104: =(DQ131-DQ127)/DQ4 | DR104: =(DR131-DR127)/DR4 | DS104: =AG104 | DU104: =(DU131-DU127)/DU4 | DV104: =(DV131-DV127)/DV4 | DW104: =AE104 | DY104: =(DY131-DY127)/DY4 | DZ104: =(DZ131-DZ127)/DZ4 | EA104: =AF104 | EC104: =(EC131-EC127)/EC4 | ED104: =(ED131-ED127)/ED4 | EE104: =AG104 | EG104: =(EG131-EG127)/EG4 | EH104: =(EH131-EH127)/EH4 | EI104: =AH104 | EK104: =(EK131-EK127)/EK4 | EL104: =(EL131-EL127)/EL4 | EM104: =AI104 | EO104: =(EO131-EO127)/EO4 | EP104: =(EP131-EP127)/EP4 | EQ104: =AJ104 | ES104: =(ES131-ES127)/ES4 | ET104: =(ET131-ET127)/ET4 | EU104: =AK104 | EW104: =(EW131-EW127)/EW4 | EX104: =(EX131-EX127)/EX4 | EY104: =AL104 | FA104: =(FA131-FA127)/FA4 | FB104: =(FB131-FB127)/FB4 | FC104: =AM104 | FE104: =(FE131-FE127)/FE4 | FF104: =(FF131-FF127)/FF4 | FG104: =AN104 | FI104: =(FI131-FI127)/FI4 | FJ104: =(FJ131-FJ127)/FJ4 | FK104: =AO104 | FM104: =(FM131-FM127)/FM4 | FN104: =(FN131-FN127)/FN4 | FO104: =AP104
B105: YoY % | I105: =I104/H104-1 | J105: =J104/I104-1 | K105: =K104/J104-1 | L105: =L104/K104-1 | M105: =M104/L104-1 | N105: =N104/M104-1 | O105: =O104/N104-1 | P105: =P104/O104-1 | ... AT105: =AT104/AS104-1 | AZ105: =AZ104/AV104-1 | BA105: =BA104/AW104-1 | BB105: =BB104/AX104-1 | BD105: =BD104/AZ104-1 | BE105: =BE104/BA104-1 | BF105: =BF104/BB104-1 | BH105: =BH104/BD104-1 | BI105: =BI104/BE104-1 | BJ105: =BJ104/BF104-1 | BL105: =BL104/BH104-1 | BM105: =BM104/BI104-1 | BN105: =BN104/BJ104-1 | BP105: =BP104/BL104-1 | BQ105: =BQ104/BM104-1 | BR105: =BR104/BN104-1 | BT105: =BT104/BP104-1 | BU105: =BU104/BQ104-1 | BV105: =BV104/BR104-1 | BX105: =BX104/BT104-1 | BY105: =BY104/BU104-1 | BZ105: =BZ104/BV104-1 | CB105: =CB104/BX104-1 | CC105: =CC104/BY104-1 | CD105: =CD104/BZ104-1 | CF105: =CF104/CB104-1 | CG105: =CG104/CC104-1 | CH105: =CH104/CD104-1 | CJ105: =CJ104/CF104-1 | CK105: =CK104/CG104-1 | CL105: =V105 | CN105: =CN104/CJ104-1 | CO105: =CO104/CK104-1 | CP105: =W105 | CR105: =CR104/CN104-1 | CT105: =CT104/CO104-1 | CU105: =X105 | CY105: =Y105 | DA105: =DA104/CW104-1 | DB105: =DB104/CX104-1 | DC105: =Z105 | DE105: =DE104/DA104-1 | DF105: =DF104/DB104-1 | DG105: =AA105 | DI105: =DI104/DE104-1 | DJ105: =DJ104/DF104-1 | DK105: =AB105 | DM105: =DM104/DI104-1 | DN105: =DN104/DJ104-1 | DO105: =AC105 | DQ105: =DQ104/DM104-1 | DR105: =DR104/DN104-1 | DS105: =AG105 | DU105: =DU104/DQ104-1 | DV105: =DV104/DR104-1 | DW105: =AE105 | DY105: =DY104/DU104-1 | DZ105: =DZ104/DV104-1 | EA105: =AF105 | EC105: =EC104/DY104-1 | ED105: =ED104/DZ104-1 | EE105: =AG105 | EG105: =EG104/EC104-1 | EH105: =EH104/ED104-1 | EI105: =AH105 | EK105: =EK104/EG104-1 | EL105: =EL104/EH104-1 | EM105: =AI105 | EO105: =EO104/EK104-1 | EP105: =EP104/EL104-1 | EQ105: =AJ105 | ES105: =ES104/EO104-1 | ET105: =ET104/EP104-1 | EU105: =AK105 | EW105: =EW104/ES104-1 | EX105: =EX104/ET104-1 | EY105: =AL105 | FA105: =FA104/EW104-1 | FB105: =FB104/EX104-1 | FC105: =AM105 | FE105: =FE104/FA104-1 | FF105: =FF104/FB104-1 | FG105: =AN105 | FI105: =FI104/FE104-1 | FJ105: =FJ104/FF104-1 | FK105: =AO105 | FM105: =FM104/FI104-1 | FN105: =FN104/FJ104-1 | FO105: =AP105
B106: Unit revenues | C106: =(C112+C114)/C4 | D106: =(D112+D114)/D4 | E106: =(E112+E114)/E4 | F106: =(F112+F114)/F4 | G106: =(G112+G114)/G4 | H106: =(H112+H114)/H4 | I106: =(I112+I114)/I4 | J106: =(J112+J114)/J4 | ... AT106: =(AT112+AT114)/AT4 | AV106: =(AV112+AV114)/AV4 | AW106: =(AW112+AW114)/AW4 | AX106: =(AX112+AX114)/AX4 | AZ106: =(AZ112+AZ114)/AZ4 | BA106: =(BA112+BA114)/BA4 | BB106: =(BB112+BB114)/BB4 | BD106: =(BD112+BD114)/BD4 | BE106: =(BE112+BE114)/BE4 | BF106: =(BF112+BF114)/BF4 | BH106: =(BH112+BH114)/BH4 | BI106: =(BI112+BI114)/BI4 | BJ106: =(BJ112+BJ114)/BJ4 | BL106: =(BL112+BL114)/BL4 | BM106: =(BM112+BM114)/BM4 | BN106: =(BN112+BN114)/BN4 | BP106: =(BP112+BP114)/BP4 | BQ106: =(BQ112+BQ114)/BQ4 | BR106: =(BR112+BR114)/BR4 | BT106: =(BT112+BT114)/BT4 | BU106: =(BU112+BU114)/BU4 | BV106: =(BV112+BV114)/BV4 | BX106: =(BX112+BX114)/BX4 | BY106: =(BY112+BY114)/BY4 | BZ106: =(BZ112+BZ114)/BZ4 | CB106: =(CB112+CB114)/CB4 | CC106: =(CC112+CC114)/CC4 | CD106: =(CD112+CD114)/CD4 | CF106: =(CF112+CF114)/CF4 | CG106: =(CG112+CG114)/CG4 | CH106: =(CH112+CH114)/CH4 | CJ106: =(CJ112+CJ114)/CJ4 | CK106: =(CK112+CK114)/CK4 | CL106: =V106 | CN106: =(CN112+CN114)/CN4 | CO106: =(CO112+CO114)/CO4 | CP106: =W106 | CR106: =(CR112+CR114)/CR4 | CT106: =(CT112+CT114)/CT4 | CU106: =X106 | CW106: =(CW112+CW114)/CW4 | CX106: =(CX112+CX114)/CX4 | CY106: =Y106 | DA106: =(DA112+DA114)/DA4 | DB106: =(DB112+DB114)/DB4 | DC106: =Z106 | DE106: =(DE112+DE114)/DE4 | DF106: =(DF112+DF114)/DF4 | DG106: =AA106 | DI106: =(DI112+DI114)/DI4 | DJ106: =(DJ112+DJ114)/DJ4 | DK106: =AB106 | DM106: =(DM112+DM114)/DM4 | DN106: =(DN112+DN114)/DN4 | DO106: =AC106 | DQ106: =(DQ112+DQ114)/DQ4 | DR106: =(DR112+DR114)/DR4 | DS106: =AG106 | DU106: =(DU112+DU114)/DU4 | DV106: =(DV112+DV114)/DV4 | DW106: =AE106 | DY106: =(DY112+DY114)/DY4 | DZ106: =(DZ112+DZ114)/DZ4 | EA106: =AF106 | EC106: =(EC112+EC114)/EC4 | ED106: =(ED112+ED114)/ED4 | EE106: =AG106 | EG106: =(EG112+EG114)/EG4 | EH106: =(EH112+EH114)/EH4 | EI106: =AH106 | EK106: =(EK112+EK114)/EK4 | EL106: =(EL112+EL114)/EL4 | EM106: =AI106 | EO106: =(EO112+EO114)/EO4 | EP106: =(EP112+EP114)/EP4 | EQ106: =AJ106 | ES106: =(ES112+ES114)/ES4 | ET106: =(ET112+ET114)/ET4 | EU106: =AK106 | EW106: =(EW112+EW114)/EW4 | EX106: =(EX112+EX114)/EX4 | EY106: =AL106 | FA106: =(FA112+FA114)/FA4 | FB106: =(FB112+FB114)/FB4 | FC106: =AM106 | FE106: =(FE112+FE114)/FE4 | FF106: =(FF112+FF114)/FF4 | FG106: =AN106 | FI106: =(FI112+FI114)/FI4 | FJ106: =(FJ112+FJ114)/FJ4 | FK106: =AO106 | FM106: =(FM112+FM114)/FM4 | FN106: =(FN112+FN114)/FN4 | FO106: =AP106
B107: YoY % | D107: =D106/C106-1 | E107: =E106/D106-1 | F107: =F106/E106-1 | G107: =G106/F106-1 | H107: =H106/G106-1 | I107: =I106/H106-1 | J107: =J106/I106-1 | K107: =K106/J106-1 | ... AT107: =AT106/AS106-1 | AZ107: =AZ106/AV106-1 | BA107: =BA106/AW106-1 | BB107: =BB106/AX106-1 | BD107: =BD106/AZ106-1 | BE107: =BE106/BA106-1 | BF107: =BF106/BB106-1 | BH107: =BH106/BD106-1 | BI107: =BI106/BE106-1 | BJ107: =BJ106/BF106-1 | BL107: =BL106/BH106-1 | BM107: =BM106/BI106-1 | BN107: =BN106/BJ106-1 | BP107: =BP106/BL106-1 | BQ107: =BQ106/BM106-1 | BR107: =BR106/BN106-1 | BT107: =BT106/BP106-1 | BU107: =BU106/BQ106-1 | BV107: =BV106/BR106-1 | BX107: =BX106/BT106-1 | BY107: =BY106/BU106-1 | BZ107: =BZ106/BV106-1 | CB107: =CB106/BX106-1 | CC107: =CC106/BY106-1 | CD107: =CD106/BZ106-1 | CF107: =CF106/CB106-1 | CG107: =CG106/CC106-1 | CH107: =CH106/CD106-1 | CJ107: =CJ106/CF106-1 | CK107: =CK106/CG106-1 | CL107: =V107 | CN107: =CN106/CJ106-1 | CO107: =CO106/CK106-1 | CP107: =W107 | CR107: =CR106/CN106-1 | CT107: =CT106/CO106-1 | CU107: =X107 | CY107: =Y107 | DA107: =DA106/CW106-1 | DB107: =DB106/CX106-1 | DC107: =Z107 | DE107: =DE106/DA106-1 | DF107: =DF106/DB106-1 | DG107: =AA107 | DI107: =DI106/DE106-1 | DJ107: =DJ106/DF106-1 | DK107: =AB107 | DM107: =DM106/DI106-1 | DN107: =DN106/DJ106-1 | DO107: =AC107 | DQ107: =DQ106/DM106-1 | DR107: =DR106/DN106-1 | DS107: =AG107 | DU107: =DU106/DQ106-1 | DV107: =DV106/DR106-1 | DW107: =AE107 | DY107: =DY106/DU106-1 | DZ107: =DZ106/DV106-1 | EA107: =AF107 | EC107: =EC106/DY106-1 | ED107: =ED106/DZ106-1 | EE107: =AG107 | EG107: =EG106/EC106-1 | EH107: =EH106/ED106-1 | EI107: =AH107 | EK107: =EK106/EG106-1 | EL107: =EL106/EH106-1 | EM107: =AI107 | EO107: =EO106/EK106-1 | EP107: =EP106/EL106-1 | EQ107: =AJ107 | ES107: =ES106/EO106-1 | ET107: =ET106/EP106-1 | EU107: =AK107 | EW107: =EW106/ES106-1 | EX107: =EX106/ET106-1 | EY107: =AL107 | FA107: =FA106/EW106-1 | FB107: =FB106/EX106-1 | FC107: =AM107 | FE107: =FE106/FA106-1 | FF107: =FF106/FB106-1 | FG107: =AN107 | FI107: =FI106/FE106-1 | FJ107: =FJ106/FF106-1 | FK107: =AO107 | FM107: =FM106/FI106-1 | FN107: =FN106/FJ106-1 | FO107: =AP107
B110: Profit & loss (HK$m)
...

Sheet Fleet
B1: Fleet Profile
B2: Source: Company data
B4: Total Hardcoded | C4: =72+13 | D4: =62+15+12 | E4: =14+64+11 | F4: =75+9+19 | G4: =79+2+24 | H4: =85+4+26 | I4: =89+5+30 | J4: =96+6+34 | K4: =102+37+8 | L4: 159 | M4: 162 | N4: 163 | O4: 167 | P4: 175 | Q4: 187 | R4: 192 | S4: 200 | T4: 201 | U4: 202 | V4: 208 | W4: 212 | X4: 236 | Y4: 239 | Z4: 234 | AA4: 222 | AB4: 230 | AC4: 236 | AF4: 8 | AG4: 21 | AH4: 76 | AI4: 105
B5: Total Check | C5: =C4-C120 | D5: =D4-D120 | E5: =E4-E120 | F5: =F4-F120 | G5: =G4-G120 | H5: =H4-H120 | I5: =I4-I120 | J5: =J4-J120 | ... AC5: =AC4-AC120 | AF5: =AF4-AF120 | AG5: =AG4-AG120 | AH5: =AH4-AH120 | AI5: =AI4-AI120
B7: As of | C7: =EOMONTH(D7,-12) | D7: =EOMONTH(E7,-12) | E7: =EOMONTH(F7,-12) | F7: =EOMONTH(G7,-12) | G7: =EOMONTH(H7,-12) | H7: =EOMONTH(I7,-12) | I7: =EOMONTH(J7,-12) | J7: =EOMONTH(K7,-12) | ... Y7: =EOMONTH(Z7,-12) | Z7: 44561 | AA7: 44926 | AB7: =EOMONTH(AA7,12) | AC7: =EOMONTH(AB7,12) | AD7: =EOMONTH(AC7,12) | AF7: Orderbook as of 30 June 2026
B8: Year | C8: =YEAR(C7) | D8: =YEAR(D7) | E8: =YEAR(E7) | F8: =YEAR(F7) | G8: =YEAR(G7) | H8: =YEAR(H7) | I8: =YEAR(I7) | J8: =YEAR(J7) | ... AD8: =YEAR(AD7) | AF8: 2026E | AG8: 2027E | AH8: 2028 and beyond | AI8: Orders
B9: Cathay Pacific
A10: N | B10: A320-200 | C10: =SUM(C11:C12) | D10: =SUM(D11:D12) | E10: =SUM(E11:E12) | F10: =SUM(F11:F12) | G10: =SUM(G11:G12) | H10: =SUM(H11:H12) | I10: =SUM(I11:I12) | J10: =SUM(J11:J12) | ... AC10: =SUM(AC11:AC12) | AF10: 0 | AG10: 0 | AH10: 0 | AI10: =SUM(AF10:AH10)
B11: Owned | C11: =0 | D11: =0 | E11: =0 | F11: =0 | G11: =0 | H11: 0 | I11: 2 | J11: 3 | K11: 3 | L11: 3 | M11: 4 | N11: 4 | O11: 5 | P11: 5 | Q11: 5 | R11: 5 | S11: 5 | T11: 5 | U11: 5 | V11: 5 | W11: 5 | X11: 5 | Y11: 5 | Z11: 5 | AA11: 4 | AB11: 4 | AC11: 5
B12: Leased | C12: =7 | D12: =5 | E12: =6 | F12: =7 | G12: =8 | H12: 8 | I12: 8 | J12: 8 | K12: 7 | L12: 7 | M12: 6 | N12: 5 | O12: 6 | P12: 6 | Q12: 10 | R12: 10 | S12: 10 | T12: 10 | U12: 10 | V12: 10 | W12: 10 | X12: 10 | Y12: 6 | Z12: 2 | AA12: 0 | AB12: 0 | AC12: 0
A13: N | B13: A321-200 | C13: =SUM(C14:C15) | D13: =SUM(D14:D15) | E13: =SUM(E14:E15) | F13: =SUM(F14:F15) | G13: =SUM(G14:G15) | H13: =SUM(H14:H15) | I13: =SUM(I14:I15) | J13: =SUM(J14:J15) | ... AC13: =SUM(AC14:AC15) | AF13: 0 | AG13: 0 | AH13: 0 | AI13: =SUM(AF13:AH13)
B14: Owned | C14: 0 | D14: =0 | E14: =0 | F14: =0 | G14: =0 | H14: 2 | I14: 2 | J14: 2 | K14: 2 | L14: 2 | M14: 2 | N14: 2 | O14: 2 | P14: 2 | Q14: 2 | R14: 2 | S14: 2 | T14: 2 | U14: 2 | V14: 2 | W14: 2 | X14: 2 | Y14: 2 | Z14: 2 | AA14: 2 | AB14: 2 | AC14: 0
B15: Leased | C15: 0 | D15: =2 | E15: =3 | F15: =3 | G15: =4 | H15: 4 | I15: 4 | J15: 4 | K15: 4 | L15: 4 | M15: 4 | N15: 4 | O15: 4 | P15: 4 | Q15: 4 | R15: 4 | S15: 6 | T15: 6 | U15: 6 | V15: 6 | W15: 6 | X15: 6 | Y15: 5 | Z15: 3 | AA15: 1 | AB15: 0 | AC15: 0
A16: N | B16: A321-200neo | C16: =SUM(C17:C18) | D16: =SUM(D17:D18) | E16: =SUM(E17:E18) | F16: =SUM(F17:F18) | G16: =SUM(G17:G18) | H16: =SUM(H17:H18) | I16: =SUM(I17:I18) | J16: =SUM(J17:J18) | ... AC16: =SUM(AC17:AC18) | AF16: 3 | AG16: 2 | AH16: 3 | AI16: =SUM(AF16:AH16)
B17: Owned | C17: 0 | D17: 0 | E17: 0 | F17: 0 | G17: 0 | H17: 0 | I17: 0 | J17: 0 | K17: 0 | L17: 0 | M17: 0 | N17: 0 | O17: 0 | P17: 0 | Q17: 0 | R17: 0 | S17: 0 | T17: 0 | U17: 0 | V17: 0 | W17: 0 | X17: 0 | Y17: 0 | Z17: 0 | AA17: 0 | AB17: 0 | AC17: 0
B18: Leased | C18: 0 | D18: 0 | E18: 0 | F18: 0 | G18: 0 | H18: 0 | I18: 0 | J18: 0 | K18: 0 | L18: 0 | M18: 0 | N18: 0 | O18: 0 | P18: 0 | Q18: 0 | R18: 0 | S18: 0 | T18: 0 | U18: 0 | V18: 0 | W18: 0 | X18: 0 | Y18: 2 | Z18: 5 | AA18: 7 | AB18: 8 | AC18: =5+6
A19: W | B19: A330-300 | C19: =SUM(C20:C21) | D19: =SUM(D20:D21) | E19: =SUM(E20:E21) | F19: =SUM(F20:F21) | G19: =SUM(G20:G21) | H19: =SUM(H20:H21) | I19: =SUM(I20:I21) | J19: =SUM(J20:J21) | ... AC19: =SUM(AC20:AC21) | AF19: 0 | AG19: 0 | AH19: 0 | AI19: =SUM(AF19:AH19)
B20: Owned | C20: =0 | D20: =0 | E20: =0 | F20: =0+2 | G20: =1 | H20: 2 | I20: =2 | J20: =1+2 | K20: =6+2 | L20: =8+3 | M20: =9+4 | N20: =9+4 | O20: =11+4 | P20: =8+4 | Q20: =13+4 | R20: =14+5 | S20: =19+10 | T20: =23+10 | U20: =23+10 | V20: =20+10 | W20: =20+18 | X20: =17+21 | Y20: 37 | Z20: 37 | AA20: 31 | AB20: 37 | AC20: 39
B21: Leased | C21: =6+12 | D21: =5+12 | E21: =5+12 | F21: =7+18 | G21: =8+20 | H21: =7+23 | I21: =8+23 | J21: =25+11 | K21: =18+3+14 | L21: =21+13 | M21: =23+12 | N21: =23+10 | O21: =21+10 | P21: =25+11 | Q21: =16+8+13 | R21: =21+15 | S21: =21+8 | T21: =19+9 | U21: =18+10 | V21: =17+14 | W21: =13+7 | X21: =12+4 | Y21: 14 | Z21: 14 | AA21: 12 | AB21: 6 | AC21: 4
A22: W | B22: A330-900 | C22: =SUM(C23:C24) | D22: =SUM(D23:D24) | E22: =SUM(E23:E24) | F22: =SUM(F23:F24) | G22: =SUM(G23:G24) | H22: =SUM(H23:H24) | I22: =SUM(I23:I24) | J22: =SUM(J23:J24) | ... AC22: =SUM(AC23:AC24) | AF22: 0 | AG22: 0 | AH22: 30 | AI22: =SUM(AF22:AH22)
B23: Owned | C23: 0 | D23: 0 | E23: 0 | F23: 0 | G23: 0 | H23: 0 | I23: 0 | J23: 0 | K23: 0 | L23: 0 | M23: 0 | N23: 0 | O23: 0 | P23: 0 | Q23: 0 | R23: 0 | S23: 0 | T23: 0 | U23: 0 | V23: 0 | W23: 0 | X23: 0 | Y23: 0 | Z23: 0 | AA23: 0 | AB23: 0 | AC23: 0
B24: Leased | C24: 0 | D24: 0 | E24: 0 | F24: 0 | G24: 0 | H24: 0 | I24: 0 | J24: 0 | K24: 0 | L24: 0 | M24: 0 | N24: 0 | O24: 0 | P24: 0 | Q24: 0 | R24: 0 | S24: 0 | T24: 0 | U24: 0 | V24: 0 | W24: 0 | X24: 0 | Y24: 0 | Z24: 0 | AA24: 0 | AB24: 0 | AC24: 0
A25: W | B25: A340-300 | C25: =SUM(C26:C27) | D25: =SUM(D26:D27) | E25: =SUM(E26:E27) | F25: =SUM(F26:F27) | G25: =SUM(G26:G27) | H25: =SUM(H26:H27) | I25: =SUM(I26:I27) | J25: =SUM(J26:J27) | ... AC25: =SUM(AC26:AC27) | AF25: 0 | AG25: 0 | AH25: 0 | AI25: =SUM(AF25:AH25)
B26: Owned | C26: 0 | D26: 0 | E26: 0 | F26: 0 | G26: 0 | H26: 0 | I26: 0 | J26: 0 | K26: 1 | L26: 1 | M26: 5 | N26: 6 | O26: 6 | P26: 6 | Q26: 6 | R26: 6 | S26: 8 | T26: 5 | U26: 4 | V26: 0 | W26: 0 | X26: 0 | Y26: 0 | Z26: 0 | AA26: 0 | AB26: 0 | AC26: 0
B27: Leased | C27: 11 | D27: 14 | E27: 14 | F27: 15 | G27: 15 | H27: 15 | I27: 15 | J27: 15 | K27: 14 | L27: 14 | M27: 10 | N27: 9 | O27: 9 | P27: 7 | Q27: 5 | R27: 5 | S27: 3 | T27: 2 | U27: 0 | V27: 0 | W27: 0 | X27: 0 | Y27: 0 | Z27: 0 | AA27: 0 | AB27: 0 | AC27: 0
A28: W | B28: A340-600 | C28: =SUM(C29:C30) | D28: =SUM(D29:D30) | E28: =SUM(E29:E30) | F28: =SUM(F29:F30) | G28: =SUM(G29:G30) | H28: =SUM(H29:H30) | I28: =SUM(I29:I30) | J28: =SUM(J29:J30) | ... AC28: =SUM(AC29:AC30) | AF28: 0 | AG28: 0 | AH28: 0 | AI28: =SUM(AF28:AH28)
B29: Owned | C29: 0 | D29: 0 | E29: 0 | F29: 0 | G29: 0 | H29: 0 | I29: 0 | J29: 0 | K29: 0 | L29: 0 | M29: 0 | N29: 0 | O29: 0 | P29: 0 | Q29: 0 | R29: 0 | S29: 0 | T29: 0 | U29: 0 | V29: 0 | W29: 0 | X29: 0 | Y29: 0 | Z29: 0 | AA29: 0 | AB29: 0 | AC29: 0
B30: Leased | C30: 0 | D30: 0 | E30: 0 | F30: 0 | G30: 2 | H30: 3 | I30: 3 | J30: 3 | K30: 3 | L30: 3 | M30: 0 | N30: 0 | O30: 0 | P30: 0 | Q30: 0 | R30: 0 | S30: 0 | T30: 0 | U30: 0 | V30: 0 | W30: 0 | X30: 0 | Y30: 0 | Z30: 0 | AA30: 0 | AB30: 0 | AC30: 0
A31: W | B31: A350-900 | C31: =SUM(C32:C33) | D31: =SUM(D32:D33) | E31: =SUM(E32:E33) | F31: =SUM(F32:F33) | G31: =SUM(G32:G33) | H31: =SUM(H32:H33) | I31: =SUM(I32:I33) | J31: =SUM(J32:J33) | ... AC31: =SUM(AC32:AC33) | AF31: 0 | AG31: 0 | AH31: 0 | AI31: =SUM(AF31:AH31)
B32: Owned | C32: 0 | D32: 0 | E32: 0 | F32: 0 | G32: 0 | H32: 0 | I32: 0 | J32: 0 | K32: 0 | L32: 0 | M32: 0 | N32: 0 | O32: 0 | P32: 0 | Q32: 0 | R32: 0 | S32: 0 | T32: 0 | U32: 5 | V32: 16 | W32: 16 | X32: 18 | Y32: 19 | Z32: 19 | AA32: 19 | AB32: 20 | AC32: 20
B33: Leased | C33: 0 | D33: 0 | E33: 0 | F33: 0 | G33: 0 | H33: 0 | I33: 0 | J33: 0 | K33: 0 | L33: 0 | M33: 0 | N33: 0 | O33: 0 | P33: 0 | Q33: 0 | R33: 0 | S33: 0 | T33: 0 | U33: 5 | V33: 6 | W33: 6 | X33: 6 | Y33: 8 | Z33: 9 | AA33: 9 | AB33: 10 | AC33: 10
A34: W | B34: A350-1000 | C34: =SUM(C35:C36) | D34: =SUM(D35:D36) | E34: =SUM(E35:E36) | F34: =SUM(F35:F36) | G34: =SUM(G35:G36) | H34: =SUM(H35:H36) | I34: =SUM(I35:I36) | J34: =SUM(J35:J36) | ... AC34: =SUM(AC35:AC36) | AF34: 0 | AG34: 0 | AH34: 0 | AI34: =SUM(AF34:AH34)
B35: Owned | C35: 0 | D35: 0 | E35: 0 | F35: 0 | G35: 0 | H35: 0 | I35: 0 | J35: 0 | K35: 0 | L35: 0 | M35: 0 | N35: 0 | O35: 0 | P35: 0 | Q35: 0 | R35: 0 | S35: 0 | T35: 0 | U35: 0 | V35: 0 | W35: 6 | X35: 9 | Y35: 10 | Z35: 10 | AA35: 11 | AB35: 11 | AC35: 11
B36: Leased | C36: 0 | D36: 0 | E36: 0 | F36: 0 | G36: 0 | H36: 0 | I36: 0 | J36: 0 | K36: 0 | L36: 0 | M36: 0 | N36: 0 | O36: 0 | P36: 0 | Q36: 0 | R36: 0 | S36: 0 | T36: 0 | U36: 0 | V36: 0 | W36: 2 | X36: 3 | Y36: 3 | Z36: 5 | AA36: 7 | AB36: 7 | AC36: 7
A37: W | B37: A350-F | C37: =SUM(C38:C39) | D37: =SUM(D38:D39) | E37: =SUM(E38:E39) | F37: =SUM(F38:F39) | G37: =SUM(G38:G39) | H37: =SUM(H38:H39) | I37: =SUM(I38:I39) | J37: =SUM(J38:J39) | ... AC37: =SUM(AC38:AC39) | AF37: 0 | AG37: 0 | AH37: 8 | AI37: =SUM(AF37:AH37)
B38: Owned | C38: 0 | D38: 0 | E38: 0 | F38: 0 | G38: 0 | H38: 0 | I38: 0 | J38: 0 | K38: 0 | L38: 0 | M38: 0 | N38: 0 | O38: 0 | P38: 0 | Q38: 0 | R38: 0 | S38: 0 | T38: 0 | U38: 0 | V38: 0 | W38: 0 | X38: 0 | Y38: 0 | Z38: 0 | AA38: 0 | AB38: 0 | AC38: 0
B39: Leased | C39: 0 | D39: 0 | E39: 0 | F39: 0 | G39: 0 | H39: 0 | I39: 0 | J39: 0 | K39: 0 | L39: 0 | M39: 0 | N39: 0 | O39: 0 | P39: 0 | Q39: 0 | R39: 0 | S39: 0 | T39: 0 | U39: 0 | V39: 0 | W39: 0 | X39: 0 | Y39: 0 | Z39: 0 | AA39: 0 | AB39: 0 | AC39: 0
A40: W | B40: 747-200 | C40: =SUM(C41:C42) | D40: =SUM(D41:D42) | E40: =SUM(E41:E42) | F40: =SUM(F41:F42) | G40: =SUM(G41:G42) | H40: =SUM(H41:H42) | I40: =SUM(I41:I42) | J40: =SUM(J41:J42) | ... AC40: =SUM(AC41:AC42) | AF40: 0 | AG40: 0 | AH40: 0 | AI40: =SUM(AF40:AH40)
B41: Owned | C41: 7 | D41: 6 | E41: 2 | F41: 0 | G41: 0 | H41: 0 | I41: 0 | J41: 0 | K41: 0 | L41: 0 | M41: 0 | N41: 0 | O41: 0 | P41: 0 | Q41: 0 | R41: 0 | S41: 0 | T41: 0 | U41: 0 | V41: 0 | W41: 0 | X41: 0 | Y41: 0 | Z41: 0 | AA41: 0 | AB41: 0 | AC41: 0
B42: Leased | C42: 0 | D42: 0 | E42: 0 | F42: 0 | G42: 0 | H42: 0 | I42: 0 | J42: 0 | K42: 0 | L42: 0 | M42: 0 | N42: 0 | O42: 0 | P42: 0 | Q42: 0 | R42: 0 | S42: 0 | T42: 0 | U42: 0 | V42: 0 | W42: 0 | X42: 0 | Y42: 0 | Z42: 0 | AA42: 0 | AB42: 0 | AC42: 0
A43: W | B43: 747-300 | C43: =SUM(C44:C45) | D43: =SUM(D44:D45) | E43: =SUM(E44:E45) | F43: =SUM(F44:F45) | G43: =SUM(G44:G45) | H43: =SUM(H44:H45) | I43: =SUM(I44:I45) | J43: =SUM(J44:J45) | ... AC43: =SUM(AC44:AC45) | AF43: 0 | AG43: 0 | AH43: 0 | AI43: =SUM(AF43:AH43)
B44: Owned | C44: 1 | D44: 1 | E44: 2 | F44: 6 | G44: 0 | H44: 0 | I44: 0 | J44: 0 | K44: 0 | L44: 0 | M44: 0 | N44: 0 | O44: 0 | P44: 0 | Q44: 0 | R44: 0 | S44: 0 | T44: 0 | U44: 0 | V44: 0 | W44: 0 | X44: 0 | Y44: 0 | Z44: 0 | AA44: 0 | AB44: 0 | AC44: 0
B45: Leased | C45: 5 | D45: 5 | E45: 4 | F45: 0 | G45: 0 | H45: 0 | I45: 0 | J45: 0 | K45: 0 | L45: 0 | M45: 0 | N45: 0 | O45: 0 | P45: 0 | Q45: 0 | R45: 0 | S45: 0 | T45: 0 | U45: 0 | V45: 0 | W45: 0 | X45: 0 | Y45: 0 | Z45: 0 | AA45: 0 | AB45: 0 | AC45: 0
A46: W | B46: 747-400 | C46: =SUM(C47:C48) | D46: =SUM(D47:D48) | E46: =SUM(E47:E48) | F46: =SUM(F47:F48) | G46: =SUM(G47:G48) | H46: =SUM(H47:H48) | I46: =SUM(I47:I48) | J46: =SUM(J47:J48) | ... AC46: =SUM(AC47:AC48) | AF46: 0 | AG46: 0 | AH46: 0 | AI46: =SUM(AF46:AH46)
B47: Owned | C47: 1 | D47: =2 | E47: 2 | F47: =2 | G47: =8 | H47: 11 | I47: 14 | J47: 19 | K47: 18 | L47: 18 | M47: 17 | N47: 17 | O47: 17 | P47: 16 | Q47: 17 | R47: 12 | S47: 6 | T47: 3 | U47: 0 | V47: 0 | W47: 0 | X47: 0 | Y47: 0 | Z47: 0 | AA47: 0 | AB47: 0 | AC47: 0
B48: Leased | C48: 18 | D48: =17 | E48: 17 | F48: =17 | G48: =11 | H48: 8 | I48: 7 | J48: 3 | K48: 4 | L48: 6 | M48: 6 | N48: 6 | O48: 5 | P48: 5 | Q48: 1 | R48: 1 | S48: 1 | T48: 0 | U48: 0 | V48: 0 | W48: 0 | X48: 0 | Y48: 0 | Z48: 0 | AA48: 0 | AB48: 0 | AC48: 0
A49: F | B49: 747-200F | C49: =SUM(C50:C51) | D49: =SUM(D50:D51) | E49: =SUM(E50:E51) | F49: =SUM(F50:F51) | G49: =SUM(G50:G51) | H49: =SUM(H50:H51) | I49: =SUM(I50:I51) | J49: =SUM(J50:J51) | ... AC49: =SUM(AC50:AC51) | AF49: 0 | AG49: 0 | AH49: 0 | AI49: =SUM(AF49:AH49)
B50: Owned | C50: 3 | D50: =3 | E50: 3 | F50: 3 | G50: =4 | H50: 4 | I50: =1+4 | J50: =4+1 | K50: 5 | L50: =7+1 | M50: =5+1 | N50: 0 | O50: 0 | P50: 0 | Q50: 0 | R50: 0 | S50: 0 | T50: 0 | U50: 0 | V50: 0 | W50: 0 | X50: 0 | Y50: 0 | Z50: 0 | AA50: 0 | AB50: 0 | AC50: 0
B51: Leased | C51: 4 | D51: =1+3 | E51: =1+3 | F51: =1+3 | G51: =2+1 | H51: =2+1 | I51: 3 | J51: 3 | K51: 3 | L51: 0 | M51: 0 | N51: 0 | O51: 0 | P51: 0 | Q51: 0 | R51: 0 | S51: 0 | T51: 0 | U51: 0 | V51: 0 | W51: 0 | X51: 0 | Y51: 0 | Z51: 0 | AA51: 0 | AB51: 0 | AC51: 0
A52: F | B52: 747-300F/SF | C52: =SUM(C53:C54) | D52: =SUM(D53:D54) | E52: =SUM(E53:E54) | F52: =SUM(F53:F54) | G52: =SUM(G53:G54) | H52: =SUM(H53:H54) | I52: =SUM(I53:I54) | J52: =SUM(J53:J54) | ... AC52: =SUM(AC53:AC54) | AF52: 0 | AG52: 0 | AH52: 0 | AI52: =SUM(AF52:AH52)
B53: Owned | C53: 0 | D53: 0 | E53: 0 | F53: =0 | G53: =3 | H53: 3 | I53: =3 | J53: 3 | K53: 3 | L53: 3 | M53: 0 | N53: 0 | O53: 0 | P53: 0 | Q53: 0 | R53: 0 | S53: 0 | T53: 0 | U53: 0 | V53: 0 | W53: 0 | X53: 0 | Y53: 0 | Z53: 0 | AA53: 0 | AB53: 0 | AC53: 0
B54: Leased | C54: 0 | D54: 0 | E54: 0 | F54: =2 | G54: =0 | H54: 0 | I54: 0 | J54: 0 | K54: 0 | L54: 0 | M54: 0 | N54: 0 | O54: 0 | P54: 0 | Q54: 0 | R54: 0 | S54: 0 | T54: 0 | U54: 0 | V54: 0 | W54: 0 | X54: 0 | Y54: 0 | Z54: 0 | AA54: 0 | AB54: 0 | AC54: 0
A55: F | B55: 747-400F | C55: =SUM(C56:C57) | D55: =SUM(D56:D57) | E55: =SUM(E56:E57) | F55: =SUM(F56:F57) | G55: =SUM(G56:G57) | H55: =SUM(H56:H57) | I55: =SUM(I56:I57) | J55: =SUM(J56:J57) | ... AC55: =SUM(AC56:AC57) | AF55: 0 | AG55: 0 | AH55: 0 | AI55: =SUM(AF55:AH55)
B56: Owned | C56: 1 | D56: =1 | E56: 1 | F56: =1 | G56: =1 | H56: 1 | I56: 1 | J56: 2 | K56: 2 | L56: 2 | M56: 2 | N56: 2 | O56: 3 | P56: 3 | Q56: 3 | R56: 3 | S56: 5 | T56: 4 | U56: 0 | V56: 0 | W56: 0 | X56: 0 | Y56: 0 | Z56: 0 | AA56: 0 | AB56: 0 | AC56: 0
B57: Leased | C57: 1 | D57: =1 | E57: 2 | F57: =4 | G57: =4 | H57: 4 | I57: 4 | J57: 4 | K57: 4 | L57: 4 | M57: 4 | N57: 4 | O57: 3 | P57: 3 | Q57: 3 | R57: 3 | S57: 0 | T57: 0 | U57: 0 | V57: 0 | W57: 0 | X57: 0 | Y57: 0 | Z57: 0 | AA57: 0 | AB57: 0 | AC57: 0
A58: F | B58: 747-400BCF | C58: =SUM(C59:C60) | D58: =SUM(D59:D60) | E58: =SUM(E59:E60) | F58: =SUM(F59:F60) | G58: =SUM(G59:G60) | H58: =SUM(H59:H60) | I58: =SUM(I59:I60) | J58: =SUM(J59:J60) | ... AC58: =SUM(AC59:AC60) | AF58: 0 | AG58: 0 | AH58: 0 | AI58: =SUM(AF58:AH58)
B59: Owned | C59: 0 | D59: 0 | E59: 0 | F59: 0 | G59: 0 | H59: 0 | I59: 0 | J59: 1 | K59: 6 | L59: =5+3 | M59: =7+2 | N59: 7 | O59: 6 | P59: 4 | Q59: 2 | R59: 0 | S59: 0 | T59: 0 | U59: 0 | V59: 0 | W59: 1 | X59: 1 | Y59: 0 | Z59: 0 | AA59: 0 | AB59: 0 | AC59: 0
B60: Leased | C60: 0 | D60: 0 | E60: 0 | F60: 0 | G60: 0 | H60: 0 | I60: 0 | J60: 0 | K60: 0 | L60: 1 | M60: 3 | N60: 6 | O60: 6 | P60: =4+3 | Q60: =4+3 | R60: =1+3 | S60: =1+3 | T60: =1+3 | U60: =1+3 | V60: 2 | W60: 0 | X60: 0 | Y60: 0 | Z60: 0 | AA60: 0 | AB60: 0 | AC60: 0
A61: F | B61: 747-400ERF | C61: =SUM(C62:C63) | D61: =SUM(D62:D63) | E61: =SUM(E62:E63) | F61: =SUM(F62:F63) | G61: =SUM(G62:G63) | H61: =SUM(H62:H63) | I61: =SUM(I62:I63) | J61: =SUM(J62:J63) | ... AC61: =SUM(AC62:AC63) | AF61: 0 | AG61: 0 | AH61: 0 | AI61: =SUM(AF61:AH61)
B62: Owned | C62: 0 | D62: 0 | E62: 0 | F62: 0 | G62: 0 | H62: 0 | I62: 0 | J62: 0 | K62: 0 | L62: 0 | M62: 0 | N62: 0 | O62: 0 | P62: 0 | Q62: 0 | R62: 0 | S62: 0 | T62: 0 | U62: 0 | V62: 0 | W62: 0 | X62: 0 | Y62: 2 | Z62: 6 | AA62: 6 | AB62: 6 | AC62: 6
B63: Leased | C63: 0 | D63: 0 | E63: 0 | F63: 0 | G63: 0 | H63: 0 | I63: 0 | J63: 0 | K63: 0 | L63: 0 | M63: 2 | N63: 6 | O63: 6 | P63: 6 | Q63: 6 | R63: 6 | S63: 6 | T63: 6 | U63: 6 | V63: 6 | W63: 6 | X63: 6 | Y63: 4 | Z63: 0 | AA63: 0 | AB63: 0 | AC63: 0
A64: F | B64: 747-8F | C64: =SUM(C65:C66) | D64: =SUM(D65:D66) | E64: =SUM(E65:E66) | F64: =SUM(F65:F66) | G64: =SUM(G65:G66) | H64: =SUM(H65:H66) | I64: =SUM(I65:I66) | J64: =SUM(J65:J66) | ... AC64: =SUM(AC65:AC66) | AF64: 0 | AG64: 0 | AH64: 0 | AI64: =SUM(AF64:AH64)
B65: Owned | C65: 0 | D65: 0 | E65: 0 | F65: 0 | G65: 0 | H65: 0 | I65: 0 | J65: 0 | K65: 0 | L65: 0 | M65: 0 | N65: 0 | O65: 0 | P65: 2 | Q65: 0 | R65: 2 | S65: 2 | T65: 2 | U65: 3 | V65: 3 | W65: 3 | X65: 3 | Y65: 3 | Z65: 3 | AA65: 3 | AB65: 10 | AC65: 11
B66: Leased | C66: 0 | D66: 0 | E66: 0 | F66: 0 | G66: 0 | H66: 0 | I66: 0 | J66: 0 | K66: 0 | L66: 0 | M66: 0 | N66: 0 | O66: 0 | P66: 2 | Q66: 8 | R66: 11 | S66: 11 | T66: 11 | U66: 11 | V66: 11 | W66: 11 | X66: 11 | Y66: 11 | Z66: 11 | AA66: 11 | AB66: 4 | AC66: 3
A67: W | B67: 777-200 | C67: =SUM(C68:C69) | D67: =SUM(D68:D69) | E67: =SUM(E68:E69) | F67: =SUM(F68:F69) | G67: =SUM(G68:G69) | H67: =SUM(H68:H69) | I67: =SUM(I68:I69) | J67: =SUM(J68:J69) | ... AC67: =SUM(AC68:AC69) | AF67: 0 | AG67: 0 | AH67: 0 | AI67: =SUM(AF67:AH67)
B68: Owned | C68: 1 | D68: =1 | E68: 1 | F68: 1 | G68: =1 | H68: 1 | I68: 1 | J68: 1 | K68: 1 | L68: 1 | M68: 1 | N68: 2 | O68: 4 | P68: 5 | Q68: 5 | R68: 5 | S68: 5 | T68: 5 | U68: 5 | V68: 5 | W68: 4 | X68: 1 | Y68: 0 | Z68: 0 | AA68: 0 | AB68: 0 | AC68: 0
B69: Leased | C69: 3 | D69: =3 | E69: 4 | F69: 4 | G69: =4 | H69: 4 | I69: 4 | J69: 4 | K69: 4 | L69: 4 | M69: 4 | N69: 3 | O69: 1 | P69: 0 | Q69: 0 | R69: 0 | S69: 0 | T69: 0 | U69: 0 | V69: 0 | W69: 0 | X69: 0 | Y69: 0 | Z69: 0 | AA69: 0 | AB69: 0 | AC69: 0
A70: F | B70: 777-200F | C70: =SUM(C71:C72) | D70: =SUM(D71:D72) | E70: =SUM(E71:E72) | F70: =SUM(F71:F72) | G70: =SUM(G71:G72) | H70: =SUM(H71:H72) | I70: =SUM(I71:I72) | J70: =SUM(J71:J72) | ... AC70: =SUM(AC71:AC72) | AF70: 0 | AG70: 0 | AH70: 0 | AI70: =SUM(AF70:AH70)
B71: Owned | C71: 0 | D71: 0 | E71: 0 | F71: 0 | G71: 0 | H71: 0 | I71: 0 | J71: 0 | K71: 0 | L71: 0 | M71: 0 | N71: 0 | O71: 0 | P71: 0 | Q71: 0 | R71: 0 | S71: 0 | T71: 0 | U71: 0 | V71: 0 | W71: 0 | X71: 0 | Y71: 0 | Z71: 0 | AA71: 0 | AB71: 0 | AC71: 0
B72: Leased | C72: 0 | D72: 0 | E72: 0 | F72: 0 | G72: 0 | H72: 0 | I72: 0 | J72: 0 | K72: 0 | L72: 0 | M72: 0 | N72: 0 | O72: 0 | P72: 0 | Q72: 0 | R72: 0 | S72: 0 | T72: 0 | U72: 0 | V72: 0 | W72: 0 | X72: 0 | Y72: 0 | Z72: 0 | AA72: 0 | AB72: 0 | AC72: 0
A73: W | B73: 777-300 | C73: =SUM(C74:C75) | D73: =SUM(D74:D75) | E73: =SUM(E74:E75) | F73: =SUM(F74:F75) | G73: =SUM(G74:G75) | H73: =SUM(H74:H75) | I73: =SUM(I74:I75) | J73: =SUM(J74:J75) | ... AC73: =SUM(AC74:AC75) | AF73: 0 | AG73: 0 | AH73: 0 | AI73: =SUM(AF73:AH73)
B74: Owned | C74: 1 | D74: =0 | E74: 0 | F74: 0 | G74: =0 | H74: 0 | I74: 1 | J74: 1 | K74: 2 | L74: 2 | M74: 2 | N74: 3 | O74: 3 | P74: 3 | Q74: 5 | R74: 7 | S74: 8 | T74: 11 | U74: 12 | V74: 12 | W74: 14 | X74: 17 | Y74: 17 | Z74: 17 | AA74: 17 | AB74: 17 | AC74: 17
B75: Leased | C75: 3 | D75: =7 | E75: 7 | F75: 7 | G75: =7 | H75: 9 | I75: 9 | J75: 10 | K75: 10 | L75: 10 | M75: 10 | N75: 9 | O75: 9 | P75: 9 | Q75: 7 | R75: 5 | S75: 4 | T75: 1 | U75: 0 | V75: 0 | W75: 0 | X75: 0 | Y75: 0 | Z75: 0 | AA75: 0 | AB75: 0 | AC75: 0
A76: W | B76: 777-300ER | C76: =SUM(C77:C78) | D76: =SUM(D77:D78) | E76: =SUM(E77:E78) | F76: =SUM(F77:F78) | G76: =SUM(G77:G78) | H76: =SUM(H77:H78) | I76: =SUM(I77:I78) | J76: =SUM(J77:J78) | ... AC76: =SUM(AC77:AC78) | AF76: 0 | AG76: 0 | AH76: 0 | AI76: =SUM(AF76:AH76)
B77: Owned | C77: 0 | D77: 0 | E77: 0 | F77: 0 | G77: 0 | H77: 0 | I77: 0 | J77: 0 | K77: 0 | L77: 1 | M77: 1 | N77: 2 | O77: 2 | P77: 5 | Q77: 4 | R77: 8 | S77: 13 | T77: 19 | U77: 19 | V77: 19 | W77: 20 | X77: 22 | Y77: 23 | Z77: 25 | AA77: 28 | AB77: 30 | AC77: 24
B78: Leased | C78: 0 | D78: 0 | E78: 0 | F78: 0 | G78: 0 | H78: 0 | I78: 0 | J78: 0 | K78: 0 | L78: 4 | M78: 8 | N78: 12 | O78: 16 | P78: 19 | Q78: 25 | R78: =11+19 | S78: =34 | T78: 34 | U78: 34 | V78: 34 | W78: 32 | X78: 29 | Y78: 28 | Z78: 20 | AA78: 13 | AB78: 9 | AC78: 12
A79: W | B79: 777-9 | C79: =SUM(C80:C81) | D79: =SUM(D80:D81) | E79: =SUM(E80:E81) | F79: =SUM(F80:F81) | G79: =SUM(G80:G81) | H79: =SUM(H80:H81) | I79: =SUM(I80:I81) | J79: =SUM(J80:J81) | ... AC79: =SUM(AC80:AC81) | AF79: 0 | AG79: 6 | AH79: 29 | AI79: =SUM(AF79:AH79)
B80: Owned | C80: 0 | D80: 0 | E80: 0 | F80: 0 | G80: 0 | H80: 0 | I80: 0 | J80: 0 | K80: 0 | L80: 0 | M80: 0 | N80: 0 | O80: 0 | P80: 0 | Q80: 0 | R80: 0 | S80: 0 | T80: 0 | U80: 0 | V80: 0 | W80: 0 | X80: 0 | Y80: 0 | Z80: 0 | AA80: 0 | AB80: 0 | AC80: 0
B81: Leased | C81: 0 | D81: 0 | E81: 0 | F81: 0 | G81: 0 | H81: 0 | I81: 0 | J81: 0 | K81: 0 | L81: 0 | M81: 0 | N81: 0 | O81: 0 | P81: 0 | Q81: 0 | R81: 0 | S81: 0 | T81: 0 | U81: 0 | V81: 0 | W81: 0 | X81: 0 | Y81: 0 | Z81: 0 | AA81: 0 | AB81: 0 | AC81: 0
B82: Sub-total | C82: =SUM(C83:C84) | D82: =SUM(D83:D84) | E82: =SUM(E83:E84) | F82: =SUM(F83:F84) | G82: =SUM(G83:G84) | H82: =SUM(H83:H84) | I82: =SUM(I83:I84) | J82: =SUM(J83:J84) | ... AC82: =SUM(AC83:AC84) | AF82: =AF10+AF13+AF16+AF19+AF31+AF34+AF61+AF64+AF73+AF76+AF79+AF58+AF67+AF70+AF25+AF46+AF55+AF49+AF28+AF52+AF43+AF40+AF37+AF22 | AG82: =AG10+AG13+AG16+AG19+AG31+AG34+AG61+AG64+AG73+AG76+AG79+AG58+AG67+AG70+AG25+AG46+AG55+AG49+AG28+AG52+AG43+AG40+AG37+AG22 | AH82: =AH10+AH13+AH16+AH19+AH31+AH34+AH61+AH64+AH73+AH76+AH79+AH58+AH67+AH70+AH25+AH46+AH55+AH49+AH28+AH52+AH43+AH40+AH37+AH22 | AI82: =AI10+AI13+AI16+AI19+AI31+AI34+AI61+AI64+AI73+AI76+AI79+AI58+AI67+AI70+AI25+AI46+AI55+AI49+AI28+AI52+AI43+AI40+AI37+AI22
B83: Owned | C83: =C11+C14+C17+C20+C23+C32+C35+C62+C65+C74+C77+C80+C59+C68+C71+C26+C47+C56+C50+C29+C53+C44+C41+C38 | D83: =D11+D14+D17+D20+D23+D32+D35+D62+D65+D74+D77+D80+D59+D68+D71+D26+D47+D56+D50+D29+D53+D44+D41+D38 | E83: =E11+E14+E17+E20+E23+E32+E35+E62+E65+E74+E77+E80+E59+E68+E71+E26+E47+E56+E50+E29+E53+E44+E41+E38 | F83: =F11+F14+F17+F20+F23+F32+F35+F62+F65+F74+F77+F80+F59+F68+F71+F26+F47+F56+F50+F29+F53+F44+F41+F38 | G83: =G11+G14+G17+G20+G23+G32+G35+G62+G65+G74+G77+G80+G59+G68+G71+G26+G47+G56+G50+G29+G53+G44+G41+G38 | H83: =H11+H14+H17+H20+H23+H32+H35+H62+H65+H74+H77+H80+H59+H68+H71+H26+H47+H56+H50+H29+H53+H44+H41+H38 | I83: =I11+I14+I17+I20+I23+I32+I35+I62+I65+I74+I77+I80+I59+I68+I71+I26+I47+I56+I50+I29+I53+I44+I41+I38 | J83: =J11+J14+J17+J20+J23+J32+J35+J62+J65+J74+J77+J80+J59+J68+J71+J26+J47+J56+J50+J29+J53+J44+J41+J38 | ... AC83: =AC11+AC14+AC17+AC20+AC23+AC32+AC35+AC62+AC65+AC74+AC77+AC80+AC59+AC68+AC71+AC26+AC47+AC56+AC50+AC29+AC53+AC44+AC41+AC38
B84: Leased | C84: =C12+C15+C18+C21+C33+C36+C63+C66+C75+C78+C81+C60+C69+C72+C27+C48+C57+C51+C30+C54+C45+C42+C39+C24 | D84: =D12+D15+D18+D21+D33+D36+D63+D66+D75+D78+D81+D60+D69+D72+D27+D48+D57+D51+D30+D54+D45+D42+D39+D24 | E84: =E12+E15+E18+E21+E33+E36+E63+E66+E75+E78+E81+E60+E69+E72+E27+E48+E57+E51+E30+E54+E45+E42+E39+E24 | F84: =F12+F15+F18+F21+F33+F36+F63+F66+F75+F78+F81+F60+F69+F72+F27+F48+F57+F51+F30+F54+F45+F42+F39+F24 | G84: =G12+G15+G18+G21+G33+G36+G63+G66+G75+G78+G81+G60+G69+G72+G27+G48+G57+G51+G30+G54+G45+G42+G39+G24 | H84: =H12+H15+H18+H21+H33+H36+H63+H66+H75+H78+H81+H60+H69+H72+H27+H48+H57+H51+H30+H54+H45+H42+H39+H24 | I84: =I12+I15+I18+I21+I33+I36+I63+I66+I75+I78+I81+I60+I69+I72+I27+I48+I57+I51+I30+I54+I45+I42+I39+I24 | J84: =J12+J15+J18+J21+J33+J36+J63+J66+J75+J78+J81+J60+J69+J72+J27+J48+J57+J51+J30+J54+J45+J42+J39+J24 | ... AC84: =AC12+AC15+AC18+AC21+AC33+AC36+AC63+AC66+AC75+AC78+AC81+AC60+AC69+AC72+AC27+AC48+AC57+AC51+AC30+AC54+AC45+AC42+AC39+AC24
B85: HK Express
A86: N | B86: A320-200 | C86: =SUM(C87:C88) | D86: =SUM(D87:D88) | E86: =SUM(E87:E88) | F86: =SUM(F87:F88) | G86: =SUM(G87:G88) | H86: =SUM(H87:H88) | I86: =SUM(I87:I88) | J86: =SUM(J87:J88) | ... AC86: =SUM(AC87:AC88) | AF86: 0 | AG86: 0 | AH86: 0 | AI86: =SUM(AF86:AH86)
B87: Owned | C87: 0 | D87: 0 | E87: 0 | F87: 0 | G87: 0 | H87: 0 | I87: 0 | J87: 0 | K87: 0 | L87: 0 | M87: 0 | N87: 0 | O87: 0 | P87: 0 | Q87: 0 | R87: 0 | S87: 0 | T87: 0 | U87: 0 | V87: 0 | W87: 0 | X87: 0 | Y87: 0 | Z87: 0 | AA87: 0 | AB87: 0 | AC87: 3
B88: Leased | C88: 0 | D88: 0 | E88: 0 | F88: 0 | G88: 0 | H88: 0 | I88: 0 | J88: 0 | K88: 0 | L88: 0 | M88: 0 | N88: 0 | O88: 0 | P88: 0 | Q88: 0 | R88: 0 | S88: 0 | T88: 0 | U88: 0 | V88: 0 | W88: 0 | X88: 8 | Y88: 8 | Z88: 6 | AA88: 5 | AB88: 8 | AC88: 3
A89: N | B89: A320-200neo | C89: =SUM(C90:C91) | D89: =SUM(D90:D91) | E89: =SUM(E90:E91) | F89: =SUM(F90:F91) | G89: =SUM(G90:G91) | H89: =SUM(H90:H91) | I89: =SUM(I90:I91) | J89: =SUM(J90:J91) | ... AC89: =SUM(AC90:AC91) | AF89: 2 | AG89: 2 | AH89: 4 | AI89: =SUM(AF89:AH89)
B90: Owned | C90: 0 | D90: 0 | E90: 0 | F90: 0 | G90: 0 | H90: 0 | I90: 0 | J90: 0 | K90: 0 | L90: 0 | M90: 0 | N90: 0 | O90: 0 | P90: 0 | Q90: 0 | R90: 0 | S90: 0 | T90: 0 | U90: 0 | V90: 0 | W90: 0 | X90: 0 | Y90: 0 | Z90: 0 | AA90: 0 | AB90: 0 | AC90: 0
B91: Leased | C91: 0 | D91: 0 | E91: 0 | F91: 0 | G91: 0 | H91: 0 | I91: 0 | J91: 0 | K91: 0 | L91: 0 | M91: 0 | N91: 0 | O91: 0 | P91: 0 | Q91: 0 | R91: 0 | S91: 0 | T91: 0 | U91: 0 | V91: 0 | W91: 0 | X91: 5 | Y91: 9 | Z91: 10 | AA91: 10 | AB91: 10 | AC91: 10
A92: N | B92: A321-200 | C92: =SUM(C93:C94) | D92: =SUM(D93:D94) | E92: =SUM(E93:E94) | F92: =SUM(F93:F94) | G92: =SUM(G93:G94) | H92: =SUM(H93:H94) | I92: =SUM(I93:I94) | J92: =SUM(J93:J94) | ... AC92: =SUM(AC93:AC94) | AF92: 0 | AG92: 0 | AH92: 0 | AI92: =SUM(AF92:AH92)
B93: Owned | C93: 0 | D93: 0 | E93: 0 | F93: 0 | G93: 0 | H93: 0 | I93: 0 | J93: 0 | K93: 0 | L93: 0 | M93: 0 | N93: 0 | O93: 0 | P93: 0 | Q93: 0 | R93: 0 | S93: 0 | T93: 0 | U93: 0 | V93: 0 | W93: 0 | X93: 0 | Y93: 0 | Z93: 0 | AA93: 0 | AB93: 0 | AC93: 2
B94: Leased | C94: 0 | D94: 0 | E94: 0 | F94: 0 | G94: 0 | H94: 0 | I94: 0 | J94: 0 | K94: 0 | L94: 0 | M94: 0 | N94: 0 | O94: 0 | P94: 0 | Q94: 0 | R94: 0 | S94: 0 | T94: 0 | U94: 0 | V94: 0 | W94: 0 | X94: 11 | Y94: 11 | Z94: 11 | AA94: 11 | AB94: 11 | AC94: 11
A95: N | B95: A321-200neo | C95: =SUM(C96:C97) | D95: =SUM(D96:D97) | E95: =SUM(E96:E97) | F95: =SUM(F96:F97) | G95: =SUM(G96:G97) | H95: =SUM(H96:H97) | I95: =SUM(I96:I97) | J95: =SUM(J96:J97) | ... AC95: =SUM(AC96:AC97) | AF95: 3 | AG95: 11 | AH95: 2 | AI95: =SUM(AF95:AH95)
B96: Owned | C96: 0 | D96: 0 | E96: 0 | F96: 0 | G96: 0 | H96: 0 | I96: 0 | J96: 0 | K96: 0 | L96: 0 | M96: 0 | N96: 0 | O96: 0 | P96: 0 | Q96: 0 | R96: 0 | S96: 0 | T96: 0 | U96: 0 | V96: 0 | W96: 0 | X96: 0 | Y96: 0 | Z96: 0 | AA96: 0 | AB96: 0 | AC96: 5
B97: Leased | C97: 0 | D97: 0 | E97: 0 | F97: 0 | G97: 0 | H97: 0 | I97: 0 | J97: 0 | K97: 0 | L97: 0 | M97: 0 | N97: 0 | O97: 0 | P97: 0 | Q97: 0 | R97: 0 | S97: 0 | T97: 0 | U97: 0 | V97: 0 | W97: 0 | X97: 0 | Y97: 0 | Z97: 0 | AA97: 0 | AB97: 4 | AC97: 7
B98: Sub-total | C98: =SUM(C99:C100) | D98: =SUM(D99:D100) | E98: =SUM(E99:E100) | F98: =SUM(F99:F100) | G98: =SUM(G99:G100) | H98: =SUM(H99:H100) | I98: =SUM(I99:I100) | J98: =SUM(J99:J100) | ... AC98: =SUM(AC99:AC100) | AF98: =AF86+AF89+AF92+AF95 | AG98: =AG86+AG89+AG92+AG95 | AH98: =AH86+AH89+AH92+AH95 | AI98: =SUM(AF98:AH98)
B99: Owned | C99: =C87+C90+C93+C96 | D99: =D87+D90+D93+D96 | E99: =E87+E90+E93+E96 | F99: =F87+F90+F93+F96 | G99: =G87+G90+G93+G96 | H99: =H87+H90+H93+H96 | I99: =I87+I90+I93+I96 | J99: =J87+J90+J93+J96 | ... AC99: =AC87+AC90+AC93+AC96
B100: Leased | C100: =C88+C91+C94+C97 | D100: =D88+D91+D94+D97 | E100: =E88+E91+E94+E97 | F100: =F88+F91+F94+F97 | G100: =G88+G91+G94+G97 | H100: =H88+H91+H94+H97 | I100: =I88+I91+I94+I97 | J100: =J88+J91+J94+J97 | ... AC100: =AC88+AC91+AC94+AC97
B101: Air Hong Kong
A102: F | B102: A300-600F | C102: =SUM(C103:C104) | D102: =SUM(D103:D104) | E102: =SUM(E103:E104) | F102: =SUM(F103:F104) | G102: =SUM(G103:G104) | H102: =SUM(H103:H104) | I102: =SUM(I103:I104) | J102: =SUM(J103:J104) | ... AC102: =SUM(AC103:AC104) | AF102: 0 | AG102: 0 | AH102: 0 | AI102: =SUM(AF102:AH102)
...

Sheet Monthly
A1: Monthly operational data of Cathay Pacific
A2: Source: Company Data
ED7: =MONTH(ED8) | EE7: =MONTH(EE8) | EF7: =MONTH(EF8) | EG7: =MONTH(EG8) | EH7: =MONTH(EH8) | EI7: =MONTH(EI8) | EJ7: =MONTH(EJ8) | EK7: =MONTH(EK8) | ... IS7: =MONTH(IS8)
A8: CATHAY PACIFIC | B8: 36191 | C8: =EOMONTH(B8,1) | D8: =EOMONTH(C8,1) | E8: =EOMONTH(D8,1) | F8: =EOMONTH(E8,1) | G8: =EOMONTH(F8,1) | H8: =EOMONTH(G8,1) | I8: =EOMONTH(H8,1) | J8: =EOMONTH(I8,1) | ... LS8: =EOMONTH(LR8,1)
A9: Capacity
A10: ASK (Million) | B10: =B14+B18+B22+B26+B30+B36 | C10: =C14+C18+C22+C26+C30+C36 | D10: =D14+D18+D22+D26+D30+D36 | E10: =E14+E18+E22+E26+E30+E36 | F10: =F14+F18+F22+F26+F30+F36 | G10: =G14+G18+G22+G26+G30+G36 | H10: =H14+H18+H22+H26+H30+H36 | I10: =I14+I18+I22+I26+I30+I36 | ... GH10: =GH14+GH18+GH22+GH26+GH30+GH36 | GI10: 11605.864 | GJ10: 11085.313 | GK10: 11820.975 | GL10: 11876.449 | GM10: 10801.044 | GN10: 11680.68 | GO10: 11522.897 | GP10: 12056.387 | GQ10: 11751.688 | GR10: 12399.24 | GS10: 12558.154 | GT10: 11594.776 | GU10: 12307.735 | GV10: 11599.726 | GW10: 12531.8 | GX10: 12574.463 | GY10: 11728.128 | GZ10: 12291.864 | HA10: 11796.619 | HB10: 12118.716 | HC10: 12136.72 | HD10: 12723.458 | HE10: 12457.876 | HF10: 11900.705 | HG10: 12334.585 | HH10: 11328.962 | HI10: 12693.382 | HJ10: 12741.323 | HK10: 11374 | HL10: 12330.894 | HM10: 12368.278 | HN10: 12302.168 | HO10: 12327.267 | HP10: 13287.379 | HQ10: 13056.61 | HR10: 12183.036 | HS10: 12905.27 | HT10: 12052.163 | HU10: 13209.584 | HV10: 13070.796 | HW10: 11926.392 | HX10: 12832.998 | HY10: 12483.039 | HZ10: 12662.581 | IA10: 12794.574 | IB10: 13665.105 | IC10: 13690.681 | ID10: 12273.949 | IE10: 13390 | IF10: 12593.062 | IG10: 13978.669 | IH10: 14004.187 | II10: 12628.435 | IJ10: 13461.313 | IK10: 13493.711 | IL10: 13495.182 | IM10: 13731.593 | IN10: 14642.473 | IO10: 14392.234 | IP10: 13480.282 | IQ10: 13709.615 | IR10: 12409.574 | IS10: 13795.313 | IT10: 13962.739 | IU10: 8924.428 | IV10: 3605.276 | IW10: =IW14+IW18+IW22+IW26+IW30+IW36 | IX10: =IX14+IX18+IX22+IX26+IX30+IX36 | IY10: =IY14+IY18+IY22+IY26+IY30+IY36 | IZ10: =IZ14+IZ18+IZ22+IZ26+IZ30+IZ36 | JA10: =JA14+JA18+JA22+JA26+JA30+JA36 | JB10: =JB14+JB18+JB22+JB26+JB30+JB36 | JC10: =JC14+JC18+JC22+JC26+JC30+JC36 | JD10: =JD14+JD18+JD22+JD26+JD30+JD36 | ... LA10: =LA14+LA18+LA22+LA26+LA30+LA36 | LB10: =LB193/1000 | LC10: =LC193/1000 | LD10: =LD193/1000 | LE10: =LE193/1000 | LF10: =LF193/1000 | LG10: =LG193/1000 | LH10: =LH193/1000 | LI10: =LI193/1000 | ... LS10: =LS193/1000
A11: m cg % | C11: =C10/B10-1 | D11: =D10/C10-1 | E11: =E10/D10-1 | F11: =F10/E10-1 | G11: =G10/F10-1 | H11: =H10/G10-1 | I11: =I10/H10-1 | J11: =J10/I10-1 | ... LS11: =LS10/LR10-1
A12: YoY cg % | N12: =N10/B10-1 | O12: =O10/C10-1 | P12: =P10/D10-1 | Q12: =Q10/E10-1 | R12: =R10/F10-1 | S12: =S10/G10-1 | T12: =T10/H10-1 | U12: =U10/I10-1 | ... LS12: =LS10/LG10-1
A13: YTD cg % | N13: =SUMIFS(10:10,$8:$8,">="&DATE(YEAR(N$8),1,1),$8:$8,"<="&EOMONTH(N$8,0))/SUMIFS(10:10,$8:$8,">="&DATE(YEAR(N$8)-1,1,1),$8:$8,"<="&EOMONTH(N$8,-12))-1 | O13: =SUMIFS(10:10,$8:$8,">="&DATE(YEAR(O$8),1,1),$8:$8,"<="&EOMONTH(O$8,0))/SUMIFS(10:10,$8:$8,">="&DATE(YEAR(O$8)-1,1,1),$8:$8,"<="&EOMONTH(O$8,-12))-1 | P13: =SUMIFS(10:10,$8:$8,">="&DATE(YEAR(P$8),1,1),$8:$8,"<="&EOMONTH(P$8,0))/SUMIFS(10:10,$8:$8,">="&DATE(YEAR(P$8)-1,1,1),$8:$8,"<="&EOMONTH(P$8,-12))-1 | Q13: =SUMIFS(10:10,$8:$8,">="&DATE(YEAR(Q$8),1,1),$8:$8,"<="&EOMONTH(Q$8,0))/SUMIFS(10:10,$8:$8,">="&DATE(YEAR(Q$8)-1,1,1),$8:$8,"<="&EOMONTH(Q$8,-12))-1 | R13: =SUMIFS(10:10,$8:$8,">="&DATE(YEAR(R$8),1,1),$8:$8,"<="&EOMONTH(R$8,0))/SUMIFS(10:10,$8:$8,">="&DATE(YEAR(R$8)-1,1,1),$8:$8,"<="&EOMONTH(R$8,-12))-1 | S13: =SUMIFS(10:10,$8:$8,">="&DATE(YEAR(S$8),1,1),$8:$8,"<="&EOMONTH(S$8,0))/SUMIFS(10:10,$8:$8,">="&DATE(YEAR(S$8)-1,1,1),$8:$8,"<="&EOMONTH(S$8,-12))-1 | T13: =SUMIFS(10:10,$8:$8,">="&DATE(YEAR(T$8),1,1),$8:$8,"<="&EOMONTH(T$8,0))/SUMIFS(10:10,$8:$8,">="&DATE(YEAR(T$8)-1,1,1),$8:$8,"<="&EOMONTH(T$8,-12))-1 | U13: =SUMIFS(10:10,$8:$8,">="&DATE(YEAR(U$8),1,1),$8:$8,"<="&EOMONTH(U$8,0))/SUMIFS(10:10,$8:$8,">="&DATE(YEAR(U$8)-1,1,1),$8:$8,"<="&EOMONTH(U$8,-12))-1 | ... LS13: =SUMIFS(10:10,$8:$8,">="&DATE(YEAR(LS$8),1,1),$8:$8,"<="&EOMONTH(LS$8,0))/SUMIFS(10:10,$8:$8,">="&DATE(YEAR(LS$8)-1,1,1),$8:$8,"<="&EOMONTH(LS$8,-12))-1
A14: Europe | B14: 1245.6969 | C14: 1112.4761 | D14: 1236.9814 | E14: 1170.4623 | F14: 1087.6983 | G14: 948.707 | H14: 1221.914 | I14: 1196.372 | J14: 1169.9 | K14: 1223.598 | L14: 1138.993 | M14: 1152.5989 | N14: 1176.187 | O14: 1110.436 | P14: 1198.635 | Q14: 1166.089 | R14: 1192.49 | S14: 1160.259 | T14: 1250.284 | U14: 1248.965 | V14: 1258.243 | W14: 1283.501 | X14: 1226.343 | Y14: 1293.216 | Z14: 1280.264 | AA14: 1154.975 | AB14: 1267.996 | AC14: 1230.704 | AD14: 1161.301 | AE14: 1135.104 | AF14: 1084.836 | AG14: 1148.159 | AH14: 1100.885 | AI14: 1130.091 | AJ14: 1042.937 | AK14: 1095.794 | AL14: 1085.425 | AM14: 990.466 | AN14: 1102.55 | AO14: 1053.619 | AP14: 1095.293 | AQ14: 1058.721 | AR14: 1186.304 | AS14: 1171.962 | AT14: 1134.344 | AU14: 1162.012 | AV14: 1115.749 | AW14: 1134.452 | AX14: 1147.39 | AY14: 1025.802 | AZ14: 1143.6266 | BA14: 811.77935 | BB14: 666.671 | BC14: 685.502 | BD14: 1064.997 | BE14: 1245.338 | BF14: 1219.125 | BG14: 1263.789 | BH14: 1199.41 | BI14: 1238.323 | BJ14: 1241.016 | BK14: 1161.686 | BL14: 1246.553 | BM14: 1258.258 | BN14: 1318.109 | BO14: 1264.448 | BP14: 1316.53 | BQ14: 1309.318 | BR14: 1265.428 | BS14: 1318.647 | BT14: 1220.957 | BU14: 1273.61 | BV14: 1281.543 | BW14: 1152.882 | BX14: 1267.546 | BY14: 1270.192 | BZ14: 1310.692 | CA14: 1309.693 | CB14: 1460.246 | CC14: 1445.73 | CD14: 1403.885 | CE14: 1450.276 | CF14: 1362.478 | CG14: 1465.94 | CH14: 1469.364 | CI14: 1308.179 | CJ14: 1497.079 | CK14: 1590.8 | CL14: 1646.8 | CM14: 1595.522 | CN14: 1695.051 | CO14: 1651.418 | CP14: 1647.931 | CQ14: 1676 | CR14: 1524 | CS14: 1581.701 | CT14: 1580.538 | CU14: 1422.731 | CV14: 1611 | CW14: 1651.81 | CX14: 1705.045 | CY14: 1650.728 | CZ14: 1696.822 | DA14: 1713.564 | DB14: 1658.22 | DC14: 1695.163 | DD14: 1602.587 | DE14: 1652.859 | DF14: 1653.938 | DG14: 1545.716 | DH14: 1654.479 | DI14: 1620.463 | DJ14: 1682.225 | DK14: 1624.199 | DL14: 1682.568 | DM14: 1705.751 | DN14: 1651.276 | DO14: 1728.612 | DP14: 1703.981 | DQ14: 1764.069 | DR14: 1782.456 | DS14: 1611.608 | DT14: 1800.199 | DU14: 1875.996 | DV14: 1725.012 | DW14: 1652.757 | DX14: 1803.141 | DY14: 1819.876 | DZ14: 1488.697 | EA14: 1518.553 | EB14: 1480.577 | EC14: 1663.57 | ED14: 1676.958 | EE14: 1498.71 | EF14: 1682.906 | EG14: 1485.697 | EH14: 1766.111 | EI14: 1727.42 | EJ14: 1933.847 | EK14: 1948.602 | EL14: 1840.759 | EM14: 1827.165 | EN14: 1748.643 | EO14: 1856.538 | EP14: 1917.208 | EQ14: 1724.483 | ER14: 1912.19 | ES14: 1858.154 | ET14: 1916.472 | EU14: 1830.954 | EV14: 1974.059 | EW14: 1979.255 | EX14: 1887.631 | EY14: 1948.614 | EZ14: 1786.393 | FA14: 1816.84 | FB14: 1837.728 | FC14: 1695.115 | FD14: 1852.452 | FE14: 1809.266 | FF14: 1824.986 | FG14: 1792.133 | FH14: 1914.41 | FI14: 1857.983 | FJ14: 1778.334 | FK14: 1812.771 | FL14: 1669.139 | FM14: 1664.777 | FN14: 1744.755 | FO14: 1536.693 | FP14: 1747.746 | FQ14: 1713.198 | FR14: 1798.799 | FS14: 1775.033 | FT14: 2008.263 | FU14: 1991.874 | FV14: 1889.105 | FW14: 1823.928 | FX14: 1733.879 | FY14: 1772.759 | FZ14: 1769.321 | GA14: 1596.349 | GB14: 1746.656 | GC14: 1741.891 | GD14: 1777.522 | GE14: 1791.756 | GF14: 1885.85 | GG14: 1887.472 | GH14: 1826.583 | GI14: 1747.21 | GJ14: 1617.275 | GK14: 1668.051 | GL14: 1900.716 | GM14: 1643.131 | GN14: 1868.226 | GO14: 1987.297 | GP14: 1962.81 | GQ14: 2032.707 | GR14: 2114.437 | GS14: 2131.265 | GT14: 2126.504 | GU14: 2189.824 | GV14: 1964.498 | GW14: 2047.889 | GX14: 2072.739 | GY14: 1927.707 | GZ14: 2088.666 | HA14: 2046.032 | HB14: 1951.135 | HC14: 2260.882 | HD14: 2307.344 | HE14: 2239.494 | HF14: 2352.749 | HG14: 2388.444 | HH14: 2075.441 | HI14: 2247.821 | HJ14: 2293.436 | HK14: 2012.497 | HL14: 2256.561 | HM14: 2307.573 | HN14: 2208.787 | HO14: 2469.468 | HP14: 2684.619 | HQ14: 2658.98 | HR14: 2601.181 | HS14: 2622.431 | HT14: 2377.341 | HU14: 2464.286 | HV14: 2469.232 | HW14: 2283.511 | HX14: 2524.673 | HY14: 2480.959 | HZ14: 2589.715 | IA14: 2795.305 | IB14: 2979.569 | IC14: 2969.912 | ID14: 2844.63 | IE14: 2923.375 | IF14: 2498.16 | IG14: 2730.83 | IH14: 2734.916 | II14: 2510.811 | IJ14: 2752.505 | IK14: 2884.249 | IL14: 2821.971 | IM14: 3062.142 | IN14: 3268.11 | IO14: 3222.711 | IP14: 3169.976 | IQ14: 3072.784 | IR14: 2525.958 | IS14: 2651.033 | IT14: 2663.279 | IU14: 1774.02 | IV14: 837.649 | IW14: 105.132 | IX14: 57.715 | IY14: 107.117 | IZ14: 195.2 | JA14: 256.676 | JB14: 377.102 | JC14: 307.156 | JD14: 322.845 | JE14: 272.473 | JF14: 149.003 | JG14: 63.047 | JH14: 35.48 | JI14: 59.521 | JJ14: 89.779 | JK14: 166.396 | JL14: 159.077 | JM14: 314.1 | JN14: 510.439 | JO14: 410.697 | JP14: 360.722 | JQ14: 343.689 | JR14: 44.672 | JS14: 31.861 | JT14: 53.591 | JU14: 56.443 | JV14: 153.631 | JW14: 433.65 | JX14: 498.625 | JY14: 489.843 | JZ14: 560.68 | KA14: 654.49 | KB14: 928.774 | KC14: 972.488 | KD14: 1217.949 | KE14: 1248.856 | KF14: 1528.77 | KG14: 1580.375 | KH14: 1560.107 | KI14: 1670.444 | KJ14: 1930.713 | KK14: 1869.865 | KL14: 1878.223 | KM14: 1771.737 | KN14: 1613.254 | KO14: 1637.903 | KP14: 1516.054 | KQ14: 1611.72 | KR14: 1660.523 | KS14: 1522.244 | KT14: 1573.869 | KU14: 1797.443 | KV14: 1754.698 | KW14: 1779.344 | KX14: 1876.845 | KY14: 1849.004 | KZ14: 1803.19 | LA14: 1819.973
A15: m cg % | C15: =C14/B14-1 | D15: =D14/C14-1 | E15: =E14/D14-1 | F15: =F14/E14-1 | G15: =G14/F14-1 | H15: =H14/G14-1 | I15: =I14/H14-1 | J15: =J14/I14-1 | ... LA15: =LA14/KZ14-1
A16: YoY cg % | N16: =N14/B14-1 | O16: =O14/C14-1 | P16: =P14/D14-1 | Q16: =Q14/E14-1 | R16: =R14/F14-1 | S16: =S14/G14-1 | T16: =T14/H14-1 | U16: =U14/I14-1 | ... LA16: =LA14/KO14-1
A17: YTD cg % | N17: =SUMIFS(14:14,$8:$8,">="&DATE(YEAR(N$8),1,1),$8:$8,"<="&EOMONTH(N$8,0))/SUMIFS(14:14,$8:$8,">="&DATE(YEAR(N$8)-1,1,1),$8:$8,"<="&EOMONTH(N$8,-12))-1 | O17: =SUMIFS(14:14,$8:$8,">="&DATE(YEAR(O$8),1,1),$8:$8,"<="&EOMONTH(O$8,0))/SUMIFS(14:14,$8:$8,">="&DATE(YEAR(O$8)-1,1,1),$8:$8,"<="&EOMONTH(O$8,-12))-1 | P17: =SUMIFS(14:14,$8:$8,">="&DATE(YEAR(P$8),1,1),$8:$8,"<="&EOMONTH(P$8,0))/SUMIFS(14:14,$8:$8,">="&DATE(YEAR(P$8)-1,1,1),$8:$8,"<="&EOMONTH(P$8,-12))-1 | Q17: =SUMIFS(14:14,$8:$8,">="&DATE(YEAR(Q$8),1,1),$8:$8,"<="&EOMONTH(Q$8,0))/SUMIFS(14:14,$8:$8,">="&DATE(YEAR(Q$8)-1,1,1),$8:$8,"<="&EOMONTH(Q$8,-12))-1 | R17: =SUMIFS(14:14,$8:$8,">="&DATE(YEAR(R$8),1,1),$8:$8,"<="&EOMONTH(R$8,0))/SUMIFS(14:14,$8:$8,">="&DATE(YEAR(R$8)-1,1,1),$8:$8,"<="&EOMONTH(R$8,-12))-1 | S17: =SUMIFS(14:14,$8:$8,">="&DATE(YEAR(S$8),1,1),$8:$8,"<="&EOMONTH(S$8,0))/SUMIFS(14:14,$8:$8,">="&DATE(YEAR(S$8)-1,1,1),$8:$8,"<="&EOMONTH(S$8,-12))-1 | T17: =SUMIFS(14:14,$8:$8,">="&DATE(YEAR(T$8),1,1),$8:$8,"<="&EOMONTH(T$8,0))/SUMIFS(14:14,$8:$8,">="&DATE(YEAR(T$8)-1,1,1),$8:$8,"<="&EOMONTH(T$8,-12))-1 | U17: =SUMIFS(14:14,$8:$8,">="&DATE(YEAR(U$8),1,1),$8:$8,"<="&EOMONTH(U$8,0))/SUMIFS(14:14,$8:$8,">="&DATE(YEAR(U$8)-1,1,1),$8:$8,"<="&EOMONTH(U$8,-12))-1 | ... LA17: =SUMIFS(14:14,$8:$8,">="&DATE(YEAR(LA$8),1,1),$8:$8,"<="&EOMONTH(LA$8,0))/SUMIFS(14:14,$8:$8,">="&DATE(YEAR(LA$8)-1,1,1),$8:$8,"<="&EOMONTH(LA$8,-12))-1
A18: SW Pacific | B18: 2289.0334 | C18: 2050.4866 | D18: 2182.0041 | E18: 1782.7147 | F18: 1802.0592 | G18: 1466.307 | H18: 1960.985 | I18: 1928.187 | J18: 1873.8 | K18: 1969.034 | L18: 2067.983 | M18: 2099.5266 | N18: 2105.224 | O18: 1991.538 | P18: 2114.362 | Q18: 2012.986 | R18: 2071.181 | S18: 1988.203 | T18: 2074.655 | U18: 2070.406 | V18: 2193.375 | W18: 2264.331 | X18: 2195.752 | Y18: 2252.792 | Z18: 2269.695 | AA18: 2037.132 | AB18: 2257.366 | AC18: 2174.819 | AD18: 2240.64 | AE18: 2168.308 | AF18: 1979.119 | AG18: 2022.686 | AH18: 1993.992 | AI18: 2041.725 | AJ18: 1802.813 | AK18: 2081.412 | AL18: 2072.712 | AM18: 1714.988 | AN18: 1858.794 | AO18: 1735.236 | AP18: 1840.25 | AQ18: 1898.527 | AR18: 2100.789 | AS18: 2230.661 | AT18: 2139.392 | AU18: 2285.111 | AV18: 2326.991 | AW18: 2470.672 | AX18: 1050.852 | AY18: 944 | AZ18: 1030.5914 | BA18: 718.46208 | BB18: 523.77648 | BC18: 490.8 | BD18: 713.6 | BE18: 809.7 | BF18: 820.46098 | BG18: 938.5 | BH18: 1005.7934 | BI18: 1065 | BJ18: 1062.923 | BK18: 995.927 | BL18: 1031.622 | BM18: 918.913 | BN18: 939.655 | BO18: 937.275 | BP18: 998.798 | BQ18: 985.022 | BR18: 985.246 | BS18: 1025.81 | BT18: 1263.264 | BU18: 1321.14 | BV18: 1325.483 | BW18: 1181.845 | BX18: 1295.979 | BY18: 1163.794 | BZ18: 1185.347 | CA18: 1157.127 | CB18: 1208.603 | CC18: 1189.84 | CD18: 1153.56 | CE18: 1211.269 | CF18: 1261.479 | CG18: 1321.883 | CH18: 1321.584 | CI18: 1195.384 | CJ18: 1291.435 | CK18: 1091.4 | CL18: 1115.7 | CM18: 1080.363 | CN18: 1132.596 | CO18: 1104.122 | CP18: 1091.64 | CQ18: 1166 | CR18: 1305 | CS18: 1351.352 | CT18: 1347.822 | CU18: 1217.708 | CV18: 1294 | CW18: 1092.609 | CX18: 1122.074 | CY18: 1093.125 | CZ18: 1127.383 | DA18: 1127.908 | DB18: 1099.706 | DC18: 1275.148 | DD18: 1290.649 | DE18: 1500.771 | DF18: 1501.18 | DG18: 1458.901 | DH18: 1535.567 | DI18: 1356.589 | DJ18: 1404.968 | DK18: 1359.705 | DL18: 1416.584 | DM18: 1392.454 | DN18: 1361.846 | DO18: 1506.067 | DP18: 1665.592 | DQ18: 1729.34 | DR18: 1733.294 | DS18: 1519.292 | DT18: 1651.207 | DU18: 1479.153 | DV18: 1421.994 | DW18: 1350.342 | DX18: 1411.887 | DY18: 1409.217 | DZ18: 1316.752 | EA18: 1392.404 | EB18: 1531.495 | EC18: 1742.106 | ED18: 1745.611 | EE18: 1582.202 | EF18: 1648.388 | EG18: 1367.827 | EH18: 1410.047 | EI18: 1418.585 | EJ18: 1478.103 | EK18: 1462.774 | EL18: 1403.441 | EM18: 1499.727 | EN18: 1555.137 | EO18: 1755.184 | EP18: 1751.807 | EQ18: 1581.745 | ER18: 1636.784 | ES18: 1496.558 | ET18: 1520.125 | EU18: 1456.604 | EV18: 1544.467 | EW18: 1541.28 | EX18: 1495.792 | EY18: 1555.47 | EZ18: 1658.082 | FA18: 1842.781 | FB18: 1853.266 | FC18: 1613.412 | FD18: 1659.524 | FE18: 1453.497 | FF18: 1473.7 | FG18: 1428.836 | FH18: 1459.945 | FI18: 1431.32 | FJ18: 1419.474 | FK18: 1469.408 | FL18: 1411.314 | FM18: 1630.143 | FN18: 1636.246 | FO18: 1462.772 | FP18: 1452.39 | FQ18: 1412.657 | FR18: 1422.845 | FS18: 1395.684 | FT18: 1440.55 | FU18: 1436.489 | FV18: 1366.368 | FW18: 1458.996 | FX18: 1403.353 | FY18: 1601.886 | FZ18: 1602.123 | GA18: 1451.844 | GB18: 1460.14 | GC18: 1465.742 | GD18: 1443.139 | GE18: 1425.594 | GF18: 1518.01 | GG18: 1516.337 | GH18: 1462.287 | GI18: 1514.629 | GJ18: 1470.313 | GK18: 1702.147 | GL18: 1712.703 | GM18: 1581.263 | GN18: 1644.138 | GO18: 1536.483 | GP18: 1589.466 | GQ18: 1527.967 | GR18: 1587.88 | GS18: 1590.137 | GT18: 1538.707 | GU18: 1627.514 | GV18: 1577.855 | GW18: 1835.935 | GX18: 1841.313 | GY18: 1724.459 | GZ18: 1644.975 | HA18: 1580.473 | HB18: 1591.938 | HC18: 1527.629 | HD18: 1622.826 | HE18: 1580.229 | HF18: 1559.996 | HG18: 1601.351 | HH18: 1583.553 | HI18: 1843.321 | HJ18: 1844.851 | HK18: 1671.253 | HL18: 1739.065 | HM18: 1655.427 | HN18: 1608.875 | HO18: 1549.174 | HP18: 1688.586 | HQ18: 1659.127 | HR18: 1621.148 | HS18: 1704.648 | HT18: 1676.751 | HU18: 2083.238 | HV18: 2073.64 | HW18: 1881.336 | HX18: 1838.498 | HY18: 1675.584 | HZ18: 1513.165 | IA18: 1538.962 | IB18: 1751.287 | IC18: 1716.737 | ID18: 1343.907 | IE18: 1486.973 | IF18: 1444.815 | IG18: 1891.968 | IH18: 1888.674 | II18: 1685.442 | IJ18: 1511.38 | IK18: 1481.776 | IL18: 1402.199 | IM18: 1417.657 | IN18: 1528.275 | IO18: 1496.876 | IP18: 1452.67 | IQ18: 1542.647 | IR18: 1464.751 | IS18: 1926.269 | IT18: 2016.481 | IU18: 1592.866 | IV18: 635.873 | IW18: 35.999 | IX18: 37.271 | IY18: 67.5 | IZ18: 107.968 | JA18: 114.21 | JB18: 153.259 | JC18: 163.643 | JD18: 162.958 | JE18: 253.083 | JF18: 308.123 | JG18: 180.611 | JH18: 19.759 | JI18: 64.778 | JJ18: 97.205 | JK18: 264.309 | JL18: 281.377 | JM18: 313.691 | JN18: 323.939 | JO18: 416.606 | JP18: 469.934 | JQ18: 442.418 | JR18: 27.169 | JS18: 27.219 | JT18: 26.44 | JU18: 46.062 | JV18: 55.663 | JW18: 297.982 | JX18: 248.629 | JY18: 205.987 | JZ18: 176.998 | KA18: 435.576 | KB18: 476.134 | KC18: 687.234 | KD18: 841.385 | KE18: 882.462 | KF18: 755.201 | KG18: 831.835 | KH18: 906.964 | KI18: 879.325 | KJ18: 889.246 | KK18: 924.728 | KL18: 917.546 | KM18: 953.714 | KN18: 1144.636 | KO18: 1272.252 | KP18: 1400.675 | KQ18: 1386.421 | KR18: 1353.118 | KS18: 1162.785 | KT18: 1077.732 | KU18: 1145.751 | KV18: 1118.066 | KW18: 1244.914 | KX18: 1274.047 | KY18: 1378.466 | KZ18: 1404.544 | LA18: 1642.114
A19: m cg % | C19: =C18/B18-1 | D19: =D18/C18-1 | E19: =E18/D18-1 | F19: =F18/E18-1 | G19: =G18/F18-1 | H19: =H18/G18-1 | I19: =I18/H18-1 | J19: =J18/I18-1 | ... LA19: =LA18/KZ18-1
A20: YoY cg % | N20: =N18/B18-1 | O20: =O18/C18-1 | P20: =P18/D18-1 | Q20: =Q18/E18-1 | R20: =R18/F18-1 | S20: =S18/G18-1 | T20: =T18/H18-1 | U20: =U18/I18-1 | ... LA20: =LA18/KO18-1
